Workbook

Sheet Task List
A1: PlantProcess IQ — Phase-Grouped Task List (v4 · 30 May 2026)
A2: 74 open tasks across 12 phases — completes the 4-Track Vision (Workflow / Hardening / Demo / Website). Supersedes v3 Phases 1–8 (PPIQ-T001–T062), now done.
A4: Task ID | B4: Task Name | C4: Phase ID | D4: Severity | E4: Track | F4: Module | G4: Submodule | H4: Description | I4: Task Type | J4: Validation | K4: Effort (hrs)
A5: Phase 01 — Carry-Forward Hotfixes & Residual Closeout | 6 tasks | 13 hrs
A6: PPIQ-T101 | B6: Build JWT auth-matrix probe across every admin endpoint group | C6: P01 | D6: critical | E6: Track 2 — Hardening | F6: App Backend | G6: Auth / Endpoint Authorization | H6: Closes the residual of v3 PPIQ-T005 (still outstanding — only the four material-search probes exist). Author scripts/probes/auth-matrix-probe.sh hitting every admin endpoint group (/admin/phase1/*, /admin/phase2/*, /admin/license/*, /admin/widgets/*, /admin/users/*, /admin/jobs/*, /demo-lifecycle/*, /diagnostics/*, /api/ml/*) under three identities: (a) no token => 401; (b) operator-tier JWT => 403 on admin routes, 200 on operator routes; (c) admin-tier JWT => 200. Emit a markdown matrix to scripts/probes/output/auth-matrix-{date}.md and wire it as a Jenkins post-deploy gate that goes red on any deviation. | I6: Bug Fix | J6: 1) Script run against staging — every row shows the expected status. 2) Removing an [Authorize] on any admin endpoint in a scratch branch makes the probe fail. 3) Jenkins marks the build red on any deviation. 4) Output archived per deploy with timestamp. | K6: 4
A7: PPIQ-T102 | B7: Resolve Phase1WorkflowTruthPanel orphan (wire or delete) | C7: P01 | D7: important | E7: Track 1 — Workflow | F7: App Frontend | G7: Refactor / Dead Code | H7: Closes v3 PPIQ-T048. src/pages/Admin/Phase1WorkflowTruthPanel.tsx (285 L, last touched 25 May) still has zero importers and appears superseded by components/license/ConnectorTruthPanel.tsx (wired). If ConnectorTruthPanel fully covers the connector-truth surface (last sync, schema fingerprint, drift, sample row count), delete the orphan + CSS; else wire it into the /admin/phase1 'Connector Truth' tab and refactor to Standard* primitives. The repo must contain exactly one connector-truth surface. | I7: Bug Fix | J7: 1) madge/dpdm shows zero unreferenced connector-truth components. 2) /admin/phase1 renders one connector-truth panel sourced from Phase1WorkflowTruthEndpoints. 3) Drift a source schema in the demo DB — the panel surfaces it. 4) Frontend builds clean; bundle size does not regress. | K7: 2
A8: PPIQ-T103 | B8: Fix Caddyfile CSP connect-src host mismatch | C8: P01 | D8: critical | E8: Track 2 — Hardening | F8: Infrastructure | G8: Caddy / HTTP Response Headers | H8: The app-host Content-Security-Policy connect-src lists api.plantprocessiq.com / wss://api.plantprocessiq.com, but production serves on the *.178.105.152.180.sslip.io wildcard. If the SPA calls the sslip.io API origin, CSP silently blocks every XHR/WebSocket in production. Re-tune connect-src to the exact API + WS origins the frontend actually calls (derive from apiConfig.ts / VITE_API_BASE_URL), single source of truth; deploy Content-Security-Policy-Report-Only for 24h, collect violations via diagnostics, then promote to enforce. Apply consistently to api/app/admin/website hosts. | I8: Bug Fix | J8: 1) DevTools Console shows zero connect-src violations while exercising every API-calling page. 2) connect-src origins exactly match apiConfig.ts. 3) securityheaders.com still scores A on every host. 4) Report-only window logged violations before enforce. | K8: 1.5
A9: PPIQ-T104 | B9: Confirm ';plantadmin' SQL token fix on staging + sweep | C9: P01 | D9: important | E9: Track 2 — Hardening | F9: Database | G9: Migration / Bootstrap SQL | H9: Closes v3 PPIQ-T006 for production posture. A fix script strips the stray trailing 'plantadmin' token from a seed status string ("...pilot foundation applied' AS status;plantadmin"). Confirm applied on the Hetzner staging clone, then sweep Backend/database/scripts/ and seed/ for any other dangling identifier after a statement terminator (regex ';[A-Za-z_]+\s*$' outside string literals). Add a CI guard failing on a dangling token. Record root cause in Backend/database/scripts/CHANGELOG.md. | I9: Bug Fix | J9: 1) Fresh Postgres 17 + dotnet ef database update + all loose scripts in order completes with zero syntax errors. 2) Same on the Hetzner staging clone via Jenkins. 3) Sweep returns zero dangling tokens. 4) CI guard fails on a reintroduced stray token. | K9: 2
A10: PPIQ-T105 | B10: Complete loopback-binding audit for all infra services | C10: P01 | D10: very important | E10: Track 2 — Hardening | F10: Infrastructure | G10: Docker Compose / Network Exposure | H10: Closes the full-surface part of v3 PPIQ-T002 (only Postgres proven). Audit every service in docker-compose.demo.yml (redis, seq, jaeger, grafana, prometheus, jenkins, workers) and bind each published port to 127.0.0.1 unless intentionally public (Caddy 80/443; Jenkins :9090 behind basicauth). Document in Infrastructure/deploy/README.md and prove with an external scan. | I10: Bug Fix | J10: 1) External nmap of 178.105.152.180 shows only 80, 443, 9090 open; all data/observability ports filtered. 2) Internal container traffic unaffected (health checks green). 3) README documents each binding decision. | K10: 1.5
A11: PPIQ-T106 | B11: Wire forbidden-phrase sweep + non-standard-import block as Jenkins gates | C11: P01 | D11: very important | E11: Track 2 — Hardening | F11: Infrastructure | G11: CI / Quality Gate | H11: Closes v3 PPIQ-T079/T080. Validators exist (scripts/validate-forbidden-copy.mjs; ESLint no-restricted-imports/syntax) but are not proven as enforced stages. Add Jenkinsfile stages ForbiddenPhraseSweep (repo-wide grep across .ts/.tsx/.cs/.sql/.md/.json/prompts) and StandardImportGate (pnpm lint). Both fail the build with a clear file listing + remediation; both run on the GitHub webhook on every push; pre-commit hooks enforce locally. | I11: Enhancement | J11: 1) Reintroducing the forbidden phrase anywhere fails the build naming every offender. 2) A native <button> in src/pages/* or an import from src/hardening/* fails lint with the canonical replacement. 3) Both stages run on every push; sweep < 5s. 4) Pre-commit blocks the commit locally. | K11: 2
A12: Phase 02 — Generic Schema Mapping & Canonical View Engine (Vision §1.4) | 6 tasks | 35 hrs
A13: PPIQ-T107 | B13: Build canonical_schema_views catalog + registration service | C13: P02 | D13: very important | E13: Track 1 — Workflow | F13: Database | G13: Schema Mapping / View Catalog | H13: Implement the first-class catalog the whole 'generic schema' depends on (and which the resolver in T108 needs). Create table canonical_schema_views (id, slug, title, owning_area_id, sql_definition, column_catalog_json, version, status, audit) + EF entity + configuration + migration. CanonicalViewCatalogService registers, versions, validates and lists views; every widget/KPI/ML feature resolves columns against this catalog. Seed the baseline views the demo uses. | I13: New Feature | J13: 1) Migration applies clean on a fresh DB; baseline views registered. 2) Registering a view stores its resolved column catalog (name+type). 3) Listing returns active views with versions. 4) Round-trip register=>read preserves columns. 5) Audit row on every change. | K13: 6
A14: PPIQ-T108 | B14: Implement SchemaViewResolver against the canonical catalog | C14: P02 | D14: very important | E14: Track 1 — Workflow | F14: App Backend | G14: Schema Mapping / Validation | H14: Build SchemaViewResolver (closes v3 PPIQ-T058 properly). Given a parsed WidgetQueryExpression or ML feature request, validate: (a) the source view exists in canonical_schema_views; (b) each dimension/measure column exists; (c) aggregate functions valid for the column type; (d) filter operators valid for the type. Return SchemaValidationError naming the offending column/operator. Cache the catalog in IMemoryCache (60s) with invalidation on change. Consolidate the ad-hoc validation currently spread across DashboardWidgetValidationService. | I14: New Feature | J14: 1) Valid expression against an existing view => success. 2) Non-existent view => NoSuchView; non-existent column => NoSuchColumn; sum() on text => InvalidAggregateForType. 3) Cache hit/invalidate visible in metrics. 4) Existing widget-expression tests still pass against the resolver. | K14: 4
A15: PPIQ-T109 | B15: Build schema-mapping UI: map source tables into the generic schema | C15: P02 | D15: very important | E15: Track 1 — Workflow | F15: App Frontend | G15: Administrator Page / Schema Config | H15: Vision §1.4.1: in Administrator => Schema Configuration, build the mapping workspace. For each imported (dumped) source table, the user maps columns to generic-schema entities, sets keys, and saves a mapping. StandardTable for column lists, StandardSelect for target mapping, JetBrains-Mono StandardTextArea (code mode) for view SQL, live validation via POST /admin/schema/validate, schema-aware autocomplete from the canonical catalog. No hardcoding — everything saved to the catalog/mapping store. | I15: New Feature | J15: 1) Map an imported HSM table's columns to the generic schema and save. 2) Live validation flags type mismatches inline. 3) Saved mapping persists and reloads. 4) Standard* primitives only. 5) Visual regression baseline captured. | K15: 10
A16: PPIQ-T110 | B16: Cross-source join authoring (dump-file to dump-file) | C16: P02 | D16: very important | E16: Track 1 — Workflow | F16: App Backend | G16: Schema Mapping / Joins | H16: Implement the cross-source join the vision calls out (Vision §1.4.2/1.4.5): join piece_id from the HSM Oracle dump with material_id from the Parsytec MySQL dump; join EAF process-definition tables to per-heat values. JoinDefinition model (left view, right view, key pairs, join type) materialized into a canonical view; validated via SchemaViewResolver + SafeSqlValidator. Endpoints + UI builder. | I16: New Feature | J16: 1) Author a join between two source dumps and materialize a canonical view. 2) Query it returns traced rows for material ADV_COIL4002 across both systems. 3) A type-mismatched key pair is rejected with a clear error. 4) SafeSqlValidator blocks cross-tenant/DDL injection in join SQL. | K16: 6
A17: PPIQ-T111 | B17: KPI-as-view authoring attached to equipment/area/process | C17: P02 | D17: important | E17: Track 1 — Workflow | F17: App Frontend | G17: Administrator Page / KPI Definition | H17: Vision §1.4.3: let a user create a KPI as a saved SQL view and attach it as a process parameter to a specific equipment/area/process (e.g. normalize EAF by joining processDefinition to per-heat values). Build on the existing KPIDefinition sub-component; persist KPI views into the canonical catalog with an area/equipment attachment; expose them to the widget builder and ML feature selectors. | I17: New Feature | J17: 1) Create a KPI view, attach to EAF area, save. 2) KPI appears as a selectable measure in the widget builder and ML feature picker. 3) KPI view validates against the catalog. 4) Standard* primitives only. | K17: 5
A18: PPIQ-T112 | B18: Mapping execution service + integration tests | C18: P02 | D18: very important | E18: Track 2 — Hardening | F18: App Backend | G18: Schema Mapping / Execution | H18: Implement the service that executes a saved mapping/view set to materialize/refresh the generic schema from the dump store, invoked by the stage-2 import job (P03). Apply SafeSqlValidator on every execution. MappingExecutionResult with row counts, duration, errors. Integration tests over a seeded dump store. | I18: New Feature | J18: 1) Executing a mapping populates the generic schema with expected row counts. 2) Re-execution is idempotent. 3) SafeSqlValidator blocks a malicious mapping at execute time. 4) Integration tests pass against the seeded dump store < 30s. | K18: 4
A19: Phase 03 — Two-Stage Delta Import Architecture (Vision §1.1–1.6) | 6 tasks | 27 hrs
A20: PPIQ-T113 | B20: Dump-copy store mirroring customer source structure (Vision §1.3) | C20: P03 | D20: very important | E20: Track 1 — Workflow | F20: Database | G20: Import / Dump Store | H20: Implement the dump-copy store: per source table, a 'latest copy state' in the customer's own structure (NOT our generic schema). Model dump tables/files + a registry (source_id, table_name, dump_location, last_index_column, last_index_value, last_synced_at). DB sources => staging tables; CSV/Excel => watched drop volumes. This is the stage-1 target the delta compare runs against. | I20: New Feature | J20: 1) Configuring a source table provisions its dump-copy target. 2) Dump preserves the source's column shape (not generic). 3) Registry tracks last_index per table. 4) Re-provisioning is idempotent. | K20: 5
A21: PPIQ-T114 | B21: Stage-1 delta import (source to dump) with last-index compare | C21: P03 | D21: very important | E21: Track 1 — Workflow | F21: App Backend | G21: Import / Delta Stage 1 | H21: Vision §1.2: each source-table import is a named job with a cycle (2 min up to several days). On each scan the job compares the dump's last index against the source's last index and imports only the new tail records into the dump copy. Use the existing connector factory; add backoff + crash detection; per-source scheduling with NextRunAtUtc filtering (extend existing scheduling). | I21: New Feature | J21: 1) New source rows beyond last_index import on the next cycle; older rows untouched. 2) Cycle configurable 2 min..days. 3) Crash mid-import is detected; job marked failed with last-run/duration. 4) Re-run resumes from last_index without duplication. | K21: 6
A22: PPIQ-T115 | B22: Stage-2 import (dump to generic schema) at HMI-refresh rate | C22: P03 | D22: very important | E22: Track 1 — Workflow | F22: App Backend | G22: Import / Delta Stage 2 | H22: Vision §1.5: after mappings/views/joins are configured, a second job copies from the dump store into our generic schema at the HMI-refresh rate (when new data is ready). Invokes the mapping execution service (P02). Named job, cycle, status, crash detection. Coordinates with stage-1 so stage-2 only runs on fresh dump data. | I22: New Feature | J22: 1) After stage-1 brings new data, stage-2 materializes it into the generic schema within the configured window. 2) Job is named, scheduled, monitored. 3) No double-processing of already-mapped rows. 4) Failure is isolated and surfaced. | K22: 5
A23: PPIQ-T116 | B23: Extend JobDefinition for two-stage import + crash/duration telemetry (Vision §1.6) | C23: P03 | D23: important | E23: Track 1 — Workflow | F23: Database | G23: Jobs / Domain Model | H23: Extend JobDefinition/JobRunHistory to model both import stages and ML jobs uniformly: job name, type, cycle, last-run datetime, duration, status (OK/crash/timeout), next-run, backoff state. Ensure standard import, mapping, and ML jobs all flow through one job model so the Jobs Monitor (§1.6, §3.1.5) shows them together. | I23: Enhancement | J23: 1) All job types persist last-run, duration, status, next-run. 2) Timeout and crash are distinct statuses. 3) Migration applies clean; existing job rows backfilled. | K23: 3
A24: PPIQ-T117 | B24: Jobs Monitor page — standard + ML jobs unified (Vision §1.6, §3.1.5) | C24: P03 | D24: very important | E24: Track 1 — Workflow | F24: App Frontend | G24: Administrator Page / Jobs Monitor | H24: Complete the Jobs Monitor (build on AdminJobsMonitorTab, 347 L) to show every job — stage-1 imports, stage-2 mapping, and ML learning jobs — with status (last run OK/crash/timeout), last-run datetime, duration, next-run, and a run-now/pause control. StandardTable with brand status chips; OperationProgressPanel for active runs. | I24: Enhancement | J24: 1) All job categories appear with correct status/last-run/duration/next-run. 2) Run-now triggers a job and the progress panel ticks. 3) A crashed job shows failed status + last error. 4) Standard* primitives only; visual regression baseline captured. | K24: 4
A25: PPIQ-T118 | B25: Delta-import integration + resumability tests | C25: P03 | D25: important | E25: Track 2 — Hardening | F25: App Backend | G25: Import / Test Coverage | H25: Integration tests for the two-stage pipeline against seeded sources: cold full-load, incremental delta, mid-run crash + resume, schema drift handling, idempotency. Opt-in via PPIQ_RUN_CONNECTOR_INTEGRATION=1; wired to the post-deploy gate. | I25: New Feature | J25: 1) Cold load then incremental delta imports only new rows. 2) Simulated crash resumes from last_index with no duplicates. 3) Source schema drift is detected and surfaced. 4) Suite < 60s, wired to Jenkins. | K25: 4
A26: Phase 04 — ML Engine — Scheduled Correlation Learning (Vision §3.1) | 5 tasks | 26 hrs
A27: PPIQ-T119 | B27: Define the four ML learning job types + EnsureMlJobDefinitions (Vision §3.1.1–3.1.4) | C27: P04 | D27: very important | E27: Track 1 — Workflow | F27: App Backend | G27: ML Engine / Job Definitions | H27: Formalize the four scheduled learning jobs: (1) process-params x defect-id correlation; (2) process-params x downtime-id; (3) process-params x KPI-id; (4) a weekly overall pass across all data. Extend the existing EnsureMlJobDefinitions/IsMlJob scaffolding into concrete JobDefinitionType entries with default off-hours schedules (daily, user-overridable) and weekly cadence for the overall job. Each is a first-class job in the unified job model (P03). | I27: New Feature | J27: 1) The four ML jobs registered with correct default schedules (daily off-hours; weekly overall). 2) Schedules user-overridable per job. 3) Jobs appear in the Jobs Monitor. 4) IsMlJob correctly classifies each. | K27: 3
A28: PPIQ-T120 | B28: ML learning worker — scheduled statistical correlation engine | C28: P04 | D28: very important | E28: Track 1 — Workflow | F28: App Backend | G28: ML Engine / Learning Worker | H28: Implement the worker that runs the four jobs off-hours: pull feature vectors (FeatureEngineeringService) for all process parameters and the chosen targets (defect/downtime/KPI ids), compute statistical associations (Pearson, Spearman, point-biserial for categorical defect flags, plus a regularized regression / mutual-information rank for non-linear signal), and persist CorrelationResult with coefficient, p-value/confidence, sample size, window, strength bucket. Honest framing only — statistical correlation and suspected contributors, never 'prediction' or 'root cause' (brand voice). Long-run safety: chunked compute, checkpointing, cancellation, concurrency cap 1/job. | I28: New Feature | J28: 1) Running a job over the demo dataset persists CorrelationResult rows with coefficient, confidence, sample size. 2) Deterministic for a fixed dataset+seed (two runs match). 3) Cancellation mid-run leaves a clean failed state, no partial-committed garbage. 4) No output uses forbidden claim language. 5) Runtime on the demo dataset is bounded and logged. | K28: 10
A29: PPIQ-T121 | B29: Per-job scheduling, backoff & training-window governance | C29: P04 | D29: important | E29: Track 1 — Workflow | F29: App Backend | G29: ML Engine / Scheduling & Governance | H29: Add per-job off-hours scheduling with failure backoff and concurrency control, and extend MlReadinessService into label/feature governance gates: minimum sample size, label completeness, feature freshness, and a training-window selector (last week/month/year). The engine refuses to learn on insufficient/ungoverned data and reports why (preserve the no_production_prediction honesty). | I29: Enhancement | J29: 1) A job below the sample/label threshold is blocked with a clear readiness reason. 2) Backoff doubles the retry interval on consecutive failures up to a cap. 3) Window selector changes the data range used. 4) Readiness gates reflect the real governance state. | K29: 5
A30: PPIQ-T122 | B30: Model registry lifecycle for rule-based correlation models | C30: P04 | D30: important | E30: Track 1 — Workflow | F30: Database | G30: ML Engine / Model Registry | H30: Extend ModelRegistry into a real lifecycle: register/version/activate/retire the rule-based correlation 'models' (a model = a parameterized correlation/scoring config over a feature set + window), with provenance (job, window, sample size) and an activation flag the risk scorer reads. Keep the 'Transparent rule-based quality risk scorer' baseline as version 1. | I30: Enhancement | J30: 1) A learning run can register a new model version with provenance. 2) Exactly one version per scope is active; activating a new one retires the prior. 3) Risk scoring reads the active model. 4) History is queryable for audit. | K30: 4
A31: PPIQ-T123 | B31: ML learning engine unit + integration tests on golden datasets | C31: P04 | D31: very important | E31: Track 2 — Hardening | F31: App Backend | G31: ML Engine / Test Coverage | H31: Tests with deterministic golden datasets where the correct correlations are known by construction (planted signal + noise). Assert the engine recovers the planted associations within tolerance, ranks them correctly, respects governance gates, and persists correct provenance. Performance test bounds the run on the standard demo size. | I31: New Feature | J31: 1) Engine recovers planted associations and rejects pure-noise columns. 2) Ranking matches the known ground-truth order. 3) Governance gate blocks an under-sampled run. 4) Deterministic; wired to the Jenkins gate. | K31: 4
A32: Phase 05 — ML Engine — Inspection Jobs to Generated Pages (Vision §3.2) | 6 tasks | 31 hrs
A33: PPIQ-T124 | B33: Inspection Job domain + persistence + endpoints (back SaveInspectionJobModal) | C33: P05 | D33: very important | E33: Track 1 — Workflow | F33: App Backend | G33: ML Engine / Inspection Jobs | H33: Vision §3.2.1: a user selects a defect/downtime/KPI id, an inspection window (last week/month/year), and names the job. Implement the InspectionJob entity + EF config + migration + endpoints (create/list/get/run/schedule/delete). Back the already-wired SaveInspectionJobModal with the real POST. Authorization + license gating (Pro Plus/Enterprise). | I33: New Feature | J33: 1) Creating an inspection job from the modal persists it and returns an id. 2) Listing shows target, window, schedule. 3) Non-licensed tier is gated with a clear hint. 4) Audit row on create/run/schedule. | K33: 5
A34: PPIQ-T125 | B34: Inspection Job runner — on-demand correlation analysis | C34: P05 | D34: very important | E34: Track 1 — Workflow | F34: App Backend | G34: ML Engine / Inspection Runner | H34: Vision §3.2.2: implement the runner that executes an inspection job using the learning engine (P04) over the selected target + window and produces a ranked 'most influential parameters' result with evidence (coefficient, confidence, sample size, supporting slices). Returns a structured InspectionResult the page generator consumes. Run-now returns 202 + progress (reuse the demo-lifecycle progress pattern). | I34: New Feature | J34: 1) Run-now over a demo target returns a ranked contributor list with evidence in bounded time. 2) Progress endpoint ticks through stages. 3) Same input+window => deterministic ranking. 4) Results persisted and linked to the job. | K34: 6
A35: PPIQ-T126 | B35: Auto-generate analysis page from inspection result (no hardcoding) | C35: P05 | D35: very important | E35: Track 1 — Workflow | F35: App Backend | G35: ML Engine / Page Generation | H35: Vision §3.2.2 + Track-3 golden rule: on run completion, auto-generate a dashboard page composed of real widgets bound to the result — top-contributors bar, contributor trend over the window, distribution by target, correlation matrix — using the canonical widget definitions and the page model (P07). No hardcoded page; the generator emits the same widget definitions a user could build by hand. | I35: New Feature | J35: 1) A completed run produces a saved-page definition referencing real widgets bound to the result data. 2) Opening the page renders the widgets with live data. 3) Regenerating after a re-run updates the page in place. 4) Generated page round-trips through the page model — zero hardcoded layout. | K35: 6
A36: PPIQ-T127 | B36: Correlation Page shell — tabbed generated pages (replace 5-line stub) | C36: P05 | D36: very important | E36: Track 1 — Workflow | F36: App Frontend | G36: ML Engine / Correlation Page | H36: Vision §3.2: replace the 5-line CorrelationPage.tsx stub with the full ML Correlation area — a StandardTabs surface where each generated inspection-job page is a tab, with run-now, a save toggle, and a schedule control (hourly/daily) per Vision §3.2.3. Standard* primitives, license gating, DataFetchBoundary states. | I36: New Feature | J36: 1) Page lists inspection jobs as tabs; selecting one renders its generated widgets. 2) Run-now refreshes the tab via the runner with a progress panel. 3) Save persists the page; Schedule enqueues a periodic job in the Jobs Monitor. 4) Standard* primitives only; visual regression baseline captured. | K36: 6
A37: PPIQ-T128 | B37: Schedule inspection jobs periodically + Jobs Monitor integration | C37: P05 | D37: important | E37: Track 1 — Workflow | F37: App Backend | G37: ML Engine / Scheduling | H37: Vision §3.2.3: allow a saved inspection job to run periodically (hourly/daily/user-defined) or on demand. Register scheduled inspection runs in the unified job model so they appear in the Jobs Monitor with status/last-run/duration, and so a periodic run regenerates the saved page. | I37: Enhancement | J37: 1) Scheduling a job enqueues a recurring run visible in the Jobs Monitor. 2) Each periodic run regenerates the page and records last-run/duration. 3) Pausing/deleting the schedule stops future runs. 4) Rate-limited to avoid overlap. | K37: 4
A38: PPIQ-T129 | B38: E2E + integration tests for run -> generate -> save -> schedule loop | C38: P05 | D38: important | E38: Track 2 — Hardening | F38: App Frontend | G38: ML Engine / Test Coverage | H38: Playwright e2e + backend integration tests covering the full §3.2 loop: create inspection job => run-now => generated page renders contributors => save => schedule => periodic run regenerates. Assert absence of the forbidden phrase and forbidden ML claims. | I38: New Feature | J38: 1) The full loop passes against staging. 2) Generated page shows the expected top contributor for a planted-signal demo target. 3) Forbidden-phrase and forbidden-claim assertions pass. 4) Test < 120s, wired to the post-deploy gate. | K38: 4
A39: Phase 06 — ML Engine — Suggestion & Recommendation Assistant (Vision §3.3) | 5 tasks | 23 hrs
A40: PPIQ-T130 | B40: Suggestion & recommendation engine (rule-based, evidence-linked) | C40: P06 | D40: very important | E40: Track 1 — Workflow | F40: App Backend | G40: ML Engine / Suggestion Engine | H40: Vision §3.3: synthesize ranked recommendations from learning-job outputs (P04), inspection results (P05) and data-quality findings — e.g. 'Heats with tundish superheat above X correlate with surface-defect class Y over the last 30 days (n=…, r=…); review caster practice.' Each suggestion carries confidence, sample size, and links to its supporting evidence. Strictly honest framing — suspected contributors, statistical pattern, evidence-based; never guaranteed root cause or prediction (enforced by a copy guard). | I40: New Feature | J40: 1) The engine emits ranked suggestions, each with confidence, sample size, evidence link. 2) Suggestions update after a new learning run. 3) No suggestion uses forbidden claim language (guarded). 4) Determinism for a fixed input set. | K40: 8
A41: PPIQ-T131 | B41: /api/suggestions endpoint + context filtering | C41: P06 | D41: important | E41: Track 1 — Workflow | F41: App Backend | G41: ML Engine / Suggestions API | H41: Implement GET /api/suggestions (the v3 PPIQ-T054 route, previously a stub) returning ranked recommendations, filterable by current investigation context (material/area/line/window) and license tier. ProblemDetails error paths; pagination; audit of which suggestions were surfaced. | I41: New Feature | J41: 1) Endpoint returns ranked suggestions with reasoning + evidence links. 2) Context filters narrow results correctly. 3) Non-licensed tier is gated. 4) Integration tests cover happy/empty/filtered. | K41: 4
A42: PPIQ-T132 | B42: Suggestions & Recommendations page (assistant-style UI) | C42: P06 | D42: very important | E42: Track 1 — Workflow | F42: App Frontend | G42: ML Engine / Suggestions Page | H42: Build the /suggestions page: an assistant-style, evidence-grade list of recommendations with reasoning, confidence, sample size, and drill-through to the supporting correlation/inspection page. Standard* primitives, DataFetchBoundary states, license gating, and an honest empty state ('no strong signal yet'). Brand voice throughout. | I42: New Feature | J42: 1) Page renders ranked recommendations with reasoning + evidence drill-through. 2) Drill-through opens the supporting analysis page. 3) Empty/loading/error states use Standard* and the 'Refreshing…' pattern. 4) Standard* primitives only; visual regression baseline captured. | K42: 6
A43: PPIQ-T133 | B43: Brand-voice copy guard for ML / suggestion surfaces | C43: P06 | D43: important | E43: Track 2 — Hardening | F43: App Frontend | G43: ML Engine / Copy Compliance | H43: Add a CI copy guard (extending validate-forbidden-copy.mjs) banning forbidden ML claims across ML/suggestion surfaces: 'guaranteed root cause', 'AI-powered prediction', 'production-ready AI', 'predicts'. Provide approved replacements ('suspected contributor', 'statistical correlation', 'rule-based risk scoring'). Wire to the Jenkins ForbiddenPhraseSweep stage. | I43: Enhancement | J43: 1) Introducing a forbidden ML claim anywhere fails CI with the approved replacement. 2) Existing rule-based copy passes. 3) Stage runs < 5s. | K43: 2
A44: PPIQ-T134 | B44: Suggestion ranking + evidence-linkage tests | C44: P06 | D44: important | E44: Track 2 — Hardening | F44: App Backend | G44: ML Engine / Test Coverage | H44: Tests asserting suggestion ranking order on golden inputs, evidence links resolve to the correct underlying results, context-filtering correctness, and license gating. Determinism check. | I44: New Feature | J44: 1) Ranking matches known ground truth on golden inputs. 2) Every evidence link resolves to the correct correlation/inspection record. 3) Gating blocks under the wrong tier. 4) Deterministic; wired to the gate. | K44: 3
A45: Phase 07 — Page Builder & Widget Library (Vision §2.1–2.2) | 5 tasks | 30 hrs
A46: PPIQ-T135 | B46: Page CRUD + /pages/{slug} dynamic load (complete v3 T054 stub) | C46: P07 | D46: very important | E46: Track 1 — Workflow | F46: App Frontend | G46: Page Builder / Page CRUD | H46: Vision §2.1.1/2.1.3: implement create/edit/delete/save of user pages, persisted per-user, and the dynamic /pages/{slug} route loading a stored page definition (backend /api/pages/{slug}, 404 on missing). This is the page model the ML page generator (P05) also emits into. Standard* primitives. | I46: New Feature | J46: 1) Create, rename, save, delete a page; reload restores it. 2) /pages/{slug} loads a stored page; missing slug 404s. 3) Pages are per-user/owner scoped. 4) The ML-generated page round-trips through the same model. | K46: 6
A47: PPIQ-T136 | B47: Drag-drop widget canvas + widget library | C47: P07 | D47: very important | E47: Track 1 — Workflow | F47: App Frontend | G47: Page Builder / Canvas & Library | H47: Vision §2.1.2: after creating a page, present a library of all widgets (every chart type, KPI, and the sorting/filtering tools — date-time picker, list-of-values). Drag-drop widgets onto the page, arrange, then Save; editing an existing page can add/remove/rearrange widgets. Drag/resize/min/max must be correct (Vision §2.5). Reuse the existing WidgetBuilderWizard for per-widget config. | I47: New Feature | J47: 1) Drag a widget from the library to the canvas, arrange, save; reload preserves layout. 2) Resize/min/max/move behave correctly with no overlap glitches. 3) Date-time and list filters available as widgets. 4) Standard* primitives; visual regression baseline captured. | K47: 10
A48: PPIQ-T137 | B48: Widget edit: link to DB values + script layer in the builder | C48: P07 | D48: very important | E48: Track 1 — Workflow | F48: App Frontend | G48: Page Builder / Widget Config | H48: Vision §2.2.1–2.2.3: the selected widget has an Edit action to link it to a list of values from the canonical schema and to add a script-layer expression (e.g. bar chart grouped by shift) so users avoid bespoke endpoints. Wire the already-built widget compiler (WidgetQueryExpressionService + WidgetScriptStep) into the live builder, with schema-aware autocomplete from the canonical catalog and SafeSqlValidator on save + execute. | I48: Enhancement | J48: 1) Editing a widget links it to a canonical view's columns and a script expression. 2) Autocomplete suggests views/columns contextually. 3) Save is gated on a valid, safe expression. 4) Execution honors the second-pass SafeSqlValidator. | K48: 6
A49: PPIQ-T138 | B49: Page persistence, ownership & sharing | C49: P07 | D49: important | E49: Track 1 — Workflow | F49: App Backend | G49: Page Builder / Persistence | H49: Backend page store (page, owner, layout json, widget bindings, version), endpoints for CRUD + list-by-owner, optional share/visibility. Tenant-scoped. Used by P05 generated pages and P07 builder. | I49: New Feature | J49: 1) Pages persist with layout + bindings + version. 2) List-by-owner returns the user's pages. 3) Tenant isolation enforced. 4) Round-trip preserves layout and bindings. | K49: 4
A50: PPIQ-T139 | B50: Page builder e2e + drag/resize correctness tests | C50: P07 | D50: important | E50: Track 2 — Hardening | F50: App Frontend | G50: Page Builder / Test Coverage | H50: Playwright e2e: create page => drag two widgets => configure one with a script expression => resize/move => save => reload renders identically. Assert no layout drift and no forbidden phrase. | I50: New Feature | J50: 1) The build-save-reload flow renders identically (snapshot). 2) Resize/move persist exactly. 3) Forbidden-phrase assertion passes. 4) Wired to the PR gate. | K50: 4
A51: Phase 08 — Demo Source-Database Suite at Real Scale (Vision Track 3) | 4 tasks | 27 hrs
A52: PPIQ-T140 | B52: docker-compose.demo-sources.yml — eight source systems (loopback-bound) | C52: P08 | D52: very important | E52: Track 3 — Demo | F52: Infrastructure | G52: Demo Sources / Compose | H52: Expands v3 PPIQ-T063 to the vision's actual systems. Provision: postgres-meltshop (EAF/LF), oracle-caster, oracle-hsm, mssql-pkl, mysql-downtime, mysql-parsytec (surface inspection), plus csv-drop (Yard) and excel-drop (QA) watched volumes. Every port bound to 127.0.0.1 only. First-run init scripts under Infrastructure/deploy/source-seeds/{system}/. External network so the backend reaches each by hostname. | I52: New Feature | J52: 1) compose up -d brings all eight up healthy within the warm-up window (Oracle slow). 2) Backend reaches each by internal hostname. 3) External scan shows no source DB publicly reachable. 4) Re-run is idempotent. | K52: 6
A53: PPIQ-T141 | B53: Coherent cross-source steel dataset at vision scale | C53: P08 | D53: very important | E53: Track 3 — Demo | F53: Database | G53: Demo Sources / Seed Data | H53: Vision Track 3: generate ~1 month / ~630 heats / ~5,600 slabs-coils / 100K+ rows of realistic, coherent data spanning all systems with full genealogy EAF->LF->CC (2-strand thin-slab)->TF->HSM->SKP->LCT/HCT/STL->PKL->GVL->Yard. Include MeltShop heat summaries + chemistry samples/results/components + additives + EAF steps/parameters; Caster heat/slab/sequence/strand/tundish/mould + samples; HSM continuation; PKL; Downtime with production-vs-equipment stoppage logic and reason taxonomy (electrical/operation/production/mechanical/hydraulic); Parsytec defects; QA sampling (every 3rd coil, up to 2/coil for difficult grades). Extend generate_synthetic_plantprocessiq.py + writers; keep total seed < 2 GB. | I53: New Feature | J53: 1) Volumes: ~630 heats, ~5,600 slabs/coils, 100K+ rows total. 2) One material (ADV_COIL4002) traces end-to-end across every system incl. a downtime and a QA sample. 3) Re-seeding is idempotent. 4) Downtime stoppage logic is realistic (short HSM stop buffered; short caster pump stop cascades to hours). | K53: 10
A54: PPIQ-T142 | B54: Connector smoke tests vs all six live DB sources + CSV/Excel golden files | C54: P08 | D54: very important | E54: Track 2 — Hardening | F54: App Backend | G54: Connectors / Smoke Tests | H54: Completes v3 PPIQ-T065–T069. Author/extend smoke tests for PostgreSqlConnector, OracleConnector (x2 instances), MsSqlConnector, MySqlConnector (x2), plus the existing CSV/Excel tests, against the live demo-sources containers: ListTables, DescribeTable, SamplePage(100), FullSync, compared to checked-in golden snapshots. Opt-in via PPIQ_RUN_CONNECTOR_INTEGRATION=1; wired to the post-deploy gate. Oracle gets a 90s warm-up. | I54: New Feature | J54: 1) Each connector passes against its seeded source. 2) Each detects drift if seed data is altered. 3) Oracle warm-up handled. 4) All wired to Jenkins post-deploy and logged. | K54: 6
A55: PPIQ-T143 | B55: Live end-to-end config demo proof (no hardcoding) | C55: P08 | D55: important | E55: Track 3 — Demo | F55: App Frontend | G55: Demo Sources / E2E Proof | H55: Track-3 golden-rule proof: a scripted e2e that, from the HMI only, connects each of the six DB sources + two drops, maps/joins one cross-source view, runs a delta import, builds a page with a script-layer widget, and runs an inspection job — verifying nothing is hardcoded. The canonical 'real user' path. | I55: New Feature | J55: 1) The full from-HMI path passes against the demo-sources stack. 2) Each step verified with a concrete checkpoint. 3) No hardcoded page/widget used anywhere in the path. 4) Run completes within the demo time budget. | K55: 5
A56: Phase 09 — Hardening Completion & Resilience (Vision Track 2) | 8 tasks | 35 hrs
A57: PPIQ-T144 | B57: HeatMapWidget for Risk Intelligence (line x shift x day) | C57: P09 | D57: important | E57: Track 2 — Hardening | F57: App Frontend | G57: Widgets / Visualization | H57: Carries v3 PPIQ-T076. Add a heat map on Risk Intelligence: risk score by line x shift x day-of-week, green->amber->red on the brand thresholds, hover tooltip with breakdown, click-through to the materials in that cell (applies filters to Material Investigation). Data via /api/risk/heatmap. Wrap in StandardCard with loading/empty/error states. | I57: New Feature | J57: 1) Heat map renders; colors match the chip treatment. 2) Click drilldown applies filters to Material Investigation. 3) States use Standard* primitives. 4) 30x7x24 grid renders < 200ms. | K57: 6
A58: PPIQ-T145 | B58: Live license tier toggle + app-wide override banner | C58: P09 | D58: important | E58: Track 1 — Workflow | F58: App Frontend | G58: License / Tier Toggle | H58: Carries v3 PPIQ-T077 (backend T053 done). In Admin Preview, a StandardSelect bound to effective-tier/tier-override lets an admin demo Pro Plus features without swapping licenses; an app-shell banner shows when an override is active ('Tier override active: Pro Plus (expires in 23h 47m). Reset.'). Brand-styled. Demonstrates Vision §4.2 (features appear/disappear by tier). | I58: Enhancement | J58: 1) Toggling tier immediately re-gates features across the app. 2) Banner appears when override active; Reset clears it. 3) Switching Enterprise->Pro visibly removes gated features. 4) Audit on every toggle. | K58: 4
A59: PPIQ-T146 | B59: Progress-percentage UI for long-running endpoints (Vision §2.1) | C59: P09 | D59: important | E59: Track 2 — Hardening | F59: App Frontend | G59: Hardening / Long Calls | H59: For every endpoint that can be slow on large datasets (imports, ML runs, heavy analytics, PDF generation), surface a loading indicator with a progress percentage (reuse OperationProgressPanel + progress endpoints). No silent multi-second hangs anywhere a customer can see. | I59: Enhancement | J59: 1) Each heavy action shows progress %, not a bare spinner. 2) Progress reflects real backend stages. 3) No visible hang > 1s without feedback. 4) e2e covers the three heaviest paths. | K59: 4
A60: PPIQ-T147 | B60: Endpoint + SQL resilience audit (PK/FK/null/timeout) (Vision §2.2) | C60: P09 | D60: very important | E60: Track 2 — Hardening | F60: App Backend | G60: Hardening / API Resilience | H60: Systematic pass over every current API + its SQL/joins: guard against null/missing PK-FK, enforce query timeouts, add ProblemDetails on every error path, assert no unexpected 500s under empty/edge data. Produce docs/hardening/endpoint-resilience-{date}.md listing each endpoint's edge-case handling. | I60: Enhancement | J60: 1) Every endpoint returns structured errors, never an unhandled 500, under empty/edge inputs. 2) Query timeouts enforced; no endpoint hangs. 3) Checklist documents each endpoint's edge handling. 4) Integration tests cover the top 20 endpoints' edge cases. | K60: 6
A61: PPIQ-T148 | B61: Full action-matrix test: every control does its job (Vision §3.1.1) | C61: P09 | D61: very important | E61: Track 2 — Hardening | F61: App Frontend | G61: Hardening / Action Matrix | H61: Build the exhaustive action matrix (extend src/hardening/actionMatrix.ts): for every page and sub-page, list every button/control/hook/recall with its expected action, and a Playwright test that exercises each and asserts the proper outcome (min/max/calc/load/navigate). No dead or misbehaving control allowed. | I61: New Feature | J61: 1) The matrix enumerates every control on every page/sub-page. 2) Each is exercised and asserted. 3) Zero dead/misbehaving controls. 4) Wired to the PR gate; a newly-added dead button fails it. | K61: 6
A62: PPIQ-T149 | B62: Responsive + cross-browser + http/https correctness (Vision §1.6, §2.1.6) | C62: P09 | D62: important | E62: Track 2 — Hardening | F62: App Frontend | G62: Hardening / Responsive | H62: Verify every page renders correctly at common screen sizes and re-adjusts properly across Chromium/Firefox/WebKit on both http and https. Fix layout/overflow/orientation issues. Add Playwright runs at three viewports x three browsers to the suite. | I62: Enhancement | J62: 1) No layout/overflow defects across three viewports and three browsers. 2) Works on http and https. 3) Snapshots captured as baselines. 4) Wired to the visual-regression job. | K62: 4
A63: PPIQ-T150 | B63: Archive synthetic seeds out of production boot path | C63: P09 | D63: important | E63: Track 2 — Hardening | F63: Database | G63: Seeds / Hygiene | H63: Carries v3 PPIQ-T078. Move any synthetic/placeholder seed out of the boot path into Backend/database/seeds/demo-only/, invoked only by the demo reset job and only when tenant.is_demo = true. Any seed touching a real tenant must be explicit and approved. | I63: Bug Fix | J63: 1) Grep of API startup shows zero demo-seed calls in the production boot path. 2) A fresh non-demo tenant has zero synthetic rows. 3) The demo tenant re-seeds correctly via reset. 4) Audit shows seed activity only on demo tenants. | K63: 2
A64: PPIQ-T151 | B64: Complete Standard* contract tests | C64: P09 | D64: important | E64: Track 2 — Hardening | F64: App Frontend | G64: Quality / Contract Tests | H64: Carries v3 PPIQ-T081. Ensure every Standard* primitive has a contract test asserting prop names/types/defaults and render shape (data-testid hooks). Fill gaps (Surface/Fields variants) beyond the existing Button/Table/Tabs tests. | I64: New Feature | J64: 1) Contract tests exist for all Standard* primitives. 2) A non-backward-compatible prop change fails a contract test. 3) Suite < 30s on every PR. | K64: 3
A65: Phase 10 — Demo Storytelling, Personas & Recording (Vision Track 3) | 6 tasks | 20 hrs
A66: PPIQ-T152 | B66: 25-step technical demo script with verification points | C66: P10 | D66: very important | E66: Track 3 — Demo | F66: Documentation | G66: Demo Scripts / Technical | H66: Carries v3 PPIQ-T070. docs/demo/technical-demo-25-steps.md: 25 steps, each with [Action],[Expected UI state],[Verification checkpoint],[Recovery line],[Backend log indicator]. Covers login, connect each source, map/join one, delta sync, Data Quality findings, save investigation, calculate risk, export PDF, run ML readiness gate, run an inspection job and view the generated page, view a suggestion, deploy a script-layer widget, view audit log, reset demo. Screenshots match the Standard*-migrated UI. | I66: New Feature | J66: 1) 25 steps, all five fields populated. 2) Screenshots match the current UI. 3) A new SE runs it end-to-end in < 40 min. 4) Each checkpoint is concrete. | K66: 4
A67: PPIQ-T153 | B67: 5-minute executive demo script with talk track | C67: P10 | D67: very important | E67: Track 3 — Demo | F67: Documentation | G67: Demo Scripts / Executive | H67: Carries v3 PPIQ-T071. docs/demo/executive-demo-5min.md: 4 acts (problem 60s; solution 90s; demo 2m30s — search -> drilldown -> calculate risk -> inspection job -> suggestion -> PDF; close 60s). Exact words + the screen to show per act. | I67: New Feature | J67: 1) Four acts, total 4:30–5:00 measured. 2) Deliverable from the script without rehearsal. 3) Each act references a specific page+state. | K67: 3
A68: PPIQ-T154 | B68: Recovery lines for known fail-points | C68: P10 | D68: important | E68: Track 3 — Demo | F68: Documentation | G68: Demo Scripts / Recovery | H68: Carries v3 PPIQ-T072. docs/demo/recovery-lines.md: >=12 known weak points (Oracle warm-up, first connector load, ML run latency, PDF render, network hiccup, stale cache) each with a calm, confident, non-apologetic recovery line + remediation gesture, in brand voice. | I68: New Feature | J68: 1) >=12 fail-points covered. 2) Each line is calm and on-brand. 3) Founder review approves the tone. | K68: 2
A69: PPIQ-T155 | B69: Demo persona accounts (Operator, QA Lead, Plant Manager, Admin) | C69: P10 | D69: very important | E69: Track 3 — Demo | F69: Database | G69: Demo Lifecycle / Personas | H69: Carries v3 PPIQ-T073. Seed four personas via the demo reset job with rotated credentials and tuned home pages (Operator: today's quality events; QA Lead: open investigations; Plant Manager: risk by line; Admin: system health). Role/tier restrictions enforced. | I69: New Feature | J69: 1) After reset all four log in. 2) Each home page is tuned per spec. 3) Operator cannot reach Admin pages. 4) Credentials documented (gitignored real values, vaulted). | K69: 3
A70: PPIQ-T156 | B70: Seed canonical demo plant layout (flat-steel, Vision Track 3) | C70: P10 | D70: very important | E70: Track 3 — Demo | F70: Database | G70: Demo Lifecycle / Canonical Layout | H70: Carries/updates v3 PPIQ-T074 to the steel-plant vision. Seed the canonical layout (EAF/LF/CC/TF/HSM/SKP/LCT/HCT/STL/PKL/GVL/Yard/Roll Shop) with realistic genealogy and per-area equipment/counters, applied via the demo reset job. Document at docs/demo/canonical-layout.md. | I70: New Feature | J70: 1) Layout after reset matches the documented canonical plant. 2) Genealogy intact across areas. 3) Process history/quality/risk realistic per material. 4) Re-applies cleanly via reset. | K70: 4
A71: PPIQ-T157 | B71: Record dry-run demo video + capture website screenshots | C71: P10 | D71: important | E71: Track 4 — Website | F71: Documentation | G71: Demo Recording / Website Assets | H71: Carries v3 PPIQ-T075. After prior phases are green, record one 5-minute executive dry-run (screen+voice) on the Standard*-migrated UI and capture 10+ 1080p screenshots (login, dashboard, material search, drilldown, risk, inspection page, suggestion, PDF, audit, reset) into Website assets. | I71: New Feature | J71: 1) 5-min video at 1080p+. 2) 10+ screenshots at 1920x1080. 3) Website renders the new assets. 4) In-app/website visual consistency confirmed. | K71: 4
A72: Phase 11 — Website Track — 5-Product Showcase & Brand (Vision Track 4) | 9 tasks | 28 hrs
A73: PPIQ-T158 | B73: Produce the logo asset set per brand brief | C73: P11 | D73: important | E73: Track 4 — Website | F73: Web | G73: Website / Brand Assets | H73: Vision §2.4: produce the full logo set — full horizontal, icon-only favicon, stacked vertical — each in full-color, dark, light, monochrome — from the connected-node concept (Electric Cyan nodes on Deep Navy). Ship optimized SVG + PNG; wire into the app header, website, and PDF reports. | I73: New Feature | J73: 1) All variants exist as SVG+PNG within palette. 2) Favicon + app header + website + PDF header use the correct variant. 3) No drop shadows/recolors/steel-only imagery (brief 'Do Not' respected). | K73: 3
A74: PPIQ-T159 | B74: PlantProcess IQ product page (full) | C74: P11 | D74: very important | E74: Track 4 — Website | F74: Web | G74: Website / Product Page | H74: Vision Track 4 product 1: full PlantProcess IQ page — description, benefits, interactive graphics/screenshots, license matrix, golden-rule CTA. Evidence-grade, on-brand. Reuse the proof components already built (PricingLicenseMatrix, ProductScreenshotShowcase). | I74: New Feature | J74: 1) Page covers description/benefits/graphics/license/CTA. 2) Uses brand grammar and post-migration screenshots. 3) CTA links to the live demo. 4) Responsive across viewports. | K74: 4
A75: PPIQ-T160 | B75: MES product page (full) | C75: P11 | D75: important | E75: Track 4 — Website | F75: Web | G75: Website / Product Page | H75: Vision Track 4 product 2: full Manufacturing Execution System page — description, benefits, interactive graphics, license, golden rule. Consistent brand grammar with the PPIQ page. | I75: New Feature | J75: 1) Full MES page with all required sections. 2) Brand-consistent with PPIQ page. 3) CTA wired. 4) Responsive. | K75: 3
A76: PPIQ-T161 | B76: QES product page (full) | C76: P11 | D76: important | E76: Track 4 — Website | F76: Web | G76: Website / Product Page | H76: Vision Track 4 product 3: full Quality Execution System page — description, benefits, interactive graphics, license, golden rule. | I76: New Feature | J76: 1) Full QES page with all required sections. 2) Brand-consistent. 3) CTA wired. 4) Responsive. | K76: 3
A77: PPIQ-T162 | B77: Yard & Warehouse Management product page (full) | C77: P11 | D77: important | E77: Track 4 — Website | F77: Web | G77: Website / Product Page | H77: Vision Track 4 product 4: full Yard & Warehouse Management page — description, benefits, interactive graphics, license, golden rule. | I77: New Feature | J77: 1) Full page with all required sections. 2) Brand-consistent. 3) CTA wired. 4) Responsive. | K77: 3
A78: PPIQ-T163 | B78: Energy Management product page (full) | C78: P11 | D78: important | E78: Track 4 — Website | F78: Web | G78: Website / Product Page | H78: Vision Track 4 product 5: full Energy Management page — description, benefits, interactive graphics, license, golden rule. | I78: New Feature | J78: 1) Full page with all required sections. 2) Brand-consistent. 3) CTA wired. 4) Responsive. | K78: 3
A79: PPIQ-T164 | B79: Pricing + CTA wired to lead capture & demo lifecycle | C79: P11 | D79: important | E79: Track 4 — Website | F79: Web | G79: Website / Pricing & CTA | H79: Carries v3 PPIQ-T085. Three tiers (Pro/Pro Plus/Enterprise) with a feature matrix consistent with in-app licensing; 'Book a demo' posts to /api/leads with UTM params and triggers a calendar booking flow; leads land where the founder is notified. Website CTA buttons match the in-app brand grammar. | I79: Enhancement | J79: 1) Pricing renders three tiers + feature matrix matching in-app gating. 2) Book-a-demo submits a lead and shows a booking flow. 3) Lead notification reaches the founder. 4) Brand consistency with the app. | K79: 4
A80: PPIQ-T165 | B80: Evidence-grade screenshots + case-study snippets | C80: P11 | D80: important | E80: Track 4 — Website | F80: Web | G80: Website / Proof | H80: Carries v3 PPIQ-T086. Integrate the T157 screenshots into hero/features/proof with 'See it in the live demo' deep links, plus one evidence-grade case-study paragraph for the canonical plant (no exaggeration, brand voice). | I80: Enhancement | J80: 1) Hero/features/proof show post-migration UI. 2) CTAs deep-link to the page shown. 3) Case-study snippet is evidence-grade and on-brand. | K80: 3
A81: PPIQ-T166 | B81: Brand identity consistency audit (app + website + reports) | C81: P11 | D81: normal | E81: Track 4 — Website | F81: Web | G81: Website / Brand Audit | H81: Vision Track 4 'same brand identity everywhere': audit palette, typography (Inter / JetBrains Mono), logo usage, and tone across app, website, and PDF reports; fix any drift. Produce docs/brand/consistency-audit-{date}.md. | I81: Enhancement | J81: 1) Palette/typography/logo usage consistent across all three surfaces. 2) PDF reports use the light-mode brand header/footer. 3) Audit document lists and resolves every drift. | K81: 2
A82: Phase 12 — Legal Templates, Runbooks & Documentation | 8 tasks | 25.5 hrs
A83: PPIQ-T167 | B83: Mutual NDA template | C83: P12 | D83: important | E83: Track 4 — Website | F83: Documentation | G83: Legal / NDA | H83: Carries v3 PPIQ-T082. docs/legal/NDA-mutual-v1.docx parameterized for {EffectiveDate}{Counterparty}{Term}: confidential-info definition, exclusions, term (default 3y), purpose limitation, return of materials, no implied license, governing law (Dusseldorf / German law default). Counsel review before first use. Plain-md version for diffing. | I83: New Feature | J83: 1) Docx template renders with placeholders. 2) Counsel sign-off captured in docs/legal/REVIEWS.md. 3) MD diff version checked in. | K83: 2
A84: PPIQ-T168 | B84: SOW pilot template parameterized for pilot scope | C84: P12 | D84: important | E84: Track 4 — Website | F84: Documentation | G84: Legal / SOW | H84: Carries v3 PPIQ-T083. docs/legal/SOW-pilot-v1.docx: scope (sources connected, modules enabled, success metrics), duration (default 8 weeks), price, deliverables, acceptance criteria, change-control. Aligned with the vision pricing model. Counsel review. | I84: New Feature | J84: 1) Docx template renders with placeholders. 2) Pricing fields match the website pricing page (T164). 3) Counsel sign-off captured. | K84: 2.5
A85: PPIQ-T169 | B85: DPA template aligned with GDPR / SOC 2 Type I | C85: P12 | D85: important | E85: Track 4 — Website | F85: Documentation | G85: Legal / DPA | H85: Carries v3 PPIQ-T084. docs/legal/DPA-gdpr-v1.docx: controller/processor roles, processing purposes, data categories, subprocessors (Hetzner; Anthropic only if used), security measures, breach notification (72h), audit rights, retention, deletion on termination. Counsel review. | I85: New Feature | J85: 1) Docx template renders with placeholders. 2) Subprocessors list matches the actual production deployment. 3) Counsel sign-off captured. | K85: 2.5
A86: PPIQ-T170 | B86: Deployment runbook (server, Compose, Caddy, Jenkins) | C86: P12 | D86: important | E86: Track 2 — Hardening | F86: Documentation | G86: Runbook / Deployment | H86: Carries v3 PPIQ-T087. docs/runbook/deployment.md: bootstrap a fresh Hetzner Ubuntu 26.04 server from zero to running PPIQ in < 30 min — SSH hardening, Docker install, repo clone, .env prep, Caddy install + Caddyfile, Jenkins install + plugins + webhook, first deploy, post-deploy verification. Each step has the exact command, expected output, and failure-and-remediation note. | I86: New Feature | J86: 1) A new engineer bootstraps a fresh server in < 30 min following the runbook. 2) Every command verified live. 3) Failure modes documented with fixes. | K86: 4
A87: PPIQ-T171 | B87: Incident-response runbook (rollback, restore, comms) + daily backup job | C87: P12 | D87: important | E87: Track 2 — Hardening | F87: Documentation | G87: Runbook / Incident Response | H87: Carries v3 PPIQ-T088. docs/runbook/incident-response.md: rollback to the previous container tag < 5 min, restore from Postgres backup, restore from audit-log replay, customer comms templates, severity matrix, escalation. Reference the Jenkinsfile rollback path and the daily backup job — verify the latter exists; if not, build it (offsite/encrypted). | I87: New Feature | J87: 1) Runbook covers the four scenarios with concrete commands. 2) Daily backup job exists, runs, stores backups offsite encrypted. 3) Restore tested end-to-end in a sandbox < 30 min. 4) Severity matrix + comms templates approved. | K87: 5
A88: PPIQ-T172 | B88: UI Standards onboarding for future contributors | C88: P12 | D88: important | E88: Track 2 — Hardening | F88: Documentation | G88: Documentation / Onboarding | H88: Carries v3 PPIQ-T089. docs/ui-standards/contributing.md: canonical import paths, the ESLint rules, how to add/extend a Standard* component without breaking the contract, how to update design tokens. Reference the Storybook URL. Worked example: add a ProgressBar primitive from scratch in < 60 min. | I88: New Feature | J88: 1) Document references all Standard* primitives. 2) Worked example is reproducible. 3) A new contributor authors a primitive PR in < 60 min following the doc. | K88: 2.5
A89: PPIQ-T173 | B89: Widget script grammar reference for power users | C89: P12 | D89: important | E89: Track 1 — Workflow | F89: Documentation | G89: Documentation / Widget Grammar | H89: Carries v3 PPIQ-T090. docs/widget-grammar/reference.md: the full grammar, every aggregate function, every filter operator, every limitation. 10+ worked examples (count by category, sum over time, top-N with rank, conditional aggregates). The explicit list of canonical schema views available. The SafeSqlValidator blocked patterns and why. Linked from the widget editor as inline help. | I89: New Feature | J89: 1) Reference covers the full grammar. 2) 10+ worked examples each compile and execute. 3) Linked from the WidgetExpressionEditor as inline help. | K89: 3
A90: PPIQ-T174 | B90: Tenant isolation, data retention & audit-log architecture doc | C90: P12 | D90: important | E90: Track 2 — Hardening | F90: Documentation | G90: Documentation / Security Architecture | H90: Carries v3 PPIQ-T091. docs/architecture/security-and-isolation.md: SingleTenantPerPilot mode, tenant_id enforcement via row-level security, audit-log immutability via trigger guards, retention defaults (audit 7y, telemetry 90d, application 365d), encryption at rest/in transit, key rotation, backup encryption. Used in SOC 2 and customer security reviews; cross-references AuditLogImmutabilityTests.cs. | I90: New Feature | J90: 1) Document covers all six topics with diagrams. 2) Cross-references AuditLogImmutabilityTests.cs as the verification proof. 3) Diagrams in mermaid, checked in as source + exported PNG. 4) Founder + counsel review for accuracy. | K90: 4

Sheet How to Use
A1: How to Use This Workbook (v4)
A3: Relationship to v3 | B3: This is the v4 plan. It contains only the OPEN work. v3 Phases 1–8 (tasks PPIQ-T001–T062) were validated as >85% complete on 30 May 2026 and are intentionally NOT repeated here. See the companion analysis report for the phase-by-phase verdict and evidence.
A4: Audience | B4: Founder / lead developer (Karim) and any future contributor. The workbook is the single source of truth for what 'finished' means against the 4-Track Vision, now including the ML engine, the generic schema-mapping + delta-import architecture, the page builder, and the full 5-product website.
A5: Sheets | B5: 1) Task List — 74 tasks grouped by 12 phases, developer-grade detail. 2) How to Use. 3) Phase Summary — effort + severity rollup per phase (formula-driven). 4) UI Standards Reference — the canonical component contract every page must conform to (unchanged, still enforced). 5) Rollups — pivot views by severity, track, module, type (formula-driven).
A6: Severity scale | B6: critical (P0, do first) > very important (this sprint) > important (before paid pilot) > normal > optional. Phase 1 closes the residual security/brand hotfixes carried over from the completed phases and must be done before any external demo.
A7: Tracks | B7: Track 1 Workflow, Track 2 Hardening, Track 3 Demo, Track 4 Website. The biggest net-new investment is the ML engine (Phases 4–6) and the schema-mapping/delta-import foundation it depends on (Phases 2–3) — the parts of the vision the earlier lists never covered.
A8: Module taxonomy | B8: App Frontend (React/TS), App Backend (.NET 9), Database (PostgreSQL 17 + EF Core), Infrastructure (Docker, Caddy, Jenkins, Hetzner), Web (marketing site), Documentation.
A9: Task ID format | B9: PPIQ-T### — continues from the v3 series and starts at PPIQ-T101 so IDs never collide with the completed T001–T091. Where a task carries forward open v3 work, its Description cites the original v3 ID (e.g. 'Carries v3 PPIQ-T076').
A10: Phase ID | B10: P01–P12 — a fresh sequence for the v4 plan. Recommended order is strictly top-to-bottom: P01 hotfixes first; P02–P03 build the schema/import foundation; P04–P06 deliver the ML engine on that foundation; P07 the page builder; P08 the demo at scale; P09 hardening; P10 storytelling; P11 website; P12 legal/docs.
A11: Effort estimates | B11: Hours for a single experienced full-stack engineer (Karim's profile). Calendar days = hours / 6 productive hours/day. Add 25–35% buffer for review, integration, and validation. Totals are computed on the Phase Summary and Rollups sheets.
A12: Validation column | B12: Every task carries explicit verification steps. A task is not Done until every validation step passes. CI gates and Jenkins post-deploy probes enforce this automatically where possible. The forbidden phrase 'could not be loaded / could not load' and forbidden ML claims ('guaranteed root cause', 'AI-powered prediction', 'production-ready AI') must never appear in any deliverable.
A13: Vision alignment | B13: Each task is tagged to one of the four Vision tracks and to the specific vision clause it satisfies (in the Submodule/Description). Completing every task in this workbook brings the 4-Track Vision to 100% at the depth the vision specifies.
A14: Update cadence | B14: Re-audit weekly. After each phase, run the validation steps end-to-end, snapshot the workbook with a Status column appended (Done / Blocked / In Progress), and commit to docs/planning/.

Sheet Phase Summary
A1: Phase Summary — effort, severity, and module distribution
A2: Recommended execution order: top-to-bottom. Counts and effort are computed live from the Task List sheet.
A3: Phase ID | B3: Phase Name | C3: Tasks | D3: Critical | E3: Very Important | F3: Important | G3: Normal | H3: Effort (hrs) | I3: Effort (days)
A4: P01 | B4: Carry-Forward Hotfixes & Residual Closeout | C4: =COUNTIF('Task List'!$C$6:$C$90,A4) -> 6 | D4: =COUNTIFS('Task List'!$C$6:$C$90,A4,'Task List'!$D$6:$D$90,"critical") -> 2 | E4: =COUNTIFS('Task List'!$C$6:$C$90,A4,'Task List'!$D$6:$D$90,"very important") -> 2 | F4: =COUNTIFS('Task List'!$C$6:$C$90,A4,'Task List'!$D$6:$D$90,"important") -> 2 | G4: =COUNTIFS('Task List'!$C$6:$C$90,A4,'Task List'!$D$6:$D$90,"normal") -> 0 | H4: =SUMIF('Task List'!$C$6:$C$90,A4,'Task List'!$K$6:$K$90) -> 13 | I4: =H4/6 -> 2.1666667
A5: P02 | B5: Generic Schema Mapping & Canonical View Engine (Vision §1.4) | C5: =COUNTIF('Task List'!$C$6:$C$90,A5) -> 6 | D5: =COUNTIFS('Task List'!$C$6:$C$90,A5,'Task List'!$D$6:$D$90,"critical") -> 0 | E5: =COUNTIFS('Task List'!$C$6:$C$90,A5,'Task List'!$D$6:$D$90,"very important") -> 5 | F5: =COUNTIFS('Task List'!$C$6:$C$90,A5,'Task List'!$D$6:$D$90,"important") -> 1 | G5: =COUNTIFS('Task List'!$C$6:$C$90,A5,'Task List'!$D$6:$D$90,"normal") -> 0 | H5: =SUMIF('Task List'!$C$6:$C$90,A5,'Task List'!$K$6:$K$90) -> 35 | I5: =H5/6 -> 5.8333333
A6: P03 | B6: Two-Stage Delta Import Architecture (Vision §1.1–1.6) | C6: =COUNTIF('Task List'!$C$6:$C$90,A6) -> 6 | D6: =COUNTIFS('Task List'!$C$6:$C$90,A6,'Task List'!$D$6:$D$90,"critical") -> 0 | E6: =COUNTIFS('Task List'!$C$6:$C$90,A6,'Task List'!$D$6:$D$90,"very important") -> 4 | F6: =COUNTIFS('Task List'!$C$6:$C$90,A6,'Task List'!$D$6:$D$90,"important") -> 2 | G6: =COUNTIFS('Task List'!$C$6:$C$90,A6,'Task List'!$D$6:$D$90,"normal") -> 0 | H6: =SUMIF('Task List'!$C$6:$C$90,A6,'Task List'!$K$6:$K$90) -> 27 | I6: =H6/6 -> 4.5
A7: P04 | B7: ML Engine — Scheduled Correlation Learning (Vision §3.1) | C7: =COUNTIF('Task List'!$C$6:$C$90,A7) -> 5 | D7: =COUNTIFS('Task List'!$C$6:$C$90,A7,'Task List'!$D$6:$D$90,"critical") -> 0 | E7: =COUNTIFS('Task List'!$C$6:$C$90,A7,'Task List'!$D$6:$D$90,"very important") -> 3 | F7: =COUNTIFS('Task List'!$C$6:$C$90,A7,'Task List'!$D$6:$D$90,"important") -> 2 | G7: =COUNTIFS('Task List'!$C$6:$C$90,A7,'Task List'!$D$6:$D$90,"normal") -> 0 | H7: =SUMIF('Task List'!$C$6:$C$90,A7,'Task List'!$K$6:$K$90) -> 26 | I7: =H7/6 -> 4.3333333
A8: P05 | B8: ML Engine — Inspection Jobs to Generated Pages (Vision §3.2) | C8: =COUNTIF('Task List'!$C$6:$C$90,A8) -> 6 | D8: =COUNTIFS('Task List'!$C$6:$C$90,A8,'Task List'!$D$6:$D$90,"critical") -> 0 | E8: =COUNTIFS('Task List'!$C$6:$C$90,A8,'Task List'!$D$6:$D$90,"very important") -> 4 | F8: =COUNTIFS('Task List'!$C$6:$C$90,A8,'Task List'!$D$6:$D$90,"important") -> 2 | G8: =COUNTIFS('Task List'!$C$6:$C$90,A8,'Task List'!$D$6:$D$90,"normal") -> 0 | H8: =SUMIF('Task List'!$C$6:$C$90,A8,'Task List'!$K$6:$K$90) -> 31 | I8: =H8/6 -> 5.1666667
A9: P06 | B9: ML Engine — Suggestion & Recommendation Assistant (Vision §3.3) | C9: =COUNTIF('Task List'!$C$6:$C$90,A9) -> 5 | D9: =COUNTIFS('Task List'!$C$6:$C$90,A9,'Task List'!$D$6:$D$90,"critical") -> 0 | E9: =COUNTIFS('Task List'!$C$6:$C$90,A9,'Task List'!$D$6:$D$90,"very important") -> 2 | F9: =COUNTIFS('Task List'!$C$6:$C$90,A9,'Task List'!$D$6:$D$90,"important") -> 3 | G9: =COUNTIFS('Task List'!$C$6:$C$90,A9,'Task List'!$D$6:$D$90,"normal") -> 0 | H9: =SUMIF('Task List'!$C$6:$C$90,A9,'Task List'!$K$6:$K$90) -> 23 | I9: =H9/6 -> 3.8333333
A10: P07 | B10: Page Builder & Widget Library (Vision §2.1–2.2) | C10: =COUNTIF('Task List'!$C$6:$C$90,A10) -> 5 | D10: =COUNTIFS('Task List'!$C$6:$C$90,A10,'Task List'!$D$6:$D$90,"critical") -> 0 | E10: =COUNTIFS('Task List'!$C$6:$C$90,A10,'Task List'!$D$6:$D$90,"very important") -> 3 | F10: =COUNTIFS('Task List'!$C$6:$C$90,A10,'Task List'!$D$6:$D$90,"important") -> 2 | G10: =COUNTIFS('Task List'!$C$6:$C$90,A10,'Task List'!$D$6:$D$90,"normal") -> 0 | H10: =SUMIF('Task List'!$C$6:$C$90,A10,'Task List'!$K$6:$K$90) -> 30 | I10: =H10/6 -> 5
A11: P08 | B11: Demo Source-Database Suite at Real Scale (Vision Track 3) | C11: =COUNTIF('Task List'!$C$6:$C$90,A11) -> 4 | D11: =COUNTIFS('Task List'!$C$6:$C$90,A11,'Task List'!$D$6:$D$90,"critical") -> 0 | E11: =COUNTIFS('Task List'!$C$6:$C$90,A11,'Task List'!$D$6:$D$90,"very important") -> 3 | F11: =COUNTIFS('Task List'!$C$6:$C$90,A11,'Task List'!$D$6:$D$90,"important") -> 1 | G11: =COUNTIFS('Task List'!$C$6:$C$90,A11,'Task List'!$D$6:$D$90,"normal") -> 0 | H11: =SUMIF('Task List'!$C$6:$C$90,A11,'Task List'!$K$6:$K$90) -> 27 | I11: =H11/6 -> 4.5
A12: P09 | B12: Hardening Completion & Resilience (Vision Track 2) | C12: =COUNTIF('Task List'!$C$6:$C$90,A12) -> 8 | D12: =COUNTIFS('Task List'!$C$6:$C$90,A12,'Task List'!$D$6:$D$90,"critical") -> 0 | E12: =COUNTIFS('Task List'!$C$6:$C$90,A12,'Task List'!$D$6:$D$90,"very important") -> 2 | F12: =COUNTIFS('Task List'!$C$6:$C$90,A12,'Task List'!$D$6:$D$90,"important") -> 6 | G12: =COUNTIFS('Task List'!$C$6:$C$90,A12,'Task List'!$D$6:$D$90,"normal") -> 0 | H12: =SUMIF('Task List'!$C$6:$C$90,A12,'Task List'!$K$6:$K$90) -> 35 | I12: =H12/6 -> 5.8333333
A13: P10 | B13: Demo Storytelling, Personas & Recording (Vision Track 3) | C13: =COUNTIF('Task List'!$C$6:$C$90,A13) -> 6 | D13: =COUNTIFS('Task List'!$C$6:$C$90,A13,'Task List'!$D$6:$D$90,"critical") -> 0 | E13: =COUNTIFS('Task List'!$C$6:$C$90,A13,'Task List'!$D$6:$D$90,"very important") -> 4 | F13: =COUNTIFS('Task List'!$C$6:$C$90,A13,'Task List'!$D$6:$D$90,"important") -> 2 | G13: =COUNTIFS('Task List'!$C$6:$C$90,A13,'Task List'!$D$6:$D$90,"normal") -> 0 | H13: =SUMIF('Task List'!$C$6:$C$90,A13,'Task List'!$K$6:$K$90) -> 20 | I13: =H13/6 -> 3.3333333
A14: P11 | B14: Website Track — 5-Product Showcase & Brand (Vision Track 4) | C14: =COUNTIF('Task List'!$C$6:$C$90,A14) -> 9 | D14: =COUNTIFS('Task List'!$C$6:$C$90,A14,'Task List'!$D$6:$D$90,"critical") -> 0 | E14: =COUNTIFS('Task List'!$C$6:$C$90,A14,'Task List'!$D$6:$D$90,"very important") -> 1 | F14: =COUNTIFS('Task List'!$C$6:$C$90,A14,'Task List'!$D$6:$D$90,"important") -> 7 | G14: =COUNTIFS('Task List'!$C$6:$C$90,A14,'Task List'!$D$6:$D$90,"normal") -> 1 | H14: =SUMIF('Task List'!$C$6:$C$90,A14,'Task List'!$K$6:$K$90) -> 28 | I14: =H14/6 -> 4.6666667
A15: P12 | B15: Legal Templates, Runbooks & Documentation | C15: =COUNTIF('Task List'!$C$6:$C$90,A15) -> 8 | D15: =COUNTIFS('Task List'!$C$6:$C$90,A15,'Task List'!$D$6:$D$90,"critical") -> 0 | E15: =COUNTIFS('Task List'!$C$6:$C$90,A15,'Task List'!$D$6:$D$90,"very important") -> 0 | F15: =COUNTIFS('Task List'!$C$6:$C$90,A15,'Task List'!$D$6:$D$90,"important") -> 8 | G15: =COUNTIFS('Task List'!$C$6:$C$90,A15,'Task List'!$D$6:$D$90,"normal") -> 0 | H15: =SUMIF('Task List'!$C$6:$C$90,A15,'Task List'!$K$6:$K$90) -> 25.5 | I15: =H15/6 -> 4.25
A16: TOTAL | B16: All open phases | C16: =SUM(C4:C15) -> 74 | D16: =SUM(D4:D15) -> 2 | E16: =SUM(E4:E15) -> 33 | F16: =SUM(F4:F15) -> 38 | G16: =SUM(G4:G15) -> 1 | H16: =SUM(H4:H15) -> 320.5 | I16: =H16/6 -> 53.416667
A18: Effort-days assume 6 productive engineering hours per workday. Add 25–35% buffer for review, integration, and validation cycles.

Sheet UI Standards Reference
A1: UI Standards — Canonical Component Contract (unchanged, still enforced)
A2: Every interactive element across all existing AND future pages must conform. Enforced via ESLint, CI lint, code review, and Storybook.
A3: Component | B3: Canonical Path | C3: Variants / Modes | D3: Required Props | E3: Required States
A4: StandardButton | B4: src/components/standard/StandardButton.tsx | C4: primary | secondary | ghost | danger | success | icon-only | D4: variant, size (sm|md|lg), leadingIcon, trailingIcon, isLoading, isDisabled, fullWidth, onClick, type, ariaLabel, as ('button'|'a'), href | E4: default, hover, focus (4px brand-cyan ring 2px offset), active (translate-y 1px), disabled (40% opacity), loading (spinner + aria-busy)
A5: StandardTable | B5: src/components/standard/StandardTable.tsx | C5: client-mode | server-mode | virtualized (>500 rows) | D5: columns (with cell renderers), data, isLoading, hasError, onRetry, totalCount, onRowClick, primaryAction, density, selectable, exportable | E5: loading (skeleton rows), error ('Refreshing X…' + retry), empty (illustration + CTA), populated, sorted, filtered, paginated, selected
A6: StandardTabs | B6: src/components/standard/StandardTabs.tsx | C6: horizontal | vertical | scroll-on-overflow | D6: items (id, label, icon?, badge?, content), value, onChange, orientation, lazy, urlParam | E6: default, active (4px brand-blue indicator), hover, disabled, overflow-scrollable, keyboard-focused
A7: StandardInput | B7: src/components/standard/StandardInput.tsx (StandardFields) | C7: text | email | password | number | search | D7: label, helperText, error, leadingIcon, trailingIcon, value, onChange, placeholder, required, disabled, isLoading, size, type | E7: default, focus (2px brand border), error (2px danger border + helper-text), disabled, with-value, search-clearable
A8: StandardSelect | B8: src/components/standard/StandardSelect.tsx (StandardFields) | C8: single | multi | searchable | D8: label, helperText, error, options, value, onChange, placeholder, required, disabled, size, multiple, searchable | E8: closed, open, searching, no-results, multi-selected (chips), keyboard-navigated
A9: StandardTextArea | B9: src/components/standard/StandardTextArea.tsx (StandardFields) | C9: default | code (monospace + syntax highlight) | D9: label, helperText, error, value, onChange, placeholder, required, disabled, rows, autoResize, language | E9: default, focus, error, disabled, autoresize-growing
A10: StandardCard | B10: src/components/standard/StandardSurface.tsx | C10: flat | raised | floating | D10: title, subtitle, headerActions, footerActions, elevation, children | E10: default, hover (raised only), with-actions, without-header
A11: StandardModal | B11: src/components/standard/StandardSurface.tsx | C11: sm | md | lg | xl | D11: open, onClose, title, size, children, footerActions, dismissOnBackdrop, dismissOnEscape, isDirty | E11: open (focus-trapped), closing, dirty-blocked (no backdrop dismiss)
A12: StandardToast | B12: src/components/standard/StandardSurface.tsx (Sonner) | C12: info | success | warning | error | loading | D12: title, description, action (label + onClick), duration, dismissible, variant | E12: incoming (slide-in), shown (with progress bar), dismissing, stacked-overflow
A13: DataFetchBoundary | B13: src/components/standard/DataFetchBoundary.tsx | C13: default | with-skeleton-mirror | D13: isLoading, hasError, onRetry, loadingFallback, errorFallback, children | E13: loading ('Refreshing X…'), error ('Refreshing X…' + retry + auto-retry-5s), success (renders children)
A14: ErrorBoundary | B14: src/components/standard/ErrorBoundary.tsx | C14: app-level | route-level | component-level | D14: fallback, onError, resetKeys, children | E14: caught (renders fallback + logs to /diagnostics/client-error), retrying, recovered
A16: FORBIDDEN PATTERNS (CI-enforced)
A17: Forbidden phrase | B17: 'could not be loaded' / 'could not load' | C17: Use the 'Refreshing X…' pattern. Founder's #1 non-negotiable (Vision §2).
A18: Forbidden ML claims | B18: 'guaranteed root cause' / 'AI-powered prediction' / 'production-ready AI' / 'predicts' | C18: Use 'suspected contributor' / 'statistical correlation' / 'rule-based risk scoring' (Vision Track 4 brand voice).
A19: Native element | B19: <button>, <input>, <select>, <table>, <textarea> in src/pages/* or src/features/* | C19: Use Standard* primitives. ESLint no-restricted-syntax enforces this.
A20: Deprecated path | B20: import from src/components/hardening/* or src/hardening/* | C20: Use src/components/standard/*. ESLint blocks reintroduction.
A21: Inline styling | B21: style={{...}} on interactive elements outside Standard* internals | C21: Use Standard* variant + size props.

Sheet Rollups
A1: Rollups — by Severity, Track, Module, Type (computed live from Task List)
A2: By Severity | E2: By Track | I2: By Module | M2: By Type
A3: Severity | B3: Count | C3: Effort (hrs) | E3: Track | F3: Count | G3: Effort (hrs) | I3: Module | J3: Count | K3: Effort (hrs) | M3: Type | N3: Count | O3: Effort (hrs)
A4: critical | B4: =COUNTIF('Task List'!$D$6:$D$90,A4) -> 2 | C4: =SUMIF('Task List'!$D$6:$D$90,A4,'Task List'!$K$6:$K$90) -> 5.5 | E4: Track 1 — Workflow | F4: =COUNTIF('Task List'!$E$6:$E$90,E4) -> 29 | G4: =SUMIF('Task List'!$E$6:$E$90,E4,'Task List'!$K$6:$K$90) -> 156 | I4: App Frontend | J4: =COUNTIF('Task List'!$F$6:$F$90,I4) -> 19 | K4: =SUMIF('Task List'!$F$6:$F$90,I4,'Task List'!$K$6:$K$90) -> 97 | M4: New Feature | N4: =COUNTIF('Task List'!$I$6:$I$90,M4) -> 53 | O4: =SUMIF('Task List'!$I$6:$I$90,M4,'Task List'!$K$6:$K$90) -> 250.5
A5: very important | B5: =COUNTIF('Task List'!$D$6:$D$90,A5) -> 33 | C5: =SUMIF('Task List'!$D$6:$D$90,A5,'Task List'!$K$6:$K$90) -> 181.5 | E5: Track 2 — Hardening | F5: =COUNTIF('Task List'!$E$6:$E$90,E5) -> 24 | G5: =SUMIF('Task List'!$E$6:$E$90,E5,'Task List'!$K$6:$K$90) -> 88.5 | I5: App Backend | J5: =COUNTIF('Task List'!$F$6:$F$90,I5) -> 21 | K5: =SUMIF('Task List'!$F$6:$F$90,I5,'Task List'!$K$6:$K$90) -> 107 | M5: Enhancement | N5: =COUNTIF('Task List'!$I$6:$I$90,M5) -> 15 | O5: =SUMIF('Task List'!$I$6:$I$90,M5,'Task List'!$K$6:$K$90) -> 57
A6: important | B6: =COUNTIF('Task List'!$D$6:$D$90,A6) -> 38 | C6: =SUMIF('Task List'!$D$6:$D$90,A6,'Task List'!$K$6:$K$90) -> 131.5 | E6: Track 3 — Demo | F6: =COUNTIF('Task List'!$E$6:$E$90,E6) -> 8 | G6: =SUMIF('Task List'!$E$6:$E$90,E6,'Task List'!$K$6:$K$90) -> 37 | I6: Database | J6: =COUNTIF('Task List'!$F$6:$F$90,I6) -> 9 | K6: =SUMIF('Task List'!$F$6:$F$90,I6,'Task List'!$K$6:$K$90) -> 39 | M6: Bug Fix | N6: =COUNTIF('Task List'!$I$6:$I$90,M6) -> 6 | O6: =SUMIF('Task List'!$I$6:$I$90,M6,'Task List'!$K$6:$K$90) -> 13
A7: normal | B7: =COUNTIF('Task List'!$D$6:$D$90,A7) -> 1 | C7: =SUMIF('Task List'!$D$6:$D$90,A7,'Task List'!$K$6:$K$90) -> 2 | E7: Track 4 — Website | F7: =COUNTIF('Task List'!$E$6:$E$90,E7) -> 13 | G7: =SUMIF('Task List'!$E$6:$E$90,E7,'Task List'!$K$6:$K$90) -> 39 | I7: Infrastructure | J7: =COUNTIF('Task List'!$F$6:$F$90,I7) -> 4 | K7: =SUMIF('Task List'!$F$6:$F$90,I7,'Task List'!$K$6:$K$90) -> 11 | M7: TOTAL | N7: =SUM(N4:N6) -> 74 | O7: =SUM(O4:O6) -> 320.5
A8: optional | B8: =COUNTIF('Task List'!$D$6:$D$90,A8) -> 0 | C8: =SUMIF('Task List'!$D$6:$D$90,A8,'Task List'!$K$6:$K$90) -> 0 | E8: TOTAL | F8: =SUM(F4:F7) -> 74 | G8: =SUM(G4:G7) -> 320.5 | I8: Web | J8: =COUNTIF('Task List'!$F$6:$F$90,I8) -> 9 | K8: =SUMIF('Task List'!$F$6:$F$90,I8,'Task List'!$K$6:$K$90) -> 28
A9: TOTAL | B9: =SUM(B4:B8) -> 74 | C9: =SUM(C4:C8) -> 320.5 | I9: Documentation | J9: =COUNTIF('Task List'!$F$6:$F$90,I9) -> 12 | K9: =SUMIF('Task List'!$F$6:$F$90,I9,'Task List'!$K$6:$K$90) -> 38.5
I10: TOTAL | J10: =SUM(J4:J9) -> 74 | K10: =SUM(K4:K9) -> 320.5
