Workbook

Sheet Roadmap
A1: Task ID | B1: Task Name | C1: Phase | D1: Track | E1: Module | F1: Submodule | G1: Severity | H1: Description | I1: Acceptance Criteria | J1: Task Type | K1: Effort (h) | L1: Prerequisites | M1: Dimensions → 100
A2: T-001 | B2: Fix PKL MSSQL seed N-literal corruption | C2: P01 · Critical Fixes & Production-Safety Baseline | D2: Demo | E2: Database | F2: Demo-Sources | G2: Critical | H2: In Infrastructure/demo-sources/pkl-mssql/init/001_schema_seed.sql the N-prefixed unicode string literals are malformed: 'IF DB_ID(Npkl)' and 'IF OBJECT_ID(Ndbo.pkl_coils, Nu)' — the single quotes were stripped, so they are invalid identifiers and the batch fails in SQL Server. Restore them to DB_ID(N'pkl'), OBJECT_ID(N'dbo.pkl_coils', N'U'). Then sweep every demo-source .sql (caster/hsm Oracle, meltshop PG, downtime/parsytec MySQL, pkl) for the same pattern, and determine the root cause: confirm whether the on-disk file is correct and the audit exporter (tools/GeneratePlantProcessIQ_UltimateAudit.ps1) corrupts N-literals on read — if so, fix its read/escape logic so future audits are faithful. | I2: Running the pkl-mssql init against a fresh mcr.microsoft.com/mssql/server:2022 container exits 0 and 'SELECT COUNT(*) FROM dbo.pkl_coils' returns 1. A new xUnit test DemoSourceSeedSyntaxTests parses every demo-source .sql and asserts no bare 'N<identifier>' token (regex \bN[A-Za-z_] outside a quoted literal) exists; it fails if reintroduced. | J2: bug fix | K2: 3 | L2: — | M2: Functionality, Repo hygiene
A3: T-002 | B3: Fix Yard CSV leading-whitespace + harden CSV trim | C3: P01 · Critical Fixes & Production-Safety Baseline | D3: Demo | E3: Database | F3: Demo-Sources | G3: Normal | H3: Infrastructure/demo-sources/excel-yard/yard_inventory.csv has leading spaces in the bay/position values (' BAY-03', ' POS-17'). Trim them to 'BAY-03','POS-17'. As a defensive measure, ensure the Excel/CSV connector trims leading/trailing whitespace on every ingested field so dirty source files never leak whitespace into canon. | I3: A connector unit test ingests the yard CSV and asserts bay == 'BAY-03' (no leading space). Add a whitespace-trim case to the CSV connector test corpus that feeds ' x ' and asserts 'x' lands in canon. | J3: bug fix | K3: 1 | L3: — | M3: Functionality
A4: T-003 | B4: Confirm & lock dev-seed endpoints to Development only | C4: P01 · Critical Fixes & Production-Safety Baseline | D4: Hardening | E4: Backend | F4: Security | G4: Critical | H4: DevSeedEndpoints.MapDevSeedEndpoints must only be registered when app.Environment.IsDevelopment(). Open Backend/PlantProcess.Api/Program.cs and verify the call-site is inside an IsDevelopment() guard; if it is not, wrap it. Add a startup assertion that throws if dev-seed routes are mapped while the environment is not Development (defense in depth alongside StartupConfigurationValidator). | I4: An integration test boots the API with ASPNETCORE_ENVIRONMENT=Production and asserts every dev-seed route returns 404 (not mapped); a second test in Development asserts they return their expected 200. A StartupConfigurationValidator test asserts startup throws if dev-seed mapping is detected outside Development. | J4: hardening | K4: 4 | L4: — | M4: Security, Functionality
A5: T-004 | B5: Bind production PostgreSQL to loopback / private network | C5: P01 · Critical Fixes & Production-Safety Baseline | D5: Hardening | E5: Infrastructure | F5: Networking | G5: Critical | H5: Per doctrine §16 the production Postgres port must not be publicly reachable. In docker-compose.demo.yml, change the postgres service to publish on 127.0.0.1:5432 (or remove the host port entirely so it is reachable only on the internal docker network). Confirm Caddy and the API/worker containers still reach it via the compose network alias. | I5: On the Hetzner host, 'ss -tlnp | grep 5432' shows a 127.0.0.1 bind (or no public bind) and an external 'nmap -p 5432 178.105.152.180' shows filtered/closed. The API /health endpoint stays green (DB reachable internally). Update deploy/server runbook with the verified binding. | J5: hardening | K5: 3 | L5: — | M5: Security
A6: T-005 | B6: Verify NotImplemented null-object services are not the active bindings | C6: P01 · Critical Fixes & Production-Safety Baseline | D6: Hardening | E6: Backend | F6: DI | G6: Very important | H6: The DI graph contains NotImplementedImportBatchService, NotImplementedSourceSystemService, NotImplementedGenealogyService and NotImplementedMaterialService that return a typed 501. Confirm the REAL implementations are the production defaults registered in AddApplication/AddInfrastructure, and the NotImplemented variants are only fallbacks/test doubles. If any NotImplemented service is the active binding, wire the concrete implementation. | I6: A DI-resolution test resolves IImportBatchService, ISourceSystemService, IGenealogyService and IMaterialService from the production ServiceProvider and asserts the concrete type is NOT a NotImplemented* type; it then smoke-invokes one method on each and asserts the result is not ApplicationErrorType.NotImplemented. | J6: bug fix | K6: 3 | L6: — | M6: Functionality
A7: T-006 | B7: Remove dead duplicate page files (flat vs foldered) | C7: P01 · Critical Fixes & Production-Safety Baseline | D7: Hardening | E7: Frontend | F7: Pages | G7: Important | H7: Six pages exist twice: flat src/pages/XPage.tsx AND foldered src/pages/X/XPage.tsx — for Admin, Correlation, Dashboard, DataQuality, MaterialInvestigation, RiskDashboard. Inspect the router (src/App.tsx / route config) to see which path is actually imported; delete the unused twin and fix any stale imports. This removes dead code and the risk of editing the wrong file. | I7: After deletion 'grep -r' finds zero imports of the deleted files; 'npm run build', 'npm run e2e', route-smoke.spec.ts and nav-graph-refresh-survival.spec.ts all pass. Add an eslint no-restricted-imports rule (or a custom check) that forbids creating a flat pages/*Page.tsx when a foldered equivalent exists. | J7: refactor | K7: 5 | L7: — | M7: Repo hygiene, Code hygiene
A8: T-007 | B8: De-duplicate Jenkinsfile and TelemetryIngestionWorker | C8: P01 · Critical Fixes & Production-Safety Baseline | D8: Hardening | E8: Infrastructure | F8: Build | G8: Important | H8: Jenkinsfile exists at repo root and at deploy/ci/Jenkinsfile; keep the one the Jenkins job references and delete the other (or make one a thin include). TelemetryIngestionWorker.cs exists in both PlantProcess.Infrastructure/TimeSeries and PlantProcess.Workers; determine the canonical location and, if logic is duplicated, extract to one type referenced by both. | I8: Exactly one authoritative Jenkinsfile remains (documented), and a manual 'Build Now' is green. The solution compiles with a single TelemetryIngestionWorker type (no duplicate-type ambiguity) and the worker still ingests in its smoke/integration test. | J8: refactor | K8: 3 | L8: — | M8: Repo hygiene
A9: T-008 | B9: Add architecture (dependency-direction) tests | C9: P01 · Critical Fixes & Production-Safety Baseline | D9: Hardening | E9: Testing | F9: Architecture | G9: Important | H9: Add a NetArchTest-based test project asserting Clean Architecture boundaries so the upcoming refactors cannot silently break layering: Domain depends on nothing outward; Application depends only on Domain; Infrastructure may depend on Application+Domain; Api depends on Application (not Infrastructure internals); Analytics.Core has no Infrastructure dependency. | I9: A test class ArchitectureTests defines ≥6 rules that all pass; deliberately adding a banned reference (e.g., a Domain→Infrastructure using) makes the relevant test fail locally. The test project runs in CI on every push. | J9: test | K9: 5 | L9: — | M9: Code hygiene
A10: T-009 | B10: Add BOM-guard & encoding CI check | C10: P01 · Critical Fixes & Production-Safety Baseline | D10: Hardening | E10: Infrastructure | F10: CI | G10: Normal | H10: The recurring UTF-8 BOM bug breaks JSON parsing and SQL hygiene. Add a CI step (script + test) that scans all .json and .sql files for a leading BOM (bytes EF BB BF) and fails if any is found, and codify the UTF8Encoding(false) rule in any file generators (the manifest CSV currently carries a BOM). | I10: A test/script scans the repo and asserts zero .json/.sql files begin with a BOM; deliberately committing a BOM'd file fails CI. Generator helpers are documented/asserted to write BOM-less UTF-8. | J10: hardening | K10: 3 | L10: — | M10: Code hygiene, Repo hygiene
A11: T-010 | B11: Archive landed run-once tooling scripts | C11: P01 · Critical Fixes & Production-Safety Baseline | D11: Hardening | E11: Documentation | F11: Tooling | G11: Normal | H11: ~116 phaseN-named and run-once scripts (fix-*, scaffold-website-frontend.ps1 + the superseded -v2, apply-phaseX migration .cjs/.mjs, ppiq_phase2_files.txt) clutter the repo. Move scripts whose migration has already landed into /tools/archive (or delete) and write a tools/ARCHIVE.md noting what each did and when it ran. Keep only actively-referenced CI/dev scripts at the top level; remove superseded scaffold duplicates. | I11: tools/ top level contains only scripts referenced by Jenkinsfile, package.json or docs (cross-checked); tools/ARCHIVE.md lists the archived scripts. CI and 'npm run' still work (nothing referenced was archived). Repo file count drops measurably — record before/after. | J11: refactor | K11: 6 | L11: — | M11: Repo hygiene
A12: T-011 | B12: Phase-1 regression & fix-validation pass | C12: P01 · Critical Fixes & Production-Safety Baseline | D12: Testing | E12: Testing | F12: Regression | G12: Very important | H12: Add/confirm tests for every Phase-1 fix and run the full suite (dotnet test + npm run test + npm run e2e) to ensure nothing regressed; fix anything the dead-file removal or dedup broke. | I12: dotnet test, npm run test and npm run e2e are all green locally and in CI, including the new tests from this phase; zero skipped tests beyond the documented audit-immutability SkippableFacts. | J12: test | K12: 4 | L12: all P01 tasks | M12: Functionality
A13: T-012 | B13: Secret-scan the repo & purge committed secrets | C13: P01 · Critical Fixes & Production-Safety Baseline | D13: Hardening | E13: Security | F13: Secrets | G13: Critical | H13: Run a secret scanner (gitleaks or trufflehog) over the working tree and git history. Confirm no real secrets live in .env.local, appsettings.*.json or scripts; ensure every .env.local is gitignored and contains no real credentials; rotate anything exposed. Add a blocking secret-scan gate to the pipeline. | I13: A gitleaks CI job passes with zero findings; '.env.local' appears in .gitignore; a deliberately planted fake secret is caught by the gate. If any real secret was found in history, document the rotation performed. | J13: hardening | K13: 5 | L13: — | M13: Security, Repo hygiene
... A139: T-138 | B139: Full-program certification & positioning refresh + major release | C139: P21 · Compliance Certification, Support & Vendor-Viability | D139: Security | E139: Testing | F139: Certification | G139: Very important | H139: Run everything (all gate, ops, resilience, compliance and support gates), refresh the doctrine/positioning to the full-program state, and tag + deploy a major release. | I139: Every gate/ops/compliance stage is green; the positioning and doctrine reflect the full program (Features/Stability/Add-value > 95); a major release is tagged and deployed with health green and a full smoke walk (golden path + C-0044170 + value range + recommendation + certificate + grounded assistant). | J139: test | K139: 8 | L139: all prior phases | M139: All

Sheet Phase Plan
A1: Phase | B1: Theme / Track | C1: Modules | D1: Deployable Outcome (what to show) | E1: Tasks | F1: Effort (h) | G1: Dimensions Advanced
A2: P01 · Critical Fixes & Production-Safety Baseline | B2: Hardening / Security / Bug-fix | C2: DB · Infra · Backend · Frontend · Security | D2: Secure, clean, green baseline: all known bugs fixed, dev-seed locked, DB port private, dead/duplicate files gone, CI guards in place. | E2: =COUNTIF(Roadmap!C:C,"P01 · Critical Fixes & Production-Safety Baseline") -> 12 | F2: =SUMIF(Roadmap!C:C,"P01 · Critical Fixes & Production-Safety Baseline",Roadmap!K:K) -> 45 | G2: Code+Repo hygiene, Security, Functionality
A3: P02 · Realism Demo Dataset Through the HMI | B3: Demo / Data | C3: Database · Backend | D3: The product alive on realistic data (~630 heats / ~5,600 coils) with the C-0044170 thread and deliberate imperfection, rebuildable from empty entirely via the HMI. | E3: =COUNTIF(Roadmap!C:C,"P02 · Realism Demo Dataset Through the HMI") -> 7 | F3: =SUMIF(Roadmap!C:C,"P02 · Realism Demo Dataset Through the HMI",Roadmap!K:K) -> 51 | G3: Workflows, Functionality, Features
A4: P03 · Gate-Exit Certification Tests | B4: Hardening / Testing / AI+ML | C4: Testing · Backend | D4: Proof artifacts: €-range value reproduction, C-0044170 walk, cross-tenant 403, FDR signal recovery, grounding & action-matrix — all enforced in CI. | E4: =COUNTIF(Roadmap!C:C,"P03 · Gate-Exit Certification Tests") -> 9 | F4: =SUMIF(Roadmap!C:C,"P03 · Gate-Exit Certification Tests",Roadmap!K:K) -> 49 | G4: AI+ML, Functionality, Security, Workflows
A5: P04 · Mapping Health & Schema-Drift Full Loop | B5: Workflow / Backend / Frontend | C5: Backend · Frontend · Database | D5: A live Mapping Health panel showing coverage + drift findings; ingestion blocks on critical drift; analyses show population/exclusions. | E5: =COUNTIF(Roadmap!C:C,"P04 · Mapping Health & Schema-Drift Full Loop") -> 7 | F5: =SUMIF(Roadmap!C:C,"P04 · Mapping Health & Schema-Drift Full Loop",Roadmap!K:K) -> 47 | G5: Workflows, Functionality, Features
A6: P05 · Frontend Hygiene & God-File Refactor | B6: Refactor / Hardening | C6: Frontend | D6: Maintainable frontend: god-files split, legacy CSS retired, brand tokens centralized, file-size lint gate — nothing broken. | E6: =COUNTIF(Roadmap!C:C,"P05 · Frontend Hygiene & God-File Refactor") -> 6 | F6: =SUMIF(Roadmap!C:C,"P05 · Frontend Hygiene & God-File Refactor",Roadmap!K:K) -> 47 | G6: Code hygiene, UI/UX, Repo hygiene
A7: P06 · WCAG 2.1 AA + Light Theme | B7: Web / Hardening | C7: Frontend | D7: Accessible, theme-able UI: contrast-audited light theme + full keyboard/screen-reader support, with an axe CI gate. | E7: =COUNTIF(Roadmap!C:C,"P06 · WCAG 2.1 AA + Light Theme") -> 6 | F7: =SUMIF(Roadmap!C:C,"P06 · WCAG 2.1 AA + Light Theme",Roadmap!K:K) -> 52 | G7: UI/UX
A8: P07 · Internationalization + Arabic RTL | B8: Web | C8: Frontend | D8: EN + Arabic with full RTL layout and locale formatting — MENA-ready, all theme/direction combinations accessible. | E8: =COUNTIF(Roadmap!C:C,"P07 · Internationalization + Arabic RTL") -> 6 | F8: =SUMIF(Roadmap!C:C,"P07 · Internationalization + Arabic RTL",Roadmap!K:K) -> 56 | G8: UI/UX, Features
A9: P08 · Backend God-File Refactor & API Hygiene | B9: Refactor / Hardening | C9: Backend | D9: Thin endpoints, decomposed services, OpenAPI snapshot guard, analyzer gate — behavior identical, all tests green. | E9: =COUNTIF(Roadmap!C:C,"P08 · Backend God-File Refactor & API Hygiene") -> 6 | F9: =SUMIF(Roadmap!C:C,"P08 · Backend God-File Refactor & API Hygiene",Roadmap!K:K) -> 45 | G9: Code hygiene, Engine
A10: P09 · Process Historian Connector (one GA) | B10: AI+ML / Integration | C10: Backend · Frontend · Database | D10: A new GA historian connector (read-only) plus an honest OPC-UA beta — registerable and mappable in the HMI. | E10: =COUNTIF(Roadmap!C:C,"P09 · Process Historian Connector (one GA)") -> 6 | F10: =SUMIF(Roadmap!C:C,"P09 · Process Historian Connector (one GA)",Roadmap!K:K) -> 54 | G10: Features, Functionality
A11: P10 · OT-Safe Edge Collector Field Agent | B11: Hardening / Integration | C11: Backend · Infrastructure · Frontend | D11: A deployable one-way edge agent feeding the acceptance gateway, with management UX and no-egress certification. | E11: =COUNTIF(Roadmap!C:C,"P10 · OT-Safe Edge Collector Field Agent") -> 6 | F11: =SUMIF(Roadmap!C:C,"P10 · OT-Safe Edge Collector Field Agent",Roadmap!K:K) -> 55 | G11: Features, Functionality, Security
A12: P11 · Security SDLC, Auth Certification & Encryption | B12: Security | C12: Security · Infra · Backend · Testing | D12: Blocking SAST/dependency/secret scans, encryption-at-rest depth, bootstrap-admin removal, MFA + SSO/SCIM certified. | E12: =COUNTIF(Roadmap!C:C,"P11 · Security SDLC, Auth Certification & Encryption") -> 6 | F12: =SUMIF(Roadmap!C:C,"P11 · Security SDLC, Auth Certification & Encryption",Roadmap!K:K) -> 45 | G12: Security, Auth
A13: P12 · Performance Budgets & Ops/Scale | B13: Hardening / Ops | C13: Frontend · Backend · Infra · Testing | D13: Enforced perf budgets, load-tested latency at scale, time-series store, tested backup/restore + runbooks. | E13: =COUNTIF(Roadmap!C:C,"P12 · Performance Budgets & Ops/Scale") -> 6 | F13: =SUMIF(Roadmap!C:C,"P12 · Performance Budgets & Ops/Scale",Roadmap!K:K) -> 46 | G13: UI/UX, Engine, Functionality
A14: P13 · Compliance Controls & Audit Evidence | B14: Security / Documentation | C14: Security · Database · Documentation | D14: Control mapping (SOC2/ISO), tamper-evident audit export, retention/erasure, sensitive-data catalog — an auditor evidence pack. | E14: =COUNTIF(Roadmap!C:C,"P13 · Compliance Controls & Audit Evidence") -> 6 | F14: =SUMIF(Roadmap!C:C,"P13 · Compliance Controls & Audit Evidence",Roadmap!K:K) -> 50 | G14: Security, Functionality
A15: P14 · Documentation Truth, §21 Refresh & Traceability | B15: Documentation | C15: Documentation · Web · Testing | D15: Doctrine §21 rewritten to the certified build, gate→code→test traceability, methodology docs, final full-system certification + release. | E15: =COUNTIF(Roadmap!C:C,"P14 · Documentation Truth, §21 Refresh & Traceability") -> 6 | F15: =SUMIF(Roadmap!C:C,"P14 · Documentation Truth, §21 Refresh & Traceability",Roadmap!K:K) -> 46 | G15: All (narrative & certification)
A16: P15 · Prescriptive-Advisory & Value-Realization Engine | B16: AI+ML / Value | C16: Backend · Frontend · AI+ML | D16: Recommended actions w/ expected €-impact + measured before/after savings + benchmarking — evidence becomes tracked, quantified value (advisory, human-approved, no OT control). | E16: =COUNTIF(Roadmap!C:C,"P15 · Prescriptive-Advisory & Value-Realization Engine") -> 7 | F16: =SUMIF(Roadmap!C:C,"P15 · Prescriptive-Advisory & Value-Realization Engine",Roadmap!K:K) -> 58 | G16: Add value, Analysis, AI+ML, Features
A17: P16 · Quality Certification, Reporting & Sustainability (PCF/CO2) Suite | B17: Workflow / Web | C17: Backend · Frontend · Database | D17: Customer-grade quality certificates, SPC/Cpk reporting and product-carbon-footprint tracking along genealogy — green-steel & automotive ready. | E17: =COUNTIF(Roadmap!C:C,"P16 · Quality Certification, Reporting & Sustainability (PCF/CO2) Suite") -> 6 | F17: =SUMIF(Roadmap!C:C,"P16 · Quality Certification, Reporting & Sustainability (PCF/CO2) Suite",Roadmap!K:K) -> 60 | G17: Features, Add value, Sustainability
A18: P17 · Enterprise Integration, Interoperability & Advisory Write-Back | B18: Integration | C18: Backend · Database · Frontend | D18: OPC-UA GA + more historians + ERP/LIMS/MES read + human-approved advisory write-back to QA/MES + public API/webhooks. | E18: =COUNTIF(Roadmap!C:C,"P17 · Enterprise Integration, Interoperability & Advisory Write-Back") -> 6 | F18: =SUMIF(Roadmap!C:C,"P17 · Enterprise Integration, Interoperability & Advisory Write-Back",Roadmap!K:K) -> 58 | G18: Features, Integration, Add value
A19: P18 · High Availability, Horizontal Scale & Disaster Recovery | B19: Hardening / Ops | C19: Infrastructure · Backend · Deploy | D19: Multi-node HA + failover, horizontal scale, zero-downtime deploys, tested multi-region DR — single-VPS risk eliminated. | E19: =COUNTIF(Roadmap!C:C,"P18 · High Availability, Horizontal Scale & Disaster Recovery") -> 6 | F19: =SUMIF(Roadmap!C:C,"P18 · High Availability, Horizontal Scale & Disaster Recovery",Roadmap!K:K) -> 60 | G19: System Stable, Scalability, Reliability, Deployment
A20: P19 · Resilience, Observability & SLA Operations | B20: Hardening / Ops | C20: Infrastructure · Backend · Testing | D20: Chaos + 30-day soak, full tracing/metrics/logs, SLO dashboards + error budgets, 99.95% SLA operating model. | E20: =COUNTIF(Roadmap!C:C,"P19 · Resilience, Observability & SLA Operations") -> 6 | F20: =SUMIF(Roadmap!C:C,"P19 · Resilience, Observability & SLA Operations",Roadmap!K:K) -> 52 | G20: System Stable, Reliability, Observability
A21: P20 · Multi-Plant Fleet, Extensibility & Marketplace | B21: Features / Web | C21: Frontend · Backend · Database | D21: Fleet/multi-plant + cross-plant benchmarking, plugin SDK + marketplace, industry-template library for rapid time-to-value. | E21: =COUNTIF(Roadmap!C:C,"P20 · Multi-Plant Fleet, Extensibility & Marketplace") -> 6 | F21: =SUMIF(Roadmap!C:C,"P20 · Multi-Plant Fleet, Extensibility & Marketplace",Roadmap!K:K) -> 56 | G21: Features, Add value, Extensibility, Time-to-Value
A22: P21 · Compliance Certification, Support & Vendor-Viability | B22: Security / Documentation | C22: Security · Documentation · Backend | D22: External SOC 2 Type II / ISO 27001 / IEC 62443 readiness, SLA-backed support + training, source-escrow/BCP/partner program. | E22: =COUNTIF(Roadmap!C:C,"P21 · Compliance Certification, Support & Vendor-Viability") -> 6 | F22: =SUMIF(Roadmap!C:C,"P21 · Compliance Certification, Support & Vendor-Viability",Roadmap!K:K) -> 50 | G22: Compliance, Support, Vendor viability, Add value
A23: TOTAL | E23: =SUM(E2:E22) -> 138 | F23: =SUM(F2:F22) -> 1082

Sheet Dimensions → 100
A1: Dimension | B1: Current /100 | C1: Target | D1: Gap | E1: Closing Phases | F1: How it reaches 100
A2: Workflows | B2: 78 | C2: 100 | D2: =C2-B2 -> 22 | E2: P02, P03, P04 | F2: Demo built end-to-end through the HMI on the realism dataset (P02); mapping-health + coverage transparency (P04); all journeys certified by gate-exit e2e (P03).
A3: Features | B3: 80 | C3: 100 | D3: =C3-B3 -> 20 | E3: P09, P10, P16, P17, P20 | F3: Historian/edge breadth (P09/P10); + certification/SPC/PCF reporting (P16), OPC-UA GA + ERP/LIMS/MES + advisory write-back + public API (P17), fleet + marketplace + templates (P20) push Features > 95.
A4: Functionality | B4: 80 | C4: 100 | D4: =C4-B4 -> 20 | E4: P01, P04, P10, P12 | F4: NotImplemented bindings verified + bugs fixed (P01); schema-drift loop + coverage (P04); edge ingestion flow (P10); load/restore validation (P12).
A5: Security | B5: 82 | C5: 100 | D5: =C5-B5 -> 18 | E5: P01, P11, P13 | F5: DB-port + dev-seed + secret-scan closed (P01); SDLC scanning, encryption depth, bootstrap removal (P11); compliance controls + audit immutability (P13).
A6: Auth | B6: 85 | C6: 100 | D6: =C6-B6 -> 15 | E6: P11 | F6: Bootstrap-admin removal/first-run (P11); MFA-by-role + SSO/SCIM runtime certification (P11).
A7: AI + ML | B7: 88 | C7: 100 | D7: =C7-B7 -> 12 | E7: P03 | F7: Value-range, FDR signal-recovery, grounding adversarial and model-gateway data-boundary certifications (P03) on the realism dataset (P02).
A8: Engine | B8: 85 | C8: 100 | D8: =C8-B8 -> 15 | E8: P08, P03, P12 | F8: Backend god-file refactor + OpenAPI guard (P08); engine certs (P03); time-series store + latency budgets (P12).
A9: UI / UX | B9: 70 | C9: 100 | D9: =C9-B9 -> 30 | E9: P05, P06, P07, P12 | F9: Frontend refactor (P05); WCAG 2.1 AA + light theme (P06); i18n + Arabic RTL (P07); enforced performance budgets (P12).
A10: Code hygiene | B10: 74 | C10: 100 | D10: =C10-B10 -> 26 | E10: P01, P05, P08 | F10: Architecture/BOM guards (P01); frontend god-file split + lint gate (P05); backend split + analyzer gate (P08).
A11: Repo hygiene | B11: 68 | C11: 100 | D11: =C11-B11 -> 32 | E11: P01 | F11: Dead duplicate pages removed, Jenkinsfile/worker deduped, run-once tooling archived, secrets scanned (all P01).
A12: Composite (weighted) | B12: =ROUND(AVERAGE(B2:B11),0) -> 79 | C12: 100 | D12: =C12-B12 -> 21

Sheet Legend & Method
A1: How to use this roadmap
A2: Goal | B2: Take every one of the ten evaluation dimensions to 100/100 (current composite ≈ 80). Phases are ordered by priority + prerequisites; each phase is 45–56h and ends in a deployable, demo-able increment with nothing broken.
A3: Deploy cadence | B3: Deploy to the server at the end of each phase. Higher-value, higher-visibility work is front-loaded (P02 demo, P03 proof) so there is always something good to show.
A4: Grouping | B4: Related files are touched in the same phase (e.g. all frontend god-file refactors in P05 before theming in P06/P07) to avoid re-opening the same file across distant tasks.
A5: Acceptance criteria | B5: Every task is 'done' only when its realistic hard test passes — not when the build merely compiles. After each phase, add the phase's deep tests AND re-run the full existing suite (dotnet test + npm run test + npm run e2e) so modifications never silently break prior gates.
A6: Severity
A7: Critical | B7: Blocks safety, a demo, or a pilot; do first.
A8: Very important | B8: Major capability or certification; high priority.
A9: Important | B9: Real value or quality; scheduled deliberately.
A10: Normal | B10: Useful hardening/cleanup.
A11: Optional | B11: Nice-to-have / regulated-only.
A12: Track
A13: Workflow / Demo / Hardening / AI+ML / Web / Integration / Security / Documentation | B13: Grouping by the kind of work and its delivery theme; a phase has one primary track but tasks may span modules.
A14: Module
A15: Frontend, Backend, Database, Infrastructure, Web, Documentation, Testing, Deploy, Security, AI+ML | B15: The part of the system the task changes.
A16: Task Type
A17: new feature | B17: Builds new capability.
A18: test | B18: Adds/strengthens automated verification.
A19: hardening | B19: Improves security/robustness/ops.
A20: refactor | B20: Restructures code without changing behavior.
A21: bug fix | B21: Corrects a defect found during the audit.
A22: modification | B22: Adjusts existing behavior/content.
A23: Honest limit on the Current scores
A24: Evidence-based, not test-run | B24: The 'Current /100' figures come from reading ~14 key files in full + capability analysis across all 1,241 files; the test suites were not executed. Treat ≥85 as 'built and correct on inspection'. P03/P11/P12 convert that into executed-test certification.
A25: Bugs folded in from the deep code scan
A26: PKL seed N-literal corruption | B26: T-001 — demo-source SQL won't run in SQL Server; fix + sweep + exporter root-cause.
A27: Dead duplicate pages (6) | B27: T-006 — flat vs foldered page twins from an unfinished refactor.
A28: Dev-seed gating / DB port | B28: T-003 / T-004 — confirm production-safety.
A29: NotImplemented bindings | B29: T-005 — verify real services are the active bindings.
A30: Duplicate Jenkinsfile / worker / BOM | B30: T-007 / T-009 — dedupe + encoding guard.
