Workbook

Sheet Backlog
A1: PPIQ PRODUCT BACKLOG v21 - 10-Jul-2026. Rebuilt on three discoveries: (1) TWO parallel import architectures - the generic, throttled, remote C# reader (Architecture A: DeltaImportExecutionService + all six IDataSourceReader connectors + Worker schedule + /admin/workflow-foundation endpoints) is BUILT and REGISTERED while the HMI is wired to the same-database SQL world (Architecture B) - journey step 3 likely already exists; verify first (M1-01). (2) Rule 1 is violated by the installer itself: scripts/110+111 create five demo-named schemas on every customer database - deleted with all of Architecture B in M2-02. (3) Journey step 14 (the weekly SUPERVISOR job that re-tunes every engine job) exists nowhere - it is M2's flagship (M2-01) and Thursday's ONLY 'next release' line. M1 = 6 days to the 16-Jul demo: show all 15 journey steps live except step 14, which is framed deliberately. M2 = the three rules and the full journey at 100%. Fixed 10-Jul, commit them: CI truth gates hardened (StripComments + e2e stage 5 unblocked + falsification harness 3/3 red).
A2: Task ID | B2: Milestone | C2: Phase | D2: Group | E2: Task Name | F2: Severity | G2: Task Type | H2: Module | I2: SubModule | J2: Description (deep, junior-dev-actionable) | K2: Validation (hard, reproducible) | L2: Est (h) | M2: Status vs v20 | N2: v20 ID
A3: M1-01 | B3: M1 | C3: M1-P1 | D3: G1 Import pipeline | E3: LIVE PROOF: Architecture A imports from the remote emulated sources (journey step 3 may already exist) | F3: Critical | G3: verification | H3: Backend | I3: ImportPipeline | J3: TWO complete, parallel, incompatible import architectures exist (proven 10-Jul by static trace). ARCHITECTURE A (C#): ConnectionProfile -> SourceDatasetDefinition -> IDataSourceConnectorFactory.GetDataSourceReader(providerType) -> ThrottlingDataSourceReader (row cap + rate limit + approved window; SourceLoadRejectedException) -> connector.ReadRowsSinceKeyAsync -> ImportBatch + StagingRecord(rawJson), cursor via IncrementalCursorField/LastCursorValue with MaxCursor(), ScheduleNextRunAfterSuccess/Failure. ALL SIX connectors implement IDataSourceReader (OracleConnector : IDataSourceConnector, ISchemaReader, IDataSourceReader). It is registered in Application/DependencyInjection.cs, scheduled by Workers/Worker.cs (SYSTEM_DELTA_IMPORT_JOB, enabled by default, config-driven interval/caps), and mapped UNGATED at Program.cs:1034 -> POST /admin/workflow-foundation/run-due-source-imports (+ source-schedule-board, staging/summary, staging/records, schema-mapping/workbench, import-jobs/from-mapping). ARCHITECTURE B (SQL): ppiq_run_stage1_delta_import = same-database INSERT...SELECT over local src_* schemas; registration refuses anything not in the LOCAL information_schema; this is what the HMI's Run Stage-1 button calls. THE EXPERIMENT: start the six source containers; login e2eadmin; GET source-schedule-board; GET staging/summary; POST run-due-source-imports {maxDatasetsPerRun:25,maxRowsPerDataset:5000}; GET staging/summary again; psql: SELECT count(*) FROM import_batches WHERE source_system='DeltaImportExecutionService'; SELECT source_object_name,count(*) FROM staging_records GROUP BY 1. Three outcomes: (a) staging grows -> step 3 DONE, zero build; (b) schedule board empty -> datasets never defined, ~2h configuration; (c) exception -> capture verbatim, becomes a numbered task same day. Do this BEFORE any import work; it decides the whole week. | K3: One of the three outcomes is recorded with pasted output. If (a): staging_records rows exist whose source_object_name names a REMOTE table (e.g. meltshop_heats, not src_meltshop_pg.heats) and a second run imports only the increment (cursor advanced). If (b)/(c): the blocker is a new numbered Critical task filed the same day with the verbatim evidence. | L3: 2 | M3: NEW | N3: -
A4: M1-02 | B4: M1 | C4: M1-P1 | D4: G16 Demo readiness | E4: Browser render verification of every surface changed on 09-Jul (nothing has been seen) | F4: Critical | G4: verification | H4: Testing | I4: Manual verification | J4: Unchanged from v20 M1-23, MOVED TO THE FRONT per its own text ('this task BLOCKS the dress rehearsal') and the Phase Plan's own theme ('Browser verification FIRST'). Seven packs landed 09-Jul, all proven only by tsc + vitest + dotnet build; zero opened in a browser. Walk with the stack up: (1) /assistant renders a CHAT (after M1-03 lands, ask returns 200 isRefusal=true, not 500/403; citation is a button); (2) /data-integration/connector-truth = EMPTY STATE, never 'MeltShop PostgreSQL'; (3) /data-integration/connections + /importing load; (4) /admin?adminTab=jobs-monitor redirects to /data-integration/jobs; (5) /admin shows Site identity + License + pointer only; (6) LogPanel word filter + Source=System toggle; (7) /advisory/benchmarking Median and 107 on separate lines, Plant percentile promoted, no Mode card; (8) /commercial/license works and /license 404s; (9) /i18n-rtl last card reads Ready not P08. Record PASS/FAIL + screenshot per row. | K4: 9-row checklist committed under docs/, every row PASS with a dated screenshot. Any FAIL becomes a numbered bug row in this backlog before M1-P2 starts. | L4: 1.5 | M4: CARRIED (moved P3->P1) | N4: M1-23
A5: M1-03 | B5: M1 | C5: M1-P1 | D5: G2 Assistant | E5: Register the assistant service graph (AddAssistant) - pack built and validated, run it | F5: Critical | G5: bug fix | H5: Backend | I5: DI wiring | J5: v20 M1-06 verbatim in substance; the apply pack ALREADY EXISTS: Apply-AssistantServiceGraphRegistration.ps1 (outputs, 10-Jul). It inserts ONE fully-qualified call after Program.cs:719 builder.Services.AddV5AssistantGateway(...) via anchored substring insert (no rewrite; BOM + terminator preserved), and ships AssistantServiceGraphRegistrationTests reading Program.cs through PipelineSourceText.StripComments() so a comment cannot satisfy the guard. DI graph verified closed: AddInfrastructure (Program.cs:321) registers NpgsqlDataSource (DependencyInjection.cs:61); AssistantService(scoped) <- NpgsqlRetrievalIndex(NpgsqlDataSource,IEmbedder), ToolRegistry(IEnumerable<ITool>), three tools each (NpgsqlDataSource), IAssistantModel singleton factory; no captive dependency. Deviations from the v20 card, both deliberate: NO using-directive (fully-qualified call, avoids second *.Assistant namespace ambiguity in a 1236-line file); acceptance item 4 (WebApplicationFactory GetRequiredService<AssistantService> test) moves to M2 - the grep guard proves text, the factory test proves resolution, and the factory test is the real one. | K5: Run the pack (-WhatIf then apply; gates auto-revert). Restart API. POST /api/assistant/ask as e2eadmin -> 200, isRefusal=true, refusalReason non-empty, citations=[], NOT 500, NOT 403. Falsify the guard: comment out the inserted line -> Registration_is_not_satisfied_by_a_comment goes RED. | L5: 0.5 | M5: CARRIED (pack pre-built) | N5: M1-06
A6: M1-04 | B6: M1 | C6: M1-P1 | D6: G0 Runtime | E6: Evidence pack: demo-dataset recoverability + Stage-1 registry truth (30 minutes that de-risk the week) | F6: Critical | G6: verification | H6: Backend | I6: Tooling | J6: TWO unverified assumptions currently under the demo. (1) DATASET: tools/reset-app-database.ps1 DROPs ppiq_app and runs ONLY Backend/database/scripts/*.sql - it NEVER runs seed/. After reset, the five src_* schemas are recreated EMPTY and the 38,345-row Session-A plant is GONE. The only path back is loadA.sql.gz + Apply-SessionA-PlantThroughPipeline.ps1 - BOTH match .gitignore (lines 109 and 112: Apply-*.ps1), and the loader's own message ('place loadA.sql.gz in the repo root first') is the wording of an untracked file. Run: git ls-files --error-unmatch loadA.sql.gz ; git ls-files --error-unmatch Apply-SessionA-PlantThroughPipeline.ps1. Zero hits = the demo dataset exists on ONE laptop with no reproduction path -> archive both files somewhere durable TODAY and never run reset until M1-12's precondition holds. (2) REGISTRY: the two psql queries against source_table_dump_registry (last_index_column per table + its data_type). Registration REFUSES a missing watermark column (NOT NULL + existence check), so the '7 tables have no source_updated_at_utc' card cannot describe the registry state - what those rows actually hold decides whether Architecture B's watermark defects matter at all before B is deleted in M2. | K6: Both git ls-files outputs pasted; if untracked, both files copied to a durable location outside the repo and the location recorded in the session log. Both psql outputs pasted. Any surprise becomes a numbered task. | L6: 0.5 | M6: NEW | N6: -
A7: M1-05 | B7: M1 | C7: M1-P2 | D7: G10 Surface 1 - staging config | E7: Rewire Surface-1 registration to Architecture A (ConnectionProfile + SourceDatasetDefinition, not the SQL registry) | F7: Critical | G7: modification | H7: Frontend+Backend | I7: Surface1-ImportPrep | J7: SourceImportPrepPage (delivered under old v17 M1-03/M1-04) does LIVE discovery correctly - /tables and /columns hit the real remote containers via ISchemaReader. But its Register step calls ppiq_register_dump_source, which validates against the LOCAL information_schema and therefore RAISES on any discovered remote table name (meltshop_heats exists in the container, not in ppiq_app). Repoint Register: create/update a SourceDatasetDefinition bound to the selected ConnectionProfile - SourceObjectName/SourceSchemaName from discovery, IncrementalCursorField = the discovered timestamp candidate (fallback PrimaryTimestampField, else null -> full-read path), the saved column subset + row filter persisted into DatasetOptionsJson (connectors already receive it via DataSourceReadRequest), IsActive=true, NextRunAtUtc=now. The existing POST /admin/workflow-foundation/import-jobs/from-mapping and source-datasets/{id}/schedule-now endpoints are the job-binding surface (journey steps 2 and 5) - wire the page's final step to them instead of inventing new routes. Keep the SQL-registry path untouched (Architecture B dies in M2, not now). Access control: /admin prefix is already covered by the Matrix ('/admin', All(), tenant.admin) - no new Matrix line needed; if you see 403 read the response body. | K7: In the HMI: pick the Meltshop profile -> discover -> select table + columns + cursor -> Register -> a SourceDatasetDefinition row exists; POST run-due-source-imports (or the worker tick) pulls its rows into staging_records; a SECOND run imports only the increment (LastCursorValue advanced, rows +delta only); an Oracle table registers the same way with zero code branches. | L7: 6 | M7: RETARGETED | N7: M1-12
A8: M1-06 | B8: M1 | C8: M1-P2 | D8: G3 Engine honesty | E8: GENERIC PROJECTOR (keystone, retargeted): StagingRecords + saved mapping -> canonical | F8: Critical | G8: new feature | H8: Backend | I8: Stage2-Projector | J8: v20 M1-03 retargeted at the RIGHT input. Architecture A ends at StagingRecords (one jsonb rawJson per source row, batch-linked); Architecture B's IF/ELSIF ladder begins at dump_store; NOTHING bridges A to canonical. Build the projector that reads StagingRecords for a SourceDatasetDefinition + the user's saved mapping definition (SchemaViewDefinition: field -> canonical column, type casts, key normalisation via ppiq_normalize_business_key, unit/site resolution) and projects into canonical (material_units, genealogy_edges via the weighted-ledger rules from the 09-Jul architectural fact, quality_events, parameter_observations). jsonb->columns via a saved mapping is SIMPLER than projecting a relational dump table - one generic reader, jsonb_extract path per mapped field. HARD RULES: no dataset identifier anywhere in the projection path (the generic-only grep gate must stay green); idempotent per batch (re-projecting an already-projected batch writes zero rows - track projected batch ids); NOT NULL coverage explicit (plant_time_zone_id + plant_utc_offset_minutes bit the seed on 09-Jul; the projector must supply them from site config, never hardcode 'Europe/Berlin'); typed error into job_log on an unmapped mandatory field, never a silent skip. The 8 demo sources become seed MAPPINGS shipped as emulation fixtures, not code branches. SCOPE: projector core only - per-view Loading job orchestration is M2 (the monolithic 'project all pending batches' entry point is acceptable for Thursday). | K8: Fresh empty DB (day-one state) + register an arbitrary schema through Surface-1 + author a mapping -> run import -> run projector -> canonical populated with ZERO code change; generic-only grep gate green over the projection path; re-running with no new staging batches writes zero rows and says so; a deliberately unmapped mandatory field produces a typed job_log error naming the field. | L8: 16 | M8: RETARGETED (input = StagingRecords not dump_store) | N8: M1-03
A9: M1-07 | B9: M1 | C9: M1-P2 | D9: G1 Import pipeline | E9: Parameter-observations data pack (unblocks the engine, both layers) | F9: Critical | G9: data fixture | H9: Backend | I9: ImportPipeline | J9: v20 M1-02 verbatim, RECLASSIFIED from 'new feature' to 'data fixture' - the misclassification is what made the old ordering rule schedule M1-05 before its own blocker. The Session-A plant created heats/slabs/coils/quality_events but ZERO parameter_observations; ppiq_ml_run_learning_job_governed_v1 correctly returns BlockedTooFewRows ('at least 30 observations required'); ml_correlation_results_v2 stays empty; Surface-3 proves machinery but never a finding. Generate observations for the 13 parameter_definitions across the 3-month window WITH the planted causal relations preserved (CRACK_LONG <- superheat/peritectic at the seeded 9.3x), delivered THROUGH THE PIPELINE (staging -> projector) if M1-06 lands first, else via the same silent loader that produced the plant core - never hand-INSERTed into canonical. | K9: SELECT count(*) FROM parameter_observations > 30 per parameter per window; ppiq_ml_run_learning_job_governed_v1('ML_PROCESS_VS_DEFECT',30) returns Ready; ml_correlation_results_v2 receives rows; the planted CRACK_LONG driver ranks top with q-value shown; SCRATCH (control) shows no significant driver. | L9: 4 | M9: CARRIED (reclassified data fixture) | N9: M1-02
A10: M1-08 | B10: M1 | C10: M1-P2 | D10: G3 Analytics gate | E10: ReadinessGate verification on the populated set (config/coverage only, never the gate's honesty) | F10: Critical | G10: verification | H10: Backend | I10: Analytics-Engine | J10: v20 M1-05 verbatim: the gate is WORKING, not broken - it blocks with readiness_status=BlockedTooFewRows because parameter_observations is empty. After M1-07, re-read ReadinessGate.Evaluate against the populated set and adjust CONFIG/COVERAGE only. The refusal path is never weakened to make a run pass. | K10: A managed run reaches Completed with findings > 0 on imported canonical data. If it still blocks after observations exist, the blocking reason is captured verbatim and the demo script carries the explicit golden-set framing line. | L10: 2 | M10: CARRIED (reclassified verification) | N10: M1-05
A11: M1-09 | B11: M1 | C11: M1-P2 | D11: G2 Assistant | E11: Chunk producer (dataset+doc+finding) + POST /api/assistant/reindex (journey step 15 answers for real) | F11: Critical | G11: new feature | H11: Backend | I11: Retrieval | J11: v20 M1-07 + the endpoint half of v20 M1-08, merged; the automatic post-analysis refresh and stale-purge defer to M2. Build CanonicalChunkProducer emitting RetrievedChunk(SourceKind,SourceRef,Content,Score,IsSynthetic,ScopeRole): (a) DATASET chunks from registered SourceDatasetDefinitions, their columns, the saved mappings, connector registry, data-quality summaries - scope_role viewer; (b) DOC chunks from the honesty contract / grounding policy / tier descriptions - scope_role viewer; (c) FINDING chunks from ml_correlation_results_v2 (available once M1-07/M1-08 land) - scope_role engineer. Use EXACTLY the three SourceKinds HandleFor() recognises (finding / report|doc / else->Dataset). Register AssistantRetrievalIndexBuildService in AddAssistant() (it is in no container). Endpoint: POST /api/assistant/reindex in the SAME MapGroup('/api/assistant') (inherits RequireAuthorization + the Matrix line assistant.use); resolve tenant exactly as /ask; return AssistantIndexBuildResult verbatim. ALL FIVE numbered notes from the v20 cards still apply verbatim - especially: ReindexAsync opens its own connection/transaction, do NOT wrap it in an ambient EF scope (the 320 deadlock class); never call refresh from /ask; never mark chunks synthetic 'for the demo'; a chunk with no canonical row behind it is a fabricated citation. | K11: POST /api/assistant/reindex as e2eadmin -> 200, chunkCount >= 20, status completed. POST /ask 'which source tables are registered?' -> isRefusal=false, >=1 citation, every citation.id resolves to a real canonical row. Reindex twice -> replacedCount equals prior chunkCount, non-stale count unchanged (idempotent). 'What will the defect rate be next month?' -> isRefusal=true. As viewer role, no engineer-scoped chunk appears in any citation (data-leak test). | L11: 10 | M11: MERGED (v20 M1-07 + endpoint of M1-08) | N11: M1-07
A12: M1-10 | B12: M1 | C12: M1-P2 | D12: G12 UX / information architecture | E12: Jobs Monitor shows all four journey job types honestly | F12: Very important | G12: modification | H12: Frontend+Backend | I12: JobsMonitor | J12: The journey names four job types the customer must SEE scheduled and monitored: db-link import (SYSTEM_DELTA_IMPORT_JOB per-dataset, with NextRunAtUtc/LastCursorValue from SourceDatasetDefinition), data loading (the M1-06 projector runs), data analysis (analysis-job definitions -> governed runs), AI+ML (the ML tier). The Jobs Monitor already exists; extend it to surface Architecture A's schedule board (the GET /admin/workflow-foundation/source-schedule-board data) alongside the existing job types, each with last-run time, outcome, duration, rows. No fabrication: a job type with no runs shows an honest empty state. | K12: On the rehearsed path, all four job types are visible in one monitor with real last-run data; a dataset scheduled via Surface-1 appears within one worker tick; nothing shows a fabricated status. | L12: 3 | M12: NEW | N12: -
A13: M1-11 | B13: M1 | C13: M1-P1 | D13: G0 Runtime | E13: ppiq.ps1 up waits for Kestrel before printing the URL | F13: Important | G13: bug fix | H13: Backend | I13: Tooling | J13: v20 M1-11 verbatim. Poll the port until it accepts a connection or a deadline expires; fail loudly naming the console window; same for 5173. All five notes apply (foreground-run-first; build!=host-starts; EF ~4s even with nothing to apply; Test-NetConnection needs -InformationLevel Quiet; the same race will hit the rehearsal script). | K13: ppiq.ps1 up does not print the API URL until the port listens; 60s deadline exits non-zero naming the window; up + immediate /health succeeds 10/10. | L13: 0.5 | M13: CARRIED | N13: M1-11
A14: M1-12 | B14: M1 | C14: M1-P3 | D14: G4 Rehearsal & HMI proof | E14: Dress rehearsal x2 (recorded): empty DB -> DB-link -> import -> prepare -> load -> dashboard -> finding -> ML tier -> chat citation | F14: Critical | G14: test | H14: Testing | I14: E2E | J14: The full 15-step journey walked live, twice, recorded - this run IS the demo. PRECONDITION (hard): M1-04 proved the plant dataset is regenerable, OR the rehearsal runs on a disposable second database - reset-app-database.ps1 destroys 38,345 material_units and the reset script never runs seed/. Choreography: reset to day-one -> every page renders an honest empty state -> Surface-1: connect Meltshop (test-connection green) -> register two tables with cursor -> watch the db-link job pull rows into staging (Jobs Monitor + LogPanel) -> second run imports only the delta -> author a mapping -> Loading/projector run fills canonical -> bind a widget, re-import, watch the number change -> genealogy walk C-0044170 (or a plant coil) both directions with 70/30 attribution -> Surface-3: run the analysis, read the ranked contributor with population/method/q-value -> ML tier gated by license toggle -> /assistant: one dataset question answered WITH a citation that opens, one unanswerable question refused honestly. Time-box <= 25 min. MANUAL rows initialed (cold-load console, stopped-container typed error, widget delta, attribution clip, honesty bar). Capture the 4-minute silent video from the second run (absorbs v20 M1-29). | K14: Recording exists; both walks <= 25 min with zero dead ends; MANUAL rows initialed; the plant data is present after the walk (count asserted, not assumed); the video file is stored with the deck. | L14: 4 | M14: MERGED (v20 M1-27 + M1-29) | N14: M1-27
... A150: M1-14 | B150: M1 | C150: M1-P2 | D150: G16 Demo readiness | E150: VERIFY (pre-rehearsal): the three no-code surfaces drive the PROVEN engine end-to-end - the mapping UI must author a MappingDefinition the generic projector consumes, NOT the /admin/schema-mapping SQL-view path | F150: Critical | G150: verification | H150: Frontend+Backend | I150: NoCodeSurfaces | J150: 12-Jul live+static finding. Two mapping subsystems exist and the no-code UI drives the WRONG one for canonical fill. PROVEN path (M1-06 Stage A, 1802 heats landed): MappingDefinition (MappingJson field map, supports const: literals) -> MappingExecutionService.ExecuteAsync(mappingId,batchId) -> writes the six canonical entities into material_units / genealogy_edges; auto-fired post-import by ImportBatchQueueProcessorService + ImportWorkflowService when an active MappingDefinition matches batch.SourceObjectName (else batch.MarkFailed 'No active mapping definition found'). UI path (CanonicalSchemaMappingPanel, routed under Data Integration -> Schema Configuration): calls /admin/schema-mapping previewJoin/createKpiView/executeMapping(viewCode); ExecuteMappingAsync loads a row from canonical_schema_views and runs its SqlText to build a DB view/KPI - it NEVER calls MappingExecutionService and NEVER writes material_units. So a user 'preparing data' in the HMI today builds SQL join/KPI views, which does NOT populate canonical the way the projector does. M1-12 (dress rehearsal) and M2-04 (per-view Loading) both ASSUME 'author a mapping in the HMI -> projector fills canonical'; that assumption is unverified and currently looks false. THE EXPERIMENT (HMI only, no scripts, stack up, a real staging batch present e.g. a fresh meltshop_heats batch with Pending rows): (S1) open the data-prep/mapping surface -> author + Save/Execute a mapping for that source object -> psql: SELECT count(*) FROM mapping_definitions WHERE source_object_name='<obj>' AND is_active; and SELECT count(*) FROM material_units WHERE source_system='postgresql'; before/after. PASS if a MappingDefinition row is created THROUGH the UI AND canonical material_units grow for that batch (staging flips Mapped). FAIL if the UI only creates a canonical_schema_views row and no MappingDefinition / no canonical rows -> file a numbered Critical bug 'no-code data-prep UI disconnected from generic projector' and scope the wiring (data-prep Save authors a MappingDefinition the projector consumes, or a SchemaView->MappingDefinition bridge). (S2) Add Widget wizard -> bind a chart to a real canonical column -> the widget renders the live number; re-import and the number changes. (S3) New Analysis (Surface-3) -> run -> a ranked contributor with population/method/q-value (needs M1-07 observations). Record PASS/FAIL per surface with pasted evidence. RUN THIS BEFORE M1-12 so any disconnection is a filed bug with runway, not a dead end in the rehearsal. SCOPE GUARD: verify-only; the fix (if S1 fails) is a separate numbered task, and the heavy build (per-view Loading from HMI = M2-04, visual-mapper polish = M3-10) stays in M2/M3 - do not expand M1 here. | K150: Three PASS/FAIL rows committed under docs/ with pasted psql/console evidence. S1: a mapping_definitions row created THROUGH the HMI (not a script) for the test source object, AND material_units count for that batch increases with staging rows flipping to Mapped (counts asserted, not assumed). S2: a saved widget renders a live value sourced from canonical, and the value changes after a re-import. S3: an analysis run returns a ranked contributor with population/method/q-value. Any FAIL is a numbered Critical bug row filed in this backlog BEFORE M1-P3 (M1-12) starts. | L150: 3 | M150: NEW (12-Jul trace) | N150: -

Sheet Change Log v20 to v21
A1: WHAT CHANGED AND WHY. v20 was written before the 10-Jul static trace found Architecture A (the real remote import engine, built and scheduled but not wired to the HMI), before the migration-path Rule-1 violation (scripts/110+111), and before the canonical 15-step journey was written down (which surfaced the missing step-14 supervisor). v21 re-centres M1 on proving/wiring what EXISTS and re-centres M2 on the three rules + the journey at 100%. Internal ID references inside CARRIED descriptions refer to v20 IDs - resolve via the v20 ID column.
A2: v20 ID | B2: Decision | C2: Evidence / reasoning | D2: Where it went in v21
A3: M1-01 | B3: SUPERSEDED (do not cure a corpse) | C3: Its five watermark defects (strict > ties-loss; ORDER BY non-monotonic LIMIT; _all shared budget; endpoint timeout; watermark-ahead) all live in Architecture B, which M2-02 deletes whole. Registry evidence still collected first. | D3: M1-04 (evidence) + M2-02 (deletion)
A4: M1-02 | B4: RECLASSIFIED data fixture | C4: 'New feature' misclassification is what made the ordering rule schedule its dependent (M1-05) first. | D4: M1-07
A5: M1-03 | B5: RETARGETED | C5: The projector's input is StagingRecords(rawJson) from Architecture A, NOT dump_store. jsonb->columns via saved mapping is simpler than the dump-table version. Scope unchanged: projector core only. | D5: M1-06
A6: M1-04 | B6: MOVED to M2 | C6: Per-view Loading jobs consume the projector; monolithic entry point acceptable for Thursday; its own card said delete-the-monolith 'once every source flows through a view' - an M2 sentence. | D6: M2-04
A7: M1-05 | B7: RECLASSIFIED verification | C7: The gate WORKS (BlockedTooFewRows on an empty parameter_observations is honesty, not a bug). | D7: M1-08
A8: M1-06 | B8: CARRIED, pack pre-built | C8: Apply-AssistantServiceGraphRegistration.ps1 built+validated 10-Jul (anchored insert, comment-proof guard). Acceptance item 4 (WebApplicationFactory resolution test) -> M2-06. | D8: M1-03
A9: M1-07 + M1-08 | B9: MERGED / SPLIT | C9: Chunk producer + reindex endpoint together (M1-09); auto-refresh + stale purge + ChangedOnly deferred (M2-06). | D9: M1-09 + M2-06
A10: M1-09 | B10: MOVED to M2 | C10: One-surface consolidation is refactor risk in demo week. | D10: M2-05
A11: M1-23 | B11: MOVED TO FRONT | C11: Its own text: 'BLOCKS the dress rehearsal'. Phase Plan theme said 'Browser verification FIRST' while the task sat in the last phase. | D11: M1-02
A12: M1-27 + M1-29 | B12: MERGED | C12: The second rehearsal IS the video take. | D12: M1-12
A13: M1-13..M1-22, M1-25, M1-26, M1-28 | B13: MOVED to M2 | C13: i18n, Admin content, e2e realignment, action matrix, genealogy triage, DemoAnalyticsPages, phase11, gate hardening, LogPanel tests, DI polish, UX/charm, grounding eval - all real, none demo-blocking in 6 days. i18n deliberately: 14h of locale keys on copy that M2's UX passes will change = paying twice; the customer hears 'German is in the next release'. | D13: M2-09..M2-21
... A17: - | B17: FIXED 10-Jul, commit them | C17: CiPipelineTruthGateTests + DeployRedPathProofTests read raw text; the Jenkinsfile header comment satisfied every assertion; 'rollback' was satisfied by the failure-echo 'no rollback was needed'. Hardened with PipelineSourceText.StripComments; e2e stage 5 when{} removed (now BLOCKING); falsification harness proved all three mutations red. CONSEQUENCE: land e2e realignment (M2-11 carried row) before the next git push. | D17: committed work + note on carried e2e row

Sheet Phase Plan & Stats
A1: PHASE PLAN v21 - formula-driven from the Backlog sheet. M1 phases are DAYS-not-45-65h (deliberate exception: 6-day demo sprint, ~53h total, ~8.8h/day). M2 phases follow the 45-65h rule.
A2: Phase | B2: Milestone | C2: Tasks | D2: Hours | E2: Critical | F2: Deliverable theme
A3: M1-P1 | B3: M1 | C3: =COUNTIFS(Backlog!$C$3:$C$150,$A3) -> 5 | D3: =SUMIFS(Backlog!$L$3:$L$150,Backlog!$C$3:$C$150,$A3) -> 5 | E3: =COUNTIFS(Backlog!$C$3:$C$150,$A3,Backlog!$F$3:$F$150,"Critical") -> 4 | F3: Verify + unblock
A4: M1-P2 | B4: M1 | C4: =COUNTIFS(Backlog!$C$3:$C$150,$A4) -> 7 | D4: =SUMIFS(Backlog!$L$3:$L$150,Backlog!$C$3:$C$150,$A4) -> 44 | E4: =COUNTIFS(Backlog!$C$3:$C$150,$A4,Backlog!$F$3:$F$150,"Critical") -> 6 | F4: Build: Surface-1 rewire, GENERIC PROJECTOR, observations, chunk producer
A5: M1-P3 | B5: M1 | C5: =COUNTIFS(Backlog!$C$3:$C$150,$A5) -> 2 | D5: =SUMIFS(Backlog!$L$3:$L$150,Backlog!$C$3:$C$150,$A5) -> 7 | E5: =COUNTIFS(Backlog!$C$3:$C$150,$A5,Backlog!$F$3:$F$150,"Critical") -> 1 | F5: Prove: rehearsal x2 + script
A6: M2-P0 KEYSTONE | B6: M2 | C6: =COUNTIFS(Backlog!$C$3:$C$150,$A6) -> 4 | D6: =SUMIFS(Backlog!$L$3:$L$150,Backlog!$C$3:$C$150,$A6) -> 51 | E6: =COUNTIFS(Backlog!$C$3:$C$150,$A6,Backlog!$F$3:$F$150,"Critical") -> 4 | F6: Rules+journey 100%: SUPERVISOR, delete Architecture B, purge seeds, per-view Loading
A7: M2-P1 | B7: M2 | C7: =COUNTIFS(Backlog!$C$3:$C$150,$A7) -> 11 | D7: =SUMIFS(Backlog!$L$3:$L$150,Backlog!$C$3:$C$150,$A7) -> 55.5 | E7: =COUNTIFS(Backlog!$C$3:$C$150,$A7,Backlog!$F$3:$F$150,"Critical") -> 7
A8: M2-P8 CARRYOVER (frontend/UX/i18n/proof) | B8: M2 | C8: =COUNTIFS(Backlog!$C$3:$C$150,$A8) -> 13 | D8: =SUMIFS(Backlog!$L$3:$L$150,Backlog!$C$3:$C$150,$A8) -> 54.5 | E8: =COUNTIFS(Backlog!$C$3:$C$150,$A8,Backlog!$F$3:$F$150,"Critical") -> 5 | F8: i18n EN/DE, Admin content, e2e realignment, action matrix, genealogy triage, gates, UX/charm
A9: M2-P4 | B9: M2 | C9: =COUNTIFS(Backlog!$C$3:$C$150,$A9) -> 14 | D9: =SUMIFS(Backlog!$L$3:$L$150,Backlog!$C$3:$C$150,$A9) -> 57.1 | E9: =COUNTIFS(Backlog!$C$3:$C$150,$A9,Backlog!$F$3:$F$150,"Critical") -> 9
A10: M2-P5 | B10: M2 | C10: =COUNTIFS(Backlog!$C$3:$C$150,$A10) -> 9 | D10: =SUMIFS(Backlog!$L$3:$L$150,Backlog!$C$3:$C$150,$A10) -> 53.1 | E10: =COUNTIFS(Backlog!$C$3:$C$150,$A10,Backlog!$F$3:$F$150,"Critical") -> 2
A11: M2-P7 | B11: M2 | C11: =COUNTIFS(Backlog!$C$3:$C$150,$A11) -> 8 | D11: =SUMIFS(Backlog!$L$3:$L$150,Backlog!$C$3:$C$150,$A11) -> 18.3 | E11: =COUNTIFS(Backlog!$C$3:$C$150,$A11,Backlog!$F$3:$F$150,"Critical") -> 1
A12: M2-P3 | B12: M2 | C12: =COUNTIFS(Backlog!$C$3:$C$150,$A12) -> 8 | D12: =SUMIFS(Backlog!$L$3:$L$150,Backlog!$C$3:$C$150,$A12) -> 51.9 | E12: =COUNTIFS(Backlog!$C$3:$C$150,$A12,Backlog!$F$3:$F$150,"Critical") -> 2
A13: M2-P6 | B13: M2 | C13: =COUNTIFS(Backlog!$C$3:$C$150,$A13) -> 10 | D13: =SUMIFS(Backlog!$L$3:$L$150,Backlog!$C$3:$C$150,$A13) -> 54.6 | E13: =COUNTIFS(Backlog!$C$3:$C$150,$A13,Backlog!$F$3:$F$150,"Critical") -> 0
A14: M2-P2 | B14: M2 | C14: =COUNTIFS(Backlog!$C$3:$C$150,$A14) -> 5 | D14: =SUMIFS(Backlog!$L$3:$L$150,Backlog!$C$3:$C$150,$A14) -> 45.5 | E14: =COUNTIFS(Backlog!$C$3:$C$150,$A14,Backlog!$F$3:$F$150,"Critical") -> 2
A15: M3-P1 | B15: M3 | C15: =COUNTIFS(Backlog!$C$3:$C$150,$A15) -> 4 | D15: =SUMIFS(Backlog!$L$3:$L$150,Backlog!$C$3:$C$150,$A15) -> 54 | E15: =COUNTIFS(Backlog!$C$3:$C$150,$A15,Backlog!$F$3:$F$150,"Critical") -> 1
A16: M3-P2 | B16: M3 | C16: =COUNTIFS(Backlog!$C$3:$C$150,$A16) -> 6 | D16: =SUMIFS(Backlog!$L$3:$L$150,Backlog!$C$3:$C$150,$A16) -> 53.9 | E16: =COUNTIFS(Backlog!$C$3:$C$150,$A16,Backlog!$F$3:$F$150,"Critical") -> 2
A17: M3-P3 | B17: M3 | C17: =COUNTIFS(Backlog!$C$3:$C$150,$A17) -> 5 | D17: =SUMIFS(Backlog!$L$3:$L$150,Backlog!$C$3:$C$150,$A17) -> 50.2 | E17: =COUNTIFS(Backlog!$C$3:$C$150,$A17,Backlog!$F$3:$F$150,"Critical") -> 0
A18: M3-P4 | B18: M3 | C18: =COUNTIFS(Backlog!$C$3:$C$150,$A18) -> 7 | D18: =SUMIFS(Backlog!$L$3:$L$150,Backlog!$C$3:$C$150,$A18) -> 49 | E18: =COUNTIFS(Backlog!$C$3:$C$150,$A18,Backlog!$F$3:$F$150,"Critical") -> 0
A19: M3-P5 | B19: M3 | C19: =COUNTIFS(Backlog!$C$3:$C$150,$A19) -> 5 | D19: =SUMIFS(Backlog!$L$3:$L$150,Backlog!$C$3:$C$150,$A19) -> 27 | E19: =COUNTIFS(Backlog!$C$3:$C$150,$A19,Backlog!$F$3:$F$150,"Critical") -> 0
A20: M4-P1 | B20: M4 | C20: =COUNTIFS(Backlog!$C$3:$C$150,$A20) -> 4 | D20: =SUMIFS(Backlog!$L$3:$L$150,Backlog!$C$3:$C$150,$A20) -> 52 | E20: =COUNTIFS(Backlog!$C$3:$C$150,$A20,Backlog!$F$3:$F$150,"Critical") -> 4
... A24: M4-P5 | B24: M4 | C24: =COUNTIFS(Backlog!$C$3:$C$150,$A24) -> 3 | D24: =SUMIFS(Backlog!$L$3:$L$150,Backlog!$C$3:$C$150,$A24) -> 20 | E24: =COUNTIFS(Backlog!$C$3:$C$150,$A24,Backlog!$F$3:$F$150,"Critical") -> 0
A26: Milestone totals
A27: Milestone | B27: Tasks | C27: Hours | D27: Critical
A28: M1 | B28: =COUNTIFS(Backlog!$B$3:$B$150,$A28) -> 14 | C28: =SUMIFS(Backlog!$L$3:$L$150,Backlog!$B$3:$B$150,$A28) -> 56 | D28: =COUNTIFS(Backlog!$B$3:$B$150,$A28,Backlog!$F$3:$F$150,"Critical") -> 11
A29: M2 | B29: =COUNTIFS(Backlog!$B$3:$B$150,$A29) -> 82 | C29: =SUMIFS(Backlog!$L$3:$L$150,Backlog!$B$3:$B$150,$A29) -> 441.5 | D29: =COUNTIFS(Backlog!$B$3:$B$150,$A29,Backlog!$F$3:$F$150,"Critical") -> 32
A30: M3 | B30: =COUNTIFS(Backlog!$B$3:$B$150,$A30) -> 27 | C30: =SUMIFS(Backlog!$L$3:$L$150,Backlog!$B$3:$B$150,$A30) -> 234.1 | D30: =COUNTIFS(Backlog!$B$3:$B$150,$A30,Backlog!$F$3:$F$150,"Critical") -> 3
A31: M4 | B31: =COUNTIFS(Backlog!$B$3:$B$150,$A31) -> 25 | C31: =SUMIFS(Backlog!$L$3:$L$150,Backlog!$B$3:$B$150,$A31) -> 218.1 | D31: =COUNTIFS(Backlog!$B$3:$B$150,$A31,Backlog!$F$3:$F$150,"Critical") -> 4
