Workbook

Sheet Active Board
A1: PPIQ PRODUCT BACKLOG v25 - 21-Jul-2026. M1 reframed to the 7 presentation targets (Parts A+B >=75% FRONTEND-demonstrable, engine >=75%, chatbot >=75%, journey on faked data, 3 premade pages + 1 built live). Frozen-ID law upheld; canvas/associative/catalogue = M2 (M2-31/37/38). New M1 target-tracker rows M1-34..M1-40.
A2: ID | B2: Milestone | C2: Phase | D2: Group | E2: Task Name | F2: Severity | G2: Type | H2: Module | I2: Status | J2: Est (h) | K2: Origin | L2: Description (junior-complete) | M2: Validation / Acceptance
A3: M1-18 | B3: M1 | C3: M1-P1 Golden Chain | D3: G0 Runtime | E3: Finish the trunk: second merge of the 10 stranded 17-Jul commits, branch deletion, fresh bundle off-machine | F3: Critical | G3: governance | H3: Repo | I3: PARTIAL | J3: 0.25 | K3: v23 + 18-Jul session | L3: STATUS: 90% done. Evidence so far: merge ab9771f9 on main; matrix fix rescued into commit 4f57b7e5 (PlantAccessControl.cs line 212 maps /api/ml/foundation - without this commit the engine 403s); root tools committed 0e2da1b7/913a8ba7; .gitignore evidence rules added. 18-Jul discovery: TEN commits sit on branch 'presentation' and NOT on main (578015f4 provider fix, 84dd6abd rebuild script, 36a317f2 test deletion, workspace page, website v2, Backlog v23 docs) - main's history is a day behind although the shared working tree hides it. The second merge conflicts on exactly ONE file (.gitignore, both sides appended different ignore blocks; correct resolution = line union). REMAINING: download Finish-PresentationMerge.ps1 from the 18-Jul chat outputs to repo root and run: powershell -NoProfile -ExecutionPolicy Bypass -File .\Finish-PresentationMerge.ps1 (it re-merges, resolves .gitignore by union from index stages :2/:3, refuses to auto-resolve any other file, commits, builds, deletes the branch with --delete, cuts a fresh --all bundle, copies to OneDrive\PPIQ-Archive with SHA256 verify). | M3: git log --oneline main..presentation prints ZERO lines; branch 'presentation' gone (git branch shows only main); dotnet build Backend\PlantProcessIQ.sln green after merge; a PPIQ_main_*.bundle newer than the merge exists in OneDrive\PPIQ-Archive and 'git bundle verify' passed on it; the M1-18_FinishMerge_*.txt log is kept as evidence.
A4: M1-19 | B4: M1 | C4: M1-P1 Golden Chain | D4: G1 Import | E4: Oracle discovery in the HMI: PPIQ_SRC schema on CP-04/CP-06 + dated screenshot | F4: Critical | G4: defect fix | H4: Connectors | I4: PARTIAL | J4: 0.25 | K4: v23 | L4: STATUS: earned x2 via API on 17-Jul (HSM_COILS..., CC_HEATS... discovered through /api). The v23 acceptance explicitly requires the UI walk, so the task is NOT closed by the API proof. REMAINING (5 minutes, in the browser): open Connections; edit profile CP-04 (caster Oracle) -> field 'Schema Name' -> type PPIQ_SRC -> Save -> Test connection (expect green) -> Discover (expect table list CC_HEATS, CC_SEQUENCES, CC_SLABS, V_PARAMETER_DEFINITIONS). Repeat on CP-06 (HSM Oracle; expect HSM_COILS, HSM_PASSES, V_PARAMETER_DEFINITIONS). Take ONE screenshot per profile showing the discovery list with today's date visible (taskbar clock suffices). If a red banner appears, STOP and file it - do not improvise credentials. | M4: Two dated screenshots committed under docs/evidence/ (or kept in the demo evidence folder) showing PPIQ_SRC table discovery for CP-04 and CP-06 in the HMI; zero red banners during the walk; the phrase 'live Oracle connector' is now permitted in customer-facing language.
A5: M1-21 | B5: M1 | C5: M1-P1 Golden Chain | D5: G3 Engine | E5: Governed engine run COMPLETES: wall-7 named and fixed, first fresh findings in results_v2 | F5: Critical | G5: defect fix | H5: Engine | I5: PARTIAL | J5: 2 | K5: v23 rewritten 20-Jul (six walls fixed this session) | L5: STATUS: six successive blockers were found and FIXED on 20-Jul, each with evidence: (1) harness grain default 'material' (a grain that exists nowhere; use -Grain coil); (2) heat_id absent at coil grain -> migration 740 added genealogy lineage view ppiq_ml_unit_heat_lineage + heat_id resolution (proof: 2,441 distinct heats at coil, log FeatureStoreFix_103157); (3) defect.class/defect.severity outcome VALUES never emitted -> 740 emits them (51,691 rows); (4) window anchored to now() excluded the historical fleet -> pass -WindowDays 3650; (5) THE API WAS CONNECTED TO ppiq_app NOT ppiq_presentation (fingerprint: refresh returned exactly 40 features/1 outcome = the post-purge ppiq_app state) -> restart via scripts\run\start-api.ps1 -Profile presentation; (6) features and outcomes never met at the same grain (loader joins on effective_sample_key WHERE grain=@g on BOTH sides; superheat lived at heat grain, CRACK at coil) -> migration 741 projects heat-grain parameter features onto descendant coils via the lineage (proof: coil-grain features 5 -> 97,183, superheat-at-coil 12,147, and the API refresh now returns 111,611 = the projection survives refresh, log Apply741_161504 + GoldenAnalysis_163106 section [3]). REMAINING - wall 7: with a COMPLETE store the 16:31 run still returned 8x Blocked. The gate's reasons are computed but discarded (DTO gap, see M2-25), so name the blocker from outside: (a) run the message query: psql -c "SELECT target_outcome_key,status,left(message,200) FROM ml_correlation_compute_runs WHERE completed_at_utc > now()-interval '2 hours' ORDER BY completed_at_utc DESC LIMIT 8;" - the message may embed the dimension; (b) run the PATCHED Diagnose-ReadinessBlock.ps1 (re-download - the disk copy crashes at [3]) with -OutcomeKey defect.rate_per_m2 -WindowDays 3650, which reconstructs all five dimensions in SQL. Then apply the named surgical fix. Most likely completer: defect.rate_per_m2 (continuous -> minority auto-passes). defect.class may honestly block on minority-class (20 categories); if so the cure is M2-27 per-code binary outcomes, NOT a threshold change - the gate is NEVER weakened. | M5: ml_correlation_compute_runs contains at least one run with status Completed/Ok created today; results_v2 row count rises above 320 with a NEW distinct compute_run_id; at least one finding pairs a param.* feature with a defect.* outcome with a non-trivial effect size and a q_value; the wall-7 root cause is written in one paragraph in the run log; NO readiness threshold in ReadinessGate.cs was modified (git diff proves it).
A6: M1-27 | B6: M1 | C6: M1-P2 Verify & Rehearse | D6: G12 UX | E6: Dashboard widgets verified rendering after the 20-template self-repair | F6: Critical | G6: defect fix | H6: Frontend | I6: NEW | J6: 1 | K6: 20-Jul session (widget toast + repair endpoint discovery) | L6: CONTEXT: /dashboard rendered eight empty widget stubs with toast 'Dashboard widget query is invalid' (POST /analytics/dashboard/widgets/query 400). The validator can only complain about: unsupported widget/chart type, unsupported/missing measure code, unsupported/missing dimension code, measure-requires-parameter, chart-vs-measure incompatibility, bad time range (DashboardWidgetValidationService.cs). At 15:57 the product's OWN repair was invoked and reported ensure created=20, repair repaired=20 system dashboards (log WidgetQueries_155747). WHAT TO DO: (1) hard-reload localhost:5173/dashboard - if all eight widgets render data and clicking a chart slice filters the workspace, mark PASS and screenshot; ALSO open 3-4 other codes via /workspace/<CODE> (list codes: psql -c "SELECT dashboard_code FROM dashboard_definitions WHERE is_deleted=false ORDER BY 1;"). (2) If ANY widget still shows the toast: run the PATCHED Diagnose-WidgetQueries.ps1 (list-extraction fixed 20-Jul evening) which replays every widget query and prints the server's validation errors verbatim per widget; send the log - the fix will be one registry/definition alignment. (3) Root-cause note for the file: templates drifted from the safety registry with no gate; the guard test is M2-33. | M6: Browser screenshot of PRODUCTION_OVERVIEW with all eight widgets showing real data; one screenshot proving click-to-filter (select a slice, another widget visibly changes); zero 'query is invalid' toasts across the demo-path workspaces; if the replay script was needed, its log shows 8 OK.
A7: M1-28 | B7: M1 | C7: M1-P1 Golden Chain | D7: G1 Import | E7: The in-room live-registration moment + prepared-instance disclosure line | F7: Critical | G7: execution | H7: Pipeline | I7: NEW | J7: 1 | K7: 20-Jul ruling: demo runs on the prepared instance (disclosed), imports become one live act | L7: RULING (20-Jul): the demo uses the prepared ppiq_presentation instance, DISCLOSED, per Rule 3. The full Runsheet A-E is deferred to M1-33 (post-demo, for the citable chain). What remains for the room is ONE live act that proves the front door: register a single small dataset live and watch rows arrive. SCRIPT: after showing Connections, say the disclosure sentence VERBATIM: 'I prepared and trained this instance on our emulated multi-source plant so we spend our time on the product - on your install this starts empty and fills through the DB-link, which I will show you right now.' Then: Prepare Import -> pick meltshop v_parameter_definitions (26 rows, fast, visible) -> map to ParameterDefinition (mapping already authored or author live if rehearsed) -> execute -> open the batch -> show staging rows -> show the canonical table gaining rows WITH source_system = the connector and the batch id. Rehearse this exact path twice tonight; it must take under 5 minutes and produce zero red banners. | M7: Rehearsal log: the act performed twice end-to-end under 5 minutes each; a written fallback line for source-down ('the connector reports the source unreachable - this is the same honesty you get in production'); the disclosure sentence is printed in the deck speaker notes on the architecture slide.
A8: M1-29 | B8: M1 | C8: M1-P2 Verify & Rehearse | D8: G12 UX | E8: Workspace switcher: the 12 dashboards reachable from the nav, not by typed URL | F8: Critical | G8: enhancement | H8: Frontend | I8: NEW | J8: 1.5 | K8: 20-Jul finding: workspaces exist but only /workspace/:code routes reach them | L8: CONTEXT: App.tsx:475 routes /workspace/:dashboardCode to RoutedInteractiveWorkspacePage and /dashboard hardcodes PRODUCTION_OVERVIEW - but NO nav entry lists the codes, so the 12 workspaces are invisible unless the URL is typed (this is why they were believed 'vanished'). TASK: add a 'Workspaces' section to the left nav (AppLayout.tsx / the nav component beside Command Dashboard): on mount, GET /analytics/dashboard/definitions (note: NO /api prefix - the group mounts at /analytics/dashboard), read the array (response may wrap it in a property - handle items/definitions/dashboards), render one NavLink per definition to /workspace/{dashboardCode} with the definition name, sorted by name, system templates first. Keep styling identical to existing nav entries (dark-industrial tokens, no new colors). Do NOT build a new page - this is nav only. If time is short before the demo, the fallback is a static list of the codes returned by the psql query in M1-27, hardcoded for the demo and replaced by the fetch in M2. | M8: All dashboard definitions appear as clickable nav entries; clicking each renders its workspace with widgets (spot-check 4 of them); browser refresh on a /workspace/<CODE> URL still renders (route param path works); vitest suite still green; screenshot of the expanded nav committed as evidence.
A9: M1-31 | B9: M1 | C9: M1-P1 Golden Chain | D9: G0 Runtime | E9: Commit migrations 740+741 into the repo + fold into Rebuild-PresentationDb | F9: Critical | G9: governance | H9: Repo | I9: NEW | J9: 1 | K9: 20-Jul session - the engine fixes exist ONLY as loose files at repo root right now | L9: DANGER: 740_feature_store_heat_lineage... and 741_feature_store_coil_grain_projection.sql live at C:\Workspace\PlantProcess-IQ\ root, UNCOMMITTED, applied by hand to ppiq_presentation. If anyone runs Rebuild-PresentationDb.ps1 (M2-18) tomorrow morning, the rebuilt DB will NOT contain the lineage view, the projection, or the defect outcomes - the engine goes blind again silently. DO: move 741 (which supersedes and contains 740) into Backend\database\scripts\741_feature_store_coil_grain_projection.sql; keep 740 beside it or archive it with a header note '741 supersedes'; add the script to whatever list Rebuild-PresentationDb executes (open scripts\demo\Rebuild-PresentationDb.ps1, find the migration loop, confirm it globs the scripts folder or add the file explicitly); commit with message 'engine: heat lineage + coil-grain projection + defect outcomes (migrations 740/741)'; re-cut the bundle (M1-18 step already does this if run after). | M9: git ls-files shows the migration(s) under Backend/database/scripts/; Rebuild-PresentationDb.ps1 demonstrably includes them (paste the relevant lines); after the next rebuild, psql 'SELECT count(*) FROM ppiq_ml_unit_heat_lineage' returns > 0 and coil-grain features survive; committed SHA recorded here.
A10: M1-32 | B10: M1 | C10: M1-P2 Verify & Rehearse | D10: G4 Quality | E10: Golden script hygiene: GROUP BY bug + the lying [PARTIAL] template | F10: Nice to have | G10: cleanup | H10: Tooling | I10: NEW | J10: 0.5 | K10: 20-Jul: the closing text claimed signal recovery on a run with zero results | L10: Two defects in Run-GoldenAnalysis.ps1: (1) the [BEFORE] method-distribution query errors 'aggregate functions are not allowed in GROUP BY' (GROUP BY 1 references the concatenated aggregate expression; fix: GROUP BY effect_size_type, method and build the string in SELECT only); (2) the closing 'WHAT YOU HAVE EARNED [PARTIAL]... engine recovered a planted validation signal' prints even when results_v2 gained ZERO rows - gate that block on (resAfter - resBefore) > 0, else print the honest 'no findings this run' line. The evidence file must never claim more than the run earned. | M10: Script runs with zero SQL errors; a run with no new results prints no recovery claim (test by re-running while blocked); diff committed.
A11: M1-01 | B11: M1 | C11: M1-P1 Golden Chain | D11: G2 Assistant | E11: Assistant grounded: reindex + one cited answer + one honest refusal | F11: Critical | G11: validation | H11: Assistant | I11: OPEN | J11: 1.5 | K11: v23 (build done; proof remains) | L11: Infrastructure exists (canon.assistant_chunk, reindex endpoint). Today kb_items=0 and the corpus is unindexed. DO: POST /api/assistant/reindex with the bearer token (login e2eadmin as in the scripts; the working login path on this build is /auth/login) -> expect 200 with chunkCount >= 20. Then in the UI ask: 'which source tables are registered?' -> expect isRefusal=false with at least one citation that resolves when clicked. Then ask a predictive question ('which coils will fail tomorrow?') -> expect an explicit refusal - THE REFUSAL IS A FEATURE, show it deliberately in the room. If a completed engine run exists by then (M1-21), also ask about the newest finding and check the answer cites the run. | M11: POST /api/assistant/reindex returns 200 with chunkCount >= 20 (paste the response); screenshot of a cited answer whose citation opens; screenshot of the refusal on the predictive question; both moments written into the demo script.
A12: M1-11 | B12: M1 | C12: M1-P2 Verify & Rehearse | D12: G16 Demo | E12: Browser certification NARROWED: the demo path graded with screenshots | F12: Critical | G12: validation | H12: All | I12: OPEN | J12: 2 | K12: v23 (narrowed per 17-Jul cut: demo path only, full 12-workspace pass moves post-demo) | L12: SCOPE (narrowed): only what the room will see. Walk in the browser, as a naive user, grading each surface [P] pass / [B] built-but-issue / [X] broken: (1) login; (2) Connections incl. the two Oracle profiles post M1-19; (3) Prepare Import + the M1-28 live-registration path; (4) Importing/Jobs Monitor; (5) genealogy search: pick one coil, walk coil->slab->heat, click into provenance; (6) Command Dashboard + PRODUCTION_OVERVIEW + 2 more workspaces: drag a widget, resize it, click a slice, watch cross-filter, save layout, reload, layout persists; (7) findings page (step 10); (8) Supervisor page (step 14); (9) assistant (step 15). EVERY [X] on this list either gets fixed tonight or its surface is REMOVED from the demo path - no red banners in the room, ever. Screenshots per step, one line per grade. | M12: A graded checklist (P/B/X per surface) with a dated screenshot per step, saved under docs/evidence/ or the demo folder; zero [X] remaining on the path (fixed or removed); each [B] has its one spoken sentence written down; the rehearsal (M1-14) uses exactly this certified path.
A13: M1-14 | B13: M1 | C13: M1-P2 Verify & Rehearse | D13: G16 Demo | E13: Dress rehearsal x2: timed full walk on the certified path with contingency sheet | F13: Critical | G13: execution | H13: All | I13: OPEN | J13: 3 | K13: v23 | L13: The exact meeting script, twice, end-to-end, timed, on ppiq_presentation: opening frame -> disclosure sentence -> connections -> LIVE registration act (M1-28) -> genealogy walk -> workspaces (drag/resize/cross-filter live) -> findings + honest-gate sentence -> supervisor sentence -> assistant cited answer + deliberate refusal -> close. Contingency sheet: one line per step for source-down / API-down / widget-dead ('this is the same honesty you get in production' family). Run 1 tonight after M1-11 certification; run 2 tomorrow morning. NO code changes after run 2 - the constitution's no-code-after-noon rule applies in spirit. | M13: Two timed runs logged (target under 40 minutes each); contingency sheet exists with a line per step; zero red banners in run 2; the deck order matches the walk order exactly.
A14: M1-15 | B14: M1 | C14: M1-P2 Verify & Rehearse | D14: G6 Docs | E14: Deck + website to the PROVEN story: evidence-linked claims + 3 vision mockups + disclosure slide | F14: Critical | G14: content | H14: Website | I14: OPEN | J14: 3 | K14: v23 expanded 20-Jul (prepared-data disclosure + canvas vision as labeled design) | L14: Every commercial claim names its evidence (batch id, run id, screenshot, cert log) or is future-tense. CHANGES: (1) the money slide uses whatever M1-21 actually produced - a completed finding with its run id, OR the honesty framing ('the gate refuses to fabricate; that refusal is the moat') - never the 9.3x number without a run id behind it; (2) add the prepared-instance disclosure line to the architecture slide speaker notes (verbatim from M1-28); (3) add THREE vision slides badged 'Pilot Milestone - Design': ETL block canvas, AI/ML toolbox composer, statistics function palette (dark-industrial mockups - being produced; place as full-bleed images with the badge visible); (4) workspace screenshots come from the M1-11 certified pass only; (5) honesty-lint stays green. | M14: Deck walk matches rehearsal exactly; each claim has a named evidence artifact in the notes; the three vision slides carry the Design badge visibly; honesty-lint green; no slide contains the 9.3x number unless a completed run id is printed beside it.
... A69: M2-39 | B69: M2 | C69: M2-P2 Product | D69: G3 Engine | E69: Transformation-definition field alignment to spec SS2/SS11 | F69: Nice to have | G69: enhancement | H69: Backend | I69: NEW | J69: 8 | K69: 21-Jul matrix | L69: The versioned artifact exists (540) but the spec's SS2/SS11 want: definition_hash (reproducibility), output_schema (inferred cols/types/nullability), source_bindings by stable internal id (rename-safe), per-output-column lineage. Add these to ppiq_visual_mapper_versions + the save path. | M69: Saved definition carries hash, output_schema, id-based bindings, per-column lineage; a source rename does not break a saved definition; SS2/SS11 checklist green.

Sheet Closed & Archived
A1: CLOSED & ARCHIVED - immutable; superseded scope always names its destination. Nothing here is deleted from history.
A2: ID | B2: Disposition | C2: Task | D2: Evidence / destination
A3: M1-25 | B3: DONE | C3: Gate hygiene: stale JourneyRail.test.tsx deleted | D3: 17-Jul: commit 36a317f2 (on presentation; lands on main via M1-18 finish); suite 253/253 green.
A4: M2-18 | B4: DONE | C4: One-command demo environment: Rebuild-PresentationDb.ps1 | D4: 17-Jul: committed (84dd6abd on presentation), proven 3x. WARNING: does not yet include migrations 735/740/741 - see M1-31/M2-25.
A5: M1-12 | B5: DONE | C5: Continuity: FLEET_RELATIONS + fixtures + fleet archived off-machine | D5: 18-Jul: FLEET_RELATIONS committed 2b8a9a44; fixtures zip + fleet3months zip + verified bundle hash-copied to OneDrive\PPIQ-Archive (logs M1-12_Complete_v4_140352).
A6: M1-24 | B6: SUPERSEDED | C6: Parallel-session code review | D6: Cut 17-Jul (post-demo); absorbed into M2-34 A11/A12 audits.
A7: M1-26 | B7: SUPERSEDED | C7: Certifier v0.2 self-defects | D7: Cut 17-Jul; folded into M2-21 certification completion.
A8: M1-20 | B8: SUPERSEDED | C8: Runsheet A-E as a DEMO prerequisite | D8: 20-Jul prepared-data ruling: demo runs on the disclosed prepared instance; the in-room act is M1-28; the full citable chain is M1-33 (post-demo). Original scope preserved verbatim inside M1-33.
A9: M1-03 | B9: SUPERSEDED | C9: Taxonomy-first proof as a demo prerequisite | D9: Merged into M1-33 Phase A acceptance (counts 26/4/7/20 + connector-only provenance).
A10: (unplanned) | B10: DONE | C10: Access-matrix engine fix committed | D10: 4f57b7e5 (18-Jul): /api/ml/foundation mapping rescued from the working tree into history.
A11: (unplanned) | B11: DONE | C11: Doctrine v8.1 produced | D11: 20-Jul: eight-directive merge executed against the real v8 text; adoption tracked in M2-30.
A12: (unplanned) | B12: DONE | C12: System dashboard templates ensure+repair 20/20 | D12: 20-Jul 15:57 via /analytics/dashboard/definitions/system-templates; browser verification = M1-27.

Sheet Lineage v22-v23
A1: REMOVED FROM v22 - traceability (nothing silently deleted)
A2: v22 ID | B2: Disposition | C2: Task | D2: Evidence / destination
A3: M1-04 | B3: DONE | C3: Step-4 mapping UI authors MappingDefinition through the HMI | D3: Proven in walk + certification tests (failedRows contract fixed 16-Jul). Evidence: walk doc [V] rows; suite green.
A4: M1-10 | B4: DONE | C4: Production error shape (no stack traces to clients) | D4: Walk P6/P10 verify the {title,errorCode,traceId} shape live [V].
A5: M1-13 | B5: DONE | C5: ppiq.ps1 API readiness poll | D5: Walk P2 cites the M1-13 line as live [V].
A6: M1-17 | B6: DONE | C6: Journey progress rail (step X of 15) | D6: Rail live in 16-Jul screenshots; certification test green; stale old test removal = new M1-25.
A7: M1-07 | B7: DONE (frontend) | C7: Arch-B frontend removal | D7: Two-Stage ghost card excised 15-Jul (SHA-confirmed). Backend residue folded into M2-20 eradication epic.
A8: M1-02 | B8: MERGED | C8: Jobs Monitor four job types honest | D8: Merged into M1-11 evidence-graded certification (one browser pass, one checklist).
A9: M1-08 | B9: SUPERSEDED | C9: Purge + re-import into ppiq_app | D9: Purge done 14-Jul. Re-import superseded by M1-20 golden chain into ppiq_presentation (strategy: senior recs 2,3).
A10: M1-16 | B10: MOVED | C10: Register page explicit job binding | D10: Not customer-critical (senior rec 17). Now M2-24.

Sheet Phase Summary
A1: PHASE SUMMARY - live formulas over the Active Board
A2: Milestone | B2: Status | C2: Tasks | D2: Hours | E2: Critical
A3: M1 | B3: PARTIAL | C3: =COUNTIFS('Active Board'!$B$3:$B$59,A3,'Active Board'!$I$3:$I$59,B3) -> 3 | D3: =SUMIFS('Active Board'!$J$3:$J$59,'Active Board'!$B$3:$B$59,A3,'Active Board'!$I$3:$I$59,B3) -> 2.5 | E3: =COUNTIFS('Active Board'!$B$3:$B$59,A3,'Active Board'!$I$3:$I$59,B3,'Active Board'!$F$3:$F$59,"Critical") -> 3
A4: M1 | B4: NEW | C4: =COUNTIFS('Active Board'!$B$3:$B$59,A4,'Active Board'!$I$3:$I$59,B4) -> 5 | D4: =SUMIFS('Active Board'!$J$3:$J$59,'Active Board'!$B$3:$B$59,A4,'Active Board'!$I$3:$I$59,B4) -> 5 | E4: =COUNTIFS('Active Board'!$B$3:$B$59,A4,'Active Board'!$I$3:$I$59,B4,'Active Board'!$F$3:$F$59,"Critical") -> 4
A5: M1 | B5: OPEN | C5: =COUNTIFS('Active Board'!$B$3:$B$59,A5,'Active Board'!$I$3:$I$59,B5) -> 7 | D5: =SUMIFS('Active Board'!$J$3:$J$59,'Active Board'!$B$3:$B$59,A5,'Active Board'!$I$3:$I$59,B5) -> 11.5 | E5: =COUNTIFS('Active Board'!$B$3:$B$59,A5,'Active Board'!$I$3:$I$59,B5,'Active Board'!$F$3:$F$59,"Critical") -> 5
A6: M1 | B6: OPTIONAL | C6: =COUNTIFS('Active Board'!$B$3:$B$59,A6,'Active Board'!$I$3:$I$59,B6) -> 2 | D6: =SUMIFS('Active Board'!$J$3:$J$59,'Active Board'!$B$3:$B$59,A6,'Active Board'!$I$3:$I$59,B6) -> 2 | E6: =COUNTIFS('Active Board'!$B$3:$B$59,A6,'Active Board'!$I$3:$I$59,B6,'Active Board'!$F$3:$F$59,"Critical") -> 0
A7: M1 | B7: DEFERRED | C7: =COUNTIFS('Active Board'!$B$3:$B$59,A7,'Active Board'!$I$3:$I$59,B7) -> 1 | D7: =SUMIFS('Active Board'!$J$3:$J$59,'Active Board'!$B$3:$B$59,A7,'Active Board'!$I$3:$I$59,B7) -> 6 | E7: =COUNTIFS('Active Board'!$B$3:$B$59,A7,'Active Board'!$I$3:$I$59,B7,'Active Board'!$F$3:$F$59,"Critical") -> 1
A8: M2 | B8: NEW | C8: =COUNTIFS('Active Board'!$B$3:$B$59,A8,'Active Board'!$I$3:$I$59,B8) -> 11 | D8: =SUMIFS('Active Board'!$J$3:$J$59,'Active Board'!$B$3:$B$59,A8,'Active Board'!$I$3:$I$59,B8) -> 54.25 | E8: =COUNTIFS('Active Board'!$B$3:$B$59,A8,'Active Board'!$I$3:$I$59,B8,'Active Board'!$F$3:$F$59,"Critical") -> 5
A9: M2 | B9: OPEN | C9: =COUNTIFS('Active Board'!$B$3:$B$59,A9,'Active Board'!$I$3:$I$59,B9) -> 22 | D9: =SUMIFS('Active Board'!$J$3:$J$59,'Active Board'!$B$3:$B$59,A9,'Active Board'!$I$3:$I$59,B9) -> 183.5 | E9: =COUNTIFS('Active Board'!$B$3:$B$59,A9,'Active Board'!$I$3:$I$59,B9,'Active Board'!$F$3:$F$59,"Critical") -> 12
A10: M3 | B10: OPEN | C10: =COUNTIFS('Active Board'!$B$3:$B$59,A10,'Active Board'!$I$3:$I$59,B10) -> 6 | D10: =SUMIFS('Active Board'!$J$3:$J$59,'Active Board'!$B$3:$B$59,A10,'Active Board'!$I$3:$I$59,B10) -> 40 | E10: =COUNTIFS('Active Board'!$B$3:$B$59,A10,'Active Board'!$I$3:$I$59,B10,'Active Board'!$F$3:$F$59,"Critical") -> 1
A11: TONIGHT (M1 not deferred/optional) | D11: =SUMIFS('Active Board'!$J$3:$J$59,'Active Board'!$B$3:$B$59,"M1",'Active Board'!$I$3:$I$59,"PARTIAL")+SUMIFS('Active Board'!$J$3:$J$59,'Active Board'!$B$3:$B$59,"M1",'Active Board'!$I$3:$I$59,"NEW")+SUMIFS('Active Board'!$J$3:$J$59,'Active Board'!$B$3:$B$59,"M1",'Active Board'!$I$3:$I$59,"OPEN") -> 19
