Workbook

Sheet Backlog
A1: PPIQ PRODUCT BACKLOG v19 - 09-Jul-2026, end of session. Delta on v18: M1-11 / M1-10 / roleAccess executed and removed; four new tasks from what the day exposed.
A2: Task ID | B2: Milestone | C2: Phase | D2: Group | E2: Task Name | F2: Severity | G2: Task Type | H2: Module | I2: SubModule | J2: Description (deep, junior-dev-actionable) | K2: Validation (hard, reproducible) | L2: Est (h) | M2: Status vs v18 | N2: v18 ID
A3: M1-01 | B3: M1 | C3: M1-P1 | D3: G1 Import pipeline | E3: Stage-1 snapshot fallback for tables without a watermark column | F3: Critical | G3: bug fix | H3: Backend | I3: ImportPipeline | J3: PARTIAL (diagnosed, not cured). 7 of 9 registered plant tables (ms_samples, ms_sample_results, cc_slabs, cc_heats, pkl_coils, downtime_events, parsytec_surface_defects) have no source_updated_at_utc. Root cause is already isolated in the 08-Jul handover; what remains is the generic cure: a per-table watermark-strategy resolver (watermark column -> full snapshot -> keyed upsert) inside the Stage-1 path. No per-table branches. Typed error in job_log on any unresolved strategy. | K3: Stage-1 dumps ALL 9 registered plant tables green; job_log shows Started/Completed per table; a second run leaves watermarked tables at +0 rows and snapshot tables byte-deterministic; the resolver is exercised by a unit test with a fabricated table having no watermark. | L3: 2 | M3: CARRIED | N3: M1-01
A4: M1-02 | B4: M1 | C4: M1-P1 | D4: G1 Import pipeline | E4: Parameter-observations data pack for the imported plant (unblocks the analytics gate) | F4: Critical | G4: new feature | H4: Backend | I4: ImportPipeline | J4: NEW - found while proving M1-05. The Session-A plant load created heats/slabs/coils/quality_events but ZERO parameter_observations. Consequences observed live: ppiq_ml_run_learning_job_governed_v1 returns BlockedTooFewRows ('at least 30 observations required'); ml_correlation_results_v2 stays empty; the rule-based pass returns no buckets. Surface-3 therefore proves the MACHINERY (definition -> governed run -> tied compute run -> rerun recompute) but never a FINDING. Generate/import parameter_observations for the 13 existing parameter_definitions across the 3-month window, with the planted causal relations preserved, using the same silent loader that produced the plant core. | K4: SELECT count(*) FROM parameter_observations > 30 per parameter per window; ppiq_ml_run_learning_job_governed_v1('ML_PROCESS_VS_DEFECT',30) returns readiness Ready; ml_correlation_results_v2 receives rows; Verify-M1-05-Surface3.ps1 reports a real top contributor instead of WARN. | L4: 4 | M4: CARRIED | N4: M1-02
A5: M1-03 | B5: M1 | C5: M1-P1 | D5: G3 Engine honesty | E5: GENERIC CANONICAL PROJECTOR (keystone): Stage-2 consumes saved mapping definitions | F5: Critical | G5: new feature | H5: Backend | I5: Stage2-Projector | J5: Replace the hardcoded IF/ELSIF ladder with a generic projector that reads the user's saved SchemaViewDefinition/mapping definitions and projects ANY registered schema into canonical dynamically. The 8 demo sources and the plant schema become seed MAPPINGS, not code branches. SCOPE NOTE (v18): this is the PROJECTOR CORE only. Per-view Loading job orchestration is the next task and must not be built here - v17 had both tasks describing the same 40h of work. | K5: Fresh install + register an arbitrary schema + author a mapping in the UI -> Stage-2 populates canonical with zero code change; the Generic-Only grep gate is green; plant and golden datasets both project via mappings only, with no dataset identifier anywhere in the projection path. | L5: 16 | M5: CARRIED | N5: M1-03
A6: M1-04 | B6: M1 | C6: M1-P1 | D6: G9 Product hardening | E6: Per-VIEW Loading jobs on top of the generic projector (one job per mapping view) | F6: Critical | G6: new feature | H6: Backend | I6: Stage2-Projector | J6: Karim-locked model (03-Jul): 'Loading' = ONE JOB PER MAPPING VIEW, not a monolithic Stage-2 refresh. Consumes the projector core from the previous task. Each active mapping view gets its own Loading JobDefinition (auto-created on save, min interval 3 min per M2 job governance) carrying its OWN processed watermark. Delete the monolithic Stage-2 entry point once every demo source flows through a view. RE-ESTIMATED: 24h -> 12h because the projector core is now a separate, preceding task. | K6: Create a NEW mapping view in the HMI over an unmapped staging table -> a Loading job appears, runs, canonical rows appear, ZERO code change. Each view's watermark advances independently. Re-running a view with no new staging rows exits without writing. | L6: 12 | M6: CARRIED | N6: M1-04
A7: M1-05 | B7: M1 | C7: M1-P1 | D7: G3 Analytics gate | E7: Managed-engine ReadinessGate passes on the imported plant data | F7: Critical | G7: bug fix | H7: Backend | I7: Analytics-Engine | J7: REWRITTEN with the measured cause. v17 assumed a threshold-tuning problem against '1,802 heats / 18,661 coils'. Verified 09-Jul: the canonical set is 2,436 heats / 18,073 slabs / 17,823 coils, and the gate blocks with readiness_status=BlockedTooFewRows because parameter_observations is EMPTY - not because a threshold is wrong. Depends on the parameter-observations data pack. Then re-read ReadinessGate.Evaluate against the populated set and adjust CONFIG/COVERAGE only. Never the gate's honesty. | K7: A managed run reaches Completed with findings > 0 on imported canonical data. If it still blocks after observations exist, the blocking reason is captured verbatim and the demo script carries the explicit golden-set framing line. The gate's refusal path is never weakened to make a run pass. | L7: 2 | M7: CARRIED | N7: M1-05
A8: M1-06 | B8: M1 | C8: M1-P1 | D8: G0 Runtime blocker | E8: API does not answer on :5063 after the M1-10 build - find the startup exception | F8: Critical | G8: bug fix | H8: Backend | I8: Startup | J8: 09-Jul, after Apply-M1-10 landed, `ppiq.ps1 up` reported a PID but Invoke-RestMethod to http://localhost:5063/auth/login returned 'Unable to connect'. dotnet build PASSES, so this is not a compile error - minimal-API endpoints can throw at MAP time. Prime suspect: the new GET /admin/system-logs delegate, which binds DateOnly? day and int? hour from the query string. If DateOnly has no TryParse binder registered in this project the host throws during MapGet. (GetJobLogsAsync already takes DateOnly? day and works, so binding is probably fine - which points elsewhere: a duplicated route name, or the pack's Stop-Process leaving a stale lock.) Run the API in the FOREGROUND (cd Backend\PlantProcess.Api ; dotnet run) and read the exception. If it is the binder, take `string? day` and parse explicitly - which is also more forgiving of the yyyy-MM-dd that <input type="date"> sends. NOTHING DELIVERED ON 09-JUL HAS BEEN SEEN IN A BROWSER; this task is what unblocks that. | K8: `dotnet run` in the foreground starts without exception; Get-NetTCPConnection -LocalPort 5063 -State Listen returns a row; POST /auth/login with e2eadmin returns an accessToken; GET /admin/system-logs?hour=<current> returns 200 with a `file` field naming systemlog_YYYYMMDDHH.log. | L8: 1 | M8: NEW | N8: -
A9: M1-07 | B9: M1 | C9: M1-P1 | D9: G2 Assistant | E9: Register /api/assistant in the RBAC matrix (or prove it is already covered) | F9: Critical | G9: bug fix | H9: Backend | I9: Security | J9: AccessControlMiddleware (Backend/PlantProcess.Api/Security/PlantAccessControl.cs) is DENY-BY-DEFAULT by longest-prefix match, and it runs BEFORE endpoint authorization. Twice on 09-Jul an endpoint returned 403 'Endpoint is not mapped in the P01/P02 permission matrix' for exactly this reason (/api/analysis-jobs, /analytics/phase2), and both were fixed with a single Matrix line. No '/api/assistant' prefix is visible in the Matrix. The only entry that prefix-matches it is ("/", GET, anonymous) - which lets GETs slip through anonymously and 403s every POST. M1-11 wired AssistantChat to POST the ask endpoint through assistantApi; if that POST 403s, the chat is dead in the demo. Confirm first, then add ONE Matrix line with the permission its siblings use (assistant.use is already used by /analytics/dashboard). Do NOT invent a new permission. | K9: Logged in as e2eadmin: POST /api/assistant/ask returns 200 (a grounded answer or an honest abstention), never 403. A user WITHOUT assistant.use receives 403 from the middleware, not a blank chat. Add the endpoint to the Matrix table in the Identity & Topology doc. | L9: 1 | M9: NEW | N9: -
A10: M1-08 | B10: M1 | C10: M1-P1 | D10: G2 Assistant | E10: Wire the assistant gateway to ONE live provider (wire-or-frame gate) | F10: Very important | G10: new feature | H10: Backend | I10: Assistant | J10: REDUCED SCOPE. The FRONTEND chain is delivered (09-Jul): AssistantChat is mounted in the routed AssistantRuntimePage, onAsk calls assistantApi.askAssistant(), citations render as buttons, refusals render as refusals. What remains is BACKEND ONLY: wire V5AssistantGateway to one provider row in ppiq_assistant_provider_configs (self-hosted or zero-retention cloud), and confirm /api/assistant/ask is reachable through AccessControlMiddleware (there is no /api/assistant prefix in the static Matrix - an unmapped POST returns 403 'not mapped in the P01/P02 permission matrix', which cost two debug cycles on other endpoints this week). | K10: Network shows POST /api/assistant/ask returning a grounded payload with >=1 citation; an out-of-evidence question returns isRefusal=true with a reason; uncited numbers are blocked. If no provider is licensed/available, the assistant abstains and the framing doc is committed verbatim - abstention is a PASS, not a failure. | L10: 3 | M10: CARRIED (frontend half delivered 09-Jul) | N10: M1-06
A11: M1-09 | B11: M1 | C11: M1-P1 | D11: G8 Hardening & rename | E11: Repair mojibake in the 6 backend .cs files | F11: Important | G11: bug fix | H11: Backend | I11: Hygiene | J11: NEW. The 09-Jul repo-wide encoding repair fixed 119 lines across 13 FRONTEND files and added a noMojibake vitest gate. The same scan reported 6 backend .cs files carrying UTF-8-decoded-as-cp1252 text, deliberately left untouched because C# string literals can reach API responses and logs. Apply the same cp1252 round-trip repair (guarded: refuse any pass that cannot round-trip), review every changed literal, and extend the CI truth gate to scan .cs as well as .ts/.tsx/.css. | K11: Zero mojibake markers in Backend/**/*.cs; every repaired line reviewed in the diff; the truth gate fails a deliberately corrupted .cs fixture. | L11: 2 | M11: CARRIED | N11: M1-07
A12: M1-10 | B12: M1 | C12: M1-P1 | D12: G3 Engine honesty | E12: Triage the 865 genealogy diagnostics on live plant data | F12: Very important | G12: verification | H12: Backend | I12: Genealogy | J12: NEW - surfaced 09-Jul. ppiq_validate_genealogy_graph() had NEVER successfully returned a row (it threw 42804 on its first result because 690's cast was not the definition loaded). With that fixed it reports 865 rows against 35,906 canonical edges / 38,346 materials: dozens of IsolatedMaterial warnings for HEATS with no genealogy edge at all (H-26001..H-27795, WALK-*, ADV_ORPHAN_MATERIAL_001, ADV_UNKNOWN_TYPE_MATERIAL_001). ppiq_golden_thread returns MissingHop when a walk does not reach a heat. Determine per source_system whether these are real plant-data orphans (Session-A load) or fixture residue, and fix or quarantine accordingly. | K12: A per-source_system breakdown of isolated materials is committed; every orphan is classified real / fixture / quarantined; the golden coil C-0044170 walk reaches a heat; ppiq_validate_genealogy_graph reports zero Error-severity rows on the demo dataset. | L12: 3 | M12: CARRIED | N12: M1-08
A13: M1-11 | B13: M1 | C13: M1-P2 | D13: G10 Surface 1 - staging config | E13: Prove the saved import-prep definition drives Stage-1/Stage-2, and eradicate discover-demo | F13: Critical | G13: modification | H13: Frontend+Backend | I13: Surface1-ImportPrep | J13: PARTIAL. SourceImportPrepPage.tsx exists on live discovery (M1-03/M1-04 delivered: literal /tables + /columns + /register routes, column subset, PK, watermark, row filter) and its T11 debt is cleared. UNPROVEN: that the saved prep definition is what Stage-1/Stage-2 actually execute, and that /api/v5/visual-mapper/.../discover-demo is gone. Bind the persisted definition to the two-stage import job, delete the discover-demo route and its client, and prove the round trip end to end. | K13: Prepare a registered plant table with a column subset + row filter -> save -> run import -> dump_store and canonical contain EXACTLY the saved subset/filter and nothing else; grep shows zero references to discover-demo; a second, differently-shaped schema works with no code change. | L13: 4 | M13: CARRIED | N13: M1-09
A14: M1-12 | B14: M1 | C14: M1-P2 | D14: G12 UX / information architecture | E14: Administrator content: Site Identity edit, Users/Roles, System health | F14: Critical | G14: new feature | H14: Frontend+Backend | I14: Admin | J14: NEW - the promise M1-06 could not keep. After extracting Data Integration, Administrator holds a read-only Site Identity card, a static License card and a pointer. The backlog says Admin = users/roles/license/site. NONE of Users/Roles, Site-Identity EDIT, or System health exists as UI. Build them: site-identity PUT (the GET already backs AppLayout's plant name), a users+roles table over the existing auth store, and a system-health card reading /health + /db-health. Two admin types per doctrine: undeletable sysadmin vs customer tenant admin. | K14: A tenant admin renames the site and the sidebar updates without a reload; the users table lists real accounts with their roles; system health shows API + DB + last migration; a non-admin receives 403 from the server, not a hidden button. | L14: 8 | M14: CARRIED | N14: M1-11
... A142: M4-25 | B142: M4 | C142: M4-P3 | D142: Contract-shaped | E142: Recorded certified dry-run (one-click readiness on video) | F142: Very important | G142: content | H142: Docs/Demo | I142: Rehearsal | J142: A recorded certified dry-run showing one-click readiness green - the reference acceptance artifact. | K142: The recording shows readiness green end-to-end. Evidence: the file. | L142: 4 | M142: CARRIED | N142: M4-25

Sheet Change Log v18 to v19
A1: WHAT CHANGED AND WHY - v18 was written earlier on 09-Jul and was already accurate. This is the delta from the packs that landed after it, and from what those packs exposed.
A2: v18 ID | B2: Decision | C2: Evidence / measurement | D2: Where it went in v19
A3: M1-06 | B3: CONTEXT UPDATED (frontend half delivered) | C3: Apply-M1-11-AssistantChain: AssistantChat mounted in the ROUTED AssistantRuntimePage; GroundedAssistantPage (unrouted, raw fetch, duplicate types, P4 kicker) deleted; citations are buttons that expand the provenance handle; 49/49 gates. The card said "mount AssistantChat inside GroundedAssistantPage" - that page was routed by NOTHING. Remaining scope is the BACKEND provider only. | D3: M1-08 (3h, unchanged)
A4: M1-10 | B4: RE-ESTIMATED 1.5h -> 1h | C4: M1-06 shipped the layout + 5 child routes + honest ConnectorTruthPage; 44/44. Only two loose ends: /prepare kept a top-level route (renders without the area header) and there is no sub-nav inside the area. | D4: M1-18
A5: M1-12 | B5: RE-ESTIMATED 1h -> 2h | C5: Admin no longer imports DemoAnalyticsPages (M1-06 removed the last one). But App.tsx STILL lazily imports it for DynamicPage / SuggestionsPage / WidgetScriptCompilerPage, and DemoAnalyticsPages.tsx is a thin re-export that noThinReExports currently passes. | D5: M1-13
A6: M1-14 | B6: EXTENDED 1.5h -> 2h, Frontend -> Frontend+Backend | C6: M1-10 shipped a SECURITY boundary (/admin/system-logs reads files from disk) with no test. The traversal guard, the hour clamp, the Serilog level mapping and the continuation-line handling are all untested. | D6: M1-22
A7: M2-11 | B7: EXTENDED 3h -> 4h | C7: The duplicate-object class bit TWICE: once via CREATE TABLE IF NOT EXISTS (310/320 -> 42703), once via CREATE OR REPLACE FUNCTION (312/690 -> 42804, and 865 diagnostics nobody had ever seen). Tables alone is half a gate. | D7: M2-11
A8: M2-15 | B8: CONTEXT UPDATED | C8: roleAccess.ts repaired 09-Jul: keys repointed to canonical routes, /connectors + /mapping (which were never routes) moved to /data-integration/*, fail-open default replaced by explicit deny, page states enforcement is server-side. What REMAINS is wiring routeDecision into real route guards. | D8: M2-15
A9: - | B9: NEW: API does not answer on :5063 | C9: After Apply-M1-10 the API reported a PID but nothing listened. dotnet build passes, so this is a MAP-time failure, not a compile error. Nothing delivered on 09-Jul has been seen in a browser. | D9: M1-06 (Critical, 1h)
A10: - | B10: NEW: register /api/assistant in the RBAC matrix | C10: AccessControlMiddleware is deny-by-default by longest prefix and no /api/assistant entry exists. The same shape 403d /api/analysis-jobs and /analytics/phase2 earlier the same day. If the ask POST 403s, the chat is dead in the demo. | D10: M1-07 (Critical, 1h)
A11: - | B11: NEW: browser render verification | C11: Seven packs landed, all proven by tsc + vitest + dotnet build. A gate cannot see layout, colour, focus order, or whether a fetch returns. Rehearsing an unseen UI is theatre. | D11: M1-21 (Critical, 1.5h) - blocks the dress rehearsal
A12: - | B12: NEW: harden the phase-token gate | C12: Two blind spots found AFTER the gate was called repo-wide: single-digit P tokens (the deleted page carried "P4 . Production Assistant" and nothing would have caught it), and file/directory names (Phase8, Phase9, phase11, three stylesheets). | D12: M1-20 (Important, 1h)
A13: - | B13: NEW: 320 takes ACCESS EXCLUSIVE unconditionally | C13: ALTER TABLE / DROP TRIGGER / CREATE TRIGGER lock before checking existence, so a no-op re-run still locks three times. It timed out at 30s against the test suite's own connections. On a customer DB at commissioning that is an outage, not a timeout. material_aliases holds 21 rows - the backfill was never the problem. | D13: M2-13 (Very important, 2h)
... A16: - | B16: ARCHITECTURAL FACT recovered | C16: genealogy_edges = weighted provenance ledger (trigger enforces sum=1.0 per child across ALL relationship types). canonical_genealogy_edges = structural graph, unweighted, no trigger. ppiq_golden_thread / ppiq_walk_genealogy read ONLY the canonical layer. A transition coil carries heat edges only; its coil->slab hop lives in the canonical layer. | D16: Belongs in Identity & Topology v5

Sheet Phase Plan & Stats
A1: PHASE PLAN v19 - each phase a releasable increment. Hours are formula-driven from the Backlog sheet.
A2: Phase | B2: Milestone | C2: Tasks | D2: Hours | E2: Critical | F2: Deliverable theme (what ships)
A3: M1-P1 | B3: M1 | C3: =COUNTIFS(Backlog!$C$3:$C$142,$A3) | D3: =SUMIFS(Backlog!$L$3:$L$142,Backlog!$C$3:$C$142,$A3) | E3: =COUNTIFS(Backlog!$C$3:$C$142,$A3,Backlog!$F$3:$F$142,"Critical") | F3: Runtime unblock (API up, assistant reachable), import pipeline, generic projector, analytics readiness
A4: M1-P2 | B4: M1 | C4: =COUNTIFS(Backlog!$C$3:$C$142,$A4) | D4: =SUMIFS(Backlog!$L$3:$L$142,Backlog!$C$3:$C$142,$A4) | E4: =COUNTIFS(Backlog!$C$3:$C$142,$A4,Backlog!$F$3:$F$142,"Critical") | F4: Surface-1 binding, Administrator content, demo eradication, i18n, gate hardening
A5: M1-P3 | B5: M1 | C5: =COUNTIFS(Backlog!$C$3:$C$142,$A5) | D5: =SUMIFS(Backlog!$L$3:$L$142,Backlog!$C$3:$C$142,$A5) | E5: =COUNTIFS(Backlog!$C$3:$C$142,$A5,Backlog!$F$3:$F$142,"Critical") | F5: Browser verification FIRST, then E2E realignment, grounding eval, rehearsal, demo assets
A6: M2-P1 | B6: M2 | C6: =COUNTIFS(Backlog!$C$3:$C$142,$A6) | D6: =SUMIFS(Backlog!$L$3:$L$142,Backlog!$C$3:$C$142,$A6) | E6: =COUNTIFS(Backlog!$C$3:$C$142,$A6,Backlog!$F$3:$F$142,"Critical")
A7: M2-P2 | B7: M2 | C7: =COUNTIFS(Backlog!$C$3:$C$142,$A7) | D7: =SUMIFS(Backlog!$L$3:$L$142,Backlog!$C$3:$C$142,$A7) | E7: =COUNTIFS(Backlog!$C$3:$C$142,$A7,Backlog!$F$3:$F$142,"Critical")
A8: M2-P3 | B8: M2 | C8: =COUNTIFS(Backlog!$C$3:$C$142,$A8) | D8: =SUMIFS(Backlog!$L$3:$L$142,Backlog!$C$3:$C$142,$A8) | E8: =COUNTIFS(Backlog!$C$3:$C$142,$A8,Backlog!$F$3:$F$142,"Critical")
A9: M2-P4 | B9: M2 | C9: =COUNTIFS(Backlog!$C$3:$C$142,$A9) | D9: =SUMIFS(Backlog!$L$3:$L$142,Backlog!$C$3:$C$142,$A9) | E9: =COUNTIFS(Backlog!$C$3:$C$142,$A9,Backlog!$F$3:$F$142,"Critical")
A10: M2-P5 | B10: M2 | C10: =COUNTIFS(Backlog!$C$3:$C$142,$A10) | D10: =SUMIFS(Backlog!$L$3:$L$142,Backlog!$C$3:$C$142,$A10) | E10: =COUNTIFS(Backlog!$C$3:$C$142,$A10,Backlog!$F$3:$F$142,"Critical")
A11: M2-P6 | B11: M2 | C11: =COUNTIFS(Backlog!$C$3:$C$142,$A11) | D11: =SUMIFS(Backlog!$L$3:$L$142,Backlog!$C$3:$C$142,$A11) | E11: =COUNTIFS(Backlog!$C$3:$C$142,$A11,Backlog!$F$3:$F$142,"Critical")
A12: M2-P7 | B12: M2 | C12: =COUNTIFS(Backlog!$C$3:$C$142,$A12) | D12: =SUMIFS(Backlog!$L$3:$L$142,Backlog!$C$3:$C$142,$A12) | E12: =COUNTIFS(Backlog!$C$3:$C$142,$A12,Backlog!$F$3:$F$142,"Critical")
A13: M3-P1 | B13: M3 | C13: =COUNTIFS(Backlog!$C$3:$C$142,$A13) | D13: =SUMIFS(Backlog!$L$3:$L$142,Backlog!$C$3:$C$142,$A13) | E13: =COUNTIFS(Backlog!$C$3:$C$142,$A13,Backlog!$F$3:$F$142,"Critical")
A14: M3-P2 | B14: M3 | C14: =COUNTIFS(Backlog!$C$3:$C$142,$A14) | D14: =SUMIFS(Backlog!$L$3:$L$142,Backlog!$C$3:$C$142,$A14) | E14: =COUNTIFS(Backlog!$C$3:$C$142,$A14,Backlog!$F$3:$F$142,"Critical")
A15: M3-P3 | B15: M3 | C15: =COUNTIFS(Backlog!$C$3:$C$142,$A15) | D15: =SUMIFS(Backlog!$L$3:$L$142,Backlog!$C$3:$C$142,$A15) | E15: =COUNTIFS(Backlog!$C$3:$C$142,$A15,Backlog!$F$3:$F$142,"Critical")
A16: M3-P4 | B16: M3 | C16: =COUNTIFS(Backlog!$C$3:$C$142,$A16) | D16: =SUMIFS(Backlog!$L$3:$L$142,Backlog!$C$3:$C$142,$A16) | E16: =COUNTIFS(Backlog!$C$3:$C$142,$A16,Backlog!$F$3:$F$142,"Critical")
A17: M3-P5 | B17: M3 | C17: =COUNTIFS(Backlog!$C$3:$C$142,$A17) | D17: =SUMIFS(Backlog!$L$3:$L$142,Backlog!$C$3:$C$142,$A17) | E17: =COUNTIFS(Backlog!$C$3:$C$142,$A17,Backlog!$F$3:$F$142,"Critical")
... A22: M4-P5 | B22: M4 | C22: =COUNTIFS(Backlog!$C$3:$C$142,$A22) | D22: =SUMIFS(Backlog!$L$3:$L$142,Backlog!$C$3:$C$142,$A22) | E22: =COUNTIFS(Backlog!$C$3:$C$142,$A22,Backlog!$F$3:$F$142,"Critical")
A24: Milestone totals
A25: Milestone | B25: Tasks | C25: Hours | D25: Critical
A26: M1 | B26: =COUNTIFS(Backlog!$B$3:$B$142,$A26) | C26: =SUMIFS(Backlog!$L$3:$L$142,Backlog!$B$3:$B$142,$A26) | D26: =COUNTIFS(Backlog!$B$3:$B$142,$A26,Backlog!$F$3:$F$142,"Critical")
A27: M2 | B27: =COUNTIFS(Backlog!$B$3:$B$142,$A27) | C27: =SUMIFS(Backlog!$L$3:$L$142,Backlog!$B$3:$B$142,$A27) | D27: =COUNTIFS(Backlog!$B$3:$B$142,$A27,Backlog!$F$3:$F$142,"Critical")
A28: M3 | B28: =COUNTIFS(Backlog!$B$3:$B$142,$A28) | C28: =SUMIFS(Backlog!$L$3:$L$142,Backlog!$B$3:$B$142,$A28) | D28: =COUNTIFS(Backlog!$B$3:$B$142,$A28,Backlog!$F$3:$F$142,"Critical")
A29: M4 | B29: =COUNTIFS(Backlog!$B$3:$B$142,$A29) | C29: =SUMIFS(Backlog!$L$3:$L$142,Backlog!$B$3:$B$142,$A29) | D29: =COUNTIFS(Backlog!$B$3:$B$142,$A29,Backlog!$F$3:$F$142,"Critical")
