Workbook

Sheet Backlog
A1: Task Id | B1: Milestone Id | C1: Phase Id | D1: Task Name | E1: Module | F1: Sub-module | G1: Priority | H1: Task Description | I1: Task Validation | J1: Hours | K1: Status
A2: T-001 | B2: M1 | C2: M1-P1 | D2: Build the six-beat Design Traceability Matrix | E2: Documentation | F2: Design contract | G2: Critical | H2: Create docs/m1/M1_Traceability_Matrix.md. One row per screen that will be opened in the customer presentation. Columns: Screen, Route, Chapter 2 journey step (J4..J15), Chapter 3 page contract id (A1..F9 / G1..G6), Chapter 4 behaviour section (5.1..5.7), Chapter 5 tutorial step, Current implementation file, Classification. Classification is one of KEEP (matches final design), MODIFY (visible surface needs change), TEMP-ADAPTER (visible surface is final but persistence behind it is temporary and M2 replaces it), NEW. Get the route list from Frontend/PlantProcess.Web/src/App.tsx, which currently declares 69 route paths. Chapter 3 section 4.4 lists the target 40 route pages plus 6 shell components; every presentation screen must map to one of them. | I2: The matrix has zero rows where the Chapter 3 column is blank. Walk the list with the App.tsx route table open: every route you intend to open in the room appears, and no route outside the list is reachable from the demo navigation. Reviewed and signed off before any other M1 task starts. | J2: 8 | K2: Done
A3: T-002 | B3: M1 | C3: M1-P1 | D3: Audit every presented route and control against the Chapter 3 page inventory | E3: Frontend | F3: Design contract | G3: Critical | H3: CORRECTED IN v2.1. The v2.0 validation only forbade phase-token routes, which was too narrow - and the code proves it was also unnecessary, because every to: value in AppLayout.tsx is already canonical and the legacy /phase8, /phase9 and /phase15 paths are Navigate reverse redirects that no navigation entry points at. The real task is wider. Compare EVERY presented route, EVERY JourneyRail stage and EVERY navigation entry against the Chapter 3 4.4 canonical inventory of 40 route pages plus 6 shell components. For each, record the Chapter 3 contract id or record it as out-of-inventory. An out-of-inventory surface that is opened in the room is a frozen contract nobody chose. Note that PPIQ-T12 (navigationContract.test.ts) already ships from this task's own applied pack and covers the token rule; the audit below extends it, it does not repeat it. | I3: A table with one row per presented route, per JourneyRail stage and per navigation entry, each carrying a Chapter 3 contract id or an explicit out-of-inventory decision. Zero rows left undecided. Cross-check the JourneyRail stage list against Chapter 2 3.3.1 J1 to J15 - a stage that names a journey step the design does not have is a defect. | J3: 8 | K3: Done
A4: T-003 | B4: M1 | C4: M1-P1 | D4: Lock the presentation profile as a data profile, not a branch | E4: Infrastructure | F4: Environments | G4: Critical | H4: Chapter 6 forbids environment branches: the same artifact moves across environments. Confirm scripts/run/start-api.ps1 keeps its ValidateSet local/test/server/presentation and that the only difference between profiles is env/profiles/*.env. Fix the duplicated ConnectionStrings__PlantProcessDb declaration that appears twice (lines 18 and 19) in both local.env and presentation.env. Add a top-of-file comment to start-api.ps1 stating that the default is `local` and that the presentation must be launched with -Profile presentation. | I4: Run `.\scripts\run\start-api.ps1 -Profile presentation` and hit GET /api/ml/foundation/readiness. It must report outcome_values around 195,221 and correlation_results around 320, which proves the API is on ppiq_presentation. Repeat with -Profile local and confirm the numbers differ. Record both outputs in the evidence folder. | J4: 4 | K4: Done
A5: T-004 | B5: M1 | C5: M1-P1 | D5: Create the M1 acceptance checklist and evidence folder | E5: Documentation | F5: Quality | G5: Important | H5: Create docs/m1/ACCEPTANCE.md holding the UI/UX Golden Gate as a checklist applied per screen: Standard* components where one exists, no raw local styling, primary Electric Blue, selection Electric Cyan, secondary Corporate Blue, warning and refusal Amber, destructive Hot Red, muted Muted Steel, inline-start/inline-end never left/right, keyboard path, RTL mirror, all seven states (Empty, Loading, Populated, Filtered-empty, Blocked, Refused, Failed), widget failure isolation, registry-driven customer vocabulary, no number without evidence. Create docs/m1/evidence/ for screenshots and command output. | I5: Every screen in the traceability matrix has a checklist instance in the folder. A screen is not Green until every line is ticked with an evidence file name beside it. | J5: 4 | K5: Done
A6: T-005 | B6: M1 | C6: M1-P1 | D6: Rebuild ppiq_presentation into scratch and diff against live | E6: Database | F6: Presentation data | G6: Critical | H6: scripts/demo/Rebuild-PresentationDb.ps1 rebuilds the demo database in one command, but it restores from deploy/.ppiq-snapshots/ppiq_app_20260713_203359.dump, a 13 July snapshot. Every correction made against the live presentation database between 14 and 27 July survives a rebuild only if it became one of the script's steps. Run the script with -TargetDb ppiq_presentation_scratch (the script's guard requires the name to contain 'presentation'), then produce a diff: object list (tables, views, functions, triggers, indexes) and row count per table, scratch versus live. | I6: Produce docs/m1/evidence/presentation_db_diff.txt. Acceptance is either an empty diff, or a written list of every difference. Do not proceed to the next task until that list exists, and never run the rebuild against the live database before it does. | J6: 6 | K6: Done
A7: T-006 | B7: M1 | C7: M1-P1 | D7: Convert every diff finding into a seed or migration script | E7: Database | F7: Presentation data | G7: Critical | H7: For each row of the diff from the previous task, decide: is this a product fix (goes to Backend/database/scripts as a numbered migration) or presentation data (goes to scripts/demo as a seed step)? The governing law is that presentation DATA may be presentation-only but presentation FIXES may never be. Add each item in the correct place and re-run the rebuild. | I7: Re-run Rebuild-PresentationDb.ps1 into a fresh scratch database and re-run the diff. It must now be empty. That output is the proof that no fix exists only as data. | J7: 8 | K7: Done
A8: T-007 | B8: M1 | C8: M1-P1 | D8: Presentation Phenomena and Widget Coverage Matrix, part 1: inventory and the 36-chart blueprint | E8: Documentation | F8: Presentation data | G8: Critical | H8: REOPENED IN v2.5 - source truth changed after runtime measurement. The artifacts stand, but they were written against FLEET_RELATIONS.md, and measurement proved that document describes a larger, richer emulation than the one staged: 630 heats not 1,802, 5,670 coils not 18,661, 1,987 defects not 34,312, SIX defect codes not twenty, and THREE chemistry elements at one station not twelve at three. This task does not restart, and it does NOT stay half-open until the fleet is rebuilt - a task that closes twenty tasks later violates both the ordering law and the no-PARTIAL rule. It closes HERE as a PRE-GENERATION SPECIFICATION: the measured current inventory plus the 36-chart blueprint. Post-generation re-measurement and final certification belong to the phenomenon-proof task in M1-P1b, which cites this task by name so the link is machine-checked from that end. REWRITTEN IN v2.4. The previous version documented seventeen relations; that was necessary but not sufficient. Two halves, and the ORDER IS THE POINT. First, inventory what the emulation already carries - chemistry by grade at whatever element count and sampling stations MEASUREMENT SHOWS - the v2.4 text said twelve elements across three stations and that was taken from a document; measurement found THREE elements at ONE station, so the inventory records what is there, additives by grade, sequence grouping, crew rotation, ladle reline counters, cold-furnace and maintenance reheating, downtime propagation, roll wear, lubrication windows, and the seventeen planted relations with their negative controls. Second, write the 36-CHART BLUEPRINT: six primary presentation pages times six visual stories, with the seventh dashboard kept as the technical backup page. For each chart state what it must SHOW - not which correlation it must prove. The acceptance standard for the dataset changes here: every one of the 36 widgets needs an intentional visual story, sufficient population and cardinality, realistic variation, and at least one meaningful drill or filter interaction. NOT every chart must reveal a correlation. Planting a hundred clean correlations would make the plant look fabricated, which costs more credibility than a flat chart does. | I8: Two artifacts in the evidence folder: the emulation inventory with a source and a row count per structure, and the blueprint with 36 rows each naming its page, chart type, and the visual story it must tell. A reviewer must be able to say, for each of the 36, what would make that chart boring - because that is the specification the data has to beat. | J8: 10 | K8: Done
A9: T-008 | B9: M1 | C9: M1-P1 | D9: Presentation Phenomena and Widget Coverage Matrix, part 2: map, classify, close | E9: Testing | F9: Dashboard | G9: Critical | H9: REOPENED IN v2.5 alongside part one, for the same reason: it cites effect sizes and defect codes that do not exist in the staged data. R1 CRACK_LONG at 9.3x, R2 INCLUSION at 4.5x and R4 SLIPPAGE_MARK at 28.9x have NO corresponding staged defect code. Aluminium, sulfur, niobium and nitrogen are absent, so four relation families cannot exist here whatever the document says. The 104 rows are kept as the SPECIFICATION OF WHAT THE FLEET MUST CARRY, and become the input to the Fleet v2 target rather than a description of what exists. This task ALSO closes here, before any generator work, and it carries one addition: PREDECLARE the expected direction, the acceptable effect band and the negative control for every phenomenon. Declaring them before the data exists is what stops the later proof from being self-fulfilling. REWRITTEN IN v2.4 as part two of the matrix. One row per phenomenon, with these columns: phenomenon; source systems; population; variables; intended effect; noise; primary chart; secondary chart; dashboard; expected analysis result; NEGATIVE CONTROL; genealogy requirement; current status EXISTING, ENRICH or NEW; and the exact automated assertion that validates it. Target roughly 85 to 110 micro-variations, distributed as 18-25 strong discoverable relationships, 20-25 moderate or conditional, 15-20 shift, crew, campaign and maintenance regimes, 8-12 temporal drifts or regime changes, 8-12 outliers or short abnormal events, and 15-20 negative controls and noise. Most of those will be extensions of the seventeen existing relation families rather than new inventions. Then map each of the 36 charts to at least one phenomenon or to a legitimate operational baseline, and give every widget a decision: KEEP, ENHANCE, REBIND, ADD WIDGET, EXTEND EMULATION, NEEDS RELATIONSHIP SLICE, or REMOVE. Weak bindings are not data shortages - Defects by Equipment returned one row in the last audit and the remedy is canonical equipment attribution or relationship resolution, never more rows. | I9: docs/m1/evidence/phenomena_widget_matrix.csv with no blank cells. Every one of the 36 charts references at least one phenomenon or a named operational baseline. Every EXTEND EMULATION row names the exact field, so the generator work has a closed list. Every phenomenon carries its automated assertion, so the statistical QA task has nothing left to invent. | J9: 10 | K9: Done
A10: T-009 | B10: M1 | C10: M1-P1 | D10: Downtime two-quantity contract: final schema and domain slice | E10: Backend | F10: Canonical model | G10: Critical | H10: CORRECTED IN v2.1, and this was a materially wrong task. v2.0 treated the downtime work as data seeding only. It is not. The canonical DowntimeEvent entity carries timestamps, equipment, a DowntimeType and a reason, but it does NOT carry the two quantities the design requires. Chapter 3 4.5.4 specifies stopped_minutes and production_impact_minutes as separate columns, both NOT NULL and both greater than or equal to zero, because they are different quantities and one may never stand in for the other - a twenty-minute mill stoppage absorbed by buffer slabs costs no production, while a three-minute caster pump stoppage can force a sequence rebuild and cost six hours. Add both fields to the domain entity, write the migration, and extend the projection mapping so a projected downtime row carries both. Use the final column names so M2a extends rather than migrates. | I10: Project a downtime batch and assert every row has both columns populated and non-negative. Attempt an insert with a null production_impact_minutes and confirm the database rejects it. Confirm no code path derives one quantity from the other. | J10: 6 | K10: Done
A11: T-010 | B11: M1 | C11: M1-P1 | D11: Run the canonical semantic path end to end through the M1 compatibility boundaries | E11: Engine | F11: Presentation data | G11: Critical | H11: CORRECTED IN v2.1. The v2.0 wording implied the final physical topology is in place. It is not, and it is not supposed to be before M2a. What M1 proves is the canonical SEMANTIC path: connection test, dataset registration, incremental import into staging, canonical projection through the customer-authored mapping, genealogy, feature and outcome refresh, then an analysis run - each step reached through the product's own services, never by loading a target table directly. Record row counts at every stage. Note the sequencing: the final external definition contract is built later in M1-P2, so this walk is repeated once it lands - the second walk is what proves the contract did not change behaviour. | I11: One command log showing a single row entering at the source and appearing in material_units and the canonical views, with stage counts that are monotonic and explainable. Every write on the path goes through the final service interface, not a table name - which is what lets M2a replace the storage without this test changing. | J11: 8 | K11: Done
A12: T-011 | B12: M1 | C12: M1-P1 | D12: Establish and fix the architecture test pool reliability | E12: Testing | F12: CI/CD | G12: Very Important | H12: NEW IN v2.1, raised by a real failure. The navigation contract pack auto-reverted on a gate that reported 15 files and 57 tests passing with one error: a vitest worker failed to START for noMojibake.test.ts and never ran. A re-run went green, which means the gate is intermittent. The diagnostic inventory found the cause candidate: all 16 architecture test files declare no environment and none needs a DOM, yet the suite spends 40 to 45 seconds of a 62 to 68 second run on environment setup and teardown - roughly two thirds of the wall time paid for a browser environment nothing uses. Add // @vitest-environment node to the architecture test files, or set it for that directory in the vitest config. Do not raise a timeout and do not add a retry: a gate that is argued with is a gate that gets switched off, and one that fails at random teaches the team to re-run until green, which is how a real failure gets ignored. | I12: Ten consecutive runs of the architecture suite on a clean tree, all green, with zero worker-start timeouts, recorded in the evidence folder. Report the wall time before and after; the environment share should fall sharply. This matters because M1-P5 certification depends on this pool - the golden journey and the visual and accessibility gates run on it, on the two days when there is no time left to diagnose anything. | J12: 6 | K12: Done
A13: T-012 | B13: M1 | C13: M1-P1 | D13: Canonicalise the JourneyRail to J1 to J15 | E13: Frontend | F13: Journey | G13: Critical | H13: NEW IN v2.3, raised by the presented-surface audit and it is a Rule 3 violation that has been on every authenticated page. JourneyRail.tsx declares its OWN fifteen-stage journey in a hardcoded STAGES array and renders it as Step N of 15. It is not the canonical J1 to J15: different steps, different order, same numbering. Rule 3 says a second journey written anywhere is deleted rather than reconciled. Four further defects sit on top. Stage 4 Prepare mapping has only /data-integration/prepare as its match prefix, which stage 2 already claims, and the longest-prefix tie-break takes the first, so stage 4 can never become the current stage. Stage 5 points at /data-integration/author-mapping, which the audit rules out of inventory. Stage 8 points at AnalysisJobConfigPage, which leaves the M1 navigation. Stage 12 is labelled AI/ML jobs and points at the Jobs Monitor. Stage 15 points at /assistant, but Chapter 3 gives the assistant no route because G1 is a shell component. Rewrite STAGES to the canonical journey with the Chapter 2 3.3.1 labels, render J1 to J3 as completed commissioning so the count is honest, give each stage exactly one unambiguous match prefix, and repoint stages 5, 8 and 15. | I13: A test asserting the rail's stage count and labels equal the canonical journey, in the same shape as PPIQ-T12. Walk every presented route and confirm the rail highlights exactly one stage, and that the stage it highlights is the journey step that route serves. No stage may be unreachable. | J13: 6 | K13: Done
... A168: T-167 | B168: M3 | C168: M3-P2 | D168: Documentation, training and production acceptance | E168: Documentation | F168: Handover | G168: Critical | H168: Runbook, operator and data-engineer and administrator guides, release notes, known limitations, rollback plan and the formal acceptance suite. | I168: The acceptance suite passes and is signed. Known limitations are written down before the customer finds them. | J168: 12 | K168: Not Started

Sheet Phase Summary
A1: Phase Id | B1: Milestone | C1: Phase Title | D1: Intent | E1: Tasks | F1: Hours
A2: M1-P1 | B2: M1 | C2: Presentation Truth and Dataset Foundation | D2: Establish what will be shown, prove the environment rebuilds from source control, and plant the analytical phenomena the whole demonstration feeds on. Blocks M1-P3 and M1-P5. | E2: =COUNTIF(Backlog!C:C,A2) | F2: =SUMIF(Backlog!C:C,A2,Backlog!J:J)
A3: M1-P1b | B3: M1 | C3: Presentation Fleet v2 - reconcile, extend, regenerate, prove | D3: Reconcile what the emulation actually contains against what the 36 charts require, extend the existing generator rather than replacing it, regenerate through the full product path, and only then re-measure and close the reopened matrix. | E3: =COUNTIF(Backlog!C:C,A3) | F3: =SUMIF(Backlog!C:C,A3,Backlog!J:J)
A4: M1-P2 | B4: M1 | C4: No-Code Authoring Shell - wiring, SQL and widget authoring | D4: Presentation beat 1 and half of beat 2. The one shell serving five purposes, in both modes, producing one governed definition. Visible contract is final; persistence behind it may be adapted. | E4: =COUNTIF(Backlog!C:C,A4) | F4: =SUMIF(Backlog!C:C,A4,Backlog!J:J)
A5: M1-P3 | B5: M1 | C5: BI Workspace and the Seven Showcase Pages | D5: Presentation beat 2. Seven dashboards are already seeded; this phase is certification, differentiation and interaction quality, not construction. | E5: =COUNTIF(Backlog!C:C,A5) | F5: =SUMIF(Backlog!C:C,A5,Backlog!J:J)
A6: M1-P4 | B6: M1 | C6: Journey J4 to J15 and the Engine Slice | D6: Presentation beats 3 and 4. RENAMED IN v2.2: the website tasks live in M1-P5, so this phase no longer carries beat 6. Every visible transition credible with no dead end. J1 to J3 are commissioning per Chapter 5 and are narrated, not demonstrated. | E6: =COUNTIF(Backlog!C:C,A6) | F6: =SUMIF(Backlog!C:C,A6,Backlog!J:J)
A7: M1-P5 | B7: M1 | C7: Assistant Dock and Presentation Certification | D7: Presentation beat 5 plus the certification gate. Deliberately smaller than the other phases because it runs in the last week and must absorb slippage from M1-P1 and M1-P3. | E7: =COUNTIF(Backlog!C:C,A7) | F7: =SUMIF(Backlog!C:C,A7,Backlog!J:J)
A8: M2a-P1 | B8: M2a | C8: Canonical Schema Authority and the Unified Definition Store | D8: Replace the M1 compatibility adapter with the real definition store and move the schema to its final three-schema topology, without the customer-visible contract moving. | E8: =COUNTIF(Backlog!C:C,A8) | F8: =SUMIF(Backlog!C:C,A8,Backlog!J:J)
A9: M2a-P2 | B9: M2a | C9: Permanent Relationship Model and Projection Quarantine | D9: Turn the M1 single-relationship slice into the permanent product mechanism, and make customer data failures visible, typed and recoverable. | E9: =COUNTIF(Backlog!C:C,A9) | F9: =SUMIF(Backlog!C:C,A9,Backlog!J:J)
A10: M2a-P3 | B10: M2a | C10: Job Runtime, Delta Propagation and Security Hardening | D10: Make execution bounded and tenancy real. Chapter 4 5.3.9 proves that the answer to large data is architecture, not tighter licence limits. | E10: =COUNTIF(Backlog!C:C,A10) | F10: =SUMIF(Backlog!C:C,A10,Backlog!J:J)
A11: M2a-P4 | B11: M2a | C11: Commissioning, Roles, Licence and the On-Site Package | D11: Everything required to install and operate at the customer site. The visible surfaces were frozen in M1; this is the backend and the operational package behind them. | E11: =COUNTIF(Backlog!C:C,A11) | F11: =SUMIF(Backlog!C:C,A11,Backlog!J:J)
A12: M2b-P1 | B12: M2b | C12: Intelligence Substrate and Practice Learning | D12: Shipped as a governed update during the soft-test period. The readiness gate requires 60 independent units and 40 outcome events, so these engines must not be relied upon to become statistically ready during the initial soft-test window - a high-throughput plant can reach those thresholds quickly, and the wording matters because the absolute version was corrected once already in v2.0. | E12: =COUNTIF(Backlog!C:C,A12) | F12: =SUMIF(Backlog!C:C,A12,Backlog!J:J)
A13: M2b-P2 | B13: M2b | C13: Prediction, Remediation, Engine Consolidation and Gates | D13: The differentiating intelligence, plus the retirement of superseded engines and the completion of the test gates. | E13: =COUNTIF(Backlog!C:C,A13) | F13: =SUMIF(Backlog!C:C,A13,Backlog!J:J)
... A15: M3-P2 | B15: M3 | C15: Production Certification, Enterprise Operations and Commercial Completion | D15: What the sale depends on. Chapter 6 cannot be frozen until C1 to C4 replace the reference assumptions. | E15: =COUNTIF(Backlog!C:C,A15) | F15: =SUMIF(Backlog!C:C,A15,Backlog!J:J)
C16: TOTAL | E16: =SUM(E2:E15) | F16: =SUM(F2:F15)

Sheet Milestone Rollup
A1: Milestone | B1: Definition | C1: Tasks | D1: Hours | E1: Critical | F1: Very Important
A2: M1 | B2: Customer presentation, 570 h of BASELINE SCOPE as corrected in v2.8. Freeze what the customer can see; adapt what sits behind it. | C2: =COUNTIF(Backlog!B:B,A2) | D2: =SUMIF(Backlog!B:B,A2,Backlog!J:J) | E2: =COUNTIFS(Backlog!B:B,A2,Backlog!G:G,"Critical") | F2: =COUNTIFS(Backlog!B:B,A2,Backlog!G:G,"Very Important")
A3: M2a | B3: Deployable core, 432 h. Canonical journey and installability. Prediction and remediation surfaces present but legitimately readiness-blocked. | C3: =COUNTIF(Backlog!B:B,A3) | D3: =SUMIF(Backlog!B:B,A3,Backlog!J:J) | E3: =COUNTIFS(Backlog!B:B,A3,Backlog!G:G,"Critical") | F3: =COUNTIFS(Backlog!B:B,A3,Backlog!G:G,"Very Important")
A4: M2b | B4: Intelligence completion, 233 h, shipped as a governed update during the soft test. Full functional J1-J15 acceptance happens here, not at M2a. | C4: =COUNTIF(Backlog!B:B,A4) | D4: =SUMIF(Backlog!B:B,A4,Backlog!J:J) | E4: =COUNTIFS(Backlog!B:B,A4,Backlog!G:G,"Critical") | F4: =COUNTIFS(Backlog!B:B,A4,Backlog!G:G,"Very Important")
A5: M3 | B5: Site stabilisation, real-data performance, certification and commercial completion. | C5: =COUNTIF(Backlog!B:B,A5) | D5: =SUMIF(Backlog!B:B,A5,Backlog!J:J) | E5: =COUNTIFS(Backlog!B:B,A5,Backlog!G:G,"Critical") | F5: =COUNTIFS(Backlog!B:B,A5,Backlog!G:G,"Very Important")
B6: TOTAL | C6: =SUM(C2:C5) | D6: =SUM(D2:D5)

Sheet Legend
A1: PPIQ EXECUTABLE BACKLOG v2.9 - LEGEND
A3: Edit only these columns | B3: Status (column K on the Backlog sheet). Everything else is generated from the plan.
A4: Task Id | B4: PLANNED EXECUTION ORDER, dependency-aware. Not severity order - severity is the Priority column. Ids restart at each backlog epoch.
A5: Milestone Id | B5: M1 presentation / M2a deployable core / M2b intelligence completion / M3 site and production.
A6: Phase Id | B6: A group of tasks on one topic, 80 to 120 hours, no exceptions. Every phase ends pushable.
A7: Priority | B7: Critical / Very Important / Important / Optional. This is SEVERITY, not sequence.
A8: Hours | B8: No task exceeds 12 hours. Larger items were split.
A9: Status values to use | B9: Not Started / In Progress / Blocked / Done. There is no Partial: a partial task is rewritten as its remainder with a fresh estimate. T-007 and T-008 were delivered and then invalidated by runtime measurement; they are REOPENED and carry Not Started, which is the no-Partial rule applied honestly rather than a claim that no work was done.
A10: Definition of Done | B10: The Validation column passes in a browser or against a running system. Compiling is not done. Gates passing is not done.
A12: Governing law | B12: Temporary data is allowed. Temporary internal implementation is sometimes allowed. Temporary product identity, UX, workflow or behaviour is never allowed.
A13: M1 visible contract | B13: UI appearance, UX flow, routes, terminology, control behaviour and placement, and visible state and refusal semantics are final in M1.
A14: M1 hidden implementation | B14: May be a compatibility adapter, temporary schema, or partial algorithm, but only if replacing it later changes nothing the customer can see.
A15: Never allowed | B15: A fake hardcoded product answer, at any milestone.
... A18: Source | B18: Estimates by Claude against Master Design Chapters 1 to 6 and the UltimateAudit_29Jul2026_233112 repository package. All hours are estimates.
