Workbook

Sheet Current Authority
A1: PPIQ BACKLOG v2.24.0 — v4.11.1 execution authority | 17Sep2026
A2: Authority | B2: Current value | C2: As of | D2: Meaning
A3: Functional Design | B3: v4.11.1 | C3: 2026-09-17 | D3: Integrated across Chapters 1–6; current functional authority.
A4: Execution Backlog | B4: v2.24.0 | C4: 2026-09-17 | D4: In-place status/evidence/dependency/acceptance reconciliation; no new task family.
A5: Integrated Chapter 3/4 visuals | B5: v4.11.1 functional authority; illustrated regeneration pending T-265/T-266 | C5: 2026-09-17 | D5: Markdown page/runtime contracts are current. Missing illustrated DOCX derivatives do not block implementation workers.
A6: Release 1 | B6: M2 — approx. one month from owner planning checkpoint | C6: Owner planning basis | D6: No new absolute delivery date.
A7: Release 2 | B7: M3 — 45 days after M2 completion | C7: Owner planning basis | D7: 45 days after M2 completion; prior approved release allocation retained.
A8: Rows and retirements | B8: 187 active; T-105→T-104; T-111→T-110/T-155/T-159 | C8: Adds T-268 through T-275 | D8: Eight new bounded industrial-integration execution owners. No existing task retired or reopened by this design revision.
A9: T-099 closure | B9: ca02b40ea1b69050a45cb35a3e1d64f15b1f66af | C9: Final14Sep terminal transcript inspected15Sep | D9: CLOSED GREEN/COMMITTED; exact transcript corroborated. DefinitionKind known-red remains; not release-wideGREEN.
A10: T-262 closure | B10: CLOSED GREEN / COMMITTED | C10: 2026-09-16 | D10: Final live definition-store closure db0b0f84ec721f8adff1da14d4a62762200a22d6; producer 86e1b677... and 33aca26a... are ancestors.
A11: Planning estimates | B11: Industrial source preflight GREEN; T-268..T-275 estimate calibration pending | C11: 2026-09-17 | D11: Estimate calibration is not a start gate. No delivery forecast is asserted until estimates are accepted.
A12: Current task table | B12: Backlog!A1:BB188 | C12: 187 task rows | D12: Dependency validation reads the saved v2.24.0 task rows. New tasks are excluded from hour totals until explicitly estimated.
A13: Derived views | B13: Worker Tracks / Dependency Graph / Capability Map / Release Plan / dashboards | C13: v2.24.0 | D13: Formula ranges are extended through Backlog row 188. New task rows are appended to Worker Tracks and Dependency Graph.
... A31: Controlled book | B31: 12 document families / 14 physical files | C31: Owner direction — 2026-09-14 | D31: PPIQ_Definition.md registers the allowed files. The Backlog holds coverage, acceptance, validation and handoffs; no new status/JSON/README/atlas files.

Sheet Backlog
A1: Task Id | B1: Milestone Id | C1: Phase Id | D1: Task Name | E1: Module | F1: Sub-module | G1: Priority | H1: Task Description | I1: Task Validation | J1: Hours | K1: Status | L1: AI Agent Owner | M1: Depends On (IDs only) | N1: Must Precede (IDs only) | O1: Delivery Target | P1: Release Criticality | Q1: AI Execution Class | R1: AI Guarded Time P80 (h) | S1: AI Sequence Wave | T1: AI Start / Dependency Gate | U1: File / Subsystem Lock | V1: No-Rework Handoff Ruling | W1: Product Track | X1: Tech-Lead Ruling | Y1: Commit String | Z1: Commit Date | AA1: Primary Capability ID | AB1: Primary Capability Name | AC1: Secondary Capability IDs | AD1: Capability Contribution | AE1: Completeness Dimensions Targeted | AF1: Capability Requirement Class | AG1: Release Scope | AH1: Capability Closure Effect | AI1: Capability Evidence | AJ1: Estimate Basis | AK1: Design Package | AL1: UI Companion Reference | AM1: Usable scope estimate (1/0) | AN1: Contract-ready predecessors (not completion) | AO1: Evidence State | AP1: Closure Evidence Basis | AQ1: Parent Commit | AR1: Estimate Status | AS1: Usable planning hours | AT1: Usable planning P80 h | AU1: Source review coverage | AV1: Proposed remaining LOW h | AW1: Proposed remaining BASE h | AX1: Proposed remaining HIGH h | AY1: Remaining estimate confidence | AZ1: Remaining estimate basis | BA1: Source locations | BB1: Source as-of / evidence boundary
A2: T-086 | B2: M2 | C2: P1 | D2: Freeze the legacy Fleet v2 controlled regression oracle | E2: Testing | F2: Emulated sources | G2: Critical | H2: Freeze and certify the existing Fleet v2 dataset only as a legacy discrete-manufacturing regression oracle with predeclared known answers/negative controls. It is not the canonical product vocabulary, not the generic M2 fixture authority and not the source of customer schema semantics. T-208 owns new generic controlled fixtures, including the continuous-process known-answer pack. | I2: Fleet v2 is immutable and its declared phenomena/negative controls are reproducible. An architecture check proves no generic runtime/Layer-B/registry contract derives vocabulary or universal grain from Fleet. T-208 can run independently with neutral/continuous fixtures. | J2: 8 | K2: Done | L2: Worker 1 | M2: T-201 | N2: T-087; T-088; T-131 | O2: M2: ~1 month from owner planning checkpoint; exact date not committed | P2: Release 1 MUST | Q2: Integration/E2E/certification | R2: 2.72 | S2: M2-P1 | T2: CLOSED BASELINE — no new start gate and no re-execution implied. Preserve accepted closure and clean owned scope; reopen only on a concrete, separately recorded regression. Downstream consumes the frozen contract. | U2: Own canonical DB/backend/security/API/infra. No W2-owned UI/admin task files and no W3 ML/Assistant runtime. | V2: Commit before downstream consumer starts; consumer must use the contract, not redesign producer-owned semantics. | W2: Product Foundation & Release Truth | X2: M2 P1 — Product Foundation & Release Truth. Release 1 is genuine early production / first-week customer work. | Y2: 77a8ea4f — T-086: freeze the legacy regression oracle and gate generic surfaces against its vocabulary | Z2: 46259 | AA2: L8.8 | AB2: C1–C4 performance certification and golden-journey release gate | AD2: Validate | AE2: D5 | AF2: Core | AG2: R1 | AH2: Advances | AI2: =IF(Y2="","",Y2) -> 77a8ea4f — T-086: freeze the legacy regression oracle and gate generic surfaces against its vocabulary | AJ2: Inherited baseline estimate | AK2: v4.11.1 | AL2: Chapters 3/4 v4.10.3 — MD + illustrated Word; UI Coverage / UI Controls in this workbook | AM2: =IF(AND(ISNUMBER(J2),OR(AR2="INHERITED ESTIMATE",AR2="CONFIRMED ESTIMATE")),1,0) -> 1 | AO2: Recorded closed — inherited evidence | AP2: Inherited v2.22.0 intended record; no new runtime certification in this repair. | AR2: INHERITED ESTIMATE | AS2: =IF(AM2=1,J2,"") -> 8 | AT2: =IF(AND(AM2=1,ISNUMBER(R2)),R2,"") -> 2.72 | AU2: NOT SOURCE-REVIEWED IN THIS PASS | AY2: NOT ESTIMATED IN THIS PASS
A3: T-087 | B3: M2 | C3: P1 | D3: Physical three-schema migration | E3: Database | F3: Schema | G3: Critical | H3: The measured database carries twelve schemas with 162 tables in public, of which 108 use a ppiq_ name prefix, while the ruled schemas ppiq_plant and ppiq_meta exist and hold zero tables. Migrate to the three ruled schemas: ppiq_staging, ppiq_plant, ppiq_meta. The staging rename is already prepared, because the canvas reads its schema from the configuration key Prep:StagingSchema rather than a literal. | I3: Rule 2 is provable in one query on a fresh database. All application tests pass. The canvas catalogue lists tables from the renamed schema with only a configuration change. AND THE BENCHMARK SURVIVES THE MOVE: the phenomenon and benchmark harness frozen in T-086 is re-run UNCHANGED after the schema migration and produces identical results. A migration that silently alters the reference dataset destroys every comparison made against it. | J3: 12 | K3: Done | L3: Worker 1 | M3: T-086; T-088 | N3: T-089; T-099; T-102; T-112; T-114; T-128; T-196; T-233; T-251; T-252; T-272 | O3: M2: ~1 month from owner planning checkpoint; exact date not committed | P3: Release 1 MUST | Q3: DB/schema/migration | R3: 2.325 | S3: M2-P1 | T3: CLOSED BASELINE — no new start gate and no re-execution implied. Preserve accepted closure and clean owned scope; reopen only on a concrete, separately recorded regression. Downstream consumes the frozen contract. | U3: Own canonical DB/backend/security/API/infra. No W2-owned UI/admin task files and no W3 ML/Assistant runtime. | V3: Commit before downstream consumer starts; consumer must use the contract, not redesign producer-owned semantics. | W3: Product Foundation & Release Truth | X3: M2 P1 — Product Foundation & Release Truth. Release 1 is genuine early production / first-week customer work. | Y3: e7d82f078d7dfa4c1ca4ec6e88d0dbc7e1ecd6ba — subject not recovered | Z3: 46262 | AA3: L2.1 | AB3: Three-schema platform and placement law | AC3: L5.7 | AD3: Converge | AE3: D4; D5 | AF3: Core | AG3: R1 | AH3: Advances | AI3: =IF(Y3="","",Y3) -> e7d82f078d7dfa4c1ca4ec6e88d0dbc7e1ecd6ba — subject not recovered | AJ3: Inherited baseline estimate | AK3: v4.11.1 | AL3: Chapters 3/4 v4.10.3 — MD + illustrated Word; UI Coverage / UI Controls in this workbook | AM3: =IF(AND(ISNUMBER(J3),OR(AR3="INHERITED ESTIMATE",AR3="CONFIRMED ESTIMATE")),1,0) -> 1 | AO3: Recorded closed — inherited evidence | AP3: Inherited v2.22.0 intended record; no new runtime certification in this repair. | AR3: INHERITED ESTIMATE | AS3: =IF(AM3=1,J3,"") -> 12 | AT3: =IF(AND(AM3=1,ISNUMBER(R3)),R3,"") -> 2.325 | AU3: NOT SOURCE-REVIEWED IN THIS PASS | AY3: NOT ESTIMATED IN THIS PASS
A4: T-088 | B4: M2 | C4: P1 | D4: Canonical migration order and legacy script archival | E4: Database | F4: Schema | G4: Very Important | H4: Backend/database/scripts contains hotfix, repair, phase and drift-correction scripts accumulated over months, including cases where two scripts created the same table. Define one canonical ordered migration path, archive superseded scripts, and add a truth gate that no two scripts create the same table. | I4: A fresh database builds from the canonical path with no manual step. The truth gate fails if a duplicate CREATE TABLE is introduced. | J4: 12 | K4: Done | L4: Worker 1 | M4: T-086 | N4: T-087; T-089; T-112; T-128; T-251; T-252; T-256; T-260; T-272 | O4: M2: ~1 month from owner planning checkpoint; exact date not committed | P4: Release 1 MUST | Q4: DB/schema/migration | R4: 2.325 | S4: M2-P1 | T4: CLOSED BASELINE — no new start gate and no re-execution implied. Preserve accepted closure and clean owned scope; reopen only on a concrete, separately recorded regression. Downstream consumes the frozen contract. | U4: Own canonical DB/backend/security/API/infra. No W2-owned UI/admin task files and no W3 ML/Assistant runtime. | V4: Commit before downstream consumer starts; consumer must use the contract, not redesign producer-owned semantics. | W4: Product Foundation & Release Truth | X4: M2 P1 — Product Foundation & Release Truth. Release 1 is genuine early production / first-week customer work. | Y4: 6a62c9d6 — Establish canonical database migration authority | Z4: 46260 | AA4: L8.1 | AB4: Fresh install and upgrade authority | AC4: L5.7; L2.1 | AD4: Converge | AE4: D4; D5 | AF4: Core | AG4: R1 | AH4: Advances | AI4: =IF(Y4="","",Y4) -> 6a62c9d6 — Establish canonical database migration authority | AJ4: Inherited baseline estimate | AK4: v4.11.1 | AL4: Chapters 3/4 v4.10.3 — MD + illustrated Word; UI Coverage / UI Controls in this workbook | AM4: =IF(AND(ISNUMBER(J4),OR(AR4="INHERITED ESTIMATE",AR4="CONFIRMED ESTIMATE")),1,0) -> 1 | AO4: Recorded closed — inherited evidence | AP4: Inherited v2.22.0 intended record; no new runtime certification in this repair. | AR4: INHERITED ESTIMATE | AS4: =IF(AM4=1,J4,"") -> 12 | AT4: =IF(AND(AM4=1,ISNUMBER(R4)),R4,"") -> 2.325 | AU4: NOT SOURCE-REVIEWED IN THIS PASS | AY4: NOT ESTIMATED IN THIS PASS
A5: T-089 | B5: M2 | C5: P1 | D5: definition_store, definition_versions and definition_dependencies | E5: Database | F5: Definition store | G5: Critical | H5: Create the tables specified in Chapter 3 4.5.11 with immutable versions and a dependency graph, plus a trigger that rejects a dependency cycle. | I5: Integration tests: create, version, publish, and reject a cycle. Version rows must be immutable, proved by an update attempt that fails. | J5: 12 | K5: Done | L5: Worker 1 | M5: T-087; T-088 | N5: T-090; T-092; T-095; T-099; T-106; T-114; T-128; T-183; T-243; T-244 | O5: M2: ~1 month from owner planning checkpoint; exact date not committed | P5: Release 1 MUST | Q5: DB/schema/migration | R5: 2.325 | S5: M2-P1 | T5: CLOSED BASELINE — no new start gate and no re-execution implied. Preserve accepted closure and clean owned scope; reopen only on a concrete, separately recorded regression. Downstream consumes the frozen contract. | U5: Own canonical DB/backend/security/API/infra. No W2-owned UI/admin task files and no W3 ML/Assistant runtime. | V5: Commit before downstream consumer starts; consumer must use the contract, not redesign producer-owned semantics. | W5: Product Foundation & Release Truth | X5: M2 P1 — Product Foundation & Release Truth. Release 1 is genuine early production / first-week customer work. | Y5: 0fd79e5e3516cdfd0ab5a73a02e16638fd02693a — subject not recovered | AA5: L2.5 | AB5: Unified definition store and immutable target/version governance | AC5: L5.6 | AD5: Build | AE5: D4; D5 | AF5: Core | AG5: R1 | AH5: Advances | AI5: =IF(Y5="","",Y5) -> 0fd79e5e3516cdfd0ab5a73a02e16638fd02693a — subject not recovered | AJ5: Inherited baseline estimate | AK5: v4.11.1 | AL5: Chapters 3/4 v4.10.3 — MD + illustrated Word; UI Coverage / UI Controls in this workbook | AM5: =IF(AND(ISNUMBER(J5),OR(AR5="INHERITED ESTIMATE",AR5="CONFIRMED ESTIMATE")),1,0) -> 1 | AO5: Recorded closed — inherited evidence | AP5: Inherited v2.22.0 intended record; no new runtime certification in this repair. | AR5: INHERITED ESTIMATE | AS5: =IF(AM5=1,J5,"") -> 12 | AT5: =IF(AND(AM5=1,ISNUMBER(R5)),R5,"") -> 2.325 | AU5: NOT SOURCE-REVIEWED IN THIS PASS | AY5: NOT ESTIMATED IN THIS PASS
A6: T-090 | B6: M2 | C6: P1 | D6: Move all five definition kinds onto the store | E6: Backend | F6: Definition store | G6: Critical | H6: Replace the M1 compatibility adapter behind IDefinitionService with the real implementation for all five purposes: S1 Transformation, S2 Pages and widgets and filters and master items, S3 Analysis, S4 Model, S5 Log rule. The old per-artifact tables become a compatibility projection and then are retired. v2.10.1 OUTCOME SEMANTICS BINDING. As part of canonical definition convergence, bind the already-frozen SM-06 OutcomeDefinition to the canonical immutable versioned definition authority; do not design a second outcome authority. The canonical binding preserves outcome_code, outcome_type, class_taxonomy_ref, ordinal_rank_map, grain_code, detection_position_code, detection_timestamp_field, direction, unit_code, censoring_policy and definition/version identity. Any legacy ml_outcome_definitions representation may remain only as a compatibility projection during convergence and must not remain an independent semantic authority. | I6: The M1 integration test written against IDefinitionService must pass unchanged, since it references no table name. That is the proof that the visible contract did not move. Publish an SM-06 OutcomeDefinition and resolve it back by exact immutable version. Changing detection_position_code, detection_timestamp_field, grain, taxonomy, ordinal map, direction, unit or censoring policy creates a new definition version rather than silently mutating published meaning. If a compatibility outcome representation remains during convergence, prove it resolves to the same canonical definition/version and cannot diverge into a second authority. | J6: 12 | K6: Done | L6: Worker 1 | M6: T-089 | N6: T-091; T-092; T-095; T-099; T-104; T-106; T-114; T-128; T-134; T-147; T-183; T-195; T-210; T-221; T-228; T-231; T-232; T-233; T-235; T-239; T-243; T-244 | O6: M2: ~1 month from owner planning checkpoint; exact date not committed | P6: Release 1 MUST | Q6: Backend/domain contract | R6: 1.8 | S6: M2-P1 | T6: CLOSED BASELINE — no new start gate and no re-execution implied. Preserve accepted closure and clean owned scope; reopen only on a concrete, separately recorded regression. Downstream consumes the frozen contract. | U6: Own canonical DB/backend/security/API/infra. No W2-owned UI/admin task files and no W3 ML/Assistant runtime. | V6: Downstream consumers wait for the committed T-090 authority. Handover/progress notes do not substitute for closure; the pack must apply, build, test, replay and commit on the user machine. | W6: Product Foundation & Release Truth | X6: CENTRAL 30-Aug-2026: canonical definition convergence remains full scope. Deliver the standard executable PowerShell pack; no Task-ID-less changes. | Y6: a6399d9c — subject not recovered | AA6: L5.6 | AB6: Unified definition-store semantics | AC6: L2.5 | AD6: Converge | AE6: D3; D4; D5 | AF6: Core | AG6: R1 | AH6: Advances | AI6: =IF(Y6="","",Y6) -> a6399d9c — subject not recovered | AJ6: Inherited baseline estimate | AK6: v4.11.1 | AL6: Chapters 3/4 v4.10.3 — MD + illustrated Word; UI Coverage / UI Controls in this workbook | AM6: =IF(AND(ISNUMBER(J6),OR(AR6="INHERITED ESTIMATE",AR6="CONFIRMED ESTIMATE")),1,0) -> 1 | AO6: Recorded closed — inherited evidence | AP6: Inherited v2.22.0 intended record; no new runtime certification in this repair. | AR6: INHERITED ESTIMATE | AS6: =IF(AM6=1,J6,"") -> 12 | AT6: =IF(AND(AM6=1,ISNUMBER(R6)),R6,"") -> 1.8 | AU6: NOT SOURCE-REVIEWED IN THIS PASS | AY6: NOT ESTIMATED IN THIS PASS
A7: T-091 | B7: M2 | C7: P1 | D7: Impact preview, export and import | E7: Backend | F7: Definition store | G7: Very Important | H7: Add dependency impact preview before a publish, and export and import of a definition with its dependencies, per Chapter 3 4.5.11. | I7: Publish a change to a definition three others depend on and confirm the preview lists all three before the publish is confirmed. Export and reimport into an empty database and confirm equality. | J7: 12 | K7: Done | L7: Worker 1 | M7: T-090 | N7: T-128; T-183 | O7: M2: ~1 month from owner planning checkpoint; exact date not committed | P7: Release 1 MUST | Q7: Backend/domain contract | R7: 1.8 | S7: M2-P1 | T7: CLOSED BASELINE — no new start gate and no re-execution implied. Preserve accepted closure and clean owned scope; reopen only on a concrete, separately recorded regression. Downstream consumes the frozen contract. | U7: Own canonical DB/backend/security/API/infra. No W2-owned UI/admin task files and no W3 ML/Assistant runtime. | V7: Commit before downstream consumer starts; consumer must use the contract, not redesign producer-owned semantics. | W7: Product Foundation & Release Truth | X7: M2 P1 — Product Foundation & Release Truth. Release 1 is genuine early production / first-week customer work. | Y7: c6d64289 — subject not recovered | AA7: L5.6 | AB7: Unified definition-store semantics | AC7: L2.5 | AD7: Build | AE7: D3; D5 | AF7: Core | AG7: R1 | AH7: Advances | AI7: =IF(Y7="","",Y7) -> c6d64289 — subject not recovered | AJ7: Inherited baseline estimate | AK7: v4.11.1 | AL7: Chapters 3/4 v4.10.3 — MD + illustrated Word; UI Coverage / UI Controls in this workbook | AM7: =IF(AND(ISNUMBER(J7),OR(AR7="INHERITED ESTIMATE",AR7="CONFIRMED ESTIMATE")),1,0) -> 1 | AO7: Recorded closed — inherited evidence | AP7: Inherited v2.22.0 intended record; no new runtime certification in this repair. | AR7: INHERITED ESTIMATE | AS7: =IF(AM7=1,J7,"") -> 12 | AT7: =IF(AND(AM7=1,ISNUMBER(R7)),R7,"") -> 1.8 | AU7: NOT SOURCE-REVIEWED IN THIS PASS | AY7: NOT ESTIMATED IN THIS PASS
A8: T-092 | B8: M2 | C8: P1 | D8: Registry authority: dimensions and measures as rows | E8: Backend | F8: Registry | G8: Critical | H8: Replace compiled dimension/measure catalogues with canonical registry projections over published definition versions. Registry rows must support customer-defined dimensions/measures without rebuild, plus analysis-grain metadata, signal/aggregation semantics and reference-derived measure roles. It remains a projection/serving authority, not a competing mutable definition store. | I8: Using the same binary, add a customer-shaped dimension and measure through definitions/registry data only and use them in an authored widget. No C#/React/product-SQL edit. Registry exposes declared grain and aggregation/reference metadata and rejects unresolved semantics. | J8: 12 | K8: Done | L8: Worker 1 | M8: T-089; T-090; T-210; T-231 | N8: T-093; T-094; T-128; T-183; T-212; T-215; T-228; T-237; T-247 | O8: M2: ~1 month from owner planning checkpoint; exact date not committed | P8: Release 1 MUST | Q8: Backend/domain contract | R8: 1.8 | S8: M2-P1 | T8: CLOSED BASELINE — no new start gate and no re-execution implied. Preserve accepted closure and clean owned scope; reopen only on a concrete, separately recorded regression. Downstream consumes the frozen contract. | U8: Own canonical DB/backend/security/API/infra. No W2-owned UI/admin task files and no W3 ML/Assistant runtime. | V8: Commit before downstream consumer starts; consumer must use the contract, not redesign producer-owned semantics. | W8: Product Foundation & Release Truth | X8: M2 P1 — Product Foundation & Release Truth. Release 1 is genuine early production / first-week customer work. | Y8: ab2962a4; 7cad36e4 — registry authority closure commits | Z8: 46267 | AA8: L3.9 | AB8: Master items, bookmarks and saved views | AC8: L5.1 | AD8: Build | AE8: D1; D3; D5 | AF8: Core | AG8: R1 | AH8: Advances | AI8: =IF(Y8="","",Y8) -> ab2962a4; 7cad36e4 — registry authority closure commits | AJ8: Inherited baseline estimate | AK8: v4.11.1 | AL8: Chapters 3/4 v4.10.3 — MD + illustrated Word; UI Coverage / UI Controls in this workbook | AM8: =IF(AND(ISNUMBER(J8),OR(AR8="INHERITED ESTIMATE",AR8="CONFIRMED ESTIMATE")),1,0) -> 1 | AO8: Recorded closed — inherited evidence | AP8: Inherited v2.22.0 intended record; no new runtime certification in this repair. | AR8: INHERITED ESTIMATE | AS8: =IF(AM8=1,J8,"") -> 12 | AT8: =IF(AND(AM8=1,ISNUMBER(R8)),R8,"") -> 1.8 | AU8: NOT SOURCE-REVIEWED IN THIS PASS | AY8: NOT ESTIMATED IN THIS PASS
A9: T-093 | B9: M2 | C9: P1 | D9: Plant-vocabulary sweep, part 1: build the term list and the architecture test | E9: Backend | F9: Registry | G9: Very Important | H9: Rule 1 needs an enforcement mechanism before the sweep, or the sweep is a one-off. Create a registry-held list of plant terms (the term list is itself DATA, never a compiled constant) and an architecture test that fails the build when any listed term appears in product code outside registry data, seed content or test fixtures. Seed the list from the dimension names already found compiled into DashboardWidgetQuerySafetyRegistry: ProductFamily, GradeOrRecipe, ShiftCode, DefectType, RiskClass. | I9: Add a term to the list and confirm the build goes red on an existing violation, then goes green once that violation is fixed. Confirm removing a term from the list does not require a code change. | J9: 6 | K9: Done | L9: Worker 1 | M9: T-092; T-206 | N9: T-094; T-128; T-183 | O9: M2: ~1 month from owner planning checkpoint; exact date not committed | P9: Release 1 MUST | Q9: Backend/domain contract | R9: 0.9 | S9: M2-P1 | T9: CLOSED BASELINE — no new start gate and no re-execution implied. Preserve accepted closure and clean owned scope; reopen only on a concrete, separately recorded regression. Downstream consumes the frozen contract. | U9: Own canonical DB/backend/security/API/infra. No W2-owned UI/admin task files and no W3 ML/Assistant runtime. | V9: Commit before downstream consumer starts; consumer must use the contract, not redesign producer-owned semantics. | W9: Product Foundation & Release Truth | X9: M2 P1 — Product Foundation & Release Truth. Release 1 is genuine early production / first-week customer work. | Y9: 4e2e0f654b93ceed2ecdfbce4d3c1768550b3079 — T-093 govern plant vocabulary as data-driven genericity debt | Z9: 46268 | AA9: L5.1 | AB9: Canonical entity catalogue | AD9: Build | AE9: D3; D5 | AF9: Core | AG9: R1 | AH9: Advances | AI9: =IF(Y9="","",Y9) -> 4e2e0f654b93ceed2ecdfbce4d3c1768550b3079 — T-093 govern plant vocabulary as data-driven genericity debt | AJ9: Inherited baseline estimate | AK9: v4.11.1 | AL9: Chapters 3/4 v4.10.3 — MD + illustrated Word; UI Coverage / UI Controls in this workbook | AM9: =IF(AND(ISNUMBER(J9),OR(AR9="INHERITED ESTIMATE",AR9="CONFIRMED ESTIMATE")),1,0) -> 1 | AO9: Recorded closed — inherited evidence | AP9: Inherited v2.22.0 intended record; no new runtime certification in this repair. | AR9: INHERITED ESTIMATE | AS9: =IF(AM9=1,J9,"") -> 6 | AT9: =IF(AND(AM9=1,ISNUMBER(R9)),R9,"") -> 0.9 | AU9: NOT SOURCE-REVIEWED IN THIS PASS | AY9: NOT ESTIMATED IN THIS PASS
A10: T-094 | B10: M2 | C10: P1 | D10: Plant-vocabulary sweep, part 2: remove hardcoded universal grain and industry vocabulary | E10: Backend | F10: Registry | G10: Very Important | H10: Clear generic-runtime/demo-vocabulary violations without replacing one industry noun with another. Complete the declared-dimension execution path on BOTH runtime wire surfaces: (A) persisted widget execution via DashboardWidgetFiltersDto/declared keyed dimensions and (B) workspace/global dashboard query execution via DashboardQueryDto and the overview/quality/risk/data-quality/materials routes. Remove fixed universal grain/industry vocabulary from DashboardReferenceDataDto and the frontend consumers by resolving published registry definitions, canonical members and governed Analysis Subject/relationship authority. The target contract is definition/registry member -> relationship/path resolution -> Analysis Subject -> typed refusal; the current direct single-reference resolver is an interim implementation until T-095/T-096 path authority lands. No presentation vocabulary becomes product authority. | I10: Using the same binary, author a foreign/customer-shaped dimension and prove it filters both a persisted widget and the workspace/global route surface through the same published definition/member identity. Both surfaces must return the same typed refusal when the dimension is undeclared, inactive, unmapped, has no subject path, or becomes ambiguous. No compiled fallback to defectType/riskClass/shiftCode or a universal material grain. Frontend consumers use the keyed contract. Wave-C genericity arithmetic remains exact: every known fingerprint is retired or explicitly lawful; unknown=0. | J10: 24 | K10: Done | L10: Worker 1 | M10: T-092; T-093; T-209 | N10: T-095; T-128; T-183; T-196; T-253; T-256; T-258 | O10: M2: ~1 month from owner planning checkpoint; exact date not committed | P10: Release 1 MUST | Q10: Backend/domain contract | R10: 3.6 | S10: M2-P1 | T10: CLOSED BASELINE — no new start gate and no re-execution implied. Preserve accepted closure and clean owned scope; reopen only on a concrete, separately recorded regression. Downstream consumes the frozen contract. | U10: Own canonical DB/backend/security/API/infra. No W2-owned UI/admin task files and no W3 ML/Assistant runtime. | V10: Commit before downstream consumer starts; consumer must use the contract, not redesign producer-owned semantics. | W10: Product Foundation & Release Truth | X10: CENTRAL 04-Sep-2026: T-094 remains open. Scope is formally amended from one wire to both declared-dimension execution surfaces. No new task is created while T-094 is open; after closure any new surface requires a new Task ID. | Y10: 377aabdffb27d651d30537ce5228ee4afe268526; 6ab97ee2; e74ecd1c; 5a967f1b0ab45961c8b8a880bb4fdec53a783134 — final: T-094 close keyed declared-dimension cutover and genericity reconciliation | Z10: 46272 | AA10: L5.1 | AB10: Canonical entity catalogue | AC10: L5.3 | AD10: Build | AE10: D1; D3; D5 | AF10: Core | AG10: R1 | AH10: Advances | AI10: =IF(Y10="","",Y10) -> 377aabdffb27d651d30537ce5228ee4afe268526; 6ab97ee2; e74ecd1c; 5a967f1b0ab45961c8b8a880bb4fdec53a783134 — final: T-094 close keyed declared-dimension cutover and genericity reconciliation | AJ10: Inherited baseline estimate | AK10: v4.11.1 | AL10: Chapters 3/4 v4.10.3 — MD + illustrated Word; UI Coverage / UI Controls in this workbook | AM10: =IF(AND(ISNUMBER(J10),OR(AR10="INHERITED ESTIMATE",AR10="CONFIRMED ESTIMATE")),1,0) -> 1 | AO10: Recorded closed — inherited evidence | AP10: Inherited v2.22.0 intended record; no new runtime certification in this repair. | AR10: INHERITED ESTIMATE | AS10: =IF(AM10=1,J10,"") -> 24 | AT10: =IF(AND(AM10=1,ISNUMBER(R10)),R10,"") -> 3.6 | AU10: NOT SOURCE-REVIEWED IN THIS PASS | AY10: NOT ESTIMATED IN THIS PASS
A11: T-095 | B11: M2 | C11: P2 | D11: Relationship members, cardinality, grain conversion and preferred paths | E11: Backend | F11: Relationship model | G11: Critical | H11: Extend the M1 slice to the full model in Chapter 3 4.5.10: members, cardinality, grain conversion between related entities, preferred path selection when more than one path exists, and published versions. v2.10.2 CONVERGENCE CORRECTION — T-095 does not merely 'extend' M1 physical tables. It converges the M1 relationship service/compatibility persistence onto the canonical Chapter 3 4.5.10 tables after definition_store exists, including source_definition_id/version, grain conversion, preferred paths, ambiguity/validation state and retirement semantics, while keeping the M1 external contract stable. | I11: Declare two paths between the same pair of entities, mark one preferred, and confirm the resolver chooses it. Change the preference and confirm the resolution changes with no other edit. | J11: 12 | K11: Done | L11: Worker 1 | M11: T-057; T-089; T-090; T-094 | N11: T-096; T-098; T-102; T-103; T-104; T-107; T-109; T-114; T-128; T-134; T-183; T-196; T-221 | O11: M2: ~1 month from owner planning checkpoint; exact date not committed | P11: Release 1 MUST | Q11: Backend/domain contract | R11: 1.8 | S11: M2-P2 | T11: CLOSED BASELINE — no new start gate and no re-execution implied. Preserve accepted closure and clean owned scope; reopen only on a concrete, separately recorded regression. Downstream consumes the frozen contract. | U11: Own canonical DB/backend/security/API/infra. No W2-owned UI/admin task files and no W3 ML/Assistant runtime. | V11: Commit before downstream consumer starts; consumer must use the contract, not redesign producer-owned semantics. | W11: Day-1 Data Workbench — DB Link, Canvas, Jobs & OPC | X11: M2 P2 — Day-1 Data Workbench — DB Link, Canvas, Jobs & OPC. Release 1 is genuine early production / first-week customer work. | Y11: 554d1ac02af122fdeb7ca54b1dd35bac0c76f23e — subject not recovered | Z11: 46272 | AA11: L5.2 | AB11: Permanent relationship model | AD11: Build | AE11: D1; D3; D5 | AF11: Core | AG11: R1 | AH11: Advances | AI11: =IF(Y11="","",Y11) -> 554d1ac02af122fdeb7ca54b1dd35bac0c76f23e — subject not recovered | AJ11: Inherited baseline estimate | AK11: v4.11.1 | AL11: Chapters 3/4 v4.10.3 — MD + illustrated Word; UI Coverage / UI Controls in this workbook | AM11: =IF(AND(ISNUMBER(J11),OR(AR11="INHERITED ESTIMATE",AR11="CONFIRMED ESTIMATE")),1,0) -> 1 | AO11: Recorded closed — inherited evidence | AP11: Inherited v2.22.0 intended record; no new runtime certification in this repair. | AR11: INHERITED ESTIMATE | AS11: =IF(AM11=1,J11,"") -> 12 | AT11: =IF(AND(AM11=1,ISNUMBER(R11)),R11,"") -> 1.8 | AU11: SOURCE CORROBORATES CLOSED FOUNDATION | AV11: 0 | AW11: 0 | AX11: 0 | AY11: UNCONFIRMED REVIEW ESTIMATE - not P80 or elapsed | AZ11: Closed original scope; zero remaining here does not certify downstream Canvas integration. | BA11: Backend/PlantProcess.Application/Relationships/RelationshipService.cs:145-217 — PublishAsync Backend/PlantProcess.Application/Relationships/RelationshipService.cs:218-260 — ValidateDeclaration | BB11: 14-Sep-2026 snapshot; later closure evidence separate; no live HEAD verification
A12: T-096 | B12: M2 | C12: P2 | D12: Path resolver, part 1: resolver core and the first eight consumers | E12: Backend | F12: Relationship model | G12: Critical | H12: Chapter 2 3.15.4 names sixteen consumers of the relationship model. Build the resolver core, then route the first eight through it: canonical projection, page and widget queries, associative filtering, drill-down, drill-through, genealogy, statistics and correlation. | I12: A regression test per consumer asserting it resolves through the published model, and refuses with a named reason when the relationship is unpublished. Eight tests, no exceptions. | J12: 8 | K12: Done | L12: Worker 1 | M12: T-095 | N12: T-097; T-098; T-107; T-109; T-128; T-134; T-183; T-221 | O12: M2: ~1 month from owner planning checkpoint; exact date not committed | P12: Release 1 MUST | Q12: Backend/domain contract | R12: 1.2 | S12: M2-P2 | T12: CLOSED BASELINE — no new start gate and no re-execution implied. Preserve accepted closure and clean owned scope; reopen only on a concrete, separately recorded regression. Downstream consumes the frozen contract. | U12: Own canonical DB/backend/security/API/infra. No W2-owned UI/admin task files and no W3 ML/Assistant runtime. | V12: Commit before downstream consumer starts; consumer must use the contract, not redesign producer-owned semantics. | W12: Day-1 Data Workbench — DB Link, Canvas, Jobs & OPC | X12: M2 P2 — Day-1 Data Workbench — DB Link, Canvas, Jobs & OPC. Release 1 is genuine early production / first-week customer work. | Y12: de243027073fc5e492d65e9f9845255342517510 — T-096 relationship resolver consumer convergence | Z12: 46273 | AA12: L5.2 | AB12: Permanent relationship model | AD12: Build | AE12: D3; D5 | AF12: Core | AG12: R1 | AH12: Advances | AI12: =IF(Y12="","",Y12) -> de243027073fc5e492d65e9f9845255342517510 — T-096 relationship resolver consumer convergence | AJ12: Inherited baseline estimate | AK12: v4.11.1 | AL12: Chapters 3/4 v4.10.3 — MD + illustrated Word; UI Coverage / UI Controls in this workbook | AM12: =IF(AND(ISNUMBER(J12),OR(AR12="INHERITED ESTIMATE",AR12="CONFIRMED ESTIMATE")),1,0) -> 1 | AO12: Recorded closed — inherited evidence | AP12: Inherited v2.22.0 intended record; no new runtime certification in this repair. | AR12: INHERITED ESTIMATE | AS12: =IF(AM12=1,J12,"") -> 8 | AT12: =IF(AND(AM12=1,ISNUMBER(R12)),R12,"") -> 1.2 | AU12: SOURCE CORROBORATES CLOSED FOUNDATION | AV12: 0 | AW12: 0 | AX12: 0 | AY12: UNCONFIRMED REVIEW ESTIMATE - not P80 or elapsed | AZ12: Original resolver/convergence closure retained; no rebuilding cost. | BA12: Backend/PlantProcess.Application/Relationships/RelationshipResolver.cs:34-113 — ResolveAsync Backend/tests/PlantProcess.Architecture.Tests/RelationshipConsumerBarrierTests.cs:55-96 — ConsumerFamilies | BB12: 14-Sep-2026 snapshot; later closure evidence separate; no live HEAD verification
A13: T-097 | B13: M2 | C13: P2 | D13: Path resolver, part 2: the remaining eight consumers and the regression suite | E13: Backend | F13: Relationship model | G13: Critical | H13: Route the remaining eight through the resolver: feature engineering, model training, prediction, practice learning, remediation search, value calculation, assistant retrieval and evidence. Some of these are built in Release 2; add the resolver seam now so they cannot be written against an ad-hoc join later. | I13: Eight further regression tests. For consumers whose engine arrives in Release 2, the test asserts the seam exists and refuses when unpublished, which is what stops a later shortcut. | J13: 6 | K13: Done | L13: Worker 1 | M13: T-096 | N13: T-098; T-107; T-109; T-128; T-183 | O13: M2: ~1 month from owner planning checkpoint; exact date not committed | P13: Release 1 MUST | Q13: Backend/domain contract | R13: 0.9 | S13: M2-P2 | T13: CLOSED BASELINE — no new start gate and no re-execution implied. Preserve accepted closure and clean owned scope; reopen only on a concrete, separately recorded regression. Downstream consumes the frozen contract. | U13: Own canonical DB/backend/security/API/infra. No W2-owned UI/admin task files and no W3 ML/Assistant runtime. | V13: Commit before downstream consumer starts; consumer must use the contract, not redesign producer-owned semantics. | W13: Day-1 Data Workbench — DB Link, Canvas, Jobs & OPC | X13: M2 P2 — Day-1 Data Workbench — DB Link, Canvas, Jobs & OPC. Release 1 is genuine early production / first-week customer work. | Y13: 95220d1804493f8e7b80347fe3ed4de24741f9ec — T-097 relationship consumer barrier across all sixteen families | Z13: 46273 | AA13: L5.2 | AB13: Permanent relationship model | AD13: Build | AE13: D3; D5 | AF13: Core | AG13: R1 | AH13: Advances | AI13: =IF(Y13="","",Y13) -> 95220d1804493f8e7b80347fe3ed4de24741f9ec — T-097 relationship consumer barrier across all sixteen families | AJ13: Inherited baseline estimate | AK13: v4.11.1 | AL13: Chapters 3/4 v4.10.3 — MD + illustrated Word; UI Coverage / UI Controls in this workbook | AM13: =IF(AND(ISNUMBER(J13),OR(AR13="INHERITED ESTIMATE",AR13="CONFIRMED ESTIMATE")),1,0) -> 1 | AO13: Recorded closed — inherited evidence | AP13: Inherited v2.22.0 intended record; no new runtime certification in this repair. | AR13: INHERITED ESTIMATE | AS13: =IF(AM13=1,J13,"") -> 6 | AT13: =IF(AND(AM13=1,ISNUMBER(R13)),R13,"") -> 0.9 | AU13: SOURCE CORROBORATES CLOSED GUARD | AV13: 0 | AW13: 0 | AX13: 0 | AY13: UNCONFIRMED REVIEW ESTIMATE - not P80 or elapsed | AZ13: No remaining original implementation; avoid counting unwired later engines against this completed guard. | BA13: Backend/tests/PlantProcess.Architecture.Tests/RelationshipConsumerBarrierTests.cs:12-44 — barrier semantics Backend/tests/PlantProcess.Architecture.Tests/RelationshipConsumerBarrierTests.cs:55-114 — consumer and forbidden-authority inventory | BB13: 14-Sep-2026 snapshot; later closure evidence separate; no live HEAD verification
A14: T-098 | B14: M2 | C14: P2 | D14: Relationship Browser page and path evidence | E14: Frontend | F14: Relationship model | G14: Very Important | H14: Build the C6 Relationship Browser from Chapter 3 4.4 with the ten-field page contract, showing declared relationships, their members, their paths and the evidence for each path. v2.10.2 CONTINUITY CORRECTION — complete the existing T-060 /relationships page in place. Do not create a second C6 surface. Preserve the route, layout and M1 control contract while replacing/extending the hidden relationship authority and path evidence. | I14: Open a relationship and confirm its members, cardinality and path are shown with evidence. Confirm an unpublished relationship is visibly distinct from a published one. Run the M1 C6 continuity snapshot before/after canonical cutover and prove no visible-contract regression. | J14: 12 | K14: Not Started | L14: Worker 2 | M14: T-095; T-096; T-097 | N14: T-107; T-109; T-128; T-183 | O14: M2: ~1 month from owner planning checkpoint; exact date not committed | P14: Release 1 MUST | Q14: Frontend/UI feature | R14: 2 | S14: M2-P2 | T14: Use the accepted M1 regression baseline; require empty index and clean owned paths, preserving unrelated user work. Then: T-060 M1 C6 surface + T-095 + T-096 + T-097. | U14: Own named UI/admin task end-to-end only after producer APIs/security are committed. | V14: Commit before downstream consumer starts; consumer must use the contract, not redesign producer-owned semantics. | W14: Day-1 Data Workbench — DB Link, Canvas, Jobs & OPC | X14: M2 P2 — Day-1 Data Workbench — DB Link, Canvas, Jobs & OPC. Release 1 is genuine early production / first-week customer work. | AA14: L5.2 | AB14: Permanent relationship model | AD14: Build | AE14: D1; D2; D5 | AF14: Core | AG14: R1 | AH14: Advances | AI14: =IF(Y14="","",Y14) | AJ14: Inherited baseline estimate | AK14: v4.11.1 | AL14: Chapters 3/4 v4.10.3 — MD + illustrated Word; UI Coverage / UI Controls in this workbook v2.23.0 — Use T-265 C6 relationship list/detail/member/cardinality/path-validation handoffs. Trace every applicable Chapter 3 control to a reachable UI variant and keep resolver behavior under its existing authority. | AM14: =IF(AND(ISNUMBER(J14),OR(AR14="INHERITED ESTIMATE",AR14="CONFIRMED ESTIMATE")),1,0) -> 1 | AO14: Not started — no completion claimed | AP14: Inherited v2.22.0 intended record; no new runtime certification in this repair. | AR14: INHERITED ESTIMATE | AS14: =IF(AM14=1,J14,"") -> 12 | AT14: =IF(AND(AM14=1,ISNUMBER(R14)),R14,"") -> 2 | AU14: REUSABLE BACKEND PRESENT; CANONICAL UI NOT LOCATED | AV14: 6 | AW14: 9 | AX14: 14 | AY14: UNCONFIRMED REVIEW ESTIMATE - not P80 or elapsed | AZ14: UI 4/6/9 + contract/negative tests 1/2/3 + targeted closure 1/1/2. Reuse all relationship producer work. | BA14: Backend/PlantProcess.Api/Endpoints/Relationships/RelationshipEndpoints.cs:21-92 — MapRelationshipEndpoints Backend/PlantProcess.Application/Relationships/RelationshipResolver.cs:62-113 — path results | BB14: 14-Sep-2026 snapshot; later closure evidence separate; no live HEAD verification
A15: T-099 | B15: M2 | C15: P2 | D15: Quarantine, part 1: the table, the reprocess API and the first eight PV classes | E15: Backend | F15: Quarantine | G15: Critical | H15: Chapter 3 4.5.14 specifies quarantine with fifteen typed PV codes. A repository search for projection_quarantine returns zero hits, so this does not exist. Build the table with its columns, the reprocess endpoint, and the first eight validation classes so a bad row is quarantined under a named code instead of corrupting the canonical layer or failing the whole batch. | I15: Craft one malformed input per implemented class and assert each is quarantined under the correct code, while the good rows in the same batch still project. | J15: 8 | K15: Done | L15: Worker 1 | M15: T-087; T-089; T-090 | N15: T-100; T-101; T-104; T-107; T-108; T-109; T-114; T-128; T-183; T-261 | O15: M2: ~1 month from owner planning checkpoint; exact date not committed | P15: Release 1 MUST | Q15: Backend/domain contract | R15: 1.2 | S15: M2-P2 | T15: CLOSED BASELINE — no new start gate and no re-execution implied. Preserve accepted closure and clean owned scope; reopen only on a concrete, separately recorded regression. Downstream consumes the frozen contract. | U15: Own canonical DB/backend/security/API/infra. No W2-owned UI/admin task files and no W3 ML/Assistant runtime. | V15: Commit before downstream consumer starts; consumer must use the contract, not redesign producer-owned semantics. | W15: Day-1 Data Workbench — DB Link, Canvas, Jobs & OPC | X15: M2 P2 — Day-1 Data Workbench — DB Link, Canvas, Jobs & OPC. Release 1 is genuine early production / first-week customer work. v2.22.1 — CLOSED GREEN / COMMITTED at ca02b40ea1b69050a45cb35a3e1d64f15b1f66af (parent 86e1b677212195f191697ecdca7e9441b3dbde33). Preserve this closure unless a concrete later regression is demonstrated. Gate O has one exact inherited DefinitionKind RED and canonical replay limitations remain; this is not Release-wide GREEN. | Y15: ca02b40ea1b69050a45cb35a3e1d64f15b1f66af | AA15: L2.3 | AB15: Canonical projection with validation, quarantine and reprocessing | AD15: Build | AE15: D3; D4; D5 | AF15: Core | AG15: R1 | AH15: Advances | AI15: =IF(Y15="","",Y15) -> ca02b40ea1b69050a45cb35a3e1d64f15b1f66af | AJ15: Inherited baseline estimate | AK15: v4.11.1 | AL15: Chapters 3/4 v4.10.3 — MD + illustrated Word; UI Coverage / UI Controls in this workbook | AM15: =IF(AND(ISNUMBER(J15),OR(AR15="INHERITED ESTIMATE",AR15="CONFIRMED ESTIMATE")),1,0) -> 1 | AO15: CLOSED GREEN / COMMITTED — FINAL TRANSCRIPT CORROBORATED | AP15: Final executed terminal transcript corroborates the owner-reported closure: 49/49 live,5/5 catalogue,19/19 owned;6/6 disposable DBs dropped;0survivors. GateO900=899passed+1exact inheritedDefinitionKindRED. Exact staging and one semantic commit proven. No live rerun performed in this review; no release-wideGREEN. Pasted text(20260914-134548).txt | lines430-450; final gatesQ/R; COMMITca02b40ea1b69050a45cb35a3e1d64f15b1f66af; PARENT86e1b677212195f191697ecdca7e9441b3dbde33; live49/49, catalogue5/5, owned19/19; not release-wideGREEN. | AQ15: 86e1b677212195f191697ecdca7e9441b3dbde33 | AR15: INHERITED ESTIMATE | AS15: =IF(AM15=1,J15,"") -> 8 | AT15: =IF(AND(AM15=1,ISNUMBER(R15)),R15,"") -> 1.2 | AU15: CLOSED SCOPE PRESERVED; SOURCE CORROBORATES | AV15: 0 | AW15: 0 | AX15: 0 | AY15: UNCONFIRMED REVIEW ESTIMATE - not P80 or elapsed | AZ15: T-099 CLOSED GREEN at ca02b40e; its inherited DefinitionKind RED is not a reason to budget a rewrite. | BA15: Backend/PlantProcess.Application/Integration/Services/Mapping/MappingRowProjector.cs:141-181 — MapMaterialUnitAsync Backend/PlantProcess.Api/Endpoints/Quarantine/QuarantineEndpoints.cs:8-33 — bounded reprocess surface Backend/database/scripts/841_genealogy_edge_weight_guard_topology_parity.sql:3-20 — narrow topology correction | BB15: 14-Sep-2026 snapshot; later closure evidence separate; no live HEAD verification
A16: T-100 | B16: M2 | C16: P2 | D16: Quarantine, part 2: the remaining seven PV classes and per-class tests | E16: Backend | F16: Quarantine | G16: Critical | H16: Implement the remaining seven validation classes and give every class its own test fixture, so the class set is provably complete against Chapter 3 4.5.14 rather than approximately complete. | I16: Distinct governed validation codes and fixture coverage must equal PV01..PV15 exactly. At least 15 classification fixtures; additional regression fixtures for an existing code are allowed. The completeness ratchet fails for an unproved enum member, not for duplicate display names or extra same-code tests. Live PostgreSQL proof executes every PV class; PV15 quarantine→cross-batch reference arrival→bounded reprocess passes; PV13 .60+.40=1.00 must not be quarantined. Exact live constraint, canonical migration order, disposable cleanup and exact single-commit closure required. | J16: 6 | K16: Done | L16: Worker 1 | M16: T-099 | N16: T-101; T-107; T-109; T-128; T-183; T-261 | O16: M2: ~1 month from owner planning checkpoint; exact date not committed | P16: Release 1 MUST | Q16: Backend/domain contract | R16: 0.9 | S16: M2-P2 | T16: RUNNER-1 CANDIDATE IS PRESENT; DO NOT RERUN RUNNER 1 or require a clean owned tree relative to HEAD. Resume from the exact handoff/postimages. Resume v1.0.1 is issued; success is not yet reported. Validate HEAD against the handoff and all owned postimage hashes before continuing. Expected parent supplied for closure is 4e0f1219ddbac3163bafe7ce510b62520683a77c; do not substitute the older T-099-only HEAD. If the exact gates fail, stop and report without manual resets, cleanup of unrelated work, or a fresh mutation pack. Worker 1/CENTRAL retains the execution lock through T-100 final commit; Worker 2 remains held. | U16: Worker 1 is the recorded execution owner; CENTRAL-assisted delivery. Preserve the existing T-100 candidate and unrelated dirty work. Exclusive shared repository mutation lock until T-100 is committed. | V16: Release Worker 2 only after T-100 final commit SHA and closure evidence. The successor consumes PROJECTION_* declaration, PV01..PV15 row-validation and JOB_EXEC_* runtime boundaries without duplication. | W16: Day-1 Data Workbench — DB Link, Canvas, Jobs & OPC | X16: M2 P2 — Day-1 Data Workbench — DB Link, Canvas, Jobs & OPC. Release 1 is genuine early production / first-week customer work. | Y16: e7ebc56341c371ce7b617585dce7f42d9a255f61 — T-100 complete remaining projection quarantine validation classes | Z16: 2026-09-15 | AA16: L2.3 | AB16: Canonical projection with validation, quarantine and reprocessing | AD16: Build | AE16: D3; D5 | AF16: Core | AG16: R1 | AH16: Advances | AI16: =IF(Y16="","",Y16) -> e7ebc56341c371ce7b617585dce7f42d9a255f61 — T-100 complete remaining projection quarantine validation classes | AJ16: SUPERSEDED: prior remaining LOW/BASE/HIGH 6/10/16 h included validators and unit tests now reported complete. Do not charge that implementation again. Closure-only remaining effort (harness recovery, live certification, cleanup, commit proof) is UNCONFIRMED, not zero; no invented elapsed time or calibrated P80. Preserve J/R as historical scope values, excluded from usable totals. | AK16: v4.11.1 | AL16: Chapters 3/4 v4.10.3 — MD + illustrated Word; UI Coverage / UI Controls in this workbook | AM16: =IF(AND(ISNUMBER(J16),OR(AR16="INHERITED ESTIMATE",AR16="CONFIRMED ESTIMATE")),1,0) -> 0 | AO16: CLOSED GREEN / COMMITTED | AP16: Final closure e7ebc56341c371ce7b617585dce7f42d9a255f61 supersedes the earlier Runner-1/live-harness-blocked state. Preserve closure absent a concrete regression. | AR16: CLOSED | AS16: =IF(AM16=1,J16,"") | AT16: =IF(AND(AM16=1,ISNUMBER(R16)),R16,"") | AU16: RUNNER 1 GREEN REPORTED / DB BUILD PASSED / LIVE HARNESS BLOCKED / UNCOMMITTED | AV16: UNCONFIRMED | AW16: UNCONFIRMED | AX16: UNCONFIRMED | AY16: UNCONFIRMED — closure-only remaining effort; prior 6/10/16 h superseded | AZ16: SUPERSEDED: prior remaining LOW/BASE/HIGH 6/10/16 h included validators and unit tests now reported complete. Do not charge that implementation again. Closure-only remaining effort (harness recovery, live certification, cleanup, commit proof) is UNCONFIRMED, not zero; no invented elapsed time or calibrated P80. Preserve J/R as historical scope values, excluded from usable totals. | BA16: Backend/PlantProcess.Api/Endpoints/Quarantine/QuarantineEndpoints.cs:8-13 — ownership Backend/PlantProcess.Application/Integration/Services/Mapping/MappingRowProjector.cs:630-690 — existing validation pattern Latest owner-supplied conversation update, received 15-Sep-2026; runner/host logs and script bytes were not independently inspected in this workbook update. This supersedes the earlier 14-Sep source-only T-100 estimate, not the frozen Design. USER-REPORTED: Runner1_1.0.5 SHA256 75B6C7DE78E0A677701BFEDF1EC70D4D1499C8168193B35D503CF26DF76DC7AA; Runner2_1.0.0 SHA256 9C29E607B52114DE680131A0FDE0F840D7CC56D3642FA09F73FD2AB5A7B3D493; Resume-ProjectionQuarantineCompletion_1.0.1.ps1 SHA256 5F6668258E8CAC517793B825AF712C8D8C9355F8CE9C0C69FBC5CAFCBDCB80E6. Names/hashes recorded as supplied, NOT locally verified. Script hashes are not commit IDs. | BB16: 14-Sep snapshot supplemented by latest 15-Sep user-reported runner progress; no current-HEAD or runner-byte verification
A17: T-101 | B17: M2 | C17: P2 | D17: Quarantine retry, reprocess and Mapping Health completion | E17: Frontend | F17: Quarantine | G17: Very Important | H17: Complete the C2 Mapping Health page against Chapter 3 4.4 C2: issues grouped by code, example rows, and Reprocess after the mapping is corrected. The M1 version delivered the shape; this delivers the full class set and the retry semantics. v2.22.0 — Quarantine inspection API/UI and schema-drift enforcement. Keep one drift event authority and reuse current schemas/compatibility safely. v2.22.1 — Own the M2 B4 Importing monitoring surface as well as C2 quarantine/Mapping Health: show each real batch status, failure code/reason, progress/counts, last committed cursor and its watermark range; drill into durable batch/run evidence. Use the existing canonical import/job contracts. T-106 owns terminal-status truth; T-108 owns durable cursor/replay; T-125 owns operational metrics/API observability. No second status or cursor authority and no advanced M3 recovery UI is introduced. | I17: Quarantine rows under three different codes, correct one mapping, reprocess, and confirm only the affected rows clear. The M1 continuity snapshot of this page must still match. v2.22.0 — GET quarantine list/detail filtered by code, dataset and batch with staging lineage/correction hint; tenant denial; remove mapped source object/field -> typed execution refusal and persisted C2 event; corrected reprocess uses declared version and records outcome. v2.22.1 — Drive B4 against a successful batch, a failed batch and a capped/partial batch; displayed outcome, counts, error and last committed cursor equal the canonical response after reload. A failed batch is never green; a retry/correction links to the same durable evidence. Tenant denial and empty/loading/failure states are asserted. Consume frozen T-106/T-108/T-125 response contracts for parallel UI work; final live integration is certified by T-247/T-150, not by a mock-only result. | J17: 12 | K17: Not Started | L17: Worker 2 | M17: T-099; T-100 | N17: T-107; T-109; T-128; T-183 | O17: M2: ~1 month from owner planning checkpoint; exact date not committed | P17: Release 1 MUST | Q17: Frontend/UI feature | R17: 2 | S17: M2-P2 | T17: GATE PROSE INCOMPLETE — original text ends with an ellipsis. Do not infer omitted conditions. Column M lists completion prerequisites; AN/Contract Handoffs lists contract-only prerequisites. Full task acceptance in column I still applies. Recover the omitted prose before claiming this gate fully reconciled. Preserved original fragment: Use the accepted M1 regression baseline; require empty index and clean owned paths, preserving unrelated user work. Then: T-061 final M1 API/page contract + T-099 + T-100 canonical quarantine impleme... | U17: Own named UI/admin task end-to-end only after producer APIs/security are committed. | V17: Commit before downstream consumer starts; consumer must use the contract, not redesign producer-owned semantics. | W17: Day-1 Data Workbench — DB Link, Canvas, Jobs & OPC | X17: M2 P2 — Day-1 Data Workbench — DB Link, Canvas, Jobs & OPC. Release 1 is genuine early production / first-week customer work. | AA17: L2.3 | AB17: Canonical projection with validation, quarantine and reprocessing | AC17: L1.6; L1.2; L1.7 | AD17: Build | AE17: D2; D5 | AF17: Core | AG17: R1 | AH17: Advances | AI17: =IF(Y17="","",Y17) | AJ17: RE-ESTIMATE REQUIRED — J/R retain the prior-scope figures for traceability; excluded from usable planning totals. New full-scope and remaining-work estimates are not supplied. | AK17: v4.11.1 | AL17: Chapters 3/4 v4.10.3 — MD + illustrated Word; UI Coverage / UI Controls in this workbook v2.23.0 — T-265 owns B4/C2/C3 visual depth. Implement its applicable batch outcome/error/committed cursor and catalogue-driven quarantine list/detail/refusal/reprocess states under the existing T-101 scope; all row actions and counts use canonical tenant-scoped payloads. Do not limit the renderer to eight PV codes. | AM17: =IF(AND(ISNUMBER(J17),OR(AR17="INHERITED ESTIMATE",AR17="CONFIRMED ESTIMATE")),1,0) -> 0 | AO17: Not started — no completion claimed | AP17: Inherited v2.22.0 intended record; no new runtime certification in this repair. | AR17: RE-ESTIMATE REQUIRED | AS17: =IF(AM17=1,J17,"") | AT17: =IF(AND(AM17=1,ISNUMBER(R17)),R17,"") | AU17: PARTIAL REUSE; CURRENT EXPANDED SCOPE OPEN | AV17: 12 | AW17: 18 | AX17: 28 | AY17: UNCONFIRMED REVIEW ESTIMATE - not P80 or elapsed | AZ17: Read API/filter/detail 3/4/6 + B4/C2/C3 UI 4/6/10 + drift/retry integration 3/5/8 + tests/closure 2/3/4. | BA17: Backend/PlantProcess.Api/Endpoints/Quarantine/QuarantineEndpoints.cs:8-33 — MapQuarantineEndpoints Backend/PlantProcess.Application/Integration/Services/Staging/StagingRecordService.cs:85-110 — durable staging identity | BB17: 14-Sep-2026 snapshot; later closure evidence separate; no live HEAD verification
A18: T-102 | B18: M2 | C18: P2 | D18: Identity resolution across sources | E18: Backend | F18: Genealogy | G18: Very Important | H18: Harden material identity resolution using material_aliases so the same physical material arriving under two different source identifiers becomes one canonical unit. The schema already supports this: material_units carries a unique key on (site_id, material_code) plus a filtered unique on (source_system, source_record_id), which makes projection idempotent without forbidding rows that have no source identity. | I18: Import the same material under two different source identifiers and confirm one canonical unit results with both aliases recorded. Re-run the import and confirm no duplicate appears. | J18: 8 | K18: Not Started | L18: Worker 1 | M18: T-087; T-095 | N18: T-103; T-107; T-109; T-128; T-183 | O18: M2: ~1 month from owner planning checkpoint; exact date not committed | P18: Release 1 MUST | Q18: Backend/domain contract | R18: 1.2 | S18: M2-P2 | T18: Use the accepted M1 regression baseline; require empty index and clean owned paths, preserving unrelated user work. Then: T-087 canonical plant schema + T-095 relationship/material identity authority. | U18: Own canonical DB/backend/security/API/infra. No W2-owned UI/admin task files and no W3 ML/Assistant runtime. | V18: Commit before downstream consumer starts; consumer must use the contract, not redesign producer-owned semantics. | W18: Day-1 Data Workbench — DB Link, Canvas, Jobs & OPC | X18: M2 P2 — Day-1 Data Workbench — DB Link, Canvas, Jobs & OPC. Release 1 is genuine early production / first-week customer work. | AA18: L2.4 | AB18: Genealogy resolution and attribution | AD18: Build | AE18: D3; D5 | AF18: Core | AG18: R1 | AH18: Advances | AI18: =IF(Y18="","",Y18) | AJ18: Inherited baseline estimate | AK18: v4.11.1 | AL18: Chapters 3/4 v4.10.3 — MD + illustrated Word; UI Coverage / UI Controls in this workbook | AM18: =IF(AND(ISNUMBER(J18),OR(AR18="INHERITED ESTIMATE",AR18="CONFIRMED ESTIMATE")),1,0) -> 1 | AO18: Not started — no completion claimed | AP18: Inherited v2.22.0 intended record; no new runtime certification in this repair. | AR18: INHERITED ESTIMATE | AS18: =IF(AM18=1,J18,"") -> 8 | AT18: =IF(AND(AM18=1,ISNUMBER(R18)),R18,"") -> 1.2 | AU18: EXISTING ALIAS FOUNDATION; IDENTITY-SAFETY GAP | AV18: 4 | AW18: 7 | AX18: 12 | AY18: UNCONFIRMED REVIEW ESTIMATE - not P80 or elapsed | AZ18: Scope-safe lookup/merge 2/4/7 + ambiguity/idempotency tests 1/2/4 + closure 1/1/1. | BA18: Backend/PlantProcess.Application/Integration/Services/Mapping/MappingRowProjector.cs:244-264 — MapMaterialAliasAsync Backend/PlantProcess.Application/Integration/Services/Mapping/MappingRowProjector.cs:721-744 — ResolveMaterialIdAsync Backend/PlantProcess.Infrastructure/Persistence/Configurations/Materials/MaterialAliasConfiguration.cs:27-36 — composite unique Backend/PlantProcess.Infrastructure/Persistence/Configurations/Materials/MaterialUnitConfiguration.cs:43-47 — site/source uniqueness | BB18: 14-Sep-2026 snapshot; later closure evidence separate; no live HEAD verification
A19: T-103 | B19: M2 | C19: P2 | D19: Genealogy bidirectional walk hardening and weight proof | E19: Backend | F19: Genealogy | G19: Very Important | H19: Confirm the genealogy layer walks both directions on the customer's own keys and that attribution weights are enforced to sum to exactly 1.0 per child by the database trigger on genealogy_edges.contribution_weight numeric(9,6). v2.22.0 — Retain genealogy semantics and add explicit cyclic/self-edge protection at service and database boundaries. | I19: Walk a chain backward and forward and confirm the same edges are traversed. Attempt an insert whose weights sum to 0.99 inside a transaction and confirm the trigger rejects it, then roll back. v2.22.0 — Negative controls: self-edge, two-node and longer cycles refused; ordered weighted genealogy valid paths remain accepted; no silent deletion of lineage. | J19: 6 | K19: Not Started | L19: Worker 1 | M19: T-095; T-102 | N19: T-107; T-109; T-128; T-183 | O19: M2: ~1 month from owner planning checkpoint; exact date not committed | P19: Release 1 MUST | Q19: Backend/domain contract | R19: 0.9 | S19: M2-P2 | T19: Use the accepted M1 regression baseline; require empty index and clean owned paths, preserving unrelated user work. Then: T-095 + T-102 canonical relationship/identity authority. | U19: Own canonical DB/backend/security/API/infra. No W2-owned UI/admin task files and no W3 ML/Assistant runtime. | V19: Commit before downstream consumer starts; consumer must use the contract, not redesign producer-owned semantics. | W19: Day-1 Data Workbench — DB Link, Canvas, Jobs & OPC | X19: M2 P2 — Day-1 Data Workbench — DB Link, Canvas, Jobs & OPC. Release 1 is genuine early production / first-week customer work. | AA19: L2.4 | AB19: Genealogy resolution and attribution | AD19: Harden | AE19: D3; D5 | AF19: Core | AG19: R1 | AH19: Advances | AI19: =IF(Y19="","",Y19) | AJ19: RE-ESTIMATE REQUIRED — J/R retain the prior-scope figures for traceability; excluded from usable planning totals. New full-scope and remaining-work estimates are not supplied. | AK19: v4.11.1 | AL19: Chapters 3/4 v4.10.3 — MD + illustrated Word; UI Coverage / UI Controls in this workbook | AM19: =IF(AND(ISNUMBER(J19),OR(AR19="INHERITED ESTIMATE",AR19="CONFIRMED ESTIMATE")),1,0) -> 0 | AO19: Not started — no completion claimed | AP19: Inherited v2.22.0 intended record; no new runtime certification in this repair. | AR19: RE-ESTIMATE REQUIRED | AS19: =IF(AM19=1,J19,"") | AT19: =IF(AND(AM19=1,ISNUMBER(R19)),R19,"") | AU19: SUBSTANTIAL FOUNDATION; ACCEPTANCE-CONTRACT MISMATCH | AV19: 4 | AW19: 6 | AX19: 10 | AY19: UNCONFIRMED REVIEW ESTIMATE - not P80 or elapsed | AZ19: Weight-contract correction 1/2/3 + direct-DB/traversal negatives 2/3/5 + closure 1/1/2. Existing cycle logic is not new work. | BA19: Backend/PlantProcess.Application/Services/Materials/GenealogyService.cs:27-69 — CreateEdgeAsync Backend/PlantProcess.Application/Services/Materials/GenealogyService.cs:95-124 — WouldCreateCycleAsync Backend/database/scripts/841_genealogy_edge_weight_guard_topology_parity.sql:55-68 — deferred weight check | BB19: 14-Sep-2026 snapshot; later closure evidence separate; no live HEAD verification
A20: T-104 | B20: M2 | C20: P2 | D20: Projection provenance, exact-version stamping and idempotent reprojection | E20: Backend | F20: Projection | G20: Critical | H20: Complete the DF5 contract: source-shaped staging projects into the canonical plant model through the customer-authored versioned mapping, and every projected row records the mapping version that produced it. v2.22.0 — Absorbs T-105: Make reprojection idempotent and add the regression suite: reprojecting the same batch must not duplicate rows, and rolling a mapping back to a previous version must produce the earlier result exactly. T-261 owns the executor. This task owns canonical row-level definition/version provenance and replay effects, using that executor; it does not implement a competing MappingDefinition runtime. | I20: Project a batch, change the mapping version, project again, and confirm each row records the version that produced it. No row may carry a null mapping version. v2.22.0 — Reproject the same batch three times and confirm row counts are unchanged. Roll a mapping back and confirm the canonical output matches the earlier snapshot byte for byte. Assert exact resolved Transformation version/hash per run and row, tenant/dataset/batch source lineage, no duplicate accepted effect and byte-identical deterministic business output on rollback. Clock/run metadata is compared separately from business-result equivalence. | J20: 14 | K20: Not Started | L20: Worker 1 | M20: T-090; T-095; T-099; T-261 | N20: T-107; T-108; T-109; T-128; T-183; T-247 | O20: M2: ~1 month from owner planning checkpoint; exact date not committed | P20: Release 1 MUST | Q20: Backend/domain contract | R20: 1.2 | S20: M2-P2 | T20: GATE PROSE INCOMPLETE — original text ends with an ellipsis. Do not infer omitted conditions. Column M lists completion prerequisites; AN/Contract Handoffs lists contract-only prerequisites. Full task acceptance in column I still applies. Recover the omitted prose before claiming this gate fully reconciled. Preserved original fragment: Use the accepted M1 regression baseline; require empty index and clean owned paths, preserving unrelated user work. Then: T-090 canonical versioned mapping definitions + T-095 relationship authority ... | U20: Own canonical DB/backend/security/API/infra. No W2-owned UI/admin task files and no W3 ML/Assistant runtime. | V20: Commit before downstream consumer starts; consumer must use the contract, not redesign producer-owned semantics. | W20: Day-1 Data Workbench — DB Link, Canvas, Jobs & OPC | X20: M2 P2 — Day-1 Data Workbench — DB Link, Canvas, Jobs & OPC. Release 1 is genuine early production / first-week customer work. | AA20: L2.3 | AB20: Canonical projection with validation, quarantine and reprocessing | AC20: L2.5 | AD20: Build | AE20: D3; D5 | AF20: Core | AG20: R1 | AH20: Advances | AI20: =IF(Y20="","",Y20) | AJ20: RE-ESTIMATE REQUIRED — J/R retain the prior-scope figures for traceability; excluded from usable planning totals. New full-scope and remaining-work estimates are not supplied. | AK20: v4.11.1 | AL20: Chapters 3/4 v4.10.3 — MD + illustrated Word; UI Coverage / UI Controls in this workbook | AM20: =IF(AND(ISNUMBER(J20),OR(AR20="INHERITED ESTIMATE",AR20="CONFIRMED ESTIMATE")),1,0) -> 0 | AO20: Not started — no completion claimed | AP20: Inherited v2.22.0 intended record; no new runtime certification in this repair. | AR20: RE-ESTIMATE REQUIRED | AS20: =IF(AM20=1,J20,"") | AT20: =IF(AND(AM20=1,ISNUMBER(R20)),R20,"") | AU20: REPLAY FOUNDATION IS NOT VERSIONED REPROJECTION | AV20: 8 | AW20: 14 | AX20: 22 | AY20: UNCONFIRMED REVIEW ESTIMATE - not P80 or elapsed | AZ20: Row-version/provenance integration 3/5/8 + replay/rollback semantics 3/6/10 + negative tests/closure 2/3/4. | BA20: Backend/PlantProcess.Application/Integration/Services/Mapping/MappingRowProjector.cs:168-181 — existing-row skip Backend/PlantProcess.Application/Integration/Services/Jobs/JobRunOrchestratorService.cs:210-249 — ResolveDeclaredTargetAsync | BB20: 14-Sep-2026 snapshot; later closure evidence separate; no live HEAD verification
A21: T-106 | B21: M2 | C21: P2 | D21: Canonical jobs: target/version, scheduling, dependencies, cancellation and outcome truth | E21: Backend | F21: Jobs | G21: Critical | H21: Build on the M1 target_definition_id work: add the full version policy (pinned or current published), the job dependency graph, and cycle validation. v2.10.2 BOUNDARY CORRECTION — the pinned/current-published PUBLIC semantics are already frozen by T-064. This task performs canonical physical convergence: job_definitions FK -> definition_store(id) ON DELETE RESTRICT, target-version policy CHECKs/target-surface trigger against the canonical store, target_parameters persistence, plus job_dependencies DAG/cycle validation. Do not redesign T-064's visible contract. v2.20.0 EXECUTION-PLANE EXPANSION — replace the central job-type switch as the authority for manual execution. Each executable job family registers an executor capability through DI/registry metadata: supported/unsupported state, target definition kind, version policy, input contract and run capability. A new executor family must be addable without editing a central switch. Unsupported families refuse at definition/save or capability discovery with a typed reason rather than surviving until RunNow. v2.20.0 LAYER-B PLACEMENT RULING — scheduling count, repetition, iteration windows and control flow belong to governed Job orchestration. Do not add new FOR/WHILE-style board execution semantics. Existing T-242 saved definitions remain readable through compatibility handling, but new orchestration authority is the Job plane. v2.22.0 — Deliver one canonical Job authority for target/version/capability, schedule grammar and occurrence identity, due scheduling, dependency resolution, cooperative cancellation and terminal-status truth. Implement Design v4.10.3 Ch4 5.3.2a / 5.3.6. The scheduler produces due requests; existing admission admits them. T-107 owns bounded pools; T-261 owns the actual Transformation executor. Keep these as separately testable sub-deliverables inside T-106 rather than additional task IDs. An executor supplied by tests proves orchestration before T-261 is commissioned, so T-106 must not depend on T-261 or T-107 closure. | I21: Declare a three-job chain, run it, and confirm order. Introduce a cycle and confirm it is refused at save time with a named code. Enumerate every job family exposed by the product and prove each is either backed by a registered executor or explicitly unavailable by typed reason. Register a test executor through DI and prove it runs without editing the orchestrator switch. The current 'no manual executor'/'not implemented yet' runtime fall-through is no longer reachable for an advertised executable job. Newly authored execution schedules express repetition/window/control-flow in the Job contract rather than creating a new Canvas FOR/WHILE node. A compatibility fixture for an existing T-242 loop definition remains readable and produces an explicit compatibility interpretation rather than data loss. v2.22.0 — Prove canonical schedule parsing/normalisation and UI next-occurrence parity; UTC/timezone and DST gap/fold rules; one atomic admission per tenant/job/schedule-revision/occurrence under racing workers; restart/missed ticks; invalid or unsupported schedule typed refusal; paused state persists. Cancel API is tenant/role-scoped, idempotent, reaches executor and records exactly one final outcome. Cancellation request is not completion acknowledgement. Define all-success, mixed, all-failed, no-work, cancelled and interrupted outcomes; one failed import batch cannot be hidden in an Ok run in either manual or worker path. Current-cycle and earlier-success reuse follow explicit allow_stale_reuse and age ceiling, with timestamps, policy and watermark in job_run_dependencies. Trigger-fires, wrong-kind/surface and actual orchestration evidence use disposable DB fixtures. Keep existing historical closure evidence; certify newly widened obligations separately. | J21: 12 | K21: Done | L21: Worker 3 | M21: T-064; T-089; T-090; T-252 | N21: T-107; T-122; T-125; T-245; T-261; T-263; T-275 | O21: M2: ~1 month from owner planning checkpoint; exact date not committed | P21: Release 1 MUST | Q21: Backend/domain contract | S21: M2-P2 | T21: Consume accepted producer contracts; remaining dependencies: T-064; T-089; T-090; T-252. No private scheduler/definition authority. Source-present is not closure proof. | U21: Own T-106/T-107/T-109 only after W1 producer contracts; no schema authority rewrites. | V21: Commit before downstream consumer starts; consumer must use the contract, not redesign producer-owned semantics. | W21: Day-1 Data Workbench — DB Link, Canvas, Jobs & OPC | X21: v2.22.0 owner-approved scope and release disposition; original evidence remains in change log/archive. 17-Sep: baseline commits remain frozen; widened/current executor-freshness-cancellation acceptance remains open. 17-Sep final reconciliation: T-106 is closed/released. Do not reopen it for Transformation executor commissioning; T-261 consumes the frozen T-106 scheduling/target/cancellation seams. | Y21: 8b3eb5c89352a2779d87f9205700f19e7c9b3e25; a5451dbaf6b55183fe65e2c626c49fdef85bd986; a0a5618d — final released short anchor | Z21: 2026-09-15 | AA21: L2.6 | AB21: Job definition, scheduling, execution monitor and history | AC21: L2.5; L2.7; L1.7 | AD21: Build | AE21: D3; D4; D5 | AF21: Core | AG21: R1 | AH21: Advances | AI21: =IF(Y21="","",Y21) -> 8b3eb5c89352a2779d87f9205700f19e7c9b3e25; a5451dbaf6b55183fe65e2c626c49fdef85bd986; a0a5618d — final released short anchor | AJ21: RE-ESTIMATE REQUIRED — prior Hours/P80 preserved in Estimate Review; not zero remaining effort. | AK21: v4.11.1 | AL21: Chapters 3/4 v4.10.3 — MD + illustrated Word; UI Coverage / UI Controls in this workbook | AM21: =IF(AND(ISNUMBER(J21),OR(AR21="INHERITED ESTIMATE",AR21="CONFIRMED ESTIMATE")),1,0) -> 1 | AO21: CLOSED GREEN / RELEASED — widened integration accepted; executor commissioning belongs to T-261 | AP21: Latest recovered execution evidence records HEAD a0a5618d as the released T-106 after the widened integration path. The remaining registered Transformation executor acceptance is T-261 scope, not a hidden T-106 remainder. Full SHA for a0a5618d is not recovered here; short anchor is preserved honestly. | AR21: INHERITED ESTIMATE | AS21: =IF(AM21=1,J21,"") -> 12 | AT21: =IF(AND(AM21=1,ISNUMBER(R21)),R21,"") | AU21: ORIGINAL CONTRACT CLOSED; EXPANDED RUNTIME OBLIGATIONS OPEN | AV21: 0 | AW21: 0 | AX21: 0 | AY21: UNCONFIRMED REVIEW ESTIMATE - not P80 or elapsed | AZ21: Schedule/parser/due-work 8/12/18 + freshness/outcome policy 4/6/10 + cancellation consumer integration 2/4/6 + targeted service/DB tests and runner 4/6/10. Original completed contracts excluded. | BA21: Backend/PlantProcess.Application/Integration/Services/Jobs/JobDefinitionService.cs:275-297 — schedule validation Backend/PlantProcess.Workers/Worker.cs:72-108 — fixed cadence loops Backend/PlantProcess.Application/Jobs/Dependencies/JobDependencyEvaluator.cs:33-39 — no age/tolerance input Backend/PlantProcess.Application/Jobs/Dependencies/JobDependencyEvaluator.cs:85-91 — Satisfied result Backend/PlantProcess.Application/Integration/Services/Jobs/JobRuntimeService.cs:127-146 — terminal-state switch Backend/PlantProcess.Application/Integration/Services/Jobs/JobRunOrchestratorService.cs:262-276 — import result mapping | BB21: 14-Sep-2026 snapshot; later closure evidence separate; no live HEAD verification
A22: T-107 | B22: M2 | C22: P2 | D22: Dual-predicate admission, bounded worker pools and the three ML execution lanes | E22: Backend | F22: Jobs | G22: Critical | H22: Replace the old single weighted-pool assumption with the frozen resource contract. Each lane has max_concurrency and resource_capacity; admission requires both running_count < max_concurrency and sum(compute_weight)+candidate <= resource_capacity. The logical ml class resolves to ml.training, ml.batch_scoring and ml.online_scoring. Online capacity is hard-reserved and unavailable to training or batch. Keep this platform-level scheduler generic; Worker 3 supplies the ML job classes and later integration tests, but this task must not wire any new AI runtime into the M1 presentation path. v2.10.2 MEASUREMENT RULING — this task implements the configurable dual-predicate admission mechanism and three-lane isolation. Test values may prove satisfiability, but no max_concurrency/resource_capacity/reserved fraction is a production-selected value here. Site values remain benchmark outputs owned by T-155/T-159. v2.20.0 BOUNDED-PARALLELISM EXPANSION — the same admission authority owns bounded parallel execution for eligible non-ML job families. The current serial import-loop behavior is replaced by queue/admission scheduling that respects both max_concurrency and resource_capacity. Do not implement unbounded Task.WhenAll/Parallel.ForEach. Per-family limits, cancellation, fair queueing and hard online reservation remain explicit. | I22: Prove a declared job can be admitted under a satisfiable configuration and a too-heavy job is refused by name. Saturate training and batch and prove an online-scoring job still admits inside its reservation. Prove batch never enters the online lane and the same compute_weight is never used as a concurrency count. Existing import/projection/analysis/report behaviour remains green. The acceptance report labels resource values as TEST_CONFIGURATION unless they come from the named production/site benchmark manifest. No code default is presented as the final capacity decision. Run multiple slow import/analysis jobs and prove concurrency rises above one only up to the configured bound, then queues. Queueing must not increase memory without bound; cancellation frees capacity; a too-heavy job remains queued/refused by named policy. A negative-control implementation using unbounded fan-out must make the gate red. | J22: 16 | K22: In Progress | L22: Worker 3 | M22: T-095; T-096; T-097; T-098; T-099; T-100; T-101; T-102; T-103; T-104; T-106 | N22: T-122; T-125; T-141; T-187; T-192; T-275 | O22: M2: ~1 month from owner planning checkpoint; exact date not committed | P22: Release 1 MUST | Q22: Backend/domain contract | R22: 1.8 | S22: M2-P2 | T22: GATE PROSE INCOMPLETE — original text ends with an ellipsis. Do not infer omitted conditions. Column M lists completion prerequisites; AN/Contract Handoffs lists contract-only prerequisites. Full task acceptance in column I still applies. Recover the omitted prose before claiming this gate fully reconciled. Preserved original fragment: Use the accepted M1 regression baseline; require empty index and clean owned paths, preserving unrelated user work. Then: T-106 canonical job contract + T-095..T-105 canonical data/relationship path;... | U22: Own T-106/T-107/T-109 only after W1 producer contracts; no schema authority rewrites. | V22: Commit before downstream consumer starts; consumer must use the contract, not redesign producer-owned semantics. | W22: Day-1 Data Workbench — DB Link, Canvas, Jobs & OPC | X22: M2 P2 — Day-1 Data Workbench — DB Link, Canvas, Jobs & OPC. Release 1 is genuine early production / first-week customer work. | AA22: L8.4 | AB22: Execution lanes, admission and resource isolation | AC22: L2.6 | AD22: Build | AE22: D3; D5 | AF22: Core | AG22: R1 | AH22: Advances | AI22: =IF(Y22="","",Y22) | AJ22: Inherited baseline estimate | AK22: v4.11.1 | AL22: Chapters 3/4 v4.10.3 — MD + illustrated Word; UI Coverage / UI Controls in this workbook | AM22: =IF(AND(ISNUMBER(J22),OR(AR22="INHERITED ESTIMATE",AR22="CONFIRMED ESTIMATE")),1,0) -> 1 | AO22: Not started — no completion claimed | AP22: Inherited v2.22.0 intended record; no new runtime certification in this repair. | AR22: INHERITED ESTIMATE | AS22: =IF(AM22=1,J22,"") -> 16 | AT22: =IF(AND(AM22=1,ISNUMBER(R22)),R22,"") -> 1.8 | AU22: TIMERS EXIST; GOVERNED JOB POOLS NOT ESTABLISHED | AV22: 12 | AW22: 20 | AX22: 32 | AY22: UNCONFIRMED REVIEW ESTIMATE - not P80 or elapsed | AZ22: Pool/admission implementation 6/10/16 + lane/worker integration 3/5/8 + saturation/cancel/closure tests 3/5/8. | BA22: Backend/PlantProcess.Workers/Worker.cs:72-108 — ExecuteAsync cadence Backend/PlantProcess.Application/Jobs/Execution/JobExecutionCapability.cs:76-107 — family capability vs capacity | BB22: 14-Sep-2026 snapshot; later closure evidence separate; no live HEAD verification
A23: T-108 | B23: M2 | C23: P2 | D23: End-to-end delta correctness: source cursor, load protection, replay and projection watermark | E23: Backend | F23: Delta propagation | G23: Critical | H23: Today only import is incremental. Chapter 4 5.3.9 requires every downstream stage to be delta-scoped. Add the stage_watermarks table and make canonical projection delta-scoped against it. The arithmetic that justifies this: a naive full scan for one Pro-tier customer is 481 TB per day, while delta-scoped is 5 to 20 GB, a ratio of 24,000 to 1. v2.22.0 — Own acquisition-to-projection delta correctness: typed total-order cursor with source-stable tie-break for non-unique watermarks; one invariant provider-native ordering contract; durable cursor/staging/receipt atomicity; replay-safe accepted effects; per-dataset/profile budget resolution constrained by installation/source ceilings; apply pre-read budget/window/rate/concurrency/timeout checks on incremental as well as preview reads. Do not replace a stricter parent ceiling with a looser child override. Source native ordering and source-version identity govern legitimate updates. Retain existing stage-watermark and delta-projection duties; T-110 owns the advanced M3 parallel chunk engine. | I23: Change one source row and confirm projection processes a bounded delta rather than a full scan, evidenced by rows-scanned telemetry. v2.22.0 — Use more equal-watermark records than three page limits, numeric/timestamp/composite cursors, declared key changes, source updates, no change, de-DE/en-US serialization, crash before and after commit and racing workers. Prove no missed rows/no duplicate accepted source revision, and checkpoint advanced only with durable effects. Over-budget incremental reads issue no source query. Replay of a partially failed import preserves legitimate later versions of the same business key. One changed source row produces bounded downstream work with recorded counts. | K23: Not Started | L23: Worker 1 | M23: T-099; T-104 | N23: T-109; T-110; T-247; T-271 | O23: M2: ~1 month from owner planning checkpoint; exact date not committed | P23: Release 1 MUST | Q23: Backend/domain contract | S23: M2-P2 | T23: Consume accepted producer contracts; remaining dependencies: T-099; T-104. No private scheduler/definition authority. Source-present is not closure proof. | U23: Own canonical DB/backend/security/API/infra. No W2-owned UI/admin task files and no W3 ML/Assistant runtime. | V23: Commit before downstream consumer starts; consumer must use the contract, not redesign producer-owned semantics. | W23: Day-1 Data Workbench — DB Link, Canvas, Jobs & OPC | X23: v2.22.0 owner-approved scope and release disposition; original evidence remains in change log/archive. | AA23: L2.8 | AB23: Delta propagation law | AC23: L1.3; L1.1; L1.7 | AD23: Build | AE23: D3; D4; D5 | AF23: Core | AG23: R1 | AH23: Advances | AI23: =IF(Y23="","",Y23) | AJ23: RE-ESTIMATE REQUIRED — prior Hours/P80 preserved in Estimate Review; not zero remaining effort. | AK23: v4.11.1 | AL23: Chapters 3/4 v4.10.3 — MD + illustrated Word; UI Coverage / UI Controls in this workbook | AM23: =IF(AND(ISNUMBER(J23),OR(AR23="INHERITED ESTIMATE",AR23="CONFIRMED ESTIMATE")),1,0) -> 0 | AO23: Not started — no completion claimed | AP23: Inherited v2.22.0 intended record; no new runtime certification in this repair. | AR23: RE-ESTIMATE REQUIRED | AS23: =IF(AM23=1,J23,"") | AT23: =IF(AND(AM23=1,ISNUMBER(R23)),R23,"") | AU23: IMPLEMENTED DELTA FOUNDATION WITH CONFIRMED CORRECTNESS GAPS | AV23: 22 | AW23: 34 | AX23: 52 | AY23: UNCONFIRMED REVIEW ESTIMATE - not P80 or elapsed | AZ23: Tuple contract+reader adaptations 8/12/18 + budget enforcement 4/6/9 + durable staging/replay+projection token 5/8/13 + adverse-boundary tests/closure 5/8/12. | BA23: Backend/PlantProcess.Application/Integration/Services/SourceSystems/DeltaImportExecutionService.cs:120-151 — read-path selection Backend/PlantProcess.Application/Integration/Services/SourceSystems/DeltaImportExecutionService.cs:173-205 — row/cursor handling Backend/PlantProcess.Application/Integration/Services/SourceSystems/DeltaImportExecutionService.cs:236-280 — source identity and MaxCursor Backend/PlantProcess.Infrastructure/Connectors/PostgreSql/PostgreSqlConnector.cs:181-206 — scalar LIMIT query Backend/PlantProcess.Application/Integration/Protection/ThrottlingDataSourceReader.cs:36-70 — unequal protection Backend/PlantProcess.Infrastructure/Integration/Protection/OptionsSourceLoadBudgetProvider.cs:21-24 — global budget Backend/PlantProcess.Infrastructure/Persistence/Configurations/Integration/StagingRecordConfiguration.cs:31-42 — existing within-batch uniqueness Backend/tests/PlantProcess.Api.IntegrationTests/Import/DeltaImportResumabilityTests.cs:58-73 — current weak continuation assertions | BB23: 14-Sep-2026 snapshot; later closure evidence separate; no live HEAD verification
A24: T-109 | B24: M2 | C24: P2 | D24: Delta-scoped feature refresh and analysis, with telemetry and ML hand-off | E24: Backend | F24: Delta propagation | G24: Critical | H24: Extend the stage-watermark mechanism into the canonical feature refresh and analysis path. The task owns delta discovery, dirty-feature identification and telemetry only; training must never read feature_store directly. Expose a bounded changed-population contract that Worker 3's Snapshot Materialiser consumes later. Do not add temporary M1/presentation schema dependencies. | I24: Insert one bounded delta and prove only affected feature rows and analyses are recomputed. Record rows scanned, rows changed and Scan Amplification. Assert no training/encoding component is reachable from this task and the output contract contains no customer table name. | J24: 6 | K24: Not Started | L24: Worker 3 | M24: T-095; T-096; T-097; T-098; T-099; T-100; T-101; T-102; T-103; T-104; T-108 | N24: T-110; T-136; T-187 | O24: M2: ~1 month from owner planning checkpoint; exact date not committed | P24: Release 1 MUST | Q24: Backend/domain contract | R24: 0.9 | S24: M2-P2 | T24: Use the accepted M1 regression baseline; require empty index and clean owned paths, preserving unrelated user work. Then: T-095..T-105; T-108 | U24: Own T-106/T-107/T-109 only after W1 producer contracts; no schema authority rewrites. | V24: Commit before downstream consumer starts; consumer must use the contract, not redesign producer-owned semantics. | W24: Day-1 Data Workbench — DB Link, Canvas, Jobs & OPC | X24: M2 P2 — Day-1 Data Workbench — DB Link, Canvas, Jobs & OPC. Release 1 is genuine early production / first-week customer work. | AA24: L2.8 | AB24: Delta propagation law | AC24: L4.3 | AD24: Build | AE24: D3; D5 | AF24: Core | AG24: R1 | AH24: Advances | AI24: =IF(Y24="","",Y24) | AJ24: Inherited baseline estimate | AK24: v4.11.1 | AL24: Chapters 3/4 v4.10.3 — MD + illustrated Word; UI Coverage / UI Controls in this workbook | AM24: =IF(AND(ISNUMBER(J24),OR(AR24="INHERITED ESTIMATE",AR24="CONFIRMED ESTIMATE")),1,0) -> 1 | AO24: Not started — no completion claimed | AP24: Inherited v2.22.0 intended record; no new runtime certification in this repair. | AR24: INHERITED ESTIMATE | AS24: =IF(AM24=1,J24,"") -> 6 | AT24: =IF(AND(AM24=1,ISNUMBER(R24)),R24,"") -> 0.9 | AU24: REUSABLE CALCULATION FOUNDATION; DELTA CONSUMER NOT PROVEN | AV24: 6 | AW24: 10 | AX24: 18 | AY24: UNCONFIRMED REVIEW ESTIMATE - not P80 or elapsed | AZ24: Scope resolution/integration 3/5/9 + telemetry/handoff 1/2/4 + idempotent/late-data tests 2/3/5. | BA24: Backend/PlantProcess.Application/Integration/Services/SourceSystems/DeltaImportExecutionService.cs:173-217 — available source delta boundary Backend/PlantProcess.Application/Relationships/RelationshipResolver.cs:85-113 — governed automated path | BB24: 14-Sep-2026 snapshot; later closure evidence separate; no live HEAD verification
A25: T-110 | B25: M3 | C25: P1 | D25: Bounded delta execution: chunks, resume, deterministic merge and scan budgets | E25: Backend | F25: Delta propagation | G25: Critical | H25: Implement Chapter 4 5.3.9.6a: bounded chunks with receipts, checkpoint and resume after interruption, and a deterministic merge so a resumed run produces the same result as an uninterrupted one. v2.22.0 — Absorb T-111 runtime scan-budget enforcement: bounded row/byte chunks, receipts, checkpoint/resume, deterministic merge, explicit scan mode, cumulative scan budget and abort/finding. T-155 owns calibrated constants/Scan Amplification bands; T-159 owns C1-C4 certification. M2 T-108/T-109 must still deliver safe bounded delta execution and replay; moving advanced chunk machinery does not waive Day-1 source limits or safe cancellation. | I25: Kill a running job at 60 percent, restart it, and confirm the final result is byte-identical to an uninterrupted run over the same input. v2.22.0 — Record a baseline, then deliberately remove a delta scope and confirm the gate goes red. Restore and confirm green. Prove chunk parallelism 1 vs 8 business output parity; abort above cumulative scan budget; uncommitted chunk rolls back; resumes exactly from committed receipts; preserved input/version pins. | J25: 24 | K25: Not Started | L25: Worker 1 | M25: T-108; T-109 | N25: T-249 | O25: M3: 45 days after M2 completion | P25: Release 2 MUST | Q25: Backend/domain contract | R25: 1.8 | S25: M3-P1 | T25: Consume accepted producer contracts; remaining dependencies: T-108; T-109. No private scheduler/definition authority. Source-present is not closure proof. | U25: Own canonical DB/backend/security/API/infra. No W2-owned UI/admin task files and no W3 ML/Assistant runtime. | V25: Commit before downstream consumer starts; consumer must use the contract, not redesign producer-owned semantics. | W25: Scale & OT Resilience | X25: v2.22.0 owner-approved scope and release disposition; original evidence remains in change log/archive. | AA25: L2.8 | AB25: Delta propagation law | AC25: L8.4 | AD25: Build | AE25: D3; D5 | AF25: Core | AG25: R2 | AH25: Advances | AI25: =IF(Y25="","",Y25) | AJ25: RE-ESTIMATE REQUIRED — J/R retain the prior-scope figures for traceability; excluded from usable planning totals. New full-scope and remaining-work estimates are not supplied. | AK25: v4.11.1 | AL25: Chapters 3/4 v4.10.3 — MD + illustrated Word; UI Coverage / UI Controls in this workbook | AM25: =IF(AND(ISNUMBER(J25),OR(AR25="INHERITED ESTIMATE",AR25="CONFIRMED ESTIMATE")),1,0) -> 0 | AO25: Not started — no completion claimed | AP25: Inherited v2.22.0 intended record; no new runtime certification in this repair. | AR25: RE-ESTIMATE REQUIRED | AS25: =IF(AM25=1,J25,"") | AT25: =IF(AND(AM25=1,ISNUMBER(R25)),R25,"") | AU25: BOUNDED SOURCE REVIEW — ADVANCED RUNTIME GAP | AV25: 16 | AW25: 28 | AX25: 44 | AY25: UNCONFIRMED REVIEW ESTIMATE - not P80 or elapsed | AZ25: Chunk/receipt persistence 6/10/16; resume/merge/enforcement 6/11/17; interruption/parallelism tests 4/7/11. | BA25: Backend/PlantProcess.Application/Integration/Services/SourceSystems/DeltaImportExecutionService.cs:120-151 — existing incremental reader use Backend/PlantProcess.Application/Integration/Services/SourceSystems/DeltaImportExecutionService.cs:173-205 — batch/cursor persistence Backend/PlantProcess.Application/Integration/Services/Jobs/JobRunOrchestratorService.cs:61-85 — existing admission/run boundary | BB25: 14-Sep-2026 snapshot; later closure evidence separate; no live HEAD verification
A26: T-116 | B26: M3 | C26: P2 | D26: API namespace migration, part 1: map the 92 prefixes onto the 27 domains and stand up dual-serve | E26: Backend | F26: Namespace | G26: Very Important | H26: Chapter 3 4.3 specifies 27 clean /api/{domain} domains. The repository registers 92 MapGroup prefixes and 544 verb-level routes, with 18 groups under /api/v5, 6 under /api/p15, plus /phase2, /phase4, /phase5, /api/phase8, /api/p09 and /admin/p03p04. Produce the mapping table, then serve both old and new paths during a transition window. v2.20.0 ORDERING — perform namespace renaming after T-256 has decided which material/legacy runtime surfaces remain legitimate compatibility surfaces. Do not preserve a semantically invalid endpoint merely to give it a cleaner URL. v2.22.0 — Maintain bounded-compatibility consumer register. Move live canon/public consumers to governed authorities before retiring compatibility objects; no delete-probes-first hotfix. | I26: Every one of the 544 routes appears exactly once in the mapping table. Both the old and the new path return identical responses for a sample of twenty routes. v2.22.0 — Inventory each consumer/object, positive and negative parity tests, old history remains readable, retirement only after no active dependency remains; upgrade/fresh install agree. | J26: 8 | K26: Not Started | L26: Worker 1 | M26: T-256 | O26: M3: 45 days after M2 completion | P26: Release 2 MUST | Q26: Backend/domain contract | R26: 1.2 | S26: M3-P2 | T26: Use the accepted M1 regression baseline; require empty index and clean owned paths, preserving unrelated user work. Then: Release 1 dependency order | U26: Own canonical DB/backend/security/API/infra. No W2-owned UI/admin task files and no W3 ML/Assistant runtime. | V26: Commit before downstream consumer starts; consumer must use the contract, not redesign producer-owned semantics. | W26: Multi-user Enterprise Operations | X26: M3 P2 — Multi-user Enterprise Operations. Release 2 is heavy production / scale / deeper enterprise use. | AA26: L8.8 | AB26: C1–C4 performance certification and golden-journey release gate | AD26: Converge | AE26: D3; D4; D5 | AF26: Core | AG26: R2 | AH26: Advances | AI26: =IF(Y26="","",Y26) | AJ26: RE-ESTIMATE REQUIRED — J/R retain the prior-scope figures for traceability; excluded from usable planning totals. New full-scope and remaining-work estimates are not supplied. | AK26: v4.11.1 | AL26: Chapters 3/4 v4.10.3 — MD + illustrated Word; UI Coverage / UI Controls in this workbook | AM26: =IF(AND(ISNUMBER(J26),OR(AR26="INHERITED ESTIMATE",AR26="CONFIRMED ESTIMATE")),1,0) -> 0 | AO26: Not started — no completion claimed | AP26: Inherited v2.22.0 intended record; no new runtime certification in this repair. | AR26: RE-ESTIMATE REQUIRED | AS26: =IF(AM26=1,J26,"") | AT26: =IF(AND(AM26=1,ISNUMBER(R26)),R26,"") | AU26: BOUNDED SOURCE REVIEW — ROUTE-WIDE CENSUS NOT COMPLETE | AV26: 8 | AW26: 14 | AX26: 24 | AY26: UNCONFIRMED REVIEW ESTIMATE - not P80 or elapsed | AZ26: Consumer/route inventory 3/5/8; safe dual routing and consumer convergence 3/5/9; parity/negative tests 2/4/7. | BA26: Backend/PlantProcess.Infrastructure/Provenance/NpgsqlProvenanceResolver.cs:16-66 — provenance dispatch and run resolution Backend/PlantProcess.Infrastructure/Provenance/NpgsqlProvenanceResolver.cs:69-90 — source/dataset existence lookup | BB26: 14-Sep-2026 snapshot; later closure evidence separate; no live HEAD verification
A27: T-117 | B27: M3 | C27: P2 | D27: API namespace migration, part 2: migrate the clients and add the token gate | E27: Backend | F27: Namespace | G27: Very Important | H27: Move the ~177 frontend API client methods across 13 modules and the 72 methods on productCoreApiClient.runtime.ts onto the new paths. Then add a gate that fails the build when a registered route or a client base path contains a phase, version or task token. Schedule the removal of the dual-serve window as a named follow-up task rather than leaving it open indefinitely. v2.20.0 CLIENT-CONTRACT CONVERGENCE — retire the dynamic `productApi as legacyApi` dispatch slices while migrating paths. Migrated client modules use typed exported methods/contracts; do not retain `any` escape hatches as the permanent compatibility seam. | I27: A test asserting no registered route matches /phase\d+|\/v\d+\/|p\d\d/. Open the browser network tab during the golden journey and confirm no request URL carries a phase or version token. Static gate: zero `productApi as legacyApi` in migrated API slices and no new `any`-typed escape for canonical clients. A deliberately removed client method fails TypeScript compilation rather than failing only at runtime. | J27: 6 | K27: Not Started | L27: Worker 1 | N27: T-122; T-194 | O27: M3: 45 days after M2 completion | P27: Release 2 MUST | Q27: Backend/domain contract | R27: 0.9 | S27: M3-P2 | T27: Use the accepted M1 regression baseline; require empty index and clean owned paths, preserving unrelated user work. Then: Release 1 dependency order | U27: Own canonical DB/backend/security/API/infra. No W2-owned UI/admin task files and no W3 ML/Assistant runtime. | V27: Commit before downstream consumer starts; consumer must use the contract, not redesign producer-owned semantics. | W27: Multi-user Enterprise Operations | X27: M3 P2 — Multi-user Enterprise Operations. Release 2 is heavy production / scale / deeper enterprise use. | AA27: L8.8 | AB27: C1–C4 performance certification and golden-journey release gate | AD27: Converge | AE27: D3; D4; D5 | AF27: Core | AG27: R2 | AH27: Advances | AI27: =IF(Y27="","",Y27) | AJ27: Inherited baseline estimate | AK27: v4.11.1 | AL27: Chapters 3/4 v4.10.3 — MD + illustrated Word; UI Coverage / UI Controls in this workbook | AM27: =IF(AND(ISNUMBER(J27),OR(AR27="INHERITED ESTIMATE",AR27="CONFIRMED ESTIMATE")),1,0) -> 1 | AO27: Not started — no completion claimed | AP27: Inherited v2.22.0 intended record; no new runtime certification in this repair. | AR27: INHERITED ESTIMATE | AS27: =IF(AM27=1,J27,"") -> 6 | AT27: =IF(AND(AM27=1,ISNUMBER(R27)),R27,"") -> 0.9 | AU27: NOT SOURCE-REVIEWED IN THIS PASS | AY27: NOT ESTIMATED IN THIS PASS
A28: T-122 | B28: M3 | C28: P1 | D28: Container architecture and configuration profiles, including isolated ML runtimes | E28: Infrastructure | F28: Deployment | G28: Critical | H28: Implement the Chapter 6 container/profile architecture and include the frozen AI runtime split: ppiq-worker for ordinary batch work including ml.batch_scoring, ppiq-ml-train for ml.training, and ppiq-ml-online for hard-reserved online scoring only. Keep assistant serving behind ModelServingRuntime/model gateway. No training module may be imported by the online container. Preserve the same signed application artifact and profile-driven deployment. v2.20.0 CONTAINER BASELINE — all production runtime images, including isolated ML images, inherit/retain explicit non-root runtime users and profile-only secret/config injection. No training/online image bakes customer credentials or signing material. | I28: Bring up each profile from a clean machine. Prove ppiq-ml-online admits online scoring only, has a warm-model readiness check, and fails a dependency test if a trainer module is imported. Prove training/batch saturation cannot consume the online reservation. All existing non-ML containers remain healthy. Inspect effective UID/GID for every production image and prove non-root. Scan built images for known runtime secret markers and fail on a match. | J28: 12 | K28: Not Started | L28: Worker 1 | M28: T-106; T-107; T-112; T-113; T-114; T-117; T-137; T-168; T-123 | N28: T-141; T-185; T-192 | O28: M3: 45 days after M2 completion | P28: Release 2 MUST | Q28: Infrastructure/deployment | R28: 3.2 | S28: M3-P1 | T28: GATE PROSE INCOMPLETE — original text ends with an ellipsis. Do not infer omitted conditions. Column M lists completion prerequisites; AN/Contract Handoffs lists contract-only prerequisites. Full task acceptance in column I still applies. Recover the omitted prose before claiming this gate fully reconciled. Preserved original fragment: Use the accepted M1 regression baseline; require empty index and clean owned paths, preserving unrelated user work. Then: T-106 + T-107 + T-112 + T-113 + T-114 + T-117; T-137/T-168 runtime contracts ... | U28: Own canonical DB/backend/security/API/infra. No W2-owned UI/admin task files and no W3 ML/Assistant runtime. | V28: Commit before downstream consumer starts; consumer must use the contract, not redesign producer-owned semantics. | W28: Scale & OT Resilience | X28: M3 P1 — Scale & OT Resilience. Release 2 is heavy production / scale / deeper enterprise use. | AA28: L8.3 | AB28: Deployment topologies | AD28: Build | AE28: D3; D5 | AF28: Core | AG28: R2 | AH28: Advances | AI28: =IF(Y28="","",Y28) | AJ28: Inherited baseline estimate | AK28: v4.11.1 | AL28: Chapters 3/4 v4.10.3 — MD + illustrated Word; UI Coverage / UI Controls in this workbook | AM28: =IF(AND(ISNUMBER(J28),OR(AR28="INHERITED ESTIMATE",AR28="CONFIRMED ESTIMATE")),1,0) -> 1 | AO28: Not started — no completion claimed | AP28: Inherited v2.22.0 intended record; no new runtime certification in this repair. | AR28: INHERITED ESTIMATE | AS28: =IF(AM28=1,J28,"") -> 12 | AT28: =IF(AND(AM28=1,ISNUMBER(R28)),R28,"") -> 3.2 | AU28: NOT SOURCE-REVIEWED IN THIS PASS | AY28: NOT ESTIMATED IN THIS PASS
A29: T-127 | B29: M3 | C29: P2 | D29: Canonical journey regression and the Continuity comparison | E29: Testing | F29: Continuity | G29: Critical | H29: Run J1 to J15 against a normal ppiq_app database with no presentation shortcut and no demonstration-only code path. Then run the Customer Contract Continuity comparison against the snapshots captured at the end of M1. | I29: The journey passes on the canonical database. The continuity comparison shows no change to navigation, control placement, authoring flow, terminology or refusal semantics. Any difference is a defect in M2, not an improvement. | J29: 12 | K29: Not Started | L29: Worker 2 | M29: T-196; T-197; T-198; T-199; T-200; T-121 | N29: T-194 | O29: M3: 45 days after M2 completion | P29: Release 2 MUST | Q29: Integration/E2E/certification | R29: 4.08 | S29: M3-P2 | T29: GATE PROSE INCOMPLETE — original text ends with an ellipsis. Do not infer omitted conditions. Column M lists completion prerequisites; AN/Contract Handoffs lists contract-only prerequisites. Full task acceptance in column I still applies. Recover the omitted prose before claiming this gate fully reconciled. Preserved original fragment: Use the accepted M1 regression baseline; require empty index and clean owned paths, preserving unrelated user work. Then: All Release 1 canonical-core/user-visible owners complete, including T-196/T-197/T-... | U29: Own named UI/admin task end-to-end only after producer APIs/security are committed. | V29: Continuity green → W1 executes T-194; Release 1 release gate may close. | W29: Multi-user Enterprise Operations | X29: M3 P2 — Multi-user Enterprise Operations. Release 2 is heavy production / scale / deeper enterprise use. | AA29: L8.8 | AB29: C1–C4 performance certification and golden-journey release gate | AD29: Build | AE29: D1; D5 | AF29: Core | AG29: R2 | AH29: Advances | AI29: =IF(Y29="","",Y29) | AJ29: Inherited baseline estimate | AK29: v4.11.1 | AL29: Chapters 3/4 v4.10.3 — MD + illustrated Word; UI Coverage / UI Controls in this workbook | AM29: =IF(AND(ISNUMBER(J29),OR(AR29="INHERITED ESTIMATE",AR29="CONFIRMED ESTIMATE")),1,0) -> 1 | AO29: Not started — no completion claimed | AP29: Inherited v2.22.0 intended record; no new runtime certification in this repair. | AR29: INHERITED ESTIMATE | AS29: =IF(AM29=1,J29,"") -> 12 | AT29: =IF(AND(AM29=1,ISNUMBER(R29)),R29,"") -> 4.08 | AU29: NOT SOURCE-REVIEWED IN THIS PASS | AY29: NOT ESTIMATED IN THIS PASS
A30: T-148 | B30: M2 | C30: P3 | D30: Map the 108 page files onto the 40 target pages | E30: Frontend | F30: Namespace | G30: Very Important | H30: Chapter 3 4.3 specifies 40 route pages plus 6 shell components. The repository holds 108 page files in 42 groups with 48 lazy route components, and roughly 14 files are reachable by nobody. Produce the keep, merge and delete decision per file, then delete the unreachable ones under Rule 4, which requires the replacement to land with the deletion in the same change. | I30: A test asserting every page file under src/pages is reachable from a declared route. The count of page files moves toward 40 and no orphan remains. v2.10.2 TARGET-INVENTORY GATE — do not merely prove every existing page file is reachable or that the count 'moves toward 40'. Assert the exact Chapter 3 inventory: all 40 target route pages are declared once at canonical routes, all 6 global shell components are present, no target route is missing, and no orphan page file remains. Any temporary legacy alias must have a named retirement owner. v2.22.0 dependency-kind clarification: T-196/T-197/T-198/T-199/T-200 are CONTRACT_READY predecessors for canonical route identity, permissions and unavailable-state interfaces, not full-M3-completion prerequisites for M2. Every one of the 40 target route identities remains in the inventory. M2 active surfaces must work; a deferred M3 surface must not promise executable functionality. Its implementation and runtime acceptance remain owned by the original M3 task. No M3 functionality is marked complete by T-148. v2.22.1 — v2.22.0 dependency-kind clarification: T-196/T-197/T-198/T-199/T-200 are CONTRACT_READY predecessors for canonical route identity, permissions and unavailable-state interfaces, not full-M3-completion prerequisites for M2. Every one of the 40 target route identities remains in the inventory. M2 active surfaces must work; a deferred M3 surface must not promise executable functionality. Its implementation and runtime acceptance remain owned by the original M3 task. No M3 functionality is marked complete by T-148. v2.23.0 — Consume per-surface approved route/control/state handoffs from T-265/T-266; do not wait for entire backend tasks merely to draft UI. Bind chapter control IDs to actual reachable controls and screen variants. Shared shell/component geometry is required consistency, not a defect. A control-label match alone is not a workflow test. Complete all current M2 route content and record explicitly deferred M3 behavior under its named implementation owner. | J30: 8 | K30: Not Started | L30: Worker 2 | N30: T-248 | O30: M2: ~1 month from owner planning checkpoint; exact date not committed | P30: Release 1 MUST | Q30: Frontend/UI feature | R30: 1.3333333 | S30: M2-P3 | T30: R1 route inventory and six shell contracts frozen. Contract-ready handoffs from T-196/T-197/T-198/T-199/T-200 are recorded separately in column AN. Do not wait for the entire M3 implementation or ship a simulated M3 page. | U30: Own route inventory/redirect cleanup only; do not touch W3 intelligence surfaces. | V30: Commit before downstream consumer starts; consumer must use the contract, not redesign producer-owned semantics. v2.22.0 dependency-kind clarification: T-196/T-197/T-198/T-199/T-200 are CONTRACT_READY predecessors for canonical route identity, permissions and unavailable-state interfaces, not full-M3-completion prerequisites for M2. Every one of the 40 target route identities remains in the inventory. M2 active surfaces must work; a deferred M3 surface must not promise executable functionality. Its implementation and runtime acceptance remain owned by the original M3 task. No M3 functionality is marked complete by T-148. | W30: Enterprise BI & Customer Experience | X30: M2 P3 — Enterprise BI & Customer Experience. Release 1 is genuine early production / first-week customer work. | AA30: L3.1 | AB30: Analysis page anatomy, layout and visual standard | AD30: Build | AE30: D2; D5 | AF30: Core | AG30: R1 | AH30: Advances | AI30: =IF(Y30="","",Y30) | AJ30: Inherited baseline estimate | AK30: v4.11.1 | AL30: Chapters 3/4 v4.10.3 — MD + illustrated Word; UI Coverage / UI Controls in this workbook | AM30: =IF(AND(ISNUMBER(J30),OR(AR30="INHERITED ESTIMATE",AR30="CONFIRMED ESTIMATE")),1,0) -> 1 | AN30: T-196; T-197; T-198; T-199; T-200; T-265; T-266 | AO30: Not started — no completion claimed | AP30: Inherited v2.22.0 intended record; no new runtime certification in this repair. | AR30: INHERITED ESTIMATE | AS30: =IF(AM30=1,J30,"") -> 8 | AT30: =IF(AND(AM30=1,ISNUMBER(R30)),R30,"") -> 1.3333333 | AU30: NOT SOURCE-REVIEWED IN THIS PASS | AY30: NOT ESTIMATED IN THIS PASS
A31: T-149 | B31: M3 | C31: P2 | D31: Delete the legacy redirects and re-verify continuity | E31: Frontend | F31: Namespace | G31: Very Important | H31: Remove the roughly 20 legacy Navigate redirects and the live phase-token routes (/phase8/*, /phase9/*, /phase15/*) that App.tsx still declares among its 69 route paths, then re-run the Customer Contract Continuity comparison. | I31: No route path matches /phase\d+/. The continuity comparison against the M1 snapshots still shows no change to any presented page. | J31: 6 | K31: Not Started | L31: Worker 2 | O31: M3: 45 days after M2 completion | P31: Release 2 MUST | Q31: Frontend/UI feature | R31: 1 | S31: M3-P2 | T31: M1 continuity frozen | U31: Own route inventory/redirect cleanup only; do not touch W3 intelligence surfaces. | V31: Commit before downstream consumer starts; consumer must use the contract, not redesign producer-owned semantics. | W31: Multi-user Enterprise Operations | X31: M3 P2 — Multi-user Enterprise Operations. Release 2 is heavy production / scale / deeper enterprise use. | AA31: L8.8 | AB31: C1–C4 performance certification and golden-journey release gate | AD31: Converge | AE31: D2; D5 | AF31: Core | AG31: R2 | AH31: Advances | AI31: =IF(Y31="","",Y31) | AJ31: Inherited baseline estimate | AK31: v4.11.1 | AL31: Chapters 3/4 v4.10.3 — MD + illustrated Word; UI Coverage / UI Controls in this workbook | AM31: =IF(AND(ISNUMBER(J31),OR(AR31="INHERITED ESTIMATE",AR31="CONFIRMED ESTIMATE")),1,0) -> 1 | AO31: Not started — no completion claimed | AP31: Inherited v2.22.0 intended record; no new runtime certification in this repair. | AR31: INHERITED ESTIMATE | AS31: =IF(AM31=1,J31,"") -> 6 | AT31: =IF(AND(AM31=1,ISNUMBER(R31)),R31,"") -> 1 | AU31: NOT SOURCE-REVIEWED IN THIS PASS | AY31: NOT ESTIMATED IN THIS PASS
A32: T-151 | B32: M3 | C32: P1 | D32: Site defect burn-down | E32: Backend | F32: Site findings | G32: Critical | H32: Fix what soft testing finds, without changing the frozen visible contract unless a formal product decision is approved and recorded. | I32: Each defect has a reproduction, a fix and a regression test. Any visible-contract change carries a written approval. | J32: 12 | K32: Not Started | L32: Worker 1 | O32: M3: 45 days after M2 completion | P32: Release 2 MUST | Q32: External/site certification | R32: 7.2 | S32: M3-P1 | T32: WAIT for deployed Release 1 + real customer/site evidence. M3 sequence | U32: Own site/platform/backend/infra. No AI/ML calibration or customer UX docs. | V32: Commit before downstream consumer starts; consumer must use the contract, not redesign producer-owned semantics. | W32: Scale & OT Resilience | X32: M3 P1 — Scale & OT Resilience. Release 2 is heavy production / scale / deeper enterprise use. | AA32: L8.8 | AB32: C1–C4 performance certification and golden-journey release gate | AD32: Build | AE32: D3; D5 | AF32: Core | AG32: R2 | AH32: Advances | AI32: =IF(Y32="","",Y32) | AJ32: Inherited baseline estimate | AK32: v4.11.1 | AL32: Chapters 3/4 v4.10.3 — MD + illustrated Word; UI Coverage / UI Controls in this workbook | AM32: =IF(AND(ISNUMBER(J32),OR(AR32="INHERITED ESTIMATE",AR32="CONFIRMED ESTIMATE")),1,0) -> 1 | AO32: Not started — no completion claimed | AP32: Inherited v2.22.0 intended record; no new runtime certification in this repair. | AR32: INHERITED ESTIMATE | AS32: =IF(AM32=1,J32,"") -> 12 | AT32: =IF(AND(AM32=1,ISNUMBER(R32)),R32,"") -> 7.2 | AU32: NOT SOURCE-REVIEWED IN THIS PASS | AY32: NOT ESTIMATED IN THIS PASS
A33: T-152 | B33: M3 | C33: P1 | D33: Customer data edge cases | E33: Database | F33: Site findings | G33: Critical | H33: New source patterns, dirty data, unusual keys, timestamps, nulls, late arrivals and customer-specific mapping requirements, handled through the three doors. | I33: Each case handled through import, registry or authoring. Any case requiring a code branch is escalated as a design gap. | J33: 12 | K33: Not Started | L33: Worker 1 | O33: M3: 45 days after M2 completion | P33: Release 2 MUST | Q33: External/site certification | R33: 7.2 | S33: M3-P1 | T33: WAIT for deployed Release 1 + real customer/site evidence. M3 sequence | U33: Own site/platform/backend/infra. No AI/ML calibration or customer UX docs. | V33: Commit before downstream consumer starts; consumer must use the contract, not redesign producer-owned semantics. | W33: Scale & OT Resilience | X33: M3 P1 — Scale & OT Resilience. Release 2 is heavy production / scale / deeper enterprise use. | AA33: L2.3 | AB33: Canonical projection with validation, quarantine and reprocessing | AC33: L8.8 | AD33: Build | AE33: D4; D5 | AF33: Core | AG33: R2 | AH33: Advances | AI33: =IF(Y33="","",Y33) | AJ33: Inherited baseline estimate | AK33: v4.11.1 | AL33: Chapters 3/4 v4.10.3 — MD + illustrated Word; UI Coverage / UI Controls in this workbook | AM33: =IF(AND(ISNUMBER(J33),OR(AR33="INHERITED ESTIMATE",AR33="CONFIRMED ESTIMATE")),1,0) -> 1 | AO33: Not started — no completion claimed | AP33: Inherited v2.22.0 intended record; no new runtime certification in this repair. | AR33: INHERITED ESTIMATE | AS33: =IF(AM33=1,J33,"") -> 12 | AT33: =IF(AND(AM33=1,ISNUMBER(R33)),R33,"") -> 7.2 | AU33: NOT SOURCE-REVIEWED IN THIS PASS | AY33: NOT ESTIMATED IN THIS PASS
A34: T-153 | B34: M3 | C34: P1 | D34: Connector certification against real sources | E34: Backend | F34: Connectors | G34: Critical | H34: Enable and certify the customer's actual connectors. A catalogue row is not a connector; an unbuilt one stays dimmed and badged as planned. | I34: Each certified connector completes a read-only import against the real source with the load budget enforced. The customer-facing capability state changes to Certified only from the executed certification result; no frontend or website code edit is required. | J34: 12 | K34: Not Started | L34: Worker 1 | M34: T-224; T-225; T-226; T-254 | N34: T-249 | O34: M3: 45 days after M2 completion | P34: Release 2 MUST | Q34: External/site certification | R34: 7.2 | S34: M3-P1 | T34: WAIT for deployed Release 1 + real customer/site evidence. M3 sequence | U34: Own site/platform/backend/infra. No AI/ML calibration or customer UX docs. | V34: Commit before downstream consumer starts; consumer must use the contract, not redesign producer-owned semantics. | W34: Scale & OT Resilience | X34: M3 P1 — Scale & OT Resilience. Release 2 is heavy production / scale / deeper enterprise use. | AA34: L1.1 | AB34: Read-only connection and source access | AC34: L1.4 | AD34: Validate | AE34: D3; D5 | AF34: Core | AG34: R2 | AH34: Advances | AI34: =IF(Y34="","",Y34) | AJ34: Inherited baseline estimate | AK34: v4.11.1 | AL34: Chapters 3/4 v4.10.3 — MD + illustrated Word; UI Coverage / UI Controls in this workbook | AM34: =IF(AND(ISNUMBER(J34),OR(AR34="INHERITED ESTIMATE",AR34="CONFIRMED ESTIMATE")),1,0) -> 1 | AO34: Not started — no completion claimed | AP34: Inherited v2.22.0 intended record; no new runtime certification in this repair. | AR34: INHERITED ESTIMATE | AS34: =IF(AM34=1,J34,"") -> 12 | AT34: =IF(AND(AM34=1,ISNUMBER(R34)),R34,"") -> 7.2 | AU34: NOT SOURCE-REVIEWED IN THIS PASS | AY34: NOT ESTIMATED IN THIS PASS
A35: T-154 | B35: M3 | C35: P1 | D35: Query plans, indexes and partition boundaries | E35: Database | F35: Performance | G35: Very Important | H35: Tune against real measurements from the customer's volumes, not against assumptions. | I35: Before and after query plans recorded for the ten slowest queries, with the improvement measured. | J35: 12 | K35: Not Started | L35: Worker 1 | O35: M3: 45 days after M2 completion | P35: Release 2 MUST | Q35: External/site certification | R35: 7.2 | S35: M3-P1 | T35: WAIT for deployed Release 1 + real customer/site evidence. M3 sequence | U35: Own site/platform/backend/infra. No AI/ML calibration or customer UX docs. | V35: Commit before downstream consumer starts; consumer must use the contract, not redesign producer-owned semantics. | W35: Scale & OT Resilience | X35: M3 P1 — Scale & OT Resilience. Release 2 is heavy production / scale / deeper enterprise use. | AA35: L8.5 | AB35: Sizing model and calibrated performance constants | AD35: Build | AE35: D4; D5 | AF35: Core | AG35: R2 | AH35: Advances | AI35: =IF(Y35="","",Y35) | AJ35: Inherited baseline estimate | AK35: v4.11.1 | AL35: Chapters 3/4 v4.10.3 — MD + illustrated Word; UI Coverage / UI Controls in this workbook | AM35: =IF(AND(ISNUMBER(J35),OR(AR35="INHERITED ESTIMATE",AR35="CONFIRMED ESTIMATE")),1,0) -> 1 | AO35: Not started — no completion claimed | AP35: Inherited v2.22.0 intended record; no new runtime certification in this repair. | AR35: INHERITED ESTIMATE | AS35: =IF(AM35=1,J35,"") -> 12 | AT35: =IF(AND(AM35=1,ISNUMBER(R35)),R35,"") -> 7.2 | AU35: NOT SOURCE-REVIEWED IN THIS PASS | AY35: NOT ESTIMATED IN THIS PASS
A36: T-155 | B36: M3 | C36: P1 | D36: B-01/B-02 capacity tuning, scan amplification and model-serving memory | E36: Infrastructure | F36: Performance | G36: Very Important | H36: On site hardware, jointly execute resource measurements for lane max_concurrency/resource_capacity/compute_weight and the hard online reservation, plus scan-amplification and warm-model/assistant memory. This task supplies measured capacity values; it does not redesign the architecture. v2.22.0 — Absorb T-111 measured Scan Amplification baseline/calibrated bands. T-110 owns runtime enforcement. | I36: Record hardware, commit and load profile. Saturate training/batch and prove online p95 remains inside the actionable budget. Publish measured lane values and before/after Scan Amplification with no starvation. v2.22.0 — Measure under declared profiles and record formula, numerator/denominator and scope; known missing delta predicate triggers breach, not a tuned threshold. | J36: 12 | K36: Not Started | L36: Worker 3 | O36: M3: 45 days after M2 completion | P36: Release 2 MUST | Q36: Real-data AI/ML/site measurement | R36: 4.32 | S36: M3-P1 | T36: WAIT for deployed Release 1 + real customer/site evidence. Release 2 accepted + site hardware | U36: Own AI/ML calibration/capacity evidence only. | V36: Commit before downstream consumer starts; consumer must use the contract, not redesign producer-owned semantics. | W36: Scale & OT Resilience | X36: M3 P1 — Scale & OT Resilience. Release 2 is heavy production / scale / deeper enterprise use. | AA36: L8.5 | AB36: Sizing model and calibrated performance constants | AC36: L8.4 | AD36: Build | AE36: D5 | AF36: Core | AG36: R2 | AH36: Advances | AI36: =IF(Y36="","",Y36) | AJ36: RE-ESTIMATE REQUIRED — J/R retain the prior-scope figures for traceability; excluded from usable planning totals. New full-scope and remaining-work estimates are not supplied. | AK36: v4.11.1 | AL36: Chapters 3/4 v4.10.3 — MD + illustrated Word; UI Coverage / UI Controls in this workbook | AM36: =IF(AND(ISNUMBER(J36),OR(AR36="INHERITED ESTIMATE",AR36="CONFIRMED ESTIMATE")),1,0) -> 0 | AO36: Not started — no completion claimed | AP36: Inherited v2.22.0 intended record; no new runtime certification in this repair. | AR36: RE-ESTIMATE REQUIRED | AS36: =IF(AM36=1,J36,"") | AT36: =IF(AND(AM36=1,ISNUMBER(R36)),R36,"") | AU36: SOURCE FOUNDATION REVIEWED — SITE MEASUREMENTS UNVERIFIED | AV36: 8 | AW36: 14 | AX36: 24 | AY36: UNCONFIRMED REVIEW ESTIMATE - not P80 or elapsed | AZ36: Workload/hook setup 3/5/8; measurement orchestration/analysis 3/5/9; governed result publication 2/4/7. | BA36: Backend/PlantProcess.ML.Runtime/Benchmarks/BenchmarkCatalogue.cs:20-36 — benchmark metadata Backend/PlantProcess.ML.Runtime/Benchmarks/BenchmarkManifest.cs:32-75 — SelectedValueGuard | BB36: 14-Sep-2026 snapshot; later closure evidence separate; no live HEAD verification
A37: T-156 | B37: M3 | C37: P3 | D37: Customer definitions built through the product | E37: Frontend | F37: Authoring | G37: Very Important | H37: Build and validate the customer's real pages, relationships, measures, analyses, models and log rules using the product's own authoring surfaces. | I37: Every customer artifact exists as a definition in the store, created through the interface, with no manual database insert. | J37: 12 | K37: Not Started | L37: Worker 2 | O37: M3: 45 days after M2 completion | P37: Release 2 MUST | Q37: External/site certification | R37: 7.2 | S37: M3-P3 | T37: WAIT for deployed Release 1 + real customer/site evidence. M3 sequence | U37: Own customer-facing UX/docs/website only. | V37: Commit before downstream consumer starts; consumer must use the contract, not redesign producer-owned semantics. | W37: Advanced BI, Authoring & Insight Boards | X37: M3 P3 — Advanced BI, Authoring & Insight Boards. Release 2 is heavy production / scale / deeper enterprise use. | AA37: L3.5 | AB37: One authoring shell, five purposes, two modes | AC37: L2.2 | AD37: Build | AE37: D2; D5 | AF37: Core | AG37: R2 | AH37: Advances | AI37: =IF(Y37="","",Y37) | AJ37: Inherited baseline estimate | AK37: v4.11.1 | AL37: Chapters 3/4 v4.10.3 — MD + illustrated Word; UI Coverage / UI Controls in this workbook | AM37: =IF(AND(ISNUMBER(J37),OR(AR37="INHERITED ESTIMATE",AR37="CONFIRMED ESTIMATE")),1,0) -> 1 | AO37: Not started — no completion claimed | AP37: Inherited v2.22.0 intended record; no new runtime certification in this repair. | AR37: INHERITED ESTIMATE | AS37: =IF(AM37=1,J37,"") -> 12 | AT37: =IF(AND(AM37=1,ISNUMBER(R37)),R37,"") -> 7.2 | AU37: NOT SOURCE-REVIEWED IN THIS PASS | AY37: NOT ESTIMATED IN THIS PASS
A38: T-159 | B38: M3 | C38: P1 | D38: C1 to C4 capacity certification | E38: Infrastructure | F38: Certification | G38: Critical | H38: Run the four Chapter 6 capacity profiles and site certification, consuming the measured benchmark outputs from B-01..B-09 where they affect sizing. Replace only CALIBRATION_REQUIRED/REFERENCE_ASSUMPTION constants with measured values and freeze Chapter 6 when all certification gates pass. v2.22.0 — Absorb T-111 capacity/regression certification; verify T-110 runtime scan guard using C1-C4 proofs. | I38: Every worked sizing example recomputes from measured constants; C1-C4 profiles pass their promised envelope. The certification bundle records hardware, commit, dataset, benchmark outputs and sign-off. v2.22.0 — Known negative control exceeds scan band/aborts; restored predicate passes; results, workload, topology and sampled period pinned. | J38: 12 | K38: Not Started | L38: Worker 3 | N38: T-249 | O38: M3: 45 days after M2 completion | P38: Release 2 MUST | Q38: Real-data AI/ML/site measurement | R38: 4.32 | S38: M3-P1 | T38: WAIT for deployed Release 1 + real customer/site evidence. Release 2 accepted + site hardware | U38: Own AI/ML calibration/capacity evidence only. | V38: Commit before downstream consumer starts; consumer must use the contract, not redesign producer-owned semantics. | W38: Scale & OT Resilience | X38: M3 P1 — Scale & OT Resilience. Release 2 is heavy production / scale / deeper enterprise use. | AA38: L8.8 | AB38: C1–C4 performance certification and golden-journey release gate | AC38: L8.5 | AD38: Certify | AE38: D5 | AF38: Core | AG38: R2 | AH38: Advances | AI38: =IF(Y38="","",Y38) | AJ38: RE-ESTIMATE REQUIRED — J/R retain the prior-scope figures for traceability; excluded from usable planning totals. New full-scope and remaining-work estimates are not supplied. | AK38: v4.11.1 | AL38: Chapters 3/4 v4.10.3 — MD + illustrated Word; UI Coverage / UI Controls in this workbook | AM38: =IF(AND(ISNUMBER(J38),OR(AR38="INHERITED ESTIMATE",AR38="CONFIRMED ESTIMATE")),1,0) -> 0 | AO38: Not started — no completion claimed | AP38: Inherited v2.22.0 intended record; no new runtime certification in this repair. | AR38: RE-ESTIMATE REQUIRED | AS38: =IF(AM38=1,J38,"") | AT38: =IF(AND(AM38=1,ISNUMBER(R38)),R38,"") | AU38: FOUNDATION REVIEWED — CAPACITY CERTIFICATION NOT EXECUTED | AV38: 8 | AW38: 16 | AX38: 28 | AY38: UNCONFIRMED REVIEW ESTIMATE - not P80 or elapsed | AZ38: Profile preparation 3/6/10; certification operation/analysis 3/6/11; reconciliation/sign-off evidence 2/4/7. | BA38: Backend/PlantProcess.ML.Runtime/Benchmarks/BenchmarkManifest.cs:43-81 — evidence guard Backend/PlantProcess.ML.Runtime/Benchmarks/BenchmarkCatalogue.cs:65-90 — B-01..B-09 registry | BB38: 14-Sep-2026 snapshot; later closure evidence separate; no live HEAD verification
A39: T-160 | B39: M3 | C39: P1 | D39: HA, DR and restore rehearsal | E39: Infrastructure | F39: Resilience | G39: Critical | H39: Production topology, RPO and RTO objectives, and a real disaster-recovery rehearsal. | I39: A full recovery rehearsal completes within the stated RPO and RTO, witnessed and recorded. | J39: 12 | K39: Not Started | L39: Worker 1 | N39: T-249 | O39: M3: 45 days after M2 completion | P39: Release 2 MUST | Q39: External/site certification | R39: 7.2 | S39: M3-P1 | T39: WAIT for deployed Release 1 + real customer/site evidence. M3 sequence | U39: Own site/platform/backend/infra. No AI/ML calibration or customer UX docs. | V39: Commit before downstream consumer starts; consumer must use the contract, not redesign producer-owned semantics. | W39: Scale & OT Resilience | X39: M3 P1 — Scale & OT Resilience. Release 2 is heavy production / scale / deeper enterprise use. | AA39: L8.7 | AB39: Backup, restore, PITR, DR and HA | AD39: Build | AE39: D4; D5 | AF39: Core | AG39: R2 | AH39: Advances | AI39: =IF(Y39="","",Y39) | AJ39: Inherited baseline estimate | AK39: v4.11.1 | AL39: Chapters 3/4 v4.10.3 — MD + illustrated Word; UI Coverage / UI Controls in this workbook | AM39: =IF(AND(ISNUMBER(J39),OR(AR39="INHERITED ESTIMATE",AR39="CONFIRMED ESTIMATE")),1,0) -> 1 | AO39: Not started — no completion claimed | AP39: Inherited v2.22.0 intended record; no new runtime certification in this repair. | AR39: INHERITED ESTIMATE | AS39: =IF(AM39=1,J39,"") -> 12 | AT39: =IF(AND(AM39=1,ISNUMBER(R39)),R39,"") -> 7.2 | AU39: NOT SOURCE-REVIEWED IN THIS PASS | AY39: NOT ESTIMATED IN THIS PASS
A40: T-161 | B40: M3 | C40: P2 | D40: SSO and identity integration | E40: Backend | F40: Security | G40: Very Important | H40: Integrate the customer identity provider with the final role catalogue, account lifecycle and emergency access. | I40: Account provisioning, de-provisioning and emergency access all tested against the customer directory. | J40: 12 | K40: Not Started | L40: Worker 1 | N40: T-249 | O40: M3: 45 days after M2 completion | P40: Release 2 MUST | Q40: External/site certification | R40: 7.2 | S40: M3-P2 | T40: WAIT for deployed Release 1 + real customer/site evidence. M3 sequence | U40: Own site/platform/backend/infra. No AI/ML calibration or customer UX docs. | V40: Commit before downstream consumer starts; consumer must use the contract, not redesign producer-owned semantics. | W40: Multi-user Enterprise Operations | X40: M3 P2 — Multi-user Enterprise Operations. Release 2 is heavy production / scale / deeper enterprise use. | AA40: L7.1 | AB40: Users, roles, permissions, MFA and enterprise identity | AD40: Harden | AE40: D3; D5 | AF40: Core | AG40: R2 | AH40: Advances | AI40: =IF(Y40="","",Y40) | AJ40: Inherited baseline estimate | AK40: v4.11.1 | AL40: Chapters 3/4 v4.10.3 — MD + illustrated Word; UI Coverage / UI Controls in this workbook | AM40: =IF(AND(ISNUMBER(J40),OR(AR40="INHERITED ESTIMATE",AR40="CONFIRMED ESTIMATE")),1,0) -> 1 | AO40: Not started — no completion claimed | AP40: Inherited v2.22.0 intended record; no new runtime certification in this repair. | AR40: INHERITED ESTIMATE | AS40: =IF(AM40=1,J40,"") -> 12 | AT40: =IF(AND(AM40=1,ISNUMBER(R40)),R40,"") -> 7.2 | AU40: NOT SOURCE-REVIEWED IN THIS PASS | AY40: NOT ESTIMATED IN THIS PASS
A41: T-162 | B41: M3 | C41: P2 | D41: Site security hardening and sign-off | E41: Infrastructure | F41: Security | G41: Critical | H41: Network rules, secrets, certificate rotation, RLS and tenant proof, audit review. | I41: A tenant-isolation proof from the database alone, plus a signed security review. | J41: 12 | K41: Not Started | L41: Worker 1 | N41: T-249 | O41: M3: 45 days after M2 completion | P41: Release 2 MUST | Q41: External/site certification | R41: 7.2 | S41: M3-P2 | T41: WAIT for deployed Release 1 + real customer/site evidence. M3 sequence | U41: Own site/platform/backend/infra. No AI/ML calibration or customer UX docs. | V41: Commit before downstream consumer starts; consumer must use the contract, not redesign producer-owned semantics. | W41: Multi-user Enterprise Operations | X41: M3 P2 — Multi-user Enterprise Operations. Release 2 is heavy production / scale / deeper enterprise use. | AA41: L7.2 | AB41: Tenant isolation | AC41: L7.5 | AD41: Harden | AE41: D5 | AF41: Core | AG41: R2 | AH41: Advances | AI41: =IF(Y41="","",Y41) | AJ41: Inherited baseline estimate | AK41: v4.11.1 | AL41: Chapters 3/4 v4.10.3 — MD + illustrated Word; UI Coverage / UI Controls in this workbook | AM41: =IF(AND(ISNUMBER(J41),OR(AR41="INHERITED ESTIMATE",AR41="CONFIRMED ESTIMATE")),1,0) -> 1 | AO41: Not started — no completion claimed | AP41: Inherited v2.22.0 intended record; no new runtime certification in this repair. | AR41: INHERITED ESTIMATE | AS41: =IF(AM41=1,J41,"") -> 12 | AT41: =IF(AND(AM41=1,ISNUMBER(R41)),R41,"") -> 7.2 | AU41: NOT SOURCE-REVIEWED IN THIS PASS | AY41: NOT ESTIMATED IN THIS PASS
A42: T-163 | B42: M3 | C42: P1 | D42: Monitoring, SLOs and support escalation | E42: Infrastructure | F42: Monitoring | G42: Very Important | H42: Operational dashboards, alerts, queue and latency and backup and certificate health, and the escalation path. | I42: Each SLO has a measured baseline and an alert that fires before it is breached. | J42: 12 | K42: Not Started | L42: Worker 1 | N42: T-249 | O42: M3: 45 days after M2 completion | P42: Release 2 MUST | Q42: External/site certification | R42: 7.2 | S42: M3-P1 | T42: WAIT for deployed Release 1 + real customer/site evidence. M3 sequence | U42: Own site/platform/backend/infra. No AI/ML calibration or customer UX docs. | V42: Commit before downstream consumer starts; consumer must use the contract, not redesign producer-owned semantics. | W42: Scale & OT Resilience | X42: M3 P1 — Scale & OT Resilience. Release 2 is heavy production / scale / deeper enterprise use. | AA42: L8.6 | AB42: Monitoring, observability, health and readiness | AD42: Build | AE42: D5 | AF42: Core | AG42: R2 | AH42: Advances | AI42: =IF(Y42="","",Y42) | AJ42: Inherited baseline estimate | AK42: v4.11.1 | AL42: Chapters 3/4 v4.10.3 — MD + illustrated Word; UI Coverage / UI Controls in this workbook | AM42: =IF(AND(ISNUMBER(J42),OR(AR42="INHERITED ESTIMATE",AR42="CONFIRMED ESTIMATE")),1,0) -> 1 | AO42: Not started — no completion claimed | AP42: Inherited v2.22.0 intended record; no new runtime certification in this repair. | AR42: INHERITED ESTIMATE | AS42: =IF(AM42=1,J42,"") -> 12 | AT42: =IF(AND(AM42=1,ISNUMBER(R42)),R42,"") -> 7.2 | AU42: NOT SOURCE-REVIEWED IN THIS PASS | AY42: NOT ESTIMATED IN THIS PASS
A43: T-166 | B43: M3 | C43: P3 | D43: Five-product website production completion | E43: Website | F43: Public site | G43: Important | H43: CORRECTED IN v2.2. The redirect replacement, the portfolio page and the mega-menu are now M1 work, because the customer sees the company architecture in the room. What remains here is production completion of the five product pages: full content, proof sections, SEO and metadata, analytics, lead flows, localization, and the final honesty certification across every claim. AUDIT HARDENING IN v2.9.2. Production completion also certifies one coherent visual identity across all five product pages and shared public-site sections. Typography, UI primitives, graphical language, motion, responsive hierarchy and accessibility must come from the same design system used by the strongest PPIQ sections. Remove mojibake, visible HTML entities and locally invented low-quality box/flowchart styling; motion must reinforce meaning and degrade cleanly under reduced-motion preferences. | I43: Each of the five products has a complete page under the Golden Rule product-page contract. Every claim passes the Chapter 6 6.2.10 honesty rule and the certification is recorded. Lead flow tested end to end on each page. Run a five-product visual-system audit at desktop, tablet and mobile. Zero mojibake/visible entities, text overflow, disconnected graphical connectors or page-local font/control systems. Automated visual/a11y checks are green, reduced-motion is honoured, and a reviewer comparison against the strongest PPIQ reference section records no page as visually less sophisticated. | J43: 12 | K43: Not Started | L43: Worker 2 | O43: M3: 45 days after M2 completion | P43: Release 2 MUST | Q43: External/site certification | R43: 7.2 | S43: M3-P3 | T43: WAIT for deployed Release 1 + real customer/site evidence. M3 sequence | U43: Own customer-facing UX/docs/website only. | V43: Commit before downstream consumer starts; consumer must use the contract, not redesign producer-owned semantics. | W43: Advanced BI, Authoring & Insight Boards | X43: M3 P3 — Advanced BI, Authoring & Insight Boards. Release 2 is heavy production / scale / deeper enterprise use. | AA43: BOUNDARY — SOU Website | AB43: SOU public website / portfolio boundary — not a PPIQ product capability | AD43: Build | AE43: D5 | AF43: Boundary | AG43: R2 | AH43: No maturity change | AI43: =IF(Y43="","",Y43) | AJ43: Inherited baseline estimate | AK43: v4.11.1 | AL43: Chapters 3/4 v4.10.3 — MD + illustrated Word; UI Coverage / UI Controls in this workbook | AM43: =IF(AND(ISNUMBER(J43),OR(AR43="INHERITED ESTIMATE",AR43="CONFIRMED ESTIMATE")),1,0) -> 1 | AO43: Not started — no completion claimed | AP43: Inherited v2.22.0 intended record; no new runtime certification in this repair. | AR43: INHERITED ESTIMATE | AS43: =IF(AM43=1,J43,"") -> 12 | AT43: =IF(AND(AM43=1,ISNUMBER(R43)),R43,"") -> 7.2 | AU43: NOT SOURCE-REVIEWED IN THIS PASS | AY43: NOT ESTIMATED IN THIS PASS
A44: T-194 | B44: M3 | C44: P2 | D44: Retire legacy API dual-serve aliases after canonical-client continuity proof | E44: Backend | F44: API namespace | G44: Very Important | H44: T-117 deliberately introduces a dual-serve transition while clients migrate. Close that transition explicitly after T-127 proves the canonical journey and continuity. Remove every legacy phase/version/task-token API alias, preserve only canonical /api/{domain} routes, and keep a machine-readable mapping artifact so support can interpret old logs without keeping old endpoints alive. | I44: After T-127 is green, enumerate the route table and prove zero legacy alias remains. A representative old path returns the governed retired-route response or 404 according to the API policy, while the canonical path remains green. Re-run the route-token gate and a bounded canonical-journey regression. No frontend client calls an old alias. | J44: 6 | K44: Not Started | L44: Worker 1 | M44: T-117; T-127 | O44: M3: 45 days after M2 completion | P44: Release 2 MUST | Q44: Backend/domain contract | R44: 0.9 | S44: M3-P2 | T44: Use the accepted M1 regression baseline; require empty index and clean owned paths, preserving unrelated user work. Then: T-117 + T-127 | U44: Own canonical DB/backend/security/API/infra. No W2-owned UI/admin task files and no W3 ML/Assistant runtime. | V44: Commit before downstream consumer starts; consumer must use the contract, not redesign producer-owned semantics. | W44: Multi-user Enterprise Operations | X44: M3 P2 — Multi-user Enterprise Operations. Release 2 is heavy production / scale / deeper enterprise use. | AA44: L8.8 | AB44: C1–C4 performance certification and golden-journey release gate | AD44: Converge | AE44: D3; D5 | AF44: Core | AG44: R2 | AH44: Advances | AI44: =IF(Y44="","",Y44) | AJ44: Inherited baseline estimate | AK44: v4.11.1 | AL44: Chapters 3/4 v4.10.3 — MD + illustrated Word; UI Coverage / UI Controls in this workbook | AM44: =IF(AND(ISNUMBER(J44),OR(AR44="INHERITED ESTIMATE",AR44="CONFIRMED ESTIMATE")),1,0) -> 1 | AO44: Not started — no completion claimed | AP44: Inherited v2.22.0 intended record; no new runtime certification in this repair. | AR44: INHERITED ESTIMATE | AS44: =IF(AM44=1,J44,"") -> 6 | AT44: =IF(AND(AM44=1,ISNUMBER(R44)),R44,"") -> 0.9 | AU44: NOT SOURCE-REVIEWED IN THIS PASS | AY44: NOT ESTIMATED IN THIS PASS
A45: T-196 | B45: M3 | C45: P2 | D45: C4 Plant Model Explorer canonical route and structural evidence surface | E45: Frontend | F45: Plant model | G45: Very Important | H45: Implement the missing Chapter 3 C4 /plant-model surface on the canonical plant authority. Show site/area/equipment hierarchy, search, unmapped-only state, selected-node details and the routes/operations that reference it. Unmapped equipment is explicit Amber evidence rather than silently dropped. The page is generic and uses imported plant vocabulary only. | I45: Route /plant-model exists exactly once. Load a canonical reference plant and prove hierarchy/details match GET /api/plant/layout and /api/plant/equipment/{id}. Introduce one unmapped equipment reference and prove it is visible with its source object. Empty install renders the designed no-projection state. Keyboard tree traversal and RTL contract pass. | J45: 8 | K45: Not Started | L45: Worker 2 | M45: T-087; T-094; T-095 | N45: T-127 | O45: M3: 45 days after M2 completion | P45: Release 2 MUST | Q45: Frontend/UI feature | R45: 1.3333333 | S45: M3-P2 | T45: Use the accepted M1 regression baseline; require empty index and clean owned paths, preserving unrelated user work. Then: T-087 + T-094 + T-095 | U45: Own named UI/admin task end-to-end only after producer APIs/security are committed. | V45: Commit before downstream consumer starts; consumer must use the contract, not redesign producer-owned semantics. | W45: Multi-user Enterprise Operations | X45: M3 P2 — Multi-user Enterprise Operations. Release 2 is heavy production / scale / deeper enterprise use. | AA45: L5.2 | AB45: Permanent relationship model | AD45: Build | AE45: D2; D5 | AF45: Core | AG45: R2 | AH45: Advances | AI45: =IF(Y45="","",Y45) | AJ45: Inherited baseline estimate | AK45: v4.11.1 | AL45: Chapters 3/4 v4.10.3 — MD + illustrated Word; UI Coverage / UI Controls in this workbook | AM45: =IF(AND(ISNUMBER(J45),OR(AR45="INHERITED ESTIMATE",AR45="CONFIRMED ESTIMATE")),1,0) -> 1 | AO45: Not started — no completion claimed | AP45: Inherited v2.22.0 intended record; no new runtime certification in this repair. | AR45: INHERITED ESTIMATE | AS45: =IF(AM45=1,J45,"") -> 8 | AT45: =IF(AND(AM45=1,ISNUMBER(R45)),R45,"") -> 1.3333333 | AU45: NOT SOURCE-REVIEWED IN THIS PASS | AY45: NOT ESTIMATED IN THIS PASS
A46: T-197 | B46: M3 | C46: P2 | D46: E6 Alert Routing and Escalation with delivery, retry and dead-letter evidence | E46: Backend + Frontend | F46: Alert routing | G46: Very Important | H46: Implement Chapter 3 E6 /alert-routing: routing rules over log/plant-data channels, severity, recipients, delivery channels, escalation delay, working hours/quiet periods, deduplication, grouping key, rate limit, suppression, test delivery, retry and dead-letter visibility. Entries are held during quiet periods, never silently lost. | I46: Create and test a routing rule, force one delivery failure through its retry ceiling and prove it appears in dead letters with reason. Prove a rule with no recipient and an escalation with no escalation recipient are refused. Quiet-period traffic is held and later delivered. Role enforcement and audit evidence pass. | J46: 10 | K46: Not Started | L46: Worker 2 | M46: T-119; T-198 | N46: T-127 | O46: M3: 45 days after M2 completion | P46: Release 2 MUST | Q46: Full-stack governed feature | R46: 2.2857143 | S46: M3-P2 | T46: Use the accepted M1 regression baseline; require empty index and clean owned paths, preserving unrelated user work. Then: T-119 + T-198 | U46: Own named UI/admin task end-to-end only after producer APIs/security are committed. | V46: Commit before downstream consumer starts; consumer must use the contract, not redesign producer-owned semantics. | W46: Multi-user Enterprise Operations | X46: M3 P2 — Multi-user Enterprise Operations. Release 2 is heavy production / scale / deeper enterprise use. | AA46: L6.4 | AB46: Alert routing and escalation | AD46: Build | AE46: D2; D3; D5 | AF46: Core | AG46: R2 | AH46: Advances | AI46: =IF(Y46="","",Y46) | AJ46: Inherited baseline estimate | AK46: v4.11.1 | AL46: Chapters 3/4 v4.10.3 — MD + illustrated Word; UI Coverage / UI Controls in this workbook | AM46: =IF(AND(ISNUMBER(J46),OR(AR46="INHERITED ESTIMATE",AR46="CONFIRMED ESTIMATE")),1,0) -> 1 | AO46: Not started — no completion claimed | AP46: Inherited v2.22.0 intended record; no new runtime certification in this repair. | AR46: INHERITED ESTIMATE | AS46: =IF(AM46=1,J46,"") -> 10 | AT46: =IF(AND(AM46=1,ISNUMBER(R46)),R46,"") -> 2.2857143 | AU46: NOT SOURCE-REVIEWED IN THIS PASS | AY46: NOT ESTIMATED IN THIS PASS
A47: T-198 | B47: M3 | C47: P2 | D47: F5 Logging and Audit plus F6 Log Channel Configuration | E47: Backend + Frontend | F47: Logging administration | G47: Critical | H47: Implement the Chapter 3 canonical logging administration contract: /admin/logs with role-scoped System/Job/Data/Audit/Assistant/Plant Data families, filtering, live tail/replay, run correlation and export; plus /admin/log-channels for channel identity, severity mapping, routing/export target and reading roles. Built-in/audit channels are locked as specified; retention is read-only here and owned by F9. | I47: Every permitted family is queryable and a forbidden family is absent for the role. Drop and resume the live stream and prove replay. Correlate one run across families. Audit has no edit/delete control. Create a custom channel, prove built-ins remain locked, and refuse an attempt to create/retarget the audit family. Canonical log tables and audit trail are used. | J47: 12 | K47: Not Started | L47: Worker 2 | M47: T-112; T-114; T-119 | N47: T-127; T-197; T-199 | O47: M3: 45 days after M2 completion | P47: Release 2 MUST | Q47: Full-stack governed feature | R47: 2.7428571 | S47: M3-P2 | T47: Use the accepted M1 regression baseline; require empty index and clean owned paths, preserving unrelated user work. Then: T-112 + T-114 + T-119 | U47: Own named UI/admin task end-to-end only after producer APIs/security are committed. | V47: Commit before downstream consumer starts; consumer must use the contract, not redesign producer-owned semantics. | W47: Multi-user Enterprise Operations | X47: M3 P2 — Multi-user Enterprise Operations. Release 2 is heavy production / scale / deeper enterprise use. | AA47: L6.6 | AB47: Plant data log, audit, log channels, retention and archival | AD47: Build | AE47: D2; D3; D5 | AF47: Core | AG47: R2 | AH47: Advances | AI47: =IF(Y47="","",Y47) | AJ47: Inherited baseline estimate | AK47: v4.11.1 | AL47: Chapters 3/4 v4.10.3 — MD + illustrated Word; UI Coverage / UI Controls in this workbook | AM47: =IF(AND(ISNUMBER(J47),OR(AR47="INHERITED ESTIMATE",AR47="CONFIRMED ESTIMATE")),1,0) -> 1 | AO47: Not started — no completion claimed | AP47: Inherited v2.22.0 intended record; no new runtime certification in this repair. | AR47: INHERITED ESTIMATE | AS47: =IF(AM47=1,J47,"") -> 12 | AT47: =IF(AND(AM47=1,ISNUMBER(R47)),R47,"") -> 2.7428571 | AU47: NOT SOURCE-REVIEWED IN THIS PASS | AY47: NOT ESTIMATED IN THIS PASS
A48: T-199 | B48: M3 | C48: P2 | D48: F9 Log Retention and Archival with dry-run, legal hold and no-delete-on-archive-failure | E48: Backend + Frontend | F48: Log retention | G48: Critical | H48: Implement Chapter 3 F9 /admin/log-retention as the sole destructive log-history policy surface. Persist per-channel retention policy, archive-before-delete, destination, cleanup schedule/batch size, governed audit minimum and legal hold. Require pre-save dry-run impact. Cleanup history records cutoff, examined/archived/deleted rows, reclaimed storage, duration and failure reason. | I48: Attempt audit retention below the governed minimum and refuse it. Save without preview and refuse it. Put a channel on legal hold and prove cleanup is blocked. Make the archive destination fail and prove zero rows are deleted. Complete one successful preview+cleanup and reconcile counts/history. Only Administrator can access the page. | J48: 12 | K48: Not Started | L48: Worker 2 | M48: T-124; T-198 | N48: T-127 | O48: M3: 45 days after M2 completion | P48: Release 2 MUST | Q48: Full-stack governed feature | R48: 2.7428571 | S48: M3-P2 | T48: Use the accepted M1 regression baseline; require empty index and clean owned paths, preserving unrelated user work. Then: T-124 + T-198 | U48: Own named UI/admin task end-to-end only after producer APIs/security are committed. | V48: Commit before downstream consumer starts; consumer must use the contract, not redesign producer-owned semantics. | W48: Multi-user Enterprise Operations | X48: M3 P2 — Multi-user Enterprise Operations. Release 2 is heavy production / scale / deeper enterprise use. | AA48: L6.6 | AB48: Plant data log, audit, log channels, retention and archival | AD48: Build | AE48: D2; D3; D5 | AF48: Core | AG48: R2 | AH48: Advances | AI48: =IF(Y48="","",Y48) | AJ48: Inherited baseline estimate | AK48: v4.11.1 | AL48: Chapters 3/4 v4.10.3 — MD + illustrated Word; UI Coverage / UI Controls in this workbook | AM48: =IF(AND(ISNUMBER(J48),OR(AR48="INHERITED ESTIMATE",AR48="CONFIRMED ESTIMATE")),1,0) -> 1 | AO48: Not started — no completion claimed | AP48: Inherited v2.22.0 intended record; no new runtime certification in this repair. | AR48: INHERITED ESTIMATE | AS48: =IF(AM48=1,J48,"") -> 12 | AT48: =IF(AND(AM48=1,ISNUMBER(R48)),R48,"") -> 2.7428571 | AU48: NOT SOURCE-REVIEWED IN THIS PASS | AY48: NOT ESTIMATED IN THIS PASS
A49: T-200 | B49: M3 | C49: P2 | D49: F7 System Settings and F8 Translation/Language canonical administration | E49: Backend + Frontend | F49: System administration | G49: Very Important | H49: Implement Chapter 3 F7 /admin/settings and F8 /admin/translation. System settings own site identity, units/formats, plant time zone, documented retention defaults and per-tenant no-egress data boundary. Translation owns language packs, review/mirror-verification state, context-aware labels, import/export and fallback language. Presentation-era hardcoded translation tables become compatibility data only. | I49: Change plant time zone through a confirmed action and prove the resulting setting is audited and used by a shift-aware display; toggle no-egress and prove affected capabilities report the new boundary. Add/edit a translation, mark review/mirror state, export and reimport a pack, and verify RTL rendering for Arabic. No machine-locale fallback silently changes formats. | J49: 10 | K49: Not Started | L49: Worker 2 | M49: T-113; T-119; T-216 | N49: T-127 | O49: M3: 45 days after M2 completion | P49: Release 2 MUST | Q49: Full-stack governed feature | R49: 2.2857143 | S49: M3-P2 | T49: Use the accepted M1 regression baseline; require empty index and clean owned paths, preserving unrelated user work. Then: T-113 + T-119 | U49: Own named UI/admin task end-to-end only after producer APIs/security are committed. | V49: Commit before downstream consumer starts; consumer must use the contract, not redesign producer-owned semantics. | W49: Multi-user Enterprise Operations | X49: M3 P2 — Multi-user Enterprise Operations. Release 2 is heavy production / scale / deeper enterprise use. | AA49: L6.8 | AB49: Settings, time zone, units, localisation and translation | AD49: Build | AE49: D2; D3; D5 | AF49: Core | AG49: R2 | AH49: Advances | AI49: =IF(Y49="","",Y49) | AJ49: Inherited baseline estimate | AK49: v4.11.1 | AL49: Chapters 3/4 v4.10.3 — MD + illustrated Word; UI Coverage / UI Controls in this workbook | AM49: =IF(AND(ISNUMBER(J49),OR(AR49="INHERITED ESTIMATE",AR49="CONFIRMED ESTIMATE")),1,0) -> 1 | AO49: Not started — no completion claimed | AP49: Inherited v2.22.0 intended record; no new runtime certification in this repair. | AR49: INHERITED ESTIMATE | AS49: =IF(AM49=1,J49,"") -> 10 | AT49: =IF(AND(AM49=1,ISNUMBER(R49)),R49,"") -> 2.2857143 | AU49: NOT SOURCE-REVIEWED IN THIS PASS | AY49: NOT ESTIMATED IN THIS PASS
A50: T-201 | B50: M2 | C50: P1 | D50: Freeze the successful M1 presentation baseline and transfer programme authority to M2 | E50: Programme | F50: Release baseline | G50: Critical | H50: Resolve the shared dirty tree, keep/revert the associative change on evidence, commit exact owned files, tag/freeze the successful presentation baseline, and formally stop presentation-only feature/page/data work. Remaining generic defects move to M2-P0 owners rather than being completed as M1 content. | I50: Clean index and explicit foreign-file inventory; immutable release/tag or equivalent frozen artifact; presentation profile still launches; one ledger lists every unclosed M1 item as frozen, superseded, or consumed by a named M2 task. No customer-demo-only task remains on the September critical path. | J50: 4 | K50: Done | L50: Worker 1 | N50: T-086; T-202; T-203; T-204; T-205; T-206; T-207; T-208; T-213; T-241 | O50: M2: ~1 month from owner planning checkpoint; exact date not committed | P50: Release 1 MUST | Q50: Release / governance | R50: 1.5 | S50: M2-P1 | T50: CLOSED BASELINE — no new start gate and no re-execution implied. Preserve accepted closure and clean owned scope; reopen only on a concrete, separately recorded regression. Downstream consumes the frozen contract. | U50: Git/worktree ownership + release/tag only. | V50: After commit/tag, all workers consume the frozen baseline; nobody reopens M1 presentation scope without a proven regression. | W50: Product Foundation & Release Truth | X50: M2 P1 — Product Foundation & Release Truth. Release 1 is genuine early production / first-week customer work. | Y50: BASELINE HEAD 7da9d46ed29545f1c4f4686fa82c117c08b9fc86; TAG m1-presentation-baseline-2026-08-21 — no task commit; tag is closure artifact | Z50: 46258 | AA50: L8.8 | AB50: C1–C4 performance certification and golden-journey release gate | AD50: Validate | AE50: D1; D5 | AF50: Core | AG50: R1 | AH50: Advances | AI50: =IF(Y50="","",Y50) -> BASELINE HEAD 7da9d46ed29545f1c4f4686fa82c117c08b9fc86; TAG m1-presentation-baseline-2026-08-21 — no task commit; tag is closure artifact | AJ50: Inherited baseline estimate | AK50: v4.11.1 | AL50: Chapters 3/4 v4.10.3 — MD + illustrated Word; UI Coverage / UI Controls in this workbook | AM50: =IF(AND(ISNUMBER(J50),OR(AR50="INHERITED ESTIMATE",AR50="CONFIRMED ESTIMATE")),1,0) -> 1 | AO50: Recorded closed — inherited evidence | AP50: Inherited v2.22.0 intended record; no new runtime certification in this repair. | AR50: INHERITED ESTIMATE | AS50: =IF(AM50=1,J50,"") -> 4 | AT50: =IF(AND(AM50=1,ISNUMBER(R50)),R50,"") -> 1.5 | AU50: NOT SOURCE-REVIEWED IN THIS PASS | AY50: NOT ESTIMATED IN THIS PASS
A51: T-202 | B51: M2 | C51: P1 | D51: Persisted page/widget definition replay gate | E51: Quality | F51: Release Truth | G51: Critical | H51: Enumerate every active customer-facing page/widget definition from the real database and execute its actual query contract against the release API/database. Validate declared terminal semantics, row/population evidence and compatibility. This gate tests the product as persisted, not merely source-code paths. | I51: Every active persisted widget executes with 2xx plus Populated/Empty/Blocked/Refused as documented; unexpected 4xx/5xx is a failure. Deliberately corrupt one dimension/measure combination and prove the gate fails. Restore and prove green. Emit machine-readable report naming definition/page/widget. | J51: 10 | K51: Done | L51: Worker 2 | M51: T-201 | N51: T-212; T-248 | O51: M2: ~1 month from owner planning checkpoint; exact date not committed | P51: Release 1 MUST | Q51: E2E / integration gate | R51: 4 | S51: M2-P1 | T51: CLOSED BASELINE — no new start gate and no re-execution implied. Preserve accepted closure and clean owned scope; reopen only on a concrete, separately recorded regression. Downstream consumes the frozen contract. | U51: Frontend E2E + dashboard query test harness; no canonical schema edits. | V51: T-150 later consumes this gate; it does not redesign it. | W51: Product Foundation & Release Truth | X51: M2 P1 — Product Foundation & Release Truth. Release 1 is genuine early production / first-week customer work. | Y51: ad37c324 — Add persisted definition replay gate for release truth | Z51: 46259 | AA51: L8.8 | AB51: C1–C4 performance certification and golden-journey release gate | AC51: L3.1; L3.4 | AD51: Validate | AE51: D2; D5 | AF51: Core | AG51: R1 | AH51: Advances | AI51: =IF(Y51="","",Y51) -> ad37c324 — Add persisted definition replay gate for release truth | AJ51: Inherited baseline estimate | AK51: v4.11.1 | AL51: Chapters 3/4 v4.10.3 — MD + illustrated Word; UI Coverage / UI Controls in this workbook | AM51: =IF(AND(ISNUMBER(J51),OR(AR51="INHERITED ESTIMATE",AR51="CONFIRMED ESTIMATE")),1,0) -> 1 | AO51: Recorded closed — inherited evidence | AP51: Inherited v2.22.0 intended record; no new runtime certification in this repair. | AR51: INHERITED ESTIMATE | AS51: =IF(AM51=1,J51,"") -> 10 | AT51: =IF(AND(AM51=1,ISNUMBER(R51)),R51,"") -> 4 | AU51: NOT SOURCE-REVIEWED IN THIS PASS | AY51: NOT ESTIMATED IN THIS PASS
A52: T-203 | B52: M2 | C52: P1 | D52: Customer-route network, console and widget-state invariant | E52: Quality | F52: Release Truth | G52: Critical | H52: For every customer-reachable route, navigate and settle against the real API; fail on unexpected HTTP >=400, failed required request, uncaught JS exception, unhandled console error, error toast, or widget Failed state. Record route/request/widget evidence. | I52: Inject one failing API response and one uncaught render error and prove the route gate fails for the named cause. With faults removed, every customer route settles with zero unexpected network/console/widget failures. | J52: 10 | K52: Done | L52: Worker 2 | M52: T-201 | N52: T-222; T-248 | O52: M2: ~1 month from owner planning checkpoint; exact date not committed | P52: Release 1 MUST | Q52: Playwright / session | R52: 4 | S52: M2-P1 | T52: CLOSED BASELINE — no new start gate and no re-execution implied. Preserve accepted closure and clean owned scope; reopen only on a concrete, separately recorded regression. Downstream consumes the frozen contract. | U52: Frontend E2E/session harness. | V52: All later customer-facing feature tasks must add their route to this gate before close. | W52: Product Foundation & Release Truth | X52: M2 P1 — Product Foundation & Release Truth. Release 1 is genuine early production / first-week customer work. | Y52: cd1a450e — Add customer route invariant gate with durable evidence | Z52: 46259 | AA52: L8.8 | AB52: C1–C4 performance certification and golden-journey release gate | AC52: L6.7 | AD52: Validate | AE52: D2; D5 | AF52: Core | AG52: R1 | AH52: Advances | AI52: =IF(Y52="","",Y52) -> cd1a450e — Add customer route invariant gate with durable evidence | AJ52: Inherited baseline estimate | AK52: v4.11.1 | AL52: Chapters 3/4 v4.10.3 — MD + illustrated Word; UI Coverage / UI Controls in this workbook | AM52: =IF(AND(ISNUMBER(J52),OR(AR52="INHERITED ESTIMATE",AR52="CONFIRMED ESTIMATE")),1,0) -> 1 | AO52: Recorded closed — inherited evidence | AP52: Inherited v2.22.0 intended record; no new runtime certification in this repair. | AR52: INHERITED ESTIMATE | AS52: =IF(AM52=1,J52,"") -> 10 | AT52: =IF(AND(AM52=1,ISNUMBER(R52)),R52,"") -> 4 | AU52: NOT SOURCE-REVIEWED IN THIS PASS | AY52: NOT ESTIMATED IN THIS PASS
A53: T-204 | B53: M2 | C53: P1 | D53: Associative cross-filter state-machine certification | E53: Frontend | F53: Associative BI | G53: Critical | H53: Replace click-smoke acceptance with a state-machine proof: capture widgets A/B/C, click X in A, assert selection state, assert B/C re-query with X, assert returned populations and visible results change, clear X and assert restoration. Execute across interactive renderer families. | I53: Bar, line, scatter, heatmap, table-row and interactive KPI families each prove selection propagation, dependent request mutation, population/result change, and restoration. A deliberate broken dependency-array/bridge falsification must fail the test. | J53: 10 | K53: Done | L53: Worker 2 | M53: T-201 | N53: T-222; T-248 | O53: M2: ~1 month from owner planning checkpoint; exact date not committed | P53: Release 1 MUST | Q53: Frontend behavioural E2E | R53: 4.25 | S53: M2-P1 | T53: CLOSED BASELINE — no new start gate and no re-execution implied. Preserve accepted closure and clean owned scope; reopen only on a concrete, separately recorded regression. Downstream consumes the frozen contract. | U53: AssociativeContext/filter bridge + E2E tests; no unrelated chart redesign. | V53: This task supersedes using browser walking as the acceptance of cross-filtering. | W53: Product Foundation & Release Truth | X53: M2 P1 — Product Foundation & Release Truth. Release 1 is genuine early production / first-week customer work. | Y53: c6491e2d — closure-state HEAD; exact task commit subject not independently recovered | Z53: 46265 | AA53: L3.2 | AB53: Associative engine and selection strip | AD53: Validate | AE53: D2; D5 | AF53: Core | AG53: R1 | AH53: Advances | AI53: =IF(Y53="","",Y53) -> c6491e2d — closure-state HEAD; exact task commit subject not independently recovered | AJ53: Inherited baseline estimate | AK53: v4.11.1 | AL53: Chapters 3/4 v4.10.3 — MD + illustrated Word; UI Coverage / UI Controls in this workbook | AM53: =IF(AND(ISNUMBER(J53),OR(AR53="INHERITED ESTIMATE",AR53="CONFIRMED ESTIMATE")),1,0) -> 1 | AO53: Recorded closed — inherited evidence | AP53: Inherited v2.22.0 intended record; no new runtime certification in this repair. | AR53: INHERITED ESTIMATE | AS53: =IF(AM53=1,J53,"") -> 10 | AT53: =IF(AND(AM53=1,ISNUMBER(R53)),R53,"") -> 4.25 | AU53: NOT SOURCE-REVIEWED IN THIS PASS | AY53: NOT ESTIMATED IN THIS PASS
A54: T-205 | B54: M2 | C54: P1 | D54: Frontend global suite termination and machine-readable gate | E54: Frontend | F54: Test infrastructure | G54: Very Important | H54: Make the global frontend unit/component suite terminate deterministically, produce a machine-readable result, and fail the pipeline on non-termination, timeout, skipped mandatory tests or leaked handles. | I54: Run the full suite twice from clean processes under the declared timeout; both terminate with identical pass/fail/skip counts and machine-readable output. Inject a leaked handle/non-terminating test and prove the gate goes red. | J54: 8 | K54: Done | L54: Worker 2 | M54: T-201 | N54: T-150; T-248; T-250; T-255; T-257 | O54: M2: ~1 month from owner planning checkpoint; exact date not committed | P54: Release 1 MUST | Q54: Frontend test infrastructure | R54: 3.2 | S54: M2-P1 | T54: CLOSED BASELINE — no new start gate and no re-execution implied. Preserve accepted closure and clean owned scope; reopen only on a concrete, separately recorded regression. Downstream consumes the frozen contract. | U54: Frontend test runner/config only. | V54: T-205 remains closed. Deterministic suite-truth mutations are owned by T-250; do not amend or reopen T-205 for product/test corrections. | W54: Product Foundation & Release Truth | X54: CENTRAL 30-Aug-2026: T-205 CLOSED GREEN at b7fcc890. The gate correctly reports suite truth; bounded corrections are a separate explicit task. | Y54: b7fcc890 — Gate the frontend suite on deterministic termination and machine-readable evidence | Z54: 46264 | AA54: L8.2 | AB54: Test architecture with disposable isolated databases | AD54: Validate | AE54: D2; D5 | AF54: Core | AG54: R1 | AH54: Advances | AI54: =IF(Y54="","",Y54) -> b7fcc890 — Gate the frontend suite on deterministic termination and machine-readable evidence | AJ54: Inherited baseline estimate | AK54: v4.11.1 | AL54: Chapters 3/4 v4.10.3 — MD + illustrated Word; UI Coverage / UI Controls in this workbook | AM54: =IF(AND(ISNUMBER(J54),OR(AR54="INHERITED ESTIMATE",AR54="CONFIRMED ESTIMATE")),1,0) -> 1 | AO54: Recorded closed — inherited evidence | AP54: Inherited v2.22.0 intended record; no new runtime certification in this repair. | AR54: INHERITED ESTIMATE | AS54: =IF(AM54=1,J54,"") -> 8 | AT54: =IF(AND(AM54=1,ISNUMBER(R54)),R54,"") -> 3.2 | AU54: NOT SOURCE-REVIEWED IN THIS PASS | AY54: NOT ESTIMATED IN THIS PASS
A55: T-206 | B55: M2 | C55: P1 | D55: Scope-aware genericity architecture gate | E55: Architecture | F55: Genericity | G55: Critical | H55: Create a scope-aware architecture test that forbids customer/demo/industry vocabulary and compiled customer dimension/grain authorities inside generic runtime/engine/API contracts while allowing that vocabulary in explicitly classified fixtures, mappings and documentation. Include detection of compiled dimension arrays and implicit grain defaults. | I55: Falsify the gate with a generic-runtime 'coil' fallback, a compiled customer dimension, and an industry-specific class; each fails. The same terms in approved fixture paths remain allowed. Gate consumes configured path/authority classes, not a naive whole-repo negative text scan. | J55: 8 | K55: Done | L55: Worker 3 | M55: T-201 | N55: T-093; T-213 | O55: M2: ~1 month from owner planning checkpoint; exact date not committed | P55: Release 1 MUST | Q55: Architecture/test | R55: 2 | S55: M2-P1 | T55: CLOSED BASELINE — no new start gate and no re-execution implied. Preserve accepted closure and clean owned scope; reopen only on a concrete, separately recorded regression. Downstream consumes the frozen contract. | U55: Architecture/genericity tests only; no W1 schema or W2 UI mutation. | V55: Violations are routed to the owning task/file; Worker 3 does not fix foreign files. | W55: Product Foundation & Release Truth | X55: M2 P1 — Product Foundation & Release Truth. Release 1 is genuine early production / first-week customer work. | Y55: Not recovered from reviewed sessions | AA55: L5.1 | AB55: Canonical entity catalogue | AD55: Validate | AE55: D1; D5 | AF55: Core | AG55: R1 | AH55: Advances | AI55: =IF(Y55="","",Y55) -> Not recovered from reviewed sessions | AJ55: Inherited baseline estimate | AK55: v4.11.1 | AL55: Chapters 3/4 v4.10.3 — MD + illustrated Word; UI Coverage / UI Controls in this workbook | AM55: =IF(AND(ISNUMBER(J55),OR(AR55="INHERITED ESTIMATE",AR55="CONFIRMED ESTIMATE")),1,0) -> 1 | AO55: Recorded closed — inherited evidence | AP55: Inherited v2.22.0 intended record; no new runtime certification in this repair. | AR55: INHERITED ESTIMATE | AS55: =IF(AM55=1,J55,"") -> 8 | AT55: =IF(AND(AM55=1,ISNUMBER(R55)),R55,"") -> 2 | AU55: NOT SOURCE-REVIEWED IN THIS PASS | AY55: NOT ESTIMATED IN THIS PASS
A56: T-207 | B56: M2 | C56: P2 | D56: Connector capability truth: stop advertising unimplemented browse/read/subscription | E56: Acquisition | F56: Connector truth | G56: Critical | H56: Make connector capability metadata executable truth. Current OPC/historian configuration validation or deterministic sample generation must not advertise live browse/bounded-read/subscription unless the connector build executes and tests that operation. | I56: Against the current implementation, unsupported browse/read/subscription report false/unavailable and attempts return typed OT01 rather than fabricated data. Add a contract test that makes any future advertised capability fail until an executable implementation passes. | J56: 6 | K56: Done | L56: Worker 1 | M56: T-201 | N56: T-150; T-224; T-247; T-254; T-266; T-268 | O56: M2: ~1 month from owner planning checkpoint; exact date not committed | P56: Release 1 MUST | Q56: Backend contract | R56: 2.25 | S56: M2-P2 | T56: CLOSED BASELINE — no new start gate and no re-execution implied. Preserve accepted closure and clean owned scope; reopen only on a concrete, separately recorded regression. Downstream consumes the frozen contract. | U56: Connector metadata/API contract and tests. | V56: T-224..T-226 later may flip capabilities to true only by passing this contract. | W56: Day-1 Data Workbench — DB Link, Canvas, Jobs & OPC | X56: M2 P2 — Day-1 Data Workbench — DB Link, Canvas, Jobs & OPC. Release 1 is genuine early production / first-week customer work. | Y56: Not recovered from reviewed sessions | AA56: L1.4 | AB56: Connector capability truth | AD56: Build | AE56: D1; D3; D5 | AF56: Core | AG56: R1 | AH56: Advances | AI56: =IF(Y56="","",Y56) -> Not recovered from reviewed sessions | AJ56: Inherited baseline estimate | AK56: v4.11.1 | AL56: Chapters 3/4 v4.10.3 — MD + illustrated Word; UI Coverage / UI Controls in this workbook | AM56: =IF(AND(ISNUMBER(J56),OR(AR56="INHERITED ESTIMATE",AR56="CONFIRMED ESTIMATE")),1,0) -> 1 | AO56: Recorded closed — inherited evidence | AP56: Inherited v2.22.0 intended record; no new runtime certification in this repair. | AR56: INHERITED ESTIMATE | AS56: =IF(AM56=1,J56,"") -> 6 | AT56: =IF(AND(AM56=1,ISNUMBER(R56)),R56,"") -> 2.25 | AU56: SOURCE CORROBORATES CLOSED TRUTH CONTRACT | AV56: 0 | AW56: 0 | AX56: 0 | AY56: UNCONFIRMED REVIEW ESTIMATE - not P80 or elapsed | AZ56: Closed honesty contract retained; separate future live acquisition. | BA56: Backend/PlantProcess.Api/PlantConnectors/V5GaHistorianConnectorEndpoints.cs:61-108 — HistorianConnectorCapabilities | BB56: 14-Sep-2026 snapshot; later closure evidence separate; no live HEAD verification
A57: T-208 | B57: M2 | C57: P1 | D57: Generic controlled validation fixture authority and continuous-process known-answer pack | E57: Quality | F57: Test data | G57: Critical | H57: Create the dataset-neutral controlled fixture authority separate from product vocabulary. Keep Fleet v2 as legacy discrete regression oracle only; continuous-process fixture includes irregular analog samples, state intervals, counters, alarms, process windows, independent manual/business records, PLUS a declared transition/stabilisation event and conflicting multi-objective practice vectors with predeclared known answers. | I57: Fixture manifests are machine-readable, immutable by version, inaccessible as planted truth to runtime, and include SampleMean vs TimeWeightedMean, StateDuration, Delta, interval overlap, transition/stabilisation regime truth, a pooled-vs-steady-state confounding case, a known Pareto frontier, negative controls and refusal cases. Product code contains no fixture vocabulary. | J57: 10 | K57: Done | L57: Worker 3 | M57: T-201 | N57: T-209; T-211; T-216; T-217; T-218; T-234; T-238 | O57: M2: ~1 month from owner planning checkpoint; exact date not committed | P57: Release 1 MUST | Q57: Test fixture / kernel | R57: 2.5 | S57: M2-P1 | T57: CLOSED BASELINE — no new start gate and no re-execution implied. Preserve accepted closure and clean owned scope; reopen only on a concrete, separately recorded regression. Downstream consumes the frozen contract. | U57: New generic fixture/test assets only. | V57: T-211/T-217/T-219 consume this fixture; they never read planted expected answers at runtime. | W57: Product Foundation & Release Truth | X57: M2 P1 — Product Foundation & Release Truth. Release 1 is genuine early production / first-week customer work. | Y57: 969c767c — T-208: generic controlled validation fixture and continuous-process known answers | AA57: L8.2 | AB57: Test architecture with disposable isolated databases | AD57: Build | AE57: D1; D5 | AF57: Core | AG57: R1 | AH57: Advances | AI57: =IF(Y57="","",Y57) -> 969c767c — T-208: generic controlled validation fixture and continuous-process known answers | AJ57: Inherited baseline estimate | AK57: v4.11.1 | AL57: Chapters 3/4 v4.10.3 — MD + illustrated Word; UI Coverage / UI Controls in this workbook | AM57: =IF(AND(ISNUMBER(J57),OR(AR57="INHERITED ESTIMATE",AR57="CONFIRMED ESTIMATE")),1,0) -> 1 | AO57: Recorded closed — inherited evidence | AP57: Inherited v2.22.0 intended record; no new runtime certification in this repair. | AR57: INHERITED ESTIMATE | AS57: =IF(AM57=1,J57,"") -> 10 | AT57: =IF(AND(AM57=1,ISNUMBER(R57)),R57,"") -> 2.5 | AU57: NOT SOURCE-REVIEWED IN THIS PASS | AY57: NOT ESTIMATED IN THIS PASS
A58: T-209 | B58: M2 | C58: P1 | D58: Analysis Subject and Grain contract + schema-independent resolution kernel | E58: Architecture / Analytics Engine | F58: Generic subject/grain contract | G58: Critical | H58: Freeze the generic AnalysisSubject/GrainDefinition contract and a schema-independent resolver/kernel. It defines subject kinds, grain identity, time-window semantics, typed GR01 refusal and the rule that no analytical result requires a material identifier. No production migration, DI registration or canonical table edit in this task. | I58: Known-answer tests resolve discrete, equipment-window and flow-interval subjects; missing grain refuses GR01; no industry noun/material-only assumption appears in the public contract. Runs without production DB access. | J58: 6 | K58: Done | L58: Worker 3 | M58: T-208 | N58: T-094; T-210; T-214; T-231; T-234; T-253 | O58: M2: ~1 month from owner planning checkpoint; exact date not committed | P58: Release 1 MUST | Q58: Kernel/contract | R58: 1.5 | S58: M2-P1 | T58: CLOSED BASELINE — no new start gate and no re-execution implied. Preserve accepted closure and clean owned scope; reopen only on a concrete, separately recorded regression. Downstream consumes the frozen contract. | U58: New generic contract/kernel/tests only. | V58: T-231 persists this contract; downstream consumers bind to contract, not table shape. | W58: Product Foundation & Release Truth | X58: M2 P1 — Product Foundation & Release Truth. Release 1 is genuine early production / first-week customer work. | Y58: f2bafdb4 — subject not recovered | Z58: 46259 | AA58: L5.3 | AB58: Analysis Subject, grain and signal aggregation authority | AD58: Build | AE58: D1; D3; D4; D5 | AF58: Core | AG58: R1 | AH58: Advances | AI58: =IF(Y58="","",Y58) -> f2bafdb4 — subject not recovered | AJ58: Inherited baseline estimate | AK58: v4.11.1 | AL58: Chapters 3/4 v4.10.3 — MD + illustrated Word; UI Coverage / UI Controls in this workbook | AM58: =IF(AND(ISNUMBER(J58),OR(AR58="INHERITED ESTIMATE",AR58="CONFIRMED ESTIMATE")),1,0) -> 1 | AO58: Recorded closed — inherited evidence | AP58: Inherited v2.22.0 intended record; no new runtime certification in this repair. | AR58: INHERITED ESTIMATE | AS58: =IF(AM58=1,J58,"") -> 6 | AT58: =IF(AND(AM58=1,ISNUMBER(R58)),R58,"") -> 1.5 | AU58: NOT SOURCE-REVIEWED IN THIS PASS | AY58: NOT ESTIMATED IN THIS PASS
A59: T-210 | B59: M2 | C59: P1 | D59: Canonical signal and aggregation semantics authority | E59: Backend | F59: Semantic measurement authority | G59: Critical | H59: Extend parameter definitions and KPI bindings with signal_kind, aggregation_kind, interpolation, weight basis, maximum gap, quality policy, counter-reset and time basis. Remove any silent DEFAULT 'Average'. Store grammar as product-owned enums/registry; customer parameters select it. | I59: Create Analog/State/Counter definitions and prove no aggregate can execute from data_type alone. Parameter or KPI binding may declare a valid method; absent semantics returns AG01. Invalid method for signal returns AG02. Fresh DB/replay green and no default Average in canonical schema. | J59: 12 | K59: Done | L59: Worker 1 | M59: T-090; T-209 | N59: T-092; T-128; T-211; T-212; T-242 | O59: M2: ~1 month from owner planning checkpoint; exact date not committed | P59: Release 1 MUST | Q59: DB/schema authority | R59: 5.1 | S59: M2-P1 | T59: CLOSED BASELINE — no new start gate and no re-execution implied. Preserve accepted closure and clean owned scope; reopen only on a concrete, separately recorded regression. Downstream consumes the frozen contract. | U59: Parameter definitions/KPI bindings/migrations/definition contract. | V59: T-211 executes exactly this contract; no second aggregation registry. | W59: Product Foundation & Release Truth | X59: M2 P1 — Product Foundation & Release Truth. Release 1 is genuine early production / first-week customer work. | Y59: 92a655e1ddc4becedbaf89a3db96dc0d0f1eaf94 — subject not recovered | Z59: 46266 | AA59: L5.3 | AB59: Analysis Subject, grain and signal aggregation authority | AC59: L4.2 | AD59: Build | AE59: D1; D3; D5 | AF59: Core | AG59: R1 | AH59: Advances | AI59: =IF(Y59="","",Y59) -> 92a655e1ddc4becedbaf89a3db96dc0d0f1eaf94 — subject not recovered | AJ59: Inherited baseline estimate | AK59: v4.11.1 | AL59: Chapters 3/4 v4.10.3 — MD + illustrated Word; UI Coverage / UI Controls in this workbook | AM59: =IF(AND(ISNUMBER(J59),OR(AR59="INHERITED ESTIMATE",AR59="CONFIRMED ESTIMATE")),1,0) -> 1 | AO59: Recorded closed — inherited evidence | AP59: Inherited v2.22.0 intended record; no new runtime certification in this repair. | AR59: INHERITED ESTIMATE | AS59: =IF(AM59=1,J59,"") -> 12 | AT59: =IF(AND(AM59=1,ISNUMBER(R59)),R59,"") -> 5.1 | AU59: NOT SOURCE-REVIEWED IN THIS PASS | AY59: NOT ESTIMATED IN THIS PASS
A60: T-212 | B60: M2 | C60: P2 | D60: Integrate aggregation semantics into Layer-A widget/query execution | E60: Backend/Frontend | F60: Dashboard query semantics | G60: Critical | H60: Make dashboard/query aggregation resolve the canonical KPI/parameter semantics and certified kernel/database implementation. Remove raw-cap-before-aggregate and implicit average fallbacks in all customer-facing measures touched by this contract. | I60: Persisted-definition replay on discrete and continuous fixtures proves exact known answers; no raw row limit is applied before aggregate; AG01/AG02 render typed Blocked/Refused rather than API 500. Query plan performs bounded server-side aggregation. | J60: 10 | K60: Not Started | L60: Worker 2 | M60: T-202; T-210; T-211; T-092; T-234; T-235; T-236 | N60: T-150; T-247 | O60: M2: ~1 month from owner planning checkpoint; exact date not committed | P60: Release 1 MUST | Q60: Cross-layer integration | R60: 5.1428571 | S60: M2-P2 | T60: T-202 + T-210/T-211 + T-092 + committed T-234/T-235/T-236. | U60: Dashboard query service/executor + focused frontend state mapping. | V60: Consumes W1 semantics and W3 kernel; no independent aggregation rules. | W60: Day-1 Data Workbench — DB Link, Canvas, Jobs & OPC | X60: M2 P2 — Day-1 Data Workbench — DB Link, Canvas, Jobs & OPC. Release 1 is genuine early production / first-week customer work. | AA60: L3.4 | AB60: Widget catalogue and intelligence visualisation | AC60: L5.3; L4.2 | AD60: Build | AE60: D1; D2; D3; D5 | AF60: Core | AG60: R1 | AH60: Advances | AI60: =IF(Y60="","",Y60) | AJ60: Inherited baseline estimate | AK60: v4.11.1 | AL60: Chapters 3/4 v4.10.3 — MD + illustrated Word; UI Coverage / UI Controls in this workbook | AM60: =IF(AND(ISNUMBER(J60),OR(AR60="INHERITED ESTIMATE",AR60="CONFIRMED ESTIMATE")),1,0) -> 1 | AO60: Not started — no completion claimed | AP60: Inherited v2.22.0 intended record; no new runtime certification in this repair. | AR60: INHERITED ESTIMATE | AS60: =IF(AM60=1,J60,"") -> 10 | AT60: =IF(AND(AM60=1,ISNUMBER(R60)),R60,"") -> 5.1428571 | AU60: AUTHORITY EXISTS; PRODUCTION QUERY CONSUMPTION GAP | AV60: 6 | AW60: 9 | AX60: 14 | AY60: UNCONFIRMED REVIEW ESTIMATE - not P80 or elapsed | AZ60: Query integration 3/5/8 + known-answer/refusal tests 2/3/4 + closure 1/1/2. | BA60: Backend/PlantProcess.Infrastructure/Definitions/Semantics/SignalSemanticsResolver.cs:30-74 — ResolveAsync Frontend/PlantProcess.Web/src/authoring/governedBlockBinding.ts:1-9 — not analytics mathematics | BB60: 14-Sep-2026 snapshot; later closure evidence separate; no live HEAD verification
A61: T-213 | B61: M2 | C61: P2 | D61: Customer Data Intake and Capability Assessment authority | E61: Onboarding | F61: Customer data assessment | G61: Critical | H61: Create a versioned assessment workflow/report for an unknown customer: source inventory, entity/equipment map, time model, identity/join strategy, parameter catalogue, KPI candidates, references, aggregation gaps, data quality, historical coverage, reconciliation/ML eligibility, OT trial requirements and missing information. The intake MUST also capture same-calendar-window manual vs machine history availability, transition/changeover definitions and stabilisation rules, sequence/campaign boundaries, setup/preparation evidence, and customer objective sets/trade-off preferences. Accepted results become normal definitions/mappings; the assessment is not a second authority. | I61: Run against one foreign/customer-shaped fixture and produce a complete report with explicit UNKNOWN/MISSING states, including regime-context readiness and multi-objective readiness. Same-window reconciliation evidence is separately reported. No product-code change is made for customer vocabulary. Re-run after one new source/field creates a new assessment version and diff. | J61: 8 | K61: Done | L61: Worker 2 | M61: T-201; T-206 | N61: T-227; T-247 | O61: M2: ~1 month from owner planning checkpoint; exact date not committed | P61: Release 1 MUST | Q61: Backend / product workflow | R61: 3.2 | S61: M2-P2 | T61: CLOSED BASELINE — no new start gate and no re-execution implied. Preserve accepted closure and clean owned scope; reopen only on a concrete, separately recorded regression. Downstream consumes the frozen contract. | U61: Onboarding assessment service/report; no customer-specific schema code. | V61: Mappings/definitions become canonical through existing authorities; report does not become a shadow registry. | W61: Day-1 Data Workbench — DB Link, Canvas, Jobs & OPC | X61: M2 P2 — Day-1 Data Workbench — DB Link, Canvas, Jobs & OPC. Release 1 is genuine early production / first-week customer work. | Y61: 2748c7fba8a5c4763bc19112ce57e484cea5b9bb — subject not recovered | Z61: 46265 | AA61: L1.2 | AB61: Dataset registration and source selection | AC61: L1.1; L7.8 | AD61: Build | AE61: D1; D5 | AF61: Core | AG61: R1 | AH61: Advances | AI61: =IF(Y61="","",Y61) -> 2748c7fba8a5c4763bc19112ce57e484cea5b9bb — subject not recovered | AJ61: Inherited baseline estimate | AK61: v4.11.1 | AL61: Chapters 3/4 v4.10.3 — MD + illustrated Word; UI Coverage / UI Controls in this workbook | AM61: =IF(AND(ISNUMBER(J61),OR(AR61="INHERITED ESTIMATE",AR61="CONFIRMED ESTIMATE")),1,0) -> 1 | AO61: Recorded closed — inherited evidence | AP61: Inherited v2.22.0 intended record; no new runtime certification in this repair. | AR61: INHERITED ESTIMATE | AS61: =IF(AM61=1,J61,"") -> 8 | AT61: =IF(AND(AM61=1,ISNUMBER(R61)),R61,"") -> 3.2 | AU61: SOURCE CORROBORATES CLOSED PRODUCER | AV61: 0 | AW61: 0 | AX61: 0 | AY61: UNCONFIRMED REVIEW ESTIMATE - not P80 or elapsed | AZ61: Original producer closure retained; no duplicate intake engine. | BA61: Backend/PlantProcess.Api/Endpoints/CustomerAssessmentEndpoints.cs:86-125 — assessment routes and tenant gate | BB61: 14-Sep-2026 snapshot; later closure evidence separate; no live HEAD verification
A62: T-215 | B62: M2 | C62: P3 | D62: Reference gap, attainment and envelope measures in registry/BI | E62: Frontend/Backend | F62: Reference analytics | G62: Very Important | H62: Expose governed derived measures: GapToReference, NormalizedDeviation, InEnvelope, DistanceToBoundary and Attainment where mathematically valid. Bind them as registry measures without creating a second reference authority. | I62: Top reference cases higher-is-better, lower-is-better and inside-range produce known answers and correct labels/provenance. An inapplicable attainment formula refuses rather than displaying a misleading percentage. Measures are usable in Page Builder without code per customer reference. | J62: 10 | K62: Not Started | L62: Worker 2 | M62: T-092; T-214; T-232 | N62: T-150; T-222 | O62: M2: ~1 month from owner planning checkpoint; exact date not committed | P62: Release 1 MUST | Q62: Frontend/backend integration | R62: 4 | S62: M2-P3 | T62: T-092 + T-214. | U62: Registry projection + query measures + widget labels. | V62: Consume reference ID/version and scoring semantics; no local UI formula. | W62: Enterprise BI & Customer Experience | X62: M2 P3 — Enterprise BI & Customer Experience. Release 1 is genuine early production / first-week customer work. | AA62: L9.1 | AB62: Performance Reference | AC62: L3.4 | AD62: Build | AE62: D2; D3; D5 | AF62: Core | AG62: R1 | AH62: Advances | AI62: =IF(Y62="","",Y62) | AJ62: Inherited baseline estimate | AK62: v4.11.1 | AL62: Chapters 3/4 v4.10.3 — MD + illustrated Word; UI Coverage / UI Controls in this workbook v2.23.0 — T-265 provides the active M2 reference/measure direction and bound-result UI; T-267 expands the deferred authoring depth. Do not introduce a second Performance Reference authority. | AM62: =IF(AND(ISNUMBER(J62),OR(AR62="INHERITED ESTIMATE",AR62="CONFIRMED ESTIMATE")),1,0) -> 1 | AO62: Not started — no completion claimed | AP62: Inherited v2.22.0 intended record; no new runtime certification in this repair. | AR62: INHERITED ESTIMATE | AS62: =IF(AM62=1,J62,"") -> 10 | AT62: =IF(AND(AM62=1,ISNUMBER(R62)),R62,"") -> 4 | AU62: NOT SOURCE-REVIEWED IN THIS PASS | AY62: NOT ESTIMATED IN THIS PASS
A63: T-216 | B63: M2 | C63: P1 | D63: Source Time Authority contract and timestamp-semantics kernel | E63: Architecture / Analytics Engine | F63: Temporal authority contract | G63: Critical | H63: Freeze the per-source time contract: timezone, timestamp basis/origin, DST policy, clock reference, observed skew, maximum tolerated skew, and source/server/ingest timestamp semantics. No production persistence in this task. | I63: Known-answer contract tests distinguish source/server/ingest timestamps and prove skew beyond tolerance yields TemporalUncertain rather than conflict. Runs without production DB access. | J63: 5 | K63: Done | L63: Worker 3 | M63: T-208 | N63: T-200; T-217; T-233 | O63: M2: ~1 month from owner planning checkpoint; exact date not committed | P63: Release 1 MUST | Q63: Kernel/contract | R63: 1.25 | S63: M2-P1 | T63: CLOSED BASELINE — no new start gate and no re-execution implied. Preserve accepted closure and clean owned scope; reopen only on a concrete, separately recorded regression. Downstream consumes the frozen contract. | U63: Temporal contract/tests only. | V63: T-233 persists source-time authority; T-217 consumes contract without waiting for persistence. | W63: Product Foundation & Release Truth | X63: M2 P1 — Product Foundation & Release Truth. Release 1 is genuine early production / first-week customer work. | Y63: ea9103fd — Establish source time authority for plant timestamps | Z63: 46259 | AA63: L1.5 | AB63: Acquisition provenance and source lineage | AC63: L5.5 | AD63: Build | AE63: D1; D3; D5 | AF63: Core | AG63: R1 | AH63: Advances | AI63: =IF(Y63="","",Y63) -> ea9103fd — Establish source time authority for plant timestamps | AJ63: Inherited baseline estimate | AK63: v4.11.1 | AL63: Chapters 3/4 v4.10.3 — MD + illustrated Word; UI Coverage / UI Controls in this workbook | AM63: =IF(AND(ISNUMBER(J63),OR(AR63="INHERITED ESTIMATE",AR63="CONFIRMED ESTIMATE")),1,0) -> 1 | AO63: Recorded closed — inherited evidence | AP63: Inherited v2.22.0 intended record; no new runtime certification in this repair. | AR63: INHERITED ESTIMATE | AS63: =IF(AM63=1,J63,"") -> 5 | AT63: =IF(AND(AM63=1,ISNUMBER(R63)),R63,"") -> 1.25 | AU63: NOT SOURCE-REVIEWED IN THIS PASS | AY63: NOT ESTIMATED IN THIS PASS
A64: T-222 | B64: M2 | C64: P3 | D64: D1/D4 reconciliation evidence surface and reference overlay | E64: Frontend | F64: Reconciliation UI | G64: Very Important | H64: Render reconciliation cases through existing Findings/Interactive Workspace paths with reference overlays, causal-confidence level and transition/stabilisation regime evidence from T-236. No oil-specific page. September surface consumes the governed kernel result seam; canonical reconciliation tables remain post-demo. | I64: Customer-shaped historical fixture shows one case end-to-end; all values/evidence open; TemporalUncertain and MissingEvidence have distinct wording; no person/lie wording; cross-filtering remains functional and route/session gates stay green. | J64: 10 | K64: Not Started | L64: Worker 2 | M64: T-219; T-220; T-215; T-203; T-204 | N64: T-150 | O64: M2: ~1 month from owner planning checkpoint; exact date not committed | P64: Release 1 MUST | Q64: Frontend integration | R64: 4.25 | S64: M2-P3 | T64: T-219/T-220 result contract + T-215 + T-203/T-204. Do not create a demo-only store. | U64: D1/D4 generic components only; no new oil route. | V64: Use existing governed evidence/result contract. T-221 later changes persistence behind the contract without UI redesign. | W64: Enterprise BI & Customer Experience | X64: M2 P3 — Enterprise BI & Customer Experience. Release 1 is genuine early production / first-week customer work. | AA64: L10.3 | AB64: Operational evidence reconciliation | AD64: Build | AE64: D2; D5 | AF64: Advanced | AG64: R1 | AH64: Advances | AI64: =IF(Y64="","",Y64) | AJ64: Inherited baseline estimate | AK64: v4.11.1 | AL64: Chapters 3/4 v4.10.3 — MD + illustrated Word; UI Coverage / UI Controls in this workbook v2.23.0 — T-265 provides the Release-1 reconciliation evidence/result/refusal surfaces. Use the canonical result envelope and citation references, not local display calculations. | AM64: =IF(AND(ISNUMBER(J64),OR(AR64="INHERITED ESTIMATE",AR64="CONFIRMED ESTIMATE")),1,0) -> 1 | AO64: Not started — no completion claimed | AP64: Inherited v2.22.0 intended record; no new runtime certification in this repair. | AR64: INHERITED ESTIMATE | AS64: =IF(AM64=1,J64,"") -> 10 | AT64: =IF(AND(AM64=1,ISNUMBER(R64)),R64,"") -> 4.25 | AU64: NOT SOURCE-REVIEWED IN THIS PASS | AY64: NOT ESTIMATED IN THIS PASS
A65: T-137 | B65: M2 | C65: P4 | D65: ModelServingRuntime and model-gateway adapter, isolated from the presentation dock | E65: AI+ML | F65: LLM runtime | G65: Very Important | H65: Replace the obsolete provider-specific POST assumption with a replaceable ModelServingRuntime plus model-gateway adapter. Support self-hosted/private/BYOM endpoints, minimum-scoped evidence payloads, provider/model release identity, timeout/cancellation and no-unapproved-fallback. IMPLEMENT NOW ONLY AS AN ISOLATED MODULE: do not register it into the current assistant DI or change the M1 dock/runtime. Canonical wiring happens in T-138. | I65: Standalone contract tests run against a deterministic fake runtime and an HTTP translating stub. They prove minimum-scoped payload, timeout/cancel, governed provider/model identity, and refusal on unapproved fallback. A repository dependency test proves no production assistant registration or M1 route/file changed in this task. | J65: 10 | K65: Done | L65: Worker 3 | N65: T-122; T-138; T-246 | O65: M2: ~1 month from owner planning checkpoint; exact date not committed | P65: Release 1 MUST | Q65: Closed | R65: 0 | S65: M2-P4 | T65: CLOSED BASELINE — no new start gate and no re-execution implied. Preserve accepted closure and clean owned scope; reopen only on a concrete, separately recorded regression. Downstream consumes the frozen contract. | U65: No active lock. | V65: None — preserve evidence. | W65: Industrial Intelligence — References, Reconciliation & Assistant | X65: M2 P4 — Industrial Intelligence — Reference, Reconciliation & Assistant. Release 1 is genuine early production / first-week customer work. | Y65: Not recovered from reviewed sessions | AA65: L4.8 | AB65: Model registry, promotion, serving and fallback | AD65: Build | AE65: D3; D5 | AF65: Core | AG65: R1 | AH65: Advances | AI65: =IF(Y65="","",Y65) -> Not recovered from reviewed sessions | AJ65: Inherited baseline estimate | AK65: v4.11.1 | AL65: Chapters 3/4 v4.10.3 — MD + illustrated Word; UI Coverage / UI Controls in this workbook | AM65: =IF(AND(ISNUMBER(J65),OR(AR65="INHERITED ESTIMATE",AR65="CONFIRMED ESTIMATE")),1,0) -> 1 | AO65: Recorded closed — inherited evidence | AP65: Inherited v2.22.0 intended record; no new runtime certification in this repair. | AR65: INHERITED ESTIMATE | AS65: =IF(AM65=1,J65,"") -> 10 | AT65: =IF(AND(AM65=1,ISNUMBER(R65)),R65,"") -> 0 | AU65: NOT SOURCE-REVIEWED IN THIS PASS | AY65: NOT ESTIMATED IN THIS PASS
A66: T-168 | B66: M2 | C66: P4 | D66: Versioned C#↔Python ML job protocol and isolated runtime harness | E66: AI+ML | F66: ML runtime | G66: Critical | H66: Build the schema-independent execution protocol between the .NET job runner and Python ML processes. A versioned job spec carries job/tenant/site identity, model family, semantic manifest handle when available, snapshot/artifact URI+hash, seed, code identity, resource/cancellation/checkpoint settings and output location. Python returns a versioned result manifest with terminal state, metrics, artifact hashes, warnings/refusal and checkpoint identity. This task is deliberately NOT registered into production DI, scheduler or presentation runtime. | I66: Run deterministic fake trainers through success, honest refusal, crash, timeout, cancellation and checkpoint/resume. C# must preserve stdout/stderr and exit identity without parsing free-form text as truth. Re-running the same seeded fixture yields the same result-manifest content hashes. A dependency test proves no current M1 runtime registration changed. | J66: 12 | K66: Done | L66: Worker 3 | N66: T-122; T-175; T-187 | O66: M2: ~1 month from owner planning checkpoint; exact date not committed | P66: Release 1 MUST | Q66: Closed | R66: 0 | S66: M2-P4 | T66: CLOSED BASELINE — no new start gate and no re-execution implied. Preserve accepted closure and clean owned scope; reopen only on a concrete, separately recorded regression. Downstream consumes the frozen contract. | U66: No active lock. | V66: None — preserve evidence. | W66: Industrial Intelligence — References, Reconciliation & Assistant | X66: M2 P4 — Industrial Intelligence — Reference, Reconciliation & Assistant. Release 1 is genuine early production / first-week customer work. | Y66: 16ea041a; 94ab4e40; 723b9434; 6aef283f; ef588f0c — multi-commit runtime/protocol/CI closure | AA66: L4.4 | AB66: Learned models MF-01 / MF-03 / MF-04 | AC66: L8.4 | AD66: Build | AE66: D3; D5 | AF66: Core | AG66: R1 | AH66: Advances | AI66: =IF(Y66="","",Y66) -> 16ea041a; 94ab4e40; 723b9434; 6aef283f; ef588f0c — multi-commit runtime/protocol/CI closure | AJ66: Inherited baseline estimate | AK66: v4.11.1 | AL66: Chapters 3/4 v4.10.3 — MD + illustrated Word; UI Coverage / UI Controls in this workbook | AM66: =IF(AND(ISNUMBER(J66),OR(AR66="INHERITED ESTIMATE",AR66="CONFIRMED ESTIMATE")),1,0) -> 1 | AO66: Recorded closed — inherited evidence | AP66: Inherited v2.22.0 intended record; no new runtime certification in this repair. | AR66: INHERITED ESTIMATE | AS66: =IF(AM66=1,J66,"") -> 12 | AT66: =IF(AND(AM66=1,ISNUMBER(R66)),R66,"") -> 0 | AU66: NOT SOURCE-REVIEWED IN THIS PASS | AY66: NOT ESTIMATED IN THIS PASS
A67: T-169 | B67: M2 | C67: P4 | D67: Typed columnar training-artifact library and B-03 harness | E67: AI+ML | F67: Data artifacts | G67: Critical | H67: Implement a typed columnar artifact abstraction used by sealed feature snapshots. Parquet/Arrow/equivalent remain implementation candidates behind the contract. Own schema/type mapping, column projection, content hash, byte/row counts, deterministic read order, corruption detection and a benchmark hook for B-03. No database table is the training read path and this task does not create final persistence. | I67: Write and read the same representative fixture through each enabled candidate. Assert stable row/schema/content identity, projected-column reads, bounded memory and explicit refusal for unsupported/corrupt schemas. Produce B-03 benchmark output format without choosing a winner or guessing a production threshold. | J67: 10 | K67: Done | L67: Worker 3 | N67: T-175; T-184; T-187 | O67: M2: ~1 month from owner planning checkpoint; exact date not committed | P67: Release 1 MUST | Q67: Closed | R67: 0 | S67: M2-P4 | T67: CLOSED BASELINE — no new start gate and no re-execution implied. Preserve accepted closure and clean owned scope; reopen only on a concrete, separately recorded regression. Downstream consumes the frozen contract. | U67: No active lock. | V67: None — preserve evidence. | W67: Industrial Intelligence — References, Reconciliation & Assistant | X67: M2 P4 — Industrial Intelligence — Reference, Reconciliation & Assistant. Release 1 is genuine early production / first-week customer work. | Y67: a887c554 — T-169 Pack 1: typed columnar artifact contract, Parquet and Arrow IPC adapters, two hashes, B-03 hook | Z67: 46247 | AA67: L4.3 | AB67: Feature engineering and incremental feature refresh | AD67: Build | AE67: D3; D5 | AF67: Core | AG67: R1 | AH67: Advances | AI67: =IF(Y67="","",Y67) -> a887c554 — T-169 Pack 1: typed columnar artifact contract, Parquet and Arrow IPC adapters, two hashes, B-03 hook | AJ67: Inherited baseline estimate | AK67: v4.11.1 | AL67: Chapters 3/4 v4.10.3 — MD + illustrated Word; UI Coverage / UI Controls in this workbook | AM67: =IF(AND(ISNUMBER(J67),OR(AR67="INHERITED ESTIMATE",AR67="CONFIRMED ESTIMATE")),1,0) -> 1 | AO67: Recorded closed — inherited evidence | AP67: Inherited v2.22.0 intended record; no new runtime certification in this repair. | AR67: INHERITED ESTIMATE | AS67: =IF(AM67=1,J67,"") -> 10 | AT67: =IF(AND(AM67=1,ISNUMBER(R67)),R67,"") -> 0 | AU67: NOT SOURCE-REVIEWED IN THIS PASS | AY67: NOT ESTIMATED IN THIS PASS
A68: T-170 | B68: M2 | C68: P4 | D68: Chunked sequence-artifact library and bounded loader | E68: AI+ML | F68: Data artifacts | G68: Critical | H68: Implement the schema-independent sequence payload contract: immutable chunked typed numeric arrays, compression seam, chunk index, content hashes and bounded streaming/memory-mapped reads where supported. PostgreSQL array payloads are forbidden; final sequence_manifests persistence is T-185. Include the B-04 benchmark hook. | I68: Generate a large synthetic multi-channel sequence fixture, read it without whole-payload materialisation, verify chunk order/content hash and detect a corrupted/missing chunk. Compare at least two chunk/compression settings and emit B-04 measurements without hardcoding the selected values. | J68: 10 | K68: Done | L68: Worker 3 | N68: T-185; T-187 | O68: M2: ~1 month from owner planning checkpoint; exact date not committed | P68: Release 1 MUST | Q68: Closed | R68: 0 | S68: M2-P4 | T68: CLOSED BASELINE — no new start gate and no re-execution implied. Preserve accepted closure and clean owned scope; reopen only on a concrete, separately recorded regression. Downstream consumes the frozen contract. | U68: No active lock. | V68: None — preserve evidence. | W68: Industrial Intelligence — References, Reconciliation & Assistant | X68: M2 P4 — Industrial Intelligence — Reference, Reconciliation & Assistant. Release 1 is genuine early production / first-week customer work. | Y68: 5a216483 — T-170 Chunked sequence-artifact library and bounded loader | Z68: 46249 | AA68: L4.3 | AB68: Feature engineering and incremental feature refresh | AD68: Build | AE68: D3; D5 | AF68: Core | AG68: R1 | AH68: Advances | AI68: =IF(Y68="","",Y68) -> 5a216483 — T-170 Chunked sequence-artifact library and bounded loader | AJ68: Inherited baseline estimate | AK68: v4.11.1 | AL68: Chapters 3/4 v4.10.3 — MD + illustrated Word; UI Coverage / UI Controls in this workbook | AM68: =IF(AND(ISNUMBER(J68),OR(AR68="INHERITED ESTIMATE",AR68="CONFIRMED ESTIMATE")),1,0) -> 1 | AO68: Recorded closed — inherited evidence | AP68: Inherited v2.22.0 intended record; no new runtime certification in this repair. | AR68: INHERITED ESTIMATE | AS68: =IF(AM68=1,J68,"") -> 10 | AT68: =IF(AND(AM68=1,ISNUMBER(R68)),R68,"") -> 0 | AU68: NOT SOURCE-REVIEWED IN THIS PASS | AY68: NOT ESTIMATED IN THIS PASS
A69: T-171 | B69: M2 | C69: P4 | D69: Capability Profiler and eligibility/refusal kernel | E69: Engine | F69: Readiness | G69: Critical | H69: Implement a pure, industry-neutral Capability Profiler that converts declared semantic/data-product facts into measured capability states for statistics, similarity, novelty, supervised prediction, practice and remediation. Include collapsed-dimension handling, genealogy strength, outcome/label availability, population sufficiency and the canonical terminal/refusal taxonomy. No database access or presentation wiring. | I69: Table-driven fixtures cover a rich plant, a sparse plant, no-genealogy, single-level context, missing labels and unsupported method cases. The same input produces the same capability profile; a collapsed single-level dimension is removed rather than treated as an error; method absence is NOT_APPLICABLE rather than a false zero-variance claim. | J69: 10 | K69: Done | L69: Worker 3 | N69: T-131; T-186; T-187 | O69: M2: ~1 month from owner planning checkpoint; exact date not committed | P69: Release 1 MUST | Q69: Closed | R69: 0 | S69: M2-P4 | T69: CLOSED BASELINE — no new start gate and no re-execution implied. Preserve accepted closure and clean owned scope; reopen only on a concrete, separately recorded regression. Downstream consumes the frozen contract. | U69: No active lock. | V69: None — preserve evidence. | W69: Industrial Intelligence — References, Reconciliation & Assistant | X69: M2 P4 — Industrial Intelligence — Reference, Reconciliation & Assistant. Release 1 is genuine early production / first-week customer work. | Y69: 95cc019c — Capability Profiler Pack 2 | AA69: L4.1 | AB69: Readiness gate and statistical discipline chain | AD69: Build | AE69: D3; D5 | AF69: Core | AG69: R1 | AH69: Advances | AI69: =IF(Y69="","",Y69) -> 95cc019c — Capability Profiler Pack 2 | AJ69: Inherited baseline estimate | AK69: v4.11.1 | AL69: Chapters 3/4 v4.10.3 — MD + illustrated Word; UI Coverage / UI Controls in this workbook | AM69: =IF(AND(ISNUMBER(J69),OR(AR69="INHERITED ESTIMATE",AR69="CONFIRMED ESTIMATE")),1,0) -> 1 | AO69: Recorded closed — inherited evidence | AP69: Inherited v2.22.0 intended record; no new runtime certification in this repair. | AR69: INHERITED ESTIMATE | AS69: =IF(AM69=1,J69,"") -> 10 | AT69: =IF(AND(AM69=1,ISNUMBER(R69)),R69,"") -> 0 | AU69: NOT SOURCE-REVIEWED IN THIS PASS | AY69: NOT ESTIMATED IN THIS PASS
A70: T-172 | B70: M2 | C70: P4 | D70: MF-01 Process Encoder runtime behind a replaceable contract | E70: AI+ML | F70: MF-01 Encoder | G70: Very Important | H70: Implement ProcessEncoder as a replaceable runtime with a PyTorch candidate, channel_set_version, deterministic seed/environment manifest, train/encode/artifact contracts and serving-cost telemetry. The encoder is optional and no production promotion decision is made here. It consumes only sealed typed sequence/snapshot artifacts and never live feature_store. | I70: Train/encode a deterministic fixture twice and compare artifact/embedding reproducibility within declared tolerance. Change channel_set_version and prove the prior encoder is incompatible. Measure metric-lift input hooks, p95 cost and artifact size for B-05; no task declares the encoder deployable merely because it trains. | J70: 12 | K70: Done | L70: Worker 3 | N70: T-187 | O70: M2: ~1 month from owner planning checkpoint; exact date not committed | P70: Release 1 MUST | Q70: Closed | R70: 0 | S70: M2-P4 | T70: CLOSED BASELINE — no new start gate and no re-execution implied. Preserve accepted closure and clean owned scope; reopen only on a concrete, separately recorded regression. Downstream consumes the frozen contract. | U70: No active lock. | V70: None — preserve evidence. | W70: Industrial Intelligence — References, Reconciliation & Assistant | X70: M2 P4 — Industrial Intelligence — Reference, Reconciliation & Assistant. Release 1 is genuine early production / first-week customer work. | Y70: d4321856 — T-172 MF-01 Process Encoder runtime behind a replaceable contract | Z70: 46249 | AA70: L4.4 | AB70: Learned models MF-01 / MF-03 / MF-04 | AD70: Build | AE70: D1; D3; D5 | AF70: Core | AG70: R1 | AH70: Advances | AI70: =IF(Y70="","",Y70) -> d4321856 — T-172 MF-01 Process Encoder runtime behind a replaceable contract | AJ70: Inherited baseline estimate | AK70: v4.11.1 | AL70: Chapters 3/4 v4.10.3 — MD + illustrated Word; UI Coverage / UI Controls in this workbook | AM70: =IF(AND(ISNUMBER(J70),OR(AR70="INHERITED ESTIMATE",AR70="CONFIRMED ESTIMATE")),1,0) -> 1 | AO70: Recorded closed — inherited evidence | AP70: Inherited v2.22.0 intended record; no new runtime certification in this repair. | AR70: INHERITED ESTIMATE | AS70: =IF(AM70=1,J70,"") -> 12 | AT70: =IF(AND(AM70=1,ISNUMBER(R70)),R70,"") -> 0 | AU70: NOT SOURCE-REVIEWED IN THIS PASS | AY70: NOT ESTIMATED IN THIS PASS
