Workbook

Sheet Current Authority
A1: PPIQ BACKLOG v2.24.0 — Industrial Integration authority 16Sep2026
A2: Authority | B2: Current value | C2: As of | D2: Meaning
A3: Functional Design | B3: v4.11.0 | C3: 2026-09-16 | D3: Owner-approved Industrial Integration Contract integrated into Chapters 1–6: stable field/layout identity, Time/Value-change/Trigger-counter policies, continuous acquisition sessions with finite accepted batches, logical Dump Store, source-data lifecycle/capacity truth. Existing closed work remains historical evidence.
A4: Execution Backlog | B4: v2.24.0 | C4: 2026-09-16 | D4: Meaningful authority revision: adds T-268..T-275 and amends affected OPC/design acceptance. No closed task is reopened; expanded industrial-integration scope is separately owned.
A5: Integrated Chapter 3/4 visuals | B5: v4.11.0 target contract; illustrated regeneration pending T-265/T-266 | C5: 2026-09-16 | D5: Functional contract is authoritative now; T-265/T-266 still own derived visual/prototype/illustrated synchronization and do not receive runtime credit.
A6: Release 1 | B6: M2 — approx. one month from owner planning checkpoint | C6: Owner planning basis | D6: No new absolute delivery date.
A7: Release 2 | B7: M3 — 45 days after M2 completion | C7: Owner planning basis | D7: 45 days after M2 completion; prior approved release allocation retained.
A8: Rows and retirements | B8: 187 active; T-105→T-104; T-111→T-110/T-155/T-159 | C8: Adds T-268 through T-275 | D8: Eight new bounded industrial-integration execution owners. No existing task retired or reopened by this design revision.
A9: T-099 closure | B9: ca02b40ea1b69050a45cb35a3e1d64f15b1f66af | C9: Final14Sep terminal transcript inspected15Sep | D9: CLOSED GREEN/COMMITTED; exact transcript corroborated. DefinitionKind known-red remains; not release-wideGREEN.
A10: T-262 evidence | B10: CONTRACT GREEN COMMIT86e1b677; INTEGRATION UNVERIFIED | C10: Evidence from12Sep; reviewed15Sep | D10: Producer declaration is committed with backend24/24, catalogue8/8, content39/39 and authoring404/404; parent36de9370 (short). Live definition-store integration is explicitly not executed. Current row asks for needed integration closure: retain In Progress pending that disposition, but withdraw the false 'no accepted SHA/run supplied' statement. No producer rewrite. Pasted text(20260912-074928).txt | lines1229-1243; T-262 GREEN committed86e1b677212195f191697ecdca7e9441b3dbde33; parent36de9370; live definition-store integration explicitly unexecuted. Later 14-Sep coordination explicitly allocates live definition-store Gate 0 to T-261 Runner 2. Reconcile that integration gate separately; no producer rewrite.
A11: Planning estimates | B11: Existing estimates preserved; T-268..T-275 intentionally unestimated | C11: 2026-09-16 | D11: New scope is not zero hours. Source-level preflight is required before LOW/BASE/HIGH or P80 is accepted; historical OPC estimates are not silently reused for expanded v4.11.0 scope.
A12: Current task table | B12: Backlog!A1:BB188 | C12: 187 task rows | D12: Dependency validation reads the saved v2.24.0 task rows. New tasks are excluded from hour totals until explicitly estimated.
A13: Derived views | B13: Worker Tracks / Dependency Graph / Capability Map / Release Plan / dashboards | C13: v2.24.0 | D13: Formula ranges are extended through Backlog row 188. New task rows are appended to Worker Tracks and Dependency Graph.
... A31: Controlled book | B31: 12 document families / 14 physical files | C31: Owner direction — 2026-09-14 | D31: PPIQ_Definition.md registers the allowed files. The Backlog holds coverage, acceptance, validation and handoffs; no new status/JSON/README/atlas files.

Sheet Backlog
A1: Task Id | B1: Milestone Id | C1: Phase Id | D1: Task Name | E1: Module | F1: Sub-module | G1: Priority | H1: Task Description | I1: Task Validation | J1: Hours | K1: Status | L1: AI Agent Owner | M1: Depends On (IDs only) | N1: Must Precede (IDs only) | O1: Delivery Target | P1: Release Criticality | Q1: AI Execution Class | R1: AI Guarded Time P80 (h) | S1: AI Sequence Wave | T1: AI Start / Dependency Gate | U1: File / Subsystem Lock | V1: No-Rework Handoff Ruling | W1: Product Track | X1: Tech-Lead Ruling | Y1: Commit String | Z1: Commit Date | AA1: Primary Capability ID | AB1: Primary Capability Name | AC1: Secondary Capability IDs | AD1: Capability Contribution | AE1: Completeness Dimensions Targeted | AF1: Capability Requirement Class | AG1: Release Scope | AH1: Capability Closure Effect | AI1: Capability Evidence | AJ1: Estimate Basis | AK1: Design Package | AL1: UI Companion Reference | AM1: Usable scope estimate (1/0) | AN1: Contract-ready predecessors (not completion) | AO1: Evidence State | AP1: Closure Evidence Basis | AQ1: Parent Commit | AR1: Estimate Status | AS1: Usable planning hours | AT1: Usable planning P80 h | AU1: Source review coverage | AV1: Proposed remaining LOW h | AW1: Proposed remaining BASE h | AX1: Proposed remaining HIGH h | AY1: Remaining estimate confidence | AZ1: Remaining estimate basis | BA1: Source locations | BB1: Source as-of / evidence boundary
A2: T-086 | B2: M2 | C2: P1 | D2: Freeze the legacy Fleet v2 controlled regression oracle | E2: Testing | F2: Emulated sources | G2: Critical | H2: Freeze and certify the existing Fleet v2 dataset only as a legacy discrete-manufacturing regression oracle with predeclared known answers/negative controls. It is not the canonical product vocabulary, not the generic M2 fixture authority and not the source of customer schema semantics. T-208 owns new generic controlled fixtures, including the continuous-process known-answer pack. | I2: Fleet v2 is immutable and its declared phenomena/negative controls are reproducible. An architecture check proves no generic runtime/Layer-B/registry contract derives vocabulary or universal grain from Fleet. T-208 can run independently with neutral/continuous fixtures. | J2: 8 | K2: Done | L2: Worker 1 | M2: T-201 | N2: T-087; T-088; T-131 | O2: M2: ~1 month from owner planning checkpoint; exact date not committed | P2: Release 1 MUST | Q2: Integration/E2E/certification | R2: 2.72 | S2: M2-P1 | T2: CLOSED BASELINE — no new start gate and no re-execution implied. Preserve accepted closure and clean owned scope; reopen only on a concrete, separately recorded regression. Downstream consumes the frozen contract. | U2: Own canonical DB/backend/security/API/infra. No W2-owned UI/admin task files and no W3 ML/Assistant runtime. | V2: Commit before downstream consumer starts; consumer must use the contract, not redesign producer-owned semantics. | W2: Product Foundation & Release Truth | X2: M2 P1 — Product Foundation & Release Truth. Release 1 is genuine early production / first-week customer work. | Y2: 77a8ea4f — T-086: freeze the legacy regression oracle and gate generic surfaces against its vocabulary | Z2: 46259 | AA2: L8.8 | AB2: C1–C4 performance certification and golden-journey release gate | AD2: Validate | AE2: D5 | AF2: Core | AG2: R1 | AH2: Advances | AI2: =IF(Y2="","",Y2) -> 77a8ea4f — T-086: freeze the legacy regression oracle and gate generic surfaces against its vocabulary | AJ2: Inherited baseline estimate | AK2: v4.10.3 | AL2: Chapters 3/4 v4.10.3 — MD + illustrated Word; UI Coverage / UI Controls in this workbook | AM2: =IF(AND(ISNUMBER(J2),OR(AR2="INHERITED ESTIMATE",AR2="CONFIRMED ESTIMATE")),1,0) -> 1 | AO2: Recorded closed — inherited evidence | AP2: Inherited v2.22.0 intended record; no new runtime certification in this repair. | AR2: INHERITED ESTIMATE | AS2: =IF(AM2=1,J2,"") -> 8 | AT2: =IF(AND(AM2=1,ISNUMBER(R2)),R2,"") -> 2.72 | AU2: =IFERROR(INDEX('Source Review'!$B$2:$B$52,MATCH($A2,'Source Review'!$A$2:$A$52,0)),"NOT SOURCE-REVIEWED IN THIS PASS") -> NOT SOURCE-REVIEWED IN THIS PASS | AV2: =IFERROR(INDEX('Source Review'!$F$2:$F$52,MATCH($A2,'Source Review'!$A$2:$A$52,0)),"") | AW2: =IFERROR(INDEX('Source Review'!$G$2:$G$52,MATCH($A2,'Source Review'!$A$2:$A$52,0)),"") | AX2: =IFERROR(INDEX('Source Review'!$H$2:$H$52,MATCH($A2,'Source Review'!$A$2:$A$52,0)),"") | AY2: =IF(COUNTIF('Source Review'!$A$2:$A$52,$A2)>0,"UNCONFIRMED REVIEW ESTIMATE - not P80 or elapsed","NOT ESTIMATED IN THIS PASS") -> NOT ESTIMATED IN THIS PASS | AZ2: =IFERROR(INDEX('Source Review'!$I$2:$I$52,MATCH($A2,'Source Review'!$A$2:$A$52,0)),"") | BA2: =IFERROR(INDEX('Source Review'!$E$2:$E$52,MATCH($A2,'Source Review'!$A$2:$A$52,0)),"") | BB2: =IF(COUNTIF('Source Review'!$A$2:$A$52,$A2)>0,"14-Sep-2026 snapshot; later closure evidence separate; no live HEAD verification","")
A3: T-087 | B3: M2 | C3: P1 | D3: Physical three-schema migration | E3: Database | F3: Schema | G3: Critical | H3: The measured database carries twelve schemas with 162 tables in public, of which 108 use a ppiq_ name prefix, while the ruled schemas ppiq_plant and ppiq_meta exist and hold zero tables. Migrate to the three ruled schemas: ppiq_staging, ppiq_plant, ppiq_meta. The staging rename is already prepared, because the canvas reads its schema from the configuration key Prep:StagingSchema rather than a literal. | I3: Rule 2 is provable in one query on a fresh database. All application tests pass. The canvas catalogue lists tables from the renamed schema with only a configuration change. AND THE BENCHMARK SURVIVES THE MOVE: the phenomenon and benchmark harness frozen in T-086 is re-run UNCHANGED after the schema migration and produces identical results. A migration that silently alters the reference dataset destroys every comparison made against it. | J3: 12 | K3: Done | L3: Worker 1 | M3: T-086; T-088 | N3: T-089; T-099; T-102; T-112; T-114; T-128; T-196; T-233; T-251; T-252 | O3: M2: ~1 month from owner planning checkpoint; exact date not committed | P3: Release 1 MUST | Q3: DB/schema/migration | R3: 2.325 | S3: M2-P1 | T3: CLOSED BASELINE — no new start gate and no re-execution implied. Preserve accepted closure and clean owned scope; reopen only on a concrete, separately recorded regression. Downstream consumes the frozen contract. | U3: Own canonical DB/backend/security/API/infra. No W2-owned UI/admin task files and no W3 ML/Assistant runtime. | V3: Commit before downstream consumer starts; consumer must use the contract, not redesign producer-owned semantics. | W3: Product Foundation & Release Truth | X3: M2 P1 — Product Foundation & Release Truth. Release 1 is genuine early production / first-week customer work. | Y3: e7d82f078d7dfa4c1ca4ec6e88d0dbc7e1ecd6ba — subject not recovered | Z3: 46262 | AA3: L2.1 | AB3: Three-schema platform and placement law | AC3: L5.7 | AD3: Converge | AE3: D4; D5 | AF3: Core | AG3: R1 | AH3: Advances | AI3: =IF(Y3="","",Y3) -> e7d82f078d7dfa4c1ca4ec6e88d0dbc7e1ecd6ba — subject not recovered | AJ3: Inherited baseline estimate | AK3: v4.10.3 | AL3: Chapters 3/4 v4.10.3 — MD + illustrated Word; UI Coverage / UI Controls in this workbook | AM3: =IF(AND(ISNUMBER(J3),OR(AR3="INHERITED ESTIMATE",AR3="CONFIRMED ESTIMATE")),1,0) -> 1 | AO3: Recorded closed — inherited evidence | AP3: Inherited v2.22.0 intended record; no new runtime certification in this repair. | AR3: INHERITED ESTIMATE | AS3: =IF(AM3=1,J3,"") -> 12 | AT3: =IF(AND(AM3=1,ISNUMBER(R3)),R3,"") -> 2.325 | AU3: =IFERROR(INDEX('Source Review'!$B$2:$B$52,MATCH($A3,'Source Review'!$A$2:$A$52,0)),"NOT SOURCE-REVIEWED IN THIS PASS") -> NOT SOURCE-REVIEWED IN THIS PASS | AV3: =IFERROR(INDEX('Source Review'!$F$2:$F$52,MATCH($A3,'Source Review'!$A$2:$A$52,0)),"") | AW3: =IFERROR(INDEX('Source Review'!$G$2:$G$52,MATCH($A3,'Source Review'!$A$2:$A$52,0)),"") | AX3: =IFERROR(INDEX('Source Review'!$H$2:$H$52,MATCH($A3,'Source Review'!$A$2:$A$52,0)),"") | AY3: =IF(COUNTIF('Source Review'!$A$2:$A$52,$A3)>0,"UNCONFIRMED REVIEW ESTIMATE - not P80 or elapsed","NOT ESTIMATED IN THIS PASS") -> NOT ESTIMATED IN THIS PASS | AZ3: =IFERROR(INDEX('Source Review'!$I$2:$I$52,MATCH($A3,'Source Review'!$A$2:$A$52,0)),"") | BA3: =IFERROR(INDEX('Source Review'!$E$2:$E$52,MATCH($A3,'Source Review'!$A$2:$A$52,0)),"") | BB3: =IF(COUNTIF('Source Review'!$A$2:$A$52,$A3)>0,"14-Sep-2026 snapshot; later closure evidence separate; no live HEAD verification","")
A4: T-088 | B4: M2 | C4: P1 | D4: Canonical migration order and legacy script archival | E4: Database | F4: Schema | G4: Very Important | H4: Backend/database/scripts contains hotfix, repair, phase and drift-correction scripts accumulated over months, including cases where two scripts created the same table. Define one canonical ordered migration path, archive superseded scripts, and add a truth gate that no two scripts create the same table. | I4: A fresh database builds from the canonical path with no manual step. The truth gate fails if a duplicate CREATE TABLE is introduced. | J4: 12 | K4: Done | L4: Worker 1 | M4: T-086 | N4: T-087; T-089; T-112; T-128; T-251; T-252; T-256; T-260 | O4: M2: ~1 month from owner planning checkpoint; exact date not committed | P4: Release 1 MUST | Q4: DB/schema/migration | R4: 2.325 | S4: M2-P1 | T4: CLOSED BASELINE — no new start gate and no re-execution implied. Preserve accepted closure and clean owned scope; reopen only on a concrete, separately recorded regression. Downstream consumes the frozen contract. | U4: Own canonical DB/backend/security/API/infra. No W2-owned UI/admin task files and no W3 ML/Assistant runtime. | V4: Commit before downstream consumer starts; consumer must use the contract, not redesign producer-owned semantics. | W4: Product Foundation & Release Truth | X4: M2 P1 — Product Foundation & Release Truth. Release 1 is genuine early production / first-week customer work. | Y4: 6a62c9d6 — Establish canonical database migration authority | Z4: 46260 | AA4: L8.1 | AB4: Fresh install and upgrade authority | AC4: L5.7; L2.1 | AD4: Converge | AE4: D4; D5 | AF4: Core | AG4: R1 | AH4: Advances | AI4: =IF(Y4="","",Y4) -> 6a62c9d6 — Establish canonical database migration authority | AJ4: Inherited baseline estimate | AK4: v4.10.3 | AL4: Chapters 3/4 v4.10.3 — MD + illustrated Word; UI Coverage / UI Controls in this workbook | AM4: =IF(AND(ISNUMBER(J4),OR(AR4="INHERITED ESTIMATE",AR4="CONFIRMED ESTIMATE")),1,0) -> 1 | AO4: Recorded closed — inherited evidence | AP4: Inherited v2.22.0 intended record; no new runtime certification in this repair. | AR4: INHERITED ESTIMATE | AS4: =IF(AM4=1,J4,"") -> 12 | AT4: =IF(AND(AM4=1,ISNUMBER(R4)),R4,"") -> 2.325 | AU4: =IFERROR(INDEX('Source Review'!$B$2:$B$52,MATCH($A4,'Source Review'!$A$2:$A$52,0)),"NOT SOURCE-REVIEWED IN THIS PASS") -> NOT SOURCE-REVIEWED IN THIS PASS | AV4: =IFERROR(INDEX('Source Review'!$F$2:$F$52,MATCH($A4,'Source Review'!$A$2:$A$52,0)),"") | AW4: =IFERROR(INDEX('Source Review'!$G$2:$G$52,MATCH($A4,'Source Review'!$A$2:$A$52,0)),"") | AX4: =IFERROR(INDEX('Source Review'!$H$2:$H$52,MATCH($A4,'Source Review'!$A$2:$A$52,0)),"") | AY4: =IF(COUNTIF('Source Review'!$A$2:$A$52,$A4)>0,"UNCONFIRMED REVIEW ESTIMATE - not P80 or elapsed","NOT ESTIMATED IN THIS PASS") -> NOT ESTIMATED IN THIS PASS | AZ4: =IFERROR(INDEX('Source Review'!$I$2:$I$52,MATCH($A4,'Source Review'!$A$2:$A$52,0)),"") | BA4: =IFERROR(INDEX('Source Review'!$E$2:$E$52,MATCH($A4,'Source Review'!$A$2:$A$52,0)),"") | BB4: =IF(COUNTIF('Source Review'!$A$2:$A$52,$A4)>0,"14-Sep-2026 snapshot; later closure evidence separate; no live HEAD verification","")
A5: T-089 | B5: M2 | C5: P1 | D5: definition_store, definition_versions and definition_dependencies | E5: Database | F5: Definition store | G5: Critical | H5: Create the tables specified in Chapter 3 4.5.11 with immutable versions and a dependency graph, plus a trigger that rejects a dependency cycle. | I5: Integration tests: create, version, publish, and reject a cycle. Version rows must be immutable, proved by an update attempt that fails. | J5: 12 | K5: Done | L5: Worker 1 | M5: T-087; T-088 | N5: T-090; T-092; T-095; T-099; T-106; T-114; T-128; T-183; T-243; T-244 | O5: M2: ~1 month from owner planning checkpoint; exact date not committed | P5: Release 1 MUST | Q5: DB/schema/migration | R5: 2.325 | S5: M2-P1 | T5: CLOSED BASELINE — no new start gate and no re-execution implied. Preserve accepted closure and clean owned scope; reopen only on a concrete, separately recorded regression. Downstream consumes the frozen contract. | U5: Own canonical DB/backend/security/API/infra. No W2-owned UI/admin task files and no W3 ML/Assistant runtime. | V5: Commit before downstream consumer starts; consumer must use the contract, not redesign producer-owned semantics. | W5: Product Foundation & Release Truth | X5: M2 P1 — Product Foundation & Release Truth. Release 1 is genuine early production / first-week customer work. | Y5: 0fd79e5e3516cdfd0ab5a73a02e16638fd02693a — subject not recovered | AA5: L2.5 | AB5: Unified definition store and immutable target/version governance | AC5: L5.6 | AD5: Build | AE5: D4; D5 | AF5: Core | AG5: R1 | AH5: Advances | AI5: =IF(Y5="","",Y5) -> 0fd79e5e3516cdfd0ab5a73a02e16638fd02693a — subject not recovered | AJ5: Inherited baseline estimate | AK5: v4.10.3 | AL5: Chapters 3/4 v4.10.3 — MD + illustrated Word; UI Coverage / UI Controls in this workbook | AM5: =IF(AND(ISNUMBER(J5),OR(AR5="INHERITED ESTIMATE",AR5="CONFIRMED ESTIMATE")),1,0) -> 1 | AO5: Recorded closed — inherited evidence | AP5: Inherited v2.22.0 intended record; no new runtime certification in this repair. | AR5: INHERITED ESTIMATE | AS5: =IF(AM5=1,J5,"") -> 12 | AT5: =IF(AND(AM5=1,ISNUMBER(R5)),R5,"") -> 2.325 | AU5: =IFERROR(INDEX('Source Review'!$B$2:$B$52,MATCH($A5,'Source Review'!$A$2:$A$52,0)),"NOT SOURCE-REVIEWED IN THIS PASS") -> NOT SOURCE-REVIEWED IN THIS PASS | AV5: =IFERROR(INDEX('Source Review'!$F$2:$F$52,MATCH($A5,'Source Review'!$A$2:$A$52,0)),"") | AW5: =IFERROR(INDEX('Source Review'!$G$2:$G$52,MATCH($A5,'Source Review'!$A$2:$A$52,0)),"") | AX5: =IFERROR(INDEX('Source Review'!$H$2:$H$52,MATCH($A5,'Source Review'!$A$2:$A$52,0)),"") | AY5: =IF(COUNTIF('Source Review'!$A$2:$A$52,$A5)>0,"UNCONFIRMED REVIEW ESTIMATE - not P80 or elapsed","NOT ESTIMATED IN THIS PASS") -> NOT ESTIMATED IN THIS PASS | AZ5: =IFERROR(INDEX('Source Review'!$I$2:$I$52,MATCH($A5,'Source Review'!$A$2:$A$52,0)),"") | BA5: =IFERROR(INDEX('Source Review'!$E$2:$E$52,MATCH($A5,'Source Review'!$A$2:$A$52,0)),"") | BB5: =IF(COUNTIF('Source Review'!$A$2:$A$52,$A5)>0,"14-Sep-2026 snapshot; later closure evidence separate; no live HEAD verification","")
A6: T-090 | B6: M2 | C6: P1 | D6: Move all five definition kinds onto the store | E6: Backend | F6: Definition store | G6: Critical | H6: Replace the M1 compatibility adapter behind IDefinitionService with the real implementation for all five purposes: S1 Transformation, S2 Pages and widgets and filters and master items, S3 Analysis, S4 Model, S5 Log rule. The old per-artifact tables become a compatibility projection and then are retired. v2.10.1 OUTCOME SEMANTICS BINDING. As part of canonical definition convergence, bind the already-frozen SM-06 OutcomeDefinition to the canonical immutable versioned definition authority; do not design a second outcome authority. The canonical binding preserves outcome_code, outcome_type, class_taxonomy_ref, ordinal_rank_map, grain_code, detection_position_code, detection_timestamp_field, direction, unit_code, censoring_policy and definition/version identity. Any legacy ml_outcome_definitions representation may remain only as a compatibility projection during convergence and must not remain an independent semantic authority. | I6: The M1 integration test written against IDefinitionService must pass unchanged, since it references no table name. That is the proof that the visible contract did not move. Publish an SM-06 OutcomeDefinition and resolve it back by exact immutable version. Changing detection_position_code, detection_timestamp_field, grain, taxonomy, ordinal map, direction, unit or censoring policy creates a new definition version rather than silently mutating published meaning. If a compatibility outcome representation remains during convergence, prove it resolves to the same canonical definition/version and cannot diverge into a second authority. | J6: 12 | K6: Done | L6: Worker 1 | M6: T-089 | N6: T-091; T-092; T-095; T-099; T-104; T-106; T-114; T-128; T-134; T-147; T-183; T-195; T-210; T-221; T-228; T-231; T-232; T-233; T-235; T-239; T-243; T-244 | O6: M2: ~1 month from owner planning checkpoint; exact date not committed | P6: Release 1 MUST | Q6: Backend/domain contract | R6: 1.8 | S6: M2-P1 | T6: CLOSED BASELINE — no new start gate and no re-execution implied. Preserve accepted closure and clean owned scope; reopen only on a concrete, separately recorded regression. Downstream consumes the frozen contract. | U6: Own canonical DB/backend/security/API/infra. No W2-owned UI/admin task files and no W3 ML/Assistant runtime. | V6: Downstream consumers wait for the committed T-090 authority. Handover/progress notes do not substitute for closure; the pack must apply, build, test, replay and commit on the user machine. | W6: Product Foundation & Release Truth | X6: CENTRAL 30-Aug-2026: canonical definition convergence remains full scope. Deliver the standard executable PowerShell pack; no Task-ID-less changes. | Y6: a6399d9c — subject not recovered | AA6: L5.6 | AB6: Unified definition-store semantics | AC6: L2.5 | AD6: Converge | AE6: D3; D4; D5 | AF6: Core | AG6: R1 | AH6: Advances | AI6: =IF(Y6="","",Y6) -> a6399d9c — subject not recovered | AJ6: Inherited baseline estimate | AK6: v4.10.3 | AL6: Chapters 3/4 v4.10.3 — MD + illustrated Word; UI Coverage / UI Controls in this workbook | AM6: =IF(AND(ISNUMBER(J6),OR(AR6="INHERITED ESTIMATE",AR6="CONFIRMED ESTIMATE")),1,0) -> 1 | AO6: Recorded closed — inherited evidence | AP6: Inherited v2.22.0 intended record; no new runtime certification in this repair. | AR6: INHERITED ESTIMATE | AS6: =IF(AM6=1,J6,"") -> 12 | AT6: =IF(AND(AM6=1,ISNUMBER(R6)),R6,"") -> 1.8 | AU6: =IFERROR(INDEX('Source Review'!$B$2:$B$52,MATCH($A6,'Source Review'!$A$2:$A$52,0)),"NOT SOURCE-REVIEWED IN THIS PASS") -> NOT SOURCE-REVIEWED IN THIS PASS | AV6: =IFERROR(INDEX('Source Review'!$F$2:$F$52,MATCH($A6,'Source Review'!$A$2:$A$52,0)),"") | AW6: =IFERROR(INDEX('Source Review'!$G$2:$G$52,MATCH($A6,'Source Review'!$A$2:$A$52,0)),"") | AX6: =IFERROR(INDEX('Source Review'!$H$2:$H$52,MATCH($A6,'Source Review'!$A$2:$A$52,0)),"") | AY6: =IF(COUNTIF('Source Review'!$A$2:$A$52,$A6)>0,"UNCONFIRMED REVIEW ESTIMATE - not P80 or elapsed","NOT ESTIMATED IN THIS PASS") -> NOT ESTIMATED IN THIS PASS | AZ6: =IFERROR(INDEX('Source Review'!$I$2:$I$52,MATCH($A6,'Source Review'!$A$2:$A$52,0)),"") | BA6: =IFERROR(INDEX('Source Review'!$E$2:$E$52,MATCH($A6,'Source Review'!$A$2:$A$52,0)),"") | BB6: =IF(COUNTIF('Source Review'!$A$2:$A$52,$A6)>0,"14-Sep-2026 snapshot; later closure evidence separate; no live HEAD verification","")
A7: T-091 | B7: M2 | C7: P1 | D7: Impact preview, export and import | E7: Backend | F7: Definition store | G7: Very Important | H7: Add dependency impact preview before a publish, and export and import of a definition with its dependencies, per Chapter 3 4.5.11. | I7: Publish a change to a definition three others depend on and confirm the preview lists all three before the publish is confirmed. Export and reimport into an empty database and confirm equality. | J7: 12 | K7: Done | L7: Worker 1 | M7: T-090 | N7: T-128; T-183 | O7: M2: ~1 month from owner planning checkpoint; exact date not committed | P7: Release 1 MUST | Q7: Backend/domain contract | R7: 1.8 | S7: M2-P1 | T7: CLOSED BASELINE — no new start gate and no re-execution implied. Preserve accepted closure and clean owned scope; reopen only on a concrete, separately recorded regression. Downstream consumes the frozen contract. | U7: Own canonical DB/backend/security/API/infra. No W2-owned UI/admin task files and no W3 ML/Assistant runtime. | V7: Commit before downstream consumer starts; consumer must use the contract, not redesign producer-owned semantics. | W7: Product Foundation & Release Truth | X7: M2 P1 — Product Foundation & Release Truth. Release 1 is genuine early production / first-week customer work. | Y7: c6d64289 — subject not recovered | AA7: L5.6 | AB7: Unified definition-store semantics | AC7: L2.5 | AD7: Build | AE7: D3; D5 | AF7: Core | AG7: R1 | AH7: Advances | AI7: =IF(Y7="","",Y7) -> c6d64289 — subject not recovered | AJ7: Inherited baseline estimate | AK7: v4.10.3 | AL7: Chapters 3/4 v4.10.3 — MD + illustrated Word; UI Coverage / UI Controls in this workbook | AM7: =IF(AND(ISNUMBER(J7),OR(AR7="INHERITED ESTIMATE",AR7="CONFIRMED ESTIMATE")),1,0) -> 1 | AO7: Recorded closed — inherited evidence | AP7: Inherited v2.22.0 intended record; no new runtime certification in this repair. | AR7: INHERITED ESTIMATE | AS7: =IF(AM7=1,J7,"") -> 12 | AT7: =IF(AND(AM7=1,ISNUMBER(R7)),R7,"") -> 1.8 | AU7: =IFERROR(INDEX('Source Review'!$B$2:$B$52,MATCH($A7,'Source Review'!$A$2:$A$52,0)),"NOT SOURCE-REVIEWED IN THIS PASS") -> NOT SOURCE-REVIEWED IN THIS PASS | AV7: =IFERROR(INDEX('Source Review'!$F$2:$F$52,MATCH($A7,'Source Review'!$A$2:$A$52,0)),"") | AW7: =IFERROR(INDEX('Source Review'!$G$2:$G$52,MATCH($A7,'Source Review'!$A$2:$A$52,0)),"") | AX7: =IFERROR(INDEX('Source Review'!$H$2:$H$52,MATCH($A7,'Source Review'!$A$2:$A$52,0)),"") | AY7: =IF(COUNTIF('Source Review'!$A$2:$A$52,$A7)>0,"UNCONFIRMED REVIEW ESTIMATE - not P80 or elapsed","NOT ESTIMATED IN THIS PASS") -> NOT ESTIMATED IN THIS PASS | AZ7: =IFERROR(INDEX('Source Review'!$I$2:$I$52,MATCH($A7,'Source Review'!$A$2:$A$52,0)),"") | BA7: =IFERROR(INDEX('Source Review'!$E$2:$E$52,MATCH($A7,'Source Review'!$A$2:$A$52,0)),"") | BB7: =IF(COUNTIF('Source Review'!$A$2:$A$52,$A7)>0,"14-Sep-2026 snapshot; later closure evidence separate; no live HEAD verification","")
A8: T-092 | B8: M2 | C8: P1 | D8: Registry authority: dimensions and measures as rows | E8: Backend | F8: Registry | G8: Critical | H8: Replace compiled dimension/measure catalogues with canonical registry projections over published definition versions. Registry rows must support customer-defined dimensions/measures without rebuild, plus analysis-grain metadata, signal/aggregation semantics and reference-derived measure roles. It remains a projection/serving authority, not a competing mutable definition store. | I8: Using the same binary, add a customer-shaped dimension and measure through definitions/registry data only and use them in an authored widget. No C#/React/product-SQL edit. Registry exposes declared grain and aggregation/reference metadata and rejects unresolved semantics. | J8: 12 | K8: Done | L8: Worker 1 | M8: T-089; T-090; T-210; T-231 | N8: T-093; T-094; T-128; T-183; T-212; T-215; T-228; T-237; T-247 | O8: M2: ~1 month from owner planning checkpoint; exact date not committed | P8: Release 1 MUST | Q8: Backend/domain contract | R8: 1.8 | S8: M2-P1 | T8: CLOSED BASELINE — no new start gate and no re-execution implied. Preserve accepted closure and clean owned scope; reopen only on a concrete, separately recorded regression. Downstream consumes the frozen contract. | U8: Own canonical DB/backend/security/API/infra. No W2-owned UI/admin task files and no W3 ML/Assistant runtime. | V8: Commit before downstream consumer starts; consumer must use the contract, not redesign producer-owned semantics. | W8: Product Foundation & Release Truth | X8: M2 P1 — Product Foundation & Release Truth. Release 1 is genuine early production / first-week customer work. | Y8: ab2962a4; 7cad36e4 — registry authority closure commits | Z8: 46267 | AA8: L3.9 | AB8: Master items, bookmarks and saved views | AC8: L5.1 | AD8: Build | AE8: D1; D3; D5 | AF8: Core | AG8: R1 | AH8: Advances | AI8: =IF(Y8="","",Y8) -> ab2962a4; 7cad36e4 — registry authority closure commits | AJ8: Inherited baseline estimate | AK8: v4.10.3 | AL8: Chapters 3/4 v4.10.3 — MD + illustrated Word; UI Coverage / UI Controls in this workbook | AM8: =IF(AND(ISNUMBER(J8),OR(AR8="INHERITED ESTIMATE",AR8="CONFIRMED ESTIMATE")),1,0) -> 1 | AO8: Recorded closed — inherited evidence | AP8: Inherited v2.22.0 intended record; no new runtime certification in this repair. | AR8: INHERITED ESTIMATE | AS8: =IF(AM8=1,J8,"") -> 12 | AT8: =IF(AND(AM8=1,ISNUMBER(R8)),R8,"") -> 1.8 | AU8: =IFERROR(INDEX('Source Review'!$B$2:$B$52,MATCH($A8,'Source Review'!$A$2:$A$52,0)),"NOT SOURCE-REVIEWED IN THIS PASS") -> NOT SOURCE-REVIEWED IN THIS PASS | AV8: =IFERROR(INDEX('Source Review'!$F$2:$F$52,MATCH($A8,'Source Review'!$A$2:$A$52,0)),"") | AW8: =IFERROR(INDEX('Source Review'!$G$2:$G$52,MATCH($A8,'Source Review'!$A$2:$A$52,0)),"") | AX8: =IFERROR(INDEX('Source Review'!$H$2:$H$52,MATCH($A8,'Source Review'!$A$2:$A$52,0)),"") | AY8: =IF(COUNTIF('Source Review'!$A$2:$A$52,$A8)>0,"UNCONFIRMED REVIEW ESTIMATE - not P80 or elapsed","NOT ESTIMATED IN THIS PASS") -> NOT ESTIMATED IN THIS PASS | AZ8: =IFERROR(INDEX('Source Review'!$I$2:$I$52,MATCH($A8,'Source Review'!$A$2:$A$52,0)),"") | BA8: =IFERROR(INDEX('Source Review'!$E$2:$E$52,MATCH($A8,'Source Review'!$A$2:$A$52,0)),"") | BB8: =IF(COUNTIF('Source Review'!$A$2:$A$52,$A8)>0,"14-Sep-2026 snapshot; later closure evidence separate; no live HEAD verification","")
A9: T-093 | B9: M2 | C9: P1 | D9: Plant-vocabulary sweep, part 1: build the term list and the architecture test | E9: Backend | F9: Registry | G9: Very Important | H9: Rule 1 needs an enforcement mechanism before the sweep, or the sweep is a one-off. Create a registry-held list of plant terms (the term list is itself DATA, never a compiled constant) and an architecture test that fails the build when any listed term appears in product code outside registry data, seed content or test fixtures. Seed the list from the dimension names already found compiled into DashboardWidgetQuerySafetyRegistry: ProductFamily, GradeOrRecipe, ShiftCode, DefectType, RiskClass. | I9: Add a term to the list and confirm the build goes red on an existing violation, then goes green once that violation is fixed. Confirm removing a term from the list does not require a code change. | J9: 6 | K9: Done | L9: Worker 1 | M9: T-092; T-206 | N9: T-094; T-128; T-183 | O9: M2: ~1 month from owner planning checkpoint; exact date not committed | P9: Release 1 MUST | Q9: Backend/domain contract | R9: 0.9 | S9: M2-P1 | T9: CLOSED BASELINE — no new start gate and no re-execution implied. Preserve accepted closure and clean owned scope; reopen only on a concrete, separately recorded regression. Downstream consumes the frozen contract. | U9: Own canonical DB/backend/security/API/infra. No W2-owned UI/admin task files and no W3 ML/Assistant runtime. | V9: Commit before downstream consumer starts; consumer must use the contract, not redesign producer-owned semantics. | W9: Product Foundation & Release Truth | X9: M2 P1 — Product Foundation & Release Truth. Release 1 is genuine early production / first-week customer work. | Y9: 4e2e0f654b93ceed2ecdfbce4d3c1768550b3079 — T-093 govern plant vocabulary as data-driven genericity debt | Z9: 46268 | AA9: L5.1 | AB9: Canonical entity catalogue | AD9: Build | AE9: D3; D5 | AF9: Core | AG9: R1 | AH9: Advances | AI9: =IF(Y9="","",Y9) -> 4e2e0f654b93ceed2ecdfbce4d3c1768550b3079 — T-093 govern plant vocabulary as data-driven genericity debt | AJ9: Inherited baseline estimate | AK9: v4.10.3 | AL9: Chapters 3/4 v4.10.3 — MD + illustrated Word; UI Coverage / UI Controls in this workbook | AM9: =IF(AND(ISNUMBER(J9),OR(AR9="INHERITED ESTIMATE",AR9="CONFIRMED ESTIMATE")),1,0) -> 1 | AO9: Recorded closed — inherited evidence | AP9: Inherited v2.22.0 intended record; no new runtime certification in this repair. | AR9: INHERITED ESTIMATE | AS9: =IF(AM9=1,J9,"") -> 6 | AT9: =IF(AND(AM9=1,ISNUMBER(R9)),R9,"") -> 0.9 | AU9: =IFERROR(INDEX('Source Review'!$B$2:$B$52,MATCH($A9,'Source Review'!$A$2:$A$52,0)),"NOT SOURCE-REVIEWED IN THIS PASS") -> NOT SOURCE-REVIEWED IN THIS PASS | AV9: =IFERROR(INDEX('Source Review'!$F$2:$F$52,MATCH($A9,'Source Review'!$A$2:$A$52,0)),"") | AW9: =IFERROR(INDEX('Source Review'!$G$2:$G$52,MATCH($A9,'Source Review'!$A$2:$A$52,0)),"") | AX9: =IFERROR(INDEX('Source Review'!$H$2:$H$52,MATCH($A9,'Source Review'!$A$2:$A$52,0)),"") | AY9: =IF(COUNTIF('Source Review'!$A$2:$A$52,$A9)>0,"UNCONFIRMED REVIEW ESTIMATE - not P80 or elapsed","NOT ESTIMATED IN THIS PASS") -> NOT ESTIMATED IN THIS PASS | AZ9: =IFERROR(INDEX('Source Review'!$I$2:$I$52,MATCH($A9,'Source Review'!$A$2:$A$52,0)),"") | BA9: =IFERROR(INDEX('Source Review'!$E$2:$E$52,MATCH($A9,'Source Review'!$A$2:$A$52,0)),"") | BB9: =IF(COUNTIF('Source Review'!$A$2:$A$52,$A9)>0,"14-Sep-2026 snapshot; later closure evidence separate; no live HEAD verification","")
A10: T-094 | B10: M2 | C10: P1 | D10: Plant-vocabulary sweep, part 2: remove hardcoded universal grain and industry vocabulary | E10: Backend | F10: Registry | G10: Very Important | H10: Clear generic-runtime/demo-vocabulary violations without replacing one industry noun with another. Complete the declared-dimension execution path on BOTH runtime wire surfaces: (A) persisted widget execution via DashboardWidgetFiltersDto/declared keyed dimensions and (B) workspace/global dashboard query execution via DashboardQueryDto and the overview/quality/risk/data-quality/materials routes. Remove fixed universal grain/industry vocabulary from DashboardReferenceDataDto and the frontend consumers by resolving published registry definitions, canonical members and governed Analysis Subject/relationship authority. The target contract is definition/registry member -> relationship/path resolution -> Analysis Subject -> typed refusal; the current direct single-reference resolver is an interim implementation until T-095/T-096 path authority lands. No presentation vocabulary becomes product authority. | I10: Using the same binary, author a foreign/customer-shaped dimension and prove it filters both a persisted widget and the workspace/global route surface through the same published definition/member identity. Both surfaces must return the same typed refusal when the dimension is undeclared, inactive, unmapped, has no subject path, or becomes ambiguous. No compiled fallback to defectType/riskClass/shiftCode or a universal material grain. Frontend consumers use the keyed contract. Wave-C genericity arithmetic remains exact: every known fingerprint is retired or explicitly lawful; unknown=0. | J10: 24 | K10: Done | L10: Worker 1 | M10: T-092; T-093; T-209 | N10: T-095; T-128; T-183; T-196; T-253; T-256; T-258 | O10: M2: ~1 month from owner planning checkpoint; exact date not committed | P10: Release 1 MUST | Q10: Backend/domain contract | R10: 3.6 | S10: M2-P1 | T10: CLOSED BASELINE — no new start gate and no re-execution implied. Preserve accepted closure and clean owned scope; reopen only on a concrete, separately recorded regression. Downstream consumes the frozen contract. | U10: Own canonical DB/backend/security/API/infra. No W2-owned UI/admin task files and no W3 ML/Assistant runtime. | V10: Commit before downstream consumer starts; consumer must use the contract, not redesign producer-owned semantics. | W10: Product Foundation & Release Truth | X10: CENTRAL 04-Sep-2026: T-094 remains open. Scope is formally amended from one wire to both declared-dimension execution surfaces. No new task is created while T-094 is open; after closure any new surface requires a new Task ID. | Y10: 377aabdffb27d651d30537ce5228ee4afe268526; 6ab97ee2; e74ecd1c; 5a967f1b0ab45961c8b8a880bb4fdec53a783134 — final: T-094 close keyed declared-dimension cutover and genericity reconciliation | Z10: 46272 | AA10: L5.1 | AB10: Canonical entity catalogue | AC10: L5.3 | AD10: Build | AE10: D1; D3; D5 | AF10: Core | AG10: R1 | AH10: Advances | AI10: =IF(Y10="","",Y10) -> 377aabdffb27d651d30537ce5228ee4afe268526; 6ab97ee2; e74ecd1c; 5a967f1b0ab45961c8b8a880bb4fdec53a783134 — final: T-094 close keyed declared-dimension cutover and genericity reconciliation | AJ10: Inherited baseline estimate | AK10: v4.10.3 | AL10: Chapters 3/4 v4.10.3 — MD + illustrated Word; UI Coverage / UI Controls in this workbook | AM10: =IF(AND(ISNUMBER(J10),OR(AR10="INHERITED ESTIMATE",AR10="CONFIRMED ESTIMATE")),1,0) -> 1 | AO10: Recorded closed — inherited evidence | AP10: Inherited v2.22.0 intended record; no new runtime certification in this repair. | AR10: INHERITED ESTIMATE | AS10: =IF(AM10=1,J10,"") -> 24 | AT10: =IF(AND(AM10=1,ISNUMBER(R10)),R10,"") -> 3.6 | AU10: =IFERROR(INDEX('Source Review'!$B$2:$B$52,MATCH($A10,'Source Review'!$A$2:$A$52,0)),"NOT SOURCE-REVIEWED IN THIS PASS") -> NOT SOURCE-REVIEWED IN THIS PASS | AV10: =IFERROR(INDEX('Source Review'!$F$2:$F$52,MATCH($A10,'Source Review'!$A$2:$A$52,0)),"") | AW10: =IFERROR(INDEX('Source Review'!$G$2:$G$52,MATCH($A10,'Source Review'!$A$2:$A$52,0)),"") | AX10: =IFERROR(INDEX('Source Review'!$H$2:$H$52,MATCH($A10,'Source Review'!$A$2:$A$52,0)),"") | AY10: =IF(COUNTIF('Source Review'!$A$2:$A$52,$A10)>0,"UNCONFIRMED REVIEW ESTIMATE - not P80 or elapsed","NOT ESTIMATED IN THIS PASS") -> NOT ESTIMATED IN THIS PASS | AZ10: =IFERROR(INDEX('Source Review'!$I$2:$I$52,MATCH($A10,'Source Review'!$A$2:$A$52,0)),"") | BA10: =IFERROR(INDEX('Source Review'!$E$2:$E$52,MATCH($A10,'Source Review'!$A$2:$A$52,0)),"") | BB10: =IF(COUNTIF('Source Review'!$A$2:$A$52,$A10)>0,"14-Sep-2026 snapshot; later closure evidence separate; no live HEAD verification","")
A11: T-201 | B11: M2 | C11: P1 | D11: Freeze the successful M1 presentation baseline and transfer programme authority to M2 | E11: Programme | F11: Release baseline | G11: Critical | H11: Resolve the shared dirty tree, keep/revert the associative change on evidence, commit exact owned files, tag/freeze the successful presentation baseline, and formally stop presentation-only feature/page/data work. Remaining generic defects move to M2-P0 owners rather than being completed as M1 content. | I11: Clean index and explicit foreign-file inventory; immutable release/tag or equivalent frozen artifact; presentation profile still launches; one ledger lists every unclosed M1 item as frozen, superseded, or consumed by a named M2 task. No customer-demo-only task remains on the September critical path. | J11: 4 | K11: Done | L11: Worker 1 | N11: T-086; T-202; T-203; T-204; T-205; T-206; T-207; T-208; T-213; T-241 | O11: M2: ~1 month from owner planning checkpoint; exact date not committed | P11: Release 1 MUST | Q11: Release / governance | R11: 1.5 | S11: M2-P1 | T11: CLOSED BASELINE — no new start gate and no re-execution implied. Preserve accepted closure and clean owned scope; reopen only on a concrete, separately recorded regression. Downstream consumes the frozen contract. | U11: Git/worktree ownership + release/tag only. | V11: After commit/tag, all workers consume the frozen baseline; nobody reopens M1 presentation scope without a proven regression. | W11: Product Foundation & Release Truth | X11: M2 P1 — Product Foundation & Release Truth. Release 1 is genuine early production / first-week customer work. | Y11: BASELINE HEAD 7da9d46ed29545f1c4f4686fa82c117c08b9fc86; TAG m1-presentation-baseline-2026-08-21 — no task commit; tag is closure artifact | Z11: 46258 | AA11: L8.8 | AB11: C1–C4 performance certification and golden-journey release gate | AD11: Validate | AE11: D1; D5 | AF11: Core | AG11: R1 | AH11: Advances | AI11: =IF(Y11="","",Y11) -> BASELINE HEAD 7da9d46ed29545f1c4f4686fa82c117c08b9fc86; TAG m1-presentation-baseline-2026-08-21 — no task commit; tag is closure artifact | AJ11: Inherited baseline estimate | AK11: v4.10.3 | AL11: Chapters 3/4 v4.10.3 — MD + illustrated Word; UI Coverage / UI Controls in this workbook | AM11: =IF(AND(ISNUMBER(J11),OR(AR11="INHERITED ESTIMATE",AR11="CONFIRMED ESTIMATE")),1,0) -> 1 | AO11: Recorded closed — inherited evidence | AP11: Inherited v2.22.0 intended record; no new runtime certification in this repair. | AR11: INHERITED ESTIMATE | AS11: =IF(AM11=1,J11,"") -> 4 | AT11: =IF(AND(AM11=1,ISNUMBER(R11)),R11,"") -> 1.5 | AU11: =IFERROR(INDEX('Source Review'!$B$2:$B$52,MATCH($A11,'Source Review'!$A$2:$A$52,0)),"NOT SOURCE-REVIEWED IN THIS PASS") -> NOT SOURCE-REVIEWED IN THIS PASS | AV11: =IFERROR(INDEX('Source Review'!$F$2:$F$52,MATCH($A11,'Source Review'!$A$2:$A$52,0)),"") | AW11: =IFERROR(INDEX('Source Review'!$G$2:$G$52,MATCH($A11,'Source Review'!$A$2:$A$52,0)),"") | AX11: =IFERROR(INDEX('Source Review'!$H$2:$H$52,MATCH($A11,'Source Review'!$A$2:$A$52,0)),"") | AY11: =IF(COUNTIF('Source Review'!$A$2:$A$52,$A11)>0,"UNCONFIRMED REVIEW ESTIMATE - not P80 or elapsed","NOT ESTIMATED IN THIS PASS") -> NOT ESTIMATED IN THIS PASS | AZ11: =IFERROR(INDEX('Source Review'!$I$2:$I$52,MATCH($A11,'Source Review'!$A$2:$A$52,0)),"") | BA11: =IFERROR(INDEX('Source Review'!$E$2:$E$52,MATCH($A11,'Source Review'!$A$2:$A$52,0)),"") | BB11: =IF(COUNTIF('Source Review'!$A$2:$A$52,$A11)>0,"14-Sep-2026 snapshot; later closure evidence separate; no live HEAD verification","")
A12: T-202 | B12: M2 | C12: P1 | D12: Persisted page/widget definition replay gate | E12: Quality | F12: Release Truth | G12: Critical | H12: Enumerate every active customer-facing page/widget definition from the real database and execute its actual query contract against the release API/database. Validate declared terminal semantics, row/population evidence and compatibility. This gate tests the product as persisted, not merely source-code paths. | I12: Every active persisted widget executes with 2xx plus Populated/Empty/Blocked/Refused as documented; unexpected 4xx/5xx is a failure. Deliberately corrupt one dimension/measure combination and prove the gate fails. Restore and prove green. Emit machine-readable report naming definition/page/widget. | J12: 10 | K12: Done | L12: Worker 2 | M12: T-201 | N12: T-212; T-248 | O12: M2: ~1 month from owner planning checkpoint; exact date not committed | P12: Release 1 MUST | Q12: E2E / integration gate | R12: 4 | S12: M2-P1 | T12: CLOSED BASELINE — no new start gate and no re-execution implied. Preserve accepted closure and clean owned scope; reopen only on a concrete, separately recorded regression. Downstream consumes the frozen contract. | U12: Frontend E2E + dashboard query test harness; no canonical schema edits. | V12: T-150 later consumes this gate; it does not redesign it. | W12: Product Foundation & Release Truth | X12: M2 P1 — Product Foundation & Release Truth. Release 1 is genuine early production / first-week customer work. | Y12: ad37c324 — Add persisted definition replay gate for release truth | Z12: 46259 | AA12: L8.8 | AB12: C1–C4 performance certification and golden-journey release gate | AC12: L3.1; L3.4 | AD12: Validate | AE12: D2; D5 | AF12: Core | AG12: R1 | AH12: Advances | AI12: =IF(Y12="","",Y12) -> ad37c324 — Add persisted definition replay gate for release truth | AJ12: Inherited baseline estimate | AK12: v4.10.3 | AL12: Chapters 3/4 v4.10.3 — MD + illustrated Word; UI Coverage / UI Controls in this workbook | AM12: =IF(AND(ISNUMBER(J12),OR(AR12="INHERITED ESTIMATE",AR12="CONFIRMED ESTIMATE")),1,0) -> 1 | AO12: Recorded closed — inherited evidence | AP12: Inherited v2.22.0 intended record; no new runtime certification in this repair. | AR12: INHERITED ESTIMATE | AS12: =IF(AM12=1,J12,"") -> 10 | AT12: =IF(AND(AM12=1,ISNUMBER(R12)),R12,"") -> 4 | AU12: =IFERROR(INDEX('Source Review'!$B$2:$B$52,MATCH($A12,'Source Review'!$A$2:$A$52,0)),"NOT SOURCE-REVIEWED IN THIS PASS") -> NOT SOURCE-REVIEWED IN THIS PASS | AV12: =IFERROR(INDEX('Source Review'!$F$2:$F$52,MATCH($A12,'Source Review'!$A$2:$A$52,0)),"") | AW12: =IFERROR(INDEX('Source Review'!$G$2:$G$52,MATCH($A12,'Source Review'!$A$2:$A$52,0)),"") | AX12: =IFERROR(INDEX('Source Review'!$H$2:$H$52,MATCH($A12,'Source Review'!$A$2:$A$52,0)),"") | AY12: =IF(COUNTIF('Source Review'!$A$2:$A$52,$A12)>0,"UNCONFIRMED REVIEW ESTIMATE - not P80 or elapsed","NOT ESTIMATED IN THIS PASS") -> NOT ESTIMATED IN THIS PASS | AZ12: =IFERROR(INDEX('Source Review'!$I$2:$I$52,MATCH($A12,'Source Review'!$A$2:$A$52,0)),"") | BA12: =IFERROR(INDEX('Source Review'!$E$2:$E$52,MATCH($A12,'Source Review'!$A$2:$A$52,0)),"") | BB12: =IF(COUNTIF('Source Review'!$A$2:$A$52,$A12)>0,"14-Sep-2026 snapshot; later closure evidence separate; no live HEAD verification","")
A13: T-203 | B13: M2 | C13: P1 | D13: Customer-route network, console and widget-state invariant | E13: Quality | F13: Release Truth | G13: Critical | H13: For every customer-reachable route, navigate and settle against the real API; fail on unexpected HTTP >=400, failed required request, uncaught JS exception, unhandled console error, error toast, or widget Failed state. Record route/request/widget evidence. | I13: Inject one failing API response and one uncaught render error and prove the route gate fails for the named cause. With faults removed, every customer route settles with zero unexpected network/console/widget failures. | J13: 10 | K13: Done | L13: Worker 2 | M13: T-201 | N13: T-222; T-248 | O13: M2: ~1 month from owner planning checkpoint; exact date not committed | P13: Release 1 MUST | Q13: Playwright / session | R13: 4 | S13: M2-P1 | T13: CLOSED BASELINE — no new start gate and no re-execution implied. Preserve accepted closure and clean owned scope; reopen only on a concrete, separately recorded regression. Downstream consumes the frozen contract. | U13: Frontend E2E/session harness. | V13: All later customer-facing feature tasks must add their route to this gate before close. | W13: Product Foundation & Release Truth | X13: M2 P1 — Product Foundation & Release Truth. Release 1 is genuine early production / first-week customer work. | Y13: cd1a450e — Add customer route invariant gate with durable evidence | Z13: 46259 | AA13: L8.8 | AB13: C1–C4 performance certification and golden-journey release gate | AC13: L6.7 | AD13: Validate | AE13: D2; D5 | AF13: Core | AG13: R1 | AH13: Advances | AI13: =IF(Y13="","",Y13) -> cd1a450e — Add customer route invariant gate with durable evidence | AJ13: Inherited baseline estimate | AK13: v4.10.3 | AL13: Chapters 3/4 v4.10.3 — MD + illustrated Word; UI Coverage / UI Controls in this workbook | AM13: =IF(AND(ISNUMBER(J13),OR(AR13="INHERITED ESTIMATE",AR13="CONFIRMED ESTIMATE")),1,0) -> 1 | AO13: Recorded closed — inherited evidence | AP13: Inherited v2.22.0 intended record; no new runtime certification in this repair. | AR13: INHERITED ESTIMATE | AS13: =IF(AM13=1,J13,"") -> 10 | AT13: =IF(AND(AM13=1,ISNUMBER(R13)),R13,"") -> 4 | AU13: =IFERROR(INDEX('Source Review'!$B$2:$B$52,MATCH($A13,'Source Review'!$A$2:$A$52,0)),"NOT SOURCE-REVIEWED IN THIS PASS") -> NOT SOURCE-REVIEWED IN THIS PASS | AV13: =IFERROR(INDEX('Source Review'!$F$2:$F$52,MATCH($A13,'Source Review'!$A$2:$A$52,0)),"") | AW13: =IFERROR(INDEX('Source Review'!$G$2:$G$52,MATCH($A13,'Source Review'!$A$2:$A$52,0)),"") | AX13: =IFERROR(INDEX('Source Review'!$H$2:$H$52,MATCH($A13,'Source Review'!$A$2:$A$52,0)),"") | AY13: =IF(COUNTIF('Source Review'!$A$2:$A$52,$A13)>0,"UNCONFIRMED REVIEW ESTIMATE - not P80 or elapsed","NOT ESTIMATED IN THIS PASS") -> NOT ESTIMATED IN THIS PASS | AZ13: =IFERROR(INDEX('Source Review'!$I$2:$I$52,MATCH($A13,'Source Review'!$A$2:$A$52,0)),"") | BA13: =IFERROR(INDEX('Source Review'!$E$2:$E$52,MATCH($A13,'Source Review'!$A$2:$A$52,0)),"") | BB13: =IF(COUNTIF('Source Review'!$A$2:$A$52,$A13)>0,"14-Sep-2026 snapshot; later closure evidence separate; no live HEAD verification","")
A14: T-204 | B14: M2 | C14: P1 | D14: Associative cross-filter state-machine certification | E14: Frontend | F14: Associative BI | G14: Critical | H14: Replace click-smoke acceptance with a state-machine proof: capture widgets A/B/C, click X in A, assert selection state, assert B/C re-query with X, assert returned populations and visible results change, clear X and assert restoration. Execute across interactive renderer families. | I14: Bar, line, scatter, heatmap, table-row and interactive KPI families each prove selection propagation, dependent request mutation, population/result change, and restoration. A deliberate broken dependency-array/bridge falsification must fail the test. | J14: 10 | K14: Done | L14: Worker 2 | M14: T-201 | N14: T-222; T-248 | O14: M2: ~1 month from owner planning checkpoint; exact date not committed | P14: Release 1 MUST | Q14: Frontend behavioural E2E | R14: 4.25 | S14: M2-P1 | T14: CLOSED BASELINE — no new start gate and no re-execution implied. Preserve accepted closure and clean owned scope; reopen only on a concrete, separately recorded regression. Downstream consumes the frozen contract. | U14: AssociativeContext/filter bridge + E2E tests; no unrelated chart redesign. | V14: This task supersedes using browser walking as the acceptance of cross-filtering. | W14: Product Foundation & Release Truth | X14: M2 P1 — Product Foundation & Release Truth. Release 1 is genuine early production / first-week customer work. | Y14: c6491e2d — closure-state HEAD; exact task commit subject not independently recovered | Z14: 46265 | AA14: L3.2 | AB14: Associative engine and selection strip | AD14: Validate | AE14: D2; D5 | AF14: Core | AG14: R1 | AH14: Advances | AI14: =IF(Y14="","",Y14) -> c6491e2d — closure-state HEAD; exact task commit subject not independently recovered | AJ14: Inherited baseline estimate | AK14: v4.10.3 | AL14: Chapters 3/4 v4.10.3 — MD + illustrated Word; UI Coverage / UI Controls in this workbook | AM14: =IF(AND(ISNUMBER(J14),OR(AR14="INHERITED ESTIMATE",AR14="CONFIRMED ESTIMATE")),1,0) -> 1 | AO14: Recorded closed — inherited evidence | AP14: Inherited v2.22.0 intended record; no new runtime certification in this repair. | AR14: INHERITED ESTIMATE | AS14: =IF(AM14=1,J14,"") -> 10 | AT14: =IF(AND(AM14=1,ISNUMBER(R14)),R14,"") -> 4.25 | AU14: =IFERROR(INDEX('Source Review'!$B$2:$B$52,MATCH($A14,'Source Review'!$A$2:$A$52,0)),"NOT SOURCE-REVIEWED IN THIS PASS") -> NOT SOURCE-REVIEWED IN THIS PASS | AV14: =IFERROR(INDEX('Source Review'!$F$2:$F$52,MATCH($A14,'Source Review'!$A$2:$A$52,0)),"") | AW14: =IFERROR(INDEX('Source Review'!$G$2:$G$52,MATCH($A14,'Source Review'!$A$2:$A$52,0)),"") | AX14: =IFERROR(INDEX('Source Review'!$H$2:$H$52,MATCH($A14,'Source Review'!$A$2:$A$52,0)),"") | AY14: =IF(COUNTIF('Source Review'!$A$2:$A$52,$A14)>0,"UNCONFIRMED REVIEW ESTIMATE - not P80 or elapsed","NOT ESTIMATED IN THIS PASS") -> NOT ESTIMATED IN THIS PASS | AZ14: =IFERROR(INDEX('Source Review'!$I$2:$I$52,MATCH($A14,'Source Review'!$A$2:$A$52,0)),"") | BA14: =IFERROR(INDEX('Source Review'!$E$2:$E$52,MATCH($A14,'Source Review'!$A$2:$A$52,0)),"") | BB14: =IF(COUNTIF('Source Review'!$A$2:$A$52,$A14)>0,"14-Sep-2026 snapshot; later closure evidence separate; no live HEAD verification","")
A15: T-205 | B15: M2 | C15: P1 | D15: Frontend global suite termination and machine-readable gate | E15: Frontend | F15: Test infrastructure | G15: Very Important | H15: Make the global frontend unit/component suite terminate deterministically, produce a machine-readable result, and fail the pipeline on non-termination, timeout, skipped mandatory tests or leaked handles. | I15: Run the full suite twice from clean processes under the declared timeout; both terminate with identical pass/fail/skip counts and machine-readable output. Inject a leaked handle/non-terminating test and prove the gate goes red. | J15: 8 | K15: Done | L15: Worker 2 | M15: T-201 | N15: T-150; T-248; T-250; T-255; T-257 | O15: M2: ~1 month from owner planning checkpoint; exact date not committed | P15: Release 1 MUST | Q15: Frontend test infrastructure | R15: 3.2 | S15: M2-P1 | T15: CLOSED BASELINE — no new start gate and no re-execution implied. Preserve accepted closure and clean owned scope; reopen only on a concrete, separately recorded regression. Downstream consumes the frozen contract. | U15: Frontend test runner/config only. | V15: T-205 remains closed. Deterministic suite-truth mutations are owned by T-250; do not amend or reopen T-205 for product/test corrections. | W15: Product Foundation & Release Truth | X15: CENTRAL 30-Aug-2026: T-205 CLOSED GREEN at b7fcc890. The gate correctly reports suite truth; bounded corrections are a separate explicit task. | Y15: b7fcc890 — Gate the frontend suite on deterministic termination and machine-readable evidence | Z15: 46264 | AA15: L8.2 | AB15: Test architecture with disposable isolated databases | AD15: Validate | AE15: D2; D5 | AF15: Core | AG15: R1 | AH15: Advances | AI15: =IF(Y15="","",Y15) -> b7fcc890 — Gate the frontend suite on deterministic termination and machine-readable evidence | AJ15: Inherited baseline estimate | AK15: v4.10.3 | AL15: Chapters 3/4 v4.10.3 — MD + illustrated Word; UI Coverage / UI Controls in this workbook | AM15: =IF(AND(ISNUMBER(J15),OR(AR15="INHERITED ESTIMATE",AR15="CONFIRMED ESTIMATE")),1,0) -> 1 | AO15: Recorded closed — inherited evidence | AP15: Inherited v2.22.0 intended record; no new runtime certification in this repair. | AR15: INHERITED ESTIMATE | AS15: =IF(AM15=1,J15,"") -> 8 | AT15: =IF(AND(AM15=1,ISNUMBER(R15)),R15,"") -> 3.2 | AU15: =IFERROR(INDEX('Source Review'!$B$2:$B$52,MATCH($A15,'Source Review'!$A$2:$A$52,0)),"NOT SOURCE-REVIEWED IN THIS PASS") -> NOT SOURCE-REVIEWED IN THIS PASS | AV15: =IFERROR(INDEX('Source Review'!$F$2:$F$52,MATCH($A15,'Source Review'!$A$2:$A$52,0)),"") | AW15: =IFERROR(INDEX('Source Review'!$G$2:$G$52,MATCH($A15,'Source Review'!$A$2:$A$52,0)),"") | AX15: =IFERROR(INDEX('Source Review'!$H$2:$H$52,MATCH($A15,'Source Review'!$A$2:$A$52,0)),"") | AY15: =IF(COUNTIF('Source Review'!$A$2:$A$52,$A15)>0,"UNCONFIRMED REVIEW ESTIMATE - not P80 or elapsed","NOT ESTIMATED IN THIS PASS") -> NOT ESTIMATED IN THIS PASS | AZ15: =IFERROR(INDEX('Source Review'!$I$2:$I$52,MATCH($A15,'Source Review'!$A$2:$A$52,0)),"") | BA15: =IFERROR(INDEX('Source Review'!$E$2:$E$52,MATCH($A15,'Source Review'!$A$2:$A$52,0)),"") | BB15: =IF(COUNTIF('Source Review'!$A$2:$A$52,$A15)>0,"14-Sep-2026 snapshot; later closure evidence separate; no live HEAD verification","")
A16: T-206 | B16: M2 | C16: P1 | D16: Scope-aware genericity architecture gate | E16: Architecture | F16: Genericity | G16: Critical | H16: Create a scope-aware architecture test that forbids customer/demo/industry vocabulary and compiled customer dimension/grain authorities inside generic runtime/engine/API contracts while allowing that vocabulary in explicitly classified fixtures, mappings and documentation. Include detection of compiled dimension arrays and implicit grain defaults. | I16: Falsify the gate with a generic-runtime 'coil' fallback, a compiled customer dimension, and an industry-specific class; each fails. The same terms in approved fixture paths remain allowed. Gate consumes configured path/authority classes, not a naive whole-repo negative text scan. | J16: 8 | K16: Done | L16: Worker 3 | M16: T-201 | N16: T-093; T-213 | O16: M2: ~1 month from owner planning checkpoint; exact date not committed | P16: Release 1 MUST | Q16: Architecture/test | R16: 2 | S16: M2-P1 | T16: CLOSED BASELINE — no new start gate and no re-execution implied. Preserve accepted closure and clean owned scope; reopen only on a concrete, separately recorded regression. Downstream consumes the frozen contract. | U16: Architecture/genericity tests only; no W1 schema or W2 UI mutation. | V16: Violations are routed to the owning task/file; Worker 3 does not fix foreign files. | W16: Product Foundation & Release Truth | X16: M2 P1 — Product Foundation & Release Truth. Release 1 is genuine early production / first-week customer work. | Y16: Not recovered from reviewed sessions | AA16: L5.1 | AB16: Canonical entity catalogue | AD16: Validate | AE16: D1; D5 | AF16: Core | AG16: R1 | AH16: Advances | AI16: =IF(Y16="","",Y16) -> Not recovered from reviewed sessions | AJ16: Inherited baseline estimate | AK16: v4.10.3 | AL16: Chapters 3/4 v4.10.3 — MD + illustrated Word; UI Coverage / UI Controls in this workbook | AM16: =IF(AND(ISNUMBER(J16),OR(AR16="INHERITED ESTIMATE",AR16="CONFIRMED ESTIMATE")),1,0) -> 1 | AO16: Recorded closed — inherited evidence | AP16: Inherited v2.22.0 intended record; no new runtime certification in this repair. | AR16: INHERITED ESTIMATE | AS16: =IF(AM16=1,J16,"") -> 8 | AT16: =IF(AND(AM16=1,ISNUMBER(R16)),R16,"") -> 2 | AU16: =IFERROR(INDEX('Source Review'!$B$2:$B$52,MATCH($A16,'Source Review'!$A$2:$A$52,0)),"NOT SOURCE-REVIEWED IN THIS PASS") -> NOT SOURCE-REVIEWED IN THIS PASS | AV16: =IFERROR(INDEX('Source Review'!$F$2:$F$52,MATCH($A16,'Source Review'!$A$2:$A$52,0)),"") | AW16: =IFERROR(INDEX('Source Review'!$G$2:$G$52,MATCH($A16,'Source Review'!$A$2:$A$52,0)),"") | AX16: =IFERROR(INDEX('Source Review'!$H$2:$H$52,MATCH($A16,'Source Review'!$A$2:$A$52,0)),"") | AY16: =IF(COUNTIF('Source Review'!$A$2:$A$52,$A16)>0,"UNCONFIRMED REVIEW ESTIMATE - not P80 or elapsed","NOT ESTIMATED IN THIS PASS") -> NOT ESTIMATED IN THIS PASS | AZ16: =IFERROR(INDEX('Source Review'!$I$2:$I$52,MATCH($A16,'Source Review'!$A$2:$A$52,0)),"") | BA16: =IFERROR(INDEX('Source Review'!$E$2:$E$52,MATCH($A16,'Source Review'!$A$2:$A$52,0)),"") | BB16: =IF(COUNTIF('Source Review'!$A$2:$A$52,$A16)>0,"14-Sep-2026 snapshot; later closure evidence separate; no live HEAD verification","")
A17: T-208 | B17: M2 | C17: P1 | D17: Generic controlled validation fixture authority and continuous-process known-answer pack | E17: Quality | F17: Test data | G17: Critical | H17: Create the dataset-neutral controlled fixture authority separate from product vocabulary. Keep Fleet v2 as legacy discrete regression oracle only; continuous-process fixture includes irregular analog samples, state intervals, counters, alarms, process windows, independent manual/business records, PLUS a declared transition/stabilisation event and conflicting multi-objective practice vectors with predeclared known answers. | I17: Fixture manifests are machine-readable, immutable by version, inaccessible as planted truth to runtime, and include SampleMean vs TimeWeightedMean, StateDuration, Delta, interval overlap, transition/stabilisation regime truth, a pooled-vs-steady-state confounding case, a known Pareto frontier, negative controls and refusal cases. Product code contains no fixture vocabulary. | J17: 10 | K17: Done | L17: Worker 3 | M17: T-201 | N17: T-209; T-211; T-216; T-217; T-218; T-234; T-238 | O17: M2: ~1 month from owner planning checkpoint; exact date not committed | P17: Release 1 MUST | Q17: Test fixture / kernel | R17: 2.5 | S17: M2-P1 | T17: CLOSED BASELINE — no new start gate and no re-execution implied. Preserve accepted closure and clean owned scope; reopen only on a concrete, separately recorded regression. Downstream consumes the frozen contract. | U17: New generic fixture/test assets only. | V17: T-211/T-217/T-219 consume this fixture; they never read planted expected answers at runtime. | W17: Product Foundation & Release Truth | X17: M2 P1 — Product Foundation & Release Truth. Release 1 is genuine early production / first-week customer work. | Y17: 969c767c — T-208: generic controlled validation fixture and continuous-process known answers | AA17: L8.2 | AB17: Test architecture with disposable isolated databases | AD17: Build | AE17: D1; D5 | AF17: Core | AG17: R1 | AH17: Advances | AI17: =IF(Y17="","",Y17) -> 969c767c — T-208: generic controlled validation fixture and continuous-process known answers | AJ17: Inherited baseline estimate | AK17: v4.10.3 | AL17: Chapters 3/4 v4.10.3 — MD + illustrated Word; UI Coverage / UI Controls in this workbook | AM17: =IF(AND(ISNUMBER(J17),OR(AR17="INHERITED ESTIMATE",AR17="CONFIRMED ESTIMATE")),1,0) -> 1 | AO17: Recorded closed — inherited evidence | AP17: Inherited v2.22.0 intended record; no new runtime certification in this repair. | AR17: INHERITED ESTIMATE | AS17: =IF(AM17=1,J17,"") -> 10 | AT17: =IF(AND(AM17=1,ISNUMBER(R17)),R17,"") -> 2.5 | AU17: =IFERROR(INDEX('Source Review'!$B$2:$B$52,MATCH($A17,'Source Review'!$A$2:$A$52,0)),"NOT SOURCE-REVIEWED IN THIS PASS") -> NOT SOURCE-REVIEWED IN THIS PASS | AV17: =IFERROR(INDEX('Source Review'!$F$2:$F$52,MATCH($A17,'Source Review'!$A$2:$A$52,0)),"") | AW17: =IFERROR(INDEX('Source Review'!$G$2:$G$52,MATCH($A17,'Source Review'!$A$2:$A$52,0)),"") | AX17: =IFERROR(INDEX('Source Review'!$H$2:$H$52,MATCH($A17,'Source Review'!$A$2:$A$52,0)),"") | AY17: =IF(COUNTIF('Source Review'!$A$2:$A$52,$A17)>0,"UNCONFIRMED REVIEW ESTIMATE - not P80 or elapsed","NOT ESTIMATED IN THIS PASS") -> NOT ESTIMATED IN THIS PASS | AZ17: =IFERROR(INDEX('Source Review'!$I$2:$I$52,MATCH($A17,'Source Review'!$A$2:$A$52,0)),"") | BA17: =IFERROR(INDEX('Source Review'!$E$2:$E$52,MATCH($A17,'Source Review'!$A$2:$A$52,0)),"") | BB17: =IF(COUNTIF('Source Review'!$A$2:$A$52,$A17)>0,"14-Sep-2026 snapshot; later closure evidence separate; no live HEAD verification","")
A18: T-209 | B18: M2 | C18: P1 | D18: Analysis Subject and Grain contract + schema-independent resolution kernel | E18: Architecture / Analytics Engine | F18: Generic subject/grain contract | G18: Critical | H18: Freeze the generic AnalysisSubject/GrainDefinition contract and a schema-independent resolver/kernel. It defines subject kinds, grain identity, time-window semantics, typed GR01 refusal and the rule that no analytical result requires a material identifier. No production migration, DI registration or canonical table edit in this task. | I18: Known-answer tests resolve discrete, equipment-window and flow-interval subjects; missing grain refuses GR01; no industry noun/material-only assumption appears in the public contract. Runs without production DB access. | J18: 6 | K18: Done | L18: Worker 3 | M18: T-208 | N18: T-094; T-210; T-214; T-231; T-234; T-253 | O18: M2: ~1 month from owner planning checkpoint; exact date not committed | P18: Release 1 MUST | Q18: Kernel/contract | R18: 1.5 | S18: M2-P1 | T18: CLOSED BASELINE — no new start gate and no re-execution implied. Preserve accepted closure and clean owned scope; reopen only on a concrete, separately recorded regression. Downstream consumes the frozen contract. | U18: New generic contract/kernel/tests only. | V18: T-231 persists this contract; downstream consumers bind to contract, not table shape. | W18: Product Foundation & Release Truth | X18: M2 P1 — Product Foundation & Release Truth. Release 1 is genuine early production / first-week customer work. | Y18: f2bafdb4 — subject not recovered | Z18: 46259 | AA18: L5.3 | AB18: Analysis Subject, grain and signal aggregation authority | AD18: Build | AE18: D1; D3; D4; D5 | AF18: Core | AG18: R1 | AH18: Advances | AI18: =IF(Y18="","",Y18) -> f2bafdb4 — subject not recovered | AJ18: Inherited baseline estimate | AK18: v4.10.3 | AL18: Chapters 3/4 v4.10.3 — MD + illustrated Word; UI Coverage / UI Controls in this workbook | AM18: =IF(AND(ISNUMBER(J18),OR(AR18="INHERITED ESTIMATE",AR18="CONFIRMED ESTIMATE")),1,0) -> 1 | AO18: Recorded closed — inherited evidence | AP18: Inherited v2.22.0 intended record; no new runtime certification in this repair. | AR18: INHERITED ESTIMATE | AS18: =IF(AM18=1,J18,"") -> 6 | AT18: =IF(AND(AM18=1,ISNUMBER(R18)),R18,"") -> 1.5 | AU18: =IFERROR(INDEX('Source Review'!$B$2:$B$52,MATCH($A18,'Source Review'!$A$2:$A$52,0)),"NOT SOURCE-REVIEWED IN THIS PASS") -> NOT SOURCE-REVIEWED IN THIS PASS | AV18: =IFERROR(INDEX('Source Review'!$F$2:$F$52,MATCH($A18,'Source Review'!$A$2:$A$52,0)),"") | AW18: =IFERROR(INDEX('Source Review'!$G$2:$G$52,MATCH($A18,'Source Review'!$A$2:$A$52,0)),"") | AX18: =IFERROR(INDEX('Source Review'!$H$2:$H$52,MATCH($A18,'Source Review'!$A$2:$A$52,0)),"") | AY18: =IF(COUNTIF('Source Review'!$A$2:$A$52,$A18)>0,"UNCONFIRMED REVIEW ESTIMATE - not P80 or elapsed","NOT ESTIMATED IN THIS PASS") -> NOT ESTIMATED IN THIS PASS | AZ18: =IFERROR(INDEX('Source Review'!$I$2:$I$52,MATCH($A18,'Source Review'!$A$2:$A$52,0)),"") | BA18: =IFERROR(INDEX('Source Review'!$E$2:$E$52,MATCH($A18,'Source Review'!$A$2:$A$52,0)),"") | BB18: =IF(COUNTIF('Source Review'!$A$2:$A$52,$A18)>0,"14-Sep-2026 snapshot; later closure evidence separate; no live HEAD verification","")
A19: T-210 | B19: M2 | C19: P1 | D19: Canonical signal and aggregation semantics authority | E19: Backend | F19: Semantic measurement authority | G19: Critical | H19: Extend parameter definitions and KPI bindings with signal_kind, aggregation_kind, interpolation, weight basis, maximum gap, quality policy, counter-reset and time basis. Remove any silent DEFAULT 'Average'. Store grammar as product-owned enums/registry; customer parameters select it. | I19: Create Analog/State/Counter definitions and prove no aggregate can execute from data_type alone. Parameter or KPI binding may declare a valid method; absent semantics returns AG01. Invalid method for signal returns AG02. Fresh DB/replay green and no default Average in canonical schema. | J19: 12 | K19: Done | L19: Worker 1 | M19: T-090; T-209 | N19: T-092; T-128; T-211; T-212; T-242 | O19: M2: ~1 month from owner planning checkpoint; exact date not committed | P19: Release 1 MUST | Q19: DB/schema authority | R19: 5.1 | S19: M2-P1 | T19: CLOSED BASELINE — no new start gate and no re-execution implied. Preserve accepted closure and clean owned scope; reopen only on a concrete, separately recorded regression. Downstream consumes the frozen contract. | U19: Parameter definitions/KPI bindings/migrations/definition contract. | V19: T-211 executes exactly this contract; no second aggregation registry. | W19: Product Foundation & Release Truth | X19: M2 P1 — Product Foundation & Release Truth. Release 1 is genuine early production / first-week customer work. | Y19: 92a655e1ddc4becedbaf89a3db96dc0d0f1eaf94 — subject not recovered | Z19: 46266 | AA19: L5.3 | AB19: Analysis Subject, grain and signal aggregation authority | AC19: L4.2 | AD19: Build | AE19: D1; D3; D5 | AF19: Core | AG19: R1 | AH19: Advances | AI19: =IF(Y19="","",Y19) -> 92a655e1ddc4becedbaf89a3db96dc0d0f1eaf94 — subject not recovered | AJ19: Inherited baseline estimate | AK19: v4.10.3 | AL19: Chapters 3/4 v4.10.3 — MD + illustrated Word; UI Coverage / UI Controls in this workbook | AM19: =IF(AND(ISNUMBER(J19),OR(AR19="INHERITED ESTIMATE",AR19="CONFIRMED ESTIMATE")),1,0) -> 1 | AO19: Recorded closed — inherited evidence | AP19: Inherited v2.22.0 intended record; no new runtime certification in this repair. | AR19: INHERITED ESTIMATE | AS19: =IF(AM19=1,J19,"") -> 12 | AT19: =IF(AND(AM19=1,ISNUMBER(R19)),R19,"") -> 5.1 | AU19: =IFERROR(INDEX('Source Review'!$B$2:$B$52,MATCH($A19,'Source Review'!$A$2:$A$52,0)),"NOT SOURCE-REVIEWED IN THIS PASS") -> NOT SOURCE-REVIEWED IN THIS PASS | AV19: =IFERROR(INDEX('Source Review'!$F$2:$F$52,MATCH($A19,'Source Review'!$A$2:$A$52,0)),"") | AW19: =IFERROR(INDEX('Source Review'!$G$2:$G$52,MATCH($A19,'Source Review'!$A$2:$A$52,0)),"") | AX19: =IFERROR(INDEX('Source Review'!$H$2:$H$52,MATCH($A19,'Source Review'!$A$2:$A$52,0)),"") | AY19: =IF(COUNTIF('Source Review'!$A$2:$A$52,$A19)>0,"UNCONFIRMED REVIEW ESTIMATE - not P80 or elapsed","NOT ESTIMATED IN THIS PASS") -> NOT ESTIMATED IN THIS PASS | AZ19: =IFERROR(INDEX('Source Review'!$I$2:$I$52,MATCH($A19,'Source Review'!$A$2:$A$52,0)),"") | BA19: =IFERROR(INDEX('Source Review'!$E$2:$E$52,MATCH($A19,'Source Review'!$A$2:$A$52,0)),"") | BB19: =IF(COUNTIF('Source Review'!$A$2:$A$52,$A19)>0,"14-Sep-2026 snapshot; later closure evidence separate; no live HEAD verification","")
A20: T-216 | B20: M2 | C20: P1 | D20: Source Time Authority contract and timestamp-semantics kernel | E20: Architecture / Analytics Engine | F20: Temporal authority contract | G20: Critical | H20: Freeze the per-source time contract: timezone, timestamp basis/origin, DST policy, clock reference, observed skew, maximum tolerated skew, and source/server/ingest timestamp semantics. No production persistence in this task. | I20: Known-answer contract tests distinguish source/server/ingest timestamps and prove skew beyond tolerance yields TemporalUncertain rather than conflict. Runs without production DB access. | J20: 5 | K20: Done | L20: Worker 3 | M20: T-208 | N20: T-200; T-217; T-233 | O20: M2: ~1 month from owner planning checkpoint; exact date not committed | P20: Release 1 MUST | Q20: Kernel/contract | R20: 1.25 | S20: M2-P1 | T20: CLOSED BASELINE — no new start gate and no re-execution implied. Preserve accepted closure and clean owned scope; reopen only on a concrete, separately recorded regression. Downstream consumes the frozen contract. | U20: Temporal contract/tests only. | V20: T-233 persists source-time authority; T-217 consumes contract without waiting for persistence. | W20: Product Foundation & Release Truth | X20: M2 P1 — Product Foundation & Release Truth. Release 1 is genuine early production / first-week customer work. | Y20: ea9103fd — Establish source time authority for plant timestamps | Z20: 46259 | AA20: L1.5 | AB20: Acquisition provenance and source lineage | AC20: L5.5 | AD20: Build | AE20: D1; D3; D5 | AF20: Core | AG20: R1 | AH20: Advances | AI20: =IF(Y20="","",Y20) -> ea9103fd — Establish source time authority for plant timestamps | AJ20: Inherited baseline estimate | AK20: v4.10.3 | AL20: Chapters 3/4 v4.10.3 — MD + illustrated Word; UI Coverage / UI Controls in this workbook | AM20: =IF(AND(ISNUMBER(J20),OR(AR20="INHERITED ESTIMATE",AR20="CONFIRMED ESTIMATE")),1,0) -> 1 | AO20: Recorded closed — inherited evidence | AP20: Inherited v2.22.0 intended record; no new runtime certification in this repair. | AR20: INHERITED ESTIMATE | AS20: =IF(AM20=1,J20,"") -> 5 | AT20: =IF(AND(AM20=1,ISNUMBER(R20)),R20,"") -> 1.25 | AU20: =IFERROR(INDEX('Source Review'!$B$2:$B$52,MATCH($A20,'Source Review'!$A$2:$A$52,0)),"NOT SOURCE-REVIEWED IN THIS PASS") -> NOT SOURCE-REVIEWED IN THIS PASS | AV20: =IFERROR(INDEX('Source Review'!$F$2:$F$52,MATCH($A20,'Source Review'!$A$2:$A$52,0)),"") | AW20: =IFERROR(INDEX('Source Review'!$G$2:$G$52,MATCH($A20,'Source Review'!$A$2:$A$52,0)),"") | AX20: =IFERROR(INDEX('Source Review'!$H$2:$H$52,MATCH($A20,'Source Review'!$A$2:$A$52,0)),"") | AY20: =IF(COUNTIF('Source Review'!$A$2:$A$52,$A20)>0,"UNCONFIRMED REVIEW ESTIMATE - not P80 or elapsed","NOT ESTIMATED IN THIS PASS") -> NOT ESTIMATED IN THIS PASS | AZ20: =IFERROR(INDEX('Source Review'!$I$2:$I$52,MATCH($A20,'Source Review'!$A$2:$A$52,0)),"") | BA20: =IFERROR(INDEX('Source Review'!$E$2:$E$52,MATCH($A20,'Source Review'!$A$2:$A$52,0)),"") | BB20: =IF(COUNTIF('Source Review'!$A$2:$A$52,$A20)>0,"14-Sep-2026 snapshot; later closure evidence separate; no live HEAD verification","")
A21: T-231 | B21: M2 | C21: P1 | D21: Persist Analysis Subject and Grain authority in canonical definition store | E21: Backend / Database | F21: Canonical subject/grain persistence | G21: Critical | H21: Persist the frozen T-209 AnalysisSubject/GrainDefinition contract through canonical definitions and analysis_subjects/grain-definition tables. This task owns migration, tenant-safe keys, version binding and canonical APIs only; it does not redesign the contract. | I21: Fresh migration/replay green. Persist discrete, equipment-window and flow-interval grains; same binary resolves all via API. GR01 preserved. Tenant isolation and definition-version replay pass. | J21: 6 | K21: Done | L21: Worker 1 | M21: T-090; T-209 | N21: T-092; T-128; T-139; T-232; T-235 | O21: M2: ~1 month from owner planning checkpoint; exact date not committed | P21: Release 1 MUST | Q21: DB/schema authority | R21: 2.55 | S21: M2-P1 | T21: CLOSED BASELINE — no new start gate and no re-execution implied. Preserve accepted closure and clean owned scope; reopen only on a concrete, separately recorded regression. Downstream consumes the frozen contract. | U21: analysis_subjects/grain definitions + API/migrations. | V21: T-092/T-128/T-139/T-213 consume committed persistence; they do not invent subject identity. | W21: Product Foundation & Release Truth | X21: M2 P1 — Product Foundation & Release Truth. Release 1 is genuine early production / first-week customer work. | Y21: c930af079502aa1660ef2bd5c50756d3fc3cf8f3 — Persist-T231-canonical-analysis-subject-grain-authority | AA21: L5.3 | AB21: Analysis Subject, grain and signal aggregation authority | AD21: Build | AE21: D1; D3; D4; D5 | AF21: Core | AG21: R1 | AH21: Advances | AI21: =IF(Y21="","",Y21) -> c930af079502aa1660ef2bd5c50756d3fc3cf8f3 — Persist-T231-canonical-analysis-subject-grain-authority | AJ21: Inherited baseline estimate | AK21: v4.10.3 | AL21: Chapters 3/4 v4.10.3 — MD + illustrated Word; UI Coverage / UI Controls in this workbook | AM21: =IF(AND(ISNUMBER(J21),OR(AR21="INHERITED ESTIMATE",AR21="CONFIRMED ESTIMATE")),1,0) -> 1 | AO21: Recorded closed — inherited evidence | AP21: Inherited v2.22.0 intended record; no new runtime certification in this repair. | AR21: INHERITED ESTIMATE | AS21: =IF(AM21=1,J21,"") -> 6 | AT21: =IF(AND(AM21=1,ISNUMBER(R21)),R21,"") -> 2.55 | AU21: =IFERROR(INDEX('Source Review'!$B$2:$B$52,MATCH($A21,'Source Review'!$A$2:$A$52,0)),"NOT SOURCE-REVIEWED IN THIS PASS") -> NOT SOURCE-REVIEWED IN THIS PASS | AV21: =IFERROR(INDEX('Source Review'!$F$2:$F$52,MATCH($A21,'Source Review'!$A$2:$A$52,0)),"") | AW21: =IFERROR(INDEX('Source Review'!$G$2:$G$52,MATCH($A21,'Source Review'!$A$2:$A$52,0)),"") | AX21: =IFERROR(INDEX('Source Review'!$H$2:$H$52,MATCH($A21,'Source Review'!$A$2:$A$52,0)),"") | AY21: =IF(COUNTIF('Source Review'!$A$2:$A$52,$A21)>0,"UNCONFIRMED REVIEW ESTIMATE - not P80 or elapsed","NOT ESTIMATED IN THIS PASS") -> NOT ESTIMATED IN THIS PASS | AZ21: =IFERROR(INDEX('Source Review'!$I$2:$I$52,MATCH($A21,'Source Review'!$A$2:$A$52,0)),"") | BA21: =IFERROR(INDEX('Source Review'!$E$2:$E$52,MATCH($A21,'Source Review'!$A$2:$A$52,0)),"") | BB21: =IF(COUNTIF('Source Review'!$A$2:$A$52,$A21)>0,"14-Sep-2026 snapshot; later closure evidence separate; no live HEAD verification","")
A22: T-250 | B22: M2 | C22: P1 | D22: Frontend suite truth convergence: Journey routing and design-system corrections | E22: Frontend | F22: Release truth / design system | G22: Very Important | H22: Resolve only the six deterministic findings exposed by T-205 without reopening T-205: correct stale JourneyRail certification for Connections=J4 and Supervisor=J15; map the real /assistant/configuration route directly to J15 and guard redirect aliases; move constant MetricCard inline styles to CSS; retain HeatmapChart only as an exact-file semantic-matrix exception; convert SpecificationTable to StandardTable while preserving observed-state semantics. No broad frontend cleanup. | I22: Narrow affected tests GREEN first: Connections=J4, Supervisor=J15, /assistant/configuration=J15, redirect-alias guard GREEN, MetricCard D2 violations=0, Heatmap exact-file exception only, SpecificationTable uses StandardTable and existing component tests stay GREEN. Then run the ordinary complete frontend suite once with failed=0 and skipped=0. Do not rerun T-205 Certify unless T-205 gate code changes. | J22: 6 | K22: Done | L22: Worker 2 | M22: T-205 | N22: T-150; T-255; T-257; T-258 | O22: M2: ~1 month from owner planning checkpoint; exact date not committed | P22: Release 1 MUST | Q22: Frontend bounded correction | R22: 2.5 | S22: M2-P1 | T22: CLOSED BASELINE — no new start gate and no re-execution implied. Preserve accepted closure and clean owned scope; reopen only on a concrete, separately recorded regression. Downstream consumes the frozen contract. | U22: Own only the bounded JourneyRail/Journey tests, MetricCard styling, exact Heatmap architecture exception and SpecificationTable convergence. No edits to T-205 runner/validator and no unrelated frontend cleanup. | V22: T-205 remains closed. After T-250 GREEN, move directly to the next eligible existing Worker-2 task. No unnamed corrective work and no repeated expensive certification loop. | W22: Product Foundation & Release Truth | X22: CENTRAL 30-Aug-2026: no Task ID = no repository mutation. T-250 is the sole owner of these six findings; bounded correction only, narrow tests first, one final normal suite. | Y22: 6615481b — Converge frontend journey and design-system truth | Z22: 46264 | AA22: L8.2 | AB22: Test architecture with disposable isolated databases | AD22: Converge | AE22: D1; D2; D5 | AF22: Core | AG22: R1 | AH22: Advances | AI22: =IF(Y22="","",Y22) -> 6615481b — Converge frontend journey and design-system truth | AJ22: Inherited baseline estimate | AK22: v4.10.3 | AL22: Chapters 3/4 v4.10.3 — MD + illustrated Word; UI Coverage / UI Controls in this workbook | AM22: =IF(AND(ISNUMBER(J22),OR(AR22="INHERITED ESTIMATE",AR22="CONFIRMED ESTIMATE")),1,0) -> 1 | AO22: Recorded closed — inherited evidence | AP22: Inherited v2.22.0 intended record; no new runtime certification in this repair. | AR22: INHERITED ESTIMATE | AS22: =IF(AM22=1,J22,"") -> 6 | AT22: =IF(AND(AM22=1,ISNUMBER(R22)),R22,"") -> 2.5 | AU22: =IFERROR(INDEX('Source Review'!$B$2:$B$52,MATCH($A22,'Source Review'!$A$2:$A$52,0)),"NOT SOURCE-REVIEWED IN THIS PASS") -> NOT SOURCE-REVIEWED IN THIS PASS | AV22: =IFERROR(INDEX('Source Review'!$F$2:$F$52,MATCH($A22,'Source Review'!$A$2:$A$52,0)),"") | AW22: =IFERROR(INDEX('Source Review'!$G$2:$G$52,MATCH($A22,'Source Review'!$A$2:$A$52,0)),"") | AX22: =IFERROR(INDEX('Source Review'!$H$2:$H$52,MATCH($A22,'Source Review'!$A$2:$A$52,0)),"") | AY22: =IF(COUNTIF('Source Review'!$A$2:$A$52,$A22)>0,"UNCONFIRMED REVIEW ESTIMATE - not P80 or elapsed","NOT ESTIMATED IN THIS PASS") -> NOT ESTIMATED IN THIS PASS | AZ22: =IFERROR(INDEX('Source Review'!$I$2:$I$52,MATCH($A22,'Source Review'!$A$2:$A$52,0)),"") | BA22: =IFERROR(INDEX('Source Review'!$E$2:$E$52,MATCH($A22,'Source Review'!$A$2:$A$52,0)),"") | BB22: =IF(COUNTIF('Source Review'!$A$2:$A$52,$A22)>0,"14-Sep-2026 snapshot; later closure evidence separate; no live HEAD verification","")
A23: T-251 | B23: M2 | C23: P1 | D23: Physical database catalogue, naming authority and zero-unknown schema dictionary | E23: Database | F23: Schema governance | G23: Critical | H23: Create the generated physical database catalogue required by Master Design v4.10.1. Reconcile canonical migration/EF authority with fresh canonical certification database `ppiq_acceptance_empty` and long-lived `ppiq_app`. Every table/view and every column in ppiq_meta, ppiq_plant, ppiq_staging and permitted public infrastructure receives schema, logical family, lifecycle class, owner, purpose, creator, readers/writers, keys/FKs, design clause, backlog owner, retention/RLS policy and naming-conformance state. Generate the relation graph. Define/enforce the forward snake_case/no-customer-vocabulary naming standard without mass-renaming grandfathered objects. Read-only census first; deletion/rename is outside this task. | I23: Fresh canonical certification DB `ppiq_acceptance_empty`: 100% tables/views/columns represented; zero unknown product objects; every table has logical family + lifecycle + owner + design clause; physical FK graph generated; public contains platform infrastructure only. Long-lived ppiq_app: every extra object classified, never auto-deleted. Generator reruns deterministically from executable schema authority. A new DDL object without catalogue classification makes the gate red. | J23: 12 | K23: Done | L23: Worker 1 | M23: T-087; T-088; T-260 | N23: T-112; T-150; T-252; T-256; T-259 | O23: M2: ~1 month from owner planning checkpoint; exact date not committed | P23: Release 1 MUST | Q23: DB/schema/migration | R23: 1.8 | S23: M2-P1 | T23: CLOSED BASELINE — no new start gate and no re-execution implied. Preserve accepted closure and clean owned scope; reopen only on a concrete, separately recorded regression. Downstream consumes the frozen contract. | U23: Own generated DB catalogue tooling/documentation and read-only pg_catalog queries. No product table deletion, rename or unrelated DDL. | V23: Publish semantic-named catalogue artifacts only; no task-number repository filename. Hand off the generated dictionary to T-115/T-123/T-150. | W23: Product Foundation & Release Truth | X23: CENTRAL 04-Sep-2026: table count is not a defect; unknown authority is. This task establishes zero-unknown physical schema governance before any cleanup. | Y23: 7ba31f96f3810bdac734bd1850275a601503d34d | AA23: L5.7 | AB23: Physical database governance and zero-unknown catalogue | AC23: L8.1 | AD23: Build | AE23: D4; D5 | AF23: Core | AG23: R1 | AH23: Advances | AI23: =IF(Y23="","",Y23) -> 7ba31f96f3810bdac734bd1850275a601503d34d | AJ23: Inherited baseline estimate | AK23: v4.10.3 | AL23: Chapters 3/4 v4.10.3 — MD + illustrated Word; UI Coverage / UI Controls in this workbook | AM23: =IF(AND(ISNUMBER(J23),OR(AR23="INHERITED ESTIMATE",AR23="CONFIRMED ESTIMATE")),1,0) -> 1 | AO23: Recorded closed — inherited evidence | AP23: Original catalogue closure explicitly frozen by CENTRAL. Retain Done; later catalogue/build changes do not retroactively erase this producer closure. Pasted text(20260910-064052).txt lines139-146: CENTRAL states T-251 CLOSED GREEN7ba31f96f3810bdac734bd1850275a601503d34d; later T-245 preflight observes its catalogue changes. | AR23: INHERITED ESTIMATE | AS23: =IF(AM23=1,J23,"") -> 12 | AT23: =IF(AND(AM23=1,ISNUMBER(R23)),R23,"") -> 1.8 | AU23: =IFERROR(INDEX('Source Review'!$B$2:$B$52,MATCH($A23,'Source Review'!$A$2:$A$52,0)),"NOT SOURCE-REVIEWED IN THIS PASS") -> NOT SOURCE-REVIEWED IN THIS PASS | AV23: =IFERROR(INDEX('Source Review'!$F$2:$F$52,MATCH($A23,'Source Review'!$A$2:$A$52,0)),"") | AW23: =IFERROR(INDEX('Source Review'!$G$2:$G$52,MATCH($A23,'Source Review'!$A$2:$A$52,0)),"") | AX23: =IFERROR(INDEX('Source Review'!$H$2:$H$52,MATCH($A23,'Source Review'!$A$2:$A$52,0)),"") | AY23: =IF(COUNTIF('Source Review'!$A$2:$A$52,$A23)>0,"UNCONFIRMED REVIEW ESTIMATE - not P80 or elapsed","NOT ESTIMATED IN THIS PASS") -> NOT ESTIMATED IN THIS PASS | AZ23: =IFERROR(INDEX('Source Review'!$I$2:$I$52,MATCH($A23,'Source Review'!$A$2:$A$52,0)),"") | BA23: =IFERROR(INDEX('Source Review'!$E$2:$E$52,MATCH($A23,'Source Review'!$A$2:$A$52,0)),"") | BB23: =IF(COUNTIF('Source Review'!$A$2:$A$52,$A23)>0,"14-Sep-2026 snapshot; later closure evidence separate; no live HEAD verification","")
A24: T-252 | B24: M2 | C24: P1 | D24: Disposable database lifecycle and integration-test database isolation | E24: Quality | F24: Database isolation | G24: Critical | H24: Remove shared-live-database mutation from certification/test infrastructure. Integration suites and corrective packs create or clone a dedicated disposable database/template, record its name, execute against it, and drop it in an unconditional finally path on success/failure. Never flip or mutate live ppiq_app/ppiq_presentation as a test fixture. Add bounded cleanup for current orphan probe/backup/scratch databases after evidence-retention adjudication. v2.20.0 PROMOTION — this is now M2-P1 foundation scope, not late P5 hardening. Every DB-dependent certification path must either receive a dedicated disposable database/template from this authority or explicitly declare that it is a read-only external probe. Local developer runs may skip an external-probe-only test with a named reason when the probe is absent; Release-1 CI/certification provisions its own disposable target and permits zero DB-fixture skips. v2.20.1 DEPENDENCY CORRECTION — T-251 is an explicit prerequisite, not only a handover convention. T-251 classifies current/fresh physical database authority before T-252 changes certification/test database lifecycle. | I24: Induced test failure, PowerShell/native-command failure and timeout each leave zero newly orphaned databases. Captured database names are gone after cleanup; ppiq_app, ppiq_acceptance_empty, ppiq_presentation and postgres are untouched. Two parallel suites use distinct DBs. A post-run orphan query is green. Current retained backups/probes are classified and removed only after retention proof. A release-profile certification provisions its own disposable DB and records zero database-fixture skips. A developer-local run with an intentionally absent external probe may skip only the named probe test and must emit the exact reason; it may not fail by mutating or assuming a shared live database. Emit the DB-fixture execution result using the canonical T-259 Release Evidence Envelope v1 fields. T-252 owns DB skip semantics and database_fixture_mode/name values; it does not invent a second envelope format. Producer contract is T-259 Release Evidence Envelope v1. T-252 may add DB-specific extension fields but may not rename/redefine common fields. For Release-1 DB-fixture certification specifically, `skipped_count` must be 0. A local approved external-probe skip is allowed only outside the Release-1 certification profile and still counts in total_count, not executed_count. | J24: 8 | K24: Done | L24: Worker 1 | M24: T-087; T-088; T-251; T-259 | N24: T-106; T-112; T-150; T-256 | O24: M2: ~1 month from owner planning checkpoint; exact date not committed | P24: Release 1 MUST | Q24: Integration/E2E/certification | R24: 1.2 | S24: M2-P1 | T24: CLOSED BASELINE — no new start gate and no re-execution implied. Preserve accepted closure and clean owned scope; reopen only on a concrete, separately recorded regression. Downstream consumes the frozen contract. | U24: Own integration-test DB fixture/runner and disposable-DB lifecycle tooling only. Do not change product schema semantics. | V24: Every pack that CREATE DATABASEs owns DROP in finally. Persistent DB roles are explicit and protected. | W24: Product Foundation & Release Truth | X24: CENTRAL v2.20.0 08-Sep-2026: promoted from P5 to P1. Certification DB isolation is foundational; Worker-1 sequence is T-251 → T-252 → T-256. | AA24: L8.2 | AB24: Test architecture with disposable isolated databases | AD24: Harden | AE24: D3; D4; D5 | AF24: Core | AG24: R1 | AH24: Advances | AI24: =IF(Y24="","",Y24) | AJ24: Inherited baseline estimate | AK24: v4.10.3 | AL24: Chapters 3/4 v4.10.3 — MD + illustrated Word; UI Coverage / UI Controls in this workbook | AM24: =IF(AND(ISNUMBER(J24),OR(AR24="INHERITED ESTIMATE",AR24="CONFIRMED ESTIMATE")),1,0) -> 1 | AO24: Recorded closed — inherited evidence | AP24: Inherited v2.22.0 intended record; no new runtime certification in this repair. | AR24: INHERITED ESTIMATE | AS24: =IF(AM24=1,J24,"") -> 8 | AT24: =IF(AND(AM24=1,ISNUMBER(R24)),R24,"") -> 1.2 | AU24: =IFERROR(INDEX('Source Review'!$B$2:$B$52,MATCH($A24,'Source Review'!$A$2:$A$52,0)),"NOT SOURCE-REVIEWED IN THIS PASS") -> NOT SOURCE-REVIEWED IN THIS PASS | AV24: =IFERROR(INDEX('Source Review'!$F$2:$F$52,MATCH($A24,'Source Review'!$A$2:$A$52,0)),"") | AW24: =IFERROR(INDEX('Source Review'!$G$2:$G$52,MATCH($A24,'Source Review'!$A$2:$A$52,0)),"") | AX24: =IFERROR(INDEX('Source Review'!$H$2:$H$52,MATCH($A24,'Source Review'!$A$2:$A$52,0)),"") | AY24: =IF(COUNTIF('Source Review'!$A$2:$A$52,$A24)>0,"UNCONFIRMED REVIEW ESTIMATE - not P80 or elapsed","NOT ESTIMATED IN THIS PASS") -> NOT ESTIMATED IN THIS PASS | AZ24: =IFERROR(INDEX('Source Review'!$I$2:$I$52,MATCH($A24,'Source Review'!$A$2:$A$52,0)),"") | BA24: =IFERROR(INDEX('Source Review'!$E$2:$E$52,MATCH($A24,'Source Review'!$A$2:$A$52,0)),"") | BB24: =IF(COUNTIF('Source Review'!$A$2:$A$52,$A24)>0,"14-Sep-2026 snapshot; later closure evidence separate; no live HEAD verification","")
A25: T-256 | B25: M2 | C25: P1 | D25: Runtime genericity and three-schema consumer convergence | E25: Backend | F25: Genericity / physical-consumer convergence | G25: Critical | H25: After T-251 classifies the physical catalogue and T-252 stabilises test DBs, converge runtime consumers onto the three-schema/generic product authority. Every runtime `public.*` product reference is either migrated to ppiq_meta/ppiq_plant/ppiq_staging/definition authority or explicitly catalogued as permitted platform compatibility with a bounded retirement owner. Material/heat/coil-specific endpoint/service families in the generic binary are retired, moved behind an explicit presentation/demo compatibility boundary, or replaced by Analysis Subject/relationship/registry-driven surfaces. Do not mass-rename blindly and do not break the retained presentation database. v2.20.1 OWNERSHIP BOUNDARY — T-256 is BACKEND/API/DB-RUNTIME convergence only. Do not edit Worker-2 frontend MaterialAnalytics pages, frontend route ownership, or productApiClient frontend types. Where backend convergence would otherwise break an existing frontend material surface, preserve a bounded typed compatibility contract long enough for T-258 to migrate/retire that frontend consumer; do not leave the generic build red. v2.20.2 RECORDED T-253 HANDOFF — `MappingDefinitionService.AllowedTargetEntities` is a measured hardcoded 12-name target vocabulary and is NOT T-253 scope. T-256 owns its backend convergence: consume the canonical projection-target capability and catalog authority established by T-253, remove the duplicate plant-vocabulary list as runtime authority, and preserve only any explicitly justified compatibility mapping. v2.20.3 DEPENDENCY RULING — T-253 remains a HARD dependency for T-256 because T-256 must replace MappingDefinitionService.AllowedTargetEntities with the exact canonical projection-target predicate created by T-253. Starting T-256 without that contract would either duplicate classification or broaden eligibility incorrectly. Phase IDs are product/outcome groupings, not chronological barriers; the dependency graph governs execution. | I25: Runtime-project scan reports zero unapproved `public.` product reference; every permitted public object exists in the T-251 platform/compatibility catalogue with owner and retirement state. Genericity gate explicitly covers material endpoint/service and generic API composition paths and has unknown=0. A foreign customer-shaped backend/API/query journey runs on the same binary with no material/heat/coil backend product dependency. If a presentation-only compatibility route remains, it is disabled outside the explicit presentation profile and is not required by canonical product paths. Backend/API acceptance is green without editing Worker-2 frontend files. Enumerate every remaining frontend material-specific consumer discovered by the backend convergence and hand it to T-258 as machine-readable evidence. The current generic frontend build remains green through the compatibility handoff. Static/runtime proof shows MappingDefinitionService no longer owns an independent hardcoded AllowedTargetEntities plant vocabulary; valid target eligibility resolves from canonical catalog/registry authority and foreign-shaped targets require no source-code list edit. MappingDefinitionService target validation consumes the same T-253 projection-target predicate used by the authoring picker. Positive/negative eligibility decisions are identical across Canvas authoring and MappingDefinitionService; no second list or schema-only rule survives. | J25: 12 | K25: Done | L25: Worker 1 | M25: T-088; T-094; T-251; T-252; T-253 | N25: T-116; T-150; T-247; T-258 | O25: M2: ~1 month from owner planning checkpoint; exact date not committed | P25: Release 1 MUST | Q25: Backend/domain contract | R25: 3.2 | S25: M2-P1 | T25: CLOSED BASELINE — no new start gate and no re-execution implied. Preserve accepted closure and clean owned scope; reopen only on a concrete, separately recorded regression. Downstream consumes the frozen contract. | U25: Backend runtime consumers, API composition, DB-facing services and backend architecture/genericity guards only. NO Frontend/PlantProcess.Web mutation. T-258 exclusively owns frontend material/genericity convergence. | V25: Publish a bounded compatibility/consumer handoff manifest to T-258. Do not solve frontend Material pages/types/routes inside T-256; do not leave generic frontend red. | W25: Product Foundation & Release Truth | X25: New P1 convergence task; closed T-093/T-094 stay closed and act as regression authorities. | Y25: 36de9370 | AA25: L2.1 | AB25: Three-schema platform and placement law | AC25: L5.1; L5.7 | AD25: Converge | AE25: D1; D3; D4; D5 | AF25: Core | AG25: R1 | AH25: Advances | AI25: =IF(Y25="","",Y25) -> 36de9370 | AJ25: Inherited baseline estimate | AK25: v4.10.3 | AL25: Chapters 3/4 v4.10.3 — MD + illustrated Word; UI Coverage / UI Controls in this workbook | AM25: =IF(AND(ISNUMBER(J25),OR(AR25="INHERITED ESTIMATE",AR25="CONFIRMED ESTIMATE")),1,0) -> 1 | AO25: Recorded closed — inherited evidence | AP25: Inherited accepted Done state retained. T-262's terminal summary identifies parent36de9370 as T-256. This corroborates a commit anchor, not a rerun of T-256 gates. Pasted text(20260912-074928).txt | lines1229-1243; T-262 GREEN committed86e1b677212195f191697ecdca7e9441b3dbde33; parent36de9370; live definition-store integration explicitly unexecuted. | AR25: INHERITED ESTIMATE | AS25: =IF(AM25=1,J25,"") -> 12 | AT25: =IF(AND(AM25=1,ISNUMBER(R25)),R25,"") -> 3.2 | AU25: =IFERROR(INDEX('Source Review'!$B$2:$B$52,MATCH($A25,'Source Review'!$A$2:$A$52,0)),"NOT SOURCE-REVIEWED IN THIS PASS") -> NOT SOURCE-REVIEWED IN THIS PASS | AV25: =IFERROR(INDEX('Source Review'!$F$2:$F$52,MATCH($A25,'Source Review'!$A$2:$A$52,0)),"") | AW25: =IFERROR(INDEX('Source Review'!$G$2:$G$52,MATCH($A25,'Source Review'!$A$2:$A$52,0)),"") | AX25: =IFERROR(INDEX('Source Review'!$H$2:$H$52,MATCH($A25,'Source Review'!$A$2:$A$52,0)),"") | AY25: =IF(COUNTIF('Source Review'!$A$2:$A$52,$A25)>0,"UNCONFIRMED REVIEW ESTIMATE - not P80 or elapsed","NOT ESTIMATED IN THIS PASS") -> NOT ESTIMATED IN THIS PASS | AZ25: =IFERROR(INDEX('Source Review'!$I$2:$I$52,MATCH($A25,'Source Review'!$A$2:$A$52,0)),"") | BA25: =IFERROR(INDEX('Source Review'!$E$2:$E$52,MATCH($A25,'Source Review'!$A$2:$A$52,0)),"") | BB25: =IF(COUNTIF('Source Review'!$A$2:$A$52,$A25)>0,"14-Sep-2026 snapshot; later closure evidence separate; no live HEAD verification","")
A26: T-259 | B26: M2 | C26: P1 | D26: Release evidence envelope v1 machine-readable contract | E26: Release / governance | F26: Evidence contract | G26: Critical | H26: Freeze the small representation-independent machine-readable Release Evidence Envelope contract before DB/frontend producers implement it. This task owns ONLY the shared schema/validator contract, not the T-227 production scorecard and not producer execution. Contract version `1.0` defines required common fields: contract_version, task_id, gate_id/suite_id, environment, profile, started_at, completed_at, total_count, executed_count, passed_count, failed_count, skipped_count, unapproved_skip_count, structured skip_reasons, commit_sha, artifact/evidence paths and final verdict. Optional producer extensions include database_fixture_mode/database_name and other namespaced evidence details. Count semantics are explicit: `total_count = executed_count + skipped_count`; `executed_count = passed_count + failed_count`; `0 <= unapproved_skip_count <= skipped_count`. A skipped case is discovered/total but NOT executed. GREEN is impossible when failed_count>0 or unapproved_skip_count>0. Producer-specific release policy may be stricter (for example T-252 Release-1 DB-fixture acceptance requires skipped_count=0). Use semantic repository filenames, never a task-number filename. | I26: Validate one DB-fixture example shaped for T-252 and one frontend/E2E example shaped for T-257 against the same contract. Required invariants: total_count=executed_count+skipped_count; executed_count=passed_count+failed_count; unapproved_skip_count<=skipped_count. Negative controls reject: wrong contract version, inconsistent totals, a skipped case counted as executed, GREEN with failed_count>0, GREEN with unapproved_skip_count>0, unapproved_skip_count greater than skipped_count, and malformed skip-reason classification. Include an all-skipped fixture and prove executed_count=0 rather than total_count. The schema/validator is consumable from PowerShell/CI and application/test tooling without either producer redefining fields. No scorecard thresholds, DB lifecycle or frontend runner behavior is implemented here. | J26: 2 | K26: Done | L26: Worker 1 | M26: T-251 | N26: T-150; T-227; T-252; T-257 | O26: M2: ~1 month from owner planning checkpoint; exact date not committed | P26: Release 1 MUST | Q26: Architecture/test | R26: 0.3 | S26: M2-P1 | T26: CLOSED BASELINE — no new start gate and no re-execution implied. Preserve accepted closure and clean owned scope; reopen only on a concrete, separately recorded regression. Downstream consumes the frozen contract. | U26: Shared release-evidence schema/validator + focused contract tests only. No DB fixture implementation, frontend test runner, scorecard, feature code or release aggregation. | V26: T-252/T-257 are producers. T-227 owns production acceptance scorecard/policy. T-150 aggregates. None may redefine the v1 envelope. | W26: Product Foundation & Release Truth | X26: v2.20.2 Option-A ruling from Worker-1 consistency review: split schema contract ahead of producers rather than pulling full T-227 P5 scorecard into P1. | AA26: L8.8 | AB26: C1–C4 performance certification and golden-journey release gate | AD26: Build | AE26: D3; D5 | AF26: Core | AG26: R1 | AH26: Advances | AI26: =IF(Y26="","",Y26) | AJ26: Inherited baseline estimate | AK26: v4.10.3 | AL26: Chapters 3/4 v4.10.3 — MD + illustrated Word; UI Coverage / UI Controls in this workbook | AM26: =IF(AND(ISNUMBER(J26),OR(AR26="INHERITED ESTIMATE",AR26="CONFIRMED ESTIMATE")),1,0) -> 1 | AO26: Recorded closed — inherited evidence | AP26: Inherited v2.22.0 intended record; no new runtime certification in this repair. | AR26: INHERITED ESTIMATE | AS26: =IF(AM26=1,J26,"") -> 2 | AT26: =IF(AND(AM26=1,ISNUMBER(R26)),R26,"") -> 0.3 | AU26: =IFERROR(INDEX('Source Review'!$B$2:$B$52,MATCH($A26,'Source Review'!$A$2:$A$52,0)),"NOT SOURCE-REVIEWED IN THIS PASS") -> NOT SOURCE-REVIEWED IN THIS PASS | AV26: =IFERROR(INDEX('Source Review'!$F$2:$F$52,MATCH($A26,'Source Review'!$A$2:$A$52,0)),"") | AW26: =IFERROR(INDEX('Source Review'!$G$2:$G$52,MATCH($A26,'Source Review'!$A$2:$A$52,0)),"") | AX26: =IFERROR(INDEX('Source Review'!$H$2:$H$52,MATCH($A26,'Source Review'!$A$2:$A$52,0)),"") | AY26: =IF(COUNTIF('Source Review'!$A$2:$A$52,$A26)>0,"UNCONFIRMED REVIEW ESTIMATE - not P80 or elapsed","NOT ESTIMATED IN THIS PASS") -> NOT ESTIMATED IN THIS PASS | AZ26: =IFERROR(INDEX('Source Review'!$I$2:$I$52,MATCH($A26,'Source Review'!$A$2:$A$52,0)),"") | BA26: =IFERROR(INDEX('Source Review'!$E$2:$E$52,MATCH($A26,'Source Review'!$A$2:$A$52,0)),"") | BB26: =IF(COUNTIF('Source Review'!$A$2:$A$52,$A26)>0,"14-Sep-2026 snapshot; later closure evidence separate; no live HEAD verification","")
A27: T-260 | B27: M2 | C27: P1 | D27: Canonical acceptance database builder convergence | E27: Database / release infrastructure | F27: Fresh certification database build path | G27: Critical | H27: Correct the governed builder for `ppiq_acceptance_empty` so a fresh NO-SEED certification database is created by the complete canonical migration authority rather than a partial EF+scripts subset. The builder must consume `canonical-migration-order.json` (or the same single canonical ordering authority) and execute every required tier in declared order, including topology/storage convergence and declared views, while excluding demonstration/seed/test content. Trace the creator authority for `dump_store.src_caster_oracle_shape_cast_pieces`; if it enters through demo/seed/test content incorrectly present on the canonical fresh path, remove that path defect. If it is an explicitly required legacy compatibility migration, report it for T-256 rather than silently deleting product data. This task may rebuild the empty certification database as a governed certification operation; it must not mutate `ppiq_app` or `ppiq_presentation` and must not use them as fixtures. | I27: One semantic PowerShell runner performs non-writing preflight, backs up owned builder/order files, builds a uniquely named disposable candidate from the canonical order, proves required topology convergence + declared views are present and demo/seed/test content is absent, then replaces/recreates `ppiq_acceptance_empty` only after the candidate is GREEN and the previous certification DB can be restored on failure. Prove the canonical-order consumer executed all declared required entries exactly once in order, with zero undeclared execution. Prove `ppiq_app` and `ppiq_presentation` are untouched. After rebuild, rerun the T-251 catalogue and record before/after counts; do not classify the old 106/81 queue. The `dump_store.src_caster_oracle_shape_cast_pieces` creator is identified exactly and ruled as canonical compatibility or excluded demo/seed/test path. Negative control: omit one terminal canonical tier in a disposable candidate and the build-path gate must go RED. | J27: 6 | K27: Done | L27: Worker 1 | M27: T-088 | N27: T-251 | O27: M2: ~1 month from owner planning checkpoint; exact date not committed | P27: Release 1 MUST | Q27: Database infrastructure corrective | R27: 1.8 | S27: M2-P1 | T27: CLOSED BASELINE — no new start gate and no re-execution implied. Preserve accepted closure and clean owned scope; reopen only on a concrete, separately recorded regression. Downstream consumes the frozen contract. | U27: Fresh acceptance DB builder, canonical migration-order consumer/validation, focused builder tests and T-251 rerun orchestration only. No product runtime/API/frontend changes; no mutation of ppiq_app or ppiq_presentation; no broad migration rewrite. | V27: T-260 corrects how the fresh certification DB is constructed; T-251 remains the physical catalogue owner and resumes only on the corrected DB. T-256 later owns genuine runtime/schema compatibility residue that remains after a correct fresh build. | W27: Product Foundation & Release Truth | X27: Created from T-251 runtime evidence on 09-Sep-2026. The catalogue machine is valid, but the designated fresh certification DB is built from an incomplete canonical path, so classifying its current queue would create false governance work. Narrow corrective task; closed T-088 is not reopened. | AA27: L8.1 | AB27: Fresh install and upgrade authority | AC27: L5.7; L8.2 | AD27: Converge | AE27: D3; D4; D5 | AF27: Core | AG27: R1 | AH27: Advances | AI27: =IF(Y27="","",Y27) | AJ27: Inherited baseline estimate | AK27: v4.10.3 | AL27: Chapters 3/4 v4.10.3 — MD + illustrated Word; UI Coverage / UI Controls in this workbook | AM27: =IF(AND(ISNUMBER(J27),OR(AR27="INHERITED ESTIMATE",AR27="CONFIRMED ESTIMATE")),1,0) -> 1 | AO27: Recorded closed — inherited evidence | AP27: Inherited v2.22.0 intended record; no new runtime certification in this repair. | AR27: INHERITED ESTIMATE | AS27: =IF(AM27=1,J27,"") -> 6 | AT27: =IF(AND(AM27=1,ISNUMBER(R27)),R27,"") -> 1.8 | AU27: =IFERROR(INDEX('Source Review'!$B$2:$B$52,MATCH($A27,'Source Review'!$A$2:$A$52,0)),"NOT SOURCE-REVIEWED IN THIS PASS") -> NOT SOURCE-REVIEWED IN THIS PASS | AV27: =IFERROR(INDEX('Source Review'!$F$2:$F$52,MATCH($A27,'Source Review'!$A$2:$A$52,0)),"") | AW27: =IFERROR(INDEX('Source Review'!$G$2:$G$52,MATCH($A27,'Source Review'!$A$2:$A$52,0)),"") | AX27: =IFERROR(INDEX('Source Review'!$H$2:$H$52,MATCH($A27,'Source Review'!$A$2:$A$52,0)),"") | AY27: =IF(COUNTIF('Source Review'!$A$2:$A$52,$A27)>0,"UNCONFIRMED REVIEW ESTIMATE - not P80 or elapsed","NOT ESTIMATED IN THIS PASS") -> NOT ESTIMATED IN THIS PASS | AZ27: =IFERROR(INDEX('Source Review'!$I$2:$I$52,MATCH($A27,'Source Review'!$A$2:$A$52,0)),"") | BA27: =IFERROR(INDEX('Source Review'!$E$2:$E$52,MATCH($A27,'Source Review'!$A$2:$A$52,0)),"") | BB27: =IF(COUNTIF('Source Review'!$A$2:$A$52,$A27)>0,"14-Sep-2026 snapshot; later closure evidence separate; no live HEAD verification","")
A28: T-095 | B28: M2 | C28: P2 | D28: Relationship members, cardinality, grain conversion and preferred paths | E28: Backend | F28: Relationship model | G28: Critical | H28: Extend the M1 slice to the full model in Chapter 3 4.5.10: members, cardinality, grain conversion between related entities, preferred path selection when more than one path exists, and published versions. v2.10.2 CONVERGENCE CORRECTION — T-095 does not merely 'extend' M1 physical tables. It converges the M1 relationship service/compatibility persistence onto the canonical Chapter 3 4.5.10 tables after definition_store exists, including source_definition_id/version, grain conversion, preferred paths, ambiguity/validation state and retirement semantics, while keeping the M1 external contract stable. | I28: Declare two paths between the same pair of entities, mark one preferred, and confirm the resolver chooses it. Change the preference and confirm the resolution changes with no other edit. | J28: 12 | K28: Done | L28: Worker 1 | M28: T-057; T-089; T-090; T-094 | N28: T-096; T-098; T-102; T-103; T-104; T-107; T-109; T-114; T-128; T-134; T-183; T-196; T-221 | O28: M2: ~1 month from owner planning checkpoint; exact date not committed | P28: Release 1 MUST | Q28: Backend/domain contract | R28: 1.8 | S28: M2-P2 | T28: CLOSED BASELINE — no new start gate and no re-execution implied. Preserve accepted closure and clean owned scope; reopen only on a concrete, separately recorded regression. Downstream consumes the frozen contract. | U28: Own canonical DB/backend/security/API/infra. No W2-owned UI/admin task files and no W3 ML/Assistant runtime. | V28: Commit before downstream consumer starts; consumer must use the contract, not redesign producer-owned semantics. | W28: Day-1 Data Workbench — DB Link, Canvas, Jobs & OPC | X28: M2 P2 — Day-1 Data Workbench — DB Link, Canvas, Jobs & OPC. Release 1 is genuine early production / first-week customer work. | Y28: 554d1ac02af122fdeb7ca54b1dd35bac0c76f23e — subject not recovered | Z28: 46272 | AA28: L5.2 | AB28: Permanent relationship model | AD28: Build | AE28: D1; D3; D5 | AF28: Core | AG28: R1 | AH28: Advances | AI28: =IF(Y28="","",Y28) -> 554d1ac02af122fdeb7ca54b1dd35bac0c76f23e — subject not recovered | AJ28: Inherited baseline estimate | AK28: v4.10.3 | AL28: Chapters 3/4 v4.10.3 — MD + illustrated Word; UI Coverage / UI Controls in this workbook | AM28: =IF(AND(ISNUMBER(J28),OR(AR28="INHERITED ESTIMATE",AR28="CONFIRMED ESTIMATE")),1,0) -> 1 | AO28: Recorded closed — inherited evidence | AP28: Inherited v2.22.0 intended record; no new runtime certification in this repair. | AR28: INHERITED ESTIMATE | AS28: =IF(AM28=1,J28,"") -> 12 | AT28: =IF(AND(AM28=1,ISNUMBER(R28)),R28,"") -> 1.8 | AU28: =IFERROR(INDEX('Source Review'!$B$2:$B$52,MATCH($A28,'Source Review'!$A$2:$A$52,0)),"NOT SOURCE-REVIEWED IN THIS PASS") -> SOURCE CORROBORATES CLOSED FOUNDATION | AV28: =IFERROR(INDEX('Source Review'!$F$2:$F$52,MATCH($A28,'Source Review'!$A$2:$A$52,0)),"") -> 0 | AW28: =IFERROR(INDEX('Source Review'!$G$2:$G$52,MATCH($A28,'Source Review'!$A$2:$A$52,0)),"") -> 0 | AX28: =IFERROR(INDEX('Source Review'!$H$2:$H$52,MATCH($A28,'Source Review'!$A$2:$A$52,0)),"") -> 0 | AY28: =IF(COUNTIF('Source Review'!$A$2:$A$52,$A28)>0,"UNCONFIRMED REVIEW ESTIMATE - not P80 or elapsed","NOT ESTIMATED IN THIS PASS") -> UNCONFIRMED REVIEW ESTIMATE - not P80 or elapsed | AZ28: =IFERROR(INDEX('Source Review'!$I$2:$I$52,MATCH($A28,'Source Review'!$A$2:$A$52,0)),"") -> Closed original scope; zero remaining here does not certify downstream Canvas integration. | BA28: =IFERROR(INDEX('Source Review'!$E$2:$E$52,MATCH($A28,'Source Review'!$A$2:$A$52,0)),"") -> Backend/PlantProcess.Application/Relationships/RelationshipService.cs:145-217 — PublishAsync Backend/PlantProcess.Application/Relationships/RelationshipService.cs:218-260 — ValidateDeclaration | BB28: =IF(COUNTIF('Source Review'!$A$2:$A$52,$A28)>0,"14-Sep-2026 snapshot; later closure evidence separate; no live HEAD verification","") -> 14-Sep-2026 snapshot; later closure evidence separate; no live HEAD verification
A29: T-096 | B29: M2 | C29: P2 | D29: Path resolver, part 1: resolver core and the first eight consumers | E29: Backend | F29: Relationship model | G29: Critical | H29: Chapter 2 3.15.4 names sixteen consumers of the relationship model. Build the resolver core, then route the first eight through it: canonical projection, page and widget queries, associative filtering, drill-down, drill-through, genealogy, statistics and correlation. | I29: A regression test per consumer asserting it resolves through the published model, and refuses with a named reason when the relationship is unpublished. Eight tests, no exceptions. | J29: 8 | K29: Done | L29: Worker 1 | M29: T-095 | N29: T-097; T-098; T-107; T-109; T-128; T-134; T-183; T-221 | O29: M2: ~1 month from owner planning checkpoint; exact date not committed | P29: Release 1 MUST | Q29: Backend/domain contract | R29: 1.2 | S29: M2-P2 | T29: CLOSED BASELINE — no new start gate and no re-execution implied. Preserve accepted closure and clean owned scope; reopen only on a concrete, separately recorded regression. Downstream consumes the frozen contract. | U29: Own canonical DB/backend/security/API/infra. No W2-owned UI/admin task files and no W3 ML/Assistant runtime. | V29: Commit before downstream consumer starts; consumer must use the contract, not redesign producer-owned semantics. | W29: Day-1 Data Workbench — DB Link, Canvas, Jobs & OPC | X29: M2 P2 — Day-1 Data Workbench — DB Link, Canvas, Jobs & OPC. Release 1 is genuine early production / first-week customer work. | Y29: de243027073fc5e492d65e9f9845255342517510 — T-096 relationship resolver consumer convergence | Z29: 46273 | AA29: L5.2 | AB29: Permanent relationship model | AD29: Build | AE29: D3; D5 | AF29: Core | AG29: R1 | AH29: Advances | AI29: =IF(Y29="","",Y29) -> de243027073fc5e492d65e9f9845255342517510 — T-096 relationship resolver consumer convergence | AJ29: Inherited baseline estimate | AK29: v4.10.3 | AL29: Chapters 3/4 v4.10.3 — MD + illustrated Word; UI Coverage / UI Controls in this workbook | AM29: =IF(AND(ISNUMBER(J29),OR(AR29="INHERITED ESTIMATE",AR29="CONFIRMED ESTIMATE")),1,0) -> 1 | AO29: Recorded closed — inherited evidence | AP29: Inherited v2.22.0 intended record; no new runtime certification in this repair. | AR29: INHERITED ESTIMATE | AS29: =IF(AM29=1,J29,"") -> 8 | AT29: =IF(AND(AM29=1,ISNUMBER(R29)),R29,"") -> 1.2 | AU29: =IFERROR(INDEX('Source Review'!$B$2:$B$52,MATCH($A29,'Source Review'!$A$2:$A$52,0)),"NOT SOURCE-REVIEWED IN THIS PASS") -> SOURCE CORROBORATES CLOSED FOUNDATION | AV29: =IFERROR(INDEX('Source Review'!$F$2:$F$52,MATCH($A29,'Source Review'!$A$2:$A$52,0)),"") -> 0 | AW29: =IFERROR(INDEX('Source Review'!$G$2:$G$52,MATCH($A29,'Source Review'!$A$2:$A$52,0)),"") -> 0 | AX29: =IFERROR(INDEX('Source Review'!$H$2:$H$52,MATCH($A29,'Source Review'!$A$2:$A$52,0)),"") -> 0 | AY29: =IF(COUNTIF('Source Review'!$A$2:$A$52,$A29)>0,"UNCONFIRMED REVIEW ESTIMATE - not P80 or elapsed","NOT ESTIMATED IN THIS PASS") -> UNCONFIRMED REVIEW ESTIMATE - not P80 or elapsed | AZ29: =IFERROR(INDEX('Source Review'!$I$2:$I$52,MATCH($A29,'Source Review'!$A$2:$A$52,0)),"") -> Original resolver/convergence closure retained; no rebuilding cost. | BA29: =IFERROR(INDEX('Source Review'!$E$2:$E$52,MATCH($A29,'Source Review'!$A$2:$A$52,0)),"") -> Backend/PlantProcess.Application/Relationships/RelationshipResolver.cs:34-113 — ResolveAsync Backend/tests/PlantProcess.Architecture.Tests/RelationshipConsumerBarrierTests.cs:55-96 — ConsumerFamilies | BB29: =IF(COUNTIF('Source Review'!$A$2:$A$52,$A29)>0,"14-Sep-2026 snapshot; later closure evidence separate; no live HEAD verification","") -> 14-Sep-2026 snapshot; later closure evidence separate; no live HEAD verification
A30: T-097 | B30: M2 | C30: P2 | D30: Path resolver, part 2: the remaining eight consumers and the regression suite | E30: Backend | F30: Relationship model | G30: Critical | H30: Route the remaining eight through the resolver: feature engineering, model training, prediction, practice learning, remediation search, value calculation, assistant retrieval and evidence. Some of these are built in Release 2; add the resolver seam now so they cannot be written against an ad-hoc join later. | I30: Eight further regression tests. For consumers whose engine arrives in Release 2, the test asserts the seam exists and refuses when unpublished, which is what stops a later shortcut. | J30: 6 | K30: Done | L30: Worker 1 | M30: T-096 | N30: T-098; T-107; T-109; T-128; T-183 | O30: M2: ~1 month from owner planning checkpoint; exact date not committed | P30: Release 1 MUST | Q30: Backend/domain contract | R30: 0.9 | S30: M2-P2 | T30: CLOSED BASELINE — no new start gate and no re-execution implied. Preserve accepted closure and clean owned scope; reopen only on a concrete, separately recorded regression. Downstream consumes the frozen contract. | U30: Own canonical DB/backend/security/API/infra. No W2-owned UI/admin task files and no W3 ML/Assistant runtime. | V30: Commit before downstream consumer starts; consumer must use the contract, not redesign producer-owned semantics. | W30: Day-1 Data Workbench — DB Link, Canvas, Jobs & OPC | X30: M2 P2 — Day-1 Data Workbench — DB Link, Canvas, Jobs & OPC. Release 1 is genuine early production / first-week customer work. | Y30: 95220d1804493f8e7b80347fe3ed4de24741f9ec — T-097 relationship consumer barrier across all sixteen families | Z30: 46273 | AA30: L5.2 | AB30: Permanent relationship model | AD30: Build | AE30: D3; D5 | AF30: Core | AG30: R1 | AH30: Advances | AI30: =IF(Y30="","",Y30) -> 95220d1804493f8e7b80347fe3ed4de24741f9ec — T-097 relationship consumer barrier across all sixteen families | AJ30: Inherited baseline estimate | AK30: v4.10.3 | AL30: Chapters 3/4 v4.10.3 — MD + illustrated Word; UI Coverage / UI Controls in this workbook | AM30: =IF(AND(ISNUMBER(J30),OR(AR30="INHERITED ESTIMATE",AR30="CONFIRMED ESTIMATE")),1,0) -> 1 | AO30: Recorded closed — inherited evidence | AP30: Inherited v2.22.0 intended record; no new runtime certification in this repair. | AR30: INHERITED ESTIMATE | AS30: =IF(AM30=1,J30,"") -> 6 | AT30: =IF(AND(AM30=1,ISNUMBER(R30)),R30,"") -> 0.9 | AU30: =IFERROR(INDEX('Source Review'!$B$2:$B$52,MATCH($A30,'Source Review'!$A$2:$A$52,0)),"NOT SOURCE-REVIEWED IN THIS PASS") -> SOURCE CORROBORATES CLOSED GUARD | AV30: =IFERROR(INDEX('Source Review'!$F$2:$F$52,MATCH($A30,'Source Review'!$A$2:$A$52,0)),"") -> 0 | AW30: =IFERROR(INDEX('Source Review'!$G$2:$G$52,MATCH($A30,'Source Review'!$A$2:$A$52,0)),"") -> 0 | AX30: =IFERROR(INDEX('Source Review'!$H$2:$H$52,MATCH($A30,'Source Review'!$A$2:$A$52,0)),"") -> 0 | AY30: =IF(COUNTIF('Source Review'!$A$2:$A$52,$A30)>0,"UNCONFIRMED REVIEW ESTIMATE - not P80 or elapsed","NOT ESTIMATED IN THIS PASS") -> UNCONFIRMED REVIEW ESTIMATE - not P80 or elapsed | AZ30: =IFERROR(INDEX('Source Review'!$I$2:$I$52,MATCH($A30,'Source Review'!$A$2:$A$52,0)),"") -> No remaining original implementation; avoid counting unwired later engines against this completed guard. | BA30: =IFERROR(INDEX('Source Review'!$E$2:$E$52,MATCH($A30,'Source Review'!$A$2:$A$52,0)),"") -> Backend/tests/PlantProcess.Architecture.Tests/RelationshipConsumerBarrierTests.cs:12-44 — barrier semantics Backend/tests/PlantProcess.Architecture.Tests/RelationshipConsumerBarrierTests.cs:55-114 — consumer and forbidden-authority inventory | BB30: =IF(COUNTIF('Source Review'!$A$2:$A$52,$A30)>0,"14-Sep-2026 snapshot; later closure evidence separate; no live HEAD verification","") -> 14-Sep-2026 snapshot; later closure evidence separate; no live HEAD verification
A31: T-098 | B31: M2 | C31: P2 | D31: Relationship Browser page and path evidence | E31: Frontend | F31: Relationship model | G31: Very Important | H31: Build the C6 Relationship Browser from Chapter 3 4.4 with the ten-field page contract, showing declared relationships, their members, their paths and the evidence for each path. v2.10.2 CONTINUITY CORRECTION — complete the existing T-060 /relationships page in place. Do not create a second C6 surface. Preserve the route, layout and M1 control contract while replacing/extending the hidden relationship authority and path evidence. | I31: Open a relationship and confirm its members, cardinality and path are shown with evidence. Confirm an unpublished relationship is visibly distinct from a published one. Run the M1 C6 continuity snapshot before/after canonical cutover and prove no visible-contract regression. | J31: 12 | K31: Not Started | L31: Worker 2 | M31: T-095; T-096; T-097 | N31: T-107; T-109; T-128; T-183 | O31: M2: ~1 month from owner planning checkpoint; exact date not committed | P31: Release 1 MUST | Q31: Frontend/UI feature | R31: 2 | S31: M2-P2 | T31: Use the accepted M1 regression baseline; require empty index and clean owned paths, preserving unrelated user work. Then: T-060 M1 C6 surface + T-095 + T-096 + T-097. | U31: Own named UI/admin task end-to-end only after producer APIs/security are committed. | V31: Commit before downstream consumer starts; consumer must use the contract, not redesign producer-owned semantics. | W31: Day-1 Data Workbench — DB Link, Canvas, Jobs & OPC | X31: M2 P2 — Day-1 Data Workbench — DB Link, Canvas, Jobs & OPC. Release 1 is genuine early production / first-week customer work. | AA31: L5.2 | AB31: Permanent relationship model | AD31: Build | AE31: D1; D2; D5 | AF31: Core | AG31: R1 | AH31: Advances | AI31: =IF(Y31="","",Y31) | AJ31: Inherited baseline estimate | AK31: v4.10.3 | AL31: Chapters 3/4 v4.10.3 — MD + illustrated Word; UI Coverage / UI Controls in this workbook v2.23.0 — Use T-265 C6 relationship list/detail/member/cardinality/path-validation handoffs. Trace every applicable Chapter 3 control to a reachable UI variant and keep resolver behavior under its existing authority. | AM31: =IF(AND(ISNUMBER(J31),OR(AR31="INHERITED ESTIMATE",AR31="CONFIRMED ESTIMATE")),1,0) -> 1 | AO31: Not started — no completion claimed | AP31: Inherited v2.22.0 intended record; no new runtime certification in this repair. | AR31: INHERITED ESTIMATE | AS31: =IF(AM31=1,J31,"") -> 12 | AT31: =IF(AND(AM31=1,ISNUMBER(R31)),R31,"") -> 2 | AU31: =IFERROR(INDEX('Source Review'!$B$2:$B$52,MATCH($A31,'Source Review'!$A$2:$A$52,0)),"NOT SOURCE-REVIEWED IN THIS PASS") -> REUSABLE BACKEND PRESENT; CANONICAL UI NOT LOCATED | AV31: =IFERROR(INDEX('Source Review'!$F$2:$F$52,MATCH($A31,'Source Review'!$A$2:$A$52,0)),"") -> 6 | AW31: =IFERROR(INDEX('Source Review'!$G$2:$G$52,MATCH($A31,'Source Review'!$A$2:$A$52,0)),"") -> 9 | AX31: =IFERROR(INDEX('Source Review'!$H$2:$H$52,MATCH($A31,'Source Review'!$A$2:$A$52,0)),"") -> 14 | AY31: =IF(COUNTIF('Source Review'!$A$2:$A$52,$A31)>0,"UNCONFIRMED REVIEW ESTIMATE - not P80 or elapsed","NOT ESTIMATED IN THIS PASS") -> UNCONFIRMED REVIEW ESTIMATE - not P80 or elapsed | AZ31: =IFERROR(INDEX('Source Review'!$I$2:$I$52,MATCH($A31,'Source Review'!$A$2:$A$52,0)),"") -> UI 4/6/9 + contract/negative tests 1/2/3 + targeted closure 1/1/2. Reuse all relationship producer work. | BA31: =IFERROR(INDEX('Source Review'!$E$2:$E$52,MATCH($A31,'Source Review'!$A$2:$A$52,0)),"") -> Backend/PlantProcess.Api/Endpoints/Relationships/RelationshipEndpoints.cs:21-92 — MapRelationshipEndpoints Backend/PlantProcess.Application/Relationships/RelationshipResolver.cs:62-113 — path results | BB31: =IF(COUNTIF('Source Review'!$A$2:$A$52,$A31)>0,"14-Sep-2026 snapshot; later closure evidence separate; no live HEAD verification","") -> 14-Sep-2026 snapshot; later closure evidence separate; no live HEAD verification
A32: T-099 | B32: M2 | C32: P2 | D32: Quarantine, part 1: the table, the reprocess API and the first eight PV classes | E32: Backend | F32: Quarantine | G32: Critical | H32: Chapter 3 4.5.14 specifies quarantine with fifteen typed PV codes. A repository search for projection_quarantine returns zero hits, so this does not exist. Build the table with its columns, the reprocess endpoint, and the first eight validation classes so a bad row is quarantined under a named code instead of corrupting the canonical layer or failing the whole batch. | I32: Craft one malformed input per implemented class and assert each is quarantined under the correct code, while the good rows in the same batch still project. | J32: 8 | K32: Done | L32: Worker 1 | M32: T-087; T-089; T-090 | N32: T-100; T-101; T-104; T-107; T-108; T-109; T-114; T-128; T-183; T-261 | O32: M2: ~1 month from owner planning checkpoint; exact date not committed | P32: Release 1 MUST | Q32: Backend/domain contract | R32: 1.2 | S32: M2-P2 | T32: CLOSED BASELINE — no new start gate and no re-execution implied. Preserve accepted closure and clean owned scope; reopen only on a concrete, separately recorded regression. Downstream consumes the frozen contract. | U32: Own canonical DB/backend/security/API/infra. No W2-owned UI/admin task files and no W3 ML/Assistant runtime. | V32: Commit before downstream consumer starts; consumer must use the contract, not redesign producer-owned semantics. | W32: Day-1 Data Workbench — DB Link, Canvas, Jobs & OPC | X32: M2 P2 — Day-1 Data Workbench — DB Link, Canvas, Jobs & OPC. Release 1 is genuine early production / first-week customer work. v2.22.1 — CLOSED GREEN / COMMITTED at ca02b40ea1b69050a45cb35a3e1d64f15b1f66af (parent 86e1b677212195f191697ecdca7e9441b3dbde33). Preserve this closure unless a concrete later regression is demonstrated. Gate O has one exact inherited DefinitionKind RED and canonical replay limitations remain; this is not Release-wide GREEN. | Y32: ca02b40ea1b69050a45cb35a3e1d64f15b1f66af | AA32: L2.3 | AB32: Canonical projection with validation, quarantine and reprocessing | AD32: Build | AE32: D3; D4; D5 | AF32: Core | AG32: R1 | AH32: Advances | AI32: =IF(Y32="","",Y32) -> ca02b40ea1b69050a45cb35a3e1d64f15b1f66af | AJ32: Inherited baseline estimate | AK32: v4.10.3 | AL32: Chapters 3/4 v4.10.3 — MD + illustrated Word; UI Coverage / UI Controls in this workbook | AM32: =IF(AND(ISNUMBER(J32),OR(AR32="INHERITED ESTIMATE",AR32="CONFIRMED ESTIMATE")),1,0) -> 1 | AO32: CLOSED GREEN / COMMITTED — FINAL TRANSCRIPT CORROBORATED | AP32: Final executed terminal transcript corroborates the owner-reported closure: 49/49 live,5/5 catalogue,19/19 owned;6/6 disposable DBs dropped;0survivors. GateO900=899passed+1exact inheritedDefinitionKindRED. Exact staging and one semantic commit proven. No live rerun performed in this review; no release-wideGREEN. Pasted text(20260914-134548).txt | lines430-450; final gatesQ/R; COMMITca02b40ea1b69050a45cb35a3e1d64f15b1f66af; PARENT86e1b677212195f191697ecdca7e9441b3dbde33; live49/49, catalogue5/5, owned19/19; not release-wideGREEN. | AQ32: 86e1b677212195f191697ecdca7e9441b3dbde33 | AR32: INHERITED ESTIMATE | AS32: =IF(AM32=1,J32,"") -> 8 | AT32: =IF(AND(AM32=1,ISNUMBER(R32)),R32,"") -> 1.2 | AU32: =IFERROR(INDEX('Source Review'!$B$2:$B$52,MATCH($A32,'Source Review'!$A$2:$A$52,0)),"NOT SOURCE-REVIEWED IN THIS PASS") -> CLOSED SCOPE PRESERVED; SOURCE CORROBORATES | AV32: =IFERROR(INDEX('Source Review'!$F$2:$F$52,MATCH($A32,'Source Review'!$A$2:$A$52,0)),"") -> 0 | AW32: =IFERROR(INDEX('Source Review'!$G$2:$G$52,MATCH($A32,'Source Review'!$A$2:$A$52,0)),"") -> 0 | AX32: =IFERROR(INDEX('Source Review'!$H$2:$H$52,MATCH($A32,'Source Review'!$A$2:$A$52,0)),"") -> 0 | AY32: =IF(COUNTIF('Source Review'!$A$2:$A$52,$A32)>0,"UNCONFIRMED REVIEW ESTIMATE - not P80 or elapsed","NOT ESTIMATED IN THIS PASS") -> UNCONFIRMED REVIEW ESTIMATE - not P80 or elapsed | AZ32: =IFERROR(INDEX('Source Review'!$I$2:$I$52,MATCH($A32,'Source Review'!$A$2:$A$52,0)),"") -> T-099 CLOSED GREEN at ca02b40e; its inherited DefinitionKind RED is not a reason to budget a rewrite. | BA32: =IFERROR(INDEX('Source Review'!$E$2:$E$52,MATCH($A32,'Source Review'!$A$2:$A$52,0)),"") -> Backend/PlantProcess.Application/Integration/Services/Mapping/MappingRowProjector.cs:141-181 — MapMaterialUnitAsync Backend/PlantProcess.Api/Endpoints/Quarantine/QuarantineEndpoints.cs:8-33 — bounded reprocess surface Backend/database/scripts/841_genealogy_edge_weight_guard_topology_parity.sql:3-20 — narrow topology correction | BB32: =IF(COUNTIF('Source Review'!$A$2:$A$52,$A32)>0,"14-Sep-2026 snapshot; later closure evidence separate; no live HEAD verification","") -> 14-Sep-2026 snapshot; later closure evidence separate; no live HEAD verification
A33: T-100 | B33: M2 | C33: P2 | D33: Quarantine, part 2: the remaining seven PV classes and per-class tests | E33: Backend | F33: Quarantine | G33: Critical | H33: Implement the remaining seven validation classes and give every class its own test fixture, so the class set is provably complete against Chapter 3 4.5.14 rather than approximately complete. | I33: Distinct governed validation codes and fixture coverage must equal PV01..PV15 exactly. At least 15 classification fixtures; additional regression fixtures for an existing code are allowed. The completeness ratchet fails for an unproved enum member, not for duplicate display names or extra same-code tests. Live PostgreSQL proof executes every PV class; PV15 quarantine→cross-batch reference arrival→bounded reprocess passes; PV13 .60+.40=1.00 must not be quarantined. Exact live constraint, canonical migration order, disposable cleanup and exact single-commit closure required. | J33: 6 | K33: Done | L33: Worker 1 | M33: T-099 | N33: T-101; T-107; T-109; T-128; T-183; T-261 | O33: M2: ~1 month from owner planning checkpoint; exact date not committed | P33: Release 1 MUST | Q33: Backend/domain contract | R33: 0.9 | S33: M2-P2 | T33: RUNNER-1 CANDIDATE IS PRESENT; DO NOT RERUN RUNNER 1 or require a clean owned tree relative to HEAD. Resume from the exact handoff/postimages. Resume v1.0.1 is issued; success is not yet reported. Validate HEAD against the handoff and all owned postimage hashes before continuing. Expected parent supplied for closure is 4e0f1219ddbac3163bafe7ce510b62520683a77c; do not substitute the older T-099-only HEAD. If the exact gates fail, stop and report without manual resets, cleanup of unrelated work, or a fresh mutation pack. Worker 1/CENTRAL retains the execution lock through T-100 final commit; Worker 2 remains held. | U33: Worker 1 is the recorded execution owner; CENTRAL-assisted delivery. Preserve the existing T-100 candidate and unrelated dirty work. Exclusive shared repository mutation lock until T-100 is committed. | V33: Release Worker 2 only after T-100 final commit SHA and closure evidence. The successor consumes PROJECTION_* declaration, PV01..PV15 row-validation and JOB_EXEC_* runtime boundaries without duplication. | W33: Day-1 Data Workbench — DB Link, Canvas, Jobs & OPC | X33: M2 P2 — Day-1 Data Workbench — DB Link, Canvas, Jobs & OPC. Release 1 is genuine early production / first-week customer work. | AA33: L2.3 | AB33: Canonical projection with validation, quarantine and reprocessing | AD33: Build | AE33: D3; D5 | AF33: Core | AG33: R1 | AH33: Advances | AI33: =IF(Y33="","",Y33) | AJ33: SUPERSEDED: prior remaining LOW/BASE/HIGH 6/10/16 h included validators and unit tests now reported complete. Do not charge that implementation again. Closure-only remaining effort (harness recovery, live certification, cleanup, commit proof) is UNCONFIRMED, not zero; no invented elapsed time or calibrated P80. Preserve J/R as historical scope values, excluded from usable totals. | AK33: v4.10.3 | AL33: Chapters 3/4 v4.10.3 — MD + illustrated Word; UI Coverage / UI Controls in this workbook | AM33: =IF(AND(ISNUMBER(J33),OR(AR33="INHERITED ESTIMATE",AR33="CONFIRMED ESTIMATE")),1,0) -> 0 | AO33: RUNNER 1 GREEN REPORTED / DB BUILD PASSED / LIVE HARNESS BLOCKED / UNCOMMITTED | AP33: Latest owner-supplied conversation update, received 15-Sep-2026; runner/host logs and script bytes were not independently inspected in this workbook update. This supersedes the earlier 14-Sep source-only T-100 estimate, not the frozen Design. Reported Runner 1 v1.0.5 completed: Backend build GREEN, integration-project build GREEN, 20/20 targeted unit tests, PPIQ_T100_RUNNER1_HANDOFF.json written; no staging, commit or DB mutation in Runner 1. Later certification reportedly executed 110/110 canonical SQL scripts, built a fresh disposable DB with 264 tables, and verified the constraint is exactly PV01..PV15. That run failed in harness setup BEFORE live classification; its disposable certification DB was cleaned up. No T-100 commit or live PV01..PV15 pass has been supplied. USER-REPORTED: Runner1_1.0.5 SHA256 75B6C7DE78E0A677701BFEDF1EC70D4D1499C8168193B35D503CF26DF76DC7AA; Runner2_1.0.0 SHA256 9C29E607B52114DE680131A0FDE0F840D7CC56D3642FA09F73FD2AB5A7B3D493; Resume-ProjectionQuarantineCompletion_1.0.1.ps1 SHA256 5F6668258E8CAC517793B825AF712C8D8C9355F8CE9C0C69FBC5CAFCBDCB80E6. Names/hashes recorded as supplied, NOT locally verified. Script hashes are not commit IDs. Expected Runner-2 parent (not an observed commit parent): 4e0f1219ddbac3163bafe7ce510b62520683a77c | AR33: RE-ESTIMATE REQUIRED | AS33: =IF(AM33=1,J33,"") | AT33: =IF(AND(AM33=1,ISNUMBER(R33)),R33,"") | AU33: =IFERROR(INDEX('Source Review'!$B$2:$B$52,MATCH($A33,'Source Review'!$A$2:$A$52,0)),"NOT SOURCE-REVIEWED IN THIS PASS") -> RUNNER 1 GREEN REPORTED / DB BUILD PASSED / LIVE HARNESS BLOCKED / UNCOMMITTED | AV33: =IFERROR(INDEX('Source Review'!$F$2:$F$52,MATCH($A33,'Source Review'!$A$2:$A$52,0)),"") -> UNCONFIRMED | AW33: =IFERROR(INDEX('Source Review'!$G$2:$G$52,MATCH($A33,'Source Review'!$A$2:$A$52,0)),"") -> UNCONFIRMED | AX33: =IFERROR(INDEX('Source Review'!$H$2:$H$52,MATCH($A33,'Source Review'!$A$2:$A$52,0)),"") -> UNCONFIRMED | AY33: UNCONFIRMED — closure-only remaining effort; prior 6/10/16 h superseded | AZ33: =IFERROR(INDEX('Source Review'!$I$2:$I$52,MATCH($A33,'Source Review'!$A$2:$A$52,0)),"") -> SUPERSEDED: prior remaining LOW/BASE/HIGH 6/10/16 h included validators and unit tests now reported complete. Do not charge that implementation again. Closure-only remaining effort (harness recovery, live certification, cleanup, commit proof) is UNCONFIRMED, not zero; no invented elapsed time or calibrated P80. Preserve J/R as historical scope values, excluded from usable totals. | BA33: =IFERROR(INDEX('Source Review'!$E$2:$E$52,MATCH($A33,'Source Review'!$A$2:$A$52,0)),"") -> Backend/PlantProcess.Api/Endpoints/Quarantine/QuarantineEndpoints.cs:8-13 — ownership Backend/PlantProcess.Application/Integration/Services/Mapping/MappingRowProjector.cs:630-690 — existing validation pattern Latest owner-supplied conversation update, received 15-Sep-2026; runner/host logs and script bytes were not independently inspected in this workbook update. This supersedes the earlier 14-Sep source-only T-100 estimate, not the frozen Design. USER-REPORTED: Runner1_1.0.5 SHA256 75B6C7DE78E0A677701BFEDF1EC70D4D1499C8168193B35D503CF26DF76DC7AA; Runner2_1.0.0 SHA256 9C29E607B52114DE680131A0FDE0F840D7CC56D3642FA09F73FD2AB5A7B3D493; Resume-ProjectionQuarantineCompletion_1.0.1.ps1 SHA256 5F6668258E8CAC517793B825AF712C8D8C9355F8CE9C0C69FBC5CAFCBDCB80E6. Names/hashes recorded as supplied, NOT locally verified. Script hashes are not commit IDs. | BB33: 14-Sep snapshot supplemented by latest 15-Sep user-reported runner progress; no current-HEAD or runner-byte verification
A34: T-101 | B34: M2 | C34: P2 | D34: Quarantine retry, reprocess and Mapping Health completion | E34: Frontend | F34: Quarantine | G34: Very Important | H34: Complete the C2 Mapping Health page against Chapter 3 4.4 C2: issues grouped by code, example rows, and Reprocess after the mapping is corrected. The M1 version delivered the shape; this delivers the full class set and the retry semantics. v2.22.0 — Quarantine inspection API/UI and schema-drift enforcement. Keep one drift event authority and reuse current schemas/compatibility safely. v2.22.1 — Own the M2 B4 Importing monitoring surface as well as C2 quarantine/Mapping Health: show each real batch status, failure code/reason, progress/counts, last committed cursor and its watermark range; drill into durable batch/run evidence. Use the existing canonical import/job contracts. T-106 owns terminal-status truth; T-108 owns durable cursor/replay; T-125 owns operational metrics/API observability. No second status or cursor authority and no advanced M3 recovery UI is introduced. | I34: Quarantine rows under three different codes, correct one mapping, reprocess, and confirm only the affected rows clear. The M1 continuity snapshot of this page must still match. v2.22.0 — GET quarantine list/detail filtered by code, dataset and batch with staging lineage/correction hint; tenant denial; remove mapped source object/field -> typed execution refusal and persisted C2 event; corrected reprocess uses declared version and records outcome. v2.22.1 — Drive B4 against a successful batch, a failed batch and a capped/partial batch; displayed outcome, counts, error and last committed cursor equal the canonical response after reload. A failed batch is never green; a retry/correction links to the same durable evidence. Tenant denial and empty/loading/failure states are asserted. Consume frozen T-106/T-108/T-125 response contracts for parallel UI work; final live integration is certified by T-247/T-150, not by a mock-only result. | J34: 12 | K34: Not Started | L34: Worker 2 | M34: T-099; T-100 | N34: T-107; T-109; T-128; T-183 | O34: M2: ~1 month from owner planning checkpoint; exact date not committed | P34: Release 1 MUST | Q34: Frontend/UI feature | R34: 2 | S34: M2-P2 | T34: GATE PROSE INCOMPLETE — original text ends with an ellipsis. Do not infer omitted conditions. Column M lists completion prerequisites; AN/Contract Handoffs lists contract-only prerequisites. Full task acceptance in column I still applies. Recover the omitted prose before claiming this gate fully reconciled. Preserved original fragment: Use the accepted M1 regression baseline; require empty index and clean owned paths, preserving unrelated user work. Then: T-061 final M1 API/page contract + T-099 + T-100 canonical quarantine impleme... | U34: Own named UI/admin task end-to-end only after producer APIs/security are committed. | V34: Commit before downstream consumer starts; consumer must use the contract, not redesign producer-owned semantics. | W34: Day-1 Data Workbench — DB Link, Canvas, Jobs & OPC | X34: M2 P2 — Day-1 Data Workbench — DB Link, Canvas, Jobs & OPC. Release 1 is genuine early production / first-week customer work. | AA34: L2.3 | AB34: Canonical projection with validation, quarantine and reprocessing | AC34: L1.6; L1.2; L1.7 | AD34: Build | AE34: D2; D5 | AF34: Core | AG34: R1 | AH34: Advances | AI34: =IF(Y34="","",Y34) | AJ34: RE-ESTIMATE REQUIRED — J/R retain the prior-scope figures for traceability; excluded from usable planning totals. New full-scope and remaining-work estimates are not supplied. | AK34: v4.10.3 | AL34: Chapters 3/4 v4.10.3 — MD + illustrated Word; UI Coverage / UI Controls in this workbook v2.23.0 — T-265 owns B4/C2/C3 visual depth. Implement its applicable batch outcome/error/committed cursor and catalogue-driven quarantine list/detail/refusal/reprocess states under the existing T-101 scope; all row actions and counts use canonical tenant-scoped payloads. Do not limit the renderer to eight PV codes. | AM34: =IF(AND(ISNUMBER(J34),OR(AR34="INHERITED ESTIMATE",AR34="CONFIRMED ESTIMATE")),1,0) -> 0 | AO34: Not started — no completion claimed | AP34: Inherited v2.22.0 intended record; no new runtime certification in this repair. | AR34: RE-ESTIMATE REQUIRED | AS34: =IF(AM34=1,J34,"") | AT34: =IF(AND(AM34=1,ISNUMBER(R34)),R34,"") | AU34: =IFERROR(INDEX('Source Review'!$B$2:$B$52,MATCH($A34,'Source Review'!$A$2:$A$52,0)),"NOT SOURCE-REVIEWED IN THIS PASS") -> PARTIAL REUSE; CURRENT EXPANDED SCOPE OPEN | AV34: =IFERROR(INDEX('Source Review'!$F$2:$F$52,MATCH($A34,'Source Review'!$A$2:$A$52,0)),"") -> 12 | AW34: =IFERROR(INDEX('Source Review'!$G$2:$G$52,MATCH($A34,'Source Review'!$A$2:$A$52,0)),"") -> 18 | AX34: =IFERROR(INDEX('Source Review'!$H$2:$H$52,MATCH($A34,'Source Review'!$A$2:$A$52,0)),"") -> 28 | AY34: =IF(COUNTIF('Source Review'!$A$2:$A$52,$A34)>0,"UNCONFIRMED REVIEW ESTIMATE - not P80 or elapsed","NOT ESTIMATED IN THIS PASS") -> UNCONFIRMED REVIEW ESTIMATE - not P80 or elapsed | AZ34: =IFERROR(INDEX('Source Review'!$I$2:$I$52,MATCH($A34,'Source Review'!$A$2:$A$52,0)),"") -> Read API/filter/detail 3/4/6 + B4/C2/C3 UI 4/6/10 + drift/retry integration 3/5/8 + tests/closure 2/3/4. | BA34: =IFERROR(INDEX('Source Review'!$E$2:$E$52,MATCH($A34,'Source Review'!$A$2:$A$52,0)),"") -> Backend/PlantProcess.Api/Endpoints/Quarantine/QuarantineEndpoints.cs:8-33 — MapQuarantineEndpoints Backend/PlantProcess.Application/Integration/Services/Staging/StagingRecordService.cs:85-110 — durable staging identity | BB34: =IF(COUNTIF('Source Review'!$A$2:$A$52,$A34)>0,"14-Sep-2026 snapshot; later closure evidence separate; no live HEAD verification","") -> 14-Sep-2026 snapshot; later closure evidence separate; no live HEAD verification
A35: T-102 | B35: M2 | C35: P2 | D35: Identity resolution across sources | E35: Backend | F35: Genealogy | G35: Very Important | H35: Harden material identity resolution using material_aliases so the same physical material arriving under two different source identifiers becomes one canonical unit. The schema already supports this: material_units carries a unique key on (site_id, material_code) plus a filtered unique on (source_system, source_record_id), which makes projection idempotent without forbidding rows that have no source identity. | I35: Import the same material under two different source identifiers and confirm one canonical unit results with both aliases recorded. Re-run the import and confirm no duplicate appears. | J35: 8 | K35: Not Started | L35: Worker 1 | M35: T-087; T-095 | N35: T-103; T-107; T-109; T-128; T-183 | O35: M2: ~1 month from owner planning checkpoint; exact date not committed | P35: Release 1 MUST | Q35: Backend/domain contract | R35: 1.2 | S35: M2-P2 | T35: Use the accepted M1 regression baseline; require empty index and clean owned paths, preserving unrelated user work. Then: T-087 canonical plant schema + T-095 relationship/material identity authority. | U35: Own canonical DB/backend/security/API/infra. No W2-owned UI/admin task files and no W3 ML/Assistant runtime. | V35: Commit before downstream consumer starts; consumer must use the contract, not redesign producer-owned semantics. | W35: Day-1 Data Workbench — DB Link, Canvas, Jobs & OPC | X35: M2 P2 — Day-1 Data Workbench — DB Link, Canvas, Jobs & OPC. Release 1 is genuine early production / first-week customer work. | AA35: L2.4 | AB35: Genealogy resolution and attribution | AD35: Build | AE35: D3; D5 | AF35: Core | AG35: R1 | AH35: Advances | AI35: =IF(Y35="","",Y35) | AJ35: Inherited baseline estimate | AK35: v4.10.3 | AL35: Chapters 3/4 v4.10.3 — MD + illustrated Word; UI Coverage / UI Controls in this workbook | AM35: =IF(AND(ISNUMBER(J35),OR(AR35="INHERITED ESTIMATE",AR35="CONFIRMED ESTIMATE")),1,0) -> 1 | AO35: Not started — no completion claimed | AP35: Inherited v2.22.0 intended record; no new runtime certification in this repair. | AR35: INHERITED ESTIMATE | AS35: =IF(AM35=1,J35,"") -> 8 | AT35: =IF(AND(AM35=1,ISNUMBER(R35)),R35,"") -> 1.2 | AU35: =IFERROR(INDEX('Source Review'!$B$2:$B$52,MATCH($A35,'Source Review'!$A$2:$A$52,0)),"NOT SOURCE-REVIEWED IN THIS PASS") -> EXISTING ALIAS FOUNDATION; IDENTITY-SAFETY GAP | AV35: =IFERROR(INDEX('Source Review'!$F$2:$F$52,MATCH($A35,'Source Review'!$A$2:$A$52,0)),"") -> 4 | AW35: =IFERROR(INDEX('Source Review'!$G$2:$G$52,MATCH($A35,'Source Review'!$A$2:$A$52,0)),"") -> 7 | AX35: =IFERROR(INDEX('Source Review'!$H$2:$H$52,MATCH($A35,'Source Review'!$A$2:$A$52,0)),"") -> 12 | AY35: =IF(COUNTIF('Source Review'!$A$2:$A$52,$A35)>0,"UNCONFIRMED REVIEW ESTIMATE - not P80 or elapsed","NOT ESTIMATED IN THIS PASS") -> UNCONFIRMED REVIEW ESTIMATE - not P80 or elapsed | AZ35: =IFERROR(INDEX('Source Review'!$I$2:$I$52,MATCH($A35,'Source Review'!$A$2:$A$52,0)),"") -> Scope-safe lookup/merge 2/4/7 + ambiguity/idempotency tests 1/2/4 + closure 1/1/1. | BA35: =IFERROR(INDEX('Source Review'!$E$2:$E$52,MATCH($A35,'Source Review'!$A$2:$A$52,0)),"") -> Backend/PlantProcess.Application/Integration/Services/Mapping/MappingRowProjector.cs:244-264 — MapMaterialAliasAsync Backend/PlantProcess.Application/Integration/Services/Mapping/MappingRowProjector.cs:721-744 — ResolveMaterialIdAsync Backend/PlantProcess.Infrastructure/Persistence/Configurations/Materials/MaterialAliasConfiguration.cs:27-36 — composite unique Backend/PlantProcess.Infrastructure/Persistence/Configurations/Materials/MaterialUnitConfiguration.cs:43-47 — site/source uniqueness | BB35: =IF(COUNTIF('Source Review'!$A$2:$A$52,$A35)>0,"14-Sep-2026 snapshot; later closure evidence separate; no live HEAD verification","") -> 14-Sep-2026 snapshot; later closure evidence separate; no live HEAD verification
A36: T-103 | B36: M2 | C36: P2 | D36: Genealogy bidirectional walk hardening and weight proof | E36: Backend | F36: Genealogy | G36: Very Important | H36: Confirm the genealogy layer walks both directions on the customer's own keys and that attribution weights are enforced to sum to exactly 1.0 per child by the database trigger on genealogy_edges.contribution_weight numeric(9,6). v2.22.0 — Retain genealogy semantics and add explicit cyclic/self-edge protection at service and database boundaries. | I36: Walk a chain backward and forward and confirm the same edges are traversed. Attempt an insert whose weights sum to 0.99 inside a transaction and confirm the trigger rejects it, then roll back. v2.22.0 — Negative controls: self-edge, two-node and longer cycles refused; ordered weighted genealogy valid paths remain accepted; no silent deletion of lineage. | J36: 6 | K36: Not Started | L36: Worker 1 | M36: T-095; T-102 | N36: T-107; T-109; T-128; T-183 | O36: M2: ~1 month from owner planning checkpoint; exact date not committed | P36: Release 1 MUST | Q36: Backend/domain contract | R36: 0.9 | S36: M2-P2 | T36: Use the accepted M1 regression baseline; require empty index and clean owned paths, preserving unrelated user work. Then: T-095 + T-102 canonical relationship/identity authority. | U36: Own canonical DB/backend/security/API/infra. No W2-owned UI/admin task files and no W3 ML/Assistant runtime. | V36: Commit before downstream consumer starts; consumer must use the contract, not redesign producer-owned semantics. | W36: Day-1 Data Workbench — DB Link, Canvas, Jobs & OPC | X36: M2 P2 — Day-1 Data Workbench — DB Link, Canvas, Jobs & OPC. Release 1 is genuine early production / first-week customer work. | AA36: L2.4 | AB36: Genealogy resolution and attribution | AD36: Harden | AE36: D3; D5 | AF36: Core | AG36: R1 | AH36: Advances | AI36: =IF(Y36="","",Y36) | AJ36: RE-ESTIMATE REQUIRED — J/R retain the prior-scope figures for traceability; excluded from usable planning totals. New full-scope and remaining-work estimates are not supplied. | AK36: v4.10.3 | AL36: Chapters 3/4 v4.10.3 — MD + illustrated Word; UI Coverage / UI Controls in this workbook | AM36: =IF(AND(ISNUMBER(J36),OR(AR36="INHERITED ESTIMATE",AR36="CONFIRMED ESTIMATE")),1,0) -> 0 | AO36: Not started — no completion claimed | AP36: Inherited v2.22.0 intended record; no new runtime certification in this repair. | AR36: RE-ESTIMATE REQUIRED | AS36: =IF(AM36=1,J36,"") | AT36: =IF(AND(AM36=1,ISNUMBER(R36)),R36,"") | AU36: =IFERROR(INDEX('Source Review'!$B$2:$B$52,MATCH($A36,'Source Review'!$A$2:$A$52,0)),"NOT SOURCE-REVIEWED IN THIS PASS") -> SUBSTANTIAL FOUNDATION; ACCEPTANCE-CONTRACT MISMATCH | AV36: =IFERROR(INDEX('Source Review'!$F$2:$F$52,MATCH($A36,'Source Review'!$A$2:$A$52,0)),"") -> 4 | AW36: =IFERROR(INDEX('Source Review'!$G$2:$G$52,MATCH($A36,'Source Review'!$A$2:$A$52,0)),"") -> 6 | AX36: =IFERROR(INDEX('Source Review'!$H$2:$H$52,MATCH($A36,'Source Review'!$A$2:$A$52,0)),"") -> 10 | AY36: =IF(COUNTIF('Source Review'!$A$2:$A$52,$A36)>0,"UNCONFIRMED REVIEW ESTIMATE - not P80 or elapsed","NOT ESTIMATED IN THIS PASS") -> UNCONFIRMED REVIEW ESTIMATE - not P80 or elapsed | AZ36: =IFERROR(INDEX('Source Review'!$I$2:$I$52,MATCH($A36,'Source Review'!$A$2:$A$52,0)),"") -> Weight-contract correction 1/2/3 + direct-DB/traversal negatives 2/3/5 + closure 1/1/2. Existing cycle logic is not new work. | BA36: =IFERROR(INDEX('Source Review'!$E$2:$E$52,MATCH($A36,'Source Review'!$A$2:$A$52,0)),"") -> Backend/PlantProcess.Application/Services/Materials/GenealogyService.cs:27-69 — CreateEdgeAsync Backend/PlantProcess.Application/Services/Materials/GenealogyService.cs:95-124 — WouldCreateCycleAsync Backend/database/scripts/841_genealogy_edge_weight_guard_topology_parity.sql:55-68 — deferred weight check | BB36: =IF(COUNTIF('Source Review'!$A$2:$A$52,$A36)>0,"14-Sep-2026 snapshot; later closure evidence separate; no live HEAD verification","") -> 14-Sep-2026 snapshot; later closure evidence separate; no live HEAD verification
A37: T-104 | B37: M2 | C37: P2 | D37: Projection provenance, exact-version stamping and idempotent reprojection | E37: Backend | F37: Projection | G37: Critical | H37: Complete the DF5 contract: source-shaped staging projects into the canonical plant model through the customer-authored versioned mapping, and every projected row records the mapping version that produced it. v2.22.0 — Absorbs T-105: Make reprojection idempotent and add the regression suite: reprojecting the same batch must not duplicate rows, and rolling a mapping back to a previous version must produce the earlier result exactly. T-261 owns the executor. This task owns canonical row-level definition/version provenance and replay effects, using that executor; it does not implement a competing MappingDefinition runtime. | I37: Project a batch, change the mapping version, project again, and confirm each row records the version that produced it. No row may carry a null mapping version. v2.22.0 — Reproject the same batch three times and confirm row counts are unchanged. Roll a mapping back and confirm the canonical output matches the earlier snapshot byte for byte. Assert exact resolved Transformation version/hash per run and row, tenant/dataset/batch source lineage, no duplicate accepted effect and byte-identical deterministic business output on rollback. Clock/run metadata is compared separately from business-result equivalence. | J37: 14 | K37: Not Started | L37: Worker 1 | M37: T-090; T-095; T-099; T-261 | N37: T-107; T-108; T-109; T-128; T-183; T-247 | O37: M2: ~1 month from owner planning checkpoint; exact date not committed | P37: Release 1 MUST | Q37: Backend/domain contract | R37: 1.2 | S37: M2-P2 | T37: GATE PROSE INCOMPLETE — original text ends with an ellipsis. Do not infer omitted conditions. Column M lists completion prerequisites; AN/Contract Handoffs lists contract-only prerequisites. Full task acceptance in column I still applies. Recover the omitted prose before claiming this gate fully reconciled. Preserved original fragment: Use the accepted M1 regression baseline; require empty index and clean owned paths, preserving unrelated user work. Then: T-090 canonical versioned mapping definitions + T-095 relationship authority ... | U37: Own canonical DB/backend/security/API/infra. No W2-owned UI/admin task files and no W3 ML/Assistant runtime. | V37: Commit before downstream consumer starts; consumer must use the contract, not redesign producer-owned semantics. | W37: Day-1 Data Workbench — DB Link, Canvas, Jobs & OPC | X37: M2 P2 — Day-1 Data Workbench — DB Link, Canvas, Jobs & OPC. Release 1 is genuine early production / first-week customer work. | AA37: L2.3 | AB37: Canonical projection with validation, quarantine and reprocessing | AC37: L2.5 | AD37: Build | AE37: D3; D5 | AF37: Core | AG37: R1 | AH37: Advances | AI37: =IF(Y37="","",Y37) | AJ37: RE-ESTIMATE REQUIRED — J/R retain the prior-scope figures for traceability; excluded from usable planning totals. New full-scope and remaining-work estimates are not supplied. | AK37: v4.10.3 | AL37: Chapters 3/4 v4.10.3 — MD + illustrated Word; UI Coverage / UI Controls in this workbook | AM37: =IF(AND(ISNUMBER(J37),OR(AR37="INHERITED ESTIMATE",AR37="CONFIRMED ESTIMATE")),1,0) -> 0 | AO37: Not started — no completion claimed | AP37: Inherited v2.22.0 intended record; no new runtime certification in this repair. | AR37: RE-ESTIMATE REQUIRED | AS37: =IF(AM37=1,J37,"") | AT37: =IF(AND(AM37=1,ISNUMBER(R37)),R37,"") | AU37: =IFERROR(INDEX('Source Review'!$B$2:$B$52,MATCH($A37,'Source Review'!$A$2:$A$52,0)),"NOT SOURCE-REVIEWED IN THIS PASS") -> REPLAY FOUNDATION IS NOT VERSIONED REPROJECTION | AV37: =IFERROR(INDEX('Source Review'!$F$2:$F$52,MATCH($A37,'Source Review'!$A$2:$A$52,0)),"") -> 8 | AW37: =IFERROR(INDEX('Source Review'!$G$2:$G$52,MATCH($A37,'Source Review'!$A$2:$A$52,0)),"") -> 14 | AX37: =IFERROR(INDEX('Source Review'!$H$2:$H$52,MATCH($A37,'Source Review'!$A$2:$A$52,0)),"") -> 22 | AY37: =IF(COUNTIF('Source Review'!$A$2:$A$52,$A37)>0,"UNCONFIRMED REVIEW ESTIMATE - not P80 or elapsed","NOT ESTIMATED IN THIS PASS") -> UNCONFIRMED REVIEW ESTIMATE - not P80 or elapsed | AZ37: =IFERROR(INDEX('Source Review'!$I$2:$I$52,MATCH($A37,'Source Review'!$A$2:$A$52,0)),"") -> Row-version/provenance integration 3/5/8 + replay/rollback semantics 3/6/10 + negative tests/closure 2/3/4. | BA37: =IFERROR(INDEX('Source Review'!$E$2:$E$52,MATCH($A37,'Source Review'!$A$2:$A$52,0)),"") -> Backend/PlantProcess.Application/Integration/Services/Mapping/MappingRowProjector.cs:168-181 — existing-row skip Backend/PlantProcess.Application/Integration/Services/Jobs/JobRunOrchestratorService.cs:210-249 — ResolveDeclaredTargetAsync | BB37: =IF(COUNTIF('Source Review'!$A$2:$A$52,$A37)>0,"14-Sep-2026 snapshot; later closure evidence separate; no live HEAD verification","") -> 14-Sep-2026 snapshot; later closure evidence separate; no live HEAD verification
A38: T-106 | B38: M2 | C38: P2 | D38: Canonical jobs: target/version, scheduling, dependencies, cancellation and outcome truth | E38: Backend | F38: Jobs | G38: Critical | H38: Build on the M1 target_definition_id work: add the full version policy (pinned or current published), the job dependency graph, and cycle validation. v2.10.2 BOUNDARY CORRECTION — the pinned/current-published PUBLIC semantics are already frozen by T-064. This task performs canonical physical convergence: job_definitions FK -> definition_store(id) ON DELETE RESTRICT, target-version policy CHECKs/target-surface trigger against the canonical store, target_parameters persistence, plus job_dependencies DAG/cycle validation. Do not redesign T-064's visible contract. v2.20.0 EXECUTION-PLANE EXPANSION — replace the central job-type switch as the authority for manual execution. Each executable job family registers an executor capability through DI/registry metadata: supported/unsupported state, target definition kind, version policy, input contract and run capability. A new executor family must be addable without editing a central switch. Unsupported families refuse at definition/save or capability discovery with a typed reason rather than surviving until RunNow. v2.20.0 LAYER-B PLACEMENT RULING — scheduling count, repetition, iteration windows and control flow belong to governed Job orchestration. Do not add new FOR/WHILE-style board execution semantics. Existing T-242 saved definitions remain readable through compatibility handling, but new orchestration authority is the Job plane. v2.22.0 — Deliver one canonical Job authority for target/version/capability, schedule grammar and occurrence identity, due scheduling, dependency resolution, cooperative cancellation and terminal-status truth. Implement Design v4.10.3 Ch4 5.3.2a / 5.3.6. The scheduler produces due requests; existing admission admits them. T-107 owns bounded pools; T-261 owns the actual Transformation executor. Keep these as separately testable sub-deliverables inside T-106 rather than additional task IDs. An executor supplied by tests proves orchestration before T-261 is commissioned, so T-106 must not depend on T-261 or T-107 closure. | I38: Declare a three-job chain, run it, and confirm order. Introduce a cycle and confirm it is refused at save time with a named code. Enumerate every job family exposed by the product and prove each is either backed by a registered executor or explicitly unavailable by typed reason. Register a test executor through DI and prove it runs without editing the orchestrator switch. The current 'no manual executor'/'not implemented yet' runtime fall-through is no longer reachable for an advertised executable job. Newly authored execution schedules express repetition/window/control-flow in the Job contract rather than creating a new Canvas FOR/WHILE node. A compatibility fixture for an existing T-242 loop definition remains readable and produces an explicit compatibility interpretation rather than data loss. v2.22.0 — Prove canonical schedule parsing/normalisation and UI next-occurrence parity; UTC/timezone and DST gap/fold rules; one atomic admission per tenant/job/schedule-revision/occurrence under racing workers; restart/missed ticks; invalid or unsupported schedule typed refusal; paused state persists. Cancel API is tenant/role-scoped, idempotent, reaches executor and records exactly one final outcome. Cancellation request is not completion acknowledgement. Define all-success, mixed, all-failed, no-work, cancelled and interrupted outcomes; one failed import batch cannot be hidden in an Ok run in either manual or worker path. Current-cycle and earlier-success reuse follow explicit allow_stale_reuse and age ceiling, with timestamps, policy and watermark in job_run_dependencies. Trigger-fires, wrong-kind/surface and actual orchestration evidence use disposable DB fixtures. Keep existing historical closure evidence; certify newly widened obligations separately. | J38: 12 | K38: Done | L38: Worker 3 | M38: T-064; T-089; T-090; T-252 | N38: T-107; T-122; T-125; T-245; T-261; T-263 | O38: M2: ~1 month from owner planning checkpoint; exact date not committed | P38: Release 1 MUST | Q38: Backend/domain contract | S38: M2-P2 | T38: Consume accepted producer contracts; remaining dependencies: T-064; T-089; T-090; T-252. No private scheduler/definition authority. Source-present is not closure proof. | U38: Own T-106/T-107/T-109 only after W1 producer contracts; no schema authority rewrites. | V38: Commit before downstream consumer starts; consumer must use the contract, not redesign producer-owned semantics. | W38: Day-1 Data Workbench — DB Link, Canvas, Jobs & OPC | X38: v2.22.0 owner-approved scope and release disposition; original evidence remains in change log/archive. | Y38: 8b3eb5c89352a2779d87f9205700f19e7c9b3e25; a5451dbaf6b55183fe65e2c626c49fdef85bd986 | AA38: L2.6 | AB38: Job definition, scheduling, execution monitor and history | AC38: L2.5; L2.7; L1.7 | AD38: Build | AE38: D3; D4; D5 | AF38: Core | AG38: R1 | AH38: Advances | AI38: =IF(Y38="","",Y38) -> 8b3eb5c89352a2779d87f9205700f19e7c9b3e25; a5451dbaf6b55183fe65e2c626c49fdef85bd986 | AJ38: RE-ESTIMATE REQUIRED — prior Hours/P80 preserved in Estimate Review; not zero remaining effort. | AK38: v4.10.3 | AL38: Chapters 3/4 v4.10.3 — MD + illustrated Word; UI Coverage / UI Controls in this workbook | AM38: =IF(AND(ISNUMBER(J38),OR(AR38="INHERITED ESTIMATE",AR38="CONFIRMED ESTIMATE")),1,0) -> 0 | AO38: BASELINE COMMITS PROVEN; CURRENT WIDENED ACCEPTANCE OPEN | AP38: Original corrective run returned GREEN with22 corrective,26 foundation,84 target-regression and15 architecture tests in24 owned paths;CENTRAL freeze after review. Later v2.22 schedule/cancel/freshness/outcome-truth scope is not closed by a10Sep run. Pasted text(20260910-102642).txt | lines244-261, T-106 FINAL RESULT: corrective COMMITTED GREEN a5451dbaf6b55183fe65e2c626c49fdef85bd986; foundation8b3eb5c89352a2779d87f9205700f19e7c9b3e25;22corrective,26foundation,84target-regression,15architecture tests;24owned paths;CENTRAL freeze after review. | AR38: RE-ESTIMATE REQUIRED | AS38: =IF(AM38=1,J38,"") | AT38: =IF(AND(AM38=1,ISNUMBER(R38)),R38,"") | AU38: =IFERROR(INDEX('Source Review'!$B$2:$B$52,MATCH($A38,'Source Review'!$A$2:$A$52,0)),"NOT SOURCE-REVIEWED IN THIS PASS") -> ORIGINAL CONTRACT CLOSED; EXPANDED RUNTIME OBLIGATIONS OPEN | AV38: =IFERROR(INDEX('Source Review'!$F$2:$F$52,MATCH($A38,'Source Review'!$A$2:$A$52,0)),"") -> 18 | AW38: =IFERROR(INDEX('Source Review'!$G$2:$G$52,MATCH($A38,'Source Review'!$A$2:$A$52,0)),"") -> 28 | AX38: =IFERROR(INDEX('Source Review'!$H$2:$H$52,MATCH($A38,'Source Review'!$A$2:$A$52,0)),"") -> 44 | AY38: =IF(COUNTIF('Source Review'!$A$2:$A$52,$A38)>0,"UNCONFIRMED REVIEW ESTIMATE - not P80 or elapsed","NOT ESTIMATED IN THIS PASS") -> UNCONFIRMED REVIEW ESTIMATE - not P80 or elapsed | AZ38: =IFERROR(INDEX('Source Review'!$I$2:$I$52,MATCH($A38,'Source Review'!$A$2:$A$52,0)),"") -> Schedule/parser/due-work 8/12/18 + freshness/outcome policy 4/6/10 + cancellation consumer integration 2/4/6 + targeted service/DB tests and runner 4/6/10. Original completed contracts excluded. | BA38: =IFERROR(INDEX('Source Review'!$E$2:$E$52,MATCH($A38,'Source Review'!$A$2:$A$52,0)),"") -> Backend/PlantProcess.Application/Integration/Services/Jobs/JobDefinitionService.cs:275-297 — schedule validation Backend/PlantProcess.Workers/Worker.cs:72-108 — fixed cadence loops Backend/PlantProcess.Application/Jobs/Dependencies/JobDependencyEvaluator.cs:33-39 — no age/tolerance input Backend/PlantProcess.Application/Jobs/Dependencies/JobDependencyEvaluator.cs:85-91 — Satisfied result Backend/PlantProcess.Application/Integration/Services/Jobs/JobRuntimeService.cs:127-146 — terminal-state switch Backend/PlantProcess.Application/Integration/Services/Jobs/JobRunOrchestratorService.cs:262-276 — import result mapping | BB38: =IF(COUNTIF('Source Review'!$A$2:$A$52,$A38)>0,"14-Sep-2026 snapshot; later closure evidence separate; no live HEAD verification","") -> 14-Sep-2026 snapshot; later closure evidence separate; no live HEAD verification
A39: T-107 | B39: M2 | C39: P2 | D39: Dual-predicate admission, bounded worker pools and the three ML execution lanes | E39: Backend | F39: Jobs | G39: Critical | H39: Replace the old single weighted-pool assumption with the frozen resource contract. Each lane has max_concurrency and resource_capacity; admission requires both running_count < max_concurrency and sum(compute_weight)+candidate <= resource_capacity. The logical ml class resolves to ml.training, ml.batch_scoring and ml.online_scoring. Online capacity is hard-reserved and unavailable to training or batch. Keep this platform-level scheduler generic; Worker 3 supplies the ML job classes and later integration tests, but this task must not wire any new AI runtime into the M1 presentation path. v2.10.2 MEASUREMENT RULING — this task implements the configurable dual-predicate admission mechanism and three-lane isolation. Test values may prove satisfiability, but no max_concurrency/resource_capacity/reserved fraction is a production-selected value here. Site values remain benchmark outputs owned by T-155/T-159. v2.20.0 BOUNDED-PARALLELISM EXPANSION — the same admission authority owns bounded parallel execution for eligible non-ML job families. The current serial import-loop behavior is replaced by queue/admission scheduling that respects both max_concurrency and resource_capacity. Do not implement unbounded Task.WhenAll/Parallel.ForEach. Per-family limits, cancellation, fair queueing and hard online reservation remain explicit. | I39: Prove a declared job can be admitted under a satisfiable configuration and a too-heavy job is refused by name. Saturate training and batch and prove an online-scoring job still admits inside its reservation. Prove batch never enters the online lane and the same compute_weight is never used as a concurrency count. Existing import/projection/analysis/report behaviour remains green. The acceptance report labels resource values as TEST_CONFIGURATION unless they come from the named production/site benchmark manifest. No code default is presented as the final capacity decision. Run multiple slow import/analysis jobs and prove concurrency rises above one only up to the configured bound, then queues. Queueing must not increase memory without bound; cancellation frees capacity; a too-heavy job remains queued/refused by named policy. A negative-control implementation using unbounded fan-out must make the gate red. | J39: 16 | K39: Not Started | L39: Worker 3 | M39: T-095; T-096; T-097; T-098; T-099; T-100; T-101; T-102; T-103; T-104; T-106 | N39: T-122; T-125; T-141; T-187; T-192 | O39: M2: ~1 month from owner planning checkpoint; exact date not committed | P39: Release 1 MUST | Q39: Backend/domain contract | R39: 1.8 | S39: M2-P2 | T39: GATE PROSE INCOMPLETE — original text ends with an ellipsis. Do not infer omitted conditions. Column M lists completion prerequisites; AN/Contract Handoffs lists contract-only prerequisites. Full task acceptance in column I still applies. Recover the omitted prose before claiming this gate fully reconciled. Preserved original fragment: Use the accepted M1 regression baseline; require empty index and clean owned paths, preserving unrelated user work. Then: T-106 canonical job contract + T-095..T-105 canonical data/relationship path;... | U39: Own T-106/T-107/T-109 only after W1 producer contracts; no schema authority rewrites. | V39: Commit before downstream consumer starts; consumer must use the contract, not redesign producer-owned semantics. | W39: Day-1 Data Workbench — DB Link, Canvas, Jobs & OPC | X39: M2 P2 — Day-1 Data Workbench — DB Link, Canvas, Jobs & OPC. Release 1 is genuine early production / first-week customer work. | AA39: L8.4 | AB39: Execution lanes, admission and resource isolation | AC39: L2.6 | AD39: Build | AE39: D3; D5 | AF39: Core | AG39: R1 | AH39: Advances | AI39: =IF(Y39="","",Y39) | AJ39: Inherited baseline estimate | AK39: v4.10.3 | AL39: Chapters 3/4 v4.10.3 — MD + illustrated Word; UI Coverage / UI Controls in this workbook | AM39: =IF(AND(ISNUMBER(J39),OR(AR39="INHERITED ESTIMATE",AR39="CONFIRMED ESTIMATE")),1,0) -> 1 | AO39: Not started — no completion claimed | AP39: Inherited v2.22.0 intended record; no new runtime certification in this repair. | AR39: INHERITED ESTIMATE | AS39: =IF(AM39=1,J39,"") -> 16 | AT39: =IF(AND(AM39=1,ISNUMBER(R39)),R39,"") -> 1.8 | AU39: =IFERROR(INDEX('Source Review'!$B$2:$B$52,MATCH($A39,'Source Review'!$A$2:$A$52,0)),"NOT SOURCE-REVIEWED IN THIS PASS") -> TIMERS EXIST; GOVERNED JOB POOLS NOT ESTABLISHED | AV39: =IFERROR(INDEX('Source Review'!$F$2:$F$52,MATCH($A39,'Source Review'!$A$2:$A$52,0)),"") -> 12 | AW39: =IFERROR(INDEX('Source Review'!$G$2:$G$52,MATCH($A39,'Source Review'!$A$2:$A$52,0)),"") -> 20 | AX39: =IFERROR(INDEX('Source Review'!$H$2:$H$52,MATCH($A39,'Source Review'!$A$2:$A$52,0)),"") -> 32 | AY39: =IF(COUNTIF('Source Review'!$A$2:$A$52,$A39)>0,"UNCONFIRMED REVIEW ESTIMATE - not P80 or elapsed","NOT ESTIMATED IN THIS PASS") -> UNCONFIRMED REVIEW ESTIMATE - not P80 or elapsed | AZ39: =IFERROR(INDEX('Source Review'!$I$2:$I$52,MATCH($A39,'Source Review'!$A$2:$A$52,0)),"") -> Pool/admission implementation 6/10/16 + lane/worker integration 3/5/8 + saturation/cancel/closure tests 3/5/8. | BA39: =IFERROR(INDEX('Source Review'!$E$2:$E$52,MATCH($A39,'Source Review'!$A$2:$A$52,0)),"") -> Backend/PlantProcess.Workers/Worker.cs:72-108 — ExecuteAsync cadence Backend/PlantProcess.Application/Jobs/Execution/JobExecutionCapability.cs:76-107 — family capability vs capacity | BB39: =IF(COUNTIF('Source Review'!$A$2:$A$52,$A39)>0,"14-Sep-2026 snapshot; later closure evidence separate; no live HEAD verification","") -> 14-Sep-2026 snapshot; later closure evidence separate; no live HEAD verification
A40: T-108 | B40: M2 | C40: P2 | D40: End-to-end delta correctness: source cursor, load protection, replay and projection watermark | E40: Backend | F40: Delta propagation | G40: Critical | H40: Today only import is incremental. Chapter 4 5.3.9 requires every downstream stage to be delta-scoped. Add the stage_watermarks table and make canonical projection delta-scoped against it. The arithmetic that justifies this: a naive full scan for one Pro-tier customer is 481 TB per day, while delta-scoped is 5 to 20 GB, a ratio of 24,000 to 1. v2.22.0 — Own acquisition-to-projection delta correctness: typed total-order cursor with source-stable tie-break for non-unique watermarks; one invariant provider-native ordering contract; durable cursor/staging/receipt atomicity; replay-safe accepted effects; per-dataset/profile budget resolution constrained by installation/source ceilings; apply pre-read budget/window/rate/concurrency/timeout checks on incremental as well as preview reads. Do not replace a stricter parent ceiling with a looser child override. Source native ordering and source-version identity govern legitimate updates. Retain existing stage-watermark and delta-projection duties; T-110 owns the advanced M3 parallel chunk engine. | I40: Change one source row and confirm projection processes a bounded delta rather than a full scan, evidenced by rows-scanned telemetry. v2.22.0 — Use more equal-watermark records than three page limits, numeric/timestamp/composite cursors, declared key changes, source updates, no change, de-DE/en-US serialization, crash before and after commit and racing workers. Prove no missed rows/no duplicate accepted source revision, and checkpoint advanced only with durable effects. Over-budget incremental reads issue no source query. Replay of a partially failed import preserves legitimate later versions of the same business key. One changed source row produces bounded downstream work with recorded counts. | K40: Not Started | L40: Worker 1 | M40: T-099; T-104 | N40: T-109; T-110; T-247 | O40: M2: ~1 month from owner planning checkpoint; exact date not committed | P40: Release 1 MUST | Q40: Backend/domain contract | S40: M2-P2 | T40: Consume accepted producer contracts; remaining dependencies: T-099; T-104. No private scheduler/definition authority. Source-present is not closure proof. | U40: Own canonical DB/backend/security/API/infra. No W2-owned UI/admin task files and no W3 ML/Assistant runtime. | V40: Commit before downstream consumer starts; consumer must use the contract, not redesign producer-owned semantics. | W40: Day-1 Data Workbench — DB Link, Canvas, Jobs & OPC | X40: v2.22.0 owner-approved scope and release disposition; original evidence remains in change log/archive. | AA40: L2.8 | AB40: Delta propagation law | AC40: L1.3; L1.1; L1.7 | AD40: Build | AE40: D3; D4; D5 | AF40: Core | AG40: R1 | AH40: Advances | AI40: =IF(Y40="","",Y40) | AJ40: RE-ESTIMATE REQUIRED — prior Hours/P80 preserved in Estimate Review; not zero remaining effort. | AK40: v4.10.3 | AL40: Chapters 3/4 v4.10.3 — MD + illustrated Word; UI Coverage / UI Controls in this workbook | AM40: =IF(AND(ISNUMBER(J40),OR(AR40="INHERITED ESTIMATE",AR40="CONFIRMED ESTIMATE")),1,0) -> 0 | AO40: Not started — no completion claimed | AP40: Inherited v2.22.0 intended record; no new runtime certification in this repair. | AR40: RE-ESTIMATE REQUIRED | AS40: =IF(AM40=1,J40,"") | AT40: =IF(AND(AM40=1,ISNUMBER(R40)),R40,"") | AU40: =IFERROR(INDEX('Source Review'!$B$2:$B$52,MATCH($A40,'Source Review'!$A$2:$A$52,0)),"NOT SOURCE-REVIEWED IN THIS PASS") -> IMPLEMENTED DELTA FOUNDATION WITH CONFIRMED CORRECTNESS GAPS | AV40: =IFERROR(INDEX('Source Review'!$F$2:$F$52,MATCH($A40,'Source Review'!$A$2:$A$52,0)),"") -> 22 | AW40: =IFERROR(INDEX('Source Review'!$G$2:$G$52,MATCH($A40,'Source Review'!$A$2:$A$52,0)),"") -> 34 | AX40: =IFERROR(INDEX('Source Review'!$H$2:$H$52,MATCH($A40,'Source Review'!$A$2:$A$52,0)),"") -> 52 | AY40: =IF(COUNTIF('Source Review'!$A$2:$A$52,$A40)>0,"UNCONFIRMED REVIEW ESTIMATE - not P80 or elapsed","NOT ESTIMATED IN THIS PASS") -> UNCONFIRMED REVIEW ESTIMATE - not P80 or elapsed | AZ40: =IFERROR(INDEX('Source Review'!$I$2:$I$52,MATCH($A40,'Source Review'!$A$2:$A$52,0)),"") -> Tuple contract+reader adaptations 8/12/18 + budget enforcement 4/6/9 + durable staging/replay+projection token 5/8/13 + adverse-boundary tests/closure 5/8/12. | BA40: =IFERROR(INDEX('Source Review'!$E$2:$E$52,MATCH($A40,'Source Review'!$A$2:$A$52,0)),"") -> Backend/PlantProcess.Application/Integration/Services/SourceSystems/DeltaImportExecutionService.cs:120-151 — read-path selection Backend/PlantProcess.Application/Integration/Services/SourceSystems/DeltaImportExecutionService.cs:173-205 — row/cursor handling Backend/PlantProcess.Application/Integration/Services/SourceSystems/DeltaImportExecutionService.cs:236-280 — source identity and MaxCursor Backend/PlantProcess.Infrastructure/Connectors/PostgreSql/PostgreSqlConnector.cs:181-206 — scalar LIMIT query Backend/PlantProcess.Application/Integration/Protection/ThrottlingDataSourceReader.cs:36-70 — unequal protection Backend/PlantProcess.Infrastructure/Integration/Protection/OptionsSourceLoadBudgetProvider.cs:21-24 — global budget Backend/PlantProcess.Infrastructure/Persistence/Configurations/Integration/StagingRecordConfiguration.cs:31-42 — existing within-batch uniqueness Backend/tests/PlantProcess.Api.IntegrationTests/Import/DeltaImportResumabilityTests.cs:58-73 — current weak continuation assertions | BB40: =IF(COUNTIF('Source Review'!$A$2:$A$52,$A40)>0,"14-Sep-2026 snapshot; later closure evidence separate; no live HEAD verification","") -> 14-Sep-2026 snapshot; later closure evidence separate; no live HEAD verification
A41: T-109 | B41: M2 | C41: P2 | D41: Delta-scoped feature refresh and analysis, with telemetry and ML hand-off | E41: Backend | F41: Delta propagation | G41: Critical | H41: Extend the stage-watermark mechanism into the canonical feature refresh and analysis path. The task owns delta discovery, dirty-feature identification and telemetry only; training must never read feature_store directly. Expose a bounded changed-population contract that Worker 3's Snapshot Materialiser consumes later. Do not add temporary M1/presentation schema dependencies. | I41: Insert one bounded delta and prove only affected feature rows and analyses are recomputed. Record rows scanned, rows changed and Scan Amplification. Assert no training/encoding component is reachable from this task and the output contract contains no customer table name. | J41: 6 | K41: Not Started | L41: Worker 3 | M41: T-095; T-096; T-097; T-098; T-099; T-100; T-101; T-102; T-103; T-104; T-108 | N41: T-110; T-136; T-187 | O41: M2: ~1 month from owner planning checkpoint; exact date not committed | P41: Release 1 MUST | Q41: Backend/domain contract | R41: 0.9 | S41: M2-P2 | T41: Use the accepted M1 regression baseline; require empty index and clean owned paths, preserving unrelated user work. Then: T-095..T-105; T-108 | U41: Own T-106/T-107/T-109 only after W1 producer contracts; no schema authority rewrites. | V41: Commit before downstream consumer starts; consumer must use the contract, not redesign producer-owned semantics. | W41: Day-1 Data Workbench — DB Link, Canvas, Jobs & OPC | X41: M2 P2 — Day-1 Data Workbench — DB Link, Canvas, Jobs & OPC. Release 1 is genuine early production / first-week customer work. | AA41: L2.8 | AB41: Delta propagation law | AC41: L4.3 | AD41: Build | AE41: D3; D5 | AF41: Core | AG41: R1 | AH41: Advances | AI41: =IF(Y41="","",Y41) | AJ41: Inherited baseline estimate | AK41: v4.10.3 | AL41: Chapters 3/4 v4.10.3 — MD + illustrated Word; UI Coverage / UI Controls in this workbook | AM41: =IF(AND(ISNUMBER(J41),OR(AR41="INHERITED ESTIMATE",AR41="CONFIRMED ESTIMATE")),1,0) -> 1 | AO41: Not started — no completion claimed | AP41: Inherited v2.22.0 intended record; no new runtime certification in this repair. | AR41: INHERITED ESTIMATE | AS41: =IF(AM41=1,J41,"") -> 6 | AT41: =IF(AND(AM41=1,ISNUMBER(R41)),R41,"") -> 0.9 | AU41: =IFERROR(INDEX('Source Review'!$B$2:$B$52,MATCH($A41,'Source Review'!$A$2:$A$52,0)),"NOT SOURCE-REVIEWED IN THIS PASS") -> REUSABLE CALCULATION FOUNDATION; DELTA CONSUMER NOT PROVEN | AV41: =IFERROR(INDEX('Source Review'!$F$2:$F$52,MATCH($A41,'Source Review'!$A$2:$A$52,0)),"") -> 6 | AW41: =IFERROR(INDEX('Source Review'!$G$2:$G$52,MATCH($A41,'Source Review'!$A$2:$A$52,0)),"") -> 10 | AX41: =IFERROR(INDEX('Source Review'!$H$2:$H$52,MATCH($A41,'Source Review'!$A$2:$A$52,0)),"") -> 18 | AY41: =IF(COUNTIF('Source Review'!$A$2:$A$52,$A41)>0,"UNCONFIRMED REVIEW ESTIMATE - not P80 or elapsed","NOT ESTIMATED IN THIS PASS") -> UNCONFIRMED REVIEW ESTIMATE - not P80 or elapsed | AZ41: =IFERROR(INDEX('Source Review'!$I$2:$I$52,MATCH($A41,'Source Review'!$A$2:$A$52,0)),"") -> Scope resolution/integration 3/5/9 + telemetry/handoff 1/2/4 + idempotent/late-data tests 2/3/5. | BA41: =IFERROR(INDEX('Source Review'!$E$2:$E$52,MATCH($A41,'Source Review'!$A$2:$A$52,0)),"") -> Backend/PlantProcess.Application/Integration/Services/SourceSystems/DeltaImportExecutionService.cs:173-217 — available source delta boundary Backend/PlantProcess.Application/Relationships/RelationshipResolver.cs:85-113 — governed automated path | BB41: =IF(COUNTIF('Source Review'!$A$2:$A$52,$A41)>0,"14-Sep-2026 snapshot; later closure evidence separate; no live HEAD verification","") -> 14-Sep-2026 snapshot; later closure evidence separate; no live HEAD verification
A42: T-207 | B42: M2 | C42: P2 | D42: Connector capability truth: stop advertising unimplemented browse/read/subscription | E42: Acquisition | F42: Connector truth | G42: Critical | H42: Make connector capability metadata executable truth. Current OPC/historian configuration validation or deterministic sample generation must not advertise live browse/bounded-read/subscription unless the connector build executes and tests that operation. | I42: Against the current implementation, unsupported browse/read/subscription report false/unavailable and attempts return typed OT01 rather than fabricated data. Add a contract test that makes any future advertised capability fail until an executable implementation passes. | J42: 6 | K42: Done | L42: Worker 1 | M42: T-201 | N42: T-150; T-224; T-247; T-254; T-266 | O42: M2: ~1 month from owner planning checkpoint; exact date not committed | P42: Release 1 MUST | Q42: Backend contract | R42: 2.25 | S42: M2-P2 | T42: CLOSED BASELINE — no new start gate and no re-execution implied. Preserve accepted closure and clean owned scope; reopen only on a concrete, separately recorded regression. Downstream consumes the frozen contract. | U42: Connector metadata/API contract and tests. | V42: T-224..T-226 later may flip capabilities to true only by passing this contract. | W42: Day-1 Data Workbench — DB Link, Canvas, Jobs & OPC | X42: M2 P2 — Day-1 Data Workbench — DB Link, Canvas, Jobs & OPC. Release 1 is genuine early production / first-week customer work. | Y42: Not recovered from reviewed sessions | AA42: L1.4 | AB42: Connector capability truth | AD42: Build | AE42: D1; D3; D5 | AF42: Core | AG42: R1 | AH42: Advances | AI42: =IF(Y42="","",Y42) -> Not recovered from reviewed sessions | AJ42: Inherited baseline estimate | AK42: v4.10.3 | AL42: Chapters 3/4 v4.10.3 — MD + illustrated Word; UI Coverage / UI Controls in this workbook | AM42: =IF(AND(ISNUMBER(J42),OR(AR42="INHERITED ESTIMATE",AR42="CONFIRMED ESTIMATE")),1,0) -> 1 | AO42: Recorded closed — inherited evidence | AP42: Inherited v2.22.0 intended record; no new runtime certification in this repair. | AR42: INHERITED ESTIMATE | AS42: =IF(AM42=1,J42,"") -> 6 | AT42: =IF(AND(AM42=1,ISNUMBER(R42)),R42,"") -> 2.25 | AU42: =IFERROR(INDEX('Source Review'!$B$2:$B$52,MATCH($A42,'Source Review'!$A$2:$A$52,0)),"NOT SOURCE-REVIEWED IN THIS PASS") -> SOURCE CORROBORATES CLOSED TRUTH CONTRACT | AV42: =IFERROR(INDEX('Source Review'!$F$2:$F$52,MATCH($A42,'Source Review'!$A$2:$A$52,0)),"") -> 0 | AW42: =IFERROR(INDEX('Source Review'!$G$2:$G$52,MATCH($A42,'Source Review'!$A$2:$A$52,0)),"") -> 0 | AX42: =IFERROR(INDEX('Source Review'!$H$2:$H$52,MATCH($A42,'Source Review'!$A$2:$A$52,0)),"") -> 0 | AY42: =IF(COUNTIF('Source Review'!$A$2:$A$52,$A42)>0,"UNCONFIRMED REVIEW ESTIMATE - not P80 or elapsed","NOT ESTIMATED IN THIS PASS") -> UNCONFIRMED REVIEW ESTIMATE - not P80 or elapsed | AZ42: =IFERROR(INDEX('Source Review'!$I$2:$I$52,MATCH($A42,'Source Review'!$A$2:$A$52,0)),"") -> Closed honesty contract retained; separate future live acquisition. | BA42: =IFERROR(INDEX('Source Review'!$E$2:$E$52,MATCH($A42,'Source Review'!$A$2:$A$52,0)),"") -> Backend/PlantProcess.Api/PlantConnectors/V5GaHistorianConnectorEndpoints.cs:61-108 — HistorianConnectorCapabilities | BB42: =IF(COUNTIF('Source Review'!$A$2:$A$52,$A42)>0,"14-Sep-2026 snapshot; later closure evidence separate; no live HEAD verification","") -> 14-Sep-2026 snapshot; later closure evidence separate; no live HEAD verification
A43: T-212 | B43: M2 | C43: P2 | D43: Integrate aggregation semantics into Layer-A widget/query execution | E43: Backend/Frontend | F43: Dashboard query semantics | G43: Critical | H43: Make dashboard/query aggregation resolve the canonical KPI/parameter semantics and certified kernel/database implementation. Remove raw-cap-before-aggregate and implicit average fallbacks in all customer-facing measures touched by this contract. | I43: Persisted-definition replay on discrete and continuous fixtures proves exact known answers; no raw row limit is applied before aggregate; AG01/AG02 render typed Blocked/Refused rather than API 500. Query plan performs bounded server-side aggregation. | J43: 10 | K43: Not Started | L43: Worker 2 | M43: T-202; T-210; T-211; T-092; T-234; T-235; T-236 | N43: T-150; T-247 | O43: M2: ~1 month from owner planning checkpoint; exact date not committed | P43: Release 1 MUST | Q43: Cross-layer integration | R43: 5.1428571 | S43: M2-P2 | T43: T-202 + T-210/T-211 + T-092 + committed T-234/T-235/T-236. | U43: Dashboard query service/executor + focused frontend state mapping. | V43: Consumes W1 semantics and W3 kernel; no independent aggregation rules. | W43: Day-1 Data Workbench — DB Link, Canvas, Jobs & OPC | X43: M2 P2 — Day-1 Data Workbench — DB Link, Canvas, Jobs & OPC. Release 1 is genuine early production / first-week customer work. | AA43: L3.4 | AB43: Widget catalogue and intelligence visualisation | AC43: L5.3; L4.2 | AD43: Build | AE43: D1; D2; D3; D5 | AF43: Core | AG43: R1 | AH43: Advances | AI43: =IF(Y43="","",Y43) | AJ43: Inherited baseline estimate | AK43: v4.10.3 | AL43: Chapters 3/4 v4.10.3 — MD + illustrated Word; UI Coverage / UI Controls in this workbook | AM43: =IF(AND(ISNUMBER(J43),OR(AR43="INHERITED ESTIMATE",AR43="CONFIRMED ESTIMATE")),1,0) -> 1 | AO43: Not started — no completion claimed | AP43: Inherited v2.22.0 intended record; no new runtime certification in this repair. | AR43: INHERITED ESTIMATE | AS43: =IF(AM43=1,J43,"") -> 10 | AT43: =IF(AND(AM43=1,ISNUMBER(R43)),R43,"") -> 5.1428571 | AU43: =IFERROR(INDEX('Source Review'!$B$2:$B$52,MATCH($A43,'Source Review'!$A$2:$A$52,0)),"NOT SOURCE-REVIEWED IN THIS PASS") -> AUTHORITY EXISTS; PRODUCTION QUERY CONSUMPTION GAP | AV43: =IFERROR(INDEX('Source Review'!$F$2:$F$52,MATCH($A43,'Source Review'!$A$2:$A$52,0)),"") -> 6 | AW43: =IFERROR(INDEX('Source Review'!$G$2:$G$52,MATCH($A43,'Source Review'!$A$2:$A$52,0)),"") -> 9 | AX43: =IFERROR(INDEX('Source Review'!$H$2:$H$52,MATCH($A43,'Source Review'!$A$2:$A$52,0)),"") -> 14 | AY43: =IF(COUNTIF('Source Review'!$A$2:$A$52,$A43)>0,"UNCONFIRMED REVIEW ESTIMATE - not P80 or elapsed","NOT ESTIMATED IN THIS PASS") -> UNCONFIRMED REVIEW ESTIMATE - not P80 or elapsed | AZ43: =IFERROR(INDEX('Source Review'!$I$2:$I$52,MATCH($A43,'Source Review'!$A$2:$A$52,0)),"") -> Query integration 3/5/8 + known-answer/refusal tests 2/3/4 + closure 1/1/2. | BA43: =IFERROR(INDEX('Source Review'!$E$2:$E$52,MATCH($A43,'Source Review'!$A$2:$A$52,0)),"") -> Backend/PlantProcess.Infrastructure/Definitions/Semantics/SignalSemanticsResolver.cs:30-74 — ResolveAsync Frontend/PlantProcess.Web/src/authoring/governedBlockBinding.ts:1-9 — not analytics mathematics | BB43: =IF(COUNTIF('Source Review'!$A$2:$A$52,$A43)>0,"14-Sep-2026 snapshot; later closure evidence separate; no live HEAD verification","") -> 14-Sep-2026 snapshot; later closure evidence separate; no live HEAD verification
A44: T-213 | B44: M2 | C44: P2 | D44: Customer Data Intake and Capability Assessment authority | E44: Onboarding | F44: Customer data assessment | G44: Critical | H44: Create a versioned assessment workflow/report for an unknown customer: source inventory, entity/equipment map, time model, identity/join strategy, parameter catalogue, KPI candidates, references, aggregation gaps, data quality, historical coverage, reconciliation/ML eligibility, OT trial requirements and missing information. The intake MUST also capture same-calendar-window manual vs machine history availability, transition/changeover definitions and stabilisation rules, sequence/campaign boundaries, setup/preparation evidence, and customer objective sets/trade-off preferences. Accepted results become normal definitions/mappings; the assessment is not a second authority. | I44: Run against one foreign/customer-shaped fixture and produce a complete report with explicit UNKNOWN/MISSING states, including regime-context readiness and multi-objective readiness. Same-window reconciliation evidence is separately reported. No product-code change is made for customer vocabulary. Re-run after one new source/field creates a new assessment version and diff. | J44: 8 | K44: Done | L44: Worker 2 | M44: T-201; T-206 | N44: T-227; T-247 | O44: M2: ~1 month from owner planning checkpoint; exact date not committed | P44: Release 1 MUST | Q44: Backend / product workflow | R44: 3.2 | S44: M2-P2 | T44: CLOSED BASELINE — no new start gate and no re-execution implied. Preserve accepted closure and clean owned scope; reopen only on a concrete, separately recorded regression. Downstream consumes the frozen contract. | U44: Onboarding assessment service/report; no customer-specific schema code. | V44: Mappings/definitions become canonical through existing authorities; report does not become a shadow registry. | W44: Day-1 Data Workbench — DB Link, Canvas, Jobs & OPC | X44: M2 P2 — Day-1 Data Workbench — DB Link, Canvas, Jobs & OPC. Release 1 is genuine early production / first-week customer work. | Y44: 2748c7fba8a5c4763bc19112ce57e484cea5b9bb — subject not recovered | Z44: 46265 | AA44: L1.2 | AB44: Dataset registration and source selection | AC44: L1.1; L7.8 | AD44: Build | AE44: D1; D5 | AF44: Core | AG44: R1 | AH44: Advances | AI44: =IF(Y44="","",Y44) -> 2748c7fba8a5c4763bc19112ce57e484cea5b9bb — subject not recovered | AJ44: Inherited baseline estimate | AK44: v4.10.3 | AL44: Chapters 3/4 v4.10.3 — MD + illustrated Word; UI Coverage / UI Controls in this workbook | AM44: =IF(AND(ISNUMBER(J44),OR(AR44="INHERITED ESTIMATE",AR44="CONFIRMED ESTIMATE")),1,0) -> 1 | AO44: Recorded closed — inherited evidence | AP44: Inherited v2.22.0 intended record; no new runtime certification in this repair. | AR44: INHERITED ESTIMATE | AS44: =IF(AM44=1,J44,"") -> 8 | AT44: =IF(AND(AM44=1,ISNUMBER(R44)),R44,"") -> 3.2 | AU44: =IFERROR(INDEX('Source Review'!$B$2:$B$52,MATCH($A44,'Source Review'!$A$2:$A$52,0)),"NOT SOURCE-REVIEWED IN THIS PASS") -> SOURCE CORROBORATES CLOSED PRODUCER | AV44: =IFERROR(INDEX('Source Review'!$F$2:$F$52,MATCH($A44,'Source Review'!$A$2:$A$52,0)),"") -> 0 | AW44: =IFERROR(INDEX('Source Review'!$G$2:$G$52,MATCH($A44,'Source Review'!$A$2:$A$52,0)),"") -> 0 | AX44: =IFERROR(INDEX('Source Review'!$H$2:$H$52,MATCH($A44,'Source Review'!$A$2:$A$52,0)),"") -> 0 | AY44: =IF(COUNTIF('Source Review'!$A$2:$A$52,$A44)>0,"UNCONFIRMED REVIEW ESTIMATE - not P80 or elapsed","NOT ESTIMATED IN THIS PASS") -> UNCONFIRMED REVIEW ESTIMATE - not P80 or elapsed | AZ44: =IFERROR(INDEX('Source Review'!$I$2:$I$52,MATCH($A44,'Source Review'!$A$2:$A$52,0)),"") -> Original producer closure retained; no duplicate intake engine. | BA44: =IFERROR(INDEX('Source Review'!$E$2:$E$52,MATCH($A44,'Source Review'!$A$2:$A$52,0)),"") -> Backend/PlantProcess.Api/Endpoints/CustomerAssessmentEndpoints.cs:86-125 — assessment routes and tenant gate | BB44: =IF(COUNTIF('Source Review'!$A$2:$A$52,$A44)>0,"14-Sep-2026 snapshot; later closure evidence separate; no live HEAD verification","") -> 14-Sep-2026 snapshot; later closure evidence separate; no live HEAD verification
A45: T-224 | B45: M2 | C45: P2 | D45: Production OPC UA edge runtime: endpoint security, certificates and session lifecycle | E45: Acquisition | F45: OPC UA edge | G45: Critical | H45: Implement real OPC UA client runtime inside the customer-side collector boundary: endpoint discovery/selection, security policy negotiation, application certificate/trust management, authenticated session lifecycle and read-only enforcement. Core never gains plant-network credentials/routes. v4.11.0 SCOPE DELTA — The session runtime consumes the governed Connection/Dataset/field/configuration identities from T-268 and must publish negotiated/effective source capability evidence without turning source settings into product guarantees. No native PLC driver is implied by OPC support. | I45: Against a real SDK test server, establish trusted and rejected sessions, rotate trust, reconnect after server restart and prove no write/control verb/path exists. Capability metadata remains false until this task and downstream browse/subscription tasks pass. Additional acceptance: operation-level capability receipt names endpoint/source profile, security/trust result and negotiated limits; offline/takeover behavior must not create a second active capture owner. Source credentials remain collector-side only. | J45: 12 | K45: Not Started | L45: Worker 3 | M45: T-207 | N45: T-153; T-225 | O45: M2: ~1 month from owner planning checkpoint; exact date not committed | P45: Release 1 MUST | Q45: External/site + backend | R45: 7.2 | S45: M2-P2 | T45: Release 1 MUST — start after T-207 connector-truth authority. Site/customer OT certification may require customer access, but the executable production OPC UA runtime itself cannot be deferred past M2. | U45: Customer-side edge agent/OPC adapter only. | V45: T-225 consumes session adapter; site certification remains T-153/T-227-like acceptance, not hidden in code. | W45: Day-1 Data Workbench — DB Link, Canvas, Jobs & OPC | X45: CENTRAL 04-Sep-2026: remove the contradictory 'after 30-Sep demo' gate. M2 is genuine early production and its P2 outcome includes real read-only OPC UA runtime. | AA45: L1.8 | AB45: OPC-UA / historian / edge acquisition | AD45: Harden | AE45: D3; D5 | AF45: Core | AG45: R1 | AH45: Advances | AI45: =IF(Y45="","",Y45) | AJ45: Inherited baseline estimate | AK45: v4.10.3 | AL45: Chapters 3/4 v4.10.3 — MD + illustrated Word; UI Coverage / UI Controls in this workbook v2.23.0 — T-266 supplies OPC profile/session/trust target and refusal designs, with Worker 1 technical review. This is a contract handoff, not a full-design completion prerequisite for backend implementation. | AM45: =IF(AND(ISNUMBER(J45),OR(AR45="INHERITED ESTIMATE",AR45="CONFIRMED ESTIMATE")),1,0) -> 0 | AO45: Not started — no completion claimed | AP45: Inherited v2.22.0 intended record; no new runtime certification in this repair. | AR45: RE-ESTIMATE REQUIRED — v4.11.0 scope delta | AS45: =IF(AM45=1,J45,"") | AT45: =IF(AND(AM45=1,ISNUMBER(R45)),R45,"") | AU45: DESIGN v4.11.0 SCOPE DELTA — SOURCE PREFLIGHT REQUIRED | AY45: NOT ESTIMATED AFTER v4.11.0 | AZ45: Original task closure remains open; new acceptance must be estimated from current source. | BA45: Design v4.11.0 + Industrial Integration review; current implementation source must be preflighted | BB45: 16-Sep-2026 design authority; no live source/runtime certification performed
A46: T-225 | B46: M2 | C46: P2 | D46: Production OPC UA edge runtime: browse, tag registration, subscription and monitored items | E46: Acquisition | F46: OPC UA edge | G46: Critical | H46: Implement namespace browse, tag selection/registration, subscriptions/monitored items, sampling/publishing interval and deadband configuration behind generic collector contracts. v4.11.0 SCOPE DELTA — Browse/tag registration emits stable field identities consumed by T-268; monitored-item sampling/publishing/filter settings remain protocol mechanics and must not be presented as PPIQ durable-record semantics. T-270 owns Time/Value-change/Trigger-counter business recording behavior. | I46: Browse a test namespace, register N tags, subscribe, receive changed values and prove disconnect/reconnect resumes without fabricated deterministic samples. Read-only operations only. `supportsTagBrowse`/`supportsSubscription` become true only after these executed tests. Additional acceptance: Namespace URI + identifier identity survives namespace-index change; server-revised settings are recorded; source-side filter pushdown is accepted only when semantics match the authored recording policy; no ordinary multi-tag read is labelled a PLC-atomic snapshot. | J46: 12 | K46: Not Started | L46: Worker 3 | M46: T-224 | N46: T-153; T-226 | O46: M2: ~1 month from owner planning checkpoint; exact date not committed | P46: Release 1 MUST | Q46: External/site + backend | R46: 7.2 | S46: M2-P2 | T46: T-224. | U46: Edge OPC adapter + tag registry integration. | V46: T-226 consumes typed acquired values; no core API direct OPC connection. | W46: Day-1 Data Workbench — DB Link, Canvas, Jobs & OPC | X46: M2 P2 — Day-1 Data Workbench — DB Link, Canvas, Jobs & OPC. Release 1 is genuine early production / first-week customer work. | AA46: L1.8 | AB46: OPC-UA / historian / edge acquisition | AD46: Build | AE46: D3; D5 | AF46: Core | AG46: R1 | AH46: Advances | AI46: =IF(Y46="","",Y46) | AJ46: Inherited baseline estimate | AK46: v4.10.3 | AL46: Chapters 3/4 v4.10.3 — MD + illustrated Word; UI Coverage / UI Controls in this workbook v2.23.0 — T-266 supplies browse tree, tag registration, bounded-read/subscription and keyboard/validation designs. Backend development follows frozen contracts in parallel; capability flags still require runtime proof. | AM46: =IF(AND(ISNUMBER(J46),OR(AR46="INHERITED ESTIMATE",AR46="CONFIRMED ESTIMATE")),1,0) -> 0 | AO46: Not started — no completion claimed | AP46: Inherited v2.22.0 intended record; no new runtime certification in this repair. | AR46: RE-ESTIMATE REQUIRED — v4.11.0 scope delta | AS46: =IF(AM46=1,J46,"") | AT46: =IF(AND(AM46=1,ISNUMBER(R46)),R46,"") | AU46: DESIGN v4.11.0 SCOPE DELTA — SOURCE PREFLIGHT REQUIRED | AY46: NOT ESTIMATED AFTER v4.11.0 | AZ46: Original task closure remains open; new acceptance must be estimated from current source. | BA46: Design v4.11.0 + Industrial Integration review; current implementation source must be preflighted | BB46: 16-Sep-2026 design authority; no live source/runtime certification performed
A47: T-226 | B47: M2 | C47: P2 | D47: Production OPC UA edge runtime: quality/timestamps, recovery and spool-to-canonical proof | E47: Acquisition | F47: OPC UA edge | G47: Critical | H47: Preserve OPC StatusCode/quality plus source/server timestamps, integrate reconnect/sequence-loss handling and existing store-and-forward spool, map acquired values into canonical observations under Source Time Authority. v4.11.0 SCOPE DELTA — OPC transport/recovery now hands durable observations through T-270/T-272/T-275: policy-state correctness, accepted-record identity, finite sealed batches during a continuous session, gap truth and replay-only behavior for a superseded collector. This task remains the OPC end-to-end proof owner, not a second storage/Job authority. | I47: Good/bad/uncertain quality and source-vs-server timestamp cases land correctly; network interruption queues locally and resumes idempotently; duplicate replay does not duplicate canonical observations; customer-core direction remains one-way. Additional acceptance: continuous session remains active while finite batches become projection-ready; same record identity+same content is idempotent and different content conflicts; edge/core outage boundaries are distinguished; Bad/Uncertain quality and source/server/capture/ingest times survive; no fabricated payload for missing counter events. | J47: 12 | K47: Not Started | L47: Worker 3 | M47: T-225; T-233; T-270; T-272; T-275 | N47: T-150; T-153 | O47: M2: ~1 month from owner planning checkpoint; exact date not committed | P47: Release 1 MUST | Q47: External/site + backend | R47: 7.2 | S47: M2-P2 | T47: T-225 + T-216 Source Time Authority. | U47: Edge spool/acquisition mapper + canonical ingest contract. | V47: T-153 real-source connector certification consumes this implementation; do not call implementation itself site-certified. | W47: Day-1 Data Workbench — DB Link, Canvas, Jobs & OPC | X47: M2 P2 — Day-1 Data Workbench — DB Link, Canvas, Jobs & OPC. Release 1 is genuine early production / first-week customer work. | AA47: L1.8 | AB47: OPC-UA / historian / edge acquisition | AD47: Build | AE47: D3; D5 | AF47: Core | AG47: R1 | AH47: Advances | AI47: =IF(Y47="","",Y47) | AJ47: Inherited baseline estimate | AK47: v4.10.3 | AL47: Chapters 3/4 v4.10.3 — MD + illustrated Word; UI Coverage / UI Controls in this workbook v2.23.0 — T-266 supplies quality/time/spool/reconnect/replay evidence presentation. The source-time and idempotency rules are unchanged; labelled design fixtures are not test-server proof. | AM47: =IF(AND(ISNUMBER(J47),OR(AR47="INHERITED ESTIMATE",AR47="CONFIRMED ESTIMATE")),1,0) -> 0 | AO47: Not started — no completion claimed | AP47: Inherited v2.22.0 intended record; no new runtime certification in this repair. | AR47: RE-ESTIMATE REQUIRED — v4.11.0 scope delta | AS47: =IF(AM47=1,J47,"") | AT47: =IF(AND(AM47=1,ISNUMBER(R47)),R47,"") | AU47: DESIGN v4.11.0 SCOPE DELTA — SOURCE PREFLIGHT REQUIRED | AY47: NOT ESTIMATED AFTER v4.11.0 | AZ47: Original task closure remains open; new acceptance must be estimated from current source. | BA47: Design v4.11.0 + Industrial Integration review; current implementation source must be preflighted | BB47: 16-Sep-2026 design authority; no live source/runtime certification performed
A48: T-232 | B48: M2 | C48: P2 | D48: Persist Performance Reference authority and projections | E48: Backend / Database | F48: Reference persistence | G48: Critical | H48: Persist the frozen T-214 Performance Reference contract, including declared standards/targets/envelopes, deterministic scope precedence, effective dating, directionality, provenance and projections from existing specifications/operating limits. No second reference authority. | I48: Migration/replay green; Global/Site/Equipment reference precedence and effective-date replay pass; equal-authority ambiguity remains RF01; existing specification/limit projections resolve through one read authority. | J48: 6 | K48: Not Started | L48: Worker 1 | M48: T-090; T-231; T-214 | N48: T-215 | O48: M2: ~1 month from owner planning checkpoint; exact date not committed | P48: Release 1 MUST | Q48: DB/schema authority | R48: 2.55 | S48: M2-P2 | T48: T-090 + T-231 + committed T-214 contract. | U48: performance reference tables/projections/API. | V48: T-215 consumes persistence; no local reference math. | W48: Day-1 Data Workbench — DB Link, Canvas, Jobs & OPC | X48: M2 P2 — Day-1 Data Workbench — DB Link, Canvas, Jobs & OPC. Release 1 is genuine early production / first-week customer work. | AA48: L9.1 | AB48: Performance Reference | AD48: Build | AE48: D1; D3; D4; D5 | AF48: Core | AG48: R1 | AH48: Advances | AI48: =IF(Y48="","",Y48) | AJ48: Inherited baseline estimate | AK48: v4.10.3 | AL48: Chapters 3/4 v4.10.3 — MD + illustrated Word; UI Coverage / UI Controls in this workbook | AM48: =IF(AND(ISNUMBER(J48),OR(AR48="INHERITED ESTIMATE",AR48="CONFIRMED ESTIMATE")),1,0) -> 1 | AO48: Not started — no completion claimed | AP48: Inherited v2.22.0 intended record; no new runtime certification in this repair. | AR48: INHERITED ESTIMATE | AS48: =IF(AM48=1,J48,"") -> 6 | AT48: =IF(AND(AM48=1,ISNUMBER(R48)),R48,"") -> 2.55 | AU48: =IFERROR(INDEX('Source Review'!$B$2:$B$52,MATCH($A48,'Source Review'!$A$2:$A$52,0)),"NOT SOURCE-REVIEWED IN THIS PASS") -> TARGET AUTHORITY NOT LOCATED IN SUPPLIED SNAPSHOT | AV48: =IFERROR(INDEX('Source Review'!$F$2:$F$52,MATCH($A48,'Source Review'!$A$2:$A$52,0)),"") -> 5 | AW48: =IFERROR(INDEX('Source Review'!$G$2:$G$52,MATCH($A48,'Source Review'!$A$2:$A$52,0)),"") -> 8 | AX48: =IFERROR(INDEX('Source Review'!$H$2:$H$52,MATCH($A48,'Source Review'!$A$2:$A$52,0)),"") -> 13 | AY48: =IF(COUNTIF('Source Review'!$A$2:$A$52,$A48)>0,"UNCONFIRMED REVIEW ESTIMATE - not P80 or elapsed","NOT ESTIMATED IN THIS PASS") -> UNCONFIRMED REVIEW ESTIMATE - not P80 or elapsed | AZ48: =IFERROR(INDEX('Source Review'!$I$2:$I$52,MATCH($A48,'Source Review'!$A$2:$A$52,0)),"") -> Persistence/resolution adapter 2/4/7 + projections/refusal tests 2/3/4 + closure 1/1/2. | BA48: =IFERROR(INDEX('Source Review'!$E$2:$E$52,MATCH($A48,'Source Review'!$A$2:$A$52,0)),"") -> Backend/PlantProcess.Infrastructure/Definitions/Semantics/SignalSemanticsResolver.cs:30-74 — existing semantic infrastructure only | BB48: =IF(COUNTIF('Source Review'!$A$2:$A$52,$A48)>0,"14-Sep-2026 snapshot; later closure evidence separate; no live HEAD verification","") -> 14-Sep-2026 snapshot; later closure evidence separate; no live HEAD verification
