Workbook

Sheet Read Me
A1: PlantProcess IQ - Product Backlog v13
A3: WHAT v13 CHANGES (03-Jul-2026, supersedes v12)
A4: 1. NEW TARGET COLUMN: every task carries a meeting target - done / 8-Jul (technical evaluation) / 14-Jul (V2 completion) / post-deal. The 8-Jul meeting (sales + technical engineer) is the V2 AUDIENCE arriving six days early; the backlog is re-cut around it.
A5: 2. SESSION LEDGER RECORDED AS DONE ROWS (V1-31..V1-34): website content refresh; header nav styling drift fix; BOM hygiene test backup exclusion; the Administrator consolidation that mounted the four orphaned journey tabs and gated PPIQ-T### codes + DEMO/DEVELOPMENT badges. Each carries its machine-verified evidence.
A6: 3. GOLDEN-RULE ERADICATION TASKS (V1-35..V1-39): the 03-Jul audit found real demo MACHINERY inside the product (hardcoded scenario fixtures, DemoModeContext, /demo-lifecycle, demo-reset in-app, "Demo Plant") plus generic code trapped in demo-named files, plus a too-narrow CI guard. All violations of the no-demo-code golden rule, now backloged for removal/rename/gating with a strengthened CI gate.
A7: 4. JOB GOVERNANCE (V2-30..V2-33, from the 03-Jul journey spec): interval floors DB-Link 2min / Loading 3min / Engine 20min / AI+ML 60min (config-driven, backend-enforced); per-type max-parallelism + per-SOURCE single-scan lock + start jitter; Loading no-op fast path via watermark compare; Run-now that respects the guards. V1-41 ships the minimum stuck-run reaper for 8-Jul (347 zombie Running rows are live evidence).
A8: 5. STAGE-2 RESHAPED (V2-28): Karim-locked - one Loading job PER MAPPING VIEW with its own watermark, generic projector consumes SchemaViewDefinition, the IF/ELSIF ladder dies, the 8 demo sources become seed mappings. Open decision inside the row: edit-a-mapping reprojection policy (full vs forward-only).
A9: 6. STALE ROWS CORRECTED: V1-09 genealogy foundation is VERIFIED-PRESENT (29-Jun live DB check), not a rebuild; V1-14 action-matrix reopened because the admin surface changed on 03-Jul; V1-17..V1-23 remaining hours reduced to the live-verification effort now that the UI is wired.
A11: HOW TO READ A TASK (unchanged from v12): Description = what a junior/mid dev does, where, and how. Validation/Acceptance = hard, falsifiable checks. Many acceptances demand LIVE HMI behaviour on the demo dataset (code present + tested is not done until proven live).
A13: THE 8-JUL BAR: the engineer clicks every button and questions every value. Ship the 7-step journey live end-to-end, zero dead buttons, no internal codes, no demo machinery behavior, honest states in Jobs Monitor, correlation producing real results, and an assistant that is either verified live or framed honestly. Numbers-fully-justified (Value Engine, universal provenance, generic projector) completes by 14-Jul; for 8-Jul the honesty answer (population + method + abstain) is the shield.

Sheet Backlog
A1: PlantProcess IQ - Product Backlog v13 . 8-Jul technical evaluation re-cut + golden-rule eradication + job governance
A2: Task ID | B2: Version | C2: Phase | D2: Task Name | E2: Persona(s) | F2: Sub-criterion lifted | G2: Gate | H2: Track | I2: Module | J2: Severity | K2: Status | L2: % done | M2: Target | N2: Description (junior-dev-actionable) | O2: Validation / Acceptance (hard, reproducible) | P2: Task Type | Q2: Effort (h) | R2: Remaining (h) | S2: Prereq | T2: Lineage
A3: V1-01 | B3: V1 | C3: V1-P1 Stable environment (nothing breaks) | D3: Local dev reproducibility: EF-first + PGCLIENTENCODING + design-time factory (MERGED) | E3: A1,A4 | F3: A1-2, A1-10 | G3: G9 | H3: Environment | I3: Infra | J3: Critical | K3: MOSTLY-DONE | L3: 0.8 | M3: 14-Jul | N3: MERGES old V1-01+V1-02 and the LOCAL residue of V1-03. The SERVER path is already green (the pipeline runs EF in a sibling before the numbered SQL, handles encoding, and uses ConnectionStrings__PlantProcessDb). Remaining is LOCAL-only and small: (a) fold `dotnet ef database update` into the start of `ppiq.ps1 migrate`/`demo`; (b) export PGCLIENTENCODING=UTF8 before every psql in ppiq.ps1; (c) rewrite PlantProcessDesignTimeDbContextFactory to read ConnectionStrings__PlantProcessDb -> PLANTPROCESS_DESIGNTIME_CONNECTION_STRING -> PLANTPROCESS_DB with an honest error; (d) converge the LOCAL compose remnants (delete duplicate demo-sources fleet + Infrastructure/deploy/docker-compose.demo.yml). Commit so the two session env-vars are no longer needed locally. | O3: From a clean LOCAL DB, `ppiq.ps1 demo` provisions one-shot (EF schema -> SQL decoration -> app on :5063) with ZERO hand-set env vars, twice. grep finds no duplicate demo compose. Evidence: clean-run terminal log + grep. | P3: refactor | Q3: 6 | R3: 1.2 | S3: - | T3: V1-01
A4: V1-02 | B4: V1 | C4: V1-P1 Stable environment (nothing breaks) | D4: Delete env/profiles/local.env (leaks plantprocess123) + rotate | E4: A1,A2 | F4: A2-5 | G4: G12 | H4: Environment | I4: Security | J4: Critical | K4: NEW | L4: 0.1 | M4: 14-Jul | N4: Remove env/profiles/local.env (it carries IsBootstrapAdmin=true and the literal plantprocess123) and rotate any key that ever touched it. Keep only deploy/compose/.env.dev (container-local creds) and the git-ignored server /var/lib/ppiq-preserve/.env. Also strip the stale 4-user set from appsettings.Development.json so it stops shadowing the canonical five locally. | O4: grep finds zero `plantprocess123` and zero `IsBootstrapAdmin=true` in the repo; the startup guard still passes; a bare `dotnet run` shows the canonical five users. Evidence: grep output + boot log. | P4: hardening | Q4: 3 | R4: 2.7 | S4: - | T4: V1-02
A5: V1-03 | B5: V1 | C5: V1-P1 Stable environment (nothing breaks) | D5: Commit LOCAL test config — fix the clean-machine failures (server suite already green) | E5: A1 | F5: A1-2 | G5: G9 | H5: Testing | I5: Testing | J5: Critical | K5: PARTIAL | L5: 0.4 | M5: 14-Jul | N5: The SERVER pipeline already runs the backend (~567) and frontend (202) suites green. The remaining gap is the LOCAL clean-machine path: author committed appsettings.Test.json (DSN + 64-char signing key + a real admin + PPIQ_FORCE_EXTERNAL_API_TEST_HOST) and wire Do-Test so WebApplicationFactory boots the host and finds the DB without per-run env vars. This was the documented cause of the local 83 reds. | O5: `ppiq.ps1 test` exits 0 TWICE on a fresh LOCAL checkout (no hand-set vars). Evidence: two consecutive green run logs. | P5: hardening | Q5: 5 | R5: 3 | S5: V1-01 | T5: V1-03
A6: V1-04 | B6: V1 | C6: V1-P1 Stable environment (nothing breaks) | D6: Persistent infra Caddyfile + correct route targets [NEW 26-Jun] | E6: A2,A4 | F6: A4-9 | G6: G9 | H6: Infra | I6: Infra | J6: Very important | K6: NEW | L6: 0 | M6: 14-Jul | N6: NEW from the 26-Jun session. The live infra Caddyfile is an orphaned inode (host bind source deleted) with STALE targets (plantprocess-app-web, plantprocess-website) that don't match the real containers (plantprocess-web, plantprocess-api); app.* still serves 200 but it's fragile and hot-reloads are non-persistent. Re-establish a persistent host-bound Caddyfile in the infra project with CORRECT targets, so routes survive a Caddy recreate. Do NOT recreate ppiq-caddy until this lands. | O6: After recreating ppiq-caddy, app.*/api.*/website.* all route to the correct live containers; the Caddyfile is host-bound and survives a restart. Evidence: docker exec cat + curl matrix. | P6: hardening | Q6: 6 | R6: 6 | S6: - | T6: V2-13
A7: V1-05 | B7: V1 | C7: V1-P1 Stable environment (nothing breaks) | D7: Harden .env<->Postgres-volume password coupling + provisioning resilience [NEW 26-Jun] | E7: A4 | F7: A4-9 | G7: G9 | H7: Infra | I7: Infra | J7: Important | K7: NEW | L7: 0 | M7: 14-Jul | N7: NEW from the 26-Jun session. Two small hardenings: (1) make ensure-runtime-env.sh PRESERVE POSTGRES_PASSWORD across a stale-key regeneration (today a regen rotates it and diverges from the existing Postgres volume -> 28P01); document the rule that /var/lib/ppiq-preserve/.env must not be deleted, and if it is, the volume must be wiped in the same step. (2) Wrap FirstRunProvisioningHostedService provisioning in try/catch so a provisioning failure logs but never crashes the API at startup. | O7: A simulated stale-key regen keeps the same POSTGRES_PASSWORD and the API still connects; an induced provisioning error is logged and the API still starts. Evidence: regen log + fault-injection test. | P7: hardening | Q7: 5 | R7: 5 | S7: - | T7: V2-14
A8: V1-06 | B8: V1 | C8: V1-P1 Stable environment (nothing breaks) | D8: Spamhaus / outbound-mail relay remediation (relay + SPF/DKIM/PTR + block 25) | E8: A4, A6 | F8: A6.10 CTA/lead capture | G8: G9 | H8: hardening | I8: Infra | J8: Very important | K8: NEW | L8: 0 | M8: 14-Jul | N8: The Hetzner/Spamhaus abuse notice (23 Jun) requires lead-capture email to stop sending direct on port 25. Route all outbound mail (the website lead-capture, V5OutboundLeadSystemEndpoints) through an authenticated transactional relay on 587/465, publish SPF and DKIM DNS records for plantprocessiq.com, set a valid PTR/reverse-DNS for the sending IP, and block outbound port 25 at the firewall. Relay host/port/credentials live in env/secret config, never hardcoded. Confirm delisting with a PUBLIC Spamhaus checker, not Hetzner's resolvers. | O8: A lead submitted on the live site is delivered to the inbox via the 587/465 relay (headers show the relay, not direct 25); `dig TXT` shows valid SPF + DKIM for plantprocessiq.com; the sending IP has a matching PTR; outbound 25 is closed (egress test); a public Spamhaus lookup shows the IP/domain not listed. | P8: hardening | Q8: 5 | R8: 5 | T8: (new)
A9: V1-07 | B9: V1 | C9: V1-P1 Stable environment (nothing breaks) | D9: Phase gate: clean checkout boots seeded + green twice + SERVER deploy green | E9: A1,A4 | F9: A1-2, A1-9 | G9: G9 | H9: Environment | I9: Deploy | J9: Critical | K9: NEW | L9: 0.3 | M9: 14-Jul | N9: End-of-phase regression. LOCAL: clean clone -> `ppiq.ps1 reset && ppiq.ps1 demo` boots the seeded stack; `ppiq.ps1 test` green twice; genealogy walk resolves; capture the `seed exit=0` line. SERVER: confirm `git push` -> Jenkins `plantprocessiq-deploy` reaches PIPELINE GREEN (already true at build #96; the gate is to keep it green after the foundation/test work lands). Seals V1-P1 as deployable in both environments. | O9: All LOCAL gates pass on a fresh machine, scripted, with seed exit=0; the SERVER pipeline is green on the same commit. Evidence: one combined run log + the green Jenkins build. | P9: verification | Q9: 4 | R9: 2.8 | S9: V1-01, V1-03, V1-04 | T9: V1-07
A10: V1-08 | B10: V1 | C10: V1-P1 Stable environment (nothing breaks) | D10: Wire website CTA to a real inbox (CODE DONE — commit + SMTP + relay) | E10: A6 | F10: A6-10 | G10: G8 | H10: Web | I10: Web | J10: Very important | K10: MOSTLY-DONE | L10: 0.65 | M10: 14-Jul | N10: Per the handover the lead-email CODE is DONE and builds clean (V5OutboundLeadSystemEndpoints.cs TrySendLeadEmailAsync; env PlantProcess__Lead__Smtp__*; form POSTs to /api/v5/outbound/leads). Remaining: COMMIT it; supply live SMTP env; do a real-send test. IMPORTANT: route via an authenticated transactional relay (587/465) with SPF+DKIM+PTR and outbound port 25 blocked - never send from the VPS IP (Hetzner/Spamhaus notice). (Hardened backend + e2e assert is the separate V2 task.) | O10: A test submit lands in your inbox/DB via the relay; Spamhaus web-checker shows the IP not listing. Evidence: the received lead + checker screenshot + commit hash. | P10: feature | Q10: 4 | R10: 1.4 | S10: - | T10: V1-18
A11: V1-09 | B11: V1 | C11: V1-P2 The 7-step journey walk (end-to-end, no dead end) | D11: Rebuild mapping/genealogy/safe-SQL foundation (demo-minimum, model-first) [P0 — biggest real gap] | E11: A3,A4 | F11: A3-5, A4-2, A4-6 | G11: G2 | H11: Workflow | I11: Database | J11: Critical | K11: VERIFIED-PRESENT | L11: 0.9 | M11: done | N11: STALE-REBUILD FRAMING CORRECTED (29-Jun live DB check on ppiq_app): the foundation EXISTS and WORKS - ppiq_walk_genealogy (self + both heats for C-0044170 with viaEdgeId provenance), ppiq_resolve_material_by_business_key, ppiq_resolve_safe_sql, ppiq_v5_blended_attribution_for_child (0.70/0.30 across H-3361/H-3362), ppiq_golden_thread, plus ppiq_business_key_definitions / canonical_business_keys / canonical_genealogy_edges / canonical_material_units / genealogy_edges. Remaining: only canonical_mapping_versions (mapping-lifecycle versioning) is absent - defer to V2 (generic projector task); write the one-paragraph verification note into the docs. | O11: SELECT ppiq_walk_genealogy(tenant, 'C-0044170', 'both', 6) returns both heats with provenance; blended attribution returns 0.70/0.30; note committed. No rebuild performed.' | P11: feature | Q11: 4 | R11: 0.5 | S11: V1-01 | T11: V1-04
A12: V1-10 | B12: V1 | C12: V1-P2 The 7-step journey walk (end-to-end, no dead end) | D12: Verify genealogy both directions on C-0044170 live | E12: A3 | F12: A3-5 | G12: G2 | H12: Workflow | I12: FrontEnd | J12: Critical | K12: PARTIAL | L12: 0.85 | M12: 8-Jul | N12: With the foundation rebuilt, walk C-0044170 coil->melt and melt->coils in the running HMI, confirming the Material Investigation evidence panel renders both directions on the customer's own keys. | O12: Recorded walk: both directions resolve on the demo data, no stall. Evidence: clip in the dry-run. | P12: verification | Q12: 2 | R12: 0.3 | S12: V1-04 | T12: V1-05
A13: V1-11 | B13: V1 | C13: V1-P2 The 7-step journey walk (end-to-end, no dead end) | D13: Verify transition-coil weighted attribution (70/30) live | E13: A3 | F13: A3-8 | G13: G15 | H13: Workflow | I13: FrontEnd | J13: Very important | K13: PARTIAL | L13: 0.8 | M13: 8-Jul | N13: Confirm a casting-transition coil reports weighted (e.g. 70/30) attribution across two heats (H-3361/H-3362) with the population/exclusions shown, never a single fabricated heat. The backend test is already green; the live HMI clip is owed. | O13: A transition coil renders weighted provenance + stated population live. Evidence: clip. | P13: verification | Q13: 2 | R13: 0.4 | S13: V1-04 | T13: V1-06
A14: V1-12 | B14: V1 | C14: V1-P2 The 7-step journey walk (end-to-end, no dead end) | D14: App boots under Playwright (no early webServer exit) | E14: A1 | F14: A1-2 | G14: G9 | H14: Testing | I14: Testing | J14: Critical | K14: PARTIAL | L14: 0.55 | M14: 14-Jul | N14: Fix playwright config so webServer starts the API+web and waits for :5063/:5173 instead of exiting early; run at least one real spec against the booted app. | O14: `ppiq.ps1 e2e` starts the app and runs >=1 spec to green. Evidence: Playwright HTML report. | P14: hardening | Q14: 5 | R14: 2.2 | S14: V1-01 | T14: V1-08
A15: V1-13 | B15: V1 | C15: V1-P2 The 7-step journey walk (end-to-end, no dead end) | D15: One-click readiness check passes live | E15: A4 | F15: A4-7 | G15: G7 | H15: Workflow | I15: Backend | J15: Critical | K15: PARTIAL | L15: 0.5 | M15: 8-Jul | N15: Make the readiness surface return green (sources healthy, counts match, jobs ready) in one call on the seeded stack. | O15: Readiness endpoint returns all-green on the demo data, shown live. Evidence: screenshot + clip. | P15: feature | Q15: 5 | R15: 2.5 | S15: V1-04 | T15: V1-09
A16: V1-14 | B16: V1 | C16: V1-P2 The 7-step journey walk (end-to-end, no dead end) | D16: Verify every demo-path button live (click-through) + commit the action-matrix | E16: A3 | F16: A3-1, A3-3 | G16: G6 | H16: Workflow | I16: FrontEnd | J16: Critical | K16: PARTIAL | L16: 0.4 | M16: 8-Jul | N16: The action-matrix was green against the OLD admin surface (Connector Truth | Import Jobs | Tier Override). 03-Jul the Administrator was consolidated to six tabs (DB Configuration | Schema Configuration | Importing Data | Jobs Monitor | Connector Truth | License), so phase9ActionMatrix.ts + phase9-action-matrix.spec.ts must be updated to enumerate the NEW admin controls (every button in all six tabs), then the full click-through re-recorded. | O16: The action-matrix files are committed; every button on the 9-step script performs its action live; 0 unhandled rejections on the path. Evidence: recorded run + commit hash. | P16: verification | Q16: 3 | R16: 3 | S16: V1-04 | T16: V1-10
A17: V1-15 | B17: V1 | C17: V1-P2 The 7-step journey walk (end-to-end, no dead end) | D17: Demo-path robustness fault gate - no crash from user/license/docker/DB | E17: A3, A4 | F17: A3.2 e2e no crash · A4.9 operational resilience | G17: G6 | H17: demo | I17: Testing | J17: Critical | K17: NEW | L17: 0 | M17: 8-Jul | N17: Guarantee the demo path never crashes from any cause a Procurement viewer could trigger. Enumerate the fault classes - bad login, a role/tier-gated control clicked, a license expiry/grace state, a Jenkins/Docker restart mid-session, a transient DB connection drop (the orphan-stack / conn-key / SigningKey issues) - and make each degrade gracefully (typed error, retry, or read-only banner) instead of a white screen, unhandled 500, or dead UI. Add an error boundary on every demo route and health/retry on the API client. This is enforcement, not a one-off fix. | O17: Inducing each fault (kill the API container, expire the license, drop the DB connection, click a gated control as a low-tier role) produces a graceful message and the app recovers when the fault clears - zero white screens, zero uncaught 500s reaching the user, zero frozen buttons. A checklist enumerates every fault class and its observed graceful behaviour. | P17: test | Q17: 6 | R17: 6 | T17: (new)
A18: V1-16 | B18: V1 | C18: V1-P2 The 7-step journey walk (end-to-end, no dead end) | D18: Record the clean dry-run video (insurance) — Karim-owned | E18: A3,A5 | F18: A3-2 | G18: G7 | H18: Demo | I18: Docs | J18: Critical | K18: NEW | L18: 0 | M18: 8-Jul | N18: Per the handover this CANNOT be AI-done. Record an MP4 of the full 9-step walk on the seeded stack against the live server demo URL (app.178.105.152.180.sslip.io) logged in as sysadmin - the pilot acceptance artifact and the backup if live ever fails. Blocks the demo-reel cut. | O18: MP4 exists; no dead click; matches the script. Evidence: the file. | P18: content | Q18: 3 | R18: 3 | S18: V1-10 | T18: V1-11
A19: V1-17 | B19: V1 | C19: V1-P2 The 7-step journey walk (end-to-end, no dead end) | D19: J1 - Auto-login lands on a working home (sysadmin, no login page) | E19: A4, A3 | F19: A2.4 token/session | G19: G12 | H19: workflow | I19: FrontEnd | J19: Important | K19: PARTIAL | L19: 0.7 | M19: 8-Jul | N19: Verify + harden step 1: the app auto-authenticates as the permanent sysadmin (FirstRunProvisioning SOU support account) and lands directly on a populated, navigable home - no login page in V1. No 401, no blank screen, no console error on first load. The auto-login uses the real auth/session machinery (signed token + __Host- cookie), not a bypass. | O19: A cold load of the demo URL reaches a working authenticated home as sysadmin with the nav visible and at least one populated panel; no login prompt appears; the browser console shows no errors; the session is a real signed token (verifiable in the cookie), not a stub. | P19: test | Q19: 2 | R19: 0.6 | T19: (new)
A20: V1-18 | B20: V1 | C20: V1-P2 The 7-step journey walk (end-to-end, no dead end) | D20: J2 - Connect + select the demo data source(s) via the DB Configuration tab | E20: A4, A3 | F20: A4.1 source onboarding HMI | G20: G1 | H20: workflow | I20: FrontEnd | J20: Critical | K20: PARTIAL | L20: 0.6 | M20: 8-Jul | N20: UI now mounted (03-Jul consolidation) - remaining is the LIVE walk: register a source, test-connect (incl. against a stopped container -> typed error), table picker populates from live source metadata. PRIOR SCOPE: Verify + harden step 2: the DB Configuration tab (AdminDbConfigurationTab.tsx, 1126 lines) lets the user register/select one, two, or all 8 demo sources, run a connection test, and choose which tables to import. Confirm the tab invokes the connector/registry backend (ConnectorAdminEndpoints -> ppiq_register_dump_source / ProvisionBaseline) and shows a clear success/failure state. Fix any dead control, any test button that does nothing, any table-picker that does not populate. The 6 connectors (Csv/Excel/MySql/Oracle/Postgres/historian) already exist - this is wiring + UX verification. | O20: From the HMI: select a demo source, run the connection test and see a green result; choose tables and see them registered (verify via SELECT * FROM source_table_dump_registry); repeat for two and for all eight; every control does something (no dead button); a deliberately bad connection shows a typed error, not a crash. | P20: test | Q20: 4 | R20: 1 | T20: (new)
A21: V1-19 | B21: V1 | C21: V1-P2 The 7-step journey walk (end-to-end, no dead end) | D21: J3 - Run Stage-1 import to staging + see it in Jobs Monitor + job log | E21: A4, A3 | F21: A4.4 Jobs Monitor | G21: G1 | H21: workflow | I21: FrontEnd | J21: Critical | K21: PARTIAL | L21: 0.5 | M21: 8-Jul | N21: Scheduling UI now reachable via Importing Data tab - remaining is the live Stage-1 run + incremental second-run proof (watermark tail-only). PRIOR SCOPE: Verify + harden step 3: trigger Stage-1 (ppiq_run_stage1_delta_import) from the Importing Data tab; confirm the dump/staging tables fill, the Jobs Monitor tab (AdminJobsMonitorTab 350) + TwoStageImportMonitorPanel (376) show last-run status/duration/rows, and the job log records the run. Confirm incremental behaviour: a second run imports only the new tail (two_stage_processed_watermarks / last-index comparison), not the whole table. | O21: A Stage-1 run populates staging (row count > 0 in the dump tables); the Jobs Monitor shows the run with status, rows, duration; a second immediate run imports 0 or only-new rows (watermark proven); the job log has an Info entry; a forced failure (bad source) shows an Error entry in the monitor and the log. | P21: test | Q21: 4 | R21: 1.5 | T21: (new)
A22: V1-20 | B22: V1 | C22: V1-P2 The 7-step journey walk (end-to-end, no dead end) | D22: J4 - No-code Mapper UI loads the demo staging schema and previews/joins/filters | E22: A4, A3 | F22: A3.4 widget/mapping config | G22: G2 | H22: workflow | I22: FrontEnd | J22: Critical | K22: PARTIAL | L22: 0.5 | M22: 8-Jul | N22: Verify + harden step 4: the Schema Configuration tab (AdminSchemaConfigurationTab.implementation.generated 955) + CanonicalSchemaMappingPanel (514) + V5NoCodeMapperPage must read the real demo STAGING schema (tables + columns from the dump), let the user define a view/join/filter, preview rows, and validate via SafeSqlValidator/SqlAllowlistProvider. This is the verify-needed seam: confirm the UI binds to live staging metadata, not a placeholder. Fix any panel that loads empty. | O22: On the demo staging data the mapper lists the actual source tables and columns; defining a view previews real rows; a join across two dump tables previews correctly; a malformed SQL is rejected by safe-SQL with a typed error (not a 500); no dead control on the tab. | P22: test | Q22: 6 | R22: 2.5 | T22: (new)
A23: V1-21 | B23: V1 | C23: V1-P2 The 7-step journey walk (end-to-end, no dead end) | D23: J5 - Run Stage-2 canonical refresh + monitor + log (TEMP demo shapes - V1 ONLY) | E23: A4, A3 | F23: A4.4 Jobs Monitor | G23: G2 | H23: workflow | I23: FrontEnd | J23: Critical | K23: PARTIAL | L23: 0.5 | M23: 8-Jul | N23: GENERIC-ONLY RED LINE: the hardcoded demo-shape projection used here is a TEMPORARY V1-ONLY measure to hit 1 Jul and MUST be eradicated in V2 (see the V2 generic-projector task). | O23: nan | P23: test | Q23: 4 | R23: 2 | T23: (new)
A24: V1-22 | B24: V1 | C24: V1-P2 The 7-step journey walk (end-to-end, no dead end) | D24: J6 - Build/open a dashboard + widget bound to the freshly-imported canonical data | E24: A4, A3 | F24: A3.1 zero dead buttons | G24: G3 | H24: workflow | I24: FrontEnd | J24: Critical | K24: PARTIAL | L24: 0.4 | M24: 8-Jul | N24: Verify + harden step 6: on the now-populated canonical data, create a page (PageBuilderPage.implementation 435), drag a widget (WidgetBuilder wizard - data/filter/preview steps), bind it to a canonical view via the widget script layer (WidgetScriptSqlCompiler 240), and save. CRITICAL seam-6 check: confirm widgets read the canonical_* views that Stage-2 populates - NOT pre-seeded tables - so a live re-import visibly changes the widget. Use DashboardGridLayout (552-state) for drag-drop persistence. | O24: A newly created page+widget renders rows that came through the import; re-running the import and refreshing visibly changes the widget's numbers (proving it reads canonical views, not seed); save+reload persists the page and layout; no dead button in the page/widget builder; the widget's query passes the safe-SQL compiler. | P24: test | Q24: 6 | R24: 3 | T24: (new)
A25: V1-23 | B25: V1 | C25: V1-P2 The 7-step journey walk (end-to-end, no dead end) | D25: J7 - Run a correlation / inspection + read grounded results on the imported data | E25: A4, A3 | F25: A3.7 correlation honest | G25: G4 | H25: workflow | I25: FrontEnd | J25: Critical | K25: PARTIAL | L25: 0.5 | M25: 8-Jul | N25: Verify + harden step 7: from Advanced Analysis (AdvancedAnalysisPage 214) + Inspection Jobs (InspectionJobsPage 88), configure an inspection (a defect/downtime/KPI + a duration window), run it on the imported canonical data using the already-built engines (CorrelationService 564 + AdvancedCorrelationComputeService 390), and read a grounded suspected-contributor result. The GroundedAssistantPage (129) must explain it with citations and render no uncited number (GroundingService). Wire the engines to the imported demo data live. | O25: An inspection job runs on imported data and returns a suspected contributor with population + method shown (Spearman/MI/etc., q-value, bootstrap stability); the grounded assistant explains it citing evidence handles and renders no uncited number; clicking a number opens its provenance; results match the demo expectation (the defect linked to its superheat driver). | P25: test | Q25: 5 | R25: 2.5 | T25: (new)
A26: V1-24 | B26: V1 | C26: V1-P2 The 7-step journey walk (end-to-end, no dead end) | D26: J-WALK - End-to-end journey walk under induced faults (the no-dead-end gate) | E26: A4, A3 | F26: A3.2 e2e no crash | G26: G6 | H26: workflow | I26: Testing | J26: Critical | K26: NEW | L26: 0 | M26: 8-Jul | N26: The actual V1 test: walk all 7 steps as ONE continuous flow on a clean demo stack (source -> staging -> map -> canonical -> dashboard -> analysis), then induce the fault classes (bad login, role/tier gate, container restart, DB blip) at each step. Enumerate EVERY break, dead button, and crash in ONE pass (preventive-maintenance mandate - do not fix one runtime error at a time) and fix each at source. This gate is the no-dead-end guarantee for the Procurement demo. | O26: The full source-to-analysis walk completes with zero dead buttons, zero white screens, zero uncaught 500s reaching the user; each induced fault degrades gracefully and the stack recovers when it clears; ppiq e2e and the dead-button scanner are both clean; a recorded walk shows no dead click. | P26: test | Q26: 6 | R26: 6 | T26: (new)
A27: V1-25 | B27: V1 | C27: V1-P3 Presentation pack (deck, ROI, video) | D27: Finalize the 9-step demo script (DELIVERED — fill 2 placeholders) | E27: A5 | F27: C5 | G27: G7 | H27: Demo | I27: Docs | J27: Very important | K27: MOSTLY-DONE | L27: 0.8 | M27: 8-Jul | N27: Per the handover the script PlantProcess-IQ-Live-Demo-Script.md is DELIVERED (connect->map->build page->...). Remaining: fill the 2 placeholders (roadmap specifics + your real per-plant price) and rehearse it cold once, including the surprise-question answers (incl. the new 'do you ship a customer-usable admin?' -> no; only the sysadmin support account, customer admin added at commissioning). | O27: You run it cold once end-to-end with the placeholders filled. Evidence: the script doc + a rehearsal note. | P27: content | Q27: 2 | R27: 0.4 | S27: V1-11 | T27: V1-12
A28: V1-26 | B28: V1 | C28: V1-P3 Presentation pack (deck, ROI, video) | D28: Finalize the ROI model + slide (DELIVERED — fill real price) | E28: A5 | F28: A5-1, A5-7 | G28: G5 | H28: Web | I28: Docs | J28: Very important | K28: MOSTLY-DONE | L28: 0.8 | M28: 8-Jul | N28: Per the handover PlantProcess-IQ-ROI-Model.xlsx + PlantProcess-IQ-ROI-Slide.pptx are DELIVERED (base case EUR 480,000/yr vs a EUR 300k placeholder price; labelled projected-not-proven). Remaining: replace the placeholder price with your real per-plant price and re-verify the figure still exceeds it. Also fits the 07-editions-and-licensing doc (which carries [[PER_PLANT_ACV_RANGE]]). | O28: The model + slide carry a defensible EUR/yr number against your real price, assumptions stated, tied to the demo finding. Evidence: the files. | P28: content | Q28: 4 | R28: 0.8 | S28: - | T28: V1-13
A29: V1-27 | B29: V1 | C29: V1-P3 Presentation pack (deck, ROI, video) | D29: Finalize the founder credibility pack (DELIVERED as 09-founder doc — fill background) | E29: A5 | F29: A5-10 | G29: - | H29: Web | I29: Docs | J29: Very important | K29: MOSTLY-DONE | L29: 0.8 | M29: 8-Jul | N29: The customer doc 09-founder-and-company.md is DELIVERED and on-brand. Remaining: fill [[YEARS]] and [[BACKGROUND_DETAIL]] (your 14 yrs PSI Metals / SMS / EzzSteel, named plants/processes), [[COMPANY_LOCATION]], [[CONTACT_NAME_AND_EMAIL]], [[WEBSITE_URL]]; optionally produce the one-slide version placed before the offer slide. | O29: The doc (and optional slide) has your named plants + contact filled; on-brand. Evidence: the file. | P29: content | Q29: 2 | R29: 0.4 | S29: - | T29: V1-14
A30: V1-28 | B30: V1 | C30: V1-P3 Presentation pack (deck, ROI, video) | D30: Technical annex to the 1-Jul deck (engineer/CEO audience: architecture, stats methods, security) | E30: A5,A6 | F30: A6-1 | G30: G8 | H30: Web | I30: Docs | J30: Very important | K30: NEW | L30: 0 | M30: 8-Jul | N30: The 22-slide procurement deck exists (1-Jul). For 8-Jul add a short technical annex: architecture/topology slide (read-only, OT-safe, two-stage pipeline), statistics discipline slide (methods, FDR, readiness gates, abstain), security slide (Argon2id, signed license, RBAC, no-egress AI), and the honest-status slide (implemented vs validation-ongoing, per capability with data volumes). Fix contact placeholders (email/phone) from slide 22. | O30: Rehearsed once; <=12 slides; on-brand. Evidence: the file. | P30: content | Q30: 3 | R30: 3 | S30: - | T30: V1-15
A31: V1-29 | B31: V1 | C31: V1-P3 Presentation pack (deck, ROI, video) | D31: Finalize the pilot offer (DELIVERED as 08-pilot doc — fill price/customer) | E31: A5 | F31: A5-7 | G31: - | H31: Web | I31: Docs | J31: Very important | K31: MOSTLY-DONE | L31: 0.8 | M31: 8-Jul | N31: The customer doc 08-pilot-offer.md is DELIVERED (read-only, time-boxed, fee-credited-on-conversion; scope/success/commercials tables). Remaining: fill [[PILOT_FEE]] (lean EUR30k for the first), [[CONVERSION_TARGET]] (the EUR120k/yr figure), [[CUSTOMER_NAME]], [[PILOT_DURATION]], and the source/target-question specifics per prospect. | O31: One offer with the price + conversion figure + ask filled for a named prospect. Evidence: the file. | P31: content | Q31: 2 | R31: 0.4 | S31: - | T31: V1-16
A32: V1-30 | B32: V1 | C32: V1-P3 Presentation pack (deck, ROI, video) | D32: Cut the 2-3 minute demo video (blueprint delivered) | E32: A6 | F32: A6-10 | G32: G8 | H32: Web | I32: Docs | J32: Important | K32: NEW | L32: 0 | M32: 14-Jul | N32: Per the handover the cut sheet PlantProcess-IQ-Demo-Reel-CutSheet.md is DELIVERED (2:45 EDL + VO + export + 'no dead click' QC). The MP4 render is yours and depends on the V1-13 recording. | O32: 2-3 min MP4; no dead click. Evidence: the file. | P32: content | Q32: 3 | R32: 3 | S32: V1-11 | T32: V1-17
A33: V1-31 | B33: V1 | C33: V1-P3 Presentation pack (deck, ROI, video) | D33: DONE 03-Jul: Website content refresh (aim/features/value-chain/pricing/diagram) | E33: A6 | F33: A6-6, A6-7 | G33: G14 | H33: Web | I33: Web | J33: Critical | K33: DONE | L33: 1 | M33: done | N33: Rewrote phase1WebsiteProof.ts + App.tsx + PricingLicenseMatrix + Showcase: canonical-tagline hero, How-It-Works 6-step pipeline, Beyond-BI differentiator (correlation/suggestions/grounded AI, "implemented, validation ongoing"), Proven-At-Scale (11,997/1,993/5,688/6), pricing rebuilt to locked deposit+subscription (Standard 12k+6k / Pro Plus 28k+14k Recommended / Enterprise 50k+25k), connector truth updated (PG/MSSQL/MySQL/Oracle run live in demo env). Content validator updated in the same change. | O33: validate-website-content.mjs PASS (80 checks incl. new tier/value-chain/AI-honesty needles); check-tagline PASS; tsc+vite build PASS on target machine 03-Jul 11:12. | P33: modification | Q33: 5 | R33: 0 | T33: NEW 03-Jul
A34: V1-32 | B34: V1 | C34: V1-P3 Presentation pack (deck, ROI, video) | D34: DONE 03-Jul: Header nav styling drift fix (.site-nav never styled) | E34: A6 | F34: A6-8 | G34: G14 | H34: Web | I34: Web | J34: Very important | K34: DONE | L34: 1 | M34: done | N34: Root cause: markup uses .site-nav/.phase10-nav but only .nav-links was ever styled -> raw underlined links, brand text inline. Appended nav-polish CSS (pill links, hover, cyan active, brand column stack, sticky border) to phase10.css, idempotent marker. | O34: Header renders spaced pill links with active page highlighted; validators green; applied 03-Jul. | P34: bug fix | Q34: 2 | R34: 0 | T34: NEW 03-Jul
A35: V1-33 | B35: V1 | C35: V1-P1 Stable environment (nothing breaks) | D35: DONE 03-Jul: BOM hygiene test excludes deploy\.ppiq-backups (+ stray BOM stripped) | E35: A1 | F35: A1-2 | G35: G9 | H35: Testing | I35: Backend | J35: Very important | K35: DONE | L35: 1 | M35: done | N35: Utf8NoBomRepositoryHygieneTests skip-list lacked .ppiq-backups, so ANY backup of a .sql/.json broke the suite (conflicts with backup-before-edit mandate). Added StartsWith deploy\.ppiq-backups + Contains \.ppiq-backups mirroring the existing pattern; stripped the BOM from stage2_fn_dump.sql. | O35: dotnet test --filter Utf8NoBomRepositoryHygieneTests PASS; full suite no longer fails on backups. | P35: bug fix | Q35: 1 | R35: 0 | T35: NEW 03-Jul
A36: V1-34 | B36: V1 | C36: V1-P2 The 7-step journey walk (end-to-end, no dead end) | D36: DONE 03-Jul: Consolidated Administrator - journey tabs wired; internal codes + env badges gated | E36: A3,A4 | F36: A4-1, A3-1 | G36: G6 | H36: Workflow | I36: FrontEnd | J36: Critical | K36: DONE | L36: 1 | M36: done | N36: Root cause of "Test Journey not implemented": three competing admin surfaces; the routed one was the shallow demo-orchestration page while DbConfigurationTab (1150), SchemaConfigurationTab (955), ImportingDataTab, JobsMonitorTab were mounted nowhere. AdminPageContent now mounts all four + Connector Truth + honest read-only License card. PageShell task eyebrows render only under VITE_SHOW_TASK_CODES=1; AppLayout DEVELOPMENT/DEMO/tier badges only under VITE_SHOW_ENVIRONMENT_BADGES=1 (data-* attrs preserved for e2e). | O36: tsc clean, vite build clean, vitest 202/202 PASS on target machine 03-Jul 13:05; /admin shows six tabs; no PPIQ-T### or DEMO/DEVELOPMENT badges visible. | P36: bug fix | Q36: 6 | R36: 0 | T36: NEW 03-Jul; unblocks V1-18..V1-24
A37: V1-35 | B37: V1 | C37: V1-P3 Product truth & golden rule (03-Jul findings) | D37: Demo-layer eradication A: remove demo MACHINERY from the app (golden rule) | E37: A1,A3 | F37: A1-6 | G37: G6 | H37: Hardening | I37: FrontEnd | J37: Critical | K37: NEW | L37: 0 | M37: 8-Jul | N37: Per the golden rule (no demo code/page/path/mode in the product, demo = external emulated sources only): remove src/demo/plantProcessDemoScenario* (hardcoded fake scenario fixtures consumed by DemoModeContext + LockedFeatureOverlay - fabricated state in the product), remove state/DemoModeContext (unwire from App.tsx + AppLayout), components/demo/* (EnvironmentBanner/ModeControl/ReadinessPanel/LifecycleKpiStrip), the /demo-lifecycle route + DemoLifecyclePage, api/demo/*. Demo-RESET moves OUT of the app into tools/ (PowerShell + compose script that resets the emulation source containers + re-seeds) - Karim decision pending: default = delete-from-app. LockedFeatureOverlay must read real license state, never scenario fixtures. | O37: grep -ri "demoScenario|DemoModeContext|demo-lifecycle" src/ returns ONLY the architecture test; tsc+build+vitest green; LockedFeatureOverlay renders from LicenseContext live; tools/reset-emulation-sources.ps1 resets + reseeds the fleet. | P37: refactor | Q37: 8 | R37: 8 | S37: V1-34 | T37: NEW 03-Jul audit
A38: V1-36 | B38: V1 | C38: V1-P3 Product truth & golden rule (03-Jul findings) | D38: Demo-layer eradication B: rename generic code trapped in demo-named files | E38: A1 | F38: A1-4 | G38: G6 | H38: Hardening | I38: FrontEnd | J38: Very important | K38: NEW | L38: 0 | M38: 14-Jul | N38: Class-1 renames with all references updated: DemoAnalyticsPages(.implementation) -> PlatformOpsPages; DemoAnalyticsWorkflowTruthPage -> ConnectorTruthPage; demo-analytics.css -> platform-ops.css; api/demo-analytics/demoAnalytics.api.ts -> split generic Suggestions/DynamicPage endpoints into platformOps.api.ts; Phase10LicenseDemoPage -> CommercialLicenseShowcasePage (also kills a phase code). Naming Golden Rule applies; customer must never see "demo" in a route, title, or bundle chunk name. | O38: No file/route/component in src/ contains "demo" except the architecture test + allowlist; bundle chunk names contain no Demo*; tsc+build+vitest green; /admin Connector Truth tab unchanged visually. | P38: refactor | Q38: 6 | R38: 6 | S38: V1-35 | T38: NEW 03-Jul audit; feeds V2-24
A39: V1-37 | B39: V1 | C39: V1-P3 Product truth & golden rule (03-Jul findings) | D39: Strengthened NO-DEMO-CODE CI gate (the guard that failed) | E39: A1 | F39: A1-2 | G39: G6 | H39: Hardening | I39: Testing | J39: Very important | K39: NEW | L39: 0 | M39: 14-Jul | N39: noHardcodedDemoPages.test.ts passed while the whole demo layer existed - its rule is too narrow. Rewrite as a real gate: FAIL if any file/symbol/route under src/ matches (?i)demo (allowlist: the test itself + an explicit documented list, empty after V1-35/36); FAIL on fixture datasets imported by product components. Wire into vitest architecture suite + the repo guard script so CI blocks regressions. | O39: Introduce a dummy src/pages/DemoFoo.tsx -> vitest fails with a clear message; remove it -> green. Gate runs in the Jenkins frontend stage. | P39: test | Q39: 3 | R39: 3 | S39: V1-36 | T39: NEW 03-Jul
A40: V1-38 | B40: V1 | C40: V1-P3 Product truth & golden rule (03-Jul findings) | D40: Plant display name from configuration (kill hardcoded "Demo Plant") | E40: A1,A6 | F40: A1-6 | G40: G6 | H40: Workflow | I40: FrontEnd | J40: Important | K40: NEW | L40: 0 | M40: 8-Jul | N40: AppLayout hardcodes "Demo Plant" in the plant strip. Plant/site display name must come from configuration (site/tenant record in ppiq_meta via an existing overview endpoint, fallback to a neutral default like the tenant name). Generic for mineral-water/cars/food installs. | O40: Change the site name in DB/config -> sidebar shows it after reload; grep "Demo Plant" in src/ returns nothing. | P40: modification | Q40: 3 | R40: 3 | T40: NEW 03-Jul
A41: V1-39 | B41: V1 | C41: V1-P3 Product truth & golden rule (03-Jul findings) | D41: Remove the duplicate Phase56 Administrator (dead Run button) + review AdminPreview | E41: A1,A3 | F41: A3-1 | G41: G6 | H41: Hardening | I41: FrontEnd | J41: Important | K41: NEW | L41: 0 | M41: 8-Jul | N41: Phase56AdministratorPage duplicates the admin surface with read-only tables and a Run button with NO onClick (dead button - engineer-facing liability). Delete it (or reduce to a component reused by tests) and remove its route/usages; review AdminPreviewWorkspacePage for the same fate. One admin surface only (the 03-Jul consolidation). | O41: grep Phase56AdministratorPage src/ -> only history; no route serves it; dead-button-scan clean on /admin*; tsc+build+vitest green. | P41: refactor | Q41: 2 | R41: 2 | S41: V1-34 | T41: NEW 03-Jul
A42: V1-40 | B42: V1 | C42: V1-P3 Product truth & golden rule (03-Jul findings) | D42: Permanent launcher fix: start-web.ps1 / start-website.ps1 stop passing positional args | E42: A1 | F42: A1-10 | G42: G9 | H42: Environment | I42: Infra | J42: Important | K42: NEW | L42: 0 | M42: 8-Jul | N42: Launchers run "vite localhost 5173" positionally; Vite 5+ rejects (CACError: Unused args). Fix to npm run dev -- --host $env:VITE_HOST --port $env:VITE_PORT (defaults if unset); same for website (5080). Also fold the drafted ppiq-run.ps1 (three windows via Start-Process) in as the one-command dev start. | O42: Fresh clone: .\scripts\run\start-web.ps1 serves http://localhost:5173 with zero manual args; same for website on 5080. | P42: bug fix | Q42: 1 | R42: 1 | T42: NEW 03-Jul from 02-Jul handover
A43: V1-41 | B43: V1 | C43: V1-P2 The 7-step journey walk (end-to-end, no dead end) | D43: Stuck-run reaper (minimum viable): zombie Running -> Failed(timeout), clean the 347 | E43: A4 | F43: A4-4 | G43: G7 | H43: Hardening | I43: Backend | J43: Critical | K43: NEW | L43: 0 | M43: 8-Jul | N43: ml_correlation_compute_runs holds 347 rows stuck "Running" - there is no max-runtime. Minimum for 8-Jul: (1) per-job-type max-runtime config (default e.g. Engine 30min); (2) a reaper (hosted service or the existing scheduler tick) transitions over-age Running -> Failed with reason "timeout", logged; (3) one-off ops migration marks the existing 347 zombies Failed(timeout-backfill); (4) Jobs Monitor shows the honest state. Full governance (floors/locks/jitter) stays V2-30..V2-33. | O43: Induce a hung run (sleep in a test hook) -> reaper flips it to Failed(timeout) within one tick; SELECT count(*) FROM ml_correlation_compute_runs WHERE status='Running' AND started < now()-maxage returns 0; monitor renders the state. | P43: new feature | Q43: 6 | R43: 6 | T43: NEW 03-Jul; lineage -> V2-30
A44: V1-42 | B44: V1 | C44: V1-P2 The 7-step journey walk (end-to-end, no dead end) | D44: Correlation run-to-result completes E2E on imported demo data (0 results today) | E44: A3 | F44: A3-7 | G44: G7 | H44: AI+ML | I44: Backend | J44: Critical | K44: NEW | L44: 0 | M44: 8-Jul | N44: Despite 358 attempted runs, ml_correlation_results_v2 and correlation_results are EMPTY locally - the run-to-result path has never completed. Root-cause (likely readiness gate/blocked inputs vs the stuck-run defect), fix at source, and prove: run the full journey (import -> canonical), start an inspection job from the HMI, engine completes, results rows written, result page renders ranked suspected contributors with population + method + q-values. This is the #1 AI-scrutiny item for 8-Jul. | O44: After a clean journey: inspection job status Ok; ml_correlation_results_v2 > 0 for the run; CorrelationPage tab renders the ranked list with AnalysisHonestyBar; re-run with a changed duration window recomputes. | P44: bug fix | Q44: 8 | R44: 8 | S44: V1-19,V1-21,V1-41 | T44: NEW 03-Jul
A45: V1-43 | B45: V1 | C45: V1-P2 The 7-step journey walk (end-to-end, no dead end) | D45: Assistant provider wiring verified live (or framed "grounding implemented, provider validation ongoing") | E45: A3,A5 | F45: A5-4 | G45: G8 | H45: AI+ML | I45: Backend | J45: Very important | K45: NEW | L45: 0 | M45: 8-Jul | N45: 02-Jul left open: ppiq_assistant_provider_configs schema differs from assumed (no is_active) and live model wiring was never confirmed. Verify the real schema, wire ONE provider (self-hosted default or zero-retention endpoint) through V5AssistantGateway, and run one grounded Q&A live over engine results (citations resolve, uncited numbers blocked). If wiring cannot be completed by 8-Jul, lock the honest framing in the script instead - never demo an unverified assistant. | O45: One live question over imported demo data returns a cited answer whose citation opens the evidence; egress guard verified for the no-egress toggle; OR the demo script carries the fallback framing verbatim. | P45: new feature | Q45: 4 | R45: 4 | S45: V1-42 | T45: NEW 03-Jul from 02-Jul handover
A46: V2-01 | B46: V2 | C46: V2-P3 Value engine & justified numbers | D46: Wire + prove the Value Engine LIVE on demo data (engine already built) | E46: A5, A3 | F46: A5.1 quantified value · A5.7 price-to-value | G46: G5 | H46: AI+ML | I46: Backend | J46: Critical | K46: PARTIAL | L46: 0.7 | M46: 14-Jul (honest framing ready for 8-Jul) | N46: CODE-VALIDATED: ValueImpactEngine.cs is BUILT (bounded Low/Expected/High, ABSTAINS on missing assumptions, attaches a provenance handle + input JSON per term, monotonic guard); ValueRealizationContracts.cs adds the realized-value ledger; ValueHonestyLint blocks forbidden phrases. DO NOT rebuild. LAST MILE: (1) populate ValueImpactInputs + CostAssumptionSet from the DEMO dataset and the real per-plant rates (not BuildDemoRequest); (2) surface the result in a Value dashboard widget with drill-through to each term's input JSON; (3) prove the worked euro range reproduces LIVE through the HMI on a finding for C-0044170; (4) confirm MapValueEndpoints / MapP15ValueRealizationEndpoints return it on demo data. | O46: LIVE on the demo dataset: a defect finding on C-0044170 yields a bounded euro range in the HMI; each term drills through to its input JSON + provenance handle; removing a required assumption flips the widget to the explicit abstain message (never a fabricated number); an e2e spec asserts both the live range and the abstain branch. | P46: new feature | Q46: 10 | R46: 3 | T46: (new)
A47: V2-02 | B47: V2 | C47: V2-P3 Value engine & justified numbers | D47: Extend the grounding contract to ALL widgets (render-time uncited-number gate) | E47: A5, A3 | F47: A5.4 trustworthy AI · A3.6 population stated | G47: G4 | H47: AI+ML | I47: Backend | J47: Very important | K47: PARTIAL | L47: 0.55 | M47: 14-Jul (honest framing ready for 8-Jul) | N47: CODE-VALIDATED: GroundingService.cs already blocks uncited numbers (every number must trace to a claim handle), blocks causation language, drops synthetic claims, refuses honestly. DO NOT rebuild the contract. Lift the SAME mechanism from the assistant to EVERY surfaced number across dashboards: each KPI/chart-series/tile/cell carries a resolvable provenance handle or is not rendered. Add a render-time guard plus a CI gate enumerating demo-path widgets that fails on any uncited numeric. | O47: A CI gate asserts 0 uncited numerics on the demo path; clicking any number/graph/tile opens its provenance handle resolving to a real source; a deliberately uncited test value is BLOCKED from render (negative test); the implementation reuses GroundingService's proven logic, not a parallel one. | P47: hardening | Q47: 8 | R47: 3.6 | T47: (new)
A48: V2-03 | B48: V2 | C48: V2-P3 Value engine & justified numbers | D48: Wire + expose L4 statistics LIVE (Spearman/MI/Lasso/VIF/bootstrap/FDR already built) | E48: A3 | F48: A3.7 correlation/ML honest | G48: G4 | H48: AI+ML | I48: Backend | J48: Very important | K48: PARTIAL | L48: 0.7 | M48: 14-Jul (honest framing ready for 8-Jul) | N48: CODE-VALIDATED: AdvancedCorrelationComputeService.cs (390) is BUILT - Spearman, Pearson/point-biserial, normalized MI, Cramer's V, iterative VIF, Lasso, Benjamini-Hochberg FDR, bootstrap stability, stratification. Update Doctrine sec.21 ('unstarted' is wrong). Remaining: run a correlation/inspection job LIVE on demo data through the HMI and surface the suspected contributor (method, q, bootstrap %, strata, excluded records) in 'suspected contributor' language; expose the VIF/Lasso exclusions and FDR q-values in the result UI. | O48: A correlation job recomputes LIVE on demo data and the HMI shows a suspected contributor with the method named, q<0.05 under BH-FDR, bootstrap stability %, stratified, population/exclusions stated; a golden dataset recovers true signals and rejects spurious ones under FDR; the engine test is extended to assert the LIVE surface, not just the compute. | P48: test | Q48: 6 | R48: 1.8 | T48: (new)
A49: V2-04 | B49: V2 | C49: V2-P3 Value engine & justified numbers | D49: Sharpen AI/ML results: calibration, effect-size ranking, stratified quality | E49: A3 | F49: A3-7 | G49: G4 | H49: AI+ML | I49: AI+ML | J49: Very important | K49: NEW | L49: 0 | M49: 14-Jul | N49: Improve the learning output: calibrated scores, effect-size (not just p-value) ranking, stratified quality by visible confounders, under BH-FDR - framed as suspected contributors. The 06-analytics-methodology doc already commits to this posture. | O49: On the golden dataset, true signals are recovered and spurious rejected under FDR; results show effect size + stratification. Evidence: golden-set test + clip. | P49: feature | Q49: 12 | R49: 12 | S49: V1-04 | T49: V2-17
A50: V2-05 | B50: V2 | C50: V2-P3 Value engine & justified numbers | D50: Impressive evidence-ranked suggestion engine (deterministic, euro impact) | E50: A3,A5 | F50: A5-1 | G50: G4 | H50: AI+ML | I50: AI+ML | J50: Very important | K50: PARTIAL | L50: 0.55 | M50: 14-Jul | N50: Deterministic, MD5-stable suggestions ranked by evidence + euro impact, workflow-bound with RBAC, surfaced in SuggestionCardsPanel - the 'told me something I didn't know, and proved it' moment. | O50: Suggestions render with population, method, evidence handle and a euro range; reproducible IDs. Evidence: test + clip. | P50: feature | Q50: 10 | R50: 4.5 | S50: V1-04 | T50: V2-18
A51: V2-06 | B51: V2 | C51: V2-P3 Value engine & justified numbers | D51: Assistant eval harness + model-version governance gate | E51: A2,A5 | F51: A5-4 | G51: G13 | H51: AI+ML | I51: Testing | J51: Important | K51: NEW | L51: 0 | M51: 14-Jul | N51: An eval harness that gates assistant regressions and a model-version governance gate (no uncited number, citations resolve). | O51: The harness fails on an injected uncited-number regression; passes clean. Evidence: the harness + CI. | P51: feature | Q51: 6 | R51: 6 | S51: - | T51: V2-19
A52: V2-07 | B52: V2 | C52: V2-P4 Completeness + performance/speed | D52: Full backend+frontend suite green twice on clean machine (local) | E52: A1 | F52: A1-2 | G52: G9 | H52: Testing | I52: Testing | J52: Critical | K52: PARTIAL | L52: 0.3 | M52: 14-Jul | N52: Server suite is green; close the LOCAL clean-machine path so the whole backend+frontend suite runs green twice on a fresh checkout with no hand-set vars. Builds on the local test-config task. | O52: Both suites exit 0 twice on a fresh local machine. Evidence: two green logs. | P52: hardening | Q52: 10 | R52: 7 | S52: V1-03 | T52: V2-01
A53: V2-08 | B53: V2 | C53: V2-P4 Completeness + performance/speed | D53: Standardize all native buttons onto StandardButton | E53: A1,A3 | F53: A3-3 | G53: G6 | H53: FrontEnd | I53: FrontEnd | J53: Important | K53: PARTIAL | L53: 0.1 | M53: 14-Jul | N53: ~151 native buttons not on StandardButton. Migrate all to the standard component so styling is uniform current AND future (the Material-Investigation mismatch class is standardized away, not patched once). | O53: A scan shows 0 native buttons outside StandardButton; visual-regression green. Evidence: scan + diff. | P53: refactor | Q53: 14 | R53: 12.6 | S53: V2-04 | T53: V2-02
A54: V2-09 | B54: V2 | C54: V2-P4 Completeness + performance/speed | D54: E2E action-matrix enumerating every demo-path control (CI gate) | E54: A1,A3 | F54: A1-5, A3-1 | G54: G6 | H54: Testing | I54: Testing | J54: Very important | K54: PARTIAL | L54: 0.4 | M54: 14-Jul | N54: The action-matrix spec exists and is 20/20 green (handover); promote it to a BLOCKING CI gate that enumerates every control on every demo-path page and runs on push. | O54: The action-matrix spec is green and blocking in CI. Evidence: the spec + CI run. | P54: feature | Q54: 8 | R54: 4.8 | S54: V1-10 | T54: V2-03
A55: V2-10 | B55: V2 | C55: V2-P4 Completeness + performance/speed | D55: Visual-regression harness (baseline + diff gate) | E55: A3,A6 | F55: A3-3, A6-8 | G55: G6 | H55: Testing | I55: Testing | J55: Important | K55: NEW | L55: 0 | M55: 14-Jul | N55: Capture a baseline of every demo-path page and gate PRs on a pixel/DOM diff so styling never silently drifts. | O55: A deliberate style change fails the diff gate; an intended change updates the baseline. Evidence: CI run. | P55: feature | Q55: 6 | R55: 6 | S55: - | T55: V2-04
A56: V2-11 | B56: V2 | C56: V2-P4 Completeness + performance/speed | D56: Performance-at-scale validation (630/5,600, virtualized tables) | E56: A3 | F56: A3-9 | G56: G6 | H56: FrontEnd | I56: Testing | J56: Important | K56: NEW | L56: 0 | M56: 14-Jul | N56: Validate no hang/lag at demo scale; virtualize large tables; progress indicators on long loads. | O56: At ~630 heats/~5,600 coils, no hang; tables virtualize; long loads show progress. Evidence: measured run. | P56: feature | Q56: 8 | R56: 8 | S56: - | T56: V3-10
A57: V2-12 | B57: V2 | C57: V2-P4 Completeness + performance/speed | D57: Real lead-capture backend (form->DB row+email via relay, e2e asserts) | E57: A6 | F57: A6-10 | G57: G8 | H57: Web | I57: Backend | J57: Important | K57: PARTIAL | L57: 0.3 | M57: 14-Jul | N57: Harden the CTA path into a real backend: validated submit -> stored row + email (via the authenticated relay, never the VPS IP), with an e2e test asserting the row. Builds on the V1 lead-email code. | O57: e2e asserts a lead row + email on submit through the relay. Evidence: the test. | P57: feature | Q57: 6 | R57: 4.2 | S57: V1-18 | T57: V2-22
A58: V2-13 | B58: V2 | C58: V2-P5 Role/license/AI-boundary depth | D58: MFA step-up for admin accounts | E58: A2 | F58: A2-4 | G58: G12 | H58: Security | I58: Backend | J58: Very important | K58: NEW | L58: 0 | M58: 14-Jul | N58: TOTP/WebAuthn step-up enforced for admin roles per the identity doctrine. (sysadmin is the support account; MFA applies to any admin-capable login.) | O58: An admin action triggers an MFA step-up live; non-admin does not. Evidence: test + clip. | P58: feature | Q58: 8 | R58: 8 | S58: - | T58: V2-07
A59: V2-14 | B59: V2 | C59: V2-P5 Role/license/AI-boundary depth | D59: Deepen license tiers: caps enforced + expiry/grace + admin governance | E59: A5 | F59: A5-3 | G59: G12 | H59: Security | I59: Backend | J59: Very important | K59: PARTIAL | L59: 0.2 | M59: 14-Jul | N59: The signed-token activation works (proven on the server with Enterprise). Deepen ENFORCEMENT: seat/source/env caps actually enforced from the token; expiry -> warnings -> configurable read-only grace -> read-only (data never destroyed); soft-vs-hard caps; admin governance to add/manage seats. The 07-editions-and-licensing doc already describes the intended model. | O59: Toggling a tier visibly adds/removes features AND enforces a cap live; an expired token enters grace then read-only. Evidence: tamper test + clips. | P59: feature | Q59: 12 | R59: 9.6 | S59: - | T59: V2-08
A60: V2-15 | B60: V2 | C60: V2-P5 Role/license/AI-boundary depth | D60: Real production Ed25519 license signing key (Option-1 -> Option-3) [NEW 26-Jun] | E60: A2,A5 | F60: A2-5, A5-3 | G60: G12 | H60: Security | I60: Security | J60: Very important | K60: NEW | L60: 0 | M60: 14-Jul | N60: NEW from the 26-Jun session. The demo activates Enterprise with the DEV Ed25519 key (kid ppiq-dev-ed25519), registered only when PPIQ_PRESENTATION=on. For real customers: generate a REAL production Ed25519 signing keypair (kept in a secret store, never in git), sign per-customer/per-tier tokens with it, register the real public key through the canonical licensing/ops flow (not the dev fixture), and ensure the dev key is NEVER shipped/registered in a real customer Production. ALSO: real customer frontend builds must NOT bake VITE_SMOKE_* (demo credentials) into the bundle - gate the demo auto-login to the demo host only. | O60: A real-key-signed per-customer token activates on a clean 'customer' install with PPIQ_PRESENTATION off and NO dev key registered; grep shows the dev key + VITE_SMOKE_* absent from a customer build. Evidence: activation log + grep. | P60: feature | Q60: 10 | R60: 10 | S60: - | T60: V2-09
... A69: V2-24 | B69: V2 | C69: V2-P6 Documentation (screenshots) + web | D69: Naming golden-rule pass: rename phase/task-named artifacts | E69: A1 | F69: A1-4 | G69: - | H69: Docs | I69: Database | J69: Important | K69: NEW | L69: 0 | M69: 14-Jul | N69: ~193 files carry phase/task tokens (p03_p04, phase8, T042, _v6_, hotfix). This includes the production SQL still named 301_p01_p02_authstore_compatibility_bridge.sql, 302_p02_*, 300_p01_p02_*, 500_v5_p01_*, etc. Rename to descriptive names and update references; preserve only ordered-migration numeric prefixes (strip the embedded phase label). The ppiq-app project rename is already done. | O69: The phase/task-token grep returns 0 (outside ordered-prefix migrations); build + tests green; the server deploy stays green after the renames. Evidence: grep + green build + green deploy. | P69: refactor | Q69: 18 | R69: 18 | S69: - | T69: V2-28
A70: V2-25 | B70: V2 | C70: V2-P4 Completeness + performance/speed | D70: System logging to rolling file (systemLog_<day>_<hr>.log, hourly) | E70: A1, A4 | F70: A4.9 operational resilience | G70: G9 | H70: hardening | I70: Backend | J70: Very important | K70: PARTIAL | L70: 0.3 | M70: 14-Jul | N70: Serilog + Sinks.File are already packaged but not configured to a system log file. Configure a structured system-oriented sink: systemLog_<yyyyMMdd>_<HH>.log with RollingInterval.Hour (a new file each hour), levels Info/Warning/Error, enrichers (machine, environment, the correlation id from CorrelationIdMiddleware), exceptions via Serilog.Exceptions. Log path and minimum level are env-configurable, never hardcoded. | O70: Running the API writes systemLog_<day>_<hr>.log; a new file appears at the hour boundary; an induced warning and an induced error both land with timestamp, level, and correlation id (errors include the exception); log path/level are read from config, proven by an override. | P70: hardening | Q70: 6 | R70: 4.2 | T70: (new)
A71: V2-26 | B71: V2 | C71: V2-P4 Completeness + performance/speed | D71: Job + Data operational logging to rolling files (JobLog/DataLog_<day>_<hr>.log) | E71: A4 | F71: A4.4 Jobs Monitor | G71: G9 | H71: hardening | I71: Backend | J71: Very important | K71: NEW | L71: 0 | M71: 14-Jul | N71: Customer-oriented operational logging for EVERY job and data-source operation. Emit a structured event (job type, job name, severity, started/ended, duration, rows, outcome) for: connector reads, incremental/delta imports (DeltaImportExecutionService), mapping publish/rollback, and each correlation/learning job; hook JobRegistrationService + the two-stage functions. Write to JobLog_<day>_<hr>.log and DataLog_<day>_<hr>.log hourly AND persist the same events to a queryable store (table) so the in-app log tab can filter them. | O71: Running an import + a correlation job produces Info events (start/finish, duration, rows) and any failure produces an Error event, in JobLog/DataLog_<day>_<hr>.log AND in the queryable store; a forced job crash is logged as Error with the reason; hourly rotation verified; events carry the job type/name/severity the log tab needs. | P71: new feature | Q71: 8 | R71: 8 | T71: (new)
A72: V2-27 | B72: V2 | C72: V2-P5 Role/license/AI-boundary depth | D72: In-app Log tab on every page (filter by job type / name / severity / day) | E72: A4, A3 | F72: A4.4 Jobs Monitor | G72: G6 | H72: workflow | I72: FrontEnd | J72: Important | K72: NEW | L72: 0 | M72: 14-Jul | N72: A collapsible Log panel docked at the bottom of every page (Dark-Industrial), reading the queryable job/data-log store. Filters: job type, job name, severity (Info/Warning/Error), and day. Live-updates while a job runs; severity colour-coded (ok/warn/crit tokens). Role-scoped (respects FormalRoleAccessMatrix). One generic log-query endpoint + the existing widget/data patterns - no endpoint-per-page. | O72: On any page the Log tab opens and shows recent job/data events; each filter (type, name, severity, day) narrows results correctly; a running job streams new lines into the tab; an Error row renders in the crit colour; a viewer role sees only its permitted scope. | P72: new feature | Q72: 10 | R72: 10 | T72: (new)
A73: V2-28 | B73: V2 | C73: V2-P3 Value engine & justified numbers | D73: ERADICATE hardcoded Stage-2 -> generic per-VIEW Loading projector (one job per mapping view) | E73: A3, A1 | F73: A1.6 generic/any-DB | G73: G2 | H73: workflow | I73: Backend | J73: Critical | K73: NEW | L73: 0 | M73: 14-Jul | N73: Karim-locked model (03-Jul): 'Loading' = ONE JOB PER MAPPING VIEW, not a monolithic Stage-2 refresh. Build the generic projector that consumes a single SchemaViewDefinition (from the no-code mapper) and projects staging -> canonical for that view, keeping its OWN processed watermark; a Loading JobDefinition is created per active mapping view (auto on save, min interval 3 min per V2-30). Delete the ppiq_run_stage2_canonical_refresh IF/ELSIF ladder entirely; the 8 demo sources become seed MAPPINGS, zero code branches. Editing a mapping view triggers the reprojection policy (Karim to decide: full reproject vs forward-only - ask before implementing). | O73: Create a NEW mapping view in the HMI for an unmapped staging table -> a Loading job appears, runs, canonical rows appear - ZERO code change. grep the repo for src_meltshop/hsm_coils/FlatSteel identifiers in the projection path -> none (V2-29 gate enforces). All 8 demo sources flow through mappings only. | P73: new feature | Q73: 24 | R73: 24 | T73: (new)
A74: V2-29 | B74: V2 | C74: V2-P4 Completeness + performance/speed | D74: Generic-Only CI gate - build FAILS on any dataset/industry-specific identifier in core | E74: A1, A3 | F74: A1.6 generic/any-DB | G74: G10 | H74: hardening | I74: Testing | J74: Critical | K74: NEW | L74: 0 | M74: 14-Jul | N74: Make the Generic-Only red line ENFORCEABLE (same spirit as the CI truth-gate). Add an architecture test + CI lint that scans the core/canonical/projection/import path (Domain, Application, the SQL functions under database/scripts, the connectors' canonical mapping) and FAILS the build on any dataset/industry-specific literal: demo schema/table names (src_meltshop_pg, src_hsm_oracle_shape, ...), demo column names (heat_no, coil_id, piece_id, steel_grade, ...), industry type literals ('Heat','Slab','Coil','FlatSteel'), or hardcoded plant constants ('Europe/Berlin', fixed UTC offsets). Allow them ONLY inside seed-data / demo-mapping fixtures (explicit allowlist path). This keeps the product generic forever. | O74: Re-introducing a hardcoded demo identifier into the canonical projection path turns the build RED (negative test). The gate runs in Jenkins and blocks merge. Seed/demo-mapping fixtures are allowlisted and pass. After V2's eradication task, the gate is GREEN on the real code. | P74: hardening | Q74: 6 | R74: 6
A75: V2-30 | B75: V2 | C75: V2-P4 Completeness + performance/speed | D75: Job governance 1: per-type interval FLOORS (config-driven, backend-enforced) | E75: A4 | F75: A4-4 | G75: G7 | H75: Hardening | I75: Backend | J75: Critical | K75: NEW | L75: 0 | M75: 14-Jul | N75: Karim-locked floors: DB Link (Stage-1) 2 min; Loading (Stage-2 per-view) 3 min (must exceed DB Link or it reprocesses unchanged staging); Engine 20 min; AI+ML 60 min. Floors live in ONE config surface (table or options, per-type defaults, overridable per install - never constants). Enforce in the schedule create/update endpoint (reject below floor with a typed error) AND in the scheduler (defense in depth); the schedule UI validates with the same values fetched from the API. | O75: POST a 1-min DB Link schedule -> 400 with floor message; UI blocks with the same message; change the config floor -> both honor it without redeploy of frontend logic (values come from API). | P75: new feature | Q75: 8 | R75: 8 | T75: NEW 03-Jul from journey spec 1.1
A76: V2-31 | B76: V2 | C76: V2-P4 Completeness + performance/speed | D76: Job governance 2: per-type max-parallelism + per-source single-scan lock + start jitter | E76: A2,A4 | F76: A2-3, A4-8 | G76: G7 | H76: Hardening | I76: Backend | J76: Critical | K76: NEW | L76: 0 | M76: 14-Jul | N76: Floors limit frequency, not concurrency: 60 DB-Link jobs at the 2-min floor would fire on one tick and hammer 5 source DBs. Add: (1) per-type max concurrent executions (queue the rest, FIFO); (2) per-SOURCE-SYSTEM single-scan lock (Doctrine 4.8 source-load protection: at most one concurrent scan per customer source); (3) deterministic start jitter/stagger so schedules spread across the window. Design the queue to scale toward the V4 ~1000-job load test - no rebuild later. | O76: Schedule 60 DB-Link + 35 Loading + 10 Engine + 5 AI+ML on the demo stack; run 30 min: server healthy, docker stats bounded, no source container ever shows 2 concurrent scans (assert via lock table), monitor shows queued -> running transitions. | P76: new feature | Q76: 12 | R76: 12 | S76: V2-30 | T76: NEW 03-Jul from journey spec 1.1
A77: V2-32 | B77: V2 | C77: V2-P4 Completeness + performance/speed | D77: Job governance 3: Loading no-op fast path (watermark compare, exit in ms) | E77: A4 | F77: A4-4 | G77: G7 | H77: Hardening | I77: Backend | J77: Very important | K77: NEW | L77: 0 | M77: 14-Jul | N77: A Loading job first compares ITS processed watermark against the Stage-1 watermarks of the staging tables its mapping view reads; if nothing new arrived it exits as NoNewData in milliseconds (logged, cheap). Makes the 3-min floor safe and 35 Loading jobs nearly free between real arrivals. | O77: Run a Loading job twice with no new staging rows: second run completes < 200 ms with status NoNewData; insert one staging row -> next run processes exactly the delta. | P77: new feature | Q77: 4 | R77: 4 | S77: V2-28,V2-30 | T77: NEW 03-Jul from journey spec 1.1/1.2
A78: V2-33 | B78: V2 | C78: V2-P4 Completeness + performance/speed | D78: Job governance 4: Run-now button on every job type (respects locks, refuses double-run) | E78: A4,A3 | F78: A4-4 | G78: G7 | H78: Workflow | I78: Backend | J78: Very important | K78: NEW | L78: 0 | M78: 14-Jul | N78: Run-now bypasses the SCHEDULE, never the guards: it acquires the same per-source lock/parallelism slot, and refuses politely (typed 409) if the same job is already executing (no silent queue-forever, no double-execution). Exposed on all four job types in Jobs Monitor + the owning pages. | O78: Click Run-now while the job runs -> UI shows "already running" from the 409; run-now on a source mid-scan queues/locks correctly; no duplicate concurrent execution observable in the run table. | P78: new feature | Q78: 4 | R78: 4 | S78: V2-31,V1-41 | T78: NEW 03-Jul from journey spec 1.1
A79: V3-01 | B79: V3 | C79: V3-P7 Deep security & ops hardening | D79: Enforce RLS on core tables (decide tenant_id; non-superuser app role) | E79: A2 | F79: A2-6 | G79: G12 | H79: Security | I79: Database | J79: Very important | K79: PARTIAL | L79: 0.4 | M79: post-deal | N79: Decide deliberately (RLS-scoped core vs single-tenant-per-deploy). If multi-tenant: add tenant_id to the core EF entities model-first, run the app under a non-superuser role so RLS is actually enforced (locally ppiq_dev is bypassrls), and prove cross-tenant 403/empty. NOTE: ppiq_ed25519_license_public_keys already demonstrates forced RLS - use it as the pattern. | O79: Cross-tenant access returns 403/empty live under a non-superuser role. Evidence: RlsTenantIsolation test green + clip. | P79: feature | Q79: 10 | R79: 6 | S79: - | T79: V2-11
A80: V3-02 | B80: V3 | C80: V3-P7 Deep security & ops hardening | D80: Encryption at rest: staging/canonical/credential-vault | E80: A2 | F80: A2-9 | G80: G12 | H80: Security | I80: Infra | J80: Important | K80: NEW | L80: 0 | M80: post-deal | N80: Encryption at rest for the app DB and the source-credential vault; document the key management. The 04-security doc already states this as a design property - implement + verify it. | O80: At-rest encryption is on and verified; credentials are encrypted in the vault. Evidence: config + verification. | P80: hardening | Q80: 6 | R80: 6 | S80: - | T80: V2-12
A81: V3-03 | B81: V3 | C81: V3-P7 Deep security & ops hardening | D81: Move Jenkins to a separate Docker network from the app project [NEW 26-Jun] | E81: A2 | F81: A2-10 | G81: G12 | H81: Infra | I81: Infra | J81: Normal | K81: NEW | L81: 0 | M81: post-deal | N81: NEW from the 26-Jun session. Today ppiq-jenkins and the app project share network reachability via the edge alias. Move Jenkins onto its own network so the CI/CD agent is isolated from the app stack (defense in depth), keeping only the Caddy fronting it. | O81: Jenkins runs on a dedicated network; the app stack cannot reach Jenkins by name; deploys still work. Evidence: network inspect + a green deploy. | P81: hardening | Q81: 4 | R81: 4 | S81: V2-13 | T81: V2-15
A82: V3-04 | B82: V3 | C82: V3-P7 Deep security & ops hardening | D82: Wire SourceLoadProtectionPolicy into the live query path | E82: A2 | F82: A2-3 | G82: G11 | H82: Security | I82: Backend | J82: Very important | K82: PARTIAL | L82: 0.5 | M82: post-deal | N82: Enforce the per-source impact budget on a real query path so an over-budget query is throttled, not just policy-defined. | O82: An over-budget query is throttled live. Evidence: test + clip. | P82: feature | Q82: 7 | R82: 3.5 | S82: - | T82: V2-21
A83: V3-05 | B83: V3 | C83: V3-P7 Deep security & ops hardening | D83: Nightly full-suite CI job (cron) | E83: A1 | F83: A1-5 | G83: G9 | H83: Testing | I83: Deploy | J83: Very important | K83: PARTIAL | L83: 0.3 | M83: post-deal | N83: The deploy pipeline runs on push; add a scheduled nightly job that runs the FULL backend+frontend+e2e suite and reports flaky tests, independent of pushes. | O83: A nightly run exists and reports pass-rate + flaky count. Evidence: the cron job + a nightly report. | P83: feature | Q83: 6 | R83: 4.2 | S83: V2-01 | T83: V2-05
A84: V3-06 | B84: V3 | C84: V3-P7 Deep security & ops hardening | D84: Health dashboard (suite/e2e pass-rate, flaky count) | E84: A1 | F84: A1-5 | G84: G9 | H84: Testing | I84: Web | J84: Normal | K84: NEW | L84: 0 | M84: post-deal | N84: A small dashboard surfacing suite pass-rate, e2e pass-rate, and flaky-test count over time. | O84: The dashboard renders current + trend from real runs. Evidence: the page. | P84: feature | Q84: 5 | R84: 5 | S84: V2-05 | T84: V2-06
A85: V3-07 | B85: V3 | C85: V3-P7 Deep security & ops hardening | D85: HasDefaultSchema -> ppiq_meta/ppiq_plant for EF entities | E85: A1 | F85: A1-3 | G85: - | H85: Database | I85: Database | J85: Normal | K85: NEW | L85: 0 | M85: post-deal | N85: Add HasDefaultSchema mapping so EF tables land in ppiq_meta/ppiq_plant instead of public, realising the app-metadata vs customer-data split. | O85: `\dt ppiq_meta.*` and `ppiq_plant.*` list the EF tables after migrate. Evidence: psql output. | P85: refactor | Q85: 4 | R85: 4 | S85: - | T85: V2-29
A86: V3-08 | B86: V3 | C86: V3-P8 Multi-industry & generic | D86: Second-industry demo dataset (paper/board line) + mapping templates | E86: A1,A3 | F86: A3-11 | G86: G3 | H86: Demo | I86: Database | J86: Very important | K86: NEW | L86: 0 | M86: post-deal | N86: A paper/board demo dataset (sources + fixtures) and mapping templates, built entirely through the HMI like the steel demo - proving the generic mandate the docs claim. | O86: The paper demo builds from empty via HMI; a genealogy thread resolves on its keys. Evidence: clip. | P86: feature | Q86: 14 | R86: 14 | S86: V1-04 | T86: V3-01
A87: V3-09 | B87: V3 | C87: V3-P8 Multi-industry & generic | D87: Third-industry demo dataset (food & beverage) + tier configs | E87: A1,A3 | F87: A3-11 | G87: G3 | H87: Demo | I87: Database | J87: Very important | K87: NEW | L87: 0 | M87: post-deal | N87: A food & beverage demo dataset + per-tier configs, same HMI-only build. | O87: The F&B demo builds from empty via HMI. Evidence: clip. | P87: feature | Q87: 12 | R87: 12 | S87: V3-01 | T87: V3-02
... A98: V3-20 | B98: V3 | C98: V3-P9 Accessibility, i18n & scale | D98: Energy Management product page to depth | E98: A6 | F98: A6-7 | G98: G8 | H98: Web | I98: Web | J98: Optional | K98: NEW | L98: 0 | M98: post-deal | N98: Take the Energy Management product page to full depth. | O98: The Energy page is complete; honesty-lint green. Evidence: the page. | P98: content | Q98: 7 | R98: 7 | S98: - | T98: V3-14
A99: V3-21 | B99: V3 | C99: V3-P7 Deep security & ops hardening | D99: Multi-tenancy: tenant column on material_units + tenant-parameterized canonical layer + RLS | E99: A2, A1 | F99: A2.6 tenant isolation | G99: G12 | H99: hardening | I99: Database | J99: Very important | K99: NEW | L99: 0 | M99: post-deal | N99: CODE-VALIDATED GAP: the canonical layer is single-tenant-baked. canonical_material_units / canonical_genealogy_edges (310_mapping_genealogy_foundation.sql) are VIEWS with a HARDCODED tenant_id constant; material_units has NO tenant column; two tests only agree because a migration forces the constant to be the earliest ppiq_tenants row. Add a real tenant_id to material_units (+ backfill migration), parameterize the canonical views by the session tenant, and put RLS on the base tables so a customer can never read another tenant's rows. Model-first: EF entity + IEntityTypeConfiguration + ModelSnapshot in sync; DB constructs in a numbered SQL migration. | O99: A cross-tenant query returns 0 rows / 403 (RLS proven by test); the canonical views resolve the SESSION tenant, not a constant; the genealogy tests pass without relying on 'earliest row == constant'; a second seeded tenant's data is fully isolated end-to-end. | P99: hardening | Q99: 16 | R99: 16 | T99: (new)
A100: V3-22 | B100: V3 | C100: V3-P7 Deep security & ops hardening | D100: i18n-harden the honesty + grounding gates (structural, not English keywords) | E100: A5, A2 | F100: A5.4 trustworthy AI | G100: G4 | H100: hardening | I100: Backend | J100: Important | K100: NEW | L100: 0 | M100: post-deal | N100: CODE-VALIDATED GAP (violates the EN/DE/AR i18n doctrine): ValueHonestyLint forbids English literals ('guaranteed','will save') and GroundingService's forbidden-phrase list is English-only ('root cause','is caused by'...). The number-block is structural (good) but the phrase-block breaks in German/Arabic. Replace English-keyword phrase detection with structural/typed signals: a causation-assertion type flag on claims, claim-type metadata, and locale-aware resource-backed term sets - so the honesty/causation gate holds in EN/DE/AR. | O100: The honesty/causation gate blocks the same intent in German and Arabic test fixtures (not just English); no raw English-keyword regex remains in the value/grounding path; the existing English tests still pass. | P100: hardening | Q100: 8 | R100: 8 | T100: (new)
A101: V3-23 | B101: V3 | C101: V3-P7 Deep security & ops hardening | D101: Log retention, size caps & optional forwarding (ops policy) | E101: A4, A2 | F101: A4.9 operational resilience | G101: G9 | H101: hardening | I101: Infra | J101: Normal | K101: NEW | L101: 0 | M101: post-deal | N101: Production logging policy: a retention window (delete/compress logs older than N days), per-file and total size caps, and an optional forward target (a file share or syslog/OTLP) - all env-configurable. Ensure logs never fill the VPS disk; ensure no secrets are written (scrub connection strings/tokens from log output). | O101: Logs older than the configured window are pruned/compressed; total log size stays under the cap under a soak; a secret deliberately passed through is NOT present in any log (scrub test); the forwarding target receives events when enabled. | P101: hardening | Q101: 4 | R101: 4 | T101: (new)
A102: V4-01 | B102: V4 | C102: V4-P10 Ops / HA + OT | D102: Backup/restore drill (verified restore, recorded) | E102: A4 | F102: A4-9 | G102: G9 | H102: Infra | I102: Deploy | J102: Very important | K102: NEW | L102: 0 | M102: post-deal | N102: Drill a full backup + verified restore of the app DB; record it. Closes the restore half of A4-9/G9 the deploy session did not. | O102: A restore from backup reaches a working login; recorded. Evidence: the recording. | P102: feature | Q102: 8 | R102: 8 | S102: - | T102: V4-01
A103: V4-02 | B103: V4 | C103: V4-P10 Ops / HA + OT | D103: Verify deploy rollback to :previous | E103: A4 | F103: A4-9 | G103: G9 | H103: Infra | I103: Deploy | J103: Important | K103: NEW | L103: 0.3 | M103: post-deal | N103: The pipeline already tags :previous and rolls back on a failed health gate. Verify it end-to-end by inducing a health-gate failure and confirming the rollback restores service. | O103: An induced bad deploy rolls back to :previous and service stays up. Evidence: pipeline log. | P103: verification | Q103: 5 | R103: 3.5 | S103: - | T103: V4-02
A104: V4-03 | B104: V4 | C104: V4-P10 Ops / HA + OT | D104: Time-series store (hypertables, compression, retention) | E104: A4 | F104: A4-8 | G104: G9 | H104: Infra | I104: Database | J104: Very important | K104: NEW | L104: 0 | M104: post-deal | N104: Introduce a time-series store (hypertables/columnar, compression, downsampling, retention) for high-frequency parameters. | O104: Parameter data lands in the time-series store with compression + retention. Evidence: schema + query. | P104: feature | Q104: 12 | R104: 12 | S104: - | T104: V4-03
A105: V4-04 | B105: V4 | C105: V4-P10 Ops / HA + OT | D105: Deployable OT-safe edge agent (one-way push) | E105: A2 | F105: A2-2 | G105: G11 | H105: Infra | I105: Backend | J105: Very important | K105: NEW | L105: 0 | M105: post-deal | N105: Build a deployable Edge Collector that pushes one-way from the DMZ; the core never connects into OT. The docs already describe this model. | O105: The agent pushes one-way; no inbound path to OT; load within budget. Evidence: deploy + capture. | P105: feature | Q105: 12 | R105: 12 | S105: - | T105: V4-04
A106: V4-05 | B106: V4 | C106: V4-P10 Ops / HA + OT | D106: Human-approved advisory write-back (business workflow, never OT) | E106: A5 | F106: A5-9 | G106: G5 | H106: Backend | I106: Backend | J106: Very important | K106: NEW | L106: 0 | M106: post-deal | N106: Advisory write-back into business workflow (case/action tracking) with human approval - never a setpoint/command to control. | O106: An approved advisory creates a tracked action; no OT write path exists. Evidence: workflow + code-search. | P106: feature | Q106: 10 | R106: 10 | S106: - | T106: V4-05
A107: V4-06 | B107: V4 | C107: V4-P10 Ops / HA + OT | D107: Enforce performance budgets in CI | E107: A1 | F107: A1-2 | G107: G6 | H107: Testing | I107: Testing | J107: Important | K107: NEW | L107: 0 | M107: post-deal | N107: Add performance budgets as CI gates so regressions fail the build. | O107: A deliberate perf regression fails CI. Evidence: CI run. | P107: feature | Q107: 6 | R107: 6 | S107: - | T107: V4-06
A108: V4-07 | B108: V4 | C108: V4-P10 Ops / HA + OT | D108: Load-test at reference-plant scale | E108: A4 | F108: A4-9 | G108: G9 | H108: Testing | I108: Testing | J108: Very important | K108: NEW | L108: 0 | M108: post-deal | N108: Load-test at realistic reference-plant scale (well beyond demo scale). | O108: The system holds at reference scale within budget. Evidence: load report. | P108: feature | Q108: 8 | R108: 8 | S108: - | T108: V4-07
A109: V4-08 | B109: V4 | C109: V4-P11 Compliance + ops | D109: Start SOC 2 Type II observation window | E109: A2 | F109: A2-9 | G109: G16 | H109: Docs | I109: Security | J109: Very important | K109: NEW | L109: 0 | M109: post-deal | N109: Begin the SOC 2 Type II observation window (controls evidenced over time). | O109: The observation window is open with controls evidenced. Evidence: the tracker. | P109: content | Q109: 10 | R109: 10 | S109: - | T109: V4-08
A110: V4-09 | B110: V4 | C110: V4-P11 Compliance + ops | D110: ISO 27001 mapping + sensitive-data catalog | E110: A2 | F110: A2-9 | G110: G16 | H110: Docs | I110: Security | J110: Important | K110: NEW | L110: 0 | M110: post-deal | N110: Map controls to ISO 27001 and catalog sensitive data. | O110: The mapping + catalog exist. Evidence: the docs. | P110: content | Q110: 8 | R110: 8 | S110: - | T110: V4-09
A111: V4-10 | B111: V4 | C111: V4-P11 Compliance + ops | D111: GxP / 21 CFR Part 11 pack (audit trail, e-signature) | E111: A2 | F111: A2-9 | G111: G16 | H111: Docs | I111: Security | J111: Optional | K111: NEW | L111: 0 | M111: post-deal | N111: A GxP / 21 CFR Part 11 pack where required (audit trail + e-signature). | O111: The pack evidences audit trail + e-signature. Evidence: the docs. | P111: content | Q111: 12 | R111: 12 | S111: - | T111: V4-10
A112: V4-11 | B112: V4 | C112: V4-P11 Compliance + ops | D112: Public status page | E112: A4 | F112: A4-9 | G112: - | H112: Web | I112: Web | J112: Normal | K112: NEW | L112: 0 | M112: post-deal | N112: A public status page for the hosted service. | O112: The status page reflects real health. Evidence: the page. | P112: content | Q112: 4 | R112: 4 | S112: - | T112: V4-11
A113: V4-12 | B113: V4 | C113: V4-P11 Compliance + ops | D113: AI triage loop (agent drafts fix PRs, human-approved) | E113: A1 | F113: A1-5 | G113: - | H113: AI+ML | I113: Testing | J113: Important | K113: NEW | L113: 0 | M113: post-deal | N113: An AI triage loop where an agent drafts fix PRs from failing tests, human-approved. | O113: The loop drafts a PR for an injected failure; human merges. Evidence: the PR. | P113: feature | Q113: 10 | R113: 10 | S113: - | T113: V4-12
... A126: V4-25 | B126: V4 | C126: V4-P12 Business / reference | D126: Funding / partnership decision | E126: A5 | F126: - | G126: - | H126: Web | I126: Docs | J126: Normal | K126: NEW | L126: 0 | M126: post-deal | N126: Decide funding/partnership direction. | O126: A decision recorded. Evidence: the note. | P126: content | Q126: 4 | R126: 4 | S126: - | T126: V4-25

Sheet Version Summary
A1: Version Summary v13
A2: Version | B2: Tasks | C2: Scope (h) | D2: Remaining (h)
A3: V1 | B3: =COUNTIF(Backlog!B3:B126,A3) -> 43 | C3: =SUMIF(Backlog!B3:B126,A3,Backlog!Q3:Q126) -> 176 | D3: =SUMIF(Backlog!B3:B126,A3,Backlog!R3:R126) -> 113.1
A4: V2 | B4: =COUNTIF(Backlog!B3:B126,A4) -> 33 | C4: =SUMIF(Backlog!B3:B126,A4,Backlog!Q3:Q126) -> 290 | D4: =SUMIF(Backlog!B3:B126,A4,Backlog!R3:R126) -> 220.9
A5: V3 | B5: =COUNTIF(Backlog!B3:B126,A5) -> 23 | C5: =SUMIF(Backlog!B3:B126,A5,Backlog!Q3:Q126) -> 188 | D5: =SUMIF(Backlog!B3:B126,A5,Backlog!R3:R126) -> 175.1
A6: V4 | B6: =COUNTIF(Backlog!B3:B126,A6) -> 25 | C6: =SUMIF(Backlog!B3:B126,A6,Backlog!Q3:Q126) -> 222 | D6: =SUMIF(Backlog!B3:B126,A6,Backlog!R3:R126) -> 218.1
A7: TOTAL | B7: =B3+B4+B5+B6 -> 124 | C7: =C3+C4+C5+C6 -> 876 | D7: =D3+D4+D5+D6 -> 727.2
A9: By meeting target
A10: Target | B10: Tasks | C10: Remaining (h)
A11: done | B11: =COUNTIF(Backlog!M3:M126,A11) -> 5 | C11: =SUMIF(Backlog!M3:M126,A11,Backlog!R3:R126) -> 0.5
A12: 8-Jul | B12: =COUNTIF(Backlog!M3:M126,A12) -> 26 | C12: =SUMIF(Backlog!M3:M126,A12,Backlog!R3:R126) -> 71.3
A13: 14-Jul | B13: =COUNTIF(Backlog!M3:M126,A13) -> 42 | C13: =SUMIF(Backlog!M3:M126,A13,Backlog!R3:R126) -> 253.8
A14: 14-Jul (honest framing ready for 8-Jul) | B14: =COUNTIF(Backlog!M3:M126,A14) -> 3 | C14: =SUMIF(Backlog!M3:M126,A14,Backlog!R3:R126) -> 8.4
A15: post-deal | B15: =COUNTIF(Backlog!M3:M126,A15) -> 48 | C15: =SUMIF(Backlog!M3:M126,A15,Backlog!R3:R126) -> 393.2
