Workbook

Sheet Read Me
B2: PlantProcess IQ — Product Backlog v4
B3: Versioned release plan. Operationalizes PPIQ_Product_Roadmap_v3, the Identity & Topology v3 reference, and the 20-Jun realization scoreboard.
B5: WHAT CHANGED FROM v3.1
B6: 1. Reorganized from milestones (M1/M2/M3) into VERSIONS (V1-V4). Version 1 is the first release for the customer presentation and totals < 100 h.
B7: 2. Tasks >85% done are REMOVED to the 'Completed (Removed)' sheet (5 tasks: the .env.dev, schemas, demo-sources, role-users and Ed25519-token closures).
B8: 3. Tasks 65-85% done are marked MOSTLY-DONE and ordered FIRST in their phase (e.g. ppiq.ps1 entrypoint).
B9: 4. Added the gap-closing tasks needed so every persona AND every sub-criterion reaches >=75 — proven on the 'Coverage to 75' sheet.
B10: 5. Surfaced the new realities the optimistic file-count hid: the lost genealogy/safe-SQL foundation (now V1-07, P0), the 151 non-standard buttons (V2-02, not 41), and the live config defects (V1-04/05).
B12: THE FOUR VERSIONS
B13: V1 · First Release — Presentation-Ready (<100 h). A crash-free, live, reproducible demo + healthy server deploy + ROI story + collateral + a sharp website. Lifts the demo-gating personas.
B14: V2 · Product Depth. License + user-role depth, sharper AI/ML results + an impressive suggestion engine, the full test harness, and docs WITH app screenshots (how-to-use / how-to-install).
B15: V3 · Generic & Multi-Industry. Paper and food/beverage demo datasets + tiers, a generic no-code mapping template library, a historian connector, accessibility (WCAG light + Arabic RTL) and scale.
... B28: Critical <55 · Needs work 55-69 · Solid 70-84 · Strong 85+ | Status: REMOVED >=85% · MOSTLY-DONE 65-84% · PARTIAL <65% · NEW 0%

Sheet Backlog
A1: PlantProcess IQ — Product Backlog v4 · versioned (V1<100h) · floor-to-75 · generated from Roadmap v3 + Identity v3 + the 20-Jun scoreboard
A2: Task ID | B2: Version | C2: Phase | D2: Task Name | E2: Persona(s) | F2: Sub-criterion lifted | G2: Gate | H2: Track | I2: Module | J2: Severity | K2: Status | L2: % done | M2: Description (junior-dev-actionable) | N2: Validation / Acceptance (hard, reproducible) | O2: Task Type | P2: Effort (h) | Q2: Prereq
A3: V1-01 | B3: V1 | C3: V1-P1 Reproducible env | D3: Harden ppiq.ps1 single entrypoint (bake env, EF-first migrate) | E3: A1,A4 | F3: A1-2, A1-10 | G3: G9 | H3: Environment | I3: Infra | J3: Critical | K3: MOSTLY-DONE | L3: 0.72 | M3: ppiq.ps1 verbs exist and work, but `migrate`/`demo` do not run `dotnet ef database update` before the numbered SQL, and PGCLIENTENCODING is not baked in. Fold EF-update into the start of migrate/demo; export PGCLIENTENCODING=UTF8 before every psql; remove the redundant inline EF call from the Jenkins stage. | N3: From a clean DB, `ppiq.ps1 demo` provisions one-shot (EF schema then SQL decoration then app on :5063) with no manually-set env vars. Evidence: terminal log of a clean run. | O3: refactor | P3: 3 | Q3: —
A4: V1-02 | B4: V1 | C4: V1-P1 Reproducible env | D4: Commit reproducibility config: design-time factory + PGCLIENTENCODING + EF-first | E4: A1 | F4: A1-2 | G4: G9 | H4: Environment | I4: Infra | J4: Critical | K4: NEW | L4: 0.1 | M4: Rewrite PlantProcessDesignTimeDbContextFactory to read ConnectionStrings__PlantProcessDb -> PLANTPROCESS_DESIGNTIME_CONNECTION_STRING -> PLANTPROCESS_DB with an honest error. Commit so the two session env-vars (PLANTPROCESS_DB, PGCLIENTENCODING) are no longer needed to boot. | N4: A fresh clone runs `dotnet ef database update` and `ppiq.ps1 migrate` with zero hand-set env vars. Evidence: clean-clone run log; grep shows no transient env-var requirement in docs. | O4: hardening | P4: 5 | Q4: V1-01
A5: V1-03 | B5: V1 | C5: V1-P1 Reproducible env | D5: Converge to ONE canonical compose + delete orphaned + duplicate fleets | E5: A1,A2 | F5: A1-3, A2-10 | G5: G9 | H5: Environment | I5: Infra | J5: Critical | K5: NEW | L5: 0.2 | M5: Keep the live `plantprocessiq` project + `docker-compose.sources.yml`. Delete the orphaned `plantprocess-*` stack, the duplicate `docker-compose.demo-sources*.yml` fleet and `.ports.yml`, and `Infrastructure/deploy/docker-compose.demo.yml`. Align Caddy service/port to the API :5063. | N5: `grep -rl docker-compose.demo` and the duplicate-fleet grep both return nothing; `docker compose ... up -d` brings up exactly one healthy app stack Caddy routes to. Evidence: dir listing + docker ps. | O5: refactor | P5: 6 | Q5: —
A6: V1-04 | B6: V1 | C6: V1-P1 Reproducible env | D6: Fix connection-string key __DefaultConnection -> __PlantProcessDb (incl. the generator) | E6: A2 | F6: A2-5, A2-10 | G6: G12 | H6: Environment | I6: Infra | J6: Critical | K6: NEW | L6: 0.1 | M6: Replace ConnectionStrings__DefaultConnection with ConnectionStrings__PlantProcessDb in deploy/compose/.env.dev, docker-compose.yml, and env/profiles/local.env, AND in the generator tools/realization/continue-phase03-phase04-from-t016.cjs that re-emits the wrong key. The generator is the root cause - fix it or it re-introduces the defect. | N6: grep finds zero `__DefaultConnection`; a generated compose contains `__PlantProcessDb`; the container API boots and connects. Evidence: grep output + boot log. | O6: bug fix | P6: 3 | Q6: —
A7: V1-05 | B7: V1 | C7: V1-P1 Reproducible env | D7: Delete env/profiles/local.env (leaks plantprocess123) + rotate | E7: A2 | F7: A2-5 | G7: G12 | H7: Environment | I7: Security | J7: Critical | K7: NEW | L7: 0.1 | M7: Remove env/profiles/local.env (it carries IsBootstrapAdmin=true and the literal plantprocess123) and rotate any key that ever touched it. Keep only deploy/compose/.env.dev (container-local creds) and a git-ignored server .env. | N7: grep finds zero `plantprocess123` and zero `IsBootstrapAdmin=true` in the repo; the startup guard still passes. Evidence: grep output. | O7: bug fix | P7: 2 | Q7: —
A8: V1-06 | B8: V1 | C8: V1-P1 Reproducible env | D8: Commit test config — permanently fix the 83 clean-machine failures | E8: A1 | F8: A1-2 | G8: G10 | H8: Environment | I8: Testing | J8: Critical | K8: PARTIAL | L8: 0.25 | M8: Author committed appsettings.Test.json (DSN + 64-char signing key + a real admin + PPIQ_FORCE_EXTERNAL_API_TEST_HOST) and wire Do-Test so WebApplicationFactory boots the host and finds the DB without per-run env vars. This is the documented cause of the 83 reds. | N8: `ppiq.ps1 test` exits 0 TWICE on a fresh checkout (no hand-set vars). Evidence: two consecutive green run logs. | O8: hardening | P8: 6 | Q8: V1-02
A9: V1-07 | B9: V1 | C9: V1-P1 Reproducible env | D9: Rebuild mapping/genealogy/safe-SQL foundation (demo-minimum, model-first) | E9: A3,A4 | F9: A3-5, A3-8, A4-2 | G9: G2 | H9: Foundation | I9: Database | J9: Critical | K9: NEW | L9: 0.05 | M9: The foundation is lost (no clean git copy): ppiq_business_key_definitions, canonical_business_keys, canonical_mapping_versions, the canonical genealogy tables, ppiq_walk_genealogy and ppiq_resolve_safe_sql are gone; only genealogy_edges (EF) survives. Rebuild the DEMO-MINIMUM set model-first: entities + IEntityTypeConfiguration for the business-key/canonical-mapping tables; the recursive walk + cycle/orphan validators + the safe-SQL resolver in a thin SQL migration. Scope to what the demo thread needs; defer full mapping-lifecycle hardening to V2. | N9: On the demo dataset, ppiq_walk_genealogy(C-0044170) returns the full coil->melt chain both directions; a bad mapping returns a typed error and rolls back; the 311/321 validators are green (un-quarantined). Evidence: psql output + green migration. | O9: new feature | P9: 18 | Q9: V1-02
A10: V1-08 | B10: V1 | C10: V1-P1 Reproducible env | D10: Verify genealogy both directions on C-0044170 live | E10: A3 | F10: A3-5 | G10: G2 | H10: Demo | I10: Backend | J10: Critical | K10: PARTIAL | L10: 0.2 | M10: With the foundation rebuilt, walk C-0044170 coil->melt and melt->coils in the running HMI, confirming the Material Investigation evidence panel renders both directions. | N10: Recorded walk: both directions resolve on the demo data, no stall. Evidence: clip in the dry-run. | O10: test | P10: 4 | Q10: V1-07
A11: V1-09 | B11: V1 | C11: V1-P1 Reproducible env | D11: Verify transition-coil weighted attribution (70/30) live | E11: A3 | F11: A3-8 | G11: G15 | H11: Demo | I11: AI+ML | J11: Very important | K11: PARTIAL | L11: 0.3 | M11: Confirm a casting-transition coil reports weighted (e.g. 70/30) attribution across two heats with the population/exclusions shown. | N11: A transition coil renders weighted provenance + stated population live. Evidence: clip. | O11: test | P11: 3 | Q11: V1-07
A12: V1-PT1 | B12: V1 | C12: V1-P1 Reproducible env | D12: V1-P1 acceptance gate: clean checkout boots seeded + green twice | E12: A1 | F12: A1-2, A1-5 | G12: G10 | H12: Environment | I12: Testing | J12: Critical | K12: NEW | L12: 0 | M12: End-of-phase regression: clean clone -> `ppiq.ps1 reset && ppiq.ps1 demo` boots the seeded stack; `ppiq.ps1 test` green twice; genealogy walk resolves. Seals V1-P1 as deployable. | N12: All three gates pass on a fresh machine, scripted. Evidence: one combined run log. | O12: test | P12: 4 | Q12: V1-06,V1-07
A13: V1-10 | B13: V1 | C13: V1-P2 Live demo + collateral | D13: App boots under Playwright (no early webServer exit) | E13: A3,A5 | F13: A3-2, A5-8 | G13: G7 | H13: Demo | I13: FrontEnd | J13: Critical | K13: PARTIAL | L13: 0.55 | M13: Fix playwright config so webServer starts the API+web and waits for :5063/:5173 instead of exiting early; run at least one real spec against the booted app. | N13: `ppiq.ps1 e2e` starts the app and runs >=1 spec to green. Evidence: Playwright HTML report. | O13: bug fix | P13: 5 | Q13: V1-PT1
A14: V1-11 | B14: V1 | C14: V1-P2 Live demo + collateral | D14: One-click readiness check passes live | E14: A4 | F14: A4-7 | G14: G7 | H14: Demo | I14: Backend | J14: Critical | K14: PARTIAL | L14: 0.5 | M14: Make the readiness surface return green (sources healthy, counts match, jobs ready) in one call on the seeded stack. | N14: Readiness endpoint returns all-green on the demo data, shown live. Evidence: screenshot + clip. | O14: modification | P14: 4 | Q14: V1-10
... A88: V4-25 | B88: V4 | C88: V4-P11 Business/Reference | D88: Funding / partnership decision | E88: A5 | F88: A5-10 | G88: — | H88: Admin-business | I88: Docs | J88: Normal | K88: NEW | L88: 0 | M88: A written decision on the funding/partnership path + next step. | N88: A written decision + next step. Evidence: the doc. | O88: new feature | P88: 4 | Q88: —
O89: TOTAL (all versions) | P89: =SUM(P3:P88) -> 644

Sheet Version Summary
A1: Version Summary · effort + the floor each version lifts
A2: Version | B2: Theme | C2: Tasks | D2: Effort (h) | E2: < 100 h? | F2: Defining outcome (deployable) | G2: Personas it lifts | H2: Floor after
A3: V1 | B3: First Release — Presentation-Ready | C3: =COUNTIF(Backlog!$B$3:$B$88,"V1") -> 23 | D3: =SUMIF(Backlog!$B$3:$B$88,"V1",Backlog!$P$3:$P$88) -> 96 | E3: =IF(D3<100,"YES — "&D3&" h","no — "&D3&" h") -> YES — 96 h | F3: Live recorded demo + healthy deploy + ROI + collateral + sharp website | G3: A3,A5,A6 (the demo-gating lenses) | H3: ~70-76
A4: V2 | B4: Product Depth — license/role · AI-ML · tests · docs | C4: =COUNTIF(Backlog!$B$3:$B$88,"V2") -> 25 | D4: =SUMIF(Backlog!$B$3:$B$88,"V2",Backlog!$P$3:$P$88) -> 206 | E4: — | F4: Suite green twice, MFA + tier/role depth, sharper AI + suggestions, docs w/ screenshots | G4: A1,A2,A5 to Solid | H4: ~75-80
A5: V3 | B5: Generic & Multi-Industry | C5: =COUNTIF(Backlog!$B$3:$B$88,"V3") -> 13 | D5: =SUMIF(Backlog!$B$3:$B$88,"V3",Backlog!$P$3:$P$88) -> 120 | E5: — | F5: Paper + food datasets, generic mapper, historian GA, WCAG + RTL, scale | G5: A1,A3,A4,A6 generic depth | H5: ~76-82
A6: V4 | B6: Enterprise & Reference | C6: =COUNTIF(Backlog!$B$3:$B$88,"V4") -> 25 | D6: =SUMIF(Backlog!$B$3:$B$88,"V4",Backlog!$P$3:$P$88) -> 222 | E6: — | F6: HA + OT agent + advisory write-back + SOC2/ISO + signed pilot + case study | G6: A2,A4,A5 enterprise + reference | H6: ~80+
B7: TOTAL | C7: =SUM(C3:C6) -> 86 | D7: =SUM(D3:D6) -> 644

Sheet Phase Summary
A1: Phase Summary · each phase deployable; V2-V4 phases held to ~45-65 h
A2: Phase | B2: Version | C2: Tasks | D2: Effort (h) | E2: 45-65 h band?
A3: V1-P1 Reproducible env | B3: V1 | C3: =COUNTIF(Backlog!$C$3:$C$88,"V1-P1 Reproducible env") -> 10 | D3: =SUMIF(Backlog!$C$3:$C$88,"V1-P1 Reproducible env",Backlog!$P$3:$P$88) -> 54 | E3: =IF(AND(D3>=45,D3<=65),"in band",IF(D3<45,"lean "&D3,"heavy "&D3)) -> in band
A4: V1-P2 Live demo + collateral | B4: V1 | C4: =COUNTIF(Backlog!$C$3:$C$88,"V1-P2 Live demo + collateral") -> 13 | D4: =SUMIF(Backlog!$C$3:$C$88,"V1-P2 Live demo + collateral",Backlog!$P$3:$P$88) -> 42 | E4: =IF(AND(D4>=45,D4<=65),"in band",IF(D4<45,"lean "&D4,"heavy "&D4)) -> lean 42
A5: V2-P3 Stability + UI | B5: V2 | C5: =COUNTIF(Backlog!$C$3:$C$88,"V2-P3 Stability + UI") -> 6 | D5: =SUMIF(Backlog!$C$3:$C$88,"V2-P3 Stability + UI",Backlog!$P$3:$P$88) -> 49 | E5: =IF(AND(D5>=45,D5<=65),"in band",IF(D5<45,"lean "&D5,"heavy "&D5)) -> in band
A6: V2-P4 License + Role + Security | B6: V2 | C6: =COUNTIF(Backlog!$C$3:$C$88,"V2-P4 License + Role + Security") -> 6 | D6: =SUMIF(Backlog!$C$3:$C$88,"V2-P4 License + Role + Security",Backlog!$P$3:$P$88) -> 51 | E6: =IF(AND(D6>=45,D6<=65),"in band",IF(D6<45,"lean "&D6,"heavy "&D6)) -> in band
A7: V2-P5 AI/ML quality | B7: V2 | C7: =COUNTIF(Backlog!$C$3:$C$88,"V2-P5 AI/ML quality") -> 6 | D7: =SUMIF(Backlog!$C$3:$C$88,"V2-P5 AI/ML quality",Backlog!$P$3:$P$88) -> 48 | E7: =IF(AND(D7>=45,D7<=65),"in band",IF(D7<45,"lean "&D7,"heavy "&D7)) -> in band
A8: V2-P6 Docs + hygiene | B8: V2 | C8: =COUNTIF(Backlog!$C$3:$C$88,"V2-P6 Docs + hygiene") -> 7 | D8: =SUMIF(Backlog!$C$3:$C$88,"V2-P6 Docs + hygiene",Backlog!$P$3:$P$88) -> 58 | E8: =IF(AND(D8>=45,D8<=65),"in band",IF(D8<45,"lean "&D8,"heavy "&D8)) -> in band
A9: V3-P7 Multi-industry data | B9: V3 | C9: =COUNTIF(Backlog!$C$3:$C$88,"V3-P7 Multi-industry data") -> 6 | D9: =SUMIF(Backlog!$C$3:$C$88,"V3-P7 Multi-industry data",Backlog!$P$3:$P$88) -> 64 | E9: =IF(AND(D9>=45,D9<=65),"in band",IF(D9<45,"lean "&D9,"heavy "&D9)) -> in band
A10: V3-P8 Accessibility + scale | B10: V3 | C10: =COUNTIF(Backlog!$C$3:$C$88,"V3-P8 Accessibility + scale") -> 7 | D10: =SUMIF(Backlog!$C$3:$C$88,"V3-P8 Accessibility + scale",Backlog!$P$3:$P$88) -> 56 | E10: =IF(AND(D10>=45,D10<=65),"in band",IF(D10<45,"lean "&D10,"heavy "&D10)) -> in band
A11: V4-P9 Ops/HA + OT | B11: V4 | C11: =COUNTIF(Backlog!$C$3:$C$88,"V4-P9 Ops/HA + OT") -> 7 | D11: =SUMIF(Backlog!$C$3:$C$88,"V4-P9 Ops/HA + OT",Backlog!$P$3:$P$88) -> 61 | E11: =IF(AND(D11>=45,D11<=65),"in band",IF(D11<45,"lean "&D11,"heavy "&D11)) -> in band
A12: V4-P10 Compliance + ops | B12: V4 | C12: =COUNTIF(Backlog!$C$3:$C$88,"V4-P10 Compliance + ops") -> 7 | D12: =SUMIF(Backlog!$C$3:$C$88,"V4-P10 Compliance + ops",Backlog!$P$3:$P$88) -> 56 | E12: =IF(AND(D12>=45,D12<=65),"in band",IF(D12<45,"lean "&D12,"heavy "&D12)) -> in band
A13: V4-P11 Business/Reference | B13: V4 | C13: =COUNTIF(Backlog!$C$3:$C$88,"V4-P11 Business/Reference") -> 11 | D13: =SUMIF(Backlog!$C$3:$C$88,"V4-P11 Business/Reference",Backlog!$P$3:$P$88) -> 105 | E13: =IF(AND(D13>=45,D13<=65),"in band",IF(D13<45,"lean "&D13,"heavy "&D13)) -> heavy 105
A15: V1's two phases run ~54 h and ~42 h (kept tight so the whole release stays under 100 h). V2-V4 phases are sized to the 45-65 h working band; each phase ends deployable.

Sheet Coverage to 75
A1: Coverage to 75 · every sub-criterion has a lifting task and projects >=75
A2: Current floors (20-Jun): A1 63 · A2 72 · A3 61 (headline) · A4 64 · A5 67 · A6 63. Target: all six personas AND all 63 sub-criteria >=75.
A3: Sub-criterion | B3: Name | C3: Current | D3: Lifting task(s) | E3: Version | F3: Projected
A4: A1-1 | B4: Hygiene & clean code | C4: 58 | D4: V2-02 | E4: V2 | F4: 78
A5: A1-2 | B5: Stability under change | C5: 58 | D5: V1-06 / V2-01 | E5: V1->V2 | F5: 80
A6: A1-3 | B6: Repo structure | C6: 59 | D6: V1-03 / V2-25 | E6: V1 | F6: 80
A7: A1-4 | B7: Naming & structure | C7: 60 | D7: V2-24 | E7: V2 | F7: 82
A8: A1-5 | B8: Tests execute, not enumerate | C8: 80 | D8: holds (CI truth-gate) | E8: - | F8: 82
A9: A1-6 | B9: Generic any-DB | C9: 68 | D9: V3-01 / V3-05 | E9: V3 | F9: 80
A10: A1-7 | B10: Extensibility | C10: 72 | D10: V3-05 / V2-23 | E10: V2/V3 | F10: 80
A11: A1-8 | B11: Structural consistency | C11: 66 | D11: V2-02 | E11: V2 | F11: 76
A12: A1-9 | B12: Pipeline & deploy | C12: 72 | D12: V1-03 / V4-06 | E12: V1/V4 | F12: 82
A13: A1-10 | B13: Switchable profiles | C13: 62 | D13: V1-01 / V2-09 | E13: V1/V2 | F13: 78
A14: A1-11 | B14: No silent failure | C14: 68 | D14: V1-12 / V2-03 | E14: V1/V2 | F14: 80
A15: A1-12 | B15: Endpoint resilience | C15: 63 | D15: V2-03 | E15: V2 | F15: 76
... A66: A6-10 | B66: CTA & lead capture | C66: 58 | D66: V1-22 / V2-18 | E66: V1/V2 | F66: 80

Sheet Completed (Removed)
A1: Completed (Removed) · tasks >85% done — taken off the active plan
A2: Old ID | B2: Task | C2: % done | D2: Evidence (20-Jun / Identity v3) | E2: Residual work moved to
A3: M1-T02 | B3: Author committed .env.dev (local-only, non-secret) | C3: 0.95 | D3: Identity v3 sec.0/3/4: .env.dev carries the 5 role users, the token-free 68-char signing key and ConnectionStrings__PlantProcessDb. Canonical identity values locked. | E3: A new V1 task (V1-04/V1-05) fixes the wrong key + the local.env leak that live alongside it.
A4: M1-T03 | B4: Two-schema migration 000_schemas.sql | C4: 0.85 | D4: Schemas ppiq_meta + ppiq_plant are created. Identity v3 sec.2.2 confirms (gate `\dn` met). | E4: Residual: EF tables still land in public -> moved to V2-25 (HasDefaultSchema).
A5: M1-T04 | B5: Demo-sources compose + committed fixtures (8 sources) | C5: 0.9 | D5: Identity v3 sec.5: docker-compose.sources.yml (project ppiq-sources) + 630 heats/5,670 coils/39,690 passes/1,987 defects/17,010 QA/210 downtime seeded. T04 closed. | E5: Residual: delete the DUPLICATE demo-sources fleet -> moved into V1-03 (compose convergence).
A6: M1-T05 | B6: Seed one user per role via config | C6: 0.95 | D6: Identity v3 sec.4: 5 role users (admin/exec/engineer/operator/viewer) in .env.dev; login uses config users; Argon2id on load; bootstrap disabled. | E6: Residual: delete the stale 4-user set in appsettings.Development.json -> folded into V1-05 cleanup.
A7: M1-T06 | B7: Dev Ed25519 license keypair + per-tier tokens | C7: 0.95 | D7: Identity v3 sec.6: light/pro/proplus/enterprise tokens minted (kid ppiq-dev-ed25519); all 5 Ed25519 checks green this session. | E7: None for the demo; tier-cap ENFORCEMENT depth moved to V2-08.
