Workbook

Sheet Backlog
A1: Task Id | B1: Milestone Id | C1: Phase Id | D1: Task Name | E1: Module | F1: Sub-module | G1: Priority | H1: Task Description | I1: Task Validation | J1: Hours | K1: Status | L1: Recommended Owner | M1: Worker 3 Parallel Label | N1: Worker 3 Boundary / Scope | O1: Depends On / Release Gate | P1: v2.10.2 Change | Q1: Verified Live State | R1: Evidence / Commit | S1: Design Review Verdict | T1: Design / Concept Finding | U1: Tech-Lead Ruling | V1: Revised Dependency / Gate | W1: Parallel / Booster Ruling | X1: Rework Risk | Y1: Review Authority / Date | Z1: Product Track | AA1: Delivery Target | AB1: Release Criticality | AC1: Concept Alignment Ruling | AD1: Deadline Risk | AE1: AI Agent Owner | AF1: AI Agent Lane | AG1: AI Execution Class | AH1: AI Speed Factor (x) | AI1: P80 Guard Multiplier | AJ1: AI Active Time P50 (h) | AK1: AI Guarded Time P80 (h) | AL1: AI Sequence Wave | AM1: AI Start / Dependency Gate | AN1: File / Subsystem Lock | AO1: No-Rework Handoff Ruling
A2: T-001 | B2: M1 | C2: M1-P1 | D2: Build the six-beat Design Traceability Matrix | E2: Documentation | F2: Design contract | G2: Critical | H2: Create docs/m1/M1_Traceability_Matrix.md. One row per screen that will be opened in the customer presentation. Columns: Screen, Route, Chapter 2 journey step (J4..J15), Chapter 3 page contract id (A1..F9 / G1..G6), Chapter 4 behaviour section (5.1..5.7), Chapter 5 tutorial step, Current implementation file, Classification. Classification is one of KEEP (matches final design), MODIFY (visible surface needs change), TEMP-ADAPTER (visible surface is final but persistence behind it is temporary and M2 replaces it), NEW. Get the route list from Frontend/PlantProcess.Web/src/App.tsx, which currently declares 69 route paths. Chapter 3 section 4.4 lists the target 40 route pages plus 6 shell components; every presentation screen must map to one of them. | I2: The matrix has zero rows where the Chapter 3 column is blank. Walk the list with the App.tsx route table open: every route you intend to open in the room appears, and no route outside the list is reachable from the demo navigation. Reviewed and signed off before any other M1 task starts. | J2: 8 | K2: Done | L2: Completed / no assignment | M2: CLOSED | N2: No new work. Preserve evidence and do not reopen unless a regression proves it. | O2: — | P2: CARRIED v2.9.2 | Q2: Done — backlog-claimed; closure evidence not reloaded in this pass | S2: No new contradiction identified in this pass | V2: — | W2: CLOSED | X2: Low / not newly identified | Y2: Deep design reconciliation 16-Aug-2026; Chapter 3/4 + Layer-B architecture + latest source/audit evidence | Z2: Track 1 — Presentation / Demo | AA2: 2026-08-20 Presentation RC | AB2: M1 Contract | AC2: Presentation-visible contract. Prepared Fleet v2 topology is allowed; no fake product behaviour and no production-only scope. | AD2: Closed | AE2: CLOSED | AF2: Closed / evidence preserved | AG2: Closed | AH2: 0 | AI2: 0 | AJ2: =IF($K2="Done",0,MAX(0.25,$J2/$AH2)) -> 0 | AK2: =IF($K2="Done",0,$AJ2*$AI2) -> 0 | AL2: CLOSED | AM2: Closed — do not reopen without contradictory regression evidence. | AN2: No active lock. | AO2: None — preserve evidence.
A3: T-002 | B3: M1 | C3: M1-P1 | D3: Audit every presented route and control against the Chapter 3 page inventory | E3: Frontend | F3: Design contract | G3: Critical | H3: CORRECTED IN v2.1. The v2.0 validation only forbade phase-token routes, which was too narrow - and the code proves it was also unnecessary, because every to: value in AppLayout.tsx is already canonical and the legacy /phase8, /phase9 and /phase15 paths are Navigate reverse redirects that no navigation entry points at. The real task is wider. Compare EVERY presented route, EVERY JourneyRail stage and EVERY navigation entry against the Chapter 3 4.4 canonical inventory of 40 route pages plus 6 shell components. For each, record the Chapter 3 contract id or record it as out-of-inventory. An out-of-inventory surface that is opened in the room is a frozen contract nobody chose. Note that PPIQ-T12 (navigationContract.test.ts) already ships from this task's own applied pack and covers the token rule; the audit below extends it, it does not repeat it. | I3: A table with one row per presented route, per JourneyRail stage and per navigation entry, each carrying a Chapter 3 contract id or an explicit out-of-inventory decision. Zero rows left undecided. Cross-check the JourneyRail stage list against Chapter 2 3.3.1 J1 to J15 - a stage that names a journey step the design does not have is a defect. | J3: 8 | K3: Done | L3: Completed / no assignment | M3: CLOSED | N3: No new work. Preserve evidence and do not reopen unless a regression proves it. | O3: — | P3: CARRIED v2.9.2 | Q3: Done — backlog-claimed; closure evidence not reloaded in this pass | S3: No new contradiction identified in this pass | V3: — | W3: CLOSED | X3: Low / not newly identified | Y3: Deep design reconciliation 16-Aug-2026; Chapter 3/4 + Layer-B architecture + latest source/audit evidence | Z3: Track 1 — Presentation / Demo | AA3: 2026-08-20 Presentation RC | AB3: M1 Contract | AC3: Presentation-visible contract. Prepared Fleet v2 topology is allowed; no fake product behaviour and no production-only scope. | AD3: Closed | AE3: CLOSED | AF3: Closed / evidence preserved | AG3: Closed | AH3: 0 | AI3: 0 | AJ3: =IF($K3="Done",0,MAX(0.25,$J3/$AH3)) -> 0 | AK3: =IF($K3="Done",0,$AJ3*$AI3) -> 0 | AL3: CLOSED | AM3: Closed — do not reopen without contradictory regression evidence. | AN3: No active lock. | AO3: None — preserve evidence.
A4: T-003 | B4: M1 | C4: M1-P1 | D4: Lock the presentation profile as a data profile, not a branch | E4: Infrastructure | F4: Environments | G4: Critical | H4: Chapter 6 forbids environment branches: the same artifact moves across environments. Confirm scripts/run/start-api.ps1 keeps its ValidateSet local/test/server/presentation and that the only difference between profiles is env/profiles/*.env. Fix the duplicated ConnectionStrings__PlantProcessDb declaration that appears twice (lines 18 and 19) in both local.env and presentation.env. Add a top-of-file comment to start-api.ps1 stating that the default is `local` and that the presentation must be launched with -Profile presentation. | I4: Run `.\scripts\run\start-api.ps1 -Profile presentation` and hit GET /api/ml/foundation/readiness. It must report outcome_values around 195,221 and correlation_results around 320, which proves the API is on ppiq_presentation. Repeat with -Profile local and confirm the numbers differ. Record both outputs in the evidence folder. | J4: 4 | K4: Done | L4: Completed / no assignment | M4: CLOSED | N4: No new work. Preserve evidence and do not reopen unless a regression proves it. | O4: — | P4: CARRIED v2.9.2 | Q4: Done — backlog-claimed; closure evidence not reloaded in this pass | S4: No new contradiction identified in this pass | V4: — | W4: CLOSED | X4: Low / not newly identified | Y4: Deep design reconciliation 16-Aug-2026; Chapter 3/4 + Layer-B architecture + latest source/audit evidence | Z4: Track 1 — Presentation / Demo | AA4: 2026-08-20 Presentation RC | AB4: M1 Contract | AC4: Presentation is a profile/release artifact, NOT a long-lived code branch. Freeze with immutable tag/release + presentation profile/database. | AD4: Closed | AE4: CLOSED | AF4: Closed / evidence preserved | AG4: Closed | AH4: 0 | AI4: 0 | AJ4: =IF($K4="Done",0,MAX(0.25,$J4/$AH4)) -> 0 | AK4: =IF($K4="Done",0,$AJ4*$AI4) -> 0 | AL4: CLOSED | AM4: Closed — do not reopen without contradictory regression evidence. | AN4: No active lock. | AO4: None — preserve evidence.
A5: T-004 | B5: M1 | C5: M1-P1 | D5: Create the M1 acceptance checklist and evidence folder | E5: Documentation | F5: Quality | G5: Important | H5: Create docs/m1/ACCEPTANCE.md holding the UI/UX Golden Gate as a checklist applied per screen: Standard* components where one exists, no raw local styling, primary Electric Blue, selection Electric Cyan, secondary Corporate Blue, warning and refusal Amber, destructive Hot Red, muted Muted Steel, inline-start/inline-end never left/right, keyboard path, RTL mirror, all seven states (Empty, Loading, Populated, Filtered-empty, Blocked, Refused, Failed), widget failure isolation, registry-driven customer vocabulary, no number without evidence. Create docs/m1/evidence/ for screenshots and command output. | I5: Every screen in the traceability matrix has a checklist instance in the folder. A screen is not Green until every line is ticked with an evidence file name beside it. | J5: 4 | K5: Done | L5: Completed / no assignment | M5: CLOSED | N5: No new work. Preserve evidence and do not reopen unless a regression proves it. | O5: — | P5: CARRIED v2.9.2 | Q5: Done — backlog-claimed; closure evidence not reloaded in this pass | S5: No new contradiction identified in this pass | V5: — | W5: CLOSED | X5: Low / not newly identified | Y5: Deep design reconciliation 16-Aug-2026; Chapter 3/4 + Layer-B architecture + latest source/audit evidence | Z5: Track 1 — Presentation / Demo | AA5: 2026-08-20 Presentation RC | AB5: M1 Contract | AC5: Presentation-visible contract. Prepared Fleet v2 topology is allowed; no fake product behaviour and no production-only scope. | AD5: Closed | AE5: CLOSED | AF5: Closed / evidence preserved | AG5: Closed | AH5: 0 | AI5: 0 | AJ5: =IF($K5="Done",0,MAX(0.25,$J5/$AH5)) -> 0 | AK5: =IF($K5="Done",0,$AJ5*$AI5) -> 0 | AL5: CLOSED | AM5: Closed — do not reopen without contradictory regression evidence. | AN5: No active lock. | AO5: None — preserve evidence.
A6: T-005 | B6: M1 | C6: M1-P1 | D6: Rebuild ppiq_presentation into scratch and diff against live | E6: Database | F6: Presentation data | G6: Critical | H6: scripts/demo/Rebuild-PresentationDb.ps1 rebuilds the demo database in one command, but it restores from deploy/.ppiq-snapshots/ppiq_app_20260713_203359.dump, a 13 July snapshot. Every correction made against the live presentation database between 14 and 27 July survives a rebuild only if it became one of the script's steps. Run the script with -TargetDb ppiq_presentation_scratch (the script's guard requires the name to contain 'presentation'), then produce a diff: object list (tables, views, functions, triggers, indexes) and row count per table, scratch versus live. | I6: Produce docs/m1/evidence/presentation_db_diff.txt. Acceptance is either an empty diff, or a written list of every difference. Do not proceed to the next task until that list exists, and never run the rebuild against the live database before it does. | J6: 6 | K6: Done | L6: Completed / no assignment | M6: CLOSED | N6: No new work. Preserve evidence and do not reopen unless a regression proves it. | O6: — | P6: CARRIED v2.9.2 | Q6: Done — backlog-claimed; closure evidence not reloaded in this pass | S6: No new contradiction identified in this pass | V6: — | W6: CLOSED | X6: Low / not newly identified | Y6: Deep design reconciliation 16-Aug-2026; Chapter 3/4 + Layer-B architecture + latest source/audit evidence | Z6: Track 1 — Presentation / Demo | AA6: 2026-08-20 Presentation RC | AB6: M1 Contract | AC6: Presentation-visible contract. Prepared Fleet v2 topology is allowed; no fake product behaviour and no production-only scope. | AD6: Closed | AE6: CLOSED | AF6: Closed / evidence preserved | AG6: Closed | AH6: 0 | AI6: 0 | AJ6: =IF($K6="Done",0,MAX(0.25,$J6/$AH6)) -> 0 | AK6: =IF($K6="Done",0,$AJ6*$AI6) -> 0 | AL6: CLOSED | AM6: Closed — do not reopen without contradictory regression evidence. | AN6: No active lock. | AO6: None — preserve evidence.
A7: T-006 | B7: M1 | C7: M1-P1 | D7: Convert every diff finding into a seed or migration script | E7: Database | F7: Presentation data | G7: Critical | H7: For each row of the diff from the previous task, decide: is this a product fix (goes to Backend/database/scripts as a numbered migration) or presentation data (goes to scripts/demo as a seed step)? The governing law is that presentation DATA may be presentation-only but presentation FIXES may never be. Add each item in the correct place and re-run the rebuild. | I7: Re-run Rebuild-PresentationDb.ps1 into a fresh scratch database and re-run the diff. It must now be empty. That output is the proof that no fix exists only as data. | J7: 8 | K7: Done | L7: Completed / no assignment | M7: CLOSED | N7: No new work. Preserve evidence and do not reopen unless a regression proves it. | O7: — | P7: CARRIED v2.9.2 | Q7: Done — backlog-claimed; closure evidence not reloaded in this pass | S7: No new contradiction identified in this pass | V7: — | W7: CLOSED | X7: Low / not newly identified | Y7: Deep design reconciliation 16-Aug-2026; Chapter 3/4 + Layer-B architecture + latest source/audit evidence | Z7: Track 1 — Presentation / Demo | AA7: 2026-08-20 Presentation RC | AB7: M1 Contract | AC7: Presentation-visible contract. Prepared Fleet v2 topology is allowed; no fake product behaviour and no production-only scope. | AD7: Closed | AE7: CLOSED | AF7: Closed / evidence preserved | AG7: Closed | AH7: 0 | AI7: 0 | AJ7: =IF($K7="Done",0,MAX(0.25,$J7/$AH7)) -> 0 | AK7: =IF($K7="Done",0,$AJ7*$AI7) -> 0 | AL7: CLOSED | AM7: Closed — do not reopen without contradictory regression evidence. | AN7: No active lock. | AO7: None — preserve evidence.
A8: T-007 | B8: M1 | C8: M1-P1 | D8: Presentation Phenomena and Widget Coverage Matrix, part 1: inventory and the 36-chart blueprint | E8: Documentation | F8: Presentation data | G8: Critical | H8: REOPENED IN v2.5 - source truth changed after runtime measurement. The artifacts stand, but they were written against FLEET_RELATIONS.md, and measurement proved that document describes a larger, richer emulation than the one staged: 630 heats not 1,802, 5,670 coils not 18,661, 1,987 defects not 34,312, SIX defect codes not twenty, and THREE chemistry elements at one station not twelve at three. This task does not restart, and it does NOT stay half-open until the fleet is rebuilt - a task that closes twenty tasks later violates both the ordering law and the no-PARTIAL rule. It closes HERE as a PRE-GENERATION SPECIFICATION: the measured current inventory plus the 36-chart blueprint. Post-generation re-measurement and final certification belong to the phenomenon-proof task in M1-P1b, which cites this task by name so the link is machine-checked from that end. REWRITTEN IN v2.4. The previous version documented seventeen relations; that was necessary but not sufficient. Two halves, and the ORDER IS THE POINT. First, inventory what the emulation already carries - chemistry by grade at whatever element count and sampling stations MEASUREMENT SHOWS - the v2.4 text said twelve elements across three stations and that was taken from a document; measurement found THREE elements at ONE station, so the inventory records what is there, additives by grade, sequence grouping, crew rotation, ladle reline counters, cold-furnace and maintenance reheating, downtime propagation, roll wear, lubrication windows, and the seventeen planted relations with their negative controls. Second, write the 36-CHART BLUEPRINT: six primary presentation pages times six visual stories, with the seventh dashboard kept as the technical backup page. For each chart state what it must SHOW - not which correlation it must prove. The acceptance standard for the dataset changes here: every one of the 36 widgets needs an intentional visual story, sufficient population and cardinality, realistic variation, and at least one meaningful drill or filter interaction. NOT every chart must reveal a correlation. Planting a hundred clean correlations would make the plant look fabricated, which costs more credibility than a flat chart does. | I8: Two artifacts in the evidence folder: the emulation inventory with a source and a row count per structure, and the blueprint with 36 rows each naming its page, chart type, and the visual story it must tell. A reviewer must be able to say, for each of the 36, what would make that chart boring - because that is the specification the data has to beat. | J8: 10 | K8: Done | L8: Completed / no assignment | M8: CLOSED | N8: No new work. Preserve evidence and do not reopen unless a regression proves it. | O8: — | P8: CARRIED v2.9.2 | Q8: Done — backlog-claimed; closure evidence not reloaded in this pass | S8: No new contradiction identified in this pass | V8: — | W8: CLOSED | X8: Low / not newly identified | Y8: Deep design reconciliation 16-Aug-2026; Chapter 3/4 + Layer-B architecture + latest source/audit evidence | Z8: Track 1 — Presentation / Demo | AA8: 2026-08-20 Presentation RC | AB8: M1 Contract | AC8: Presentation-visible contract. Prepared Fleet v2 topology is allowed; no fake product behaviour and no production-only scope. | AD8: Closed | AE8: CLOSED | AF8: Closed / evidence preserved | AG8: Closed | AH8: 0 | AI8: 0 | AJ8: =IF($K8="Done",0,MAX(0.25,$J8/$AH8)) -> 0 | AK8: =IF($K8="Done",0,$AJ8*$AI8) -> 0 | AL8: CLOSED | AM8: Closed — do not reopen without contradictory regression evidence. | AN8: No active lock. | AO8: None — preserve evidence.
A9: T-008 | B9: M1 | C9: M1-P1 | D9: Presentation Phenomena and Widget Coverage Matrix, part 2: map, classify, close | E9: Testing | F9: Dashboard | G9: Critical | H9: REOPENED IN v2.5 alongside part one, for the same reason: it cites effect sizes and defect codes that do not exist in the staged data. R1 CRACK_LONG at 9.3x, R2 INCLUSION at 4.5x and R4 SLIPPAGE_MARK at 28.9x have NO corresponding staged defect code. Aluminium, sulfur, niobium and nitrogen are absent, so four relation families cannot exist here whatever the document says. The 104 rows are kept as the SPECIFICATION OF WHAT THE FLEET MUST CARRY, and become the input to the Fleet v2 target rather than a description of what exists. This task ALSO closes here, before any generator work, and it carries one addition: PREDECLARE the expected direction, the acceptable effect band and the negative control for every phenomenon. Declaring them before the data exists is what stops the later proof from being self-fulfilling. REWRITTEN IN v2.4 as part two of the matrix. One row per phenomenon, with these columns: phenomenon; source systems; population; variables; intended effect; noise; primary chart; secondary chart; dashboard; expected analysis result; NEGATIVE CONTROL; genealogy requirement; current status EXISTING, ENRICH or NEW; and the exact automated assertion that validates it. Target roughly 85 to 110 micro-variations, distributed as 18-25 strong discoverable relationships, 20-25 moderate or conditional, 15-20 shift, crew, campaign and maintenance regimes, 8-12 temporal drifts or regime changes, 8-12 outliers or short abnormal events, and 15-20 negative controls and noise. Most of those will be extensions of the seventeen existing relation families rather than new inventions. Then map each of the 36 charts to at least one phenomenon or to a legitimate operational baseline, and give every widget a decision: KEEP, ENHANCE, REBIND, ADD WIDGET, EXTEND EMULATION, NEEDS RELATIONSHIP SLICE, or REMOVE. Weak bindings are not data shortages - Defects by Equipment returned one row in the last audit and the remedy is canonical equipment attribution or relationship resolution, never more rows. | I9: docs/m1/evidence/phenomena_widget_matrix.csv with no blank cells. Every one of the 36 charts references at least one phenomenon or a named operational baseline. Every EXTEND EMULATION row names the exact field, so the generator work has a closed list. Every phenomenon carries its automated assertion, so the statistical QA task has nothing left to invent. | J9: 10 | K9: Done | L9: Completed / no assignment | M9: CLOSED | N9: No new work. Preserve evidence and do not reopen unless a regression proves it. | O9: — | P9: CARRIED v2.9.2 | Q9: Done — backlog-claimed; closure evidence not reloaded in this pass | S9: No new contradiction identified in this pass | V9: — | W9: CLOSED | X9: Low / not newly identified | Y9: Deep design reconciliation 16-Aug-2026; Chapter 3/4 + Layer-B architecture + latest source/audit evidence | Z9: Track 1 — Presentation / Demo | AA9: 2026-08-20 Presentation RC | AB9: M1 Contract | AC9: Presentation-visible contract. Prepared Fleet v2 topology is allowed; no fake product behaviour and no production-only scope. | AD9: Closed | AE9: CLOSED | AF9: Closed / evidence preserved | AG9: Closed | AH9: 0 | AI9: 0 | AJ9: =IF($K9="Done",0,MAX(0.25,$J9/$AH9)) -> 0 | AK9: =IF($K9="Done",0,$AJ9*$AI9) -> 0 | AL9: CLOSED | AM9: Closed — do not reopen without contradictory regression evidence. | AN9: No active lock. | AO9: None — preserve evidence.
A10: T-009 | B10: M1 | C10: M1-P1 | D10: Downtime two-quantity contract: final schema and domain slice | E10: Backend | F10: Canonical model | G10: Critical | H10: CORRECTED IN v2.1, and this was a materially wrong task. v2.0 treated the downtime work as data seeding only. It is not. The canonical DowntimeEvent entity carries timestamps, equipment, a DowntimeType and a reason, but it does NOT carry the two quantities the design requires. Chapter 3 4.5.4 specifies stopped_minutes and production_impact_minutes as separate columns, both NOT NULL and both greater than or equal to zero, because they are different quantities and one may never stand in for the other - a twenty-minute mill stoppage absorbed by buffer slabs costs no production, while a three-minute caster pump stoppage can force a sequence rebuild and cost six hours. Add both fields to the domain entity, write the migration, and extend the projection mapping so a projected downtime row carries both. Use the final column names so M2a extends rather than migrates. | I10: Project a downtime batch and assert every row has both columns populated and non-negative. Attempt an insert with a null production_impact_minutes and confirm the database rejects it. Confirm no code path derives one quantity from the other. | J10: 6 | K10: Done | L10: Completed / no assignment | M10: CLOSED | N10: No new work. Preserve evidence and do not reopen unless a regression proves it. | O10: — | P10: CARRIED v2.9.2 | Q10: Done — backlog-claimed; closure evidence not reloaded in this pass | S10: No new contradiction identified in this pass | V10: — | W10: CLOSED | X10: Low / not newly identified | Y10: Deep design reconciliation 16-Aug-2026; Chapter 3/4 + Layer-B architecture + latest source/audit evidence | Z10: Track 1 — Presentation / Demo | AA10: 2026-08-20 Presentation RC | AB10: M1 Contract | AC10: Presentation-visible contract. Prepared Fleet v2 topology is allowed; no fake product behaviour and no production-only scope. | AD10: Closed | AE10: CLOSED | AF10: Closed / evidence preserved | AG10: Closed | AH10: 0 | AI10: 0 | AJ10: =IF($K10="Done",0,MAX(0.25,$J10/$AH10)) -> 0 | AK10: =IF($K10="Done",0,$AJ10*$AI10) -> 0 | AL10: CLOSED | AM10: Closed — do not reopen without contradictory regression evidence. | AN10: No active lock. | AO10: None — preserve evidence.
A11: T-010 | B11: M1 | C11: M1-P1 | D11: Run the canonical semantic path end to end through the M1 compatibility boundaries | E11: Engine | F11: Presentation data | G11: Critical | H11: CORRECTED IN v2.1. The v2.0 wording implied the final physical topology is in place. It is not, and it is not supposed to be before M2a. What M1 proves is the canonical SEMANTIC path: connection test, dataset registration, incremental import into staging, canonical projection through the customer-authored mapping, genealogy, feature and outcome refresh, then an analysis run - each step reached through the product's own services, never by loading a target table directly. Record row counts at every stage. Note the sequencing: the final external definition contract is built later in M1-P2, so this walk is repeated once it lands - the second walk is what proves the contract did not change behaviour. | I11: One command log showing a single row entering at the source and appearing in material_units and the canonical views, with stage counts that are monotonic and explainable. Every write on the path goes through the final service interface, not a table name - which is what lets M2a replace the storage without this test changing. | J11: 8 | K11: Done | L11: Completed / no assignment | M11: CLOSED | N11: No new work. Preserve evidence and do not reopen unless a regression proves it. | O11: — | P11: CARRIED v2.9.2 | Q11: Done — backlog-claimed; closure evidence not reloaded in this pass | S11: No new contradiction identified in this pass | V11: — | W11: CLOSED | X11: Low / not newly identified | Y11: Deep design reconciliation 16-Aug-2026; Chapter 3/4 + Layer-B architecture + latest source/audit evidence | Z11: Track 1 — Presentation / Demo | AA11: 2026-08-20 Presentation RC | AB11: M1 Contract | AC11: Presentation-visible contract. Prepared Fleet v2 topology is allowed; no fake product behaviour and no production-only scope. | AD11: Closed | AE11: CLOSED | AF11: Closed / evidence preserved | AG11: Closed | AH11: 0 | AI11: 0 | AJ11: =IF($K11="Done",0,MAX(0.25,$J11/$AH11)) -> 0 | AK11: =IF($K11="Done",0,$AJ11*$AI11) -> 0 | AL11: CLOSED | AM11: Closed — do not reopen without contradictory regression evidence. | AN11: No active lock. | AO11: None — preserve evidence.
A12: T-011 | B12: M1 | C12: M1-P1 | D12: Establish and fix the architecture test pool reliability | E12: Testing | F12: CI/CD | G12: Very Important | H12: NEW IN v2.1, raised by a real failure. The navigation contract pack auto-reverted on a gate that reported 15 files and 57 tests passing with one error: a vitest worker failed to START for noMojibake.test.ts and never ran. A re-run went green, which means the gate is intermittent. The diagnostic inventory found the cause candidate: all 16 architecture test files declare no environment and none needs a DOM, yet the suite spends 40 to 45 seconds of a 62 to 68 second run on environment setup and teardown - roughly two thirds of the wall time paid for a browser environment nothing uses. Add // @vitest-environment node to the architecture test files, or set it for that directory in the vitest config. Do not raise a timeout and do not add a retry: a gate that is argued with is a gate that gets switched off, and one that fails at random teaches the team to re-run until green, which is how a real failure gets ignored. | I12: Ten consecutive runs of the architecture suite on a clean tree, all green, with zero worker-start timeouts, recorded in the evidence folder. Report the wall time before and after; the environment share should fall sharply. This matters because M1-P5 certification depends on this pool - the golden journey and the visual and accessibility gates run on it, on the two days when there is no time left to diagnose anything. | J12: 6 | K12: Done | L12: Completed / no assignment | M12: CLOSED | N12: No new work. Preserve evidence and do not reopen unless a regression proves it. | O12: — | P12: CARRIED v2.9.2 | Q12: Done — backlog-claimed; closure evidence not reloaded in this pass | S12: No new contradiction identified in this pass | V12: — | W12: CLOSED | X12: Low / not newly identified | Y12: Deep design reconciliation 16-Aug-2026; Chapter 3/4 + Layer-B architecture + latest source/audit evidence | Z12: Track 1 — Presentation / Demo | AA12: 2026-08-20 Presentation RC | AB12: M1 Contract | AC12: Presentation-visible contract. Prepared Fleet v2 topology is allowed; no fake product behaviour and no production-only scope. | AD12: Closed | AE12: CLOSED | AF12: Closed / evidence preserved | AG12: Closed | AH12: 0 | AI12: 0 | AJ12: =IF($K12="Done",0,MAX(0.25,$J12/$AH12)) -> 0 | AK12: =IF($K12="Done",0,$AJ12*$AI12) -> 0 | AL12: CLOSED | AM12: Closed — do not reopen without contradictory regression evidence. | AN12: No active lock. | AO12: None — preserve evidence.
A13: T-012 | B13: M1 | C13: M1-P1 | D13: Canonicalise the JourneyRail to J1 to J15 | E13: Frontend | F13: Journey | G13: Critical | H13: NEW IN v2.3, raised by the presented-surface audit and it is a Rule 3 violation that has been on every authenticated page. JourneyRail.tsx declares its OWN fifteen-stage journey in a hardcoded STAGES array and renders it as Step N of 15. It is not the canonical J1 to J15: different steps, different order, same numbering. Rule 3 says a second journey written anywhere is deleted rather than reconciled. Four further defects sit on top. Stage 4 Prepare mapping has only /data-integration/prepare as its match prefix, which stage 2 already claims, and the longest-prefix tie-break takes the first, so stage 4 can never become the current stage. Stage 5 points at /data-integration/author-mapping, which the audit rules out of inventory. Stage 8 points at AnalysisJobConfigPage, which leaves the M1 navigation. Stage 12 is labelled AI/ML jobs and points at the Jobs Monitor. Stage 15 points at /assistant, but Chapter 3 gives the assistant no route because G1 is a shell component. Rewrite STAGES to the canonical journey with the Chapter 2 3.3.1 labels, render J1 to J3 as completed commissioning so the count is honest, give each stage exactly one unambiguous match prefix, and repoint stages 5, 8 and 15. | I13: A test asserting the rail's stage count and labels equal the canonical journey, in the same shape as PPIQ-T12. Walk every presented route and confirm the rail highlights exactly one stage, and that the stage it highlights is the journey step that route serves. No stage may be unreachable. | J13: 6 | K13: Done | L13: Completed / no assignment | M13: CLOSED | N13: No new work. Preserve evidence and do not reopen unless a regression proves it. | O13: — | P13: CARRIED v2.9.2 | Q13: Done — backlog-claimed; closure evidence not reloaded in this pass | S13: No new contradiction identified in this pass | V13: — | W13: CLOSED | X13: Low / not newly identified | Y13: Deep design reconciliation 16-Aug-2026; Chapter 3/4 + Layer-B architecture + latest source/audit evidence | Z13: Track 1 — Presentation / Demo | AA13: 2026-08-20 Presentation RC | AB13: M1 Contract | AC13: Presentation-visible contract. Prepared Fleet v2 topology is allowed; no fake product behaviour and no production-only scope. | AD13: Closed | AE13: CLOSED | AF13: Closed / evidence preserved | AG13: Closed | AH13: 0 | AI13: 0 | AJ13: =IF($K13="Done",0,MAX(0.25,$J13/$AH13)) -> 0 | AK13: =IF($K13="Done",0,$AJ13*$AI13) -> 0 | AL13: CLOSED | AM13: Closed — do not reopen without contradictory regression evidence. | AN13: No active lock. | AO13: None — preserve evidence.
... A44: T-043 | B44: M1 | C44: M1-P3 | D44: Bring the workspace to the final D1 anatomy | E44: Frontend | F44: Dashboard | G44: Critical | H44: EXPANDED IN v2.1. v2.0 described header, selections bar, grid and associative strip, and treated the current DashboardFilterBar as the final architecture. Chapter 4 5.1.2 asks for more: header, PERMANENT selection bar, associative strip, SHEET NAVIGATOR, and a 12-column widget grid. It also defines the relationship between a filter WIDGET placed on the page and the page-level selection state, and the as-of and edit semantics. Do not freeze DashboardFilterBar as the final shape - align it to the specified selection bar, and add the sheet navigator so a page with more than one sheet is navigable. | I44: Screenshot against the 5.1.2 diagram. Apply three selections and confirm three removable chips appear and that removing one updates every widget. Add a second sheet and confirm the navigator switches between them while the selection bar persists. Place a filter widget on the page and confirm it composes with the page-level selection rather than competing with it. | J44: 12 | K44: Done | L44: Completed / no assignment | M44: CLOSED | N44: No new work. Preserve evidence and do not reopen unless a regression proves it. | O44: — | P44: CARRIED v2.9.2 | Q44: Done — backlog-claimed; closure evidence not reloaded in this pass | S44: No new contradiction identified in this pass | V44: — | W44: CLOSED | X44: Low / not newly identified | Y44: Deep design reconciliation 16-Aug-2026; Chapter 3/4 + Layer-B architecture + latest source/audit evidence | Z44: Track 1 — Presentation / Demo | AA44: 2026-08-20 Presentation RC | AB44: M1 Contract | AC44: Presentation-visible contract. Prepared Fleet v2 topology is allowed; no fake product behaviour and no production-only scope. | AD44: Closed | AE44: CLOSED | AF44: Closed / evidence preserved | AG44: Closed | AH44: 0 | AI44: 0 | AJ44: =IF($K44="Done",0,MAX(0.25,$J44/$AH44)) -> 0 | AK44: =IF($K44="Done",0,$AJ44*$AI44) -> 0 | AL44: CLOSED | AM44: Closed — do not reopen without contradictory regression evidence. | AN44: No active lock. | AO44: None — preserve evidence.
A45: T-044 | B45: M1 | C45: M1-P3 | D45: Certify the three operational dashboards and fix their bindings | E45: Frontend | F45: Dashboard | G45: Critical | H45: SPLIT IN v2.3 to respect the twelve-hour rule. Part one covers the three OPERATIONAL pages: Production and Shift, Quality and Chemistry, Equipment and Downtime and Flow. The seeded set is already seven and it already matches the intended story, so this is certification, not construction. Working from the coverage matrix, fix each failing widget in this order of preference: correct the widget definition in the seed script; then the chart type; only then the code. A single-row bar chart is a binding defect, not a data shortage - the last audit found Defects by Equipment returning one row, and the remedy there is canonical equipment attribution or relationship resolution, never generating more rows. AUDIT HARDENING IN v2.9.2. Treat presentation semantics as part of the binding contract. A widget is not certified merely because it returns rows: do not present raw GUIDs/technical identifiers when a registry/customer label exists, do not promote `unknown` into a meaningful business category unless the source genuinely carries an unknown bucket, and do not use a dimension whose usable cardinality makes the chart analytically degenerate. Fix the reusable binding/relationship/label path rather than Fleet-v2 screenshot-patching. | I45: Every widget on these three pages returns rows and renders the chart type its title implies. Confirm no widget title describes something other than what it plots. The chemistry conditional format draws its limits from the grade specification source data, never from a literal in the product. For every presented widget, record dimension cardinality and the human-readable label source. No raw UUID/GUID is visible where a registry label is resolvable. A Pie/Donut with one effective category, a Heatmap with only one meaningful axis, or a trend whose x-axis is merely an arbitrary date bucket for a non-temporal question fails acceptance even if it renders. | J45: 8 | K45: Done | L45: Completed / no assignment | M45: CLOSED | N45: No new work. Preserve evidence and do not reopen unless a regression proves it. | O45: — | P45: CARRIED v2.9.2 | Q45: Done — evidenced | R45: f966719f functional/data closure + 55157a98 EF/runtime migration parity | S45: Execution closed; no new design contradiction identified in this pass | V45: — | W45: CLOSED | X45: Low / not newly identified | Y45: Deep design reconciliation 16-Aug-2026; Chapter 3/4 + Layer-B architecture + latest source/audit evidence | Z45: Track 1 — Presentation / Demo | AA45: 2026-08-20 Presentation RC | AB45: M1 Contract | AC45: Presentation-visible contract. Prepared Fleet v2 topology is allowed; no fake product behaviour and no production-only scope. | AD45: Closed | AE45: CLOSED | AF45: Closed / evidence preserved | AG45: Closed | AH45: 0 | AI45: 0 | AJ45: =IF($K45="Done",0,MAX(0.25,$J45/$AH45)) -> 0 | AK45: =IF($K45="Done",0,$AJ45*$AI45) -> 0 | AL45: CLOSED | AM45: Closed — do not reopen without contradictory regression evidence. | AN45: No active lock. | AO45: None — preserve evidence.
A46: T-045 | B46: M1 | C46: M1-P3 | D46: Certify the analysis and model dashboards and choose the six shown | E46: Frontend | F46: Dashboard | G46: Critical | H46: SPLIT IN v2.3, part two. Covers Parameter Deep Analysis, Correlation and Statistical Findings, Risk Intelligence and Model Insights. Correlation is the weakest today - roughly two widgets - and it is the page that should exploit the planted relations hardest. Model Insights must stay honest: if the production model is not ready, show the five readiness dimensions with their measured values beside their thresholds rather than a fabricated prediction curve, because that refusal IS the selling point. Then record the decision: ALL SEVEN are certified, SIX are shown, and which six depends on the audience - an operations-heavy customer sees Risk and Model Insights is held back; a technical customer sees Model Insights and Risk is shortened. Nothing is deleted from the product to make a number. AUDIT HARDENING IN v2.9.2. A technically rendered but information-free visual is not an insight. A flat-zero series, single-slice donut or constant risk-class chart must be rebound to a meaningful supported question, or replaced by the honest readiness/coverage/refusal state that explains why no analytical variation exists. Prefer measured readiness, population, evidence coverage and contributor/refusal semantics over decorative empty charts. | I46: Every widget on these four pages returns rows. Confirm Model Insights makes no claim a live model has predicted anything unless one has. Record the primary six, the backup, and the reason for each choice, in the demonstration script. The six customer-facing pages contain no chart whose visible distribution is constant or single-category unless the visual is intentionally and explicitly a readiness/refusal/coverage statement. Model Insights and Risk must communicate measured state and evidence, not create the appearance of intelligence from a constant series. | J46: 6 | K46: Done | L46: Presentation lane (Workers 1/2) | M46: CLOSED | N46: Presentation target is active. Worker 3 must not edit M1 pages, presentation DB/seeds, current assistant wiring or runtime behaviour. | O46: Current M1 sequence / presentation owner hand-off | P46: CARRIED v2.9.2 | Q46: Done — evidenced | R46: T-045-R1 closed: c56008c0 / dd9a6b04 / 39ce59ef / 283aae2c | S46: Execution closed; no new design contradiction identified in this pass | V46: Current M1 sequence / presentation owner hand-off | W46: CLOSED | X46: Low / not newly identified | Y46: Deep design reconciliation 16-Aug-2026; Chapter 3/4 + Layer-B architecture + latest source/audit evidence | Z46: Track 1 — Presentation / Demo | AA46: 2026-08-20 Presentation RC | AB46: M1 Contract | AC46: Presentation-visible contract. Prepared Fleet v2 topology is allowed; no fake product behaviour and no production-only scope. | AD46: Closed | AE46: CLOSED | AF46: Closed / evidence preserved | AG46: Closed | AH46: 0 | AI46: 0 | AJ46: =IF($K46="Done",0,MAX(0.25,$J46/$AH46)) -> 0 | AK46: =IF($K46="Done",0,$AJ46*$AI46) -> 0 | AL46: CLOSED | AM46: Closed — do not reopen without contradictory regression evidence. | AN46: No active lock. | AO46: None — preserve evidence.
A47: T-046 | B47: M1 | C47: M1-P3 | D47: Register the final chart grammar and implement the presentation subset | E47: Backend | F47: Registry | G47: Critical | H47: CORRECTED IN v2.1, and this was a real design conflict. v2.0 declared the ten currently implemented chart types as the closed grammar and said do not extend it. Chapter 4 5.1.5 defines seventeen: Bar, stacked Column, Line, Area, Combo, Pie, Donut, Scatter, Heatmap, Pareto, Box plot, Histogram, Gauge, Waterfall, Table, Pivot table and KPI. Freezing ten would show the customer a smaller product than the one they receive. The correction is not to build seventeen renderers in ten days: declare the FINAL seventeen in the registry with an implemented or not-yet-available state, implement only the subset the six presentation pages need, and have the switcher offer compatible implemented types while saying in one sentence why an unavailable or incompatible type is not offered. ORDERED IN v2.2 to run before the six-grammar task, which selects from this registry. AUDIT HARDENING IN v2.9.2. Compatibility is semantic, not only renderer-capability metadata. Encode and test at minimum: temporal+numeric -> Line/Area or appropriate Bar; categorical+numeric -> Bar/Pareto; two meaningful categorical axes plus a measure -> Heatmap; numeric×numeric -> Scatter; numeric distribution -> Histogram/Box; low-cardinality categorical share -> Pie/Donut. Do not offer Pie/Donut-by-date, a Heatmap without two meaningful axes and an intensity, or a one-value categorical Pie merely because the renderer can draw it. | I47: The registry returns seventeen chart types. The switcher on a temporal-dimension widget offers only compatible implemented types and gives a reason for each omission. Flip one type from not-yet-available to implemented in the registry and confirm it becomes selectable with no code change. Switch a KPI to Bar and back to KPI and confirm the round trip works. Add known-compatible and known-incompatible binding tests for those pairings. A switcher must explain why an incompatible type is unavailable. Deliberately pass Date+measure to Pie/Donut and one-axis data to Heatmap and prove both are refused before rendering. | J47: 8 | K47: Done | L47: Presentation lane (Workers 1/2) | M47: CLOSED | N47: Presentation target is active. Worker 3 must not edit M1 pages, presentation DB/seeds, current assistant wiring or runtime behaviour. | O47: Current M1 sequence / presentation owner hand-off | P47: CARRIED v2.9.2 | Q47: Done — evidenced | R47: 56ade951 R1 generic heatmap/combo; prior grammar fc146483 | S47: Execution closed; no new design contradiction identified in this pass | V47: Current M1 sequence / presentation owner hand-off | W47: CLOSED | X47: Low / not newly identified | Y47: Deep design reconciliation 16-Aug-2026; Chapter 3/4 + Layer-B architecture + latest source/audit evidence | Z47: Track 1 — Presentation / Demo | AA47: 2026-08-20 Presentation RC | AB47: M1 Contract | AC47: Presentation-visible contract. Prepared Fleet v2 topology is allowed; no fake product behaviour and no production-only scope. | AD47: Closed | AE47: CLOSED | AF47: Closed / evidence preserved | AG47: Closed | AH47: 0 | AI47: 0 | AJ47: =IF($K47="Done",0,MAX(0.25,$J47/$AH47)) -> 0 | AK47: =IF($K47="Done",0,$AJ47*$AI47) -> 0 | AL47: CLOSED | AM47: Closed — do not reopen without contradictory regression evidence. | AN47: No active lock. | AO47: None — preserve evidence.
A48: T-047 | B48: M1 | C48: M1-P3 | D48: Give the seven pages distinct visual grammars from the registered grammar | E48: Frontend | F48: Dashboard | G48: Very Important | H48: Runs AFTER the chart grammar registry, because the grammars are chosen from the FINAL registered set rather than from whichever types happen to be implemented today. Seven pages that are all bar charts read as one page shown seven times. The intended languages, page by page: Production takes KPI with trend, stacked column by shift, bar by grade, area for weekly throughput and a detail table; Quality takes KPI with sparkline, Pareto by defect type, stacked bar by grade, a positional heatmap of defects along coil length and width, and a conditionally formatted chemistry table; Equipment takes bar, Pareto and a paired-column comparison of equipment stoppage against production impact; Parameter Deep Analysis takes histogram, box plot by grade and scatter; Correlation takes a parameter-by-outcome heatmap, a ranked contributor bar and a before-and-after conditioning pair; Risk takes KPI, trend, distribution and a contribution table; Model Insights takes the five readiness dimensions as status cards with coverage bars. AUDIT HARDENING IN v2.9.2. Distinct analytical grammars must still look like one product. Every page uses the same application typography, spacing scale, control primitives, card anatomy, state colours, focus language and motion rules; variation comes from the analytical story and chart grammar, not from page-local design systems. | I48: Place the seven pages side by side as screenshots. A reviewer who has not seen the product must be able to say what each page is for from the shapes alone. Every chart type used appears in the registry as implemented. The conditional-formatting table must draw its limits from the grade specification source data, never from a literal in the product. In the seven-page screenshot comparison, reject any page that introduces a different font scale, card language, control styling or motion vocabulary. The pages must be recognisably different in analytical purpose and recognisably identical in product identity. | J48: 10 | K48: Done | L48: Presentation lane (Workers 1/2) | M48: CLOSED | N48: Presentation target is active. Worker 3 must not edit M1 pages, presentation DB/seeds, current assistant wiring or runtime behaviour. | O48: Current M1 sequence / presentation owner hand-off | P48: CARRIED v2.9.2 | Q48: Done — evidenced | R48: 4b431463 semantic/data certification + 3cdd3a23 frontend conformance | S48: Execution closed; no new design contradiction identified in this pass | V48: Current M1 sequence / presentation owner hand-off | W48: CLOSED | X48: Low / not newly identified | Y48: Deep design reconciliation 16-Aug-2026; Chapter 3/4 + Layer-B architecture + latest source/audit evidence | Z48: Track 1 — Presentation / Demo | AA48: 2026-08-20 Presentation RC | AB48: M1 Contract | AC48: Presentation-visible contract. Prepared Fleet v2 topology is allowed; no fake product behaviour and no production-only scope. | AD48: Closed | AE48: CLOSED | AF48: Closed / evidence preserved | AG48: Closed | AH48: 0 | AI48: 0 | AJ48: =IF($K48="Done",0,MAX(0.25,$J48/$AH48)) -> 0 | AK48: =IF($K48="Done",0,$AJ48*$AI48) -> 0 | AL48: CLOSED | AM48: Closed — do not reopen without contradictory regression evidence. | AN48: No active lock. | AO48: None — preserve evidence.
A49: T-048 | B49: M1 | C49: M1-P3 | D49: Associative model, part 1: the alternative state and registry-driven fields | E49: Frontend | F49: Dashboard | G49: Very Important | H49: SPLIT IN v2.2 by dependency. Part 1 has no dependency outside this phase and runs here; part 2 needs the relationship resolver and runs in M1-P4 after it exists. Do not rebuild the excluded pivot - it already works, an excluded value can be clicked and the selection pivots. The work here is twofold: add the ALTERNATIVE state, which is the fourth state Chapter 4 5.1.3 requires and which is missing today; and make the associative field set registry-driven instead of a fixed list. | I49: All four states render distinctly - selected, possible, excluded, alternative - on the token colours, selection Electric Cyan and excluded Muted Steel. Add a dimension through the registry and confirm it appears in the strip with no code change. | J49: 4 | K49: Done | L49: Presentation lane (Workers 1/2) | M49: CLOSED | N49: Presentation target is active. Worker 3 must not edit M1 pages, presentation DB/seeds, current assistant wiring or runtime behaviour. | O49: Current M1 sequence / presentation owner hand-off | P49: CARRIED v2.9.2 | Q49: Done — evidenced | R49: b687cba4 associative selection states | S49: Execution closed; no new design contradiction identified in this pass | V49: Current M1 sequence / presentation owner hand-off | W49: CLOSED | X49: Low / not newly identified | Y49: Deep design reconciliation 16-Aug-2026; Chapter 3/4 + Layer-B architecture + latest source/audit evidence | Z49: Track 1 — Presentation / Demo | AA49: 2026-08-20 Presentation RC | AB49: M1 Contract | AC49: Presentation-visible contract. Prepared Fleet v2 topology is allowed; no fake product behaviour and no production-only scope. | AD49: Closed | AE49: CLOSED | AF49: Closed / evidence preserved | AG49: Closed | AH49: 0 | AI49: 0 | AJ49: =IF($K49="Done",0,MAX(0.25,$J49/$AH49)) -> 0 | AK49: =IF($K49="Done",0,$AJ49*$AI49) -> 0 | AL49: CLOSED | AM49: Closed — do not reopen without contradictory regression evidence. | AN49: No active lock. | AO49: None — preserve evidence.
A50: T-049 | B50: M1 | C50: M1-P3 | D50: Certify layout drag, resize, save, reload and responsive behaviour | E50: Frontend | F50: Dashboard | G50: Important | H50: REDUCED IN v2.1 from implementation to certification. useDashboardGridLayout and useDashboardLayoutPersistence already serialise, save and reload the grid through the API. The work is hardening and proof, not building: confirm the Save layout control confirms with a toast, that a reload restores exactly what was saved, and that the behaviour holds at 1920x1080, 1440x900 and 1280x800. | I50: Move and resize three widgets, save, hard-reload, and confirm the layout is identical. Repeat at each of the three widths. Record a short screen capture into the evidence folder. v2.10.2 ACCEPTANCE CORRECTION — each viewport is isolated. Snapshot the original persisted layout, perform a relative mutation that is guaranteed to differ from the starting canonical geometry, SAVE and capture the PATCH layoutJson, poll until the DOM converges to the saved active-breakpoint geometry, hard reload, prove GET layoutJson == PATCH layoutJson and poll to the same rendered geometry, then restore the original layout in a finally/cleanup path. 'Changed' means the stable post-save canonical/rendered state, not transient mouse-up pixels. Run 1920x1080, 1440x900 and 1280x800 serially with zero skips and no cross-test state contamination. | J50: 4 | K50: Done | L50: Presentation lane (Workers 1/2) | M50: CLOSED | N50: Presentation target is active. Worker 3 must not edit M1 pages, presentation DB/seeds, current assistant wiring or runtime behaviour. | O50: Current M1 sequence / presentation owner hand-off | P50: v2.10.2 — isolated canonical round-trip acceptance after R1-R4 test-oracle findings | Q50: In Progress — canonical PATCH/GET persistence proven; final isolated viewport certification and baseline restoration remain. | R50: 16-Aug-2026 R1–R4: auth/license + canonical persistence green; current work is final test isolation/oracle convergence, not backend persistence. | S50: REVISE — important design/coverage issue | T50: F-070 [Very Important] — R1-R4 exposed two test-design flaws: viewport runs share the same persisted dashboard and contaminate each other, and transient post-mouse DOM was treated as authoritative changed state even when Save canonicalised/compacted to different geometry. | U50: F-070 — Each viewport must snapshot/restore its original layout in finally, mutate relative to its starting state, use PATCH canonical as authoritative changed state, poll DOM to converge after save/reload, and then restore baseline. No more diagnostic-only packs. | V50: Current M1 sequence / presentation owner hand-off | W50: Presentation lane; Worker 3 only by explicit formal reassignment after zero-overlap + stable-prerequisite check | X50: MEDIUM | Y50: Deep design reconciliation 16-Aug-2026; Chapter 3/4 + Layer-B architecture + latest source/audit evidence | Z50: Track 1 — Presentation / Demo | AA50: 2026-08-20 Presentation RC | AB50: M1 Contract | AC50: Presentation-visible contract. Prepared Fleet v2 topology is allowed; no fake product behaviour and no production-only scope. | AD50: Medium | AE50: Worker 2 | AF50: Presentation BI/UX + E2E release integration | AG50: E2E/debug convergence | AH50: 5.3333333 | AI50: 2 | AJ50: =IF($K50="Done",0,MAX(0.25,$J50/$AH50)) -> 0 | AK50: =IF($K50="Done",0,$AJ50*$AI50) -> 0 | AL50: M1-A — parallel foundations | AM50: GO now. Final isolated certification only; no more diagnostic-only iteration. | AN50: Own Dashboard/workspace/shared shell/AnalysisToolbox/E2E. No W1 active vertical files; no W3 Jobs/Findings/Assistant files. | AO50: Commit before downstream consumer starts; consumer must use the contract, not redesign producer-owned semantics.
A51: T-050 | B51: M1 | C51: M1-P3 | D51: Drill to population, provenance and evidence | E51: Frontend | F51: Dashboard | G51: Very Important | H51: RETARGETED IN v2.1. The v2.0 assessment of the drawer's visual state was stale, and the real value is not the transition. Focus on the chain: click a point, see the POPULATION behind it, see its PROVENANCE, and reach the source evidence. Correct the off-palette colours to the token set and position the drawer logically with inline-start and inline-end so RTL mirrors correctly. Add the open transition and respect prefers-reduced-motion, but treat that as the smallest part of the task. | I51: Click a bar and confirm the drawer lists the underlying population with a resolvable provenance handle and a path to the source rows. Set prefers-reduced-motion and confirm the transition is suppressed. Switch to RTL and confirm the drawer opens from the correct edge. Confirm every colour used appears in the token set. | J51: 6 | K51: Done | L51: Presentation lane (Workers 1/2) | M51: CLOSED | N51: Presentation target is active. Worker 3 must not edit M1 pages, presentation DB/seeds, current assistant wiring or runtime behaviour. | O51: Current M1 sequence / presentation owner hand-off | P51: CARRIED v2.9.2 | Q51: Not Started | S51: No new contradiction identified in this pass | V51: Current M1 sequence / presentation owner hand-off | W51: Presentation lane; Worker 3 only by explicit formal reassignment after zero-overlap + stable-prerequisite check | X51: Low / not newly identified | Y51: Deep design reconciliation 16-Aug-2026; Chapter 3/4 + Layer-B architecture + latest source/audit evidence | Z51: Track 1 — Presentation / Demo | AA51: 2026-08-20 Presentation RC | AB51: M1 Contract | AC51: Presentation-visible contract. Prepared Fleet v2 topology is allowed; no fake product behaviour and no production-only scope. | AD51: Medium | AE51: Worker 2 | AF51: Presentation BI/UX + E2E release integration | AG51: Frontend/UI feature | AH51: 9 | AI51: 1.5 | AJ51: =IF($K51="Done",0,MAX(0.25,$J51/$AH51)) -> 0 | AK51: =IF($K51="Done",0,$AJ51*$AI51) -> 0 | AL51: M1-A — parallel foundations | AM51: Current M1 sequence / presentation owner hand-off | AN51: Own Dashboard/workspace/shared shell/AnalysisToolbox/E2E. No W1 active vertical files; no W3 Jobs/Findings/Assistant files. | AO51: Commit before downstream consumer starts; consumer must use the contract, not redesign producer-owned semantics.
A52: T-051 | B52: M1 | C52: M1-P3 | D52: Widget failure isolation and the seven states | E52: Frontend | F52: Dashboard | G52: Critical | H52: Chapter 4 requires that one widget failing never destroys the page, and that filtered-empty is distinguishable from genuinely empty. Wrap each widget in its own boundary and implement all seven states with the correct colour semantics: Blocked and Refused in Amber, Failed in Hot Red, Empty and Filtered-empty in Muted Steel with different wording. | I52: Inject a failure into one widget query and confirm the other widgets on the page continue to render and interact. Apply a filter that returns no rows and confirm the widget says the selection returned nothing, not that there is no data. | J52: 6 | K52: Done | L52: Presentation lane (Workers 1/2) | M52: CLOSED | N52: Presentation target is active. Worker 3 must not edit M1 pages, presentation DB/seeds, current assistant wiring or runtime behaviour. | O52: Current M1 sequence / presentation owner hand-off | P52: CARRIED v2.9.2 | Q52: Not Started | S52: No new contradiction identified in this pass | V52: Current M1 sequence / presentation owner hand-off | W52: Presentation lane; Worker 3 only by explicit formal reassignment after zero-overlap + stable-prerequisite check | X52: Low / not newly identified | Y52: Deep design reconciliation 16-Aug-2026; Chapter 3/4 + Layer-B architecture + latest source/audit evidence | Z52: Track 1 — Presentation / Demo | AA52: 2026-08-20 Presentation RC | AB52: M1 Contract | AC52: Presentation-visible contract. Prepared Fleet v2 topology is allowed; no fake product behaviour and no production-only scope. | AD52: Medium | AE52: Worker 2 | AF52: Presentation BI/UX + E2E release integration | AG52: Frontend/UI feature | AH52: 9 | AI52: 1.5 | AJ52: =IF($K52="Done",0,MAX(0.25,$J52/$AH52)) -> 0 | AK52: =IF($K52="Done",0,$AJ52*$AI52) -> 0 | AL52: M1-A — parallel foundations | AM52: Current M1 sequence / presentation owner hand-off | AN52: Own Dashboard/workspace/shared shell/AnalysisToolbox/E2E. No W1 active vertical files; no W3 Jobs/Findings/Assistant files. | AO52: Commit before downstream consumer starts; consumer must use the contract, not redesign producer-owned semantics.
A53: T-052 | B53: M1 | C53: M1-P3 | D53: Remove the hardcoded parameter default from the API client | E53: Frontend | F53: Dashboard | G53: Critical | H53: Frontend/PlantProcess.Web/src/api/productCoreApiClient.runtime.ts line 300 reads `parameterCode: filters.parameterCode || "CastingSpeed"`. That is a steel-specific literal in product logic and a Rule 1 violation reachable by a customer. Remove the fallback. When no parameter is selected, either omit the field or resolve a default from the parameter registry returned by the metadata endpoint. | I53: Grep the whole src tree for CastingSpeed and confirm the only remaining hits are in demo content or test fixtures, never in product code paths. Load a parameter widget with no parameter selected and confirm it either shows a chooser or a registry-resolved default, and does not silently query a steel parameter. | J53: 4 | K53: Done | L53: Presentation lane (Workers 1/2) | M53: CLOSED | N53: Presentation target is active. Worker 3 must not edit M1 pages, presentation DB/seeds, current assistant wiring or runtime behaviour. | O53: Current M1 sequence / presentation owner hand-off | P53: CARRIED v2.9.2 | Q53: Not Started | S53: No new contradiction identified in this pass | V53: Current M1 sequence / presentation owner hand-off | W53: Presentation lane; Worker 3 only by explicit formal reassignment after zero-overlap + stable-prerequisite check | X53: Low / not newly identified | Y53: Deep design reconciliation 16-Aug-2026; Chapter 3/4 + Layer-B architecture + latest source/audit evidence | Z53: Track 1 — Presentation / Demo | AA53: 2026-08-20 Presentation RC | AB53: M1 Contract | AC53: Presentation-visible contract. Prepared Fleet v2 topology is allowed; no fake product behaviour and no production-only scope. | AD53: Medium | AE53: Worker 2 | AF53: Presentation BI/UX + E2E release integration | AG53: Frontend/UI feature | AH53: 9 | AI53: 1.5 | AJ53: =IF($K53="Done",0,MAX(0.25,$J53/$AH53)) -> 0 | AK53: =IF($K53="Done",0,$AJ53*$AI53) -> 0 | AL53: M1-A — parallel foundations | AM53: Current M1 sequence / presentation owner hand-off | AN53: Own Dashboard/workspace/shared shell/AnalysisToolbox/E2E. No W1 active vertical files; no W3 Jobs/Findings/Assistant files. | AO53: Commit before downstream consumer starts; consumer must use the contract, not redesign producer-owned semantics.
A54: T-053 | B54: M1 | C54: M1-P4 | D54: Reduce the demonstration navigation and add the inventory ratchet | E54: Frontend | F54: Design contract | G54: Critical | H54: NEW IN v2.3, also from the presented-surface audit. Thirty-five navigation targets were classified and ELEVEN have no Chapter 3 contract, nine of them in the System group: the widget schema-drift diagnostic, author-mapping, four advisory pages, edge collector, historian connector, admin preview, brand, and /assistant once the dock lands. Every one is a surface the customer can open, and any surface opened is a frozen contract. Reduce the demonstration navigation to the entries backing the eighteen presented screens. HIDE the rest behind a configuration flag rather than deleting them - they are M2 retirement debt, not demo-day deletions. Then extend PPIQ-T12 with a fourth assertion: every navigation target resolves to a Chapter 3 contract id read from a checked-in inventory file. The inventory is DATA, so adding a page in M2a is a data change and not a code change. | I54: The architecture suite fails when a navigation entry is added whose target is not in the inventory file. Open every navigation group and confirm every entry maps to one of the eighteen screens. Confirm the hidden entries are still reachable by direct URL, so nothing is lost, only unlisted. | J54: 4 | K54: Not Started | L54: Presentation lane (Workers 1/2) | M54: DO NOT ASSIGN W3 | N54: Presentation target is active. Worker 3 must not edit M1 pages, presentation DB/seeds, current assistant wiring or runtime behaviour. | O54: Current M1 sequence / presentation owner hand-off | P54: CARRIED v2.9.2 | Q54: Not Started | S54: No new contradiction identified in this pass | V54: Current M1 sequence / presentation owner hand-off | W54: Presentation lane; Worker 3 only by explicit formal reassignment after zero-overlap + stable-prerequisite check | X54: Low / not newly identified | Y54: Deep design reconciliation 16-Aug-2026; Chapter 3/4 + Layer-B architecture + latest source/audit evidence | Z54: Track 1 — Presentation / Demo | AA54: 2026-08-20 Presentation RC | AB54: M1 Contract | AC54: Presentation-visible contract. Prepared Fleet v2 topology is allowed; no fake product behaviour and no production-only scope. | AD54: High | AE54: Worker 2 | AF54: Presentation BI/UX + E2E release integration | AG54: Frontend/UI feature | AH54: 9 | AI54: 1.5 | AJ54: =IF($K54="Done",0,MAX(0.25,$J54/$AH54)) -> 0.44444444 | AK54: =IF($K54="Done",0,$AJ54*$AI54) -> 0.66666667 | AL54: M1-B — journey/config surfaces | AM54: Current M1 sequence / presentation owner hand-off | AN54: Own Dashboard/workspace/shared shell/AnalysisToolbox/E2E. No W1 active vertical files; no W3 Jobs/Findings/Assistant files. | AO54: Commit before downstream consumer starts; consumer must use the contract, not redesign producer-owned semantics.
A55: T-054 | B55: M1 | C55: M1-P4 | D55: J4 Connections: read-only proof and load budget made visible | E55: Frontend | F55: Connections | G55: Very Important | H55: The connection page must show, for a configured source, that the connection is read-only enforced, what the load budget is, and the result of a live test. The backing facts already exist: connection_profiles carries read_only_enforced, and ThrottlingDataSourceReader evaluates every read against ISourceLoadBudgetProvider and ISourceQueryRateLimiter before it reaches the source. Surface those three facts on the page. | I55: Open the page with one configured source, press Test, and confirm three visible outcomes: connection succeeded, read-only enforced true, and the current load budget. Then stop the emulated source container and confirm the failure state names the reason rather than showing a raw exception. | J55: 4 | K55: Not Started | L55: Presentation lane (Workers 1/2) | M55: DO NOT ASSIGN W3 | N55: Presentation target is active. Worker 3 must not edit M1 pages, presentation DB/seeds, current assistant wiring or runtime behaviour. | O55: Current M1 sequence / presentation owner hand-off | P55: CARRIED v2.9.2 | Q55: Not Started | S55: No new contradiction identified in this pass | V55: Current M1 sequence / presentation owner hand-off | W55: Presentation lane; Worker 3 only by explicit formal reassignment after zero-overlap + stable-prerequisite check | X55: Low / not newly identified | Y55: Deep design reconciliation 16-Aug-2026; Chapter 3/4 + Layer-B architecture + latest source/audit evidence | Z55: Track 1 — Presentation / Demo | AA55: 2026-08-20 Presentation RC | AB55: M1 Contract | AC55: Live connection/discovery is valid. Registration may be demonstrated; do not imply a bulk import/projection ran live unless it actually did. | AD55: High | AE55: Worker 1 | AF55: Presentation data/config verticals | AG55: Frontend/UI feature | AH55: 9 | AI55: 1.5 | AJ55: =IF($K55="Done",0,MAX(0.25,$J55/$AH55)) -> 0.44444444 | AK55: =IF($K55="Done",0,$AJ55*$AI55) -> 0.66666667 | AL55: M1-B — journey/config surfaces | AM55: Current M1 sequence / presentation owner hand-off | AN55: Own Connections/Datasets/Import + Relationship/Mapping/Genealogy verticals. No DashboardGridLayout, AnalysisToolbox, Findings/Assistant, or W2 E2E. | AO55: Commit before downstream consumer starts; consumer must use the contract, not redesign producer-owned semantics.
A56: T-055 | B56: M1 | C56: M1-P4 | D56: J5 and J6 Dataset registry browse and watermark suggestion | E56: Frontend | F56: Data integration | G56: Very Important | H56: The Prepare Source for Import page already discovers tables from a live source. Improve schema, table and column search, and make the business key and watermark column suggestions explicit with the reason for each suggestion. Note the demonstration warning: staged tables carry emulator plumbing names such as the generated presentation-staging display name for cast pieces (NOT the donor schema name - `src_*` is retired by then and Chapter 3 forbids calling it staging). Decide deliberately whether to show them with an honest sentence or to present display names; do not discover this live in front of the customer. | I56: Register one dataset end to end and confirm the suggested business key and watermark are shown with reasons and can be overridden. Record which naming decision was taken in the traceability matrix. | J56: 6 | K56: Not Started | L56: Presentation lane (Workers 1/2) | M56: DO NOT ASSIGN W3 | N56: Presentation target is active. Worker 3 must not edit M1 pages, presentation DB/seeds, current assistant wiring or runtime behaviour. | O56: Current M1 sequence / presentation owner hand-off | P56: CARRIED v2.9.2 | Q56: Not Started | S56: No new contradiction identified in this pass | V56: Current M1 sequence / presentation owner hand-off | W56: Presentation lane; Worker 3 only by explicit formal reassignment after zero-overlap + stable-prerequisite check | X56: Low / not newly identified | Y56: Deep design reconciliation 16-Aug-2026; Chapter 3/4 + Layer-B architecture + latest source/audit evidence | Z56: Track 1 — Presentation / Demo | AA56: 2026-08-20 Presentation RC | AB56: M1 Contract | AC56: Live connection/discovery is valid. Registration may be demonstrated; do not imply a bulk import/projection ran live unless it actually did. | AD56: High | AE56: Worker 1 | AF56: Presentation data/config verticals | AG56: Frontend/UI feature | AH56: 9 | AI56: 1.5 | AJ56: =IF($K56="Done",0,MAX(0.25,$J56/$AH56)) -> 0.66666667 | AK56: =IF($K56="Done",0,$AJ56*$AI56) -> 1 | AL56: M1-B — journey/config surfaces | AM56: Current M1 sequence / presentation owner hand-off | AN56: Own Connections/Datasets/Import + Relationship/Mapping/Genealogy verticals. No DashboardGridLayout, AnalysisToolbox, Findings/Assistant, or W2 E2E. | AO56: Commit before downstream consumer starts; consumer must use the contract, not redesign producer-owned semantics.
A57: T-056 | B57: M1 | C57: M1-P4 | D57: J6 Import progress visibility | E57: Frontend | F57: Data integration | G57: Important | H57: An import that runs with no visible progress reads as a hang. Add a named progress indication driven by the existing import batch records: batch started, rows staged, batch completed, with the dataset name. Use the activity tray pattern rather than a modal. v2.10.3 RULING: this task certifies the real progress contract, but a live 100k bulk import is not a Presentation RC gate; Chapter 3 permits prepared import state in M1. | I57: Certify that real import-batch events drive started / rows-staged / completed progress and correct row counts in an integration environment. For the live M1 presentation, prepared import state is allowed; never claim a bulk import ran live unless it actually did. | J57: 4 | K57: Not Started | L57: Presentation lane (Workers 1/2) | M57: DO NOT ASSIGN W3 | N57: Presentation target is active. Worker 3 must not edit M1 pages, presentation DB/seeds, current assistant wiring or runtime behaviour. | O57: Current M1 sequence / presentation owner hand-off | P57: v2.10.3 — M1 live-bulk-import requirement removed from Presentation RC gate | Q57: Not Started | S57: No new contradiction identified in this pass | V57: Current M1 sequence / presentation owner hand-off | W57: Presentation lane; Worker 3 only by explicit formal reassignment after zero-overlap + stable-prerequisite check | X57: Low / not newly identified | Y57: Deep design reconciliation 16-Aug-2026; Chapter 3/4 + Layer-B architecture + latest source/audit evidence | Z57: Track 1 — Presentation / Demo | AA57: 2026-08-20 Presentation RC | AB57: Optional Demo Booster | AC57: Progress UI contract is useful, but a live 100k bulk import is NOT an Aug-20 presentation gate. Certify the real progress mechanism outside the live demo; M1 may show prepared import state. | AD57: High if kept as live-demo gate | AE57: Worker 1 | AF57: Presentation data/config verticals | AG57: Frontend/UI feature | AH57: 9 | AI57: 1.5 | AJ57: =IF($K57="Done",0,MAX(0.25,$J57/$AH57)) -> 0.44444444 | AK57: =IF($K57="Done",0,$AJ57*$AI57) -> 0.66666667 | AL57: M1-B — journey/config surfaces | AM57: Current M1 sequence / presentation owner hand-off | AN57: Own Connections/Datasets/Import + Relationship/Mapping/Genealogy verticals. No DashboardGridLayout, AnalysisToolbox, Findings/Assistant, or W2 E2E. | AO57: Commit before downstream consumer starts; consumer must use the contract, not redesign producer-owned semantics.
A58: T-057 | B58: M1 | C58: M1-P4 | D58: J7 Relationship model vertical slice, part 1: publish one relationship | E58: Backend | F58: Relationship model | G58: Critical | H58: Chapter 3 4.5.10 specifies plant_relationships plus members and paths, with sixteen declared consumers. A repository search for plant_relationships returns zero hits, so this does not exist. M1 does not build the whole model. M1 builds the smallest FINAL slice: the three tables with their real columns, and the ability to declare and publish one relationship between two source entities with its members and cardinality. Use the final table and column names from 4.5.10 so M2 extends rather than migrates. v2.10.2 AUTHORITY CORRECTION — Chapter 3 4.5.10's physical tables cannot be FINAL in M1 because source_definition_id is an FK to definition_store(id), which does not exist until T-089/T-090. M1 therefore freezes the FINAL EXTERNAL relationship contract/service/API and uses compatibility persistence only. Do not create a fake FK or steal definition_store into M1. T-095 owns canonical physical convergence. | I58: An integration test that publishes one relationship, reads it back, and asserts it is versioned and marked published. A second test asserting an unpublished relationship is not returned to consumers. The M1 integration test must not reference a concrete relationship table name. It proves publish/read/version/publication semantics through the service/API so the same test can pass unchanged after T-095 replaces the hidden persistence. | J58: 10 | K58: Done | L58: Presentation lane (Workers 1/2) | M58: CLOSED | N58: Presentation target is active. Worker 3 must not edit M1 pages, presentation DB/seeds, current assistant wiring or runtime behaviour. | O58: T-039 complete; M1 relationship compatibility slice only. Canonical physical relationship schema waits for T-089/T-090/T-095. | P58: v2.10.2 — final external contract separated from final physical relationship schema | Q58: Not Started | S58: REVISE — critical design/sequencing issue | T58: F-052 [Critical] — M1 relationship task calls the three Chapter 3 relationship tables a FINAL physical slice, but Chapter 3 4.5.10 requires source_definition_id -> definition_store(id). definition_store is intentionally absent until T-089/T-090. A physically final M1 table set therefore cannot exist without stealing M2a authority or creating a temporary FK contract. | U58: F-052 — T-057 must deliver the final external relationship service/API and M1-compatible persistence only. Do not claim final physical schema. T-095 owns canonical ppiq_meta.plant_relationships/_members/_paths convergence after T-089/T-090. T-058/T-059/T-060 consume the service, never table names. | V58: T-039 complete; M1 relationship compatibility slice only. Canonical physical relationship schema waits for T-089/T-090/T-095. | W58: Presentation contract required; NOT booster-safe for physical-schema work until canonical prerequisite exists | X58: HIGH | Y58: Deep design reconciliation 16-Aug-2026; Chapter 3/4 + Layer-B architecture + latest source/audit evidence | Z58: Track 1 — Presentation / Demo | AA58: 2026-08-20 Presentation RC | AB58: M1 Contract | AC58: M1 freezes the stable external/semantic contract only. Do not create fake final FKs/storage that M2a will replace; canonical physical convergence has an explicit M2a owner. | AD58: High | AE58: Worker 1 | AF58: Presentation data/config verticals | AG58: Backend/domain contract | AH58: 10 | AI58: 1.5 | AJ58: =IF($K58="Done",0,MAX(0.25,$J58/$AH58)) -> 0 | AK58: =IF($K58="Done",0,$AJ58*$AI58) -> 0 | AL58: M1-A — parallel foundations | AM58: T-039 complete; M1 relationship compatibility slice only. Canonical physical ... | AN58: Own Connections/Datasets/Import + Relationship/Mapping/Genealogy verticals. No DashboardGridLayout, AnalysisToolbox, Findings/Assistant, or W2 E2E. | AO58: Commit → W2 may consume relationship contract in T-059; W1 keeps T-060.
A59: T-058 | B59: M1 | C59: M1-P4 | D59: J7 Relationship model vertical slice, part 2: one resolver consumer | E59: Backend | F59: Relationship model | G59: Critical | H59: Chapter 3 says page and widget associative queries resolve through the published relationship model. Implement the path resolver for the single published relationship and make exactly one widget query use it for a cross-source join, instead of a join written into the widget's own query. This matters because the cross-source correlation is the categorical value proposition and a demonstration that joins inside one dashboard proves the opposite of the product design. | I59: Point one widget at data spanning two sources, confirm it renders, then unpublish the relationship and confirm the widget refuses with a named reason instead of silently returning a partial result. Restore and confirm it renders again. | J59: 10 | K59: Done | L59: Presentation lane (Workers 1/2) | M59: CLOSED | N59: Presentation target is active. Worker 3 must not edit M1 pages, presentation DB/seeds, current assistant wiring or runtime behaviour. | O59: T-057 final external relationship contract published; consume service/resolver only, never compatibility table names. | P59: v2.10.2 — explicit dependency on T-057 service contract | Q59: Not Started | S59: REVISE — critical design/sequencing issue | T59: F-052 [Critical] — M1 relationship task calls the three Chapter 3 relationship tables a FINAL physical slice, but Chapter 3 4.5.10 requires source_definition_id -> definition_store(id). definition_store is intentionally absent until T-089/T-090. A physically final M1 table set therefore cannot exist without stealing M2a authority or creating a temporary FK contract. | U59: F-052 — T-057 must deliver the final external relationship service/API and M1-compatible persistence only. Do not claim final physical schema. T-095 owns canonical ppiq_meta.plant_relationships/_members/_paths convergence after T-089/T-090. T-058/T-059/T-060 consume the service, never table names. | V59: T-057 final external relationship contract published; consume service/resolver only, never compatibility table names. | W59: Presentation lane; Worker 3 only by explicit formal reassignment after zero-overlap + stable-prerequisite check | X59: HIGH | Y59: Deep design reconciliation 16-Aug-2026; Chapter 3/4 + Layer-B architecture + latest source/audit evidence | Z59: Track 1 — Presentation / Demo | AA59: 2026-08-20 Presentation RC | AB59: M1 Contract | AC59: M1 freezes the stable external/semantic contract only. Do not create fake final FKs/storage that M2a will replace; canonical physical convergence has an explicit M2a owner. | AD59: High | AE59: Worker 1 | AF59: Presentation data/config verticals | AG59: Backend/domain contract | AH59: 10 | AI59: 1.5 | AJ59: =IF($K59="Done",0,MAX(0.25,$J59/$AH59)) -> 0 | AK59: =IF($K59="Done",0,$AJ59*$AI59) -> 0 | AL59: M1-A — parallel foundations | AM59: T-057 final external relationship contract published; consume service/resolve... | AN59: Own Connections/Datasets/Import + Relationship/Mapping/Genealogy verticals. No DashboardGridLayout, AnalysisToolbox, Findings/Assistant, or W2 E2E. | AO59: Commit → W2 may consume relationship contract in T-059; W1 keeps T-060.
A60: T-059 | B60: M1 | C60: M1-P4 | D60: Associative model, part 2: cross-source state through the published relationship | E60: Frontend | F60: Dashboard | G60: Very Important | H60: SPLIT IN v2.2 and placed here because it DEPENDS on the resolver built immediately above. Make the cross-source associative state resolve through the published relationship model rather than through a join a dashboard owns. Chapter 3 DF7 requires page and widget queries and associative states to resolve through the published model; a selection that spans two sources and works by a dashboard-local join proves the opposite of the product design. | I60: Apply a selection that spans two sources and confirm the strip and every widget narrow consistently. Unpublish the relationship and confirm the cross-source state refuses with a named reason rather than silently narrowing to one source. | J60: 4 | K60: Not Started | L60: Presentation lane (Workers 1/2) | M60: DO NOT ASSIGN W3 | N60: Presentation target is active. Worker 3 must not edit M1 pages, presentation DB/seeds, current assistant wiring or runtime behaviour. | O60: T-048 + T-057 + T-058; cross-source associative state must resolve through the published relationship service. | P60: v2.10.2 — explicit relationship-resolver dependency | Q60: Not Started | S60: REVISE — critical design/sequencing issue | T60: F-052 [Critical] — M1 relationship task calls the three Chapter 3 relationship tables a FINAL physical slice, but Chapter 3 4.5.10 requires source_definition_id -> definition_store(id). definition_store is intentionally absent until T-089/T-090. A physically final M1 table set therefore cannot exist without stealing M2a authority or creating a temporary FK contract. | U60: F-052 — T-057 must deliver the final external relationship service/API and M1-compatible persistence only. Do not claim final physical schema. T-095 owns canonical ppiq_meta.plant_relationships/_members/_paths convergence after T-089/T-090. T-058/T-059/T-060 consume the service, never table names. | V60: T-048 + T-057 + T-058; cross-source associative state must resolve through the published relationship service. | W60: Presentation lane; Worker 3 only by explicit formal reassignment after zero-overlap + stable-prerequisite check | X60: HIGH | Y60: Deep design reconciliation 16-Aug-2026; Chapter 3/4 + Layer-B architecture + latest source/audit evidence | Z60: Track 1 — Presentation / Demo | AA60: 2026-08-20 Presentation RC | AB60: M1 Contract | AC60: Presentation-visible contract. Prepared Fleet v2 topology is allowed; no fake product behaviour and no production-only scope. | AD60: High | AE60: Worker 2 | AF60: Presentation BI/UX + E2E release integration | AG60: Frontend/UI feature | AH60: 9 | AI60: 1.5 | AJ60: =IF($K60="Done",0,MAX(0.25,$J60/$AH60)) -> 0.44444444 | AK60: =IF($K60="Done",0,$AJ60*$AI60) -> 0.66666667 | AL60: M1-B — journey/config surfaces | AM60: T-048 + T-057 + T-058; cross-source associative state must resolve through th... | AN60: Own Dashboard/workspace/shared shell/AnalysisToolbox/E2E. No W1 active vertical files; no W3 Jobs/Findings/Assistant files. | AO60: Commit before downstream consumer starts; consumer must use the contract, not redesign producer-owned semantics.
A61: T-060 | B61: M1 | C61: M1-P4 | D61: C6 Relationship Browser, minimal read-only slice | E61: Frontend | F61: Relationship model | G61: Very Important | H61: NEW IN v2.3. Decision taken at traceability sign-off: show it. The relationship model slice is funded and it is the mechanism that separates this product from a dashboard with joins - a join declared once, published, versioned, and resolved by every consumer. Until now nothing rendered it. Build the smallest honest C6 from Chapter 3 4.4: a read-only list of published relationships, their members, their cardinality and their resolved path, with the evidence for each path. No authoring in M1; authoring is the shared shell in S1. Four hours to make the strongest differentiator visible is the best-value decision on this surface. | I61: Open a published relationship and confirm its members, cardinality and path render with evidence. Confirm an unpublished relationship is visibly distinct from a published one. Confirm the page is read-only - no control on it can modify a relationship. | J61: 4 | K61: In Progress | L61: Presentation lane (Workers 1/2) | M61: DO NOT ASSIGN W3 | N61: Presentation target is active. Worker 3 must not edit M1 pages, presentation DB/seeds, current assistant wiring or runtime behaviour. | O61: T-057 + T-058; C6 reads the relationship service/API, not compatibility table names. | P61: v2.10.2 — continuity-safe C6 dependency | Q61: Not Started | S61: REVISE — critical design/sequencing issue | T61: F-052 [Critical] — M1 relationship task calls the three Chapter 3 relationship tables a FINAL physical slice, but Chapter 3 4.5.10 requires source_definition_id -> definition_store(id). definition_store is intentionally absent until T-089/T-090. A physically final M1 table set therefore cannot exist without stealing M2a authority or creating a temporary FK contract. F-060 [Very Important] — T-060 builds the M1 C6 route, then T-098 says 'Build the C6 Relationship Browser' again. That wording invites a second page/rebuild rather than hidden-authority convergence. | U61: F-052 — T-057 must deliver the final external relationship service/API and M1-compatible persistence only. Do not claim final physical schema. T-095 owns canonical ppiq_meta.plant_relationships/_members/_paths convergence after T-089/T-090. T-058/T-059/T-060 consume the service, never table names. F-060 — T-098 must complete the already-shown /relationships page in place: preserve route/layout/controls and replace/extend only the canonical relationship source/path evidence. | V61: T-057 + T-058; C6 reads the relationship service/API, not compatibility table names. | W61: Presentation lane; Worker 3 only by explicit formal reassignment after zero-overlap + stable-prerequisite check | X61: HIGH | Y61: Deep design reconciliation 16-Aug-2026; Chapter 3/4 + Layer-B architecture + latest source/audit evidence | Z61: Track 1 — Presentation / Demo | AA61: 2026-08-20 Presentation RC | AB61: M1 Contract | AC61: Presentation-visible contract. Prepared Fleet v2 topology is allowed; no fake product behaviour and no production-only scope. | AD61: High | AE61: Worker 1 | AF61: Presentation data/config verticals | AG61: Frontend/UI feature | AH61: 9 | AI61: 1.5 | AJ61: =IF($K61="Done",0,MAX(0.25,$J61/$AH61)) -> 0.44444444 | AK61: =IF($K61="Done",0,$AJ61*$AI61) -> 0.66666667 | AL61: M1-B — journey/config surfaces | AM61: T-057 + T-058; C6 reads the relationship service/API, not compatibility table... | AN61: Own Connections/Datasets/Import + Relationship/Mapping/Genealogy verticals. No DashboardGridLayout, AnalysisToolbox, Findings/Assistant, or W2 E2E. | AO61: Commit before downstream consumer starts; consumer must use the contract, not redesign producer-owned semantics.
A62: T-061 | B62: M1 | C62: M1-P4 | D62: C2 Mapping Health, part 1: the typed issue contract and the reprocess API | E62: Backend | F62: Mapping health | G62: Critical | H62: CORRECTED IN v2.1. v2.0 said the API exists and only the control is missing. That was wrong. The current MappingHealthPage consumes a source-level SUMMARY only - mapped field count, drift counts, blocking state - from /mapping-health/summary. There is no issue-row model and no typed quarantine or reprocess contract at all. Build the minimal FINAL slice: a typed issue record with a named code, the offending source row as an example, and a reprocess endpoint. Use the final Chapter 3 4.5.14 code names for the classes you implement so M2a adds the remaining PV classes without the contract or the page changing. v2.10.2 AUTHORITY CORRECTION — 'minimal FINAL slice' means the FINAL DTO/API/error-code/reprocess semantics, not the final projection_quarantine table. The Chapter 3 4.5.14 table depends on canonical staging_records and definition_versions that arrive in T-087/T-089/T-090. M1 may use compatibility persistence behind the final contract, with no table identity exposed to the page. | I62: Introduce a deliberately malformed mapping, run the projection, and confirm the API returns issues grouped by a named code with an example row. Call reprocess after correcting the mapping and confirm only the affected rows clear. An integration test asserting the response shape matches the final contract. Add an architecture/contract assertion that the M1 API/page does not depend on a compatibility table name. T-099/T-100 must later replace persistence without changing this response/action contract. | J62: 6 | K62: Not Started | L62: Presentation lane (Workers 1/2) | M62: DO NOT ASSIGN W3 | N62: Presentation target is active. Worker 3 must not edit M1 pages, presentation DB/seeds, current assistant wiring or runtime behaviour. | O62: Current M1 projection/mapping compatibility path + stable API seam. Canonical projection_quarantine persistence waits for T-087/T-089/T-090/T-099. | P62: v2.10.2 — final API contract separated from canonical quarantine persistence | Q62: Not Started | S62: REVISE — critical design/sequencing issue | T62: F-054 [Critical] — The final projection_quarantine physical schema requires canonical staging_records and definition_versions. M1 cannot honestly create the final table before T-087/T-089/T-090, yet T-061 currently says 'minimal FINAL slice' and validates real projection/reprocess behavior. | U62: F-054 — T-061 owns the final typed DTO/API/error-code/reprocess semantics over compatibility persistence only. T-099/T-100 own canonical projection_quarantine and all 15 PV classes; T-101 completes retry/reprocess and preserves the M1 page contract unchanged. | V62: Current M1 projection/mapping compatibility path + stable API seam. Canonical projection_quarantine persistence waits for T-087/T-089/T-090/T-099. | W62: Presentation contract required; NOT booster-safe for physical-schema work until canonical prerequisite exists | X62: HIGH | Y62: Deep design reconciliation 16-Aug-2026; Chapter 3/4 + Layer-B architecture + latest source/audit evidence | Z62: Track 1 — Presentation / Demo | AA62: 2026-08-20 Presentation RC | AB62: M1 Contract | AC62: M1 freezes the stable external/semantic contract only. Do not create fake final FKs/storage that M2a will replace; canonical physical convergence has an explicit M2a owner. | AD62: High | AE62: Worker 1 | AF62: Presentation data/config verticals | AG62: Backend/domain contract | AH62: 10 | AI62: 1.5 | AJ62: =IF($K62="Done",0,MAX(0.25,$J62/$AH62)) -> 0.6 | AK62: =IF($K62="Done",0,$AJ62*$AI62) -> 0.9 | AL62: M1-B — journey/config surfaces | AM62: Current M1 projection/mapping compatibility path + stable API seam. Canonical... | AN62: Own Connections/Datasets/Import + Relationship/Mapping/Genealogy verticals. No DashboardGridLayout, AnalysisToolbox, Findings/Assistant, or W2 E2E. | AO62: Commit → W1 consumes in T-062; contract remains stable through M2a convergence.
A63: T-062 | B63: M1 | C63: M1-P4 | D63: C2 Mapping Health, part 2: the final visible page | E63: Frontend | F63: Mapping health | G63: Critical | H63: Build the C2 page shape from Chapter 3 4.4 over the contract above: issues grouped by code, an example row per group, and a Reprocess control. The full fifteen PV classes are M2a work; M1 needs the SHAPE to be final so the customer sees the same page after M2a with more codes in it, not a different page. | I63: Walk the page with three issue codes present, reprocess one, and confirm the group clears while the others remain. Confirm the empty state says the mapping is clean rather than that there is no data. | J63: 4 | K63: Not Started | L63: Presentation lane (Workers 1/2) | M63: DO NOT ASSIGN W3 | N63: Presentation target is active. Worker 3 must not edit M1 pages, presentation DB/seeds, current assistant wiring or runtime behaviour. | O63: T-061 committed final Mapping Health issue/reprocess API contract. | P63: v2.10.2 — explicit backend-contract dependency | Q63: Not Started | S63: REVISE — critical design/sequencing issue | T63: F-054 [Critical] — The final projection_quarantine physical schema requires canonical staging_records and definition_versions. M1 cannot honestly create the final table before T-087/T-089/T-090, yet T-061 currently says 'minimal FINAL slice' and validates real projection/reprocess behavior. | U63: F-054 — T-061 owns the final typed DTO/API/error-code/reprocess semantics over compatibility persistence only. T-099/T-100 own canonical projection_quarantine and all 15 PV classes; T-101 completes retry/reprocess and preserves the M1 page contract unchanged. | V63: T-061 committed final Mapping Health issue/reprocess API contract. | W63: Presentation lane; Worker 3 only by explicit formal reassignment after zero-overlap + stable-prerequisite check | X63: HIGH | Y63: Deep design reconciliation 16-Aug-2026; Chapter 3/4 + Layer-B architecture + latest source/audit evidence | Z63: Track 1 — Presentation / Demo | AA63: 2026-08-20 Presentation RC | AB63: M1 Contract | AC63: Presentation-visible contract. Prepared Fleet v2 topology is allowed; no fake product behaviour and no production-only scope. | AD63: High | AE63: Worker 1 | AF63: Presentation data/config verticals | AG63: Frontend/UI feature | AH63: 9 | AI63: 1.5 | AJ63: =IF($K63="Done",0,MAX(0.25,$J63/$AH63)) -> 0.44444444 | AK63: =IF($K63="Done",0,$AJ63*$AI63) -> 0.66666667 | AL63: M1-B — journey/config surfaces | AM63: T-061 committed final Mapping Health issue/reprocess API contract. | AN63: Own Connections/Datasets/Import + Relationship/Mapping/Genealogy verticals. No DashboardGridLayout, AnalysisToolbox, Findings/Assistant, or W2 E2E. | AO63: Commit before downstream consumer starts; consumer must use the contract, not redesign producer-owned semantics.
A64: T-063 | B64: M1 | C64: M1-P4 | D64: C5 Genealogy: converge the legacy workbench onto the final two-state surface | E64: Frontend | F64: Genealogy | G64: Very Important | H64: EXPANDED IN v2.1. v2.0 said make the landing search work, and estimated six hours. The real gap is larger: /materials currently renders a legacy investigation workbench, which is a different surface from the Chapter 3 4.4 C5 contract of a two-state page - a search state and a selected-unit state opening the bidirectional genealogy thread with attribution weights and evidence. Converge the workbench onto that contract rather than adding a search box to it. Keep the genealogy walk itself, which is strong and trigger-enforced. | I64: Search a known material code, open it, walk backward to parents and forward to children, and confirm the attribution weights on each child sum to exactly 1.0 - enforced by a database trigger, so a failure here is a data problem. Confirm the page has exactly two states and that no legacy workbench panel remains reachable from it. v2.10.2 GENERICITY RATCHeT — the converged C5 page must use generic material-unit vocabulary from data/registry. Product UI/help text must not contain steel-only explanatory wording such as 'coil to heat/melt'. The unit type/native grain shown is data-driven so T-094 does not have to rewrite this page. | J64: 10 | K64: Not Started | L64: Presentation lane (Workers 1/2) | M64: DO NOT ASSIGN W3 | N64: Presentation target is active. Worker 3 must not edit M1 pages, presentation DB/seeds, current assistant wiring or runtime behaviour. | O64: Current M1 sequence / presentation owner hand-off | P64: v2.10.2 — generic material-unit acceptance added | Q64: Not Started | S64: REVISE — important design/coverage issue | T64: F-081 [Very Important] — Current GenealogyThreadPanel still contains steel-specific explanatory copy ('coil to heat/melt') while C5 is a generic material-unit explorer. If T-063 converges layout without removing product vocabulary, T-094 will immediately rework the same surface. | U64: F-081 — T-063 acceptance must require generic material-unit labels driven by data/registry and no industry noun in product UI. T-094 remains the whole-product ratchet. | V64: Current M1 sequence / presentation owner hand-off | W64: Presentation lane; Worker 3 only by explicit formal reassignment after zero-overlap + stable-prerequisite check | X64: MEDIUM | Y64: Deep design reconciliation 16-Aug-2026; Chapter 3/4 + Layer-B architecture + latest source/audit evidence | Z64: Track 1 — Presentation / Demo | AA64: 2026-08-20 Presentation RC | AB64: M1 Contract | AC64: Presentation-visible contract. Prepared Fleet v2 topology is allowed; no fake product behaviour and no production-only scope. | AD64: High | AE64: Worker 1 | AF64: Presentation data/config verticals | AG64: Frontend/UI feature | AH64: 9 | AI64: 1.5 | AJ64: =IF($K64="Done",0,MAX(0.25,$J64/$AH64)) -> 1.1111111 | AK64: =IF($K64="Done",0,$AJ64*$AI64) -> 1.6666667 | AL64: M1-B — journey/config surfaces | AM64: Current M1 sequence / presentation owner hand-off | AN64: Own Connections/Datasets/Import + Relationship/Mapping/Genealogy verticals. No DashboardGridLayout, AnalysisToolbox, Findings/Assistant, or W2 E2E. | AO64: Commit before downstream consumer starts; consumer must use the contract, not redesign producer-owned semantics.
A65: T-064 | B65: M1 | C65: M1-P4 | D65: Add job_definitions.target_definition_id and the JB error codes | E65: Backend | F65: Jobs | G65: Critical | H65: A repository search for target_definition_id returns zero hits. Chapter 3 4.5.5a specifies that a job must declare which definition it runs and under what version policy - a pinned version, or the current published one. Without it a job cannot say what it executes, which blocks J12 and tutorial T7. Add the column with a foreign key, the version policy field, and the JB error domain codes for the failure cases named in 4.5.5a. v2.10.2 TECH-LEAD RULING — T-064 remains REQUIRED for the M1 presentation/J12/tutorial T7, but only the stable functional/public contract is implemented now. definition_store(id), the canonical FK target, is created in T-089 and bound in T-090, so M1 MUST NOT add a fake FK to inspection_jobs or ppiq_definition_versions and MUST NOT create definition_store early. Carry target_definition_id, target_definition_version, target_version_policy (current_published|pinned), target_parameters, and the executed definition/version into run history through IDefinitionService/compatibility storage. Canonical FK/CHECK/trigger convergence is T-106 after T-089/T-090. | I65: VALIDATION CORRECTED IN v2.1: do not test by physically deleting the target definition. Definitions are an immutable versioned authority and a physical delete is not a state the design permits. Test the three states that can actually occur - the target is unpublished, the target id is missing, and a pinned version no longer exists - and confirm each fails with a JB code and a readable sentence. Also confirm the run history records the version actually used. v2.10.2 ACCEPTANCE CORRECTION — certify all four Chapter 3 refusals: JB01 target-required class with no target; JB02 target surface/job-class mismatch; JB03 pinned version not published or superseded (not 'vanished'); JB04 an attempted definition deletion/retirement operation is refused because jobs target it, naming the jobs. A valid current_published target and a valid pinned target resolve deterministically, target_parameters round-trip, and run history records the exact version executed. No M1 test may require the physical definition_store FK. | J65: 8 | K65: Done | L65: Presentation lane (Workers 1/2) | M65: CLOSED | N65: Presentation target is active. Worker 3 must not edit M1 pages, presentation DB/seeds, current assistant wiring or runtime behaviour. | O65: T-039 final IDefinitionService contract. M1 functional target/version semantics now; canonical physical FK/check/trigger convergence waits for T-089 + T-090 and is completed in T-106. | P65: v2.10.2 — M1 semantic contract retained; physical FK deferred to canonical store; JB/target contract completed | Q65: Not Started | S65: REVISE — critical design/sequencing issue | T65: F-053 [Critical] — T-064 requires a foreign key before the canonical FK target exists. It also omits target_parameters from the Chapter 3 job-target contract and its validation misses JB02/JB04 while describing a pinned version as 'no longer exists' even though published versions are immutable. F-061 [Critical] — T-064 already says version policy pinned/current-published, while T-106 says 'add the full version policy' again. The duplicate wording leaves ownership of the final DB checks/triggers ambiguous. | U65: F-053 — Keep T-064 mandatory for M1/J12/T7, but implement stable semantic fields through IDefinitionService/compatibility storage with no fake FK. Cover target_definition_id, target_definition_version, target_version_policy, target_parameters, executed-version history and JB01-JB04. T-106 performs canonical FK/check/trigger convergence after T-089/T-090 and adds the dependency DAG. F-061 — T-064 owns the M1 functional/public contract and compatibility semantics. T-106 owns canonical physical convergence after definition_store exists plus job_dependencies/DAG/cycle validation; it must not redesign the visible target/version contract. | V65: T-039 final IDefinitionService contract. M1 functional target/version semantics now; canonical physical FK/check/trigger convergence waits for T-089 + T-090 and is completed in T-106. | W65: Presentation contract required; NOT booster-safe for physical-schema work until canonical prerequisite exists | X65: HIGH | Y65: Deep design reconciliation 16-Aug-2026; Chapter 3/4 + Layer-B architecture + latest source/audit evidence | Z65: Track 1 — Presentation / Demo | AA65: 2026-08-20 Presentation RC | AB65: M1 Contract | AC65: M1 freezes the stable external/semantic contract only. Do not create fake final FKs/storage that M2a will replace; canonical physical convergence has an explicit M2a owner. | AD65: High | AE65: Worker 3 | AF65: Stable semantic booster — Jobs/Findings/Assistant | AG65: Backend/domain contract | AH65: 10 | AI65: 1.5 | AJ65: =IF($K65="Done",0,MAX(0.25,$J65/$AH65)) -> 0 | AK65: =IF($K65="Done",0,$AJ65*$AI65) -> 0 | AL65: M1-A — parallel foundations | AM65: GO now: T-039 semantic seam exists. M1 semantics only; NO fake FK. Final physical FK belongs to T-106 after T-089/T-090. | AN65: Own only T-064/T-067/T-076 files. No final M1 DB schema, DashboardGridLayout/AnalysisToolbox, or W1 config verticals. | AO65: Commit semantic target/version contract → W2 may start T-065; physical FK remains T-106.
A66: T-065 | B66: M1 | C66: M1-P4 | D66: J12 Analysis authoring: converge onto D3 Analysis Toolbox in S3 mode | E66: Frontend | F66: Engine | G66: Critical | H66: CORRECTED IN v2.1, and this was a Continuity Test blocker. v2.0 said wire the target and version selector into AnalysisJobConfigPage.tsx. That page has no Chapter 3 owner and is not the canonical surface: Chapter 3 4.4 D3 names /analysis/toolbox as the analysis authoring surface, and the design uses one shared authoring model, so analysis is authored in the shared shell in S3 mode. Showing the customer AnalysisJobConfigPage now and replacing it in M2 breaks the contract they were shown. Keep the existing backend services - AnalysisJobDefinitionEndpoints already provides definition-options, list, get, create, update, run and results - and converge the VISIBLE authoring onto D3 in S3 mode, with the target and version selector from the task above. Remove AnalysisJobConfigPage from the M1 navigation and record it on the M2a retirement list. | I66: Author one analysis definition entirely through /analysis/toolbox in S3 mode, attach a target and version, and run it. Confirm the three honest outcomes render distinctly: Completed, Blocked with the measured value beside its threshold in Amber, and Failed in Hot Red. Confirm AnalysisJobConfigPage is unreachable from the navigation used in the presentation. Do not weaken any gate threshold to produce a completion. | J66: 12 | K66: In Progress | L66: Presentation lane (Workers 1/2) | M66: DO NOT ASSIGN W3 | N66: Presentation target is active. Worker 3 must not edit M1 pages, presentation DB/seeds, current assistant wiring or runtime behaviour. | O66: T-064 M1 functional target/version contract + T-068 registry-driven outcome/grain options. Do not wait for the physical definition_store FK. | P66: v2.10.2 — T-068 moved before T-065 to avoid immediate same-file rework | Q66: Not Started | S66: REVISE — critical design/sequencing issue | T66: F-053 [Critical] — T-064 requires a foreign key before the canonical FK target exists. It also omits target_parameters from the Chapter 3 job-target contract and its validation misses JB02/JB04 while describing a pinned version as 'no longer exists' even though published versions are immutable. F-056 [Critical] — T-068 explicitly binds the UI to public.ml_outcome_definitions and GET /ml/foundation/outcomes, both compatibility-era authorities. Chapter 3 D3 requires registry-driven definition-options and T-090 later makes SM-06 OutcomeDefinition part of the immutable definition authority. F-062 [Very Important] — Current order builds the Analysis Toolbox in T-065 while its outcome/grain arrays remain hardcoded, then T-068 immediately rewrites the same page. This violates the no-rework sequencing rule. | U66: F-053 — Keep T-064 mandatory for M1/J12/T7, but implement stable semantic fields through IDefinitionService/compatibility storage with no fake FK. Cover target_definition_id, target_definition_version, target_version_policy, target_parameters, executed-version history and JB01-JB04. T-106 performs canonical FK/check/trigger convergence after T-089/T-090 and adds the dependency DAG. F-056 — T-068 must consume a stable analysis-options/outcome-registry service contract, not a physical table or temporary route. M2a swaps storage behind the contract. Complete T-068 before T-065 so the S3 authoring page is built registry-first instead of being rewritten immediately. F-062 — Dependency order is T-068 -> T-065. T-065 consumes registry-driven outcome/grain options from first implementation. | V66: T-064 M1 functional target/version contract + T-068 registry-driven outcome/grain options. Do not wait for the physical definition_store FK. | W66: Presentation lane; Worker 3 only by explicit formal reassignment after zero-overlap + stable-prerequisite check | X66: HIGH | Y66: Deep design reconciliation 16-Aug-2026; Chapter 3/4 + Layer-B architecture + latest source/audit evidence | Z66: Track 1 — Presentation / Demo | AA66: 2026-08-20 Presentation RC | AB66: M1 Contract | AC66: Registry authority must precede authoring consumption: T-068 before T-065. Visible contract must survive M2a unchanged. | AD66: High | AE66: Worker 2 | AF66: Presentation BI/UX + E2E release integration | AG66: Frontend/UI feature | AH66: 9 | AI66: 1.5 | AJ66: =IF($K66="Done",0,MAX(0.25,$J66/$AH66)) -> 1.3333333 | AK66: =IF($K66="Done",0,$AJ66*$AI66) -> 2 | AL66: M1-C — analysis/readiness/findings | AM66: T-064 M1 functional target/version contract + T-068 registry-driven outcome/g... | AN66: Own Dashboard/workspace/shared shell/AnalysisToolbox/E2E. No W1 active vertical files; no W3 Jobs/Findings/Assistant files. | AO66: Commit before downstream consumer starts; consumer must use the contract, not redesign producer-owned semantics.
A67: T-066 | B67: M1 | C67: M1-P4 | D67: One visible readiness authority on Home and Analysis | E67: Frontend | F67: Engine | G67: Critical | H67: ReadinessGate.cs is complete and correct: five dimensions, thresholds as a record, overall equals the worst dimension via Math.Max over the enum, and every dimension returns a reason string built from the measured value and its threshold. Today that authority is not visible in one place. Build one readiness panel showing the five dimensions, each with its measured value beside its threshold and its state, and place it on both Home and the Analysis surface reading from the same endpoint. v2.10.2 CONTINUITY CORRECTION — the visible panel must consume the canonical external route GET /api/readiness/evaluate (compatibility-backed during M1), not expose /api/ml/foundation/readiness as the customer contract. Canonical tenant/outcome threshold persistence and governed changes are owned by T-195. | I67: Compare the panel against a direct call to GET /api/ml/foundation/readiness. Every number on screen must match the API response exactly. Change one threshold in configuration and confirm the panel moves, proving it is not a static rendering. Compare the panel against GET /api/readiness/evaluate. During M1 a compatibility adapter may supply the same payload; after T-195 the identical visible contract must resolve from canonical readiness_thresholds/change history without UI changes. | J67: 6 | K67: In Progress | L67: Presentation lane (Workers 1/2) | M67: DO NOT ASSIGN W3 | N67: Presentation target is active. Worker 3 must not edit M1 pages, presentation DB/seeds, current assistant wiring or runtime behaviour. | O67: T-065 final D3 Analysis Toolbox surface; M1 compatibility readiness evaluator available. Canonical threshold persistence later T-195. | P67: v2.10.2 — stable readiness API facade + canonical threshold owner separated | Q67: Not Started | S67: REVISE — critical design/sequencing issue | T67: F-055 [Critical] — M1 T-066 certifies /api/ml/foundation/readiness, while the final Chapter 3 authority is /api/readiness/evaluate plus readiness_thresholds/readiness_threshold_changes and governed PUT semantics. No existing backlog task owns the canonical threshold persistence/change-history contract. | U67: F-055 — T-066 must render through the stable /api/readiness/evaluate facade (compatibility-backed in M1). Add T-195 for canonical tenant/outcome readiness thresholds, change history, fail-closed evaluation and governed updates before canonical readiness/model cutover. | V67: T-065 final D3 Analysis Toolbox surface; M1 compatibility readiness evaluator available. Canonical threshold persistence later T-195. | W67: Presentation lane; Worker 3 only by explicit formal reassignment after zero-overlap + stable-prerequisite check | X67: HIGH | Y67: Deep design reconciliation 16-Aug-2026; Chapter 3/4 + Layer-B architecture + latest source/audit evidence | Z67: Track 1 — Presentation / Demo | AA67: 2026-08-20 Presentation RC | AB67: M1 Contract | AC67: Presentation-visible contract. Prepared Fleet v2 topology is allowed; no fake product behaviour and no production-only scope. | AD67: High | AE67: Worker 2 | AF67: Presentation BI/UX + E2E release integration | AG67: Frontend/UI feature | AH67: 9 | AI67: 1.5 | AJ67: =IF($K67="Done",0,MAX(0.25,$J67/$AH67)) -> 0.66666667 | AK67: =IF($K67="Done",0,$AJ67*$AI67) -> 1 | AL67: M1-C — analysis/readiness/findings | AM67: T-065 final D3 Analysis Toolbox surface; M1 compatibility readiness evaluator... | AN67: Own Dashboard/workspace/shared shell/AnalysisToolbox/E2E. No W1 active vertical files; no W3 Jobs/Findings/Assistant files. | AO67: Commit → release W3 to T-067.
A68: T-067 | B68: M1 | C68: M1-P4 | D68: Findings evidence panel, registry-driven throughout | E68: Frontend | F68: Engine | G68: Very Important | H68: EXPANDED IN v2.1. A finding must open into its evidence: method, population, effect size, q-value after Benjamini-Hochberg, whether it survived stratification, and a path to the source rows. StatisticalDiscipline.cs already produces the ranking by absolute effect size with the p-value only as a tie-breaker at q equal to 0.05. Render what the engine computes. ADDED IN v2.1: the page's initial outcome and parameter state must come from the registry as well, not from a hardcoded default - a page that opens on a literal is the same Rule 1 defect as a dropdown built from one. | I68: Open the strongest finding and confirm all six elements are present. Confirm the ordering is by effect size and not p-value, by comparing against the API response. Change the registry's default outcome and confirm the page opens on the new one with no code change. | J68: 8 | K68: Done | L68: Presentation lane (Workers 1/2) | M68: CLOSED | N68: Presentation target is active. Worker 3 must not edit M1 pages, presentation DB/seeds, current assistant wiring or runtime behaviour. | O68: T-050 provenance/evidence drill + T-065 D3 authoring contract + T-066 visible readiness authority. | P68: v2.10.2 — explicit evidence/readiness dependencies | Q68: Not Started | S68: No new contradiction identified in this pass | V68: T-050 provenance/evidence drill + T-065 D3 authoring contract + T-066 visible readiness authority. | W68: Presentation lane; Worker 3 only by explicit formal reassignment after zero-overlap + stable-prerequisite check | X68: Low / not newly identified | Y68: Deep design reconciliation 16-Aug-2026; Chapter 3/4 + Layer-B architecture + latest source/audit evidence | Z68: Track 1 — Presentation / Demo | AA68: 2026-08-20 Presentation RC | AB68: M1 Contract | AC68: Presentation-visible contract. Prepared Fleet v2 topology is allowed; no fake product behaviour and no production-only scope. | AD68: High | AE68: Worker 3 | AF68: Stable semantic booster — Jobs/Findings/Assistant | AG68: Frontend/UI feature | AH68: 9 | AI68: 1.5 | AJ68: =IF($K68="Done",0,MAX(0.25,$J68/$AH68)) -> 0 | AK68: =IF($K68="Done",0,$AJ68*$AI68) -> 0 | AL68: M1-C — analysis/readiness/findings | AM68: WAIT for T-050 + T-065 + T-066 commits; then W3 owns Findings files exclusively. | AN68: Own only T-064/T-067/T-076 files. No final M1 DB schema, DashboardGridLayout/AnalysisToolbox, or W1 config verticals. | AO68: Commit → P4 may close once all other P4 tasks green.
A69: T-068 | B69: M1 | C69: M1-P4 | D69: Retire the hardcoded outcome and grain arrays | E69: Frontend | F69: Engine | G69: Critical | H69: Frontend/PlantProcess.Web/src/pages/Analysis/AnalysisToolboxPage.tsx line 18 declares OUTCOMES as a literal array of four steel-specific keys, and line 19 declares GRAINS as ["coil", "slab", "heat"]. A server registry already exists: table public.ml_outcome_definitions is exposed at GET /ml/foundation/outcomes by MlFoundationEndpoints.cs and carries the grain per outcome. AnalysisJobConfigPage already consumes it. Replace both arrays with the registry call and take the grain from the selected outcome's registry row rather than defaulting. v2.10.2 AUTHORITY CORRECTION — remove the literals through the stable analysis-options/outcome-registry contract used by D3 (for example /api/analysis-jobs/definition-options or the canonical /api/analyses/options facade), not by binding React to public.ml_outcome_definitions or the compatibility-era /ml/foundation/outcomes route. The physical outcome representation is allowed to change in T-090/T-147 with no frontend rewrite. | I69: Confirm the dropdown contents match the API response exactly. Add a registry row through the API and confirm it appears in the UI with no code change, which is the Rule 1 acceptance test. Also confirm no server code path falls back to the grain literal 'coil' when the outcome declares a different grain. The acceptance test adds/changes a registered outcome through the service/API contract and proves the UI follows without code change. Add an architecture assertion that AnalysisToolboxPage does not know the physical outcome table and has no fallback literal 'coil'. This task must close before T-065. | J69: 6 | K69: Done | L69: Presentation lane (Workers 1/2) | M69: DO NOT ASSIGN W3 | N69: Presentation target is active. Worker 3 must not edit M1 pages, presentation DB/seeds, current assistant wiring or runtime behaviour. | O69: T-039 definition-service/registry seam; complete BEFORE T-065. Canonical SM-06 storage convergence remains T-090/T-147. | P69: v2.10.2 — stable registry contract; no direct temporary outcome-table authority; reordered before T-065 | Q69: Not Started | S69: REVISE — critical design/sequencing issue | T69: F-056 [Critical] — T-068 explicitly binds the UI to public.ml_outcome_definitions and GET /ml/foundation/outcomes, both compatibility-era authorities. Chapter 3 D3 requires registry-driven definition-options and T-090 later makes SM-06 OutcomeDefinition part of the immutable definition authority. F-059 [Critical] — T-094 says rename the canonical grain literal 'coil' to one generic term. The frozen design does not have one generic grain: it has material_unit_type_definitions, native_grain and dynamic outcome/model grain_code. Replacing 'coil' with 'material' would preserve the same architectural error under a new word. F-062 [Very Important] — Current order builds the Analysis Toolbox in T-065 while its outcome/grain arrays remain hardcoded, then T-068 immediately rewrites the same page. This violates the no-rework sequencing rule. | U69: F-056 — T-068 must consume a stable analysis-options/outcome-registry service contract, not a physical table or temporary route. M2a swaps storage behind the contract. Complete T-068 before T-065 so the S3 authoring page is built registry-first instead of being rewritten immediately. F-059 — Remove hardcoded/default coil semantics. Preserve customer-declared multi-grain unit types and outcome-specific grain_code. Rename T-094 scope from 'rename canonical grain' to 'remove hardcoded canonical grain default and bind to registry/material-unit authority'. F-062 — Dependency order is T-068 -> T-065. T-065 consumes registry-driven outcome/grain options from first implementation. | V69: T-039 definition-service/registry seam; complete BEFORE T-065. Canonical SM-06 storage convergence remains T-090/T-147. | W69: Presentation lane; Worker 3 only by explicit formal reassignment after zero-overlap + stable-prerequisite check | X69: HIGH | Y69: Deep design reconciliation 16-Aug-2026; Chapter 3/4 + Layer-B architecture + latest source/audit evidence | Z69: Track 1 — Presentation / Demo | AA69: 2026-08-20 Presentation RC | AB69: M1 Contract | AC69: Registry authority must precede authoring consumption: T-068 before T-065. Visible contract must survive M2a unchanged. | AD69: High | AE69: Worker 2 | AF69: Presentation BI/UX + E2E release integration | AG69: Frontend/UI feature | AH69: 9 | AI69: 1.5 | AJ69: =IF($K69="Done",0,MAX(0.25,$J69/$AH69)) -> 0 | AK69: =IF($K69="Done",0,$AJ69*$AI69) -> 0 | AL69: M1-C — analysis/readiness/findings | AM69: T-039 definition-service/registry seam; complete BEFORE T-065. Canonical SM-0... | AN69: Own Dashboard/workspace/shared shell/AnalysisToolbox/E2E. No W1 active vertical files; no W3 Jobs/Findings/Assistant files. | AO69: Commit before downstream consumer starts; consumer must use the contract, not redesign producer-owned semantics.
A70: T-069 | B70: M1 | C70: M1-P5 | D70: Website, part 1: the five-product information architecture | E70: Website | F70: Public site | G70: Critical | H70: CORRECTED IN v2.1, and this was a material visible-contract error. v2.0 said do not open /products/:code because the wrong architecture is an M2 or M3 fix. That is demo avoidance, not design conformance: the customer sees the header, the navigation and the company positioning whether or not a product route is clicked, and Chapter 6 6.2 states plainly that SOU has FIVE separate products - PlantProcess IQ, MES, QES, Yard and Warehouse Management, Energy Management - with PPIQ as the flagship but NOT as the company and NOT as a container around the other four. The current site is deliberately the opposite: it removes direct product navigation and a validator asserts they are removed. Correct the visible architecture now. This is not a rebuild - Chapter 6 6.2.0 keeps 18 components as-is, enhances 9, and replaces exactly one, LegacyProductRoute. Add the Products mega-menu and the portfolio page, remove the assertion that the sibling products must not exist, and replace the redirect. | I70: The header shows a Products menu listing five products. The portfolio page presents five, with PPIQ as flagship and none of the other four described as a PPIQ capability pack. Update the validator that currently asserts their removal - a test that pins the wrong architecture is worse than no test. Confirm no claim on any product page violates the Chapter 6 6.2.10 honesty rule. | J70: 8 | K70: Done | L70: Completed / no assignment | M70: CLOSED | N70: No new work. Preserve evidence and do not reopen unless a regression proves it. | O70: — | P70: CARRIED v2.9.2 | Q70: Done — backlog-claimed; closure evidence not reloaded in this pass | S70: No new contradiction identified in this pass | V70: — | W70: CLOSED | X70: Low / not newly identified | Y70: Deep design reconciliation 16-Aug-2026; Chapter 3/4 + Layer-B architecture + latest source/audit evidence | Z70: Track 1 — Presentation / Demo | AA70: 2026-08-20 Presentation RC | AB70: M1 Contract | AC70: Presentation-visible contract. Prepared Fleet v2 topology is allowed; no fake product behaviour and no production-only scope. | AD70: Closed | AE70: CLOSED | AF70: Closed / evidence preserved | AG70: Closed | AH70: 0 | AI70: 0 | AJ70: =IF($K70="Done",0,MAX(0.25,$J70/$AH70)) -> 0 | AK70: =IF($K70="Done",0,$AJ70*$AI70) -> 0 | AL70: CLOSED | AM70: Closed — do not reopen without contradictory regression evidence. | AN70: No active lock. | AO70: None — preserve evidence.
A71: T-070 | B71: M1 | C71: M1-P5 | D71: Website, part 2: polish the presentation routes | E71: Website | F71: Public site | G71: Important | H71: With the architecture corrected, polish only the routes you will actually open: home, the PPIQ narrative, proof, security and the call to action. Preserve the components the Chapter 6 audit marked keep: HeroTopology, GoldenThread, TrustEngine, SignalVsNoise, useScrollDraw, RoiCalculator, RequestDemoForm, ConnectorHonestyBlock and PositioningTruthBlock. AUDIT HARDENING IN v2.9.2. The strongest existing polished website section is the minimum visual authority for every route touched here. Preserve one premium industrial/high-tech system across typography, spacing, node/card geometry, border radius, glow depth, cyan/green accent behaviour, graphical connector language and motion. Fix visible mojibake or HTML entities on the presented routes rather than carrying them into the meeting. New sections may extend the design system but never introduce a weaker second visual language. | I71: Click every link on every route you will open and confirm none is dead. Check desktop, mobile and keyboard navigation on those routes. Confirm no page shows a blocker, an unfinished item or a failed test, per the standing website honesty rule. Add a side-by-side visual comparison against the strongest existing website section at desktop and mobile. No text overflow, low-contrast text, disconnected graphical wires, raw HTML entities or encoding damage. Motion communicates data/system flow and respects `prefers-reduced-motion`. If a new section makes the company look less sophisticated than the reference section, T-070 is not done. | J71: 6 | K71: Done | L71: Completed / no assignment | M71: CLOSED | N71: No new work. Preserve evidence and do not reopen unless a regression proves it. | O71: — | P71: CARRIED v2.9.2 | Q71: Done — backlog-claimed; closure evidence not reloaded in this pass | S71: No new contradiction identified in this pass | V71: — | W71: CLOSED | X71: Low / not newly identified | Y71: Deep design reconciliation 16-Aug-2026; Chapter 3/4 + Layer-B architecture + latest source/audit evidence | Z71: Track 1 — Presentation / Demo | AA71: 2026-08-20 Presentation RC | AB71: M1 Contract | AC71: Presentation-visible contract. Prepared Fleet v2 topology is allowed; no fake product behaviour and no production-only scope. | AD71: Closed | AE71: CLOSED | AF71: Closed / evidence preserved | AG71: Closed | AH71: 0 | AI71: 0 | AJ71: =IF($K71="Done",0,MAX(0.25,$J71/$AH71)) -> 0 | AK71: =IF($K71="Done",0,$AJ71*$AI71) -> 0 | AL71: CLOSED | AM71: Closed — do not reopen without contradictory regression evidence. | AN71: No active lock. | AO71: None — preserve evidence.
A72: T-071 | B72: M1 | C72: M1-P5 | D72: Build the G1 persistent assistant dock | E72: Frontend | F72: Chatbot | G72: Critical | H72: Chapter 4 5.7.1 specifies a persistent dock present on every authenticated page, not a route. Today Frontend/PlantProcess.Web/src/components/assistant/AssistantChat.tsx is rendered by exactly one page, Phase8/AssistantRuntimePage.tsx. Move the chat into a dock shell mounted in AppLayout so it is available on every authenticated presentation surface, with a collapsed and expanded state. This is a visible-contract item: shipping a separate page in M1 and a dock after M2 would fail the Customer Contract Continuity Test. AUDIT HARDENING IN v2.9.2. The dock's configuration/provider path is authentication-aware. Do not fire a protected assistant-configuration request before the authenticated token/session is available; lazy-load or gate it through the authenticated layout lifecycle so the first open does not produce a transient 401 that disappears only after retry. | I72: Open the dock on at least five different pages and confirm the conversation persists across navigation. Confirm the collapsed state does not obscure any control. Add a vitest asserting the dock renders inside the authenticated layout and not as a route element. From a fresh browser session, log in and open the assistant for the first time. The network log contains no assistant/configuration 401, the dock reaches its ready state without manual retry, and the same remains true after hard reload. | J72: 8 | K72: Done | L72: Completed / no assignment | M72: CLOSED | N72: No new work. Preserve evidence and do not reopen unless a regression proves it. | O72: — | P72: CARRIED v2.9.2 | Q72: Done — backlog-claimed; closure evidence not reloaded in this pass | S72: No new contradiction identified in this pass | V72: — | W72: CLOSED | X72: Low / not newly identified | Y72: Deep design reconciliation 16-Aug-2026; Chapter 3/4 + Layer-B architecture + latest source/audit evidence | Z72: Track 1 — Presentation / Demo | AA72: 2026-08-20 Presentation RC | AB72: M1 Contract | AC72: Assistant answers must be grounded and permission-safe. Unsupported precision must refuse; 'meaningful but inaccurate' is NOT an acceptable M1 contract. | AD72: Closed | AE72: CLOSED | AF72: Closed / evidence preserved | AG72: Closed | AH72: 0 | AI72: 0 | AJ72: =IF($K72="Done",0,MAX(0.25,$J72/$AH72)) -> 0 | AK72: =IF($K72="Done",0,$AJ72*$AI72) -> 0 | AL72: CLOSED | AM72: Closed — do not reopen without contradictory regression evidence. | AN72: No active lock. | AO72: None — preserve evidence.
A73: T-072 | B73: M1 | C73: M1-P5 | D73: Page and widget context envelope | E73: Backend | F73: Chatbot | G73: Critical | H73: The assistant must know what the user is looking at. Extend the ask request so the client sends a context envelope: current route, page code, focused widget code, active selections and filters, and the widget's own last result summary with its evidence handles. The endpoint is POST /api/assistant/ask in Backend/PlantProcess.Api/Endpoints/Assistant/AssistantEndpoints.cs, which already accepts ContextChips. Use the context to narrow retrieval rather than to answer. | I73: Ask the same question on two different pages and confirm the retrieved evidence differs. Assert in an integration test that the context reaches the retrieval call and that no context field is echoed into the answer text unverified. | J73: 8 | K73: Done | L73: Completed / no assignment | M73: CLOSED | N73: No new work. Preserve evidence and do not reopen unless a regression proves it. | O73: — | P73: CARRIED v2.9.2 | Q73: Done — backlog-claimed; closure evidence not reloaded in this pass | S73: No new contradiction identified in this pass | V73: — | W73: CLOSED | X73: Low / not newly identified | Y73: Deep design reconciliation 16-Aug-2026; Chapter 3/4 + Layer-B architecture + latest source/audit evidence | Z73: Track 1 — Presentation / Demo | AA73: 2026-08-20 Presentation RC | AB73: M1 Contract | AC73: Assistant answers must be grounded and permission-safe. Unsupported precision must refuse; 'meaningful but inaccurate' is NOT an acceptable M1 contract. | AD73: Closed | AE73: CLOSED | AF73: Closed / evidence preserved | AG73: Closed | AH73: 0 | AI73: 0 | AJ73: =IF($K73="Done",0,MAX(0.25,$J73/$AH73)) -> 0 | AK73: =IF($K73="Done",0,$AJ73*$AI73) -> 0 | AL73: CLOSED | AM73: Closed — do not reopen without contradictory regression evidence. | AN73: No active lock. | AO73: None — preserve evidence.
A74: T-073 | B74: M1 | C74: M1-P5 | D74: Add the page and widget chunk family to the retrieval corpus | E74: AI+ML | F74: Chatbot | G74: Critical | H74: This is the single highest-value change in the sprint. Backend/PlantProcess.Infrastructure/Assistant/CanonicalChunkProducer.cs currently builds only five chunk families: CONNECTOR, DATASET and MAPPING from configuration, DOC for the honesty contract, and FINDING for the latest correlation results. Nothing describes what is on the page. Add a family that emits one true sentence per widget result, for example: 'On page Quality Monitoring, widget Defect rate by equipment shows EAF 3.4 per square metre and Caster 1.9 per square metre for June 2026, over 1,284 coils.' Every number in that sentence must come from a real query result and carry an evidence handle. Then rebuild the index through the existing POST /api/assistant/reindex endpoint, which is already wired to this producer through NpgsqlRetrievalIndex. This matters because GroundingService blocks any sentence containing a number not present in retrieved evidence, so without this family the assistant refuses every question about a chart. | I74: Reindex, then ask 'what does this chart show' on three different pages and confirm each answer contains numbers that match the widget on screen and carries at least one citation. Then delete the new chunks, reindex, and confirm the assistant returns the honest refusal rather than inventing an answer. Both behaviours must be demonstrable. | J74: 8 | K74: Done | L74: Completed / no assignment | M74: CLOSED | N74: No new work. Preserve evidence and do not reopen unless a regression proves it. | O74: — | P74: CARRIED v2.9.2 | Q74: Done — backlog-claimed; closure evidence not reloaded in this pass | S74: No new contradiction identified in this pass | V74: — | W74: CLOSED | X74: Low / not newly identified | Y74: Deep design reconciliation 16-Aug-2026; Chapter 3/4 + Layer-B architecture + latest source/audit evidence | Z74: Track 1 — Presentation / Demo | AA74: 2026-08-20 Presentation RC | AB74: M1 Contract | AC74: Assistant answers must be grounded and permission-safe. Unsupported precision must refuse; 'meaningful but inaccurate' is NOT an acceptable M1 contract. | AD74: Closed | AE74: CLOSED | AF74: Closed / evidence preserved | AG74: Closed | AH74: 0 | AI74: 0 | AJ74: =IF($K74="Done",0,MAX(0.25,$J74/$AH74)) -> 0 | AK74: =IF($K74="Done",0,$AJ74*$AI74) -> 0 | AL74: CLOSED | AM74: Closed — do not reopen without contradictory regression evidence. | AN74: No active lock. | AO74: None — preserve evidence.
A75: T-074 | B75: M1 | C75: M1-P5 | D75: Registry-typed quantity guard on assistant answers | E75: Backend | F75: Chatbot | G75: Very Important | H75: GroundingService.Enforce already blocks any sentence with a number absent from the retrieved claims and blocks the phrases 'root cause', 'is caused by', 'will cause', 'guaranteed' and 'will save'. Add a typed layer above it: when the question names a quantity that exists in the parameter registry, validate the answer's unit, sign and range against the registry row for that parameter. Reject a date where a speed was asked for, a mass where a speed was asked for, and a negative value where the registry declares a positive range. | I75: Unit tests feeding a crafted draft for each rejection case and asserting the sentence is blocked. Then a live check: ask for a casting speed and confirm the answer either gives a speed with the registry's unit, gives an evidence band, or refuses. It must never return a date or a mass. | J75: 4 | K75: Done | L75: Completed / no assignment | M75: CLOSED | N75: No new work. Preserve evidence and do not reopen unless a regression proves it. | O75: — | P75: CARRIED v2.9.2 | Q75: Done — backlog-claimed; closure evidence not reloaded in this pass | S75: No new contradiction identified in this pass | V75: — | W75: CLOSED | X75: Low / not newly identified | Y75: Deep design reconciliation 16-Aug-2026; Chapter 3/4 + Layer-B architecture + latest source/audit evidence | Z75: Track 1 — Presentation / Demo | AA75: 2026-08-20 Presentation RC | AB75: M1 Contract | AC75: Assistant answers must be grounded and permission-safe. Unsupported precision must refuse; 'meaningful but inaccurate' is NOT an acceptable M1 contract. | AD75: Closed | AE75: CLOSED | AF75: Closed / evidence preserved | AG75: Closed | AH75: 0 | AI75: 0 | AJ75: =IF($K75="Done",0,MAX(0.25,$J75/$AH75)) -> 0 | AK75: =IF($K75="Done",0,$AJ75*$AI75) -> 0 | AL75: CLOSED | AM75: Closed — do not reopen without contradictory regression evidence. | AN75: No active lock. | AO75: None — preserve evidence.
A76: T-075 | B76: M1 | C76: M1-P5 | D76: Citation chips, evidence strip and suggested questions | E76: Frontend | F76: Chatbot | G76: Very Important | H76: Render each citation as a chip that expands to its evidence, add an evidence strip under the answer, and add an Open in page action that navigates to the surface the evidence came from. Add three to five suggested starter questions derived from the current page context so a live demonstration has a safe opening move. | I76: Click a citation chip and confirm it expands to the underlying evidence. Click Open in page and confirm it navigates to the correct surface with the relevant selection applied. Confirm suggested questions change between two different pages. | J76: 4 | K76: Done | L76: Completed / no assignment | M76: CLOSED | N76: No new work. Preserve evidence and do not reopen unless a regression proves it. | O76: — | P76: CARRIED v2.9.2 | Q76: Done — backlog-claimed; closure evidence not reloaded in this pass | S76: No new contradiction identified in this pass | V76: — | W76: CLOSED | X76: Low / not newly identified | Y76: Deep design reconciliation 16-Aug-2026; Chapter 3/4 + Layer-B architecture + latest source/audit evidence | Z76: Track 1 — Presentation / Demo | AA76: 2026-08-20 Presentation RC | AB76: M1 Contract | AC76: Assistant answers must be grounded and permission-safe. Unsupported precision must refuse; 'meaningful but inaccurate' is NOT an acceptable M1 contract. | AD76: Closed | AE76: CLOSED | AF76: Closed / evidence preserved | AG76: Closed | AH76: 0 | AI76: 0 | AJ76: =IF($K76="Done",0,MAX(0.25,$J76/$AH76)) -> 0 | AK76: =IF($K76="Done",0,$AJ76*$AI76) -> 0 | AL76: CLOSED | AM76: Closed — do not reopen without contradictory regression evidence. | AN76: No active lock. | AO76: None — preserve evidence.
A77: T-076 | B77: M1 | C77: M1-P5 | D77: Certified question pack and offline fallback | E77: Documentation | F77: Chatbot | G77: Very Important | H77: Prepare 10 to 15 questions whose evidence is known to exist, covering at least three pages, and record for each the expected answer shape: a value with a unit, an evidence band with a record count, a conditional answer naming what would narrow it, or an honest refusal. These are not scripted answers; they are a known-good evidence landscape. Select two or three for live use. Prepare the offline path so a network failure downgrades to the extractive model rather than to an error. | I77: Run all 10 to 15 twice, once online and once with the model endpoint unreachable, and record both answers. Any question that refuses in both runs is removed from the live set. | J77: 4 | K77: Not Started | L77: Presentation lane (Workers 1/2) | M77: DO NOT ASSIGN W3 | N77: Presentation target is active. Worker 3 must not edit M1 pages, presentation DB/seeds, current assistant wiring or runtime behaviour. | O77: M1-P3 T-049..T-052 closed + M1-P4 T-053..T-068 closed; certify the frozen visible Assistant contract only. | P77: v2.10.2 — explicit presentation-freeze gate | Q77: Not Started | S77: No new contradiction identified in this pass | V77: M1-P3 T-049..T-052 closed + M1-P4 T-053..T-068 closed; certify the frozen visible Assistant contract only. | W77: Presentation lane; Worker 3 only by explicit formal reassignment after zero-overlap + stable-prerequisite check | X77: Low / not newly identified | Y77: Deep design reconciliation 16-Aug-2026; Chapter 3/4 + Layer-B architecture + latest source/audit evidence | Z77: Track 1 — Presentation / Demo | AA77: 2026-08-20 Presentation RC | AB77: M1 Contract | AC77: Assistant answers must be grounded and permission-safe. Unsupported precision must refuse; 'meaningful but inaccurate' is NOT an acceptable M1 contract. | AD77: High | AE77: Worker 3 | AF77: Stable semantic booster — Jobs/Findings/Assistant | AG77: AI documentation/static analysis | AH77: 18 | AI77: 1.35 | AJ77: =IF($K77="Done",0,MAX(0.25,$J77/$AH77)) -> 0.25 | AK77: =IF($K77="Done",0,$AJ77*$AI77) -> 0.3375 | AL77: M1-D — certification/release freeze | AM77: WAIT for T-053..T-068 frozen/closed; then certify Assistant against frozen M1 contract. | AN77: Own only T-064/T-067/T-076 files. No final M1 DB schema, DashboardGridLayout/AnalysisToolbox, or W1 config verticals. | AO77: Commit → W2 starts T-077 golden journey.
A78: T-077 | B78: M1 | C78: M1-P5 | D78: One Playwright journey covering all six beats | E78: Testing | F78: E2E | G78: Critical | H78: Write a single spec that walks the whole demonstration: connect, register a dataset, import, map and publish the relationship, open genealogy, create a page, add a widget through the shared shell, edit its query, save, open the six dashboards, cross-filter, run an analysis and see the readiness outcome, ask the assistant a question on a page, open the evidence, and open the website routes. The existing E2E stage in the Jenkinsfile already runs the full Playwright suite through deploy/scripts/ci-e2e-stack.sh, so this spec joins a gate that actually executes. | I78: VALIDATION CORRECTED IN v2.1: clean database means a FRESHLY REBUILT ppiq_presentation, produced by Rebuild-PresentationDb.ps1 - not an empty installation. The demonstration runs on prepared data by design, so an empty-install precondition would test something the presentation never does. The spec passes twice consecutively from a fresh rebuild. A deliberate break in any beat fails the spec at that beat with a readable assertion message. | J78: 6 | K78: Not Started | L78: Presentation lane (Workers 1/2) | M78: DO NOT ASSIGN W3 | N78: Presentation target is active. Worker 3 must not edit M1 pages, presentation DB/seeds, current assistant wiring or runtime behaviour. | O78: T-053..T-076 complete; journey runs only after final M1 visible surfaces/contracts are frozen. | P78: v2.10.2 — explicit six-beat journey gate | Q78: Not Started | S78: No new contradiction identified in this pass | V78: T-053..T-076 complete; journey runs only after final M1 visible surfaces/contracts are frozen. | W78: Presentation lane; Worker 3 only by explicit formal reassignment after zero-overlap + stable-prerequisite check | X78: Low / not newly identified | Y78: Deep design reconciliation 16-Aug-2026; Chapter 3/4 + Layer-B architecture + latest source/audit evidence | Z78: Track 1 — Presentation / Demo | AA78: 2026-08-20 Presentation RC | AB78: M1 Contract | AC78: Golden journey runs on freshly rebuilt prepared ppiq_presentation. Do not require live bulk import merely to prove the presentation. | AD78: High | AE78: Worker 2 | AF78: Presentation BI/UX + E2E release integration | AG78: Integration/E2E/certification | AH78: 5 | AI78: 1.7 | AJ78: =IF($K78="Done",0,MAX(0.25,$J78/$AH78)) -> 1.2 | AK78: =IF($K78="Done",0,$AJ78*$AI78) -> 2.04 | AL78: M1-D — certification/release freeze | AM78: T-053..T-076 complete; journey runs only after final M1 visible surfaces/cont... | AN78: Own Dashboard/workspace/shared shell/AnalysisToolbox/E2E. No W1 active vertical files; no W3 Jobs/Findings/Assistant files. | AO78: Commit before downstream consumer starts; consumer must use the contract, not redesign producer-owned semantics.
A79: T-078 | B79: M1 | C79: M1-P5 | D79: Execute visual regression and accessibility on the presented routes | E79: Testing | F79: Visual and a11y | G79: Very Important | H79: package.json already defines test:visual and test:a11y as genuine Playwright invocations, but nothing in the pipeline calls them, and tools/ci/validate-real-ui-gates.cjs invokes them with --list, so it verifies the gates exist rather than that they pass. Also package.json line 84 defines phase9:matrix with --list. Point the visual and accessibility specs at the presentation routes and run them for real. Remove the --list flags from validate-real-ui-gates.cjs. | I79: Both suites run and pass on every presented route. Confirm by deliberately introducing a contrast failure and checking the accessibility suite goes red, then reverting. The first run on a machine writes visual baselines and reports them as failures; that is expected and the second run is the real one. | J79: 4 | K79: Not Started | L79: Presentation lane (Workers 1/2) | M79: DO NOT ASSIGN W3 | N79: Presentation target is active. Worker 3 must not edit M1 pages, presentation DB/seeds, current assistant wiring or runtime behaviour. | O79: T-077 golden journey green; run visual/a11y against the final presented routes. | P79: v2.10.2 — explicit final-route dependency | Q79: Not Started | S79: No new contradiction identified in this pass | V79: T-077 golden journey green; run visual/a11y against the final presented routes. | W79: Presentation lane; Worker 3 only by explicit formal reassignment after zero-overlap + stable-prerequisite check | X79: Low / not newly identified | Y79: Deep design reconciliation 16-Aug-2026; Chapter 3/4 + Layer-B architecture + latest source/audit evidence | Z79: Track 1 — Presentation / Demo | AA79: 2026-08-20 Presentation RC | AB79: M1 Contract | AC79: Presentation-visible contract. Prepared Fleet v2 topology is allowed; no fake product behaviour and no production-only scope. | AD79: High | AE79: Worker 2 | AF79: Presentation BI/UX + E2E release integration | AG79: Integration/E2E/certification | AH79: 5 | AI79: 1.7 | AJ79: =IF($K79="Done",0,MAX(0.25,$J79/$AH79)) -> 0.8 | AK79: =IF($K79="Done",0,$AJ79*$AI79) -> 1.36 | AL79: M1-D — certification/release freeze | AM79: T-077 golden journey green; run visual/a11y against the final presented routes. | AN79: Own Dashboard/workspace/shared shell/AnalysisToolbox/E2E. No W1 active vertical files; no W3 Jobs/Findings/Assistant files. | AO79: Commit before downstream consumer starts; consumer must use the contract, not redesign producer-owned semantics.
A80: T-079 | B80: M1 | C80: M1-P5 | D80: Failure injection suite | E80: Testing | F80: E2E | G80: Very Important | H80: Rehearse the failures that are most likely to happen live: one widget query fails while the page keeps working; the assistant refuses because evidence is missing; the API is restarted mid-demonstration; a filter selection returns no rows; the model endpoint is unreachable. Each must produce a designed state, not a stack trace. | I80: Five scripted injections, each with a screenshot of the resulting state in the evidence folder, each showing a sentence rather than a raw error. A red outline with no sentence beside it is a failure of the specification, not an acceptable outcome. | J80: 3 | K80: Not Started | L80: Presentation lane (Workers 1/2) | M80: DO NOT ASSIGN W3 | N80: Presentation target is active. Worker 3 must not edit M1 pages, presentation DB/seeds, current assistant wiring or runtime behaviour. | O80: T-077 green + final M1 runtime/environment available; inject failures only after the visible contract is frozen. | P80: v2.10.2 — explicit final-contract dependency | Q80: Not Started | S80: No new contradiction identified in this pass | V80: T-077 green + final M1 runtime/environment available; inject failures only after the visible contract is frozen. | W80: Presentation lane; Worker 3 only by explicit formal reassignment after zero-overlap + stable-prerequisite check | X80: Low / not newly identified | Y80: Deep design reconciliation 16-Aug-2026; Chapter 3/4 + Layer-B architecture + latest source/audit evidence | Z80: Track 1 — Presentation / Demo | AA80: 2026-08-20 Presentation RC | AB80: M1 Contract | AC80: Presentation-visible contract. Prepared Fleet v2 topology is allowed; no fake product behaviour and no production-only scope. | AD80: High | AE80: Worker 2 | AF80: Presentation BI/UX + E2E release integration | AG80: Integration/E2E/certification | AH80: 5 | AI80: 1.7 | AJ80: =IF($K80="Done",0,MAX(0.25,$J80/$AH80)) -> 0.6 | AK80: =IF($K80="Done",0,$AJ80*$AI80) -> 1.02 | AL80: M1-D — certification/release freeze | AM80: T-077 green + final M1 runtime/environment available; inject failures only af... | AN80: Own Dashboard/workspace/shared shell/AnalysisToolbox/E2E. No W1 active vertical files; no W3 Jobs/Findings/Assistant files. | AO80: Commit before downstream consumer starts; consumer must use the contract, not redesign producer-owned semantics.
A81: T-080 | B81: M1 | C81: M1-P5 | D81: Capture the Customer Contract Continuity snapshots | E81: Testing | F81: Continuity | G81: Critical | H81: On the last day of M1, capture the visible contract: a screenshot of every presented page, the navigation tree, control positions, the Add Widget and Edit Widget flow, the wiring and SQL modes, the assistant dock, the engine surfaces, any logging surface shown, and the website routes. Store them under docs/m1/continuity/ with a manifest naming each file and the route it came from. | I81: The manifest covers every row of the traceability matrix. This set becomes the regression truth for M2: after M2 the comparison must show no change to navigation, control placement, authoring flow, terminology or refusal semantics. Additions and speed improvements are allowed; replacements are not. | J81: 4 | K81: Not Started | L81: Presentation lane (Workers 1/2) | M81: DO NOT ASSIGN W3 | N81: Presentation target is active. Worker 3 must not edit M1 pages, presentation DB/seeds, current assistant wiring or runtime behaviour. | O81: T-076..T-079 complete; capture continuity only from the final M1 presentation state. | P81: v2.10.2 — continuity snapshot gate tightened | Q81: Not Started | S81: No new contradiction identified in this pass | V81: T-076..T-079 complete; capture continuity only from the final M1 presentation state. | W81: Presentation lane; Worker 3 only by explicit formal reassignment after zero-overlap + stable-prerequisite check | X81: Low / not newly identified | Y81: Deep design reconciliation 16-Aug-2026; Chapter 3/4 + Layer-B architecture + latest source/audit evidence | Z81: Track 1 — Presentation / Demo | AA81: 2026-08-20 Presentation RC | AB81: M1 Contract | AC81: Mandatory presentation-freeze/rehearsal evidence before calling the 20-Aug package presentation-ready. | AD81: High | AE81: Worker 2 | AF81: Presentation BI/UX + E2E release integration | AG81: Integration/E2E/certification | AH81: 5 | AI81: 1.7 | AJ81: =IF($K81="Done",0,MAX(0.25,$J81/$AH81)) -> 0.8 | AK81: =IF($K81="Done",0,$AJ81*$AI81) -> 1.36 | AL81: M1-D — certification/release freeze | AM81: T-076..T-079 complete; capture continuity only from the final M1 presentation... | AN81: Own Dashboard/workspace/shared shell/AnalysisToolbox/E2E. No W1 active vertical files; no W3 Jobs/Findings/Assistant files. | AO81: Commit before downstream consumer starts; consumer must use the contract, not redesign producer-owned semantics.
... A87: T-086 | B87: M2a | C87: M2a-P1 | D87: Freeze and certify Fleet v2 as the M2 reference validation dataset | E87: Testing | F87: Emulated sources | G87: Critical | H87: NEW IN v2.7, and it carries the rule that matters more than the manifest. Version and freeze the phenomenon manifest from M1 with its PREDECLARED expected direction, effect bands, minimum populations, conditioning variables and negative controls. M2 ALGORITHMS MUST DISCOVER OR HONESTLY REFUSE THESE BEHAVIOURS; THEY MUST NEVER KNOW THE ANSWERS FROM CODE. Write a machine-readable M2 baseline manifest recording dataset version, generator version and seed, source schema versions, important source row counts and cardinalities, phenomenon ids, expected population ranges, negative controls, genealogy and conservation checks, and fixture identity hashes where useful. THEN THE IMMUTABILITY CONTRACT, which is the point of the whole task: during M2 the baseline is NOT modified every time an algorithm disappoints. If a feature cannot recover a behaviour the certified dataset genuinely contains, THAT IS A PRODUCT FINDING, not permission to tune the data until the test passes. Adding correlation to the generator so the optimiser succeeds is how a benchmark stops measuring anything. If M2 later needs new scenarios, create a VERSIONED EXTENSION - Fleet v2.1 or v3 - and never silently change the certified M1 baseline. | I87: The manifest exists, is machine-readable, and a harness run against the certified fleet reproduces the M1 result. The immutability contract is written into the repository where a developer will meet it, not only in the backlog. A named test asserts the baseline fixture identity, so a silent change to the certified dataset fails rather than passing quietly. State plainly which questions this baseline is meant to answer - does the engine recover the known good operating region while accounting for grade, equipment, shift and confounding; does practice learning recover the planted behaviour and reject the negative control; does readiness answer where support is sufficient and refuse where it is not. BENCHMARK HARDENING, because a reference dataset that only freezes phenomena cannot support an optimiser: every case carries a `benchmark_case_id`; the controllable parameters are named with their safe bounds; a known-good and a known-bad operating region are declared; an optimisation tolerance states how close a result must land to count as recovered; the units are split deterministically into development, validation and HOLDOUT, and the holdout is not readable by any development run; the expected refusal conditions are declared so an honest refusal is a pass rather than a failure; and TEST-ONLY TRUTH MUST NOT ENTER THE PRODUCTION RUNTIME - a named test asserts that no planted answer, holdout label or benchmark expectation is reachable from product code. | J87: 8 | K87: Not Started | L87: Core platform / presentation-core lane | M87: NOT W3 PRIMARY | N87: Do not assign to Worker 3 unless a specific AI/ML integration hand-off is requested. | O87: M2a dependency order | P87: CARRIED v2.9.2 | Q87: Not Started | S87: No new contradiction identified in this pass | V87: M2a dependency order | W87: NOT W3 PRIMARY | X87: Low / not newly identified | Y87: Deep design reconciliation 16-Aug-2026; Chapter 3/4 + Layer-B architecture + latest source/audit evidence | Z87: Track 2 — Real Customer Product | AA87: 2026-09-30 Customer Pilot RC | AB87: Customer Release | AC87: Real generic product on canonical ppiq_staging / ppiq_meta / ppiq_plant. No customer/demo vocabulary, no prepared plant rows on clean install. | AD87: High | AE87: Worker 1 | AF87: Canonical core platform — DB/backend/security/infra | AG87: Integration/E2E/certification | AH87: 5 | AI87: 1.7 | AJ87: =IF($K87="Done",0,MAX(0.25,$J87/$AH87)) -> 1.6 | AK87: =IF($K87="Done",0,$AJ87*$AI87) -> 2.72 | AL87: M2A-0 — source fixtures | AM87: WAIT for Presentation RC freeze/tag + clean index/worktree. Then: M2a dependency order | AN87: Own canonical DB/backend/security/API/infra. No W2-owned UI/admin task files and no W3 ML/Assistant runtime. | AO87: Commit before downstream consumer starts; consumer must use the contract, not redesign producer-owned semantics.
A88: T-087 | B88: M2a | C88: M2a-P1 | D88: Physical three-schema migration | E88: Database | F88: Schema | G88: Critical | H88: The measured database carries twelve schemas with 162 tables in public, of which 108 use a ppiq_ name prefix, while the ruled schemas ppiq_plant and ppiq_meta exist and hold zero tables. Migrate to the three ruled schemas: ppiq_staging, ppiq_plant, ppiq_meta. The staging rename is already prepared, because the canvas reads its schema from the configuration key Prep:StagingSchema rather than a literal. | I88: Rule 2 is provable in one query on a fresh database. All application tests pass. The canvas catalogue lists tables from the renamed schema with only a configuration change. AND THE BENCHMARK SURVIVES THE MOVE: the phenomenon and benchmark harness frozen in T-086 is re-run UNCHANGED after the schema migration and produces identical results. A migration that silently alters the reference dataset destroys every comparison made against it. | J88: 12 | K88: Not Started | L88: Core platform / presentation-core lane | M88: NOT W3 PRIMARY | N88: Do not assign to Worker 3 unless a specific AI/ML integration hand-off is requested. | O88: T-086 + T-088 canonical migration order/runner/truth gate established FIRST. | P88: v2.10.2 — migration-order dependency reversed for safety | Q88: Not Started | S88: REVISE — critical design/sequencing issue | T88: F-054 [Critical] — The final projection_quarantine physical schema requires canonical staging_records and definition_versions. M1 cannot honestly create the final table before T-087/T-089/T-090, yet T-061 currently says 'minimal FINAL slice' and validates real projection/reprocess behavior. F-057 [Critical] — The backlog performs the physical three-schema migration in T-087 before T-088 defines the one canonical migration order and duplicate-DDL truth gate. The T-044 migration-parity incident shows this ordering is unsafe. | U88: F-054 — T-061 owns the final typed DTO/API/error-code/reprocess semantics over compatibility persistence only. T-099/T-100 own canonical projection_quarantine and all 15 PV classes; T-101 completes retry/reprocess and preserves the M1 page contract unchanged. F-057 — T-088 migration authority/runner/order gate must precede T-087 physical migration. T-087 becomes a migration authored and executed only through the canonical path. Fresh-install T-115 and install/upgrade T-123 validate the same chain. | V88: T-086 + T-088 canonical migration order/runner/truth gate established FIRST. | W88: NOT W3 PRIMARY | X88: HIGH | Y88: Deep design reconciliation 16-Aug-2026; Chapter 3/4 + Layer-B architecture + latest source/audit evidence | Z88: Track 2 — Real Customer Product | AA88: 2026-09-30 Customer Pilot RC | AB88: Customer Release | AC88: Establish migration authority/order first, then converge to the final three-schema topology. Fresh ppiq_plant must be provably empty. | AD88: High | AE88: Worker 1 | AF88: Canonical core platform — DB/backend/security/infra | AG88: DB/schema/migration | AH88: 8 | AI88: 1.55 | AJ88: =IF($K88="Done",0,MAX(0.25,$J88/$AH88)) -> 1.5 | AK88: =IF($K88="Done",0,$AJ88*$AI88) -> 2.325 | AL88: M2A-1 — schema/definition authority | AM88: WAIT for Presentation RC freeze/tag + clean index/worktree. Then: T-086 + T-088 canonical migration order/runner/truth gate established FIRST. | AN88: Own canonical DB/backend/security/API/infra. No W2-owned UI/admin task files and no W3 ML/Assistant runtime. | AO88: Commit before downstream consumer starts; consumer must use the contract, not redesign producer-owned semantics.
A89: T-088 | B89: M2a | C89: M2a-P1 | D89: Canonical migration order and legacy script archival | E89: Database | F89: Schema | G89: Very Important | H89: Backend/database/scripts contains hotfix, repair, phase and drift-correction scripts accumulated over months, including cases where two scripts created the same table. Define one canonical ordered migration path, archive superseded scripts, and add a truth gate that no two scripts create the same table. | I89: A fresh database builds from the canonical path with no manual step. The truth gate fails if a duplicate CREATE TABLE is introduced. | J89: 12 | K89: Not Started | L89: Core platform / presentation-core lane | M89: NOT W3 PRIMARY | N89: Do not assign to Worker 3 unless a specific AI/ML integration hand-off is requested. | O89: T-086 frozen M2 reference dataset; define canonical migration order before T-087 physical schema move. | P89: v2.10.2 — canonical migration authority precedes physical three-schema migration | Q89: Not Started | S89: REVISE — critical design/sequencing issue | T89: F-057 [Critical] — The backlog performs the physical three-schema migration in T-087 before T-088 defines the one canonical migration order and duplicate-DDL truth gate. The T-044 migration-parity incident shows this ordering is unsafe. | U89: F-057 — T-088 migration authority/runner/order gate must precede T-087 physical migration. T-087 becomes a migration authored and executed only through the canonical path. Fresh-install T-115 and install/upgrade T-123 validate the same chain. | V89: T-086 frozen M2 reference dataset; define canonical migration order before T-087 physical schema move. | W89: NOT W3 PRIMARY | X89: HIGH | Y89: Deep design reconciliation 16-Aug-2026; Chapter 3/4 + Layer-B architecture + latest source/audit evidence | Z89: Track 2 — Real Customer Product | AA89: 2026-09-30 Customer Pilot RC | AB89: Customer Release | AC89: Establish migration authority/order first, then converge to the final three-schema topology. Fresh ppiq_plant must be provably empty. | AD89: High | AE89: Worker 1 | AF89: Canonical core platform — DB/backend/security/infra | AG89: DB/schema/migration | AH89: 8 | AI89: 1.55 | AJ89: =IF($K89="Done",0,MAX(0.25,$J89/$AH89)) -> 1.5 | AK89: =IF($K89="Done",0,$AJ89*$AI89) -> 2.325 | AL89: M2A-1 — schema/definition authority | AM89: WAIT for Presentation RC freeze/tag + clean index/worktree. Then: T-086 frozen M2 reference dataset; define canonical migration order before T-... | AN89: Own canonical DB/backend/security/API/infra. No W2-owned UI/admin task files and no W3 ML/Assistant runtime. | AO89: Commit before downstream consumer starts; consumer must use the contract, not redesign producer-owned semantics.
A90: T-089 | B90: M2a | C90: M2a-P1 | D90: definition_store, definition_versions and definition_dependencies | E90: Database | F90: Definition store | G90: Critical | H90: Create the tables specified in Chapter 3 4.5.11 with immutable versions and a dependency graph, plus a trigger that rejects a dependency cycle. | I90: Integration tests: create, version, publish, and reject a cycle. Version rows must be immutable, proved by an update attempt that fails. | J90: 12 | K90: Not Started | L90: Core platform / presentation-core lane | M90: NOT W3 PRIMARY | N90: Do not assign to Worker 3 unless a specific AI/ML integration hand-off is requested. | O90: T-087 + T-088 canonical three-schema/migration authority green. | P90: v2.10.2 — explicit schema/migration prerequisite | Q90: Not Started | S90: REVISE — critical design/sequencing issue | T90: F-052 [Critical] — M1 relationship task calls the three Chapter 3 relationship tables a FINAL physical slice, but Chapter 3 4.5.10 requires source_definition_id -> definition_store(id). definition_store is intentionally absent until T-089/T-090. A physically final M1 table set therefore cannot exist without stealing M2a authority or creating a temporary FK contract. F-053 [Critical] — T-064 requires a foreign key before the canonical FK target exists. It also omits target_parameters from the Chapter 3 job-target contract and its validation misses JB02/JB04 while describing a pinned version as 'no longer exists' even though published versions are immutable. F-054 [Critical] — The final projection_quarantine physical schema requires canonical staging_records and definition_versions. M1 cannot honestly create the final table before T-087/T-089/T-090, yet T-061 currently says 'minimal FINAL slice' and validates real projection/reprocess behavior. F-058 [Critical] — T-092 says 'dimensions and measures as registry rows' without binding those rows to the unified definition authority. Chapter 3 §4.5.11 already defines master_dimension and master_measure as definition kinds, so a separate mutable registry can become a second source of truth. | U90: F-052 — T-057 must deliver the final external relationship service/API and M1-compatible persistence only. Do not claim final physical schema. T-095 owns canonical ppiq_meta.plant_relationships/_members/_paths convergence after T-089/T-090. T-058/T-059/T-060 consume the service, never table names. F-053 — Keep T-064 mandatory for M1/J12/T7, but implement stable semantic fields through IDefinitionService/compatibility storage with no fake FK. Cover target_definition_id, target_definition_version, target_version_policy, target_parameters, executed-version history and JB01-JB04. T-106 performs canonical FK/check/trigger convergence after T-089/T-090 and adds the dependency DAG. F-054 — T-061 owns the final typed DTO/API/error-code/reprocess semantics over compatibility persistence only. T-099/T-100 own canonical projection_quarantine and all 15 PV classes; T-101 completes retry/reprocess and preserves the M1 page contract unchanged. F-058 — T-092 registry rows must be projections/catalogue views of canonical S2 master definitions (or compatibility projections during migration), never an independent definition authority. T-092 depends on T-089/T-090. | V90: T-087 + T-088 canonical three-schema/migration authority green. | W90: NOT W3 PRIMARY | X90: HIGH | Y90: Deep design reconciliation 16-Aug-2026; Chapter 3/4 + Layer-B architecture + latest source/audit evidence | Z90: Track 2 — Real Customer Product | AA90: 2026-09-30 Customer Pilot RC | AB90: Customer Release | AC90: Canonicalize M1 compatibility contracts without moving the customer-visible contract. | AD90: High | AE90: Worker 1 | AF90: Canonical core platform — DB/backend/security/infra | AG90: DB/schema/migration | AH90: 8 | AI90: 1.55 | AJ90: =IF($K90="Done",0,MAX(0.25,$J90/$AH90)) -> 1.5 | AK90: =IF($K90="Done",0,$AJ90*$AI90) -> 2.325 | AL90: M2A-1 — schema/definition authority | AM90: WAIT for Presentation RC freeze/tag + clean index/worktree. Then: T-087 + T-088 canonical three-schema/migration authority green. | AN90: Own canonical DB/backend/security/API/infra. No W2-owned UI/admin task files and no W3 ML/Assistant runtime. | AO90: Commit before downstream consumer starts; consumer must use the contract, not redesign producer-owned semantics.
A91: T-090 | B91: M2a | C91: M2a-P1 | D91: Move all five definition kinds onto the store | E91: Backend | F91: Definition store | G91: Critical | H91: Replace the M1 compatibility adapter behind IDefinitionService with the real implementation for all five purposes: S1 Transformation, S2 Pages and widgets and filters and master items, S3 Analysis, S4 Model, S5 Log rule. The old per-artifact tables become a compatibility projection and then are retired. v2.10.1 OUTCOME SEMANTICS BINDING. As part of canonical definition convergence, bind the already-frozen SM-06 OutcomeDefinition to the canonical immutable versioned definition authority; do not design a second outcome authority. The canonical binding preserves outcome_code, outcome_type, class_taxonomy_ref, ordinal_rank_map, grain_code, detection_position_code, detection_timestamp_field, direction, unit_code, censoring_policy and definition/version identity. Any legacy ml_outcome_definitions representation may remain only as a compatibility projection during convergence and must not remain an independent semantic authority. | I91: The M1 integration test written against IDefinitionService must pass unchanged, since it references no table name. That is the proof that the visible contract did not move. Publish an SM-06 OutcomeDefinition and resolve it back by exact immutable version. Changing detection_position_code, detection_timestamp_field, grain, taxonomy, ordinal map, direction, unit or censoring policy creates a new definition version rather than silently mutating published meaning. If a compatibility outcome representation remains during convergence, prove it resolves to the same canonical definition/version and cannot diverge into a second authority. | J91: 12 | K91: Not Started | L91: Core platform / presentation-core lane | M91: NOT W3 PRIMARY | N91: Do not assign to Worker 3 unless a specific AI/ML integration hand-off is requested. | O91: T-089 complete; replace compatibility persistence behind unchanged IDefinitionService. | P91: v2.10.2 — explicit definition-store dependency | Q91: Not Started | S91: REVISE — critical design/sequencing issue | T91: F-052 [Critical] — M1 relationship task calls the three Chapter 3 relationship tables a FINAL physical slice, but Chapter 3 4.5.10 requires source_definition_id -> definition_store(id). definition_store is intentionally absent until T-089/T-090. A physically final M1 table set therefore cannot exist without stealing M2a authority or creating a temporary FK contract. F-053 [Critical] — T-064 requires a foreign key before the canonical FK target exists. It also omits target_parameters from the Chapter 3 job-target contract and its validation misses JB02/JB04 while describing a pinned version as 'no longer exists' even though published versions are immutable. F-054 [Critical] — The final projection_quarantine physical schema requires canonical staging_records and definition_versions. M1 cannot honestly create the final table before T-087/T-089/T-090, yet T-061 currently says 'minimal FINAL slice' and validates real projection/reprocess behavior. F-056 [Critical] — T-068 explicitly binds the UI to public.ml_outcome_definitions and GET /ml/foundation/outcomes, both compatibility-era authorities. Chapter 3 D3 requires registry-driven definition-options and T-090 later makes SM-06 OutcomeDefinition part of the immutable definition authority. F-058 [Critical] — T-092 says 'dimensions and measures as registry rows' without binding those rows to the unified definition authority. Chapter 3 §4.5.11 already defines master_dimension and master_measure as definition kinds, so a separate mutable registry can become a second source of truth. | U91: F-052 — T-057 must deliver the final external relationship service/API and M1-compatible persistence only. Do not claim final physical schema. T-095 owns canonical ppiq_meta.plant_relationships/_members/_paths convergence after T-089/T-090. T-058/T-059/T-060 consume the service, never table names. F-053 — Keep T-064 mandatory for M1/J12/T7, but implement stable semantic fields through IDefinitionService/compatibility storage with no fake FK. Cover target_definition_id, target_definition_version, target_version_policy, target_parameters, executed-version history and JB01-JB04. T-106 performs canonical FK/check/trigger convergence after T-089/T-090 and adds the dependency DAG. F-054 — T-061 owns the final typed DTO/API/error-code/reprocess semantics over compatibility persistence only. T-099/T-100 own canonical projection_quarantine and all 15 PV classes; T-101 completes retry/reprocess and preserves the M1 page contract unchanged. F-056 — T-068 must consume a stable analysis-options/outcome-registry service contract, not a physical table or temporary route. M2a swaps storage behind the contract. Complete T-068 before T-065 so the S3 authoring page is built registry-first instead of being rewritten immediately. F-058 — T-092 registry rows must be projections/catalogue views of canonical S2 master definitions (or compatibility projections during migration), never an independent definition authority. T-092 depends on T-089/T-090. | V91: T-089 complete; replace compatibility persistence behind unchanged IDefinitionService. | W91: NOT W3 PRIMARY | X91: HIGH | Y91: Deep design reconciliation 16-Aug-2026; Chapter 3/4 + Layer-B architecture + latest source/audit evidence | Z91: Track 2 — Real Customer Product | AA91: 2026-09-30 Customer Pilot RC | AB91: Customer Release | AC91: Canonicalize M1 compatibility contracts without moving the customer-visible contract. | AD91: High | AE91: Worker 1 | AF91: Canonical core platform — DB/backend/security/infra | AG91: Backend/domain contract | AH91: 10 | AI91: 1.5 | AJ91: =IF($K91="Done",0,MAX(0.25,$J91/$AH91)) -> 1.2 | AK91: =IF($K91="Done",0,$AJ91*$AI91) -> 1.8 | AL91: M2A-1 — schema/definition authority | AM91: WAIT for Presentation RC freeze/tag + clean index/worktree. Then: T-089 complete; replace compatibility persistence behind unchanged IDefinitio... | AN91: Own canonical DB/backend/security/API/infra. No W2-owned UI/admin task files and no W3 ML/Assistant runtime. | AO91: Commit before downstream consumer starts; consumer must use the contract, not redesign producer-owned semantics.
A92: T-091 | B92: M2a | C92: M2a-P1 | D92: Impact preview, export and import | E92: Backend | F92: Definition store | G92: Very Important | H92: Add dependency impact preview before a publish, and export and import of a definition with its dependencies, per Chapter 3 4.5.11. | I92: Publish a change to a definition three others depend on and confirm the preview lists all three before the publish is confirmed. Export and reimport into an empty database and confirm equality. | J92: 12 | K92: Not Started | L92: Core platform / presentation-core lane | M92: NOT W3 PRIMARY | N92: Do not assign to Worker 3 unless a specific AI/ML integration hand-off is requested. | O92: T-090 all definition kinds bound to the canonical store. | P92: v2.10.2 — explicit canonical-store dependency | Q92: Not Started | S92: No new contradiction identified in this pass | V92: T-090 all definition kinds bound to the canonical store. | W92: NOT W3 PRIMARY | X92: Low / not newly identified | Y92: Deep design reconciliation 16-Aug-2026; Chapter 3/4 + Layer-B architecture + latest source/audit evidence | Z92: Track 2 — Real Customer Product | AA92: 2026-09-30 Customer Pilot RC | AB92: Customer Release | AC92: Real generic product on canonical ppiq_staging / ppiq_meta / ppiq_plant. No customer/demo vocabulary, no prepared plant rows on clean install. | AD92: High | AE92: Worker 1 | AF92: Canonical core platform — DB/backend/security/infra | AG92: Backend/domain contract | AH92: 10 | AI92: 1.5 | AJ92: =IF($K92="Done",0,MAX(0.25,$J92/$AH92)) -> 1.2 | AK92: =IF($K92="Done",0,$AJ92*$AI92) -> 1.8 | AL92: M2A-1 — schema/definition authority | AM92: WAIT for Presentation RC freeze/tag + clean index/worktree. Then: T-090 all definition kinds bound to the canonical store. | AN92: Own canonical DB/backend/security/API/infra. No W2-owned UI/admin task files and no W3 ML/Assistant runtime. | AO92: Commit before downstream consumer starts; consumer must use the contract, not redesign producer-owned semantics.
A93: T-092 | B93: M2a | C93: M2a-P1 | D93: Registry authority: dimensions and measures as rows | E93: Backend | F93: Registry | G93: Critical | H93: DashboardWidgetQuerySafetyRegistry declares SupportedDimensions as a compiled HashSet that includes ProductFamily, GradeOrRecipe, ShiftCode, DefectType and RiskClass, referenced through DashboardMetadataCodes.Dimensions. That is plant vocabulary compiled into the product and a Rule 1 violation reachable by a customer. Move dimensions and measures to registry rows. Chart types and the numeric limits stay closed, because they are product grammar rather than customer knowledge. v2.10.2 SINGLE-AUTHORITY RULING — master dimensions and master measures are S2 definition kinds in the unified definition authority. The selectable 'registry rows' are a catalogue/projection of those canonical definitions, not a second independently editable source of truth. | I93: Add a dimension through the registry API and confirm it becomes selectable in the authoring shell with no code change and no redeploy. Confirm chart types remain closed by attempting to add one and being refused. Create a master dimension/measure through the canonical definition service and prove it appears in the registry/authoring shell. Attempt to create a divergent second-registry definition with the same canonical identity and refuse it. | J93: 12 | K93: Not Started | L93: Core platform / presentation-core lane | M93: NOT W3 PRIMARY | N93: Do not assign to Worker 3 unless a specific AI/ML integration hand-off is requested. | O93: T-089 + T-090 canonical definition authority. | P93: v2.10.2 — prevent second dimension/measure authority | Q93: Not Started | S93: REVISE — critical design/sequencing issue | T93: F-058 [Critical] — T-092 says 'dimensions and measures as registry rows' without binding those rows to the unified definition authority. Chapter 3 §4.5.11 already defines master_dimension and master_measure as definition kinds, so a separate mutable registry can become a second source of truth. | U93: F-058 — T-092 registry rows must be projections/catalogue views of canonical S2 master definitions (or compatibility projections during migration), never an independent definition authority. T-092 depends on T-089/T-090. | V93: T-089 + T-090 canonical definition authority. | W93: NOT W3 PRIMARY | X93: HIGH | Y93: Deep design reconciliation 16-Aug-2026; Chapter 3/4 + Layer-B architecture + latest source/audit evidence | Z93: Track 2 — Real Customer Product | AA93: 2026-09-30 Customer Pilot RC | AB93: Customer Release | AC93: Real generic product on canonical ppiq_staging / ppiq_meta / ppiq_plant. No customer/demo vocabulary, no prepared plant rows on clean install. | AD93: High | AE93: Worker 1 | AF93: Canonical core platform — DB/backend/security/infra | AG93: Backend/domain contract | AH93: 10 | AI93: 1.5 | AJ93: =IF($K93="Done",0,MAX(0.25,$J93/$AH93)) -> 1.2 | AK93: =IF($K93="Done",0,$AJ93*$AI93) -> 1.8 | AL93: M2A-1 — schema/definition authority | AM93: WAIT for Presentation RC freeze/tag + clean index/worktree. Then: T-089 + T-090 canonical definition authority. | AN93: Own canonical DB/backend/security/API/infra. No W2-owned UI/admin task files and no W3 ML/Assistant runtime. | AO93: Commit before downstream consumer starts; consumer must use the contract, not redesign producer-owned semantics.
A94: T-093 | B94: M2a | C94: M2a-P1 | D94: Plant-vocabulary sweep, part 1: build the term list and the architecture test | E94: Backend | F94: Registry | G94: Very Important | H94: Rule 1 needs an enforcement mechanism before the sweep, or the sweep is a one-off. Create a registry-held list of plant terms (the term list is itself DATA, never a compiled constant) and an architecture test that fails the build when any listed term appears in product code outside registry data, seed content or test fixtures. Seed the list from the dimension names already found compiled into DashboardWidgetQuerySafetyRegistry: ProductFamily, GradeOrRecipe, ShiftCode, DefectType, RiskClass. | I94: Add a term to the list and confirm the build goes red on an existing violation, then goes green once that violation is fixed. Confirm removing a term from the list does not require a code change. | J94: 6 | K94: Not Started | L94: Core platform / presentation-core lane | M94: NOT W3 PRIMARY | N94: Do not assign to Worker 3 unless a specific AI/ML integration hand-off is requested. | O94: T-092 registry/definition authority available; architecture term list is committed data/seed input, not a runtime-only mutable dependency. | P94: v2.10.2 — explicit registry prerequisite | Q94: Not Started | S94: No new contradiction identified in this pass | V94: T-092 registry/definition authority available; architecture term list is committed data/seed input, not a runtime-only mutable dependency. | W94: NOT W3 PRIMARY | X94: Low / not newly identified | Y94: Deep design reconciliation 16-Aug-2026; Chapter 3/4 + Layer-B architecture + latest source/audit evidence | Z94: Track 2 — Real Customer Product | AA94: 2026-09-30 Customer Pilot RC | AB94: Customer Release | AC94: Real generic product on canonical ppiq_staging / ppiq_meta / ppiq_plant. No customer/demo vocabulary, no prepared plant rows on clean install. | AD94: High | AE94: Worker 1 | AF94: Canonical core platform — DB/backend/security/infra | AG94: Backend/domain contract | AH94: 10 | AI94: 1.5 | AJ94: =IF($K94="Done",0,MAX(0.25,$J94/$AH94)) -> 0.6 | AK94: =IF($K94="Done",0,$AJ94*$AI94) -> 0.9 | AL94: M2A-1 — schema/definition authority | AM94: WAIT for Presentation RC freeze/tag + clean index/worktree. Then: T-092 registry/definition authority available; architecture term list is comm... | AN94: Own canonical DB/backend/security/API/infra. No W2-owned UI/admin task files and no W3 ML/Assistant runtime. | AO94: Commit before downstream consumer starts; consumer must use the contract, not redesign producer-owned semantics.
A95: T-094 | B95: M2a | C95: M2a-P1 | D95: Plant-vocabulary sweep, part 2: clear the violations and rename the canonical grain | E95: Backend | F95: Registry | G95: Very Important | H95: Run the new architecture test and clear every violation it names across backend and frontend. Include the canonical grain literal 'coil', which the canonical layer applies even to aluminium, tyre and batch product types - native grains observed in the data include slab, heat, cast, packagedlot, rawmaterial, aluminiumroll, tyreunit, batch and lot. Rename it to a generic term and migrate existing rows. v2.10.2 SEMANTIC CORRECTION — do NOT replace 'coil' with one new universal grain word. The generic product has customer-declared material_unit_type_definitions, material_units.material_unit_type/native_grain and outcome/model grain_code. Remove all hardcoded/default steel grain assumptions and bind each consumer to the declared registry/outcome/material-unit grain. | I95: The architecture test passes with zero violations. Query the canonical layer for a non-steel product type and confirm its grain is no longer reported as 'coil'. Use at least two non-steel unit types/grains and prove each remains distinct end to end. No code path substitutes one universal 'material' grain when the definition declares a different grain_code. | J95: 8 | K95: Not Started | L95: Core platform / presentation-core lane | M95: NOT W3 PRIMARY | N95: Do not assign to Worker 3 unless a specific AI/ML integration hand-off is requested. | O95: T-092 + T-093; canonical multi-grain vocabulary authority available. | P95: v2.10.2 — 'rename grain' replaced by dynamic multi-grain authority | Q95: Not Started | S95: REVISE — critical design/sequencing issue | T95: F-059 [Critical] — T-094 says rename the canonical grain literal 'coil' to one generic term. The frozen design does not have one generic grain: it has material_unit_type_definitions, native_grain and dynamic outcome/model grain_code. Replacing 'coil' with 'material' would preserve the same architectural error under a new word. F-081 [Very Important] — Current GenealogyThreadPanel still contains steel-specific explanatory copy ('coil to heat/melt') while C5 is a generic material-unit explorer. If T-063 converges layout without removing product vocabulary, T-094 will immediately rework the same surface. | U95: F-059 — Remove hardcoded/default coil semantics. Preserve customer-declared multi-grain unit types and outcome-specific grain_code. Rename T-094 scope from 'rename canonical grain' to 'remove hardcoded canonical grain default and bind to registry/material-unit authority'. F-081 — T-063 acceptance must require generic material-unit labels driven by data/registry and no industry noun in product UI. T-094 remains the whole-product ratchet. | V95: T-092 + T-093; canonical multi-grain vocabulary authority available. | W95: NOT W3 PRIMARY | X95: HIGH | Y95: Deep design reconciliation 16-Aug-2026; Chapter 3/4 + Layer-B architecture + latest source/audit evidence | Z95: Track 2 — Real Customer Product | AA95: 2026-09-30 Customer Pilot RC | AB95: Customer Release | AC95: Real generic product on canonical ppiq_staging / ppiq_meta / ppiq_plant. No customer/demo vocabulary, no prepared plant rows on clean install. | AD95: High | AE95: Worker 1 | AF95: Canonical core platform — DB/backend/security/infra | AG95: Backend/domain contract | AH95: 10 | AI95: 1.5 | AJ95: =IF($K95="Done",0,MAX(0.25,$J95/$AH95)) -> 0.8 | AK95: =IF($K95="Done",0,$AJ95*$AI95) -> 1.2 | AL95: M2A-1 — schema/definition authority | AM95: WAIT for Presentation RC freeze/tag + clean index/worktree. Then: T-092 + T-093; canonical multi-grain vocabulary authority available. | AN95: Own canonical DB/backend/security/API/infra. No W2-owned UI/admin task files and no W3 ML/Assistant runtime. | AO95: Commit before downstream consumer starts; consumer must use the contract, not redesign producer-owned semantics.
A96: T-095 | B96: M2a | C96: M2a-P2 | D96: Relationship members, cardinality, grain conversion and preferred paths | E96: Backend | F96: Relationship model | G96: Critical | H96: Extend the M1 slice to the full model in Chapter 3 4.5.10: members, cardinality, grain conversion between related entities, preferred path selection when more than one path exists, and published versions. v2.10.2 CONVERGENCE CORRECTION — T-095 does not merely 'extend' M1 physical tables. It converges the M1 relationship service/compatibility persistence onto the canonical Chapter 3 4.5.10 tables after definition_store exists, including source_definition_id/version, grain conversion, preferred paths, ambiguity/validation state and retirement semantics, while keeping the M1 external contract stable. | I96: Declare two paths between the same pair of entities, mark one preferred, and confirm the resolver chooses it. Change the preference and confirm the resolution changes with no other edit. | J96: 12 | K96: Not Started | L96: Core platform / presentation-core lane | M96: NOT W3 PRIMARY | N96: Do not assign to Worker 3 unless a specific AI/ML integration hand-off is requested. | O96: T-057 M1 relationship contract + T-089 + T-090 + T-094. | P96: v2.10.2 — canonical physical convergence explicitly separated from M1 compatibility | Q96: Not Started | S96: REVISE — critical design/sequencing issue | T96: F-052 [Critical] — M1 relationship task calls the three Chapter 3 relationship tables a FINAL physical slice, but Chapter 3 4.5.10 requires source_definition_id -> definition_store(id). definition_store is intentionally absent until T-089/T-090. A physically final M1 table set therefore cannot exist without stealing M2a authority or creating a temporary FK contract. F-059 [Critical] — T-094 says rename the canonical grain literal 'coil' to one generic term. The frozen design does not have one generic grain: it has material_unit_type_definitions, native_grain and dynamic outcome/model grain_code. Replacing 'coil' with 'material' would preserve the same architectural error under a new word. F-060 [Very Important] — T-060 builds the M1 C6 route, then T-098 says 'Build the C6 Relationship Browser' again. That wording invites a second page/rebuild rather than hidden-authority convergence. | U96: F-052 — T-057 must deliver the final external relationship service/API and M1-compatible persistence only. Do not claim final physical schema. T-095 owns canonical ppiq_meta.plant_relationships/_members/_paths convergence after T-089/T-090. T-058/T-059/T-060 consume the service, never table names. F-059 — Remove hardcoded/default coil semantics. Preserve customer-declared multi-grain unit types and outcome-specific grain_code. Rename T-094 scope from 'rename canonical grain' to 'remove hardcoded canonical grain default and bind to registry/material-unit authority'. F-060 — T-098 must complete the already-shown /relationships page in place: preserve route/layout/controls and replace/extend only the canonical relationship source/path evidence. | V96: T-057 M1 relationship contract + T-089 + T-090 + T-094. | W96: NOT W3 PRIMARY | X96: HIGH | Y96: Deep design reconciliation 16-Aug-2026; Chapter 3/4 + Layer-B architecture + latest source/audit evidence | Z96: Track 2 — Real Customer Product | AA96: 2026-09-30 Customer Pilot RC | AB96: Customer Release | AC96: Canonicalize M1 compatibility contracts without moving the customer-visible contract. | AD96: High | AE96: Worker 1 | AF96: Canonical core platform — DB/backend/security/infra | AG96: Backend/domain contract | AH96: 10 | AI96: 1.5 | AJ96: =IF($K96="Done",0,MAX(0.25,$J96/$AH96)) -> 1.2 | AK96: =IF($K96="Done",0,$AJ96*$AI96) -> 1.8 | AL96: M2A-2 — relationships/projection | AM96: WAIT for Presentation RC freeze/tag + clean index/worktree. Then: T-057 M1 relationship contract + T-089 + T-090 + T-094. | AN96: Own canonical DB/backend/security/API/infra. No W2-owned UI/admin task files and no W3 ML/Assistant runtime. | AO96: Commit before downstream consumer starts; consumer must use the contract, not redesign producer-owned semantics.
A97: T-096 | B97: M2a | C97: M2a-P2 | D97: Path resolver, part 1: resolver core and the first eight consumers | E97: Backend | F97: Relationship model | G97: Critical | H97: Chapter 2 3.15.4 names sixteen consumers of the relationship model. Build the resolver core, then route the first eight through it: canonical projection, page and widget queries, associative filtering, drill-down, drill-through, genealogy, statistics and correlation. | I97: A regression test per consumer asserting it resolves through the published model, and refuses with a named reason when the relationship is unpublished. Eight tests, no exceptions. | J97: 8 | K97: Not Started | L97: Core platform / presentation-core lane | M97: NOT W3 PRIMARY | N97: Do not assign to Worker 3 unless a specific AI/ML integration hand-off is requested. | O97: T-095 canonical relationship publication/model complete. | P97: v2.10.2 — explicit resolver-core prerequisite | Q97: Not Started | S97: REVISE — important design/coverage issue | T97: F-060 [Very Important] — T-060 builds the M1 C6 route, then T-098 says 'Build the C6 Relationship Browser' again. That wording invites a second page/rebuild rather than hidden-authority convergence. | U97: F-060 — T-098 must complete the already-shown /relationships page in place: preserve route/layout/controls and replace/extend only the canonical relationship source/path evidence. | V97: T-095 canonical relationship publication/model complete. | W97: NOT W3 PRIMARY | X97: MEDIUM | Y97: Deep design reconciliation 16-Aug-2026; Chapter 3/4 + Layer-B architecture + latest source/audit evidence | Z97: Track 2 — Real Customer Product | AA97: 2026-09-30 Customer Pilot RC | AB97: Customer Release | AC97: Real generic product on canonical ppiq_staging / ppiq_meta / ppiq_plant. No customer/demo vocabulary, no prepared plant rows on clean install. | AD97: High | AE97: Worker 1 | AF97: Canonical core platform — DB/backend/security/infra | AG97: Backend/domain contract | AH97: 10 | AI97: 1.5 | AJ97: =IF($K97="Done",0,MAX(0.25,$J97/$AH97)) -> 0.8 | AK97: =IF($K97="Done",0,$AJ97*$AI97) -> 1.2 | AL97: M2A-2 — relationships/projection | AM97: WAIT for Presentation RC freeze/tag + clean index/worktree. Then: T-095 canonical relationship publication/model complete. | AN97: Own canonical DB/backend/security/API/infra. No W2-owned UI/admin task files and no W3 ML/Assistant runtime. | AO97: Commit before downstream consumer starts; consumer must use the contract, not redesign producer-owned semantics.
A98: T-097 | B98: M2a | C98: M2a-P2 | D98: Path resolver, part 2: the remaining eight consumers and the regression suite | E98: Backend | F98: Relationship model | G98: Critical | H98: Route the remaining eight through the resolver: feature engineering, model training, prediction, practice learning, remediation search, value calculation, assistant retrieval and evidence. Some of these are built in M2b; add the resolver seam now so they cannot be written against an ad-hoc join later. | I98: Eight further regression tests. For consumers whose engine arrives in M2b, the test asserts the seam exists and refuses when unpublished, which is what stops a later shortcut. | J98: 6 | K98: Not Started | L98: Core platform / presentation-core lane | M98: NOT W3 PRIMARY | N98: Do not assign to Worker 3 unless a specific AI/ML integration hand-off is requested. | O98: T-096 first resolver consumers green. | P98: v2.10.2 — explicit resolver-part dependency | Q98: Not Started | S98: REVISE — important design/coverage issue | T98: F-060 [Very Important] — T-060 builds the M1 C6 route, then T-098 says 'Build the C6 Relationship Browser' again. That wording invites a second page/rebuild rather than hidden-authority convergence. | U98: F-060 — T-098 must complete the already-shown /relationships page in place: preserve route/layout/controls and replace/extend only the canonical relationship source/path evidence. | V98: T-096 first resolver consumers green. | W98: NOT W3 PRIMARY | X98: MEDIUM | Y98: Deep design reconciliation 16-Aug-2026; Chapter 3/4 + Layer-B architecture + latest source/audit evidence | Z98: Track 2 — Real Customer Product | AA98: 2026-09-30 Customer Pilot RC | AB98: Customer Release | AC98: Real generic product on canonical ppiq_staging / ppiq_meta / ppiq_plant. No customer/demo vocabulary, no prepared plant rows on clean install. | AD98: High | AE98: Worker 1 | AF98: Canonical core platform — DB/backend/security/infra | AG98: Backend/domain contract | AH98: 10 | AI98: 1.5 | AJ98: =IF($K98="Done",0,MAX(0.25,$J98/$AH98)) -> 0.6 | AK98: =IF($K98="Done",0,$AJ98*$AI98) -> 0.9 | AL98: M2A-2 — relationships/projection | AM98: WAIT for Presentation RC freeze/tag + clean index/worktree. Then: T-096 first resolver consumers green. | AN98: Own canonical DB/backend/security/API/infra. No W2-owned UI/admin task files and no W3 ML/Assistant runtime. | AO98: Commit before downstream consumer starts; consumer must use the contract, not redesign producer-owned semantics.
A99: T-098 | B99: M2a | C99: M2a-P2 | D99: Relationship Browser page and path evidence | E99: Frontend | F99: Relationship model | G99: Very Important | H99: Build the C6 Relationship Browser from Chapter 3 4.4 with the ten-field page contract, showing declared relationships, their members, their paths and the evidence for each path. v2.10.2 CONTINUITY CORRECTION — complete the existing T-060 /relationships page in place. Do not create a second C6 surface. Preserve the route, layout and M1 control contract while replacing/extending the hidden relationship authority and path evidence. | I99: Open a relationship and confirm its members, cardinality and path are shown with evidence. Confirm an unpublished relationship is visibly distinct from a published one. Run the M1 C6 continuity snapshot before/after canonical cutover and prove no visible-contract regression. | J99: 12 | K99: Not Started | L99: Core platform / presentation-core lane | M99: NOT W3 PRIMARY | N99: Do not assign to Worker 3 unless a specific AI/ML integration hand-off is requested. | O99: T-060 M1 C6 surface + T-095 + T-096 + T-097. | P99: v2.10.2 — C6 completion/cutover, not page rebuild | Q99: Not Started | S99: REVISE — important design/coverage issue | T99: F-060 [Very Important] — T-060 builds the M1 C6 route, then T-098 says 'Build the C6 Relationship Browser' again. That wording invites a second page/rebuild rather than hidden-authority convergence. | U99: F-060 — T-098 must complete the already-shown /relationships page in place: preserve route/layout/controls and replace/extend only the canonical relationship source/path evidence. | V99: T-060 M1 C6 surface + T-095 + T-096 + T-097. | W99: NOT W3 PRIMARY | X99: MEDIUM | Y99: Deep design reconciliation 16-Aug-2026; Chapter 3/4 + Layer-B architecture + latest source/audit evidence | Z99: Track 2 — Real Customer Product | AA99: 2026-09-30 Customer Pilot RC | AB99: Customer Release | AC99: Real generic product on canonical ppiq_staging / ppiq_meta / ppiq_plant. No customer/demo vocabulary, no prepared plant rows on clean install. | AD99: High | AE99: Worker 2 | AF99: Canonical customer-facing UI/admin + continuity | AG99: Frontend/UI feature | AH99: 9 | AI99: 1.5 | AJ99: =IF($K99="Done",0,MAX(0.25,$J99/$AH99)) -> 1.3333333 | AK99: =IF($K99="Done",0,$AJ99*$AI99) -> 2 | AL99: M2A-2 — relationships/projection | AM99: WAIT for Presentation RC freeze/tag + clean index/worktree. Then: T-060 M1 C6 surface + T-095 + T-096 + T-097. | AN99: Own named UI/admin task end-to-end only after producer APIs/security are committed. | AO99: Commit before downstream consumer starts; consumer must use the contract, not redesign producer-owned semantics.
A100: T-099 | B100: M2a | C100: M2a-P2 | D100: Quarantine, part 1: the table, the reprocess API and the first eight PV classes | E100: Backend | F100: Quarantine | G100: Critical | H100: Chapter 3 4.5.14 specifies quarantine with fifteen typed PV codes. A repository search for projection_quarantine returns zero hits, so this does not exist. Build the table with its columns, the reprocess endpoint, and the first eight validation classes so a bad row is quarantined under a named code instead of corrupting the canonical layer or failing the whole batch. | I100: Craft one malformed input per implemented class and assert each is quarantined under the correct code, while the good rows in the same batch still project. | J100: 8 | K100: Not Started | L100: Core platform / presentation-core lane | M100: NOT W3 PRIMARY | N100: Do not assign to Worker 3 unless a specific AI/ML integration hand-off is requested. | O100: T-087 canonical staging schema + T-089/T-090 definition_versions authority. | P100: v2.10.2 — explicit physical FK prerequisites | Q100: Not Started | S100: REVISE — critical design/sequencing issue | T100: F-054 [Critical] — The final projection_quarantine physical schema requires canonical staging_records and definition_versions. M1 cannot honestly create the final table before T-087/T-089/T-090, yet T-061 currently says 'minimal FINAL slice' and validates real projection/reprocess behavior. | U100: F-054 — T-061 owns the final typed DTO/API/error-code/reprocess semantics over compatibility persistence only. T-099/T-100 own canonical projection_quarantine and all 15 PV classes; T-101 completes retry/reprocess and preserves the M1 page contract unchanged. | V100: T-087 canonical staging schema + T-089/T-090 definition_versions authority. | W100: NOT W3 PRIMARY | X100: HIGH | Y100: Deep design reconciliation 16-Aug-2026; Chapter 3/4 + Layer-B architecture + latest source/audit evidence | Z100: Track 2 — Real Customer Product | AA100: 2026-09-30 Customer Pilot RC | AB100: Customer Release | AC100: Canonicalize M1 compatibility contracts without moving the customer-visible contract. | AD100: High | AE100: Worker 1 | AF100: Canonical core platform — DB/backend/security/infra | AG100: Backend/domain contract | AH100: 10 | AI100: 1.5 | AJ100: =IF($K100="Done",0,MAX(0.25,$J100/$AH100)) -> 0.8 | AK100: =IF($K100="Done",0,$AJ100*$AI100) -> 1.2 | AL100: M2A-2 — relationships/projection | AM100: WAIT for Presentation RC freeze/tag + clean index/worktree. Then: T-087 canonical staging schema + T-089/T-090 definition_versions authority. | AN100: Own canonical DB/backend/security/API/infra. No W2-owned UI/admin task files and no W3 ML/Assistant runtime. | AO100: Commit before downstream consumer starts; consumer must use the contract, not redesign producer-owned semantics.
A101: T-100 | B101: M2a | C101: M2a-P2 | D101: Quarantine, part 2: the remaining seven PV classes and per-class tests | E101: Backend | F101: Quarantine | G101: Critical | H101: Implement the remaining seven validation classes and give every class its own test fixture, so the class set is provably complete against Chapter 3 4.5.14 rather than approximately complete. | I101: Fifteen fixtures, fifteen codes, fifteen passing tests. A test that enumerates the PV enum and fails if any member has no fixture. | J101: 6 | K101: Not Started | L101: Core platform / presentation-core lane | M101: NOT W3 PRIMARY | N101: Do not assign to Worker 3 unless a specific AI/ML integration hand-off is requested. | O101: T-099 canonical quarantine table/API and first eight PV classes. | P101: v2.10.2 — explicit part-1 dependency | Q101: Not Started | S101: REVISE — critical design/sequencing issue | T101: F-054 [Critical] — The final projection_quarantine physical schema requires canonical staging_records and definition_versions. M1 cannot honestly create the final table before T-087/T-089/T-090, yet T-061 currently says 'minimal FINAL slice' and validates real projection/reprocess behavior. | U101: F-054 — T-061 owns the final typed DTO/API/error-code/reprocess semantics over compatibility persistence only. T-099/T-100 own canonical projection_quarantine and all 15 PV classes; T-101 completes retry/reprocess and preserves the M1 page contract unchanged. | V101: T-099 canonical quarantine table/API and first eight PV classes. | W101: NOT W3 PRIMARY | X101: HIGH | Y101: Deep design reconciliation 16-Aug-2026; Chapter 3/4 + Layer-B architecture + latest source/audit evidence | Z101: Track 2 — Real Customer Product | AA101: 2026-09-30 Customer Pilot RC | AB101: Customer Release | AC101: Canonicalize M1 compatibility contracts without moving the customer-visible contract. | AD101: High | AE101: Worker 1 | AF101: Canonical core platform — DB/backend/security/infra | AG101: Backend/domain contract | AH101: 10 | AI101: 1.5 | AJ101: =IF($K101="Done",0,MAX(0.25,$J101/$AH101)) -> 0.6 | AK101: =IF($K101="Done",0,$AJ101*$AI101) -> 0.9 | AL101: M2A-2 — relationships/projection | AM101: WAIT for Presentation RC freeze/tag + clean index/worktree. Then: T-099 canonical quarantine table/API and first eight PV classes. | AN101: Own canonical DB/backend/security/API/infra. No W2-owned UI/admin task files and no W3 ML/Assistant runtime. | AO101: Commit before downstream consumer starts; consumer must use the contract, not redesign producer-owned semantics.
A102: T-101 | B102: M2a | C102: M2a-P2 | D102: Quarantine retry, reprocess and Mapping Health completion | E102: Frontend | F102: Quarantine | G102: Very Important | H102: Complete the C2 Mapping Health page against Chapter 3 4.4 C2: issues grouped by code, example rows, and Reprocess after the mapping is corrected. The M1 version delivered the shape; this delivers the full class set and the retry semantics. | I102: Quarantine rows under three different codes, correct one mapping, reprocess, and confirm only the affected rows clear. The M1 continuity snapshot of this page must still match. | J102: 12 | K102: Not Started | L102: Core platform / presentation-core lane | M102: NOT W3 PRIMARY | N102: Do not assign to Worker 3 unless a specific AI/ML integration hand-off is requested. | O102: T-061 final M1 API/page contract + T-099 + T-100 canonical quarantine implementation. | P102: v2.10.2 — compatibility-to-canonical convergence dependency | Q102: Not Started | S102: REVISE — critical design/sequencing issue | T102: F-054 [Critical] — The final projection_quarantine physical schema requires canonical staging_records and definition_versions. M1 cannot honestly create the final table before T-087/T-089/T-090, yet T-061 currently says 'minimal FINAL slice' and validates real projection/reprocess behavior. | U102: F-054 — T-061 owns the final typed DTO/API/error-code/reprocess semantics over compatibility persistence only. T-099/T-100 own canonical projection_quarantine and all 15 PV classes; T-101 completes retry/reprocess and preserves the M1 page contract unchanged. | V102: T-061 final M1 API/page contract + T-099 + T-100 canonical quarantine implementation. | W102: NOT W3 PRIMARY | X102: HIGH | Y102: Deep design reconciliation 16-Aug-2026; Chapter 3/4 + Layer-B architecture + latest source/audit evidence | Z102: Track 2 — Real Customer Product | AA102: 2026-09-30 Customer Pilot RC | AB102: Customer Release | AC102: Real generic product on canonical ppiq_staging / ppiq_meta / ppiq_plant. No customer/demo vocabulary, no prepared plant rows on clean install. | AD102: High | AE102: Worker 2 | AF102: Canonical customer-facing UI/admin + continuity | AG102: Frontend/UI feature | AH102: 9 | AI102: 1.5 | AJ102: =IF($K102="Done",0,MAX(0.25,$J102/$AH102)) -> 1.3333333 | AK102: =IF($K102="Done",0,$AJ102*$AI102) -> 2 | AL102: M2A-2 — relationships/projection | AM102: WAIT for Presentation RC freeze/tag + clean index/worktree. Then: T-061 final M1 API/page contract + T-099 + T-100 canonical quarantine impleme... | AN102: Own named UI/admin task end-to-end only after producer APIs/security are committed. | AO102: Commit before downstream consumer starts; consumer must use the contract, not redesign producer-owned semantics.
A103: T-102 | B103: M2a | C103: M2a-P2 | D103: Identity resolution across sources | E103: Backend | F103: Genealogy | G103: Very Important | H103: Harden material identity resolution using material_aliases so the same physical material arriving under two different source identifiers becomes one canonical unit. The schema already supports this: material_units carries a unique key on (site_id, material_code) plus a filtered unique on (source_system, source_record_id), which makes projection idempotent without forbidding rows that have no source identity. | I103: Import the same material under two different source identifiers and confirm one canonical unit results with both aliases recorded. Re-run the import and confirm no duplicate appears. | J103: 8 | K103: Not Started | L103: Core platform / presentation-core lane | M103: NOT W3 PRIMARY | N103: Do not assign to Worker 3 unless a specific AI/ML integration hand-off is requested. | O103: T-087 canonical plant schema + T-095 relationship/material identity authority. | P103: v2.10.2 — explicit canonical identity prerequisites | Q103: Not Started | S103: No new contradiction identified in this pass | V103: T-087 canonical plant schema + T-095 relationship/material identity authority. | W103: NOT W3 PRIMARY | X103: Low / not newly identified | Y103: Deep design reconciliation 16-Aug-2026; Chapter 3/4 + Layer-B architecture + latest source/audit evidence | Z103: Track 2 — Real Customer Product | AA103: 2026-09-30 Customer Pilot RC | AB103: Customer Release | AC103: Real generic product on canonical ppiq_staging / ppiq_meta / ppiq_plant. No customer/demo vocabulary, no prepared plant rows on clean install. | AD103: High | AE103: Worker 1 | AF103: Canonical core platform — DB/backend/security/infra | AG103: Backend/domain contract | AH103: 10 | AI103: 1.5 | AJ103: =IF($K103="Done",0,MAX(0.25,$J103/$AH103)) -> 0.8 | AK103: =IF($K103="Done",0,$AJ103*$AI103) -> 1.2 | AL103: M2A-2 — relationships/projection | AM103: WAIT for Presentation RC freeze/tag + clean index/worktree. Then: T-087 canonical plant schema + T-095 relationship/material identity authority. | AN103: Own canonical DB/backend/security/API/infra. No W2-owned UI/admin task files and no W3 ML/Assistant runtime. | AO103: Commit before downstream consumer starts; consumer must use the contract, not redesign producer-owned semantics.
